Workbook
Name Construction_End_Date: Inputs!$E$19
Name Construction_Start_Date: Inputs!$E$18
Name Model_Start: Inputs!$E$7
Name Model_start: Inputs!$E$9
Name Operations_Start_Date: Inputs!$E$22
Name RM_BaseEventDays: Inputs!$E$302
Name RM_EventDaysScale: Inputs!$E$499
Name RM_ExitMultiple: Inputs!$E$483
Name RM_HourlyRate: Inputs!$E$397
Name RM_IO_Months: Inputs!$E$69
Name RM_OutgoingsPct: Inputs!$E$36
Name RM_ShiftHours: Inputs!$E$398
Name RM_StaffPerEvent: Inputs!$E$396
Name RM_SustCapexPct: Inputs!$E$462
Name RM_TerminalGrowth: Inputs!$E$487
Name RM_VHA_Cap: Inputs!$E$309
Name RM_VHA_GBO_Fee: Inputs!$E$308
Name Total_Initial_Capex: 'Construction Timeline'!$E$18

Sheet Readme
B1: THE BEND LIVE HOUSE — MODEL README
B2: Financial Model V4:Tab Index & Descriptions
A4: No. | B4: Tab Name | C4: Description
A5: 1 | B5: General Information | C5: Project overview describing the integrated entertainment precinct at 349 Bridge Street Melbourne — Live House music venue, URWLD active leisure, parking, Central Park, and employment impact.
A6: =A5+1 -> 2 | B6: Dynamic Dashboard | C6: Interactive investor dashboard showing KPIs (Project IRR, Equity IRR, MOIC, Enterprise Value, Equity Value, Payback Period), revenue/EBITDA charts, and financial summary linked to the active scenario.
A7: =A6+1 -> 3 | B7: Inputs for Dashboard | C7: Inputs for preparation of Dynamic Dashboards that are linked to the rest of the model
A8: =A7+1 -> 4 | B8: Dashboard | C8: Executive dashboard with annual summary (Revenue, EBITDA, Closing Cash, Total Debt) across FY25–FY36, model health status, and active scenario indicator.
A9: =A8+1 -> 5 | B9: Valuations | C9: Valuation architecture sheet with DCF and return metrics (IRR, NPV), WACC/Ke inputs, sensitivity framework, and terminal value calculations.
A10: =A9+1 -> 6 | B10: Scenarios | C10: Scenario manager with Base, Optimistic, Pessimistic, and Delayed Opening scenarios. Defines multipliers for revenue, costs, capex, inflation, interest rate deltas, and event days.
A11: =A10+1 -> 7 | B11: Inputs | C11: Master global inputs sheet (v35). Contains project timing, construction parameters, financing terms, WACC/Ke assumptions, escalation rates, and all key model drivers with source references.
A12: =A11+1 -> 8 | B12: Construction Timeline | C12: Initial capex breakdown (Consultants, Structure, Civil, ICT, FF&E) and construction phasing schedule across the build period.
A13: =A12+1 -> 9 | B13: PL_BS_CFS Summary | C13: A summarised view of the P&L, Balance Sheet and Cash Flow in one single tab, linked to respective tabs of P&L, BS and CashFlow.
A14: =A13+1 -> 10 | B14: P&L | C14: Profit & Loss statement (FY25–FY36) with operations and construction flags, revenue, operating expenses, EBITDA, depreciation, interest, and net income.
A15: =A14+1 -> 11 | B15: Balance Sheet | C15: Annual balance sheet (FY25–FY36) with Assets (Cash, Receivables, PP&E), Liabilities (Debt, Payables), and Equity sections.
A16: =A15+1 -> 12 | B16: Cashflow | C16: Annual cashflow waterfall (AUD) showing operating, investing, and financing cash flows with opening/closing cash balances across FY25–FY36.
A17: =A16+1 -> 13 | B17: Debt | C17: Debt schedule for Term Debt ($10.2M, 8%, 10yr amortising) and PE Loan facility. Tracks drawdowns, repayments, interest, and closing balances.
... A28: =A27+1 -> 24 | B28: Model Checks | C28: Automated integrity checks - BS balance (A–L–E), cash tie-out (BS vs CFS), PPE tie, debt continuity, sources ≥ uses, revenue tie, and DSCR covenant with PASS/FAIL status.

Sheet KEY OUTPUT >>

Sheet General Information
A1: Integrated Entertainment and Recreational Development
A2: 349 Bridge Street Melbourne
A3: Live House Music Venue - There is a need for a 4,000 to 5,000 live venue for the Melbourne market that is suitably located to avoid issues of noise and congestion for the local community. The location within our proposed precinct will provide a beneficial location for this development and allow for the improved development of access to culture, music, entertainment and activity.
A5: "URWLD" - is an active leisure concept that will house a Sports Climbing Centre of Excellence as well as a range of 15-18 active leisure activities including surfing, scuba, ice climbing, sports climbing, bouldering, canyoning, coasteering, ninja, junior climb academy, and a range of VR activities such as skiing, snowboarding, squirrel suit, tennis, golf and other immersive game concepts. There will also be an eSports arena and concept area and interactive video games concepts. These will be supported by 4 quality, chef curated F&B concepts and 2 event venues. URWLD addresses a key community and society issue of encouraging the entire populace to be active to support lifestyle mindset change and impact the alarming trend of obesity, diabetes and inactivity that threatens our future generations. By providing an accessible environment to help introduce a broad range of activities that encourage movement we will work to address this through our communications and positioning as well as with our event activities, TedTalks hosted and others to promote improving mobility for all age groups
A7: PARKING - we are in discussions with Wilson Parking to JV on a 900 space parking building connected to URWLD to service the precinct as well as to support the government policy on congestion reduction within the CBD. We will provide business day parking with shuttle service into the CBD area to Spencer St transport hub for trains, trams and buses. In the future when the Plummer St Light Rail/Tram is undertaken by state government the proximity will allow us to reduce shuttle services. The parking building will connect to both the live venue and URWLD buildings
A11: Central Park - in keeping with the need for green space and open areas for common use we have allocated space within the site for a central park which we plan to develop with native landscape focus and a central courtyard as a "FOOD TRUCK" park highlighting handheld foods from numerous cultures as part of our F&B offering. This area will also be used for day time and evening buskers for entertainment.
A13: Employment and Community - We believe that Fisherman's Bend precinct's combined development will create almost 1,000 FTE jobs and support the planned redevelopment of the Fishermans Bend Urban Renewal Framework by encouraging further state and federal investment in infrastructure of light rail, metro and roads as well as private investor development of the larger sites for increased residential and commercial use of the area.
A15: The zone we are developing is on a site of 37k square metres

Sheet Dynamic Dashboard
B2: THE BEND LIVE HOUSE
B3: Investor Dashboard | M3: Active Scenario: | N3: ='Inputs for Dashboard'!C9 -> Base
B5: SECTION 1 — KEY PERFORMANCE INDICATORS
B7: PROJECT IRR (UNLEVERED) | D7: EQUITY IRR (LEVERED) | F7: EQUITY MOIC | H7: ENTERPRISE VALUE (DCF) | J7: EQUITY VALUE | L7: PAYBACK PERIOD
B8: ='Inputs for Dashboard'!C18 -> 0.24794587 | D8: ='Inputs for Dashboard'!C20 -> 0.33284791 | F8: ='Inputs for Dashboard'!C22 -> 17.693182 | H8: ='Inputs for Dashboard'!C19 -> 62301607 | J8: ='Inputs for Dashboard'!C21 -> 50077920 | L8: ='Inputs for Dashboard'!C23 -> FY30
B10: Return on total capital | D10: Return to equity investors | F10: Multiple on invested capital | H10: NPV @ WACC | J10: EV less net debt | L10: Equity breakeven year
B12: AVG DSCR | D12: YIELD ON COST | F12: WACC | H12: EXIT MULTIPLE | J12: TOTAL CAPEX | L12: DEBT / TOTAL CAP
B13: =AVERAGEIF('Inputs for Dashboard'!F61:N61,">0") -> 4.0738366 | D13: ='Inputs for Dashboard'!C24 -> 0.70345496 | F13: ='Inputs for Dashboard'!C10 -> 0.1 | H13: ='Inputs for Dashboard'!C12 -> 7 | J13: ='Inputs for Dashboard'!C28 -> 19761525 | L13: ='Inputs for Dashboard'!C33 -> 0.58559274
B16: SECTION 2 — REVENUE & PROFITABILITY TREND
B17: FY (operations start FY28)
B30: SECTION 3 — DEBT REPAYMENT & COVERAGE
B31: Bank term debt amortises over 10 years at 8% — fully repaid by FY36
B44: SECTION 4 — CASH FLOWS & SHAREHOLDER RETURNS
B45: Unlevered vs Equity cash flows; dividends track stabilised operations
B58: SECTION 5 — CAPITAL STRUCTURE & EQUITY BUILD
B59: Funding sources and book equity growth trajectory
B72: SECTION 6 — SENSITIVITY ANALYSIS
B73: Stress test Enterprise Value and Equity IRR under changing WACC, exit multiple and EBITDA assumptions
B75: Enterprise Value ($) — WACC vs Exit Multiple | I75: Equity IRR — EBITDA Δ vs Exit Multiple
B76: WACC ↓ / Mult → | C76: 6.0x | D76: 7.0x | E76: 8.0x | F76: 9.0x | G76: 10.0x | I76: EBITDA Δ ↓ / Mult → | J76: 6.0x | K76: 7.0x | L76: 8.0x | M76: 9.0x | N76: 10.0x
B77: 0.08 | C77: ='Inputs for Dashboard'!C80 -> 63401162 | D77: ='Inputs for Dashboard'!D80 -> 70048481 | E77: ='Inputs for Dashboard'!E80 -> 76695801 | F77: ='Inputs for Dashboard'!F80 -> 83343120 | G77: ='Inputs for Dashboard'!G80 -> 89990440 | I77: -0.2 | J77: ='Inputs for Dashboard'!C88 -> 0.23284824 | K77: ='Inputs for Dashboard'!D88 -> 0.25283307 | L77: ='Inputs for Dashboard'!E88 -> 0.27040638 | M77: ='Inputs for Dashboard'!F88 -> 0.28611164 | N77: ='Inputs for Dashboard'!G88 -> 0.30032492
B78: 0.09 | C78: ='Inputs for Dashboard'!C81 -> 60028461 | D78: ='Inputs for Dashboard'!D81 -> 66113664 | E78: ='Inputs for Dashboard'!E81 -> 72198867 | F78: ='Inputs for Dashboard'!F81 -> 78284070 | G78: ='Inputs for Dashboard'!G81 -> 84369273 | I78: -0.1 | J78: ='Inputs for Dashboard'!C89 -> 0.24808919 | K78: ='Inputs for Dashboard'!D89 -> 0.26832108 | L78: ='Inputs for Dashboard'!E89 -> 0.28611164 | M78: ='Inputs for Dashboard'!F89 -> 0.30201105 | N78: ='Inputs for Dashboard'!G89 -> 0.31640004
B79: 0.1 | C79: ='Inputs for Dashboard'!C82 -> 56967947 | D79: ='Inputs for Dashboard'!D82 -> 62543064 | E79: ='Inputs for Dashboard'!E82 -> 68118181 | F79: ='Inputs for Dashboard'!F82 -> 73693298 | G79: ='Inputs for Dashboard'!G82 -> 79268415 | I79: 0% (Base) | J79: ='Inputs for Dashboard'!C90 -> 0.26188226 | K79: ='Inputs for Dashboard'!D90 -> 0.28233774 | L79: ='Inputs for Dashboard'!E90 -> 0.30032492 | M79: ='Inputs for Dashboard'!F90 -> 0.31640004 | N79: ='Inputs for Dashboard'!G90 -> 0.33094805
B80: 0.11 | C80: ='Inputs for Dashboard'!C83 -> 54188268 | D80: ='Inputs for Dashboard'!D83 -> 59300105 | E80: ='Inputs for Dashboard'!E83 -> 64411942 | F80: ='Inputs for Dashboard'!F83 -> 69523779 | G80: ='Inputs for Dashboard'!G83 -> 74635616 | I80: 0.1 | J80: ='Inputs for Dashboard'!C91 -> 0.27449089 | K80: ='Inputs for Dashboard'!D91 -> 0.29515076 | L80: ='Inputs for Dashboard'!E91 -> 0.31331766 | M80: ='Inputs for Dashboard'!F91 -> 0.32955341 | N80: ='Inputs for Dashboard'!G91 -> 0.34424677
B81: 0.12 | C81: ='Inputs for Dashboard'!C84 -> 51661463 | D81: ='Inputs for Dashboard'!D84 -> 56352166 | E81: ='Inputs for Dashboard'!E84 -> 61042870 | F81: ='Inputs for Dashboard'!F84 -> 65733573 | G81: ='Inputs for Dashboard'!G84 -> 70424276 | I81: 0.2 | J81: ='Inputs for Dashboard'!C92 -> 0.28611164 | K81: ='Inputs for Dashboard'!D92 -> 0.30695989 | L81: ='Inputs for Dashboard'!E92 -> 0.32529243 | M81: ='Inputs for Dashboard'!F92 -> 0.34167621 | N81: ='Inputs for Dashboard'!G92 -> 0.35650356
B84: SECTION 7 — OPERATIONAL KPIS
B85: Event day utilisation and revenue intensity underpin the financial forecast
B87: STABILISED EVENT DAYS (FY30+) | E87: REVENUE / EVENT DAY (FY30+) | H87: REVENUE CAGR (FY28-FY36) | K87: FY28 → FY36 REVENUE GROWTH
B88: ='Inputs for Dashboard'!H151 -> 162.342 | E88: ='Inputs for Dashboard'!H152 -> 126988.22 | H88: =('Inputs for Dashboard'!N40/'Inputs for Dashboard'!F40)^(1/8)-1 -> 0.033412769 | K88: ='Inputs for Dashboard'!N40-'Inputs for Dashboard'!F40 -> 5645596.8
B102: SECTION 8 — USE OF PROCEEDS (CAPEX BREAKDOWN)
B103: Where the construction capex is deployed
B117: SECTION 9 — SCENARIO COMPARISON
B118: Impact of alternate assumptions on returns — active scenario set via Scenarios!B4
B120: Scenario | C120: Rev Impact | D120: Cost Impact | E120: IRR Δ (pp) | F120: Risk Level
B121: ='Inputs for Dashboard'!B174 -> Base | C121: ='Inputs for Dashboard'!C174 -> 0 | D121: ='Inputs for Dashboard'!D174 -> 0 | E121: ='Inputs for Dashboard'!E174 -> Baseline | F121: ='Inputs for Dashboard'!F174 -> ●●○○○
B122: ='Inputs for Dashboard'!B175 -> Optimistic | C122: ='Inputs for Dashboard'!C175 -> 0.1 | D122: ='Inputs for Dashboard'!D175 -> -0.05 | E122: ='Inputs for Dashboard'!E175 -> 2.95 | F122: ='Inputs for Dashboard'!F175 -> ●○○○○
B123: ='Inputs for Dashboard'!B176 -> Pessimistic | C123: ='Inputs for Dashboard'!C176 -> -0.15 | D123: ='Inputs for Dashboard'!D176 -> 0.1 | E123: ='Inputs for Dashboard'!E176 -> -5.08 | F123: ='Inputs for Dashboard'!F176 -> ●●●●○
B124: ='Inputs for Dashboard'!B177 -> Delayed +3m | C124: ='Inputs for Dashboard'!C177 -> 0 | D124: ='Inputs for Dashboard'!D177 -> 0 | E124: ='Inputs for Dashboard'!E177 -> -1.02 | F124: ='Inputs for Dashboard'!F177 -> ●●●○○
B125: ='Inputs for Dashboard'!B178 -> Delayed +6m | C125: ='Inputs for Dashboard'!C178 -> 0 | D125: ='Inputs for Dashboard'!D178 -> 0 | E125: ='Inputs for Dashboard'!E178 -> -2.04 | F125: ='Inputs for Dashboard'!F178 -> ●●●●○
B126: ='Inputs for Dashboard'!B179 -> Capex +10% | C126: ='Inputs for Dashboard'!C179 -> 0 | D126: ='Inputs for Dashboard'!D179 -> 0.1 | E126: ='Inputs for Dashboard'!E179 -> -2.03 | F126: ='Inputs for Dashboard'!F179 -> ●●●○○
B127: ='Inputs for Dashboard'!B180 -> Capex +20% | C127: ='Inputs for Dashboard'!C180 -> 0 | D127: ='Inputs for Dashboard'!D180 -> 0.2 | E127: ='Inputs for Dashboard'!E180 -> -4.05 | F127: ='Inputs for Dashboard'!F180 -> ●●●●○
B128: ='Inputs for Dashboard'!B181 -> Sponsorship Under | C128: ='Inputs for Dashboard'!C181 -> -0.1 | D128: ='Inputs for Dashboard'!D181 -> 0 | E128: ='Inputs for Dashboard'!E181 -> -2.03 | F128: ='Inputs for Dashboard'!F181 -> ●●●○○
B134: SECTION 10 — EXIT WATERFALL & EV BRIDGE
B135: How the $46M equity value is built from operating cash flows and terminal exit at FY36
B137: EV BRIDGE
B138: Component | C138: Value ($M) | D138: % of EV
B139: PV of Operating FCF (FY25–FY36) | C139: ='Inputs for Dashboard'!C188 -> 30048863 | D139: =C139/$C$141 -> 0.48231281
B140: PV of Terminal Value | C140: ='Inputs for Dashboard'!C189 -> 32252744 | D140: =C140/$C$141 -> 0.51768719
B141: Enterprise Value (DCF) | C141: ='Inputs for Dashboard'!C190 -> 62301607 | D141: 1
B142: Less: Debt at Valuation | C142: ='Inputs for Dashboard'!C191 -> -12675915 | D142: =C142/$C$141 -> -0.20346048
B143: Add: Cash at Valuation | C143: ='Inputs for Dashboard'!C192 -> -452228.4 | D143: =C143/$C$141 -> -0.0072586956
B144: EQUITY VALUE | C144: ='Inputs for Dashboard'!C193 -> 50077920 | D144: =C144/$C$141 -> 0.80379821
B146: EXIT ASSUMPTIONS (FY38)
B147: Exit Year | C147: ='Inputs for Dashboard'!C196 -> FY38
B148: Exit EBITDA | C148: ='Inputs for Dashboard'!C197 -> 13901343
B149: Exit Multiple | C149: ='Inputs for Dashboard'!C198 -> 7
B150: Terminal Value (undiscounted) | C150: ='Inputs for Dashboard'!C199 -> 97309399
B151: % of EV from Terminal | C151: =D140 -> 0.51768719
B155: INVESTOR TAKEAWAYS
B156: ="• Project IRR of "&TEXT('Inputs for Dashboard'!C18,"0.0%")&" on unlevered basis; equity IRR of "&TEXT('Inputs for Dashboard'!C20,"0.0%")&" post-leverage." -> • Project IRR of 24.8% on unlevered basis; equity IRR of 33.3% post-leverage.
B157: ="• Equity multiple of "&TEXT('Inputs for Dashboard'!C22,"0.0")&"x — $"&TEXT('Inputs for Dashboard'!C21/1000000,"0.0")&"M equity value against $"&TEXT(('Inputs for Dashboard'!C30+'Inputs for Dashboard'!C31)/1000000,"0.0")&"M invested." -> • Equity multiple of 17.7x — $50.1M equity value against $9.0M invested.
B158: ="• Payback in "&'Inputs for Dashboard'!C23&"; debt fully amortised by FY36. Average DSCR well above 1.2x covenant." -> • Payback in FY30; debt fully amortised by FY36. Average DSCR well above 1.2x covenant.
B159: ="• "&TEXT(D140,"0%")&" of EV comes from terminal value at "&TEXT('Inputs for Dashboard'!C198,"0.0")&"x EBITDA exit — sensitive to exit multiple assumption." -> • 52% of EV comes from terminal value at 7.0x EBITDA exit — sensitive to exit multiple assumption.
B160: • Stabilised operations generate consistent dividends; terminal value at exit drives the bulk of equity return.
B161: ="• Active scenario: "&'Inputs for Dashboard'!C9&" — switch via Scenarios sheet (B4) to re-run all metrics dynamically." -> • Active scenario: Base — switch via Scenarios sheet (B4) to re-run all metrics dynamically.
B165: SECTION 11 — DRAWDOWN SCHEDULE & MILESTONE FUNDING
B166: Yearly view of equity & debt deployment across construction (linked to Inputs for Dashboard Section 14)
B168: TOTAL FUNDING NEED | D168: EQUITY DRAWN | F168: DEBT DRAWN | H168: EQUITY % | J168: DEBT %
B169: ='Inputs for Dashboard'!Q249 -> 22496298 | D169: ='Inputs for Dashboard'!Q247 -> 8970383.1 | F169: ='Inputs for Dashboard'!Q248+'Inputs for Dashboard'!Q242+'Inputs for Dashboard'!Q243 -> 13525915 | H169: =D169/B169 -> 0.3987493 | J169: =F169/B169 -> 0.6012507
B171: Total project cost incl. lease + IDC | D171: Total equity deployed FY26-FY27 | F171: Total senior debt drawn FY27 | H171: Equity share at completion | J171: Debt share at completion
B173: YEARLY DRAWDOWN | C173: FY25 | D173: FY26 | E173: FY27 | F173: FY28 | G173: FY29 | H173: FY30 | I173: TOTAL
B174: Total funding need | C174: ='Inputs for Dashboard'!C235 -> 0 | D174: ='Inputs for Dashboard'!D235 -> 0 | E174: ='Inputs for Dashboard'!E235+'Inputs for Dashboard'!Q251 -> 22496298 | F174: ='Inputs for Dashboard'!F235 -> 0 | G174: ='Inputs for Dashboard'!G235 -> 0 | H174: ='Inputs for Dashboard'!H235 -> 0 | I174: =SUM(C174:H174) -> 22496298
B175: Equity drawn | C175: ='Inputs for Dashboard'!C240 -> 0 | D175: ='Inputs for Dashboard'!D240 -> 0 | E175: ='Inputs for Dashboard'!E240 -> 8970383.1 | F175: ='Inputs for Dashboard'!F240 -> 0 | G175: ='Inputs for Dashboard'!G240 -> 0 | H175: ='Inputs for Dashboard'!H240 -> 0 | I175: =SUM(C175:H175) -> 8970383.1
B176: Debt drawn | C176: ='Inputs for Dashboard'!C241 -> 0 | D176: ='Inputs for Dashboard'!D241 -> 0 | E176: ='Inputs for Dashboard'!E241 -> 11856915 | F176: ='Inputs for Dashboard'!F241 -> 0 | G176: ='Inputs for Dashboard'!G241 -> 0 | H176: ='Inputs for Dashboard'!H241 -> 0 | I176: =SUM(C176:H176) -> 11856915
B177: Cumulative funding | C177: ='Inputs for Dashboard'!C249 -> 0 | D177: ='Inputs for Dashboard'!D249 -> 0 | E177: ='Inputs for Dashboard'!E249 -> 22496298 | F177: ='Inputs for Dashboard'!F249 -> 22496298 | G177: ='Inputs for Dashboard'!G249 -> 22496298 | H177: ='Inputs for Dashboard'!H249 -> 22496298 | I177: =H177 -> 22496298
B179: → Click 'Inputs for Dashboard' tab, scroll to Section 14 for full schedule, milestone map, capital structure split, and validation checks.
B181: SECTION 12 — OPERATING & FINANCIAL HEALTH SNAPSHOT
B182: Profitability margins, coverage ratios, and operating intensity at stabilised exit (FY36) — sourced from Dashboard tab
B184: A. PROFITABILITY AT STABILISED EXIT (FY36)
B185: EBITDA MARGIN | D185: GROSS MARGIN | F185: NET MARGIN | H185: REV / EVENT DAY | J185: EBITDA / EVENT DAY
B186: =Dashboard!J56 -> 0.54361595 | D186: =Dashboard!J54 -> 0.87856188 | F186: =Dashboard!J58 -> 0.35348387 | H186: =Dashboard!J77 -> 146965.47 | J186: =Dashboard!J78 -> 79892.774
B188: EBITDA / Revenue at exit | D188: Gross Profit / Revenue | F188: NPAT / Revenue at exit | H188: Revenue per event day (180 days/yr) | J188: EBITDA per event day
B190: B. COVERAGE, RUNWAY & OPERATING INTENSITY
B191: MIN DSCR | D191: MIN ICR | F191: ANNUAL EVENT DAYS | H191: DEBT PAYOFF YEAR | J191: OPERATIONS START
B192: =Dashboard!G76 -> 3.0466904 | D192: =Dashboard!G78 -> 9.7508767 | F192: =Dashboard!J75 -> 174 | H192: =Dashboard!P48 -> FY32 | J192: =IF(MONTH('Construction Timeline'!C200)>=7,"FY"&TEXT(YEAR('Construction Timeline'!C200)-1999,"00"),"FY"&TEXT(YEAR('Construction Timeline'!C200)-2000,"00")) -> FY28
B194: Worst-case debt service cover | D194: Worst-case interest cover | F194: Stabilised event days per year | H194: When senior debt is fully repaid | J194: Soft opening / revenue commencement
B196: → Click 'Dashboard' tab for the full static metric inventory (Capacity Configurations, Revenue Mix, Event Days Mix, OPEX detail, full Coverage Ratios).

Sheet Dashboard
A1: THE BEND LIVE HOUSE — EXECUTIVE DASHBOARD
P2: Active Scenario | Q2: =Scenarios!$B$4 -> Base
P3: Model Health | Q3: =IF(#REF!=0,"OK","FAIL") -> #REF!
B5: Summary
B6: FY | C6: =IFERROR(Cashflow!D$7,"") -> FY25 | D6: =IFERROR(Cashflow!E$7,"") -> FY26 | E6: =IFERROR(Cashflow!F$7,"") -> FY27 | F6: =IFERROR(Cashflow!G$7,"") -> FY28 | G6: =IFERROR(Cashflow!H$7,"") -> FY29 | H6: =IFERROR(Cashflow!I$7,"") -> FY30 | I6: =IFERROR(Cashflow!J$7,"") -> FY31 | J6: =IFERROR(Cashflow!K$7,"") -> FY32 | ... P6: =IFERROR(Cashflow!Q$7,"") -> FY38
B7: Revenue | C7: =IFERROR(Cashflow!D$48,"") -> 0 | D7: =IFERROR(Cashflow!E$48,"") -> 0 | E7: =IFERROR(Cashflow!F$48,"") -> 0 | F7: =IFERROR(Cashflow!G$48,"") -> 18772333 | G7: =IFERROR(Cashflow!H$48,"") -> 19676502 | H7: =IFERROR(Cashflow!I$48,"") -> 20615522 | I7: =IFERROR(Cashflow!J$48,"") -> 21808635 | J7: =IFERROR(Cashflow!K$48,"") -> 22300757 | ... P7: =IFERROR(Cashflow!Q$48,"") -> 25571992
B8: EBITDA | C8: =IFERROR(Cashflow!D$64,"") -> 0 | D8: =IFERROR(Cashflow!E$64,"") -> 0 | E8: =IFERROR(Cashflow!F$64,"") -> 0 | F8: =IFERROR(Cashflow!G$64,"") -> 10240353 | G8: =IFERROR(Cashflow!H$64,"") -> 10221611 | H8: =IFERROR(Cashflow!I$64,"") -> 10726643 | I8: =IFERROR(Cashflow!J$64,"") -> 11603174 | J8: =IFERROR(Cashflow!K$64,"") -> 11825139 | ... P8: =IFERROR(Cashflow!Q$64,"") -> 13901343
B9: Closing Cash | C9: =IFERROR(Cashflow!D38,"") -> 0 | D9: =IFERROR(Cashflow!E38,"") -> 0 | E9: =IFERROR(Cashflow!F38,"") -> 452228.4 | F9: =IFERROR(Cashflow!G38,"") -> 1724785.6 | G9: =IFERROR(Cashflow!H38,"") -> 2184190 | H9: =IFERROR(Cashflow!I38,"") -> 2729888 | I9: =IFERROR(Cashflow!J38,"") -> 3408439 | J9: =IFERROR(Cashflow!K38,"") -> 4135811.4 | ... P9: =IFERROR(Cashflow!Q38,"") -> 12278575
B10: Total Debt | C10: =IFERROR(Debt!H48,0) -> 0 | D10: =IFERROR(Debt!I48,0) -> 0 | E10: =IFERROR(Debt!J48,0) -> 12675915 | F10: =IFERROR(Debt!K48,0) -> 12675915 | G10: =IFERROR(Debt!L48,0) -> 11091426 | H10: =IFERROR(Debt!M48,0) -> 9506936.2 | I10: =IFERROR(Debt!N48,0) -> 7922446.9 | J10: =IFERROR(Debt!O48,0) -> 6337957.5 | ... P10: =IFERROR(Debt!U48,0) -> 0
B11: DSCR | C11: =Cashflow!D67 | D11: =Cashflow!E67 | E11: =Cashflow!F67 | F11: =Cashflow!G67 -> 3.748065 | G11: =Cashflow!H67 -> 3.0466904 | H11: =Cashflow!I67 -> 3.3189554 | I11: =Cashflow!J67 -> 3.7480419 | J11: =Cashflow!K67 -> 4.0469539 | ... P11: =Cashflow!Q67
B12: ICR | C12: =IFERROR(IF(Debt!H$57=0,"",Cashflow!D$64/Debt!H$57),"") | D12: =IFERROR(IF(Debt!I$57=0,"",Cashflow!E$64/Debt!I$57),"") | E12: =IFERROR(IF(Debt!J$57=0,"",Cashflow!F$64/Debt!J$57),"") -> 0 | F12: =IFERROR(IF(Debt!K$57=0,"",Cashflow!G$64/Debt!K$57),"") -> 10.098239 | G12: =IFERROR(IF(Debt!L$57=0,"",Cashflow!H$64/Debt!L$57),"") -> 10.75174 | H12: =IFERROR(IF(Debt!M$57=0,"",Cashflow!I$64/Debt!M$57),"") -> 13.018806 | I12: =IFERROR(IF(Debt!N$57=0,"",Cashflow!J$64/Debt!N$57),"") -> 16.643121 | J12: =IFERROR(IF(Debt!O$57=0,"",Cashflow!K$64/Debt!O$57),"") -> 20.730722 | ... P12: =IFERROR(IF(Debt!U$57=0,"",Cashflow!Q$64/Debt!U$57),"")
B13: Net Leverage (Net Debt/EBITDA) | C13: =IFERROR(IF(Cashflow!D$64=0,"",((Cashflow!D$72+Cashflow!D$73)-Cashflow!D$39)/Cashflow!D$64),"") | D13: =IFERROR(IF(Cashflow!E$64=0,"",((Cashflow!E$72+Cashflow!E$73)-Cashflow!E$39)/Cashflow!E$64),"") | E13: =IFERROR(IF(Cashflow!F$64=0,"",((Cashflow!F$72+Cashflow!F$73)-Cashflow!F$39)/Cashflow!F$64),"") | F13: =IFERROR(IF(Cashflow!G$64=0,"",((Cashflow!G$72+Cashflow!G$73)-Cashflow!G$39)/Cashflow!G$64),"") -> 1.2378396 | G13: =IFERROR(IF(Cashflow!H$64=0,"",((Cashflow!H$72+Cashflow!H$73)-Cashflow!H$39)/Cashflow!H$64),"") -> 1.0850957 | H13: =IFERROR(IF(Cashflow!I$64=0,"",((Cashflow!I$72+Cashflow!I$73)-Cashflow!I$39)/Cashflow!I$64),"") -> 0.88629181 | I13: =IFERROR(IF(Cashflow!J$64=0,"",((Cashflow!J$72+Cashflow!J$73)-Cashflow!J$39)/Cashflow!J$64),"") -> 0.68278276 | J13: =IFERROR(IF(Cashflow!K$64=0,"",((Cashflow!K$72+Cashflow!K$73)-Cashflow!K$39)/Cashflow!K$64),"") -> 0.53597319 | ... P13: =IFERROR(IF(Cashflow!Q$64=0,"",((Cashflow!Q$72+Cashflow!Q$73)-Cashflow!Q$39)/Cashflow!Q$64),"") -> 0
P16: Active Scenario | Q16: =Scenarios!B4 -> Base
P17: Model Health | Q17: =Q3 -> #REF!
B19: FINANCIAL SUMMARY
C20: FY25 | D20: FY26 | E20: FY27 | F20: FY28 | G20: FY29 | H20: FY30 | I20: FY31 | J20: FY32 | K20: FY33 | L20: FY34 | M20: FY35 | N20: FY36 | O20: FY37 | P20: FY38
B21: Revenue | C21: ='P&L'!H28 -> 0 | D21: ='P&L'!I28 -> 0 | E21: ='P&L'!J28 -> 18772333 | F21: ='P&L'!K28 -> 19676502 | G21: ='P&L'!L28 -> 20615522 | H21: ='P&L'!M28 -> 21808635 | I21: ='P&L'!N28 -> 22300757 | J21: ='P&L'!O28 -> 22807316 | ... M21: ='P&L'!R28 -> 24417930 | N21: ='P&L'!R28 -> 24417930 | O21: ='P&L'!S28 -> 24986615 | P21: ='P&L'!T28 -> 25571992
B22: EBITDA | C22: ='P&L'!H79 -> 0 | D22: ='P&L'!I79 -> 0 | E22: ='P&L'!J79 -> 10240353 | F22: ='P&L'!K79 -> 10221611 | G22: ='P&L'!L79 -> 10726643 | H22: ='P&L'!M79 -> 11603174 | I22: ='P&L'!N79 -> 11825139 | J22: ='P&L'!O79 -> 11488417 | ... M22: ='P&L'!R79 -> 12008307 | N22: ='P&L'!R79 -> 12008307 | O22: ='P&L'!S79 -> 12146815 | P22: ='P&L'!T79 -> 13901343
B23: Closing Cash | C23: ='Balance Sheet'!G10 -> 0 | D23: ='Balance Sheet'!H10 -> 452228.4 | E23: ='Balance Sheet'!I10 -> 1724785.6 | F23: ='Balance Sheet'!J10 -> 2184190 | G23: ='Balance Sheet'!K10 -> 2729888 | H23: ='Balance Sheet'!L10 -> 3408439 | I23: ='Balance Sheet'!M10 -> 4135811.4 | J23: ='Balance Sheet'!N10 -> 4833789 | ... M23: ='Balance Sheet'!Q10 -> 7159432.3 | N23: ='Balance Sheet'!Q10 -> 7159432.3 | O23: ='Balance Sheet'!R10 -> 9596186.9 | P23: ='Balance Sheet'!S10 -> 12278575
B24: Total Debt | C24: =Debt!I24+Debt!I43 -> 0 | D24: =Debt!J24+Debt!J43 -> 12675915 | E24: =Debt!K24+Debt!K43 -> 12675915 | F24: =Debt!L24+Debt!L43 -> 11091426 | G24: =Debt!M24+Debt!M43 -> 9506936.2 | H24: =Debt!N24+Debt!N43 -> 7922446.9 | I24: =Debt!O24+Debt!O43 -> 6337957.5 | J24: =Debt!P24+Debt!P43 -> 4753468.1 | ... M24: =Debt!S24+Debt!S43 -> 0 | N24: =Debt!S24+Debt!S43 -> 0 | O24: =Debt!T24+Debt!T43 -> 0 | P24: =Debt!U24+Debt!U43 -> 0
B27: DEBT & LEVERAGE | F27: EVENT DAYS MIX (STABILIZED FY) | I27: EVENT INDUSTRY KPIs (STABILIZED FY)
B28: Metric | C28: Value | F28: Event Type | G28: Days | I28: Metric | J28: Value | K28: Units
B29: Total Debt Facility | C29: =Inputs!E66 -> 11856915 | F29: Music GA (all tiers) | G29: {=IFERROR((INDEX('Calendar Assumptions'!$F$5:$P$5,MATCH(Valuations!C128,'Calendar Assumptions'!$F$4:$P$4,0))+INDEX('Calendar Assumptions'!$F$6:$P$6,MATCH(Valuations!C128,'Calendar Assumptions'!$F$4:$P$4,0))+INDEX('Calendar Assumptions'!$F$7:$P$7,MATCH(Valuations!C128,'Calendar Assumptions'!$F$4:$P$4,0))),0)} -> 48.516 | I29: Annual Event Days | J29: ='Calendar Assumptions'!H16 -> 162.342 | K29: days
B30: Bank Debt | C30: =Inputs!E66 -> 11856915 | F30: EDM | G30: {=IFERROR(INDEX('Calendar Assumptions'!$F$8:$P$8, MATCH(Valuations!C128,'Calendar Assumptions'!$F$4:$P$4,0)),0)} -> 16.794 | I30: Total Revenue | J30: ='P&L'!L28 -> 20615522 | K30: A$
B31: PE Equity | C31: =Inputs!E118+Inputs!E114 -> 8970383.1 | F31: Seated Music | G31: {=IFERROR(INDEX('Calendar Assumptions'!$F$9:$P$9, MATCH(Valuations!C128,'Calendar Assumptions'!$F$4:$P$4,0)),0)} -> 13.995 | I31: Revenue per Event Day | J31: =J30/J29 -> 126988.22 | K31: A$/day
B32: Bank Term (years) | C32: =Inputs!E64 -> 10 | F32: Comedy | G32: {=IFERROR(INDEX('Calendar Assumptions'!$F$10:$P$10, MATCH(Valuations!C128,'Calendar Assumptions'!$F$4:$P$4,0)),0)} -> 13.995 | I32: EBITDA per Event Day | J32: ='P&L'!L79/J29 -> 66074.358 | K32: A$/day
B33: PE Equity Injection Year | C33: =Inputs!E131 -> FY27 | F33: Corporate | G33: {=IFERROR(INDEX('Calendar Assumptions'!$F$11:$P$11, MATCH(Valuations!C128,'Calendar Assumptions'!$F$4:$P$4,0)),0)} -> 2.799 | I33: Yield on Cost | J33: =Valuations!C130 -> 0.54280444 | K33: %
B34: Bank Interest Rate | C34: =Inputs!E63 -> 0.08 | F34: MICE | G34: {=IFERROR(INDEX('Calendar Assumptions'!$F$12:$P$12, MATCH(Valuations!C128,'Calendar Assumptions'!$F$4:$P$4,0)),0)} -> 27.057
B35: Shareholder Loan Toggle | C35: =IF(Inputs!E133=0,"OFF","ON") -> OFF | F35: Community | G35: {=IFERROR(INDEX('Calendar Assumptions'!$F$13:$P$13, MATCH(Valuations!C128,'Calendar Assumptions'!$F$4:$P$4,0)),0)} -> 11.196
B36: Debt/Total Capex | C36: =(Inputs!E66+Inputs!E75)/Inputs!E159 -> 0.6 | F36: Live Site | G36: {=IFERROR(INDEX('Calendar Assumptions'!$F$14:$P$14, MATCH(Valuations!C128,'Calendar Assumptions'!$F$4:$P$4,0)),0)} -> 3.732
B39: VALUATION SUMMARY | F39: PROFITABILITY METRICS (EXIT FY) | I39: KEY INVESTMENT METRICS | J39: Value | L39: REVENUE MIX (EXIT FY) | O39: DEBT & LEVERAGE
B40: Metric | C40: Value | D40: Notes | F40: Metric | G40: Value | I40: Metric | J40: Value | L40: Stream | M40: Value | O40: Metric | P40: Value
B41: WACC | C41: =Valuations!C9 -> 0.1 | D41: Discount rate | F41: Total Revenue | G41: ='P&L'!L28 -> 20615522 | I41: Total Capex | J41: =Inputs!E159 -> 19761525 | L41: VHA | M41: {=IFERROR(INDEX('P&L'!$G$14:$T$14, MATCH(Inputs!$E$488,'P&L'!$G$6:$T$6,0)),0)} -> 7723631.2 | O41: Total Debt Facility | P41: =Debt!C5+Debt!D5 -> 12675915
B42: Exit Multiple | C42: =Valuations!C15 -> 7 | D42: EBITDA multiple | F42: Gross Profit | G42: ='P&L'!L40 -> 18125573 | I42: Equity Required | J42: =SUM(Cashflow!D13:O14) -> 8970383.1 | L42: Premium Sales | M42: {=IFERROR(INDEX('P&L'!$G$15:$T$15, MATCH(Inputs!$E$488,'P&L'!$G$6:$T$6,0)),0)} -> 1084742.1 | O42: Bank Debt | P42: =Debt!C5 -> 12675915
B43: Exit EBITDA | C43: =Valuations!C72 -> 13901343 | D43: FY38 EBITDA | F43: Gross Margin % | G43: ='P&L'!L41 -> 0.87921971 | I43: Total Debt | J43: =Debt!C5+Debt!D5 -> 12675915 | L43: Premium F&B | M43: {=IFERROR(INDEX('P&L'!$G$16:$T$16, MATCH(Inputs!$E$488,'P&L'!$G$6:$T$6,0)),0)} -> 182520 | O43: PE Loan | P43: =Debt!D5 -> 0
B44: Terminal Value | C44: =Valuations!C74 -> 97309399 | D44: Exit value | F44: EBITDA | G44: ='P&L'!L79 -> 10726643 | I44: Debt/Equity Ratio | J44: =J43/J42 -> 1.4130851 | L44: F&B | M44: {=IFERROR(INDEX('P&L'!$G$17:$T$17, MATCH(Inputs!$E$488,'P&L'!$G$6:$T$6,0)),0)} -> 8690093.4 | O44: Bank Term (years) | P44: =Debt!C6 -> 10
B45: Enterprise Value | C45: =Valuations!C91 -> 62301607 | D45: DCF valuation | F45: EBITDA Margin % | G45: ='P&L'!L80 -> 0.52031879 | I45: Project IRR | J45: =Valuations!C109 -> 0.24794587 | L45: Merchandise | M45: {=IFERROR(INDEX('P&L'!$G$18:$T$18, MATCH(Inputs!$E$488,'P&L'!$G$6:$T$6,0)),0)} -> 832800 | O45: PE Term (years) | P45: =Debt!D6 -> 10
B46: Net Debt (Exit) | C46: =Valuations!C93+Valuations!C94 -> -12223687 | D46: Debt - Cash at exit | F46: NPAT | G46: ='P&L'!L95 -> 6240242.9 | I46: Equity IRR | J46: =Valuations!C123 -> 0.33284791 | L46: Equipment Hire | M46: {=IFERROR(INDEX('P&L'!$G$20:$T$20, MATCH(Inputs!$E$488,'P&L'!$G$6:$T$6,0)),0)} -> 2610000 | O46: Bank Interest Rate | P46: =Debt!C7 -> 0.08
B47: Equity Value | C47: =Valuations!C23 -> 50077920 | D47: EV less Net Debt | F47: Net Margin % | G47: =IF(G41=0,0,G46/G41) -> 0.30269634 | I47: MOIC | J47: =Valuations!C127 -> 17.693182 | L47: Sponsorship | M47: {=IFERROR(INDEX('P&L'!$G$24:$T$24, MATCH(Inputs!$E$488,'P&L'!$G$6:$T$6,0)),0)} -> 2368156.4 | O47: PE Interest Rate | P47: =Debt!D7 -> 0.12
I48: Payback Period | J48: FY30 | L48: Advertising | M48: {=IFERROR(INDEX('P&L'!$G$25:$T$25, MATCH(Inputs!$E$488,'P&L'!$G$6:$T$6,0)),0)} -> 736048.61 | O48: Debt Payoff Year | P48: FY32
O49: Debt/Total Capex | P49: =P41/Inputs!E159 -> 0.64144417
B50: RETURN METRICS | F50: KEY INVESTMENT METRICS | I50: PROFITABILITY METRICS (EXIT FY) | L50: EVENT DAYS MIX (EXIT FY) | O50: VENUE CAPACITY
B51: Metric | C51: Value | D51: Description | F51: Metric | G51: Value | I51: Metric | J51: Value | L51: Event Type | M51: Days | O51: Configuration | P51: Capacity
B52: Project IRR | C52: =Valuations!C20 -> 0.24794587 | D52: Unlevered return | F52: Total Funding Requirement | G52: =Inputs!E60 -> 22496298 | I52: Total Revenue | J52: ='P&L'!T28 -> 25571992 | L52: Music GA (all tiers) | M52: {=IFERROR((INDEX('Calendar Assumptions'!$F$5:$P$5,MATCH(Inputs!$E$488,'Calendar Assumptions'!$F$4:$P$4,0))+INDEX('Calendar Assumptions'!$F$6:$P$6,MATCH(Inputs!$E$488,'Calendar Assumptions'!$F$4:$P$4,0))+INDEX('Calendar Assumptions'!$F$7:$P$7,MATCH(Inputs!$E$488,'Calendar Assumptions'!$F$4:$P$4,0))),0)} -> 52 | O52: Music GA (Large) | P52: ='Revenue Assumptions'!D5 -> 5000
B53: Equity IRR | C53: =Valuations!C22 -> 0.33284791 | D53: Levered return | F53: Total Equity | G53: =Inputs!E120 -> 8970383.1 | I53: Gross Profit | J53: ='P&L'!T40 -> 22466577 | L53: EDM | M53: {=IFERROR(INDEX('Calendar Assumptions'!$F$8:$P$8, MATCH(Inputs!$E$488,'Calendar Assumptions'!$F$4:$P$4,0)),0)} -> 18 | O53: Music GA (Medium) | P53: ='Revenue Assumptions'!D6 -> 3000
B54: Project NPV @ WACC | C54: =Valuations!C21 -> 62301607 | D54: Value creation | F54: Total Debt | G54: =Inputs!E53-Inputs!E51 -> 12675915 | I54: Gross Margin % | J54: ='P&L'!T41 -> 0.87856188 | L54: Seated Music | M54: {=IFERROR(INDEX('Calendar Assumptions'!$F$9:$P$9, MATCH(Inputs!$E$488,'Calendar Assumptions'!$F$4:$P$4,0)),0)} -> 15 | O54: Music GA (Small) | P54: ='Revenue Assumptions'!D7 -> 1500
B55: Equity NPV @ Ke | C55: =Valuations!C23 -> 50077920 | D55: Value to equity | F55: Debt/Equity Ratio | G55: =IF(Inputs!E120>0,Inputs!E66/Inputs!E120,0) -> 1.3217847 | I55: EBITDA | J55: ='P&L'!T79 -> 13901343 | L55: Comedy | M55: {=IFERROR(INDEX('Calendar Assumptions'!$F$10:$P$10, MATCH(Inputs!$E$488,'Calendar Assumptions'!$F$4:$P$4,0)),0)} -> 15 | O55: EDM/Dance | P55: ='Revenue Assumptions'!D8 -> 3500
B56: MOIC | C56: =Valuations!C24 -> 17.693182 | D56: Cash multiple | F56: Project IRR | G56: =Valuations!C20 -> 0.24794587 | I56: EBITDA Margin % | J56: ='P&L'!T80 -> 0.54361595 | L56: Corporate | M56: {=IFERROR(INDEX('Calendar Assumptions'!$F$11:$P$11, MATCH(Inputs!$E$488,'Calendar Assumptions'!$F$4:$P$4,0)),0)} -> 3 | O56: Seated Events | P56: ='Revenue Assumptions'!D9 -> 3500
B57: Yield on Cost | C57: =Valuations!C26 -> 0.70345496 | D57: Stabilised EBITDA / Capex | F57: Equity IRR | G57: =Valuations!C22 -> 0.33284791 | I57: NPAT | J57: ='P&L'!T95 -> 9039286.5 | L57: MICE | M57: {=IFERROR(INDEX('Calendar Assumptions'!$F$12:$P$12, MATCH(Inputs!$E$488,'Calendar Assumptions'!$F$4:$P$4,0)),0)} -> 29 | O57: MICE/Corporate | P57: ='Revenue Assumptions'!D12 -> 3500
F58: MOIC | G58: =Valuations!C24 -> 17.693182 | I58: Net Margin % | J58: =IF(J52=0,0,J57/J52) -> 0.35348387 | L58: Community | M58: {=IFERROR(INDEX('Calendar Assumptions'!$F$13:$P$13, MATCH(Inputs!$E$488,'Calendar Assumptions'!$F$4:$P$4,0)),0)} -> 12 | O58: Community | P58: ='Revenue Assumptions'!D13 -> 2000
F59: Payback Period | G59: =Valuations!C25 -> FY30 | L59: Live Site | M59: {=IFERROR(INDEX('Calendar Assumptions'!$F$14:$P$14, MATCH(Inputs!$E$488,'Calendar Assumptions'!$F$4:$P$4,0)),0)} -> 4 | O59: Max Capacity | P59: 6000
B63: PROJECT TIMELINE | F63: SENSITIVITY SUMMARY
B64: Milestone | C64: Date | F64: Enterprise Value Sensitivity (WACC vs Exit Multiple)
B65: Model Start | C65: =Inputs!E9 -> 46054 | F65: EV ($m) | G65: 6.0x | H65: 7.0x | I65: 8.0x | J65: 9.0x | K65: 10.0x
B66: Lease Signing | C66: =Inputs!E14 -> 46357 | F66: 0.08 | G66: =Valuations!$C$72*6/(1+0.08)^10 -> 38634068 | H66: =Valuations!$C$72*7/(1+0.08)^10 -> 45073080 | I66: =Valuations!$C$72*8/(1+0.08)^10 -> 51512091 | J66: =Valuations!$C$72*9/(1+0.08)^10 -> 57951103 | K66: =Valuations!$C$72*10/(1+0.08)^10 -> 64390114
B67: Construction Start | C67: =Inputs!E18 -> 46420 | F67: 0.09 | G67: =Valuations!$C$72*6/(1+0.09)^10 -> 35232464 | H67: =Valuations!$C$72*7/(1+0.09)^10 -> 41104542 | I67: =Valuations!$C$72*8/(1+0.09)^10 -> 46976619 | J67: =Valuations!$C$72*9/(1+0.09)^10 -> 52848696 | K67: =Valuations!$C$72*10/(1+0.09)^10 -> 58720774
B68: Construction End | C68: =Inputs!E19 -> 46568 | F68: 0.1 | G68: =Valuations!$C$72*6/(1+0.1)^10 -> 32157416 | H68: =Valuations!$C$72*7/(1+0.1)^10 -> 37516986 | I68: =Valuations!$C$72*8/(1+0.1)^10 -> 42876555 | J68: =Valuations!$C$72*9/(1+0.1)^10 -> 48236124 | K68: =Valuations!$C$72*10/(1+0.1)^10 -> 53595694
B69: Operations Start | C69: =Inputs!E22 -> 46569 | F69: 0.11 | G69: =Valuations!$C$72*6/(1+0.11)^10 -> 29375023 | H69: =Valuations!$C$72*7/(1+0.11)^10 -> 34270860 | I69: =Valuations!$C$72*8/(1+0.11)^10 -> 39166697 | J69: =Valuations!$C$72*9/(1+0.11)^10 -> 44062534 | K69: =Valuations!$C$72*10/(1+0.11)^10 -> 48958371
B70: Model End | C70: =Inputs!E10 -> 50526 | F70: 0.12 | G70: =Valuations!$C$72*6/(1+0.12)^10 -> 26855162 | H70: =Valuations!$C$72*7/(1+0.12)^10 -> 31331022 | I70: =Valuations!$C$72*8/(1+0.12)^10 -> 35806882 | J70: =Valuations!$C$72*9/(1+0.12)^10 -> 40282743 | K70: =Valuations!$C$72*10/(1+0.12)^10 -> 44758603
B71: Exit Year | C71: =Valuations!C13 -> FY38
B72: Project Duration | C72: ="12 years" -> 12 years
F73: DEBT COVERAGE RATIOS | I73: EVENT INDUSTRY KPIs (EXIT FY)
B74: OPEX MIX (EXIT FY) | F74: Metric | G74: Value | I74: Metric | J74: Value | K74: Units
B75: Category | C75: Value | F75: Average DSCR | G75: =AVERAGE(Cashflow!G67:O67) -> 4.0738366 | I75: Annual Event Days | J75: ='Calendar Assumptions'!P16 -> 174 | K75: days
B76: Staff Costs | C76: {=IFERROR(INDEX('P&L'!$G$67:$T$67, MATCH(Inputs!$E$488,'P&L'!$G$6:$T$6,0)),0)} -> 2497512.1 | F76: Minimum DSCR | G76: =MIN(Cashflow!G67:O67) -> 3.0466904 | I76: Total Revenue | J76: ='P&L'!T28 -> 25571992 | K76: A$
B77: Lease / Rent | C77: {=IFERROR(INDEX('P&L'!$G$45:$T$45, MATCH(Inputs!$E$488,'P&L'!$G$6:$T$6,0)),0)} -> 956218.63 | F77: Average ICR | G77: =AVERAGE('P&L'!J79/'P&L'!J87,'P&L'!K79/'P&L'!K87,'P&L'!L79/'P&L'!L87,'P&L'!M79/'P&L'!M87) -> 12.541136 | I77: Revenue per Event Day | J77: =J76/J75 -> 146965.47 | K77: A$/day
B78: Utilities | C78: {=IFERROR(INDEX('P&L'!$G$46:$T$46, MATCH(Inputs!$E$488,'P&L'!$G$6:$T$6,0)),0)} -> 315820.35 | F78: Minimum ICR | G78: =MIN('P&L'!J79/'P&L'!J87,'P&L'!K79/'P&L'!K87,'P&L'!L79/'P&L'!L87,'P&L'!M79/'P&L'!M87) -> 9.7508767 | I78: EBITDA per Event Day | J78: ='P&L'!T79/J75 -> 79892.774 | K78: A$/day
B79: Maintenance | C79: 0 | I79: Yield on Cost | J79: =Valuations!C26 -> 0.70345496 | K79: %
B80: Marketing | C80: {=IFERROR(INDEX('P&L'!$G$48:$T$48, MATCH(Inputs!$E$488,'P&L'!$G$6:$T$6,0)),0)} -> 161269.97
B81: Admin/Legal/Insurance/etc | C81: {=IFERROR((INDEX('P&L'!$G$59:$T$59, MATCH(Inputs!$E$488,'P&L'!$G$6:$T$6,0))+INDEX('P&L'!$G$60:$T$60, MATCH(Inputs!$E$488,'P&L'!$G$6:$T$6,0))+INDEX('P&L'!$G$62:$T$62, MATCH(Inputs!$E$488,'P&L'!$G$6:$T$6,0))+INDEX('P&L'!$G$63:$T$63, MATCH(Inputs!$E$488,'P&L'!$G$6:$T$6,0))+INDEX('P&L'!$G$64:$T$64, MATCH(Inputs!$E$488,'P&L'!$G$6:$T$6,0))+INDEX('P&L'!$G$65:$T$65, MATCH(Inputs!$E$488,'P&L'!$G$6:$T$6,0))),0)} -> 486093.46
B82: Other OPEX | C82: 0
A120: ▲ END OF DASHBOARD ▲

Sheet Dashboard (backup)
A1: THE BEND LIVE HOUSE — EXECUTIVE DASHBOARD
A2: THE BEND LIVE HOUSE — EXECUTIVE DASHBOARD | P2: Active Scenario | Q2: =Scenarios!$B$4 -> Base
P3: Model Health | Q3: =IF(#REF!=0,"OK","FAIL") -> #REF!
B5: Summary
B6: FY | C6: =IFERROR(Cashflow!D$7,"") -> FY25 | D6: =IFERROR(Cashflow!E$7,"") -> FY26 | E6: =IFERROR(Cashflow!F$7,"") -> FY27 | F6: =IFERROR(Cashflow!G$7,"") -> FY28 | G6: =IFERROR(Cashflow!H$7,"") -> FY29 | H6: =IFERROR(Cashflow!I$7,"") -> FY30 | I6: =IFERROR(Cashflow!J$7,"") -> FY31 | J6: =IFERROR(Cashflow!K$7,"") -> FY32 | ... P6: =IFERROR(Cashflow!Q$7,"") -> FY38
B7: Revenue | C7: =IFERROR(Cashflow!D$48,"") -> 0 | D7: =IFERROR(Cashflow!E$48,"") -> 0 | E7: =IFERROR(Cashflow!F$48,"") -> 0 | F7: =IFERROR(Cashflow!G$48,"") -> 18772333 | G7: =IFERROR(Cashflow!H$48,"") -> 19676502 | H7: =IFERROR(Cashflow!I$48,"") -> 20615522 | I7: =IFERROR(Cashflow!J$48,"") -> 21808635 | J7: =IFERROR(Cashflow!K$48,"") -> 22300757 | ... P7: =IFERROR(Cashflow!Q$48,"") -> 25571992
B8: EBITDA | C8: =IFERROR(Cashflow!D$64,"") -> 0 | D8: =IFERROR(Cashflow!E$64,"") -> 0 | E8: =IFERROR(Cashflow!F$64,"") -> 0 | F8: =IFERROR(Cashflow!G$64,"") -> 10240353 | G8: =IFERROR(Cashflow!H$64,"") -> 10221611 | H8: =IFERROR(Cashflow!I$64,"") -> 10726643 | I8: =IFERROR(Cashflow!J$64,"") -> 11603174 | J8: =IFERROR(Cashflow!K$64,"") -> 11825139 | ... P8: =IFERROR(Cashflow!Q$64,"") -> 13901343
B9: Closing Cash | C9: =IFERROR(Cashflow!D38,"") -> 0 | D9: =IFERROR(Cashflow!E38,"") -> 0 | E9: =IFERROR(Cashflow!F38,"") -> 452228.4 | F9: =IFERROR(Cashflow!G38,"") -> 1724785.6 | G9: =IFERROR(Cashflow!H38,"") -> 2184190 | H9: =IFERROR(Cashflow!I38,"") -> 2729888 | I9: =IFERROR(Cashflow!J38,"") -> 3408439 | J9: =IFERROR(Cashflow!K38,"") -> 4135811.4 | ... P9: =IFERROR(Cashflow!Q38,"") -> 12278575
B10: Total Debt | C10: =IFERROR(Debt!H48,0) -> 0 | D10: =IFERROR(Debt!I48,0) -> 0 | E10: =IFERROR(Debt!J48,0) -> 12675915 | F10: =IFERROR(Debt!K48,0) -> 12675915 | G10: =IFERROR(Debt!L48,0) -> 11091426 | H10: =IFERROR(Debt!M48,0) -> 9506936.2 | I10: =IFERROR(Debt!N48,0) -> 7922446.9 | J10: =IFERROR(Debt!O48,0) -> 6337957.5 | ... P10: =IFERROR(Debt!U48,0) -> 0
B11: DSCR | C11: =Cashflow!D67 | D11: =Cashflow!E67 | E11: =Cashflow!F67 | F11: =Cashflow!G67 -> 3.748065 | G11: =Cashflow!H67 -> 3.0466904 | H11: =Cashflow!I67 -> 3.3189554 | I11: =Cashflow!J67 -> 3.7480419 | J11: =Cashflow!K67 -> 4.0469539 | ... P11: =Cashflow!Q67
B12: ICR | C12: =IFERROR(IF(Debt!H$57=0,"",Cashflow!D$64/Debt!H$57),"") | D12: =IFERROR(IF(Debt!I$57=0,"",Cashflow!E$64/Debt!I$57),"") | E12: =IFERROR(IF(Debt!J$57=0,"",Cashflow!F$64/Debt!J$57),"") -> 0 | F12: =IFERROR(IF(Debt!K$57=0,"",Cashflow!G$64/Debt!K$57),"") -> 10.098239 | G12: =IFERROR(IF(Debt!L$57=0,"",Cashflow!H$64/Debt!L$57),"") -> 10.75174 | H12: =IFERROR(IF(Debt!M$57=0,"",Cashflow!I$64/Debt!M$57),"") -> 13.018806 | I12: =IFERROR(IF(Debt!N$57=0,"",Cashflow!J$64/Debt!N$57),"") -> 16.643121 | J12: =IFERROR(IF(Debt!O$57=0,"",Cashflow!K$64/Debt!O$57),"") -> 20.730722 | ... P12: =IFERROR(IF(Debt!U$57=0,"",Cashflow!Q$64/Debt!U$57),"")
B13: Net Leverage (Net Debt/EBITDA) | C13: =IFERROR(IF(Cashflow!D$64=0,"",((Cashflow!D$72+Cashflow!D$73)-Cashflow!D$39)/Cashflow!D$64),"") | D13: =IFERROR(IF(Cashflow!E$64=0,"",((Cashflow!E$72+Cashflow!E$73)-Cashflow!E$39)/Cashflow!E$64),"") | E13: =IFERROR(IF(Cashflow!F$64=0,"",((Cashflow!F$72+Cashflow!F$73)-Cashflow!F$39)/Cashflow!F$64),"") | F13: =IFERROR(IF(Cashflow!G$64=0,"",((Cashflow!G$72+Cashflow!G$73)-Cashflow!G$39)/Cashflow!G$64),"") -> 1.2378396 | G13: =IFERROR(IF(Cashflow!H$64=0,"",((Cashflow!H$72+Cashflow!H$73)-Cashflow!H$39)/Cashflow!H$64),"") -> 1.0850957 | H13: =IFERROR(IF(Cashflow!I$64=0,"",((Cashflow!I$72+Cashflow!I$73)-Cashflow!I$39)/Cashflow!I$64),"") -> 0.88629181 | I13: =IFERROR(IF(Cashflow!J$64=0,"",((Cashflow!J$72+Cashflow!J$73)-Cashflow!J$39)/Cashflow!J$64),"") -> 0.68278276 | J13: =IFERROR(IF(Cashflow!K$64=0,"",((Cashflow!K$72+Cashflow!K$73)-Cashflow!K$39)/Cashflow!K$64),"") -> 0.53597319 | ... P13: =IFERROR(IF(Cashflow!Q$64=0,"",((Cashflow!Q$72+Cashflow!Q$73)-Cashflow!Q$39)/Cashflow!Q$64),"") -> 0
A15: THE BEND LIVE HOUSE — EXECUTIVE DASHBOARD
A16: THE BEND LIVE HOUSE — EXECUTIVE DASHBOARD | P16: Active Scenario | Q16: =Scenarios!B4 -> Base
P17: Model Health | Q17: =Q3 -> #REF!
B19: FINANCIAL SUMMARY
C20: FY25 | D20: FY26 | E20: FY27 | F20: FY28 | G20: FY29 | H20: FY30 | I20: FY31 | J20: FY32 | K20: FY33 | L20: FY34 | M20: FY35 | N20: FY36 | O20: FY37 | P20: FY38
B21: Revenue | C21: ='P&L'!H28 -> 0 | D21: ='P&L'!I28 -> 0 | E21: ='P&L'!J28 -> 18772333 | F21: ='P&L'!K28 -> 19676502 | G21: ='P&L'!L28 -> 20615522 | H21: ='P&L'!M28 -> 21808635 | I21: ='P&L'!N28 -> 22300757 | J21: ='P&L'!O28 -> 22807316 | ... M21: ='P&L'!R28 -> 24417930 | N21: ='P&L'!R28 -> 24417930 | O21: ='P&L'!S28 -> 24986615 | P21: ='P&L'!T28 -> 25571992
B22: EBITDA | C22: ='P&L'!H79 -> 0 | D22: ='P&L'!I79 -> 0 | E22: ='P&L'!J79 -> 10240353 | F22: ='P&L'!K79 -> 10221611 | G22: ='P&L'!L79 -> 10726643 | H22: ='P&L'!M79 -> 11603174 | I22: ='P&L'!N79 -> 11825139 | J22: ='P&L'!O79 -> 11488417 | ... M22: ='P&L'!R79 -> 12008307 | N22: ='P&L'!R79 -> 12008307 | O22: ='P&L'!S79 -> 12146815 | P22: ='P&L'!T79 -> 13901343
B23: Closing Cash | C23: ='Balance Sheet'!G10 -> 0 | D23: ='Balance Sheet'!H10 -> 452228.4 | E23: ='Balance Sheet'!I10 -> 1724785.6 | F23: ='Balance Sheet'!J10 -> 2184190 | G23: ='Balance Sheet'!K10 -> 2729888 | H23: ='Balance Sheet'!L10 -> 3408439 | I23: ='Balance Sheet'!M10 -> 4135811.4 | J23: ='Balance Sheet'!N10 -> 4833789 | ... M23: ='Balance Sheet'!Q10 -> 7159432.3 | N23: ='Balance Sheet'!Q10 -> 7159432.3 | O23: ='Balance Sheet'!R10 -> 9596186.9 | P23: ='Balance Sheet'!S10 -> 12278575
B24: Total Debt | C24: =Debt!I24+Debt!I43 -> 0 | D24: =Debt!J24+Debt!J43 -> 12675915 | E24: =Debt!K24+Debt!K43 -> 12675915 | F24: =Debt!L24+Debt!L43 -> 11091426 | G24: =Debt!M24+Debt!M43 -> 9506936.2 | H24: =Debt!N24+Debt!N43 -> 7922446.9 | I24: =Debt!O24+Debt!O43 -> 6337957.5 | J24: =Debt!P24+Debt!P43 -> 4753468.1 | ... M24: =Debt!S24+Debt!S43 -> 0 | N24: =Debt!S24+Debt!S43 -> 0 | O24: =Debt!T24+Debt!T43 -> 0 | P24: =Debt!U24+Debt!U43 -> 0
B27: DEBT & LEVERAGE | F27: EVENT DAYS MIX (STABILIZED FY) | I27: EVENT INDUSTRY KPIs (STABILIZED FY)
B28: Metric | C28: Value | F28: Event Type | G28: Days | I28: Metric | J28: Value | K28: Units
B29: Total Debt Facility | C29: =Inputs!E66 -> 11856915 | F29: Music GA (all tiers) | G29: {=IFERROR((INDEX('Calendar Assumptions'!$F$5:$P$5,MATCH(Valuations!C128,'Calendar Assumptions'!$F$4:$P$4,0))+INDEX('Calendar Assumptions'!$F$6:$P$6,MATCH(Valuations!C128,'Calendar Assumptions'!$F$4:$P$4,0))+INDEX('Calendar Assumptions'!$F$7:$P$7,MATCH(Valuations!C128,'Calendar Assumptions'!$F$4:$P$4,0))),0)} -> 48.516 | I29: Annual Event Days | J29: ='Calendar Assumptions'!H16 -> 162.342 | K29: days
B30: Bank Debt | C30: =Inputs!E66 -> 11856915 | F30: EDM | G30: {=IFERROR(INDEX('Calendar Assumptions'!$F$8:$P$8, MATCH(Valuations!C128,'Calendar Assumptions'!$F$4:$P$4,0)),0)} -> 16.794 | I30: Total Revenue | J30: ='P&L'!L28 -> 20615522 | K30: A$
B31: PE Equity | C31: =Inputs!E118+Inputs!E114 -> 8970383.1 | F31: Seated Music | G31: {=IFERROR(INDEX('Calendar Assumptions'!$F$9:$P$9, MATCH(Valuations!C128,'Calendar Assumptions'!$F$4:$P$4,0)),0)} -> 13.995 | I31: Revenue per Event Day | J31: =J30/J29 -> 126988.22 | K31: A$/day
B32: Bank Term (years) | C32: =Inputs!E64 -> 10 | F32: Comedy | G32: {=IFERROR(INDEX('Calendar Assumptions'!$F$10:$P$10, MATCH(Valuations!C128,'Calendar Assumptions'!$F$4:$P$4,0)),0)} -> 13.995 | I32: EBITDA per Event Day | J32: ='P&L'!L79/J29 -> 66074.358 | K32: A$/day
B33: PE Equity Injection Year | C33: =Inputs!E131 -> FY27 | F33: THE BEND LIVE HOUSE — EXECUTIVE DASHBOARD | G33: {=IFERROR(INDEX('Calendar Assumptions'!$F$11:$P$11, MATCH(Valuations!C128,'Calendar Assumptions'!$F$4:$P$4,0)),0)} -> 2.799 | I33: Yield on Cost | J33: =Valuations!C130 -> 0.54280444 | K33: %
B34: Bank Interest Rate | C34: =Inputs!E63 -> 0.08 | F34: MICE | G34: {=IFERROR(INDEX('Calendar Assumptions'!$F$12:$P$12, MATCH(Valuations!C128,'Calendar Assumptions'!$F$4:$P$4,0)),0)} -> 27.057
B35: Shareholder Loan Toggle | C35: =IF(Inputs!E133=0,"OFF","ON") -> OFF | F35: Community | G35: {=IFERROR(INDEX('Calendar Assumptions'!$F$13:$P$13, MATCH(Valuations!C128,'Calendar Assumptions'!$F$4:$P$4,0)),0)} -> 11.196
B36: Debt/Total Capex | C36: =(Inputs!E66+Inputs!E75)/Inputs!E159 -> 0.6 | F36: Live Site | G36: {=IFERROR(INDEX('Calendar Assumptions'!$F$14:$P$14, MATCH(Valuations!C128,'Calendar Assumptions'!$F$4:$P$4,0)),0)} -> 3.732
B39: VALUATION SUMMARY | F39: PROFITABILITY METRICS (EXIT FY) | I39: KEY INVESTMENT METRICS | J39: Value | L39: REVENUE MIX (EXIT FY) | O39: DEBT & LEVERAGE
B40: Metric | C40: Value | D40: Notes | F40: Metric | G40: Value | I40: Metric | J40: Value | L40: Stream | M40: Value | O40: Metric | P40: Value
B41: WACC | C41: =Valuations!C9 -> 0.1 | D41: Discount rate | F41: Total Revenue | G41: ='P&L'!L28 -> 20615522 | I41: Total Capex | J41: =Inputs!E159 -> 19761525 | L41: VHA | M41: {=IFERROR(INDEX('P&L'!$G$14:$T$14, MATCH(Inputs!$E$488,'P&L'!$G$6:$T$6,0)),0)} -> 7723631.2 | O41: Total Debt Facility | P41: =Debt!C5+Debt!D5 -> 12675915
B42: Exit Multiple | C42: =Valuations!C15 -> 7 | D42: EBITDA multiple | F42: Gross Profit | G42: ='P&L'!L40 -> 18125573 | I42: Equity Required | J42: =SUM(Cashflow!D13:O14) -> 8970383.1 | L42: Premium Sales | M42: {=IFERROR(INDEX('P&L'!$G$15:$T$15, MATCH(Inputs!$E$488,'P&L'!$G$6:$T$6,0)),0)} -> 1084742.1 | O42: Bank Debt | P42: =Debt!C5 -> 12675915
B43: Exit EBITDA | C43: =Valuations!C72 -> 13901343 | D43: FY38 EBITDA | F43: Gross Margin % | G43: ='P&L'!L41 -> 0.87921971 | I43: Total Debt | J43: =Debt!C5+Debt!D5 -> 12675915 | L43: Premium F&B | M43: {=IFERROR(INDEX('P&L'!$G$16:$T$16, MATCH(Inputs!$E$488,'P&L'!$G$6:$T$6,0)),0)} -> 182520 | O43: PE Loan | P43: =Debt!D5 -> 0
B44: Terminal Value | C44: =Valuations!C74 -> 97309399 | D44: Exit value | F44: EBITDA | G44: ='P&L'!L79 -> 10726643 | I44: Debt/Equity Ratio | J44: =J43/J42 -> 1.4130851 | L44: F&B | M44: {=IFERROR(INDEX('P&L'!$G$17:$T$17, MATCH(Inputs!$E$488,'P&L'!$G$6:$T$6,0)),0)} -> 8690093.4 | O44: Bank Term (years) | P44: =Debt!C6 -> 10
B45: Enterprise Value | C45: =Valuations!C91 -> 62301607 | D45: DCF valuation | F45: EBITDA Margin % | G45: ='P&L'!L80 -> 0.52031879 | I45: Project IRR | J45: =Valuations!C109 -> 0.24794587 | L45: Merchandise | M45: {=IFERROR(INDEX('P&L'!$G$18:$T$18, MATCH(Inputs!$E$488,'P&L'!$G$6:$T$6,0)),0)} -> 832800 | O45: PE Term (years) | P45: =Debt!D6 -> 10
B46: Net Debt (Exit) | C46: =Valuations!C93+Valuations!C94 -> -12223687 | D46: Debt - Cash at exit | F46: NPAT | G46: ='P&L'!L95 -> 6240242.9 | I46: Equity IRR | J46: =Valuations!C123 -> 0.33284791 | L46: Equipment Hire | M46: {=IFERROR(INDEX('P&L'!$G$20:$T$20, MATCH(Inputs!$E$488,'P&L'!$G$6:$T$6,0)),0)} -> 2610000 | O46: Bank Interest Rate | P46: =Debt!C7 -> 0.08
B47: Equity Value | C47: =Valuations!C23 -> 50077920 | D47: EV less Net Debt | F47: Net Margin % | G47: =IF(G41=0,0,G46/G41) -> 0.30269634 | I47: MOIC | J47: =Valuations!C127 -> 17.693182 | L47: Sponsorship | M47: {=IFERROR(INDEX('P&L'!$G$24:$T$24, MATCH(Inputs!$E$488,'P&L'!$G$6:$T$6,0)),0)} -> 2368156.4 | O47: PE Interest Rate | P47: =Debt!D7 -> 0.12
I48: Payback Period | J48: FY30 | L48: Advertising | M48: {=IFERROR(INDEX('P&L'!$G$25:$T$25, MATCH(Inputs!$E$488,'P&L'!$G$6:$T$6,0)),0)} -> 736048.61 | O48: Debt Payoff Year | P48: FY32
O49: Debt/Total Capex | P49: =P41/Inputs!E159 -> 0.64144417
B50: RETURN METRICS | F50: KEY INVESTMENT METRICS | I50: PROFITABILITY METRICS (EXIT FY) | L50: EVENT DAYS MIX (EXIT FY) | O50: VENUE CAPACITY
B51: Metric | C51: Value | D51: Description | F51: Metric | G51: Value | I51: Metric | J51: Value | L51: Event Type | M51: Days | O51: Configuration | P51: Capacity
B52: Project IRR | C52: =Valuations!C20 -> 0.24794587 | D52: Unlevered return | F52: Total Funding Requirement | G52: =Inputs!E60 -> 22496298 | I52: Total Revenue | J52: ='P&L'!T28 -> 25571992 | L52: Music GA (all tiers) | M52: {=IFERROR((INDEX('Calendar Assumptions'!$F$5:$P$5,MATCH(Inputs!$E$488,'Calendar Assumptions'!$F$4:$P$4,0))+INDEX('Calendar Assumptions'!$F$6:$P$6,MATCH(Inputs!$E$488,'Calendar Assumptions'!$F$4:$P$4,0))+INDEX('Calendar Assumptions'!$F$7:$P$7,MATCH(Inputs!$E$488,'Calendar Assumptions'!$F$4:$P$4,0))),0)} -> 52 | O52: Music GA (Large) | P52: ='Revenue Assumptions'!D5 -> 5000
B53: Equity IRR | C53: =Valuations!C22 -> 0.33284791 | D53: Levered return | F53: Total Equity | G53: =Inputs!E120 -> 8970383.1 | I53: Gross Profit | J53: ='P&L'!T40 -> 22466577 | L53: EDM | M53: {=IFERROR(INDEX('Calendar Assumptions'!$F$8:$P$8, MATCH(Inputs!$E$488,'Calendar Assumptions'!$F$4:$P$4,0)),0)} -> 18 | O53: Music GA (Medium) | P53: ='Revenue Assumptions'!D6 -> 3000
B54: Project NPV @ WACC | C54: =Valuations!C21 -> 62301607 | D54: Value creation | F54: Total Debt | G54: =Inputs!E53-Inputs!E51 -> 12675915 | I54: Gross Margin % | J54: ='P&L'!T41 -> 0.87856188 | L54: Seated Music | M54: {=IFERROR(INDEX('Calendar Assumptions'!$F$9:$P$9, MATCH(Inputs!$E$488,'Calendar Assumptions'!$F$4:$P$4,0)),0)} -> 15 | O54: Music GA (Small) | P54: ='Revenue Assumptions'!D7 -> 1500
B55: Equity NPV @ Ke | C55: =Valuations!C23 -> 50077920 | D55: Value to equity | F55: Debt/Equity Ratio | G55: =IF(Inputs!E120>0,Inputs!E66/Inputs!E120,0) -> 1.3217847 | I55: EBITDA | J55: ='P&L'!T79 -> 13901343 | L55: Comedy | M55: {=IFERROR(INDEX('Calendar Assumptions'!$F$10:$P$10, MATCH(Inputs!$E$488,'Calendar Assumptions'!$F$4:$P$4,0)),0)} -> 15 | O55: EDM/Dance | P55: ='Revenue Assumptions'!D8 -> 3500
B56: MOIC | C56: =Valuations!C24 -> 17.693182 | D56: Cash multiple | F56: Project IRR | G56: =Valuations!C20 -> 0.24794587 | I56: EBITDA Margin % | J56: ='P&L'!T80 -> 0.54361595 | L56: THE BEND LIVE HOUSE — EXECUTIVE DASHBOARD | M56: {=IFERROR(INDEX('Calendar Assumptions'!$F$11:$P$11, MATCH(Inputs!$E$488,'Calendar Assumptions'!$F$4:$P$4,0)),0)} -> 3 | O56: Seated Events | P56: ='Revenue Assumptions'!D9 -> 3500
B57: Yield on Cost | C57: =Valuations!C26 -> 0.70345496 | D57: Stabilised EBITDA / Capex | F57: Equity IRR | G57: =Valuations!C22 -> 0.33284791 | I57: NPAT | J57: ='P&L'!T95 -> 9039286.5 | L57: MICE | M57: {=IFERROR(INDEX('Calendar Assumptions'!$F$12:$P$12, MATCH(Inputs!$E$488,'Calendar Assumptions'!$F$4:$P$4,0)),0)} -> 29 | O57: MICE/Corporate | P57: ='Revenue Assumptions'!D12 -> 3500
F58: MOIC | G58: =Valuations!C24 -> 17.693182 | I58: Net Margin % | J58: =IF(J52=0,0,J57/J52) -> 0.35348387 | L58: Community | M58: {=IFERROR(INDEX('Calendar Assumptions'!$F$13:$P$13, MATCH(Inputs!$E$488,'Calendar Assumptions'!$F$4:$P$4,0)),0)} -> 12 | O58: Community | P58: ='Revenue Assumptions'!D13 -> 2000
F59: Payback Period | G59: =Valuations!C25 -> FY30 | L59: Live Site | M59: {=IFERROR(INDEX('Calendar Assumptions'!$F$14:$P$14, MATCH(Inputs!$E$488,'Calendar Assumptions'!$F$4:$P$4,0)),0)} -> 4 | O59: Max Capacity | P59: 6000
B63: PROJECT TIMELINE | F63: SENSITIVITY SUMMARY
B64: Milestone | C64: Date | F64: Enterprise Value Sensitivity (WACC vs Exit Multiple)
B65: Model Start | C65: =Inputs!E9 -> 46054 | F65: EV ($m) | G65: 6.0x | H65: 7.0x | I65: 8.0x | J65: 9.0x | K65: 10.0x
B66: Lease Signing | C66: =Inputs!E14 -> 46357 | F66: 0.08 | G66: =Valuations!$C$72*6/(1+0.08)^10 -> 38634068 | H66: =Valuations!$C$72*7/(1+0.08)^10 -> 45073080 | I66: =Valuations!$C$72*8/(1+0.08)^10 -> 51512091 | J66: =Valuations!$C$72*9/(1+0.08)^10 -> 57951103 | K66: =Valuations!$C$72*10/(1+0.08)^10 -> 64390114
B67: Construction Start | C67: =Inputs!E18 -> 46420 | F67: 0.09 | G67: =Valuations!$C$72*6/(1+0.09)^10 -> 35232464 | H67: =Valuations!$C$72*7/(1+0.09)^10 -> 41104542 | I67: =Valuations!$C$72*8/(1+0.09)^10 -> 46976619 | J67: =Valuations!$C$72*9/(1+0.09)^10 -> 52848696 | K67: =Valuations!$C$72*10/(1+0.09)^10 -> 58720774
B68: Construction End | C68: =Inputs!E19 -> 46568 | F68: 0.1 | G68: =Valuations!$C$72*6/(1+0.1)^10 -> 32157416 | H68: =Valuations!$C$72*7/(1+0.1)^10 -> 37516986 | I68: =Valuations!$C$72*8/(1+0.1)^10 -> 42876555 | J68: =Valuations!$C$72*9/(1+0.1)^10 -> 48236124 | K68: =Valuations!$C$72*10/(1+0.1)^10 -> 53595694
B69: Operations Start | C69: =Inputs!E22 -> 46569 | F69: 0.11 | G69: =Valuations!$C$72*6/(1+0.11)^10 -> 29375023 | H69: =Valuations!$C$72*7/(1+0.11)^10 -> 34270860 | I69: =Valuations!$C$72*8/(1+0.11)^10 -> 39166697 | J69: =Valuations!$C$72*9/(1+0.11)^10 -> 44062534 | K69: =Valuations!$C$72*10/(1+0.11)^10 -> 48958371
B70: Model End | C70: =Inputs!E10 -> 50526 | F70: 0.12 | G70: =Valuations!$C$72*6/(1+0.12)^10 -> 26855162 | H70: =Valuations!$C$72*7/(1+0.12)^10 -> 31331022 | I70: =Valuations!$C$72*8/(1+0.12)^10 -> 35806882 | J70: =Valuations!$C$72*9/(1+0.12)^10 -> 40282743 | K70: =Valuations!$C$72*10/(1+0.12)^10 -> 44758603
B71: Exit Year | C71: =Valuations!C13 -> FY38
B72: Project Duration | C72: ="12 years" -> 12 years
F73: DEBT COVERAGE RATIOS | I73: EVENT INDUSTRY KPIs (EXIT FY)
B74: OPEX MIX (EXIT FY) | F74: Metric | G74: Value | I74: Metric | J74: Value | K74: Units
B75: Category | C75: Value | F75: Average DSCR | G75: =AVERAGE(Cashflow!G67:O67) -> 4.0738366 | I75: Annual Event Days | J75: ='Calendar Assumptions'!P16 -> 174 | K75: days
B76: Staff Costs | C76: {=IFERROR(INDEX('P&L'!$G$67:$T$67, MATCH(Inputs!$E$488,'P&L'!$G$6:$T$6,0)),0)} -> 2497512.1 | F76: Minimum DSCR | G76: =MIN(Cashflow!G67:O67) -> 3.0466904 | I76: Total Revenue | J76: ='P&L'!T28 -> 25571992 | K76: A$
B77: Lease / Rent | C77: {=IFERROR(INDEX('P&L'!$G$45:$T$45, MATCH(Inputs!$E$488,'P&L'!$G$6:$T$6,0)),0)} -> 956218.63 | F77: Average ICR | G77: =AVERAGE('P&L'!J79/'P&L'!J87,'P&L'!K79/'P&L'!K87,'P&L'!L79/'P&L'!L87,'P&L'!M79/'P&L'!M87) -> 12.541136 | I77: Revenue per Event Day | J77: =J76/J75 -> 146965.47 | K77: A$/day
B78: Utilities | C78: {=IFERROR(INDEX('P&L'!$G$46:$T$46, MATCH(Inputs!$E$488,'P&L'!$G$6:$T$6,0)),0)} -> 315820.35 | F78: Minimum ICR | G78: =MIN('P&L'!J79/'P&L'!J87,'P&L'!K79/'P&L'!K87,'P&L'!L79/'P&L'!L87,'P&L'!M79/'P&L'!M87) -> 9.7508767 | I78: EBITDA per Event Day | J78: ='P&L'!T79/J75 -> 79892.774 | K78: A$/day
B79: Maintenance | C79: 0 | I79: Yield on Cost | J79: =Valuations!C26 -> 0.70345496 | K79: %
B80: Marketing | C80: {=IFERROR(INDEX('P&L'!$G$48:$T$48, MATCH(Inputs!$E$488,'P&L'!$G$6:$T$6,0)),0)} -> 161269.97
B81: Admin/Legal/Insurance/etc | C81: {=IFERROR((INDEX('P&L'!$G$59:$T$59, MATCH(Inputs!$E$488,'P&L'!$G$6:$T$6,0))+INDEX('P&L'!$G$60:$T$60, MATCH(Inputs!$E$488,'P&L'!$G$6:$T$6,0))+INDEX('P&L'!$G$62:$T$62, MATCH(Inputs!$E$488,'P&L'!$G$6:$T$6,0))+INDEX('P&L'!$G$63:$T$63, MATCH(Inputs!$E$488,'P&L'!$G$6:$T$6,0))+INDEX('P&L'!$G$64:$T$64, MATCH(Inputs!$E$488,'P&L'!$G$6:$T$6,0))+INDEX('P&L'!$G$65:$T$65, MATCH(Inputs!$E$488,'P&L'!$G$6:$T$6,0))),0)} -> 486093.46
B82: Other OPEX | C82: 0
A120: ▲ END OF DASHBOARD ▲

Sheet Cashflow
A1: Annual Cashflow Waterfall (AUD)
A2: THE BEND Live House
C4: Currency | E4: AUD
C5: FY Start | D5: ='P&L'!G4 -> 45689 | E5: ='P&L'!H4 -> 45839 | F5: ='P&L'!I4 -> 46204 | G5: ='P&L'!J4 -> 46569 | H5: ='P&L'!K4 -> 46935 | I5: ='P&L'!L4 -> 47300 | J5: ='P&L'!M4 -> 47665 | K5: ='P&L'!N4 -> 48030 | ... Q5: ='P&L'!T4 -> 50222
C6: FY End | D6: ='P&L'!G5 -> 45838 | E6: ='P&L'!H5 -> 46203 | F6: ='P&L'!I5 -> 46568 | G6: ='P&L'!J5 -> 46934 | H6: ='P&L'!K5 -> 47299 | I6: ='P&L'!L5 -> 47664 | J6: ='P&L'!M5 -> 48029 | K6: ='P&L'!N5 -> 48395 | ... Q6: ='P&L'!T5 -> 50586
C7: Year | D7: ='P&L'!G6 -> FY25 | E7: ='P&L'!H6 -> FY26 | F7: ='P&L'!I6 -> FY27 | G7: ='P&L'!J6 -> FY28 | H7: ='P&L'!K6 -> FY29 | I7: ='P&L'!L6 -> FY30 | J7: ='P&L'!M6 -> FY31 | K7: ='P&L'!N6 -> FY32 | ... Q7: ='P&L'!T6 -> FY38
A10: Opening Cash Balance | D10: 0 | E10: =Cashflow!D38 -> 0 | F10: =E38 -> 0 | G10: =F38 -> 452228.4 | H10: =G38 -> 1724785.6 | I10: =H38 -> 2184190 | J10: =I38 -> 2729888 | K10: =J38 -> 3408439 | L10: =K38 -> 4135811.4 | M10: =L38 -> 4833789 | ... Q10: =P38 -> 9596186.9
A12: INFLOWS
A13: Initial Cash Inflow through deposits via Partnerships | D13: =IF(D7=Inputs!$E$126,Inputs!$E$114,0) -> 0 | E13: =IF(E7=Inputs!$E$126,Inputs!$E$114,0) -> 0 | F13: =IF(F7=Inputs!$E$126,Inputs!$E$114,0) -> 1500000 | G13: =IF(G7=Inputs!$E$126,Inputs!$E$114,0) -> 0 | H13: =IF(H7=Inputs!$E$126,Inputs!$E$114,0) -> 0 | I13: =IF(I7=Inputs!$E$126,Inputs!$E$114,0) -> 0 | J13: =IF(J7=Inputs!$E$126,Inputs!$E$114,0) -> 0 | K13: =IF(K7=Inputs!$E$126,Inputs!$E$114,0) -> 0 | ... Q13: =IF(Q7=Inputs!$E$126,Inputs!$E$114,0) -> 0
A14: PE Equity Inflow | D14: =IF(AND(D7=Inputs!$E$131,Inputs!$E$133=0),Inputs!$E$118,0) -> 0 | E14: =IF(AND(E7=Inputs!$E$131,Inputs!$E$133=0),Inputs!$E$118,0) -> 0 | F14: =IF(AND(F7=Inputs!$E$131,Inputs!$E$133=0),Inputs!$E$118,0) -> 7470383.1 | G14: =IF(AND(G7=Inputs!$E$131,Inputs!$E$133=0),Inputs!$E$118,0) -> 0 | H14: =IF(AND(H7=Inputs!$E$131,Inputs!$E$133=0),Inputs!$E$118,0) -> 0 | I14: =IF(AND(I7=Inputs!$E$131,Inputs!$E$133=0),Inputs!$E$118,0) -> 0 | J14: =IF(AND(J7=Inputs!$E$131,Inputs!$E$133=0),Inputs!$E$118,0) -> 0 | K14: =IF(AND(K7=Inputs!$E$131,Inputs!$E$133=0),Inputs!$E$118,0) -> 0 | ... Q14: =IF(AND(Q7=Inputs!$E$131,Inputs!$E$133=0),Inputs!$E$118,0) -> 0
A15: Additional Equity Tranches | D15: =IF(D7=Inputs!$E$128,Inputs!$E$127,0)+IF(D7=Inputs!$E$130,Inputs!$E$129,0)+IF(D7=Inputs!$E$135,Inputs!$E$134,0) -> 0 | E15: =IF(E7=Inputs!$E$128,Inputs!$E$127,0)+IF(E7=Inputs!$E$130,Inputs!$E$129,0)+IF(E7=Inputs!$E$135,Inputs!$E$134,0) -> 0 | F15: =IF(F7=Inputs!$E$128,Inputs!$E$127,0)+IF(F7=Inputs!$E$130,Inputs!$E$129,0)+IF(F7=Inputs!$E$135,Inputs!$E$134,0) -> 0 | G15: =IF(G7=Inputs!$E$128,Inputs!$E$127,0)+IF(G7=Inputs!$E$130,Inputs!$E$129,0)+IF(G7=Inputs!$E$135,Inputs!$E$134,0) -> 0 | H15: =IF(H7=Inputs!$E$128,Inputs!$E$127,0)+IF(H7=Inputs!$E$130,Inputs!$E$129,0)+IF(H7=Inputs!$E$135,Inputs!$E$134,0) -> 0 | I15: =IF(I7=Inputs!$E$128,Inputs!$E$127,0)+IF(I7=Inputs!$E$130,Inputs!$E$129,0)+IF(I7=Inputs!$E$135,Inputs!$E$134,0) -> 0 | J15: =IF(J7=Inputs!$E$128,Inputs!$E$127,0)+IF(J7=Inputs!$E$130,Inputs!$E$129,0)+IF(J7=Inputs!$E$135,Inputs!$E$134,0) -> 0 | K15: =IF(K7=Inputs!$E$128,Inputs!$E$127,0)+IF(K7=Inputs!$E$130,Inputs!$E$129,0)+IF(K7=Inputs!$E$135,Inputs!$E$134,0) -> 0 | ... Q15: =IF(Q7=Inputs!$E$128,Inputs!$E$127,0)+IF(Q7=Inputs!$E$130,Inputs!$E$129,0)+IF(Q7=Inputs!$E$135,Inputs!$E$134,0) -> 0
A16: Total Equity Inflow | D16: =D13+D14+D15 -> 0 | E16: =E13+E14+E15 -> 0 | F16: =F13+F14+F15 -> 8970383.1 | G16: =G13+G14+G15 -> 0 | H16: =H13+H14+H15 -> 0 | I16: =I13+I14+I15 -> 0 | J16: =J13+J14+J15 -> 0 | K16: =K13+K14+K15 -> 0 | ... Q16: =Q13+Q14+Q15 -> 0
A18: Debt drawdowns – Bank (from Debt) | D18: =IFERROR(Debt!H20,0) -> 0 | E18: =IFERROR(Debt!I20,0) -> 0 | F18: =IFERROR(Debt!J20,0) -> 12675915 | G18: =IFERROR(Debt!K20,0) -> 0 | H18: =IFERROR(Debt!L20,0) -> 0 | I18: =IFERROR(Debt!M20,0) -> 0 | J18: =IFERROR(Debt!N20,0) -> 0 | K18: =IFERROR(Debt!O20,0) -> 0 | ... Q18: =IFERROR(Debt!U20,0) -> 0
A19: WC Facility drawdowns (from Debt) | D19: =IFERROR(Debt!H76,0) -> 0 | E19: =IFERROR(Debt!I76,0) -> 0 | F19: =IFERROR(Debt!J76,0) -> 850000 | G19: =IFERROR(Debt!K76,0) -> 0 | H19: =IFERROR(Debt!L76,0) -> 0 | I19: =IFERROR(Debt!M76,0) -> 0 | J19: =IFERROR(Debt!N76,0) -> 0 | K19: =IFERROR(Debt!O76,0) -> 0 | ... Q19: =IFERROR(Debt!U76,0) -> 0
A20: PE Loan drawdowns – LEGACY INACTIVE | D20: =0 -> 0 | E20: =0 -> 0 | F20: =0 -> 0 | G20: =0 -> 0 | H20: =0 -> 0 | I20: =0 -> 0 | J20: =0 -> 0 | K20: =0 -> 0 | ... Q20: =0 -> 0
A21: Pre-op revenue (from Cashflow) | D21: =SUMIF(Timing!$C$6:$Q$6,D7,Timing!$C$22:$Q$22) -> 0 | E21: =SUMIF(Timing!$C$6:$Q$6,E7,Timing!$C$22:$Q$22) -> 0 | F21: =SUMIF(Timing!$C$6:$Q$6,F7,Timing!$C$22:$Q$22) -> 0 | G21: =SUMIF(Timing!$C$6:$Q$6,G7,Timing!$C$22:$Q$22) -> 0 | H21: =SUMIF(Timing!$C$6:$Q$6,H7,Timing!$C$22:$Q$22) -> 0 | I21: =SUMIF(Timing!$C$6:$Q$6,I7,Timing!$C$22:$Q$22) -> 0 | J21: =SUMIF(Timing!$C$6:$Q$6,J7,Timing!$C$22:$Q$22) -> 0 | K21: =SUMIF(Timing!$C$6:$Q$6,K7,Timing!$C$22:$Q$22) -> 0 | ... Q21: =SUMIF(Timing!$C$6:$Q$6,Q7,Timing!$C$22:$Q$22) -> 0
A22: Operational revenue (from P&L) | D22: {=IFERROR(INDEX('P&L'!$G$28:$S$28,MATCH(D$7,'P&L'!$G$6:$S$6,0)),0)} -> 0 | E22: {=IFERROR(INDEX('P&L'!$G$28:$S$28,MATCH(E$7,'P&L'!$G$6:$S$6,0)),0)} -> 0 | F22: {=IFERROR(INDEX('P&L'!$G$28:$S$28,MATCH(F$7,'P&L'!$G$6:$S$6,0)),0)} -> 0 | G22: {=IFERROR(INDEX('P&L'!$G$28:$S$28,MATCH(G$7,'P&L'!$G$6:$S$6,0)),0)} -> 18772333 | H22: {=IFERROR(INDEX('P&L'!$G$28:$S$28,MATCH(H$7,'P&L'!$G$6:$S$6,0)),0)} -> 19676502 | I22: {=IFERROR(INDEX('P&L'!$G$28:$S$28,MATCH(I$7,'P&L'!$G$6:$S$6,0)),0)} -> 20615522 | J22: {=IFERROR(INDEX('P&L'!$G$28:$S$28,MATCH(J$7,'P&L'!$G$6:$S$6,0)),0)} -> 21808635 | K22: {=IFERROR(INDEX('P&L'!$G$28:$S$28,MATCH(K$7,'P&L'!$G$6:$S$6,0)),0)} -> 22300757 | ... O22: {=IFERROR(INDEX('P&L'!$G$28:$S$28,MATCH(O$7,'P&L'!$G$6:$S$6,0)),0)} -> 24417930 | P22: {=IFERROR(INDEX('P&L'!$G$28:$T$28,MATCH(P$7,'P&L'!$G$6:$T$6,0)),0)} -> 24986615 | Q22: {=IFERROR(INDEX('P&L'!$G$28:$T$28,MATCH(Q$7,'P&L'!$G$6:$T$6,0)),0)} -> 25571992
A23: Total inflows | D23: =D16+D18+D20+D21+D22 -> 0 | E23: =E16+E18+E20+E21+E22 -> 0 | F23: =F16+F18+F20+F21+F22+F19 -> 22496298 | G23: =G16+G18+G20+G21+G22 -> 18772333 | H23: =H16+H18+H20+H21+H22 -> 19676502 | I23: =I16+I18+I20+I21+I22 -> 20615522 | J23: =J16+J18+J20+J21+J22 -> 21808635 | K23: =K16+K18+K20+K21+K22 -> 22300757 | L23: =L16+L18+L20+L21+L22 -> 22807316 | M23: =M16+M18+M20+M21+M22 -> 23328738 | N23: =N16+N18+N20+N21+N22 -> 23865459 | ... Q23: =Q16+Q18+Q20+Q21+Q22 -> 25571992
A24: Terminal value + bond return | D24: =IF(D$7=Inputs!$E$488,D64*Valuations!$C$15,0) -> 0 | E24: =IF(E$7=Inputs!$E$488,E64*Valuations!$C$15,0) -> 0 | F24: =IF(F$7=Inputs!$E$488,F64*Valuations!$C$15,0) -> 0 | G24: =IF(G$7=Inputs!$E$488,G64*Valuations!$C$15,0) -> 0 | H24: =IF(H$7=Inputs!$E$488,H64*Valuations!$C$15,0) -> 0 | I24: =IF(I$7=Inputs!$E$488,I64*Valuations!$C$15,0) -> 0 | J24: =IF(J$7=Inputs!$E$488,J64*Valuations!$C$15,0) -> 0 | K24: =IF(K$7=Inputs!$E$488,K64*Valuations!$C$15,0) -> 0 | ... Q24: =IF(Q$7=Inputs!$E$488,Q64*Valuations!$C$15,0) -> 97309399
A26: OUTFLOWS (shown as negatives)
A27: Capex (from Construction Timeline) + Lease Deposit | D27: =-'Construction Timeline'!D227 -> 0 | E27: =-'Construction Timeline'!E227 -> 0 | F27: =-'Construction Timeline'!F227-'Construction Timeline'!F219 -> -20580525 | G27: =-'Construction Timeline'!G227 -> 0 | H27: =-'Construction Timeline'!H227 -> 0 | I27: =-'Construction Timeline'!I227 -> 0 | J27: =-'Construction Timeline'!J227 -> 0 | K27: =-'Construction Timeline'!K227 -> 0 | L27: =-'Construction Timeline'!L227 -> 0 | M27: =-'Construction Timeline'!M227 -> 0 | N27: =-'Construction Timeline'!N227 -> 0 | O27: =-'Construction Timeline'!O227 -> 0 | P27: =0 -> 0 | Q27: =0 -> 0
A28: Pre-op expenses excl. capex (from Cashflow) | D28: =-SUMIF(Timing!$C$6:$Q$6,D7,Timing!$C$23:$Q$23) -> 0 | E28: =-SUMIF(Timing!$C$6:$Q$6,E7,Timing!$C$23:$Q$23) -> 0 | F28: =-SUMIF(Timing!$C$6:$Q$6,F7,Timing!$C$23:$Q$23) -> 0 | G28: =-SUMIF(Timing!$C$6:$Q$6,G7,Timing!$C$23:$Q$23) -> 0 | H28: =-SUMIF(Timing!$C$6:$Q$6,H7,Timing!$C$23:$Q$23) -> 0 | I28: =-SUMIF(Timing!$C$6:$Q$6,I7,Timing!$C$23:$Q$23) -> 0 | J28: =-SUMIF(Timing!$C$6:$Q$6,J7,Timing!$C$23:$Q$23) -> 0 | K28: =-SUMIF(Timing!$C$6:$Q$6,K7,Timing!$C$23:$Q$23) -> 0 | ... Q28: =-SUMIF(Timing!$C$6:$Q$6,Q7,Timing!$C$23:$Q$23) -> 0
A29: COGS +Operating expenses (excl lease/outgoings) + Hold Co Fees – from P&L | D29: {=IFERROR(-(INDEX('P&L'!$G$74:$R$74,MATCH(D$7,'P&L'!$G$6:$R$6,0))-INDEX('P&L'!$G$58:$R$58,MATCH(D$7,'P&L'!$G$6:$R$6,0))-INDEX('P&L'!$G$59:$R$59,MATCH(D$7,'P&L'!$G$6:$R$6,0))+INDEX('P&L'!$G$35:$R$35,MATCH(D$7,'P&L'!$G$6:$R$6,0))+INDEX('P&L'!$G$77:$R$77,MATCH(D$7,'P&L'!$G$6:$R$6,0))),0)} -> 0 | E29: {=IFERROR(-(INDEX('P&L'!$G$74:$R$74,MATCH(E$7,'P&L'!$G$6:$R$6,0))-INDEX('P&L'!$G$58:$R$58,MATCH(E$7,'P&L'!$G$6:$R$6,0))-INDEX('P&L'!$G$59:$R$59,MATCH(E$7,'P&L'!$G$6:$R$6,0))+INDEX('P&L'!$G$35:$R$35,MATCH(E$7,'P&L'!$G$6:$R$6,0))+INDEX('P&L'!$G$77:$R$77,MATCH(E$7,'P&L'!$G$6:$R$6,0))),0)} -> 0 | F29: {=IFERROR(-(INDEX('P&L'!$G$74:$R$74,MATCH(F$7,'P&L'!$G$6:$R$6,0))-INDEX('P&L'!$G$58:$R$58,MATCH(F$7,'P&L'!$G$6:$R$6,0))-INDEX('P&L'!$G$59:$R$59,MATCH(F$7,'P&L'!$G$6:$R$6,0))+INDEX('P&L'!$G$35:$R$35,MATCH(F$7,'P&L'!$G$6:$R$6,0))+INDEX('P&L'!$G$77:$R$77,MATCH(F$7,'P&L'!$G$6:$R$6,0))),0)} -> -920383.09 | G29: {=IFERROR(-(INDEX('P&L'!$G$74:$R$74,MATCH(G$7,'P&L'!$G$6:$R$6,0))-INDEX('P&L'!$G$58:$R$58,MATCH(G$7,'P&L'!$G$6:$R$6,0))-INDEX('P&L'!$G$59:$R$59,MATCH(G$7,'P&L'!$G$6:$R$6,0))+INDEX('P&L'!$G$35:$R$35,MATCH(G$7,'P&L'!$G$6:$R$6,0))+INDEX('P&L'!$G$77:$R$77,MATCH(G$7,'P&L'!$G$6:$R$6,0))),0)} -> -8531980.2 | H29: {=IFERROR(-(INDEX('P&L'!$G$74:$R$74,MATCH(H$7,'P&L'!$G$6:$R$6,0))-INDEX('P&L'!$G$58:$R$58,MATCH(H$7,'P&L'!$G$6:$R$6,0))-INDEX('P&L'!$G$59:$R$59,MATCH(H$7,'P&L'!$G$6:$R$6,0))+INDEX('P&L'!$G$35:$R$35,MATCH(H$7,'P&L'!$G$6:$R$6,0))+INDEX('P&L'!$G$77:$R$77,MATCH(H$7,'P&L'!$G$6:$R$6,0))),0)} -> -9023210.4 | I29: {=IFERROR(-(INDEX('P&L'!$G$74:$R$74,MATCH(I$7,'P&L'!$G$6:$R$6,0))-INDEX('P&L'!$G$58:$R$58,MATCH(I$7,'P&L'!$G$6:$R$6,0))-INDEX('P&L'!$G$59:$R$59,MATCH(I$7,'P&L'!$G$6:$R$6,0))+INDEX('P&L'!$G$35:$R$35,MATCH(I$7,'P&L'!$G$6:$R$6,0))+INDEX('P&L'!$G$77:$R$77,MATCH(I$7,'P&L'!$G$6:$R$6,0))),0)} -> -9402844.5 | J29: {=IFERROR(-(INDEX('P&L'!$G$74:$R$74,MATCH(J$7,'P&L'!$G$6:$R$6,0))-INDEX('P&L'!$G$58:$R$58,MATCH(J$7,'P&L'!$G$6:$R$6,0))-INDEX('P&L'!$G$59:$R$59,MATCH(J$7,'P&L'!$G$6:$R$6,0))+INDEX('P&L'!$G$35:$R$35,MATCH(J$7,'P&L'!$G$6:$R$6,0))+INDEX('P&L'!$G$77:$R$77,MATCH(J$7,'P&L'!$G$6:$R$6,0))),0)} -> -9702415.9 | K29: {=IFERROR(-(INDEX('P&L'!$G$74:$R$74,MATCH(K$7,'P&L'!$G$6:$R$6,0))-INDEX('P&L'!$G$58:$R$58,MATCH(K$7,'P&L'!$G$6:$R$6,0))-INDEX('P&L'!$G$59:$R$59,MATCH(K$7,'P&L'!$G$6:$R$6,0))+INDEX('P&L'!$G$35:$R$35,MATCH(K$7,'P&L'!$G$6:$R$6,0))+INDEX('P&L'!$G$77:$R$77,MATCH(K$7,'P&L'!$G$6:$R$6,0))),0)} -> -9954966 | ... O29: {=IFERROR(-(INDEX('P&L'!$G$74:$R$74,MATCH(O$7,'P&L'!$G$6:$R$6,0))-INDEX('P&L'!$G$58:$R$58,MATCH(O$7,'P&L'!$G$6:$R$6,0))-INDEX('P&L'!$G$59:$R$59,MATCH(O$7,'P&L'!$G$6:$R$6,0))+INDEX('P&L'!$G$35:$R$35,MATCH(O$7,'P&L'!$G$6:$R$6,0))+INDEX('P&L'!$G$77:$R$77,MATCH(O$7,'P&L'!$G$6:$R$6,0))),0)} -> -11214704 | P29: {=IFERROR(-(INDEX('P&L'!$G$74:$T$74,MATCH(P$7,'P&L'!$G$6:$T$6,0))-INDEX('P&L'!$G$58:$T$58,MATCH(P$7,'P&L'!$G$6:$T$6,0))-INDEX('P&L'!$G$59:$T$59,MATCH(P$7,'P&L'!$G$6:$T$6,0))+INDEX('P&L'!$G$35:$T$35,MATCH(P$7,'P&L'!$G$6:$T$6,0))+INDEX('P&L'!$G$77:$T$77,MATCH(P$7,'P&L'!$G$6:$T$6,0))),0)} -> -11603059 | Q29: {=IFERROR(-(INDEX('P&L'!$G$74:$T$74,MATCH(Q$7,'P&L'!$G$6:$T$6,0))-INDEX('P&L'!$G$58:$T$58,MATCH(Q$7,'P&L'!$G$6:$T$6,0))-INDEX('P&L'!$G$59:$T$59,MATCH(Q$7,'P&L'!$G$6:$T$6,0))+INDEX('P&L'!$G$35:$T$35,MATCH(Q$7,'P&L'!$G$6:$T$6,0))+INDEX('P&L'!$G$77:$T$77,MATCH(Q$7,'P&L'!$G$6:$T$6,0))),0)} -> -11139414
A30: Lease payments (venue lease + outgoings) – from P&L | D30: {=IFERROR(-(INDEX('P&L'!$G$58:$R$58,MATCH(D$7,'P&L'!$G$6:$R$6,0))+INDEX('P&L'!$G$59:$R$59,MATCH(D$7,'P&L'!$G$6:$R$6,0))),0)} -> 0 | E30: {=IFERROR(-(INDEX('P&L'!$G$58:$R$58,MATCH(E$7,'P&L'!$G$6:$R$6,0))+INDEX('P&L'!$G$59:$R$59,MATCH(E$7,'P&L'!$G$6:$R$6,0))),0)} -> 0 | F30: {=IFERROR(-(INDEX('P&L'!$G$58:$R$58,MATCH(F$7,'P&L'!$G$6:$R$6,0))+INDEX('P&L'!$G$59:$R$59,MATCH(F$7,'P&L'!$G$6:$R$6,0))),0)} -> 0 | G30: {=IFERROR(-(INDEX('P&L'!$G$58:$R$58,MATCH(G$7,'P&L'!$G$6:$R$6,0))+INDEX('P&L'!$G$59:$R$59,MATCH(G$7,'P&L'!$G$6:$R$6,0))),0)} -> 0 | H30: {=IFERROR(-(INDEX('P&L'!$G$58:$R$58,MATCH(H$7,'P&L'!$G$6:$R$6,0))+INDEX('P&L'!$G$59:$R$59,MATCH(H$7,'P&L'!$G$6:$R$6,0))),0)} -> -431681.25 | I30: {=IFERROR(-(INDEX('P&L'!$G$58:$R$58,MATCH(I$7,'P&L'!$G$6:$R$6,0))+INDEX('P&L'!$G$59:$R$59,MATCH(I$7,'P&L'!$G$6:$R$6,0))),0)} -> -486033.84 | J30: {=IFERROR(-(INDEX('P&L'!$G$58:$R$58,MATCH(J$7,'P&L'!$G$6:$R$6,0))+INDEX('P&L'!$G$59:$R$59,MATCH(J$7,'P&L'!$G$6:$R$6,0))),0)} -> -503045.03 | K30: {=IFERROR(-(INDEX('P&L'!$G$58:$R$58,MATCH(K$7,'P&L'!$G$6:$R$6,0))+INDEX('P&L'!$G$59:$R$59,MATCH(K$7,'P&L'!$G$6:$R$6,0))),0)} -> -520651.6 | ... O30: {=IFERROR(-(INDEX('P&L'!$G$58:$R$58,MATCH(O$7,'P&L'!$G$6:$R$6,0))+INDEX('P&L'!$G$59:$R$59,MATCH(O$7,'P&L'!$G$6:$R$6,0))),0)} -> -1194919.4 | P30: {=IFERROR(-(INDEX('P&L'!$G$58:$T$58,MATCH(P$7,'P&L'!$G$6:$T$6,0))+INDEX('P&L'!$G$59:$T$59,MATCH(P$7,'P&L'!$G$6:$T$6,0))),0)} -> -1236741.6 | Q30: {=IFERROR(-(INDEX('P&L'!$G$58:$T$58,MATCH(Q$7,'P&L'!$G$6:$T$6,0))+INDEX('P&L'!$G$59:$T$59,MATCH(Q$7,'P&L'!$G$6:$T$6,0))),0)} -> -531234.67
A31: Debt service (principal + interest) – cash (from Debt) | D31: {=IFERROR(-INDEX(Debt!$H$120:$S$120,MATCH(D$7,Debt!$H$14:$S$14,0))+IF(D$5<Inputs!$E$22,INDEX(Debt!$H$119:$S$119,MATCH(D$7,Debt!$H$14:$S$14,0)),0),0)} -> 0 | E31: {=IFERROR(-INDEX(Debt!$H$120:$S$120,MATCH(E$7,Debt!$H$14:$S$14,0))+IF(E$5<Inputs!$E$22,INDEX(Debt!$H$119:$S$119,MATCH(E$7,Debt!$H$14:$S$14,0)),0),0)} -> 0 | F31: =-Debt!J120 -> -543161.6 | G31: {=IFERROR(-INDEX(Debt!$H$120:$S$120,MATCH(G$7,Debt!$H$14:$S$14,0))+IF(G$5<Inputs!$E$22,INDEX(Debt!$H$119:$S$119,MATCH(G$7,Debt!$H$14:$S$14,0)),0),0)} -> -1900198.2 | H31: {=IFERROR(-INDEX(Debt!$H$120:$S$120,MATCH(H$7,Debt!$H$14:$S$14,0))+IF(H$5<Inputs!$E$22,INDEX(Debt!$H$119:$S$119,MATCH(H$7,Debt!$H$14:$S$14,0)),0),0)} -> -2535183 | I31: {=IFERROR(-INDEX(Debt!$H$120:$S$120,MATCH(I$7,Debt!$H$14:$S$14,0))+IF(I$5<Inputs!$E$22,INDEX(Debt!$H$119:$S$119,MATCH(I$7,Debt!$H$14:$S$14,0)),0),0)} -> -2408423.9 | J31: {=IFERROR(-INDEX(Debt!$H$120:$S$120,MATCH(J$7,Debt!$H$14:$S$14,0))+IF(J$5<Inputs!$E$22,INDEX(Debt!$H$119:$S$119,MATCH(J$7,Debt!$H$14:$S$14,0)),0),0)} -> -2281664.7 | K31: {=IFERROR(-INDEX(Debt!$H$120:$S$120,MATCH(K$7,Debt!$H$14:$S$14,0))+IF(K$5<Inputs!$E$22,INDEX(Debt!$H$119:$S$119,MATCH(K$7,Debt!$H$14:$S$14,0)),0),0)} -> -2154905.5 | L31: {=IFERROR(-INDEX(Debt!$H$120:$S$120,MATCH(L$7,Debt!$H$14:$S$14,0))+IF(L$5<Inputs!$E$22,INDEX(Debt!$H$119:$S$119,MATCH(L$7,Debt!$H$14:$S$14,0)),0),0)} -> -2028146.4 | M31: {=IFERROR(-INDEX(Debt!$H$120:$S$120,MATCH(M$7,Debt!$H$14:$S$14,0))+IF(M$5<Inputs!$E$22,INDEX(Debt!$H$119:$S$119,MATCH(M$7,Debt!$H$14:$S$14,0)),0),0)} -> -1901387.2 | N31: {=IFERROR(-INDEX(Debt!$H$120:$S$120,MATCH(N$7,Debt!$H$14:$S$14,0))+IF(N$5<Inputs!$E$22,INDEX(Debt!$H$119:$S$119,MATCH(N$7,Debt!$H$14:$S$14,0)),0),0)} -> -1774628.1 | O31: {=IFERROR(-INDEX(Debt!$H$120:$S$120,MATCH(O$7,Debt!$H$14:$S$14,0))+IF(O$5<Inputs!$E$22,INDEX(Debt!$H$119:$S$119,MATCH(O$7,Debt!$H$14:$S$14,0)),0),0)} -> -1647868.9 | P31: {=IFERROR(-INDEX(Debt!$H$120:$U$120,MATCH(P$7,Debt!$H$14:$U$14,0))+IF(P$5<Inputs!$E$22,INDEX(Debt!$H$119:$U$119,MATCH(P$7,Debt!$H$14:$U$14,0)),0),0)} -> 0 | Q31: {=IFERROR(-INDEX(Debt!$H$120:$U$120,MATCH(Q$7,Debt!$H$14:$U$14,0))+IF(Q$5<Inputs!$E$22,INDEX(Debt!$H$119:$U$119,MATCH(Q$7,Debt!$H$14:$U$14,0)),0),0)} -> 0
A32: Taxes (from P&L if modelled) | D32: {=-INDEX('P&L'!$G$91:$R$91,MATCH(D$7,'P&L'!$G$6:$R$6,0))} -> 0 | E32: {=-INDEX('P&L'!$G$91:$R$91,MATCH(E$7,'P&L'!$G$6:$R$6,0))} -> 0 | F32: {=-INDEX('P&L'!$G$91:$R$91,MATCH(F$7,'P&L'!$G$6:$R$6,0))} -> 0 | G32: {=-INDEX('P&L'!$G$91:$R$91,MATCH(G$7,'P&L'!$G$6:$R$6,0))} -> -2021560.2 | H32: {=-INDEX('P&L'!$G$91:$R$91,MATCH(H$7,'P&L'!$G$6:$R$6,0))} -> -2484852.2 | I32: {=-INDEX('P&L'!$G$91:$R$91,MATCH(I$7,'P&L'!$G$6:$R$6,0))} -> -2674389.8 | J32: {=-INDEX('P&L'!$G$91:$R$91,MATCH(J$7,'P&L'!$G$6:$R$6,0))} -> -2975376.6 | K32: {=-INDEX('P&L'!$G$91:$R$91,MATCH(K$7,'P&L'!$G$6:$R$6,0))} -> -3079994 | ... O32: {=-INDEX('P&L'!$G$91:$R$91,MATCH(O$7,'P&L'!$G$6:$R$6,0))} -> -3287055.3 | P32: {=-INDEX('P&L'!$G$91:$T$91,MATCH(P$7,'P&L'!$G$6:$T$6,0))} -> -3347621.5 | Q32: {=-INDEX('P&L'!$G$91:$T$91,MATCH(Q$7,'P&L'!$G$6:$T$6,0))} -> -3873979.9
A33: Dividends | D33: {=-INDEX('P&L'!$G$104:$R$104,MATCH(D$7,'P&L'!$G$6:$R$6,0))} -> 0 | E33: {=-INDEX('P&L'!$G$105:$T$105,MATCH(E$7,'P&L'!$G$6:$T$6,0))} -> 0 | F33: {=-INDEX('P&L'!$G$105:$T$105,MATCH(F$7,'P&L'!$G$6:$T$6,0))} -> 0 | G33: {=-INDEX('P&L'!$G$105:$T$105,MATCH(G$7,'P&L'!$G$6:$T$6,0))} -> -3847688.2 | H33: {=-INDEX('P&L'!$G$105:$T$105,MATCH(H$7,'P&L'!$G$6:$T$6,0))} -> -4625550.2 | I33: {=-INDEX('P&L'!$G$105:$T$105,MATCH(I$7,'P&L'!$G$6:$T$6,0))} -> -4933391.9 | J33: {=-INDEX('P&L'!$G$105:$T$105,MATCH(J$7,'P&L'!$G$6:$T$6,0))} -> -5478014.2 | K33: {=-INDEX('P&L'!$G$105:$T$105,MATCH(K$7,'P&L'!$G$6:$T$6,0))} -> -5724980.5 | L33: {=-INDEX('P&L'!$G$105:$T$105,MATCH(L$7,'P&L'!$G$6:$T$6,0))} -> -5653138 | ... Q33: {=-INDEX('P&L'!$G$105:$T$105,MATCH(Q$7,'P&L'!$G$6:$T$6,0))} -> -7152677.1
A34: Transfer to Community Fund (Restricted Cash) | D34: {=IFERROR(-INDEX('P&L'!$G$102:$R$102,MATCH(D$7,'P&L'!$G$6:$R$6,0)),0)} -> 0 | E34: {=IFERROR(-INDEX('P&L'!$G$102:$R$102,MATCH(E$7,'P&L'!$G$6:$R$6,0)),0)} -> 0 | F34: {=IFERROR(-INDEX('P&L'!$G$102:$R$102,MATCH(F$7,'P&L'!$G$6:$R$6,0)),0)} -> 0 | G34: {=IFERROR(-INDEX('P&L'!$G$102:$R$102,MATCH(G$7,'P&L'!$G$6:$R$6,0)),0)} -> -101622.77 | H34: {=IFERROR(-INDEX('P&L'!$G$102:$R$102,MATCH(H$7,'P&L'!$G$6:$R$6,0)),0)} -> -103780.13 | I34: {=IFERROR(-INDEX('P&L'!$G$102:$R$102,MATCH(I$7,'P&L'!$G$6:$R$6,0)),0)} -> -105937.49 | J34: {=IFERROR(-INDEX('P&L'!$G$102:$R$102,MATCH(J$7,'P&L'!$G$6:$R$6,0)),0)} -> -113545 | K34: {=IFERROR(-INDEX('P&L'!$G$102:$R$102,MATCH(K$7,'P&L'!$G$6:$R$6,0)),0)} -> -113545 | ... O34: {=IFERROR(-INDEX('P&L'!$G$102:$R$102,MATCH(O$7,'P&L'!$G$6:$R$6,0)),0)} -> -113545 | P34: {=IFERROR(-INDEX('P&L'!$G$102:$T$102,MATCH(P$7,'P&L'!$G$6:$T$6,0)),0)} -> -113545 | Q34: {=IFERROR(-INDEX('P&L'!$G$102:$T$102,MATCH(Q$7,'P&L'!$G$6:$T$6,0)),0)} -> -113545
A35: Total outflows | D35: =D27+D28+D29+D30+D31+D32+D33+D34 -> 0 | E35: =E27+E28+E29+E30+E31+E32+E33+E34 -> 0 | F35: =F27+F28+F29+F30+F31+F32+F33+F34 -> -22044070 | G35: =G27+G28+G29+G30+G31+G32+G33+G34 -> -16403050 | H35: =H27+H28+H29+H30+H31+H32+H33+H34 -> -19204257 | I35: =I27+I28+I29+I30+I31+I32+I33+I34 -> -20011021 | J35: =J27+J28+J29+J30+J31+J32+J33+J34 -> -21054061 | K35: =K27+K28+K29+K30+K31+K32+K33+K34 -> -21549043 | ... Q35: =Q27+Q28+Q29+Q30+Q31+Q32+Q33+Q34 -> -22810851
A36: Net working capital movement (ΔWC) | D36: =D61 -> 0 | E36: =E61 -> 0 | F36: =F61 -> 0 | G36: =G61 -> -1096726.6 | H36: =H61 -> -12840.594 | I36: =I61 -> -58802.416 | J36: =J61 -> -76022.193 | K36: =K61 -> -24341.653 | ... Q36: =Q61 -> -78752.097
A37: Net Cash Flow | D37: =D23+D35+D36 -> 0 | E37: =E23+E35+E36 -> 0 | F37: =F23+F35+F36 -> 452228.4 | G37: =G23+G35+G36 -> 1272557.2 | H37: =H23+H35+H36 -> 459404.45 | I37: =I23+I35+I36 -> 545697.98 | J37: =J23+J35+J36 -> 678550.96 | K37: =K23+K35+K36 -> 727372.41 | ... Q37: =Q23+Q35+Q36 -> 2682388.6
A38: Closing Cash Balance | D38: =D10+D37 -> 0 | E38: =E10+E37 -> 0 | F38: =F10+F37 -> 452228.4 | G38: =G10+G37 -> 1724785.6 | H38: =H10+H37 -> 2184190 | I38: =I10+I37 -> 2729888 | J38: =J10+J37 -> 3408439 | K38: =K10+K37 -> 4135811.4 | ... Q38: =Q10+Q37 -> 12278575
A39: Cash tie (CFS - BS cash) | D39: =D38-'Balance Sheet'!F10 -> 0 | E39: =E38-'Balance Sheet'!G10 -> 0 | F39: =F38-'Balance Sheet'!H10 -> 0 | G39: =G38-'Balance Sheet'!I10 -> 0 | H39: =H38-'Balance Sheet'!J10 -> 0 | I39: =I38-'Balance Sheet'!K10 -> 0 | J39: =J38-'Balance Sheet'!L10 -> 0 | K39: =K38-'Balance Sheet'!M10 -> 0 | ... Q39: =Q38-'Balance Sheet'!S10 -> 0
A40: Cash tie (Waterfall - BS cash) | D40: =D10+D37-D38 -> 0 | E40: =E10+E37-E38 -> 0 | F40: =F10+F37-F38 -> 0 | G40: =G10+G37-G38 -> 0 | H40: =H10+H37-H38 -> 0 | I40: =I10+I37-I38 -> 0 | J40: =J10+J37-J38 -> 0 | K40: =K10+K37-K38 -> 0 | ... Q40: =Q10+Q37-Q38 -> 0
A43: Year | D43: =D7 -> FY25 | E43: =E7 -> FY26 | F43: =F7 -> FY27 | G43: =G7 -> FY28 | H43: =H7 -> FY29 | I43: =I7 -> FY30 | J43: =J7 -> FY31 | K43: =K7 -> FY32 | ... Q43: =Q7 -> FY38
A44: FY Start | D44: =D5 -> 45689 | E44: =E5 -> 45839 | F44: =F5 -> 46204 | G44: =G5 -> 46569 | H44: =H5 -> 46935 | I44: =I5 -> 47300 | J44: =J5 -> 47665 | K44: =K5 -> 48030 | ... Q44: =Q5 -> 50222
A45: FY End | D45: =D6 -> 45838 | E45: =E6 -> 46203 | F45: =F6 -> 46568 | G45: =G6 -> 46934 | H45: =H6 -> 47299 | I45: =I6 -> 47664 | J45: =J6 -> 48029 | K45: =K6 -> 48395 | ... Q45: =Q6 -> 50586
A47: DRIVERS
A48: Revenue | D48: {=IFERROR(INDEX('P&L'!$G$28:$R$28,MATCH(D$7,'P&L'!$G$6:$R$6,0)),0)} -> 0 | E48: {=IFERROR(INDEX('P&L'!$G$28:$R$28,MATCH(E$7,'P&L'!$G$6:$R$6,0)),0)} -> 0 | F48: {=IFERROR(INDEX('P&L'!$G$28:$R$28,MATCH(F$7,'P&L'!$G$6:$R$6,0)),0)} -> 0 | G48: {=IFERROR(INDEX('P&L'!$G$28:$R$28,MATCH(G$7,'P&L'!$G$6:$R$6,0)),0)} -> 18772333 | H48: {=IFERROR(INDEX('P&L'!$G$28:$R$28,MATCH(H$7,'P&L'!$G$6:$R$6,0)),0)} -> 19676502 | I48: {=IFERROR(INDEX('P&L'!$G$28:$R$28,MATCH(I$7,'P&L'!$G$6:$R$6,0)),0)} -> 20615522 | J48: {=IFERROR(INDEX('P&L'!$G$28:$R$28,MATCH(J$7,'P&L'!$G$6:$R$6,0)),0)} -> 21808635 | K48: {=IFERROR(INDEX('P&L'!$G$28:$R$28,MATCH(K$7,'P&L'!$G$6:$R$6,0)),0)} -> 22300757 | ... O48: {=IFERROR(INDEX('P&L'!$G$28:$R$28,MATCH(O$7,'P&L'!$G$6:$R$6,0)),0)} -> 24417930 | P48: {=IFERROR(INDEX('P&L'!$G$28:$T$28,MATCH(P$7,'P&L'!$G$6:$T$6,0)),0)} -> 24986615 | Q48: {=IFERROR(INDEX('P&L'!$G$28:$T$28,MATCH(Q$7,'P&L'!$G$6:$T$6,0)),0)} -> 25571992
A49: COGS | D49: {=IFERROR(INDEX('P&L'!$G$35:$R$35,MATCH(D$7,'P&L'!$G$6:$R$6,0)),0)} -> 0 | E49: {=IFERROR(INDEX('P&L'!$G$35:$R$35,MATCH(E$7,'P&L'!$G$6:$R$6,0)),0)} -> 0 | F49: {=IFERROR(INDEX('P&L'!$G$35:$R$35,MATCH(F$7,'P&L'!$G$6:$R$6,0)),0)} -> 0 | G49: {=IFERROR(INDEX('P&L'!$G$35:$R$35,MATCH(G$7,'P&L'!$G$6:$R$6,0)),0)} -> 2168980.6 | H49: {=IFERROR(INDEX('P&L'!$G$35:$R$35,MATCH(H$7,'P&L'!$G$6:$R$6,0)),0)} -> 2325901.7 | I49: {=IFERROR(INDEX('P&L'!$G$35:$R$35,MATCH(I$7,'P&L'!$G$6:$R$6,0)),0)} -> 2489948.7 | J49: {=IFERROR(INDEX('P&L'!$G$35:$R$35,MATCH(J$7,'P&L'!$G$6:$R$6,0)),0)} -> 2536926.4 | K49: {=IFERROR(INDEX('P&L'!$G$35:$R$35,MATCH(K$7,'P&L'!$G$6:$R$6,0)),0)} -> 2611117.8 | ... O49: {=IFERROR(INDEX('P&L'!$G$35:$R$35,MATCH(O$7,'P&L'!$G$6:$R$6,0)),0)} -> 2930818.3 | P49: {=IFERROR(INDEX('P&L'!$G$35:$T$35,MATCH(P$7,'P&L'!$G$6:$T$6,0)),0)} -> 3016826.4 | Q49: {=IFERROR(INDEX('P&L'!$G$35:$T$35,MATCH(Q$7,'P&L'!$G$6:$T$6,0)),0)} -> 3105414.7
A50: OPEX (cash, excl dep'n) | D50: ='P&L'!G74 -> 0 | E50: ='P&L'!H74 -> 0 | F50: 0 | G50: ='P&L'!J74 -> 5428826.7 | H50: ='P&L'!K74 -> 6176768.3 | I50: ='P&L'!L74 -> 6400358.5 | J50: ='P&L'!M74 -> 6668534.5 | K50: ='P&L'!N74 -> 6864499.9 | L50: ='P&L'!O74 -> 7631363.9 | M50: ='P&L'!P74 -> 7995628.6 | N50: ='P&L'!Q74 -> 8233544 | ... Q50: ='P&L'!T74 -> 8450200.2
A52: BALANCES
A53: Accounts receivable | D53: =(D48/365)*Inputs!$E$527 -> 0 | E53: =(E48/365)*Inputs!$E$527 -> 0 | F53: =(F48/365)*Inputs!$E$527 -> 0 | G53: =(G48/365)*Inputs!$E$527 -> 1542931.5 | H53: =(H48/365)*Inputs!$E$527 -> 1617246.8 | I53: =(I48/365)*Inputs!$E$527 -> 1694426.5 | J53: =(J48/365)*Inputs!$E$527 -> 1792490.5 | K53: =(K48/365)*Inputs!$E$527 -> 1832938.9 | ... Q53: =(Q48/365)*Inputs!$E$527 -> 2101807.5
A54: Inventory | D54: =(D49/365)*Inputs!$E$529 -> 0 | E54: =(E49/365)*Inputs!$E$529 -> 0 | F54: =(F49/365)*Inputs!$E$529 -> 0 | G54: =(G49/365)*Inputs!$E$529 -> 178272.38 | H54: =(H49/365)*Inputs!$E$529 -> 191170 | I54: =(I49/365)*Inputs!$E$529 -> 204653.32 | J54: =(J49/365)*Inputs!$E$529 -> 208514.5 | K54: =(K49/365)*Inputs!$E$529 -> 214612.42 | ... Q54: =(Q49/365)*Inputs!$E$529 -> 255239.56
A55: Accounts payable | D55: =(((D49+D50)/365))*Inputs!$E$528 -> 0 | E55: =(((E49+E50)/365))*Inputs!$E$528 -> 0 | F55: =(((F49+F50)/365))*Inputs!$E$528 -> 0 | G55: =(((G49+G50)/365))*Inputs!$E$528 -> 624477.31 | H55: =(((H49+H50)/365))*Inputs!$E$528 -> 698849.59 | I55: =(((I49+I50)/365))*Inputs!$E$528 -> 730710.18 | J55: =(((J49+J50)/365))*Inputs!$E$528 -> 756613.23 | K55: =(((K49+K50)/365))*Inputs!$E$528 -> 778817.89 | ... Q55: =(((Q49+Q50)/365))*Inputs!$E$528 -> 949776.57
A57: CASHFLOW IMPACT (positive = inflow)
A58: Change in AR | D58: =-D53 -> 0 | E58: =-(E53-D53) -> 0 | F58: =-(F53-E53) -> 0 | G58: =-(G53-F53) -> -1542931.5 | H58: =-(H53-G53) -> -74315.25 | I58: =-(I53-H53) -> -77179.693 | J58: =-(J53-I53) -> -98064.055 | K58: =-(K53-J53) -> -40448.395 | L58: =-(L53-K53) -> -41635.017 | ... Q58: =-(Q53-P53) -> -48113.129
A59: Change in Inventory | D59: =-D54 -> 0 | E59: =-(E54-D54) -> 0 | F59: =-(F54-E54) -> 0 | G59: =-(G54-F54) -> -178272.38 | H59: =-(H54-G54) -> -12897.626 | I59: =-(I54-H54) -> -13483.315 | J59: =-(J54-I54) -> -3861.182 | K59: =-(K54-J54) -> -6097.9177 | L59: =-(L54-K54) -> -6280.8553 | ... Q59: =-(Q54-P54) -> -7281.2327
A60: Change in AP | D60: =D55 -> 0 | E60: =(E55-D55) -> 0 | F60: =(F55-E55) -> 0 | G60: =(G55-F55) -> 624477.31 | H60: =(H55-G55) -> 74372.282 | I60: =(I55-H55) -> 31860.591 | J60: =(J55-I55) -> 25903.045 | K60: =(K55-J55) -> 22204.659 | L60: =(L55-K55) -> 69310.774 | ... Q60: =(Q55-P55) -> -23357.736
A61: Net working capital change | D61: =SUM(D58:D60) -> 0 | E61: =SUM(E58:E60) -> 0 | F61: =SUM(F58:F60) -> 0 | G61: =SUM(G58:G60) -> -1096726.6 | H61: =SUM(H58:H60) -> -12840.594 | I61: =SUM(I58:I60) -> -58802.416 | J61: =SUM(J58:J60) -> -76022.193 | K61: =SUM(K58:K60) -> -24341.653 | ... Q61: =SUM(Q58:Q60) -> -78752.097
A63: KEY METRICS
A64: EBITDA (from P&L) | D64: =IFERROR('P&L'!G79,0) -> 0 | E64: =IFERROR('P&L'!H79,0) -> 0 | F64: =IFERROR('P&L'!I79,0) -> 0 | G64: =IFERROR('P&L'!J79,0) -> 10240353 | H64: =IFERROR('P&L'!K79,0) -> 10221611 | I64: =IFERROR('P&L'!L79,0) -> 10726643 | J64: =IFERROR('P&L'!M79,0) -> 11603174 | K64: =IFERROR('P&L'!N79,0) -> 11825139 | ... Q64: =IFERROR('P&L'!T79,0) -> 13901343
A65: Debt Service (cash) – positive | D65: =ABS(D31) -> 0 | E65: =ABS(E31) -> 0 | F65: =ABS(F31) -> 543161.6 | G65: =ABS(G31) -> 1900198.2 | H65: =ABS(H31) -> 2535183 | I65: =ABS(I31) -> 2408423.9 | J65: =ABS(J31) -> 2281664.7 | K65: =ABS(K31) -> 2154905.5 | ... Q65: =ABS(Q31) -> 0
A66: Capex | G66: =G27 -> 0 | H66: =H27 -> 0 | I66: =I27 -> 0 | J66: =J27 -> 0 | K66: =K27 -> 0 | L66: =L27 -> 0 | M66: =M27 -> 0 | N66: =N27 -> 0 | ... Q66: =Q27 -> 0
A67: DSCR = CFADS / Debt Service | D67: =IF(OR(D65=0,D64=0),"",(D64+D32+D36)/D65) | E67: =IF(OR(E65=0,E64=0),"",(E64+E32+E36)/E65) | F67: =IF(OR(F65=0,F64=0),"",(F64+F32+F36)/F65) | G67: =IF(OR(G65=0,G64=0),"",(G64+G32+G36+G66)/G65) -> 3.748065 | H67: =IF(OR(H65=0,H64=0),"",(H64+H32+H36+H66)/H65) -> 3.0466904 | I67: =IF(OR(I65=0,I64=0),"",(I64+I32+I36+I66)/I65) -> 3.3189554 | J67: =IF(OR(J65=0,J64=0),"",(J64+J32+J36+J66)/J65) -> 3.7480419 | K67: =IF(OR(K65=0,K64=0),"",(K64+K32+K36+K66)/K65) -> 4.0469539 | L67: =IF(OR(L65=0,L64=0),"",(L64+L32+L36+L66)/L65) -> 4.1874724 | M67: =IF(OR(M65=0,M64=0),"",(M64+M32+M36+M66)/M65) -> 4.457472 | N67: =IF(OR(N65=0,N64=0),"",(N64+N32+N36+N66)/N65) -> 4.8337591 | ... Q67: =IF(OR(Q65=0,Q64=0),"",(Q64+Q32+Q36+Q66)/Q65)
A68: Minimum Closing Cash (FY27–FY37) | F68: =IF(F$6>=Inputs!$E$9,Inputs!$E$531,0) -> 500 | G68: =IF(G$6>=Inputs!$E$9,Inputs!$E$531,0) -> 500 | H68: =IF(H$6>=Inputs!$E$9,Inputs!$E$531,0) -> 500 | I68: =IF(I$6>=Inputs!$E$9,Inputs!$E$531,0) -> 500 | J68: =IF(J$6>=Inputs!$E$9,Inputs!$E$531,0) -> 500 | K68: =IF(K$6>=Inputs!$E$9,Inputs!$E$531,0) -> 500 | L68: =IF(L$6>=Inputs!$E$9,Inputs!$E$531,0) -> 500 | M68: =IF(M$6>=Inputs!$E$9,Inputs!$E$531,0) -> 500 | ... Q68: =IF(Q$6>=Inputs!$E$9,Inputs!$E$531,0) -> 500
A69: Funding Surplus / (Shortfall) | D69: =MAX(0,D68-D38) -> 0 | E69: =MAX(0,E68-E38) -> 0 | F69: =MAX(0,F68-F38) -> 0 | G69: =MAX(0,G68-G38) -> 0 | H69: =MAX(0,H68-H38) -> 0 | I69: =MAX(0,I68-I38) -> 0 | J69: =MAX(0,J68-J38) -> 0 | K69: =MAX(0,K68-K38) -> 0 | ... Q69: =MAX(0,Q68-Q38) -> 0
A70: Funding Status | D70: =IF(D69>0,"Shortfall",IF(D38<0,"Negative Cash","OK")) -> OK | E70: =IF(E69>0,"Shortfall",IF(E38<0,"Negative Cash","OK")) -> OK | F70: =IF(F69>0,"Shortfall",IF(F38<0,"Negative Cash","OK")) -> OK | G70: =IF(G69>0,"Shortfall",IF(G38<0,"Negative Cash","OK")) -> OK | H70: =IF(H69>0,"Shortfall",IF(H38<0,"Negative Cash","OK")) -> OK | I70: =IF(I69>0,"Shortfall",IF(I38<0,"Negative Cash","OK")) -> OK | J70: =IF(J69>0,"Shortfall",IF(J38<0,"Negative Cash","OK")) -> OK | K70: =IF(K69>0,"Shortfall",IF(K38<0,"Negative Cash","OK")) -> OK | ... Q70: =IF(Q69>0,"Shortfall",IF(Q38<0,"Negative Cash","OK")) -> OK
A72: Total current borrowings (next 12 months) | D72: =IFERROR(Debt!H49,0) -> 0 | E72: =IFERROR(Debt!I49,0) -> 0 | F72: =IFERROR(Debt!J49,0) -> 0 | G72: =IFERROR(Debt!K49,0) -> 1584489.4 | H72: =IFERROR(Debt!L49,0) -> 1584489.4 | I72: =IFERROR(Debt!M49,0) -> 1584489.4 | J72: =IFERROR(Debt!N49,0) -> 1584489.4 | K72: =IFERROR(Debt!O49,0) -> 1584489.4 | ... Q72: =IFERROR(Debt!U49,0) -> 0
A73: Total non-current borrowings | D73: =IFERROR(Debt!H50,0) -> 0 | E73: =IFERROR(Debt!I50,0) -> 0 | F73: =IFERROR(Debt!J50,0) -> 12675915 | G73: =IFERROR(Debt!K50,0) -> 11091426 | H73: =IFERROR(Debt!L50,0) -> 9506936.2 | I73: =IFERROR(Debt!M50,0) -> 7922446.9 | J73: =IFERROR(Debt!N50,0) -> 6337957.5 | K73: =IFERROR(Debt!O50,0) -> 4753468.1 | ... Q73: =IFERROR(Debt!U50,0) -> 0
A76: Unlevered FCF | D76: =D27+D64-D93+D36 -> 0 | E76: =E27+E64-E93+E36 -> 0 | F76: =F27+F64-F93+F36 -> -20580525 | G76: =G27+G64-G93+G36 -> 9143626.6 | H76: =H27+H64-H93+H36 -> 10208770 | I76: =I27+I64-I93+I36 -> 10667841 | J76: =J27+J64-J93+J36 -> 11527151 | K76: =K27+K64-K93+K36 -> 11800797 | ... N76: =N27+N64-N93+N36 -> 11760040 | O76: =O27+O64-O93+O36+O24 -> 11983057 | P76: =P27+P64-P93+P36+P24 -> 12128361 | Q76: =Q27+Q64-Q93+Q36+Q24 -> 1.1113199e+08
A77: Equity CF | D77: =-D16 -> 0 | E77: =-E16 -> 0 | F77: =-F16 -> -8970383.1 | G77: =-G16 -> 0 | H77: =-H16 -> 0 | I77: =-I16 -> 0 | J77: =-J16 -> 0 | K77: =-K16 -> 0 | ... N77: =-N16 -> 0 | O77: =-O16+O24 -> 0 | P77: =-P16+P24 -> 0 | Q77: =-Q16+Q24 -> 97309399
A80: EQUITY SCHEDULE
A81: Year | D81: =D7 -> FY25 | E81: =E7 -> FY26 | F81: =F7 -> FY27 | G81: =G7 -> FY28 | H81: =H7 -> FY29 | I81: =I7 -> FY30 | J81: =J7 -> FY31 | K81: =K7 -> FY32 | ... Q81: =Q7 -> FY38
D83: 0 | E83: =D89 -> 0 | F83: =E89 -> 0 | G83: =F89 -> 8970383.1 | H83: =G89 -> 8970383.1 | I83: =H89 -> 8970383.1 | J83: =I89 -> 8970383.1 | K83: =J89 -> 8970383.1 | L83: =K89 -> 8970383.1 | ... Q83: =P89 -> 8970383.1
D84: =D13 -> 0 | E84: =E13 -> 0 | F84: =F13 -> 1500000 | G84: =G13 -> 0 | H84: =H13 -> 0 | I84: =I13 -> 0 | J84: =J13 -> 0 | K84: =K13 -> 0 | ... Q84: =Q13 -> 0
D85: =D14 -> 0 | E85: =E14 -> 0 | F85: =F14 -> 7470383.1 | G85: =G14 -> 0 | H85: =H14 -> 0 | I85: =I14 -> 0 | J85: =J14 -> 0 | K85: =K14 -> 0 | ... Q85: =Q14 -> 0
D86: =D15 -> 0 | E86: =E15 -> 0 | F86: =F15 -> 0 | G86: =G15 -> 0 | H86: =H15 -> 0 | I86: =I15 -> 0 | J86: =J15 -> 0 | K86: =K15 -> 0 | ... Q86: =Q15 -> 0
A87: Total New Equity | D87: =D84+D85+D86 -> 0 | E87: =E84+E85+E86 -> 0 | F87: =F84+F85+F86 -> 8970383.1 | G87: =G84+G85+G86 -> 0 | H87: =H84+H85+H86 -> 0 | I87: =I84+I85+I86 -> 0 | J87: =J84+J85+J86 -> 0 | K87: =K84+K85+K86 -> 0 | ... Q87: =Q84+Q85+Q86 -> 0
A88: Distributions / Buybacks | D88: 0 | E88: 0 | F88: 0 | G88: 0 | H88: 0 | I88: 0 | J88: 0 | K88: 0 | L88: 0 | M88: 0 | N88: 0 | O88: 0 | P88: 0 | Q88: 0
A89: Closing Contributed Equity | D89: =D83+D87+D88 -> 0 | E89: =E83+E87+E88 -> 0 | F89: =F83+F87+F88 -> 8970383.1 | G89: =G83+G87+G88 -> 8970383.1 | H89: =H83+H87+H88 -> 8970383.1 | I89: =I83+I87+I88 -> 8970383.1 | J89: =J83+J87+J88 -> 8970383.1 | K89: =K83+K87+K88 -> 8970383.1 | ... Q89: =Q83+Q87+Q88 -> 8970383.1
A91: Cumulative Contributed Equity | D91: =D89 -> 0 | E91: =E89 -> 0 | F91: =F89 -> 8970383.1 | G91: =G89 -> 8970383.1 | H91: =H89 -> 8970383.1 | I91: =I89 -> 8970383.1 | J91: =J89 -> 8970383.1 | K91: =K89 -> 8970383.1 | ... Q91: =Q89 -> 8970383.1

Sheet P&L
A1: Profit & Loss Statement
A2: THE BEND Live House
F4: FY START | G4: 45689 | H4: =G5+1 -> 45839 | I4: =H5+1 -> 46204 | J4: =I5+1 -> 46569 | K4: =J5+1 -> 46935 | L4: =K5+1 -> 47300 | M4: =L5+1 -> 47665 | N4: =M5+1 -> 48030 | O4: =N5+1 -> 48396 | ... T4: =S5+1 -> 50222
F5: FY END | G5: =DATE(YEAR(G4) + (MONTH(G4)>=7), 6, 30) -> 45838 | H5: =DATE(YEAR(H4) + (MONTH(H4)>=7), 6, 30) -> 46203 | I5: =DATE(YEAR(I4) + (MONTH(I4)>=7), 6, 30) -> 46568 | J5: =DATE(YEAR(J4) + (MONTH(J4)>=7), 6, 30) -> 46934 | K5: =DATE(YEAR(K4) + (MONTH(K4)>=7), 6, 30) -> 47299 | L5: =DATE(YEAR(L4) + (MONTH(L4)>=7), 6, 30) -> 47664 | M5: =DATE(YEAR(M4) + (MONTH(M4)>=7), 6, 30) -> 48029 | N5: =DATE(YEAR(N4) + (MONTH(N4)>=7), 6, 30) -> 48395 | ... T5: =DATE(YEAR(T4) + (MONTH(T4)>=7), 6, 30) -> 50586
F6: Year | G6: ="FY"&RIGHT(YEAR(G5)+(MONTH(G5)>6),2) -> FY25 | H6: ="FY"&RIGHT(YEAR(H5)+(MONTH(H5)>6),2) -> FY26 | I6: ="FY"&RIGHT(YEAR(I5)+(MONTH(I5)>6),2) -> FY27 | J6: ="FY"&RIGHT(YEAR(J5)+(MONTH(J5)>6),2) -> FY28 | K6: ="FY"&RIGHT(YEAR(K5)+(MONTH(K5)>6),2) -> FY29 | L6: ="FY"&RIGHT(YEAR(L5)+(MONTH(L5)>6),2) -> FY30 | M6: ="FY"&RIGHT(YEAR(M5)+(MONTH(M5)>6),2) -> FY31 | N6: ="FY"&RIGHT(YEAR(N5)+(MONTH(N5)>6),2) -> FY32 | ... T6: ="FY"&RIGHT(YEAR(T5)+(MONTH(T5)>6),2) -> FY38
C8: Ops Flag | D8: =Inputs!E22 -> 46569 | G8: =IF(G$5>$D$8,1,0) -> 0 | H8: =IF(H$5>$D$8,1,0) -> 0 | I8: =IF(I$5>$D$8,1,0) -> 0 | J8: =IF(J$5>$D$8,1,0) -> 1 | K8: =IF(K$5>$D$8,1,0) -> 1 | L8: =IF(L$5>$D$8,1,0) -> 1 | M8: =IF(M$5>$D$8,1,0) -> 1 | N8: =IF(N$5>$D$8,1,0) -> 1 | ... T8: =IF(T$5>$D$8,1,0) -> 1
C9: Construction Flag | D9: =Inputs!E18 -> 46420 | G9: =IF(G8=1,0,IF(AND(G$5>=$D$9,G$5<=$D$10),1,0)) -> 0 | H9: =IF(H8=1,0,IF(AND(H$5>=$D$9,H$5<=$D$10),1,0)) -> 0 | I9: =IF(I8=1,0,IF(AND(I$5>=$D$9,I$5<=$D$10),1,0)) -> 1 | J9: =IF(J8=1,0,IF(AND(J$5>=$D$9,J$5<=$D$10),1,0)) -> 0 | K9: =IF(K8=1,0,IF(AND(K$5>=$D$9,K$5<=$D$10),1,0)) -> 0 | L9: =IF(L8=1,0,IF(AND(L$5>=$D$9,L$5<=$D$10),1,0)) -> 0 | M9: =IF(M8=1,0,IF(AND(M$5>=$D$9,M$5<=$D$10),1,0)) -> 0 | N9: =IF(N8=1,0,IF(AND(N$5>=$D$9,N$5<=$D$10),1,0)) -> 0 | ... T9: =IF(T8=1,0,IF(AND(T$5>=$D$9,T$5<=$D$10),1,0)) -> 0
C10: =Inputs!D17 -> Date | D10: =Inputs!E19 -> 46568
B12: REVENUE
C13: Event day revenue
C14: VHA | H14: {=(IF(H8=1,INDEX('Revenue Assumptions'!$F$93:$P$93,MATCH((2000+VALUE(RIGHT(H$6,2))),'Revenue Assumptions'!$F$34:$P$34,0))*Scenarios!$B$6,0))} -> 0 | I14: {=(IF(I8=1,INDEX('Revenue Assumptions'!$F$93:$P$93,MATCH((2000+VALUE(RIGHT(I$6,2))),'Revenue Assumptions'!$F$34:$P$34,0))*Scenarios!$B$6,0))} -> 0 | J14: ='Revenue Assumptions'!F108*Scenarios!$B$6 -> 5143660.8 | K14: ='Revenue Assumptions'!G108*Scenarios!$B$6 -> 5410441.5 | L14: ='Revenue Assumptions'!H108*Scenarios!$B$6 -> 5688599.7 | M14: ='Revenue Assumptions'!I108*Scenarios!$B$6 -> 6280019 | N14: ='Revenue Assumptions'!J108*Scenarios!$B$6 -> 6468419.6 | O14: ='Revenue Assumptions'!K108*Scenarios!$B$6 -> 6662472.1 | P14: ='Revenue Assumptions'!L108*Scenarios!$B$6 -> 6862346.3 | Q14: ='Revenue Assumptions'!M108*Scenarios!$B$6 -> 7068216.7 | ... T14: ='Revenue Assumptions'!P108*Scenarios!$B$6 -> 7723631.2
C15: Premium Sales | H15: {=(IF(H8=1,INDEX('Revenue Assumptions'!$F$124:$P$124,MATCH((2000+VALUE(RIGHT(H$6,2))),'Revenue Assumptions'!$F$34:$P$34,0))*Scenarios!$B$6,0))} -> 0 | I15: {=(IF(I8=1,INDEX('Revenue Assumptions'!$F$124:$P$124,MATCH((2000+VALUE(RIGHT(I$6,2))),'Revenue Assumptions'!$F$34:$P$34,0))*Scenarios!$B$6,0))} -> 0 | J15: ='Revenue Assumptions'!F124*Scenarios!$B$6 -> 722399.25 | K15: ='Revenue Assumptions'!G124*Scenarios!$B$6 -> 759867.15 | L15: ='Revenue Assumptions'!H124*Scenarios!$B$6 -> 798932.97 | M15: ='Revenue Assumptions'!I124*Scenarios!$B$6 -> 881994.6 | N15: ='Revenue Assumptions'!J124*Scenarios!$B$6 -> 908454.44 | O15: ='Revenue Assumptions'!K124*Scenarios!$B$6 -> 935708.07 | P15: ='Revenue Assumptions'!L124*Scenarios!$B$6 -> 963779.31 | Q15: ='Revenue Assumptions'!M124*Scenarios!$B$6 -> 992692.69 | ... T15: ='Revenue Assumptions'!P124*Scenarios!$B$6 -> 1084742.1
C16: Premium F&B | H16: {=(IF(H8=1,INDEX('Revenue Assumptions'!$F$159:$P$159,MATCH((2000+VALUE(RIGHT(H$6,2))),'Revenue Assumptions'!$F$34:$P$34,0))*Scenarios!$B$6,0))} -> 0 | I16: {=(IF(I8=1,INDEX('Revenue Assumptions'!$F$159:$P$159,MATCH((2000+VALUE(RIGHT(I$6,2))),'Revenue Assumptions'!$F$34:$P$34,0))*Scenarios!$B$6,0))} -> 0 | J16: ='Revenue Assumptions'!F159*Scenarios!$B$6 -> 163355.4 | K16: ='Revenue Assumptions'!G159*Scenarios!$B$6 -> 166823.28 | L16: ='Revenue Assumptions'!H159*Scenarios!$B$6 -> 170291.16 | M16: ='Revenue Assumptions'!I159*Scenarios!$B$6 -> 182520 | N16: ='Revenue Assumptions'!J159*Scenarios!$B$6 -> 182520 | O16: ='Revenue Assumptions'!K159*Scenarios!$B$6 -> 182520 | P16: ='Revenue Assumptions'!L159*Scenarios!$B$6 -> 182520 | Q16: ='Revenue Assumptions'!M159*Scenarios!$B$6 -> 182520 | ... T16: ='Revenue Assumptions'!P159*Scenarios!$B$6 -> 182520
C17: F&B | H17: {=(IF(H8=1,INDEX('Revenue Assumptions'!$F$141:$P$141,MATCH((2000+VALUE(RIGHT(H$6,2))),'Revenue Assumptions'!$F$34:$P$34,0))*Scenarios!$B$6,0))} -> 0 | I17: {=(IF(I8=1,INDEX('Revenue Assumptions'!$F$141:$P$141,MATCH((2000+VALUE(RIGHT(I$6,2))),'Revenue Assumptions'!$F$34:$P$34,0))*Scenarios!$B$6,0))} -> 0 | J17: ='Revenue Assumptions'!F141*Scenarios!$B$6 -> 6033732 | K17: ='Revenue Assumptions'!G141*Scenarios!$B$6 -> 6478610.2 | L17: ='Revenue Assumptions'!H141*Scenarios!$B$6 -> 6943848 | M17: ='Revenue Assumptions'!I141*Scenarios!$B$6 -> 7065841.2 | N17: ='Revenue Assumptions'!J141*Scenarios!$B$6 -> 7277816.4 | O17: ='Revenue Assumptions'!K141*Scenarios!$B$6 -> 7496150.9 | P17: ='Revenue Assumptions'!L141*Scenarios!$B$6 -> 7721035.5 | Q17: ='Revenue Assumptions'!M141*Scenarios!$B$6 -> 7952666.5 | ... T17: ='Revenue Assumptions'!P141*Scenarios!$B$6 -> 8690093.4
C18: Merchandise | H18: {=IF(H$8=1,INDEX('Calendar Assumptions'!$F$52:$Q$52,MATCH((2000+VALUE(RIGHT(H$6,2))),'Calendar Assumptions'!$F$2:$Q$2,0))*Inputs!$E$360*Scenarios!$B$6,0)} -> 0 | I18: {=IF(I$8=1,INDEX('Calendar Assumptions'!$F$52:$Q$52,MATCH((2000+VALUE(RIGHT(I$6,2))),'Calendar Assumptions'!$F$2:$Q$2,0))*Inputs!$E$360*Scenarios!$B$6,0)} -> 0 | J18: ='Calendar Assumptions'!F54*Scenarios!$B$6*Inputs!$E$360 -> 745356 | K18: ='Calendar Assumptions'!G54*Scenarios!$B$6*Inputs!$E$360 -> 761179.2 | L18: ='Calendar Assumptions'!H54*Scenarios!$B$6*Inputs!$E$360 -> 777002.4 | M18: ='Calendar Assumptions'!I54*Scenarios!$B$6*Inputs!$E$360 -> 832800 | N18: ='Calendar Assumptions'!J54*Scenarios!$B$6*Inputs!$E$360 -> 832800 | O18: ='Calendar Assumptions'!K54*Scenarios!$B$6*Inputs!$E$360 -> 832800 | P18: ='Calendar Assumptions'!L54*Scenarios!$B$6*Inputs!$E$360 -> 832800 | Q18: ='Calendar Assumptions'!M54*Scenarios!$B$6*Inputs!$E$360 -> 832800 | ... T18: ='Calendar Assumptions'!P54*Scenarios!$B$6*Inputs!$E$360 -> 832800
C19: Facilities Fee | H19: {=IF(H$8=1,INDEX('Calendar Assumptions'!$F$16:$Q$16,MATCH((2000+VALUE(RIGHT(H$6,2))),'Calendar Assumptions'!$F$2:$Q$2,0))*Inputs!$E$362*Scenarios!$B$6,0)} -> 0 | I19: {=IF(I$8=1,INDEX('Calendar Assumptions'!$F$16:$Q$16,MATCH((2000+VALUE(RIGHT(I$6,2))),'Calendar Assumptions'!$F$2:$Q$2,0))*Inputs!$E$362*Scenarios!$B$6,0)} -> 0 | J19: ='Calendar Assumptions'!F52*Scenarios!$B$6*Inputs!$E$362 -> 1202880 | K19: ='Calendar Assumptions'!G52*Scenarios!$B$6*Inputs!$E$362 -> 1228416 | L19: ='Calendar Assumptions'!H52*Scenarios!$B$6*Inputs!$E$362 -> 1253952 | M19: ='Calendar Assumptions'!I52*Scenarios!$B$6*Inputs!$E$362 -> 1344000 | N19: ='Calendar Assumptions'!J52*Scenarios!$B$6*Inputs!$E$362 -> 1344000 | O19: ='Calendar Assumptions'!K52*Scenarios!$B$6*Inputs!$E$362 -> 1344000 | P19: ='Calendar Assumptions'!L52*Scenarios!$B$6*Inputs!$E$362 -> 1344000 | Q19: ='Calendar Assumptions'!M52*Scenarios!$B$6*Inputs!$E$362 -> 1344000 | ... T19: ='Calendar Assumptions'!P52*Scenarios!$B$6*Inputs!$E$362 -> 1344000
C20: Equipment Hire | H20: {=IF(H$8=1,INDEX('Revenue Assumptions'!$F$199:$P$199,MATCH((2000+VALUE(RIGHT(H$6,2))),'Revenue Assumptions'!$F$34:$P$34,0))*Scenarios!$B$6,0)} -> 0 | I20: {=IF(I$8=1,INDEX('Revenue Assumptions'!$F$199:$P$199,MATCH((2000+VALUE(RIGHT(I$6,2))),'Revenue Assumptions'!$F$34:$P$34,0))*Scenarios!$B$6,0)} -> 0 | J20: ='Revenue Assumptions'!F199*Scenarios!$B$6 -> 2335950 | K20: ='Revenue Assumptions'!G199*Scenarios!$B$6 -> 2385540 | L20: ='Revenue Assumptions'!H199*Scenarios!$B$6 -> 2435130 | M20: ='Revenue Assumptions'!I199*Scenarios!$B$6 -> 2610000 | N20: ='Revenue Assumptions'!J199*Scenarios!$B$6 -> 2610000 | O20: ='Revenue Assumptions'!K199*Scenarios!$B$6 -> 2610000 | P20: ='Revenue Assumptions'!L199*Scenarios!$B$6 -> 2610000 | Q20: ='Revenue Assumptions'!M199*Scenarios!$B$6 -> 2610000 | ... T20: ='Revenue Assumptions'!P199*Scenarios!$B$6 -> 2610000
C21: ="Total "& C13 -> Total Event day revenue | H21: =SUM(H14:H20) -> 0 | I21: =SUM(I14:I20) -> 0 | J21: =SUM(J14:J20) -> 16347333 | K21: =SUM(K14:K20) -> 17190877 | L21: =SUM(L14:L20) -> 18067756 | M21: =SUM(M14:M20) -> 19197175 | N21: =SUM(N14:N20) -> 19624010 | O21: =SUM(O14:O20) -> 20063651 | ... T21: =SUM(T14:T20) -> 22467787
C23: Non-event day revenue
C24: Sponsorship | H24: {=IF(H8=1,INDEX('Revenue Assumptions'!$F$175:$P$175,MATCH((2000+VALUE(RIGHT(H$6,2))),'Revenue Assumptions'!$F$34:$P$34,0))*Scenarios!$B$6,0)} -> 0 | I24: {=IF(I8=1,INDEX('Revenue Assumptions'!$F$175:$P$175,MATCH((2000+VALUE(RIGHT(I$6,2))),'Revenue Assumptions'!$F$34:$P$34,0))*Scenarios!$B$6,0)} -> 0 | J24: ='Revenue Assumptions'!F175*Scenarios!$B$6 -> 1850000 | K24: ='Revenue Assumptions'!G175*Scenarios!$B$6 -> 1896250 | L24: ='Revenue Assumptions'!H175*Scenarios!$B$6 -> 1943656.2 | M24: ='Revenue Assumptions'!I175*Scenarios!$B$6 -> 1992247.7 | N24: ='Revenue Assumptions'!J175*Scenarios!$B$6 -> 2042053.8 | O24: ='Revenue Assumptions'!K175*Scenarios!$B$6 -> 2093105.2 | P24: ='Revenue Assumptions'!L175*Scenarios!$B$6 -> 2145432.8 | Q24: ='Revenue Assumptions'!M175*Scenarios!$B$6 -> 2199068.6 | ... T24: ='Revenue Assumptions'!P175*Scenarios!$B$6 -> 2368156.4
C25: Advertising | H25: {=(IF(H8=1,INDEX('Revenue Assumptions'!$F$183:$P$183,MATCH((2000+VALUE(RIGHT(H$6,2))),'Revenue Assumptions'!$F$34:$P$34,0))*Scenarios!$B$6,0))} -> 0 | I25: {=(IF(I8=1,INDEX('Revenue Assumptions'!$F$183:$P$183,MATCH((2000+VALUE(RIGHT(I$6,2))),'Revenue Assumptions'!$F$34:$P$34,0))*Scenarios!$B$6,0))} -> 0 | J25: =Scenarios!$B$6*'Revenue Assumptions'!F183 -> 575000 | K25: =Scenarios!$B$6*'Revenue Assumptions'!G183 -> 589375 | L25: =Scenarios!$B$6*'Revenue Assumptions'!H183 -> 604109.37 | M25: =Scenarios!$B$6*'Revenue Assumptions'!I183 -> 619212.11 | N25: =Scenarios!$B$6*'Revenue Assumptions'!J183 -> 634692.41 | O25: =Scenarios!$B$6*'Revenue Assumptions'!K183 -> 650559.72 | P25: =Scenarios!$B$6*'Revenue Assumptions'!L183 -> 666823.72 | Q25: =Scenarios!$B$6*'Revenue Assumptions'!M183 -> 683494.31 | ... T25: =Scenarios!$B$6*'Revenue Assumptions'!P183 -> 736048.61
C26: ="Total "& C23 -> Total Non-event day revenue | H26: =H24+H25 -> 0 | I26: =I24+I25 -> 0 | J26: =J24+J25 -> 2425000 | K26: =K24+K25 -> 2485625 | L26: =L24+L25 -> 2547765.6 | M26: =M24+M25 -> 2611459.8 | N26: =N24+N25 -> 2676746.3 | O26: =O24+O25 -> 2743664.9 | ... T26: =T24+T25 -> 3104205
C28: Total Revenue | H28: =H21+H26 -> 0 | I28: =I21+I26 -> 0 | J28: =J21+J26 -> 18772333 | K28: =K21+K26 -> 19676502 | L28: =L21+L26 -> 20615522 | M28: =M21+M26 -> 21808635 | N28: =N21+N26 -> 22300757 | O28: =O21+O26 -> 22807316 | ... T28: =T21+T26 -> 25571992
C29: Yearly Revenue Growth | K29: =(K28-J28)/J28 -> 0.04816497 | L29: =(L28-K28)/K28 -> 0.047722892 | M29: =(M28-L28)/L28 -> 0.057874483 | N29: =(N28-M28)/M28 -> 0.022565472 | O29: =(O28-N28)/N28 -> 0.022714896 | P29: =(P28-O28)/O28 -> 0.022862031 | Q29: =(Q28-P28)/P28 -> 0.023006871 | R29: =(R28-Q28)/Q28 -> 0.023149412 | ... T29: =(T28-S28)/S28 -> 0.023427599
B30: COGS
C31: Food & Beverage
C32: CoG F&B (GA) | H32: =H17*Inputs!$E$466*Scenarios!$B$7 -> 0 | I32: =I17*Inputs!$E$466*Scenarios!$B$7 -> 0 | J32: ='Expense Assumptions'!G71 -> 1810119.6 | K32: ='Expense Assumptions'!H71 -> 1943583.1 | L32: ='Expense Assumptions'!I71 -> 2083154.4 | M32: ='Expense Assumptions'!J71 -> 2119752.4 | N32: ='Expense Assumptions'!K71 -> 2183344.9 | O32: ='Expense Assumptions'!L71 -> 2248845.3 | P32: ='Expense Assumptions'!M71 -> 2316310.6 | Q32: ='Expense Assumptions'!N71 -> 2385800 | ... T32: ='Expense Assumptions'!Q71 -> 2607028
C33: CoG F&B (Premium) | H33: =H16*Inputs!$E$466*Scenarios!$B$7 -> 0 | I33: =I16*Inputs!$E$466*Scenarios!$B$7 -> 0 | J33: ='Expense Assumptions'!G72 -> 49006.62 | K33: ='Expense Assumptions'!H72 -> 50046.984 | L33: ='Expense Assumptions'!I72 -> 51087.348 | M33: ='Expense Assumptions'!J72 -> 54756 | N33: ='Expense Assumptions'!K72 -> 54756 | O33: ='Expense Assumptions'!L72 -> 54756 | P33: ='Expense Assumptions'!M72 -> 54756 | Q33: ='Expense Assumptions'!N72 -> 54756 | ... T33: ='Expense Assumptions'!Q72 -> 54756
C34: Consumables | H34: =(H16+H17)*Inputs!$E$467*Scenarios!$B$7 -> 0 | I34: =(I16+I17)*Inputs!$E$467*Scenarios!$B$7 -> 0 | J34: ='Expense Assumptions'!G73 -> 309854.37 | K34: ='Expense Assumptions'!H73 -> 332271.67 | L34: ='Expense Assumptions'!I73 -> 355706.96 | M34: ='Expense Assumptions'!J73 -> 362418.06 | N34: ='Expense Assumptions'!K73 -> 373016.82 | O34: ='Expense Assumptions'!L73 -> 383933.55 | P34: ='Expense Assumptions'!M73 -> 395177.77 | Q34: ='Expense Assumptions'!N73 -> 406759.33 | ... T34: ='Expense Assumptions'!Q73 -> 443630.67
C35: Total COGS | H35: =SUM(H32:H34) -> 0 | I35: =SUM(I32:I34) -> 0 | J35: =SUM(J32:J34) -> 2168980.6 | K35: =SUM(K32:K34) -> 2325901.7 | L35: =SUM(L32:L34) -> 2489948.7 | M35: =SUM(M32:M34) -> 2536926.4 | N35: =SUM(N32:N34) -> 2611117.8 | O35: =SUM(O32:O34) -> 2687534.8 | ... T35: =SUM(T32:T34) -> 3105414.7
C37: COGS % | H37: =IF(H28=0,"",H35/H28) | I37: =IF(I28=0,"",I35/I28) | J37: =IF(J28=0,"",J35/J28) -> 0.11554134 | K37: =IF(K28=0,"",K35/K28) -> 0.11820707 | L37: =IF(L28=0,"",L35/L28) -> 0.12078029 | M37: =IF(M28=0,"",M35/M28) -> 0.1163267 | N37: =IF(N28=0,"",N35/N28) -> 0.11708651 | O37: =IF(O28=0,"",O35/O28) -> 0.11783652 | ... T37: =IF(T28=0,"",T35/T28) -> 0.12143812
B39: GROSS PROFIT
C40: Gross Profit | H40: =H28-H35 -> 0 | I40: =I28-I35 -> 0 | J40: =J28-J35 -> 16603353 | K40: =K28-K35 -> 17350601 | L40: =L28-L35 -> 18125573 | M40: =M28-M35 -> 19271708 | N40: =N28-N35 -> 19689639 | O40: =O28-O35 -> 20119781 | ... T40: =T28-T35 -> 22466577
C41: GPM | H41: =IF(H28=0,"",H40/H28) | I41: =IF(I28=0,"",I40/I28) | J41: =IF(J28=0,"",J40/J28) -> 0.88445866 | K41: =IF(K28=0,"",K40/K28) -> 0.88179293 | L41: =IF(L28=0,"",L40/L28) -> 0.87921971 | M41: =IF(M28=0,"",M40/M28) -> 0.8836733 | N41: =IF(N28=0,"",N40/N28) -> 0.88291349 | O41: =IF(O28=0,"",O40/O28) -> 0.88216348 | ... T41: =IF(T28=0,"",T40/T28) -> 0.87856188
C42: GPM F&B | J42: =((J16+J17)-(J32+J33+J34))/(J16+J17) -> 0.65 | K42: =((K16+K17)-(K32+K33+K34))/(K16+K17) -> 0.65 | L42: =((L16+L17)-(L32+L33+L34))/(L16+L17) -> 0.65 | M42: =((M16+M17)-(M32+M33+M34))/(M16+M17) -> 0.65 | N42: =((N16+N17)-(N32+N33+N34))/(N16+N17) -> 0.65 | O42: =((O16+O17)-(O32+O33+O34))/(O16+O17) -> 0.65 | P42: =((P16+P17)-(P32+P33+P34))/(P16+P17) -> 0.65 | Q42: =((Q16+Q17)-(Q32+Q33+Q34))/(Q16+Q17) -> 0.65 | ... T42: =((T16+T17)-(T32+T33+T34))/(T16+T17) -> 0.65
C43: GPM Equipment lease | J43: =(J20-J45)/J45 -> 2.2806996 | K43: =(K20-K45)/K45 -> 2.2530283 | L43: =(L20-L45)/L45 -> 2.224189 | M43: =(M20-M45)/M45 -> 2.3553286 | N43: =(N20-N45)/N45 -> 2.2578443 | O43: =(O20-O45)/O45 -> 2.1631855 | P43: =(P20-P45)/P45 -> 2.0712707 | Q43: =(Q20-Q45)/Q45 -> 1.9820207 | ... T43: =(T20-T45)/T45 -> 1.7295013
B44: OPERATING EXPENSES
C45: Leased equipment | H45: =IF(H$8=1,Inputs!$E$401*Scenarios!$B$7,0) -> 0 | I45: =IF(I$8=1,Inputs!$E$401*Scenarios!$B$7,0) -> 0 | J45: ='Expense Assumptions'!G82*Scenarios!$B$7 -> 712028 | K45: ='Expense Assumptions'!H82*Scenarios!$B$7 -> 733329 | L45: ='Expense Assumptions'!I82*Scenarios!$B$7 -> 755269 | M45: ='Expense Assumptions'!J82*Scenarios!$B$7 -> 777867.17 | N45: ='Expense Assumptions'!K82*Scenarios!$B$7 -> 801143.26 | O45: ='Expense Assumptions'!L82*Scenarios!$B$7 -> 825117.59 | P45: ='Expense Assumptions'!M82*Scenarios!$B$7 -> 849811.13 | Q45: ='Expense Assumptions'!N82*Scenarios!$B$7 -> 875245.44 | ... T45: ='Expense Assumptions'!Q82*Scenarios!$B$7 -> 956218.63
C46: Utilities | H46: =IF(H8=1,Inputs!$E$403*(1+Inputs!$E$537)^((2000+VALUE(RIGHT(H$6,2)))-2027)*Scenarios!$B$7,0) -> 0 | I46: =IF(I8=1,Inputs!$E$403*(1+Inputs!$E$537)^((2000+VALUE(RIGHT(I$6,2)))-2027)*Scenarios!$B$7,0) -> 0 | J46: ='Expense Assumptions'!G101*Scenarios!$B$7 -> 235000 | K46: ='Expense Assumptions'!H101*Scenarios!$B$7 -> 242050 | L46: ='Expense Assumptions'!I101*Scenarios!$B$7 -> 249311.5 | M46: ='Expense Assumptions'!J101*Scenarios!$B$7 -> 256790.85 | N46: ='Expense Assumptions'!K101*Scenarios!$B$7 -> 264494.57 | O46: ='Expense Assumptions'!L101*Scenarios!$B$7 -> 272429.41 | P46: ='Expense Assumptions'!M101*Scenarios!$B$7 -> 280602.29 | Q46: ='Expense Assumptions'!N101*Scenarios!$B$7 -> 289020.36 | ... T46: ='Expense Assumptions'!Q101*Scenarios!$B$7 -> 315820.35
C47: Maintenance (R&M) | H47: {=IF(H8=1,INDEX('Expense Assumptions'!$F$86:$Q$86,MATCH((2000+VALUE(RIGHT(H$6,2))),'Expense Assumptions'!$F$21:$Q$21,0))*Scenarios!$B$7,0)} -> 0 | I47: {=IF(I8=1,INDEX('Expense Assumptions'!$F$86:$Q$86,MATCH((2000+VALUE(RIGHT(I$6,2))),'Expense Assumptions'!$F$21:$Q$21,0))*Scenarios!$B$7,0)} -> 0 | J47: ='Expense Assumptions'!G128*Scenarios!$B$7 -> 838000 | K47: ='Expense Assumptions'!H128*Scenarios!$B$7 -> 863140 | L47: ='Expense Assumptions'!I128*Scenarios!$B$7 -> 889034.2 | M47: ='Expense Assumptions'!J128*Scenarios!$B$7 -> 915705.23 | N47: ='Expense Assumptions'!K128*Scenarios!$B$7 -> 943176.38 | O47: ='Expense Assumptions'!L128*Scenarios!$B$7 -> 971471.67 | P47: ='Expense Assumptions'!M128*Scenarios!$B$7 -> 1000615.8 | Q47: ='Expense Assumptions'!N128*Scenarios!$B$7 -> 1030634.3 | ... T47: ='Expense Assumptions'!Q128*Scenarios!$B$7 -> 1126201.9
C48: Marketing | H48: =IF(H8=1,Inputs!$E$404*(1+Inputs!$E$535)^((2000+VALUE(RIGHT(H$6,2)))-2027)*Scenarios!$B$7,0) -> 0 | I48: =Inputs!E392 -> 100000 | J48: ='Expense Assumptions'!G105*Scenarios!$B$7 -> 120000 | K48: ='Expense Assumptions'!H105*Scenarios!$B$7 -> 123600 | L48: ='Expense Assumptions'!I105*Scenarios!$B$7 -> 127308 | M48: ='Expense Assumptions'!J105*Scenarios!$B$7 -> 131127.24 | N48: ='Expense Assumptions'!K105*Scenarios!$B$7 -> 135061.06 | O48: ='Expense Assumptions'!L105*Scenarios!$B$7 -> 139112.89 | P48: ='Expense Assumptions'!M105*Scenarios!$B$7 -> 143286.28 | Q48: ='Expense Assumptions'!N105*Scenarios!$B$7 -> 147584.86 | ... T48: ='Expense Assumptions'!Q105*Scenarios!$B$7 -> 161269.97
C49: T&E | H49: =IF(H$8=1,Inputs!$E$407*(1+Inputs!$E$535)^((2000+VALUE(RIGHT(H$6,2)))-2027)*Scenarios!$B$7,0) -> 0 | I49: =IF(I$8=1,Inputs!$E$407*(1+Inputs!$E$535)^((2000+VALUE(RIGHT(I$6,2)))-2027)*Scenarios!$B$7,0) -> 0 | J49: ='Expense Assumptions'!G114*Scenarios!$B$7 -> 150000 | K49: ='Expense Assumptions'!H114*Scenarios!$B$7 -> 154500 | L49: ='Expense Assumptions'!I114*Scenarios!$B$7 -> 159135 | M49: ='Expense Assumptions'!J114*Scenarios!$B$7 -> 163909.05 | N49: ='Expense Assumptions'!K114*Scenarios!$B$7 -> 168826.32 | O49: ='Expense Assumptions'!L114*Scenarios!$B$7 -> 173891.11 | P49: ='Expense Assumptions'!M114*Scenarios!$B$7 -> 179107.84 | Q49: ='Expense Assumptions'!N114*Scenarios!$B$7 -> 184481.08 | ... T49: ='Expense Assumptions'!Q114*Scenarios!$B$7 -> 201587.46
C50: Uniforms | H50: =IF(H$8=1,Inputs!$E$415*(1+Inputs!$E$535)^((2000+VALUE(RIGHT(H$6,2)))-2027)*Scenarios!$B$7,0) -> 0 | I50: =IF(I$8=1,Inputs!$E$415*(1+Inputs!$E$535)^((2000+VALUE(RIGHT(I$6,2)))-2027)*Scenarios!$B$7,0) -> 0 | J50: ='Expense Assumptions'!G111*Scenarios!$B$7 -> 6500 | K50: ='Expense Assumptions'!H111*Scenarios!$B$7 -> 6695 | L50: ='Expense Assumptions'!I111*Scenarios!$B$7 -> 6895.85 | M50: ='Expense Assumptions'!J111*Scenarios!$B$7 -> 7102.7255 | N50: ='Expense Assumptions'!K111*Scenarios!$B$7 -> 7315.8073 | O50: ='Expense Assumptions'!L111*Scenarios!$B$7 -> 7535.2815 | P50: ='Expense Assumptions'!M111*Scenarios!$B$7 -> 7761.3399 | Q50: ='Expense Assumptions'!N111*Scenarios!$B$7 -> 7994.1801 | ... T50: ='Expense Assumptions'!Q111*Scenarios!$B$7 -> 8735.4565
C51: Dues and subscriptions | H51: =IF(H$8=1,Inputs!$E$416*(1+Inputs!$E$535)^((2000+VALUE(RIGHT(H$6,2)))-2027)*Scenarios!$B$7,0) -> 0 | I51: =IF(I$8=1,Inputs!$E$416*(1+Inputs!$E$535)^((2000+VALUE(RIGHT(I$6,2)))-2027)*Scenarios!$B$7,0) -> 0 | J51: ='Expense Assumptions'!G112*Scenarios!$B$7 -> 20000 | K51: ='Expense Assumptions'!H112*Scenarios!$B$7 -> 20600 | L51: ='Expense Assumptions'!I112*Scenarios!$B$7 -> 21218 | M51: ='Expense Assumptions'!J112*Scenarios!$B$7 -> 21854.54 | N51: ='Expense Assumptions'!K112*Scenarios!$B$7 -> 22510.176 | O51: ='Expense Assumptions'!L112*Scenarios!$B$7 -> 23185.481 | P51: ='Expense Assumptions'!M112*Scenarios!$B$7 -> 23881.046 | Q51: ='Expense Assumptions'!N112*Scenarios!$B$7 -> 24597.477 | ... T51: ='Expense Assumptions'!Q112*Scenarios!$B$7 -> 26878.328
C52: Licenses | H52: =IF(H$8=1,Inputs!$E$408*(1+Inputs!$E$535)^((2000+VALUE(RIGHT(H$6,2)))-2027)*Scenarios!$B$7,0) -> 0 | I52: =IF(I$8=1,Inputs!$E$408*(1+Inputs!$E$535)^((2000+VALUE(RIGHT(I$6,2)))-2027)*Scenarios!$B$7,0) -> 0 | J52: ='Expense Assumptions'!G110*Scenarios!$B$7 -> 50000 | K52: ='Expense Assumptions'!H110*Scenarios!$B$7 -> 51500 | L52: ='Expense Assumptions'!I110*Scenarios!$B$7 -> 53045 | M52: ='Expense Assumptions'!J110*Scenarios!$B$7 -> 54636.35 | N52: ='Expense Assumptions'!K110*Scenarios!$B$7 -> 56275.44 | O52: ='Expense Assumptions'!L110*Scenarios!$B$7 -> 57963.704 | P52: ='Expense Assumptions'!M110*Scenarios!$B$7 -> 59702.615 | Q52: ='Expense Assumptions'!N110*Scenarios!$B$7 -> 61493.693 | ... T52: ='Expense Assumptions'!Q110*Scenarios!$B$7 -> 67195.819
C53: Security Monitoring | H53: =IF(H$8=1,Inputs!$E$413*(1+Inputs!$E$535)^((2000+VALUE(RIGHT(H$6,2)))-2027)*Scenarios!$B$7,0) -> 0 | I53: =IF(I$8=1,Inputs!$E$413*(1+Inputs!$E$535)^((2000+VALUE(RIGHT(I$6,2)))-2027)*Scenarios!$B$7,0) -> 0 | J53: ='Expense Assumptions'!G95*Scenarios!$B$7 -> 410000 | K53: ='Expense Assumptions'!H95*Scenarios!$B$7 -> 422300 | L53: ='Expense Assumptions'!I95*Scenarios!$B$7 -> 434969 | M53: ='Expense Assumptions'!J95*Scenarios!$B$7 -> 448018.07 | N53: ='Expense Assumptions'!K95*Scenarios!$B$7 -> 461458.61 | O53: ='Expense Assumptions'!L95*Scenarios!$B$7 -> 475302.37 | P53: ='Expense Assumptions'!M95*Scenarios!$B$7 -> 489561.44 | Q53: ='Expense Assumptions'!N95*Scenarios!$B$7 -> 504248.28 | ... T53: ='Expense Assumptions'!Q95*Scenarios!$B$7 -> 551005.72
C54: Health & Safety | H54: =IF(H$8=1,Inputs!$E$411*(1+Inputs!$E$535)^((2000+VALUE(RIGHT(H$6,2)))-2027)*Scenarios!$B$7,0) -> 0 | I54: =IF(I$8=1,Inputs!$E$411*(1+Inputs!$E$535)^((2000+VALUE(RIGHT(I$6,2)))-2027)*Scenarios!$B$7,0) -> 0 | J54: ='Expense Assumptions'!G107*Scenarios!$B$7 -> 80000 | K54: ='Expense Assumptions'!H107*Scenarios!$B$7 -> 82400 | L54: ='Expense Assumptions'!I107*Scenarios!$B$7 -> 84872 | M54: ='Expense Assumptions'!J107*Scenarios!$B$7 -> 87418.16 | N54: ='Expense Assumptions'!K107*Scenarios!$B$7 -> 90040.705 | O54: ='Expense Assumptions'!L107*Scenarios!$B$7 -> 92741.926 | P54: ='Expense Assumptions'!M107*Scenarios!$B$7 -> 95524.184 | Q54: ='Expense Assumptions'!N107*Scenarios!$B$7 -> 98389.909 | ... T54: ='Expense Assumptions'!Q107*Scenarios!$B$7 -> 107513.31
C55: Sponsorship Commission (15%) | H55: =IF(H8=1,Inputs!$E$352*H24,0) -> 0 | I55: =IF(I8=1,Inputs!$E$352*I24,0) -> 0 | J55: =Inputs!$E$352*J24*Scenarios!$B$7 -> 277500 | K55: =Inputs!$E$352*K24*Scenarios!$B$7 -> 284437.5 | L55: =Inputs!$E$352*L24*Scenarios!$B$7 -> 291548.44 | M55: =Inputs!$E$352*M24*Scenarios!$B$7 -> 298837.15 | N55: =Inputs!$E$352*N24*Scenarios!$B$7 -> 306308.08 | O55: =Inputs!$E$352*O24*Scenarios!$B$7 -> 313965.78 | P55: =Inputs!$E$352*P24*Scenarios!$B$7 -> 321814.92 | Q55: =Inputs!$E$352*Q24*Scenarios!$B$7 -> 329860.3 | ... T55: =Inputs!$E$352*T24*Scenarios!$B$7 -> 355223.46
C56: Sponsorship Activation (5%) | H56: =IF(H8=1,Inputs!$E$353*H24,0) -> 0 | I56: =IF(I8=1,Inputs!$E$353*I24,0) -> 0 | J56: =Inputs!$E$353*J24*Scenarios!$B$7 -> 92500 | K56: =Inputs!$E$353*K24*Scenarios!$B$7 -> 94812.5 | L56: =Inputs!$E$353*L24*Scenarios!$B$7 -> 97182.812 | M56: =Inputs!$E$353*M24*Scenarios!$B$7 -> 99612.383 | N56: =Inputs!$E$353*N24*Scenarios!$B$7 -> 102102.69 | O56: =Inputs!$E$353*O24*Scenarios!$B$7 -> 104655.26 | P56: =Inputs!$E$353*P24*Scenarios!$B$7 -> 107271.64 | Q56: =Inputs!$E$353*Q24*Scenarios!$B$7 -> 109953.43 | ... T56: =Inputs!$E$353*T24*Scenarios!$B$7 -> 118407.82
C57: Lease deposit | H57: =0 -> 0 | I57: =0 -> 0 | J57: =0 -> 0 | K57: =0 -> 0 | L57: =0 -> 0 | M57: =0 -> 0 | N57: =0 -> 0 | O57: =0 -> 0 | ... T57: =0 -> 0
C58: ='Expense Assumptions'!C62 -> Annual Venue Lease | H58: {=IF(H8=1,INDEX('Expense Assumptions'!$F$62:$Q$62,MATCH((2000+VALUE(RIGHT(H$6,2))),'Expense Assumptions'!$F$21:$Q$21,0))*Scenarios!$B$7,0)} -> 0 | I58: {=IF(I8=1,INDEX('Expense Assumptions'!$F$62:$Q$62,MATCH((2000+VALUE(RIGHT(I$6,2))),'Expense Assumptions'!$F$21:$Q$21,0))*Scenarios!$B$7,0)} -> 0 | J58: {=IF(J8=1,INDEX('Expense Assumptions'!$F$62:$Q$62,MATCH((2000+VALUE(RIGHT(J$6,2))),'Expense Assumptions'!$F$21:$Q$21,0))*Scenarios!$B$7,0)} -> 0 | K58: ='Expense Assumptions'!H62 -> 375375 | L58: ='Expense Assumptions'!I62 -> 422638.12 | M58: ='Expense Assumptions'!J62 -> 437430.46 | N58: ='Expense Assumptions'!K62 -> 452740.53 | O58: ='Expense Assumptions'!L62 -> 899337.89 | P58: ='Expense Assumptions'!M62 -> 969973.94 | Q58: ='Expense Assumptions'!N62 -> 1003923 | R58: ='Expense Assumptions'!O62 -> 1039060.3 | ... T58: ='Expense Assumptions'!Q62 -> 461943.19
C59: Landlord Outgoings | H59: =IF(H$8=1,H$58*RM_OutgoingsPct,0) -> 0 | I59: =IF(I$8=1,I$58*RM_OutgoingsPct,0) -> 0 | J59: =IF(I$8=1,J$58*RM_OutgoingsPct,0) -> 0 | K59: ='Expense Assumptions'!H63 -> 56306.25 | L59: ='Expense Assumptions'!I63 -> 63395.719 | M59: ='Expense Assumptions'!J63 -> 65614.569 | N59: ='Expense Assumptions'!K63 -> 67911.079 | O59: ='Expense Assumptions'!L63 -> 134900.68 | P59: ='Expense Assumptions'!M63 -> 145496.09 | Q59: ='Expense Assumptions'!N63 -> 150588.45 | R59: ='Expense Assumptions'!O63 -> 155859.05 | ... T59: ='Expense Assumptions'!Q63 -> 69291.479
C60: Administrative / Legal / Other | H60: =IF(H8=1,Inputs!$E$406*(1+Inputs!$E$535)^((2000+VALUE(RIGHT(H$6,2)))-2027)*Scenarios!$B$7,0) -> 0 | I60: =Inputs!E391 -> 200000 | J60: ='Expense Assumptions'!G103*Scenarios!$B$7 -> 100000 | K60: ='Expense Assumptions'!H103*Scenarios!$B$7 -> 103000 | L60: ='Expense Assumptions'!I103*Scenarios!$B$7 -> 106090 | M60: ='Expense Assumptions'!J103*Scenarios!$B$7 -> 109272.7 | N60: ='Expense Assumptions'!K103*Scenarios!$B$7 -> 112550.88 | O60: ='Expense Assumptions'!L103*Scenarios!$B$7 -> 115927.41 | P60: ='Expense Assumptions'!M103*Scenarios!$B$7 -> 119405.23 | Q60: ='Expense Assumptions'!N103*Scenarios!$B$7 -> 122987.39 | ... T60: ='Expense Assumptions'!Q103*Scenarios!$B$7 -> 134391.64
C61: General Consultant | H61: =IF(H9=1,Inputs!$E$406*(1+Inputs!$E$535)^((2000+VALUE(RIGHT(H$6,2)))-2027)*Scenarios!$B$7,0) -> 0 | I61: 0 | J61: ='Expense Assumptions'!G104*Scenarios!$B$7 -> 80000 | K61: ='Expense Assumptions'!H104*Scenarios!$B$7 -> 82400 | L61: ='Expense Assumptions'!I104*Scenarios!$B$7 -> 84872 | M61: ='Expense Assumptions'!J104*Scenarios!$B$7 -> 87418.16 | N61: ='Expense Assumptions'!K104*Scenarios!$B$7 -> 90040.705 | O61: ='Expense Assumptions'!L104*Scenarios!$B$7 -> 92741.926 | P61: ='Expense Assumptions'!M104*Scenarios!$B$7 -> 95524.184 | Q61: ='Expense Assumptions'!N104*Scenarios!$B$7 -> 98389.909 | ... T61: ='Expense Assumptions'!Q104*Scenarios!$B$7 -> 107513.31
C62: Insurance | H62: =IF(H8=1,Inputs!$E$405*(1+Inputs!$E$538)^((2000+VALUE(RIGHT(H$6,2)))-2027)*Scenarios!$B$7,0) -> 0 | I62: =Inputs!E393 -> 30000 | J62: ='Expense Assumptions'!G113*Scenarios!$B$7 -> 80000 | K62: ='Expense Assumptions'!H113*Scenarios!$B$7 -> 82400 | L62: ='Expense Assumptions'!I113*Scenarios!$B$7 -> 84872 | M62: ='Expense Assumptions'!J113*Scenarios!$B$7 -> 87418.16 | N62: ='Expense Assumptions'!K113*Scenarios!$B$7 -> 90040.705 | O62: ='Expense Assumptions'!L113*Scenarios!$B$7 -> 92741.926 | P62: ='Expense Assumptions'!M113*Scenarios!$B$7 -> 95524.184 | Q62: ='Expense Assumptions'!N113*Scenarios!$B$7 -> 98389.909 | ... T62: ='Expense Assumptions'!Q113*Scenarios!$B$7 -> 107513.31
C63: Bad debts | H63: =IF(H8=1,H28*Inputs!$E$460*Scenarios!$B$7,0) -> 0 | I63: =IF(I8=1,I28*Inputs!$E$460*Scenarios!$B$7,0) -> 0 | J63: =J28*Inputs!$E$460*Scenarios!$B$7 -> 93861.667 | K63: =K28*Inputs!$E$460*Scenarios!$B$7 -> 98382.511 | L63: =L28*Inputs!$E$460*Scenarios!$B$7 -> 103077.61 | M63: =M28*Inputs!$E$460*Scenarios!$B$7 -> 109043.17 | N63: =N28*Inputs!$E$460*Scenarios!$B$7 -> 111503.78 | O63: =O28*Inputs!$E$460*Scenarios!$B$7 -> 114036.58 | P63: =P28*Inputs!$E$460*Scenarios!$B$7 -> 116643.69 | Q63: =Q28*Inputs!$E$460*Scenarios!$B$7 -> 119327.29 | ... T63: =T28*Inputs!$E$460*Scenarios!$B$7 -> 127859.96
C64: Audit | H64: =IF(H$8=1,Inputs!$E$409*(1+Inputs!$E$535)^((2000+VALUE(RIGHT(H$6,2)))-2027)*Scenarios!$B$7,0) -> 0 | I64: =IF(I$8=1,Inputs!$E$409*(1+Inputs!$E$535)^((2000+VALUE(RIGHT(I$6,2)))-2027)*Scenarios!$B$7,0) -> 0 | J64: ='Expense Assumptions'!G109*Scenarios!$B$7 -> 25000 | K64: ='Expense Assumptions'!H109*Scenarios!$B$7 -> 25750 | L64: ='Expense Assumptions'!I109*Scenarios!$B$7 -> 26522.5 | M64: ='Expense Assumptions'!J109*Scenarios!$B$7 -> 27318.175 | N64: ='Expense Assumptions'!K109*Scenarios!$B$7 -> 28137.72 | O64: ='Expense Assumptions'!L109*Scenarios!$B$7 -> 28981.852 | P64: ='Expense Assumptions'!M109*Scenarios!$B$7 -> 29851.307 | Q64: ='Expense Assumptions'!N109*Scenarios!$B$7 -> 30746.847 | ... T64: ='Expense Assumptions'!Q109*Scenarios!$B$7 -> 33597.909
C65: Payroll Processing | H65: =IF(H$8=1,Inputs!$E$410*(1+Inputs!$E$535)^((2000+VALUE(RIGHT(H$6,2)))-2027)*Scenarios!$B$7,0) -> 0 | I65: =IF(I$8=1,Inputs!$E$410*(1+Inputs!$E$535)^((2000+VALUE(RIGHT(I$6,2)))-2027)*Scenarios!$B$7,0) -> 0 | J65: ='Expense Assumptions'!G108*Scenarios!$B$7 -> 10000 | K65: ='Expense Assumptions'!H108*Scenarios!$B$7 -> 10300 | L65: ='Expense Assumptions'!I108*Scenarios!$B$7 -> 10609 | M65: ='Expense Assumptions'!J108*Scenarios!$B$7 -> 10927.27 | N65: ='Expense Assumptions'!K108*Scenarios!$B$7 -> 11255.088 | O65: ='Expense Assumptions'!L108*Scenarios!$B$7 -> 11592.741 | P65: ='Expense Assumptions'!M108*Scenarios!$B$7 -> 11940.523 | Q65: ='Expense Assumptions'!N108*Scenarios!$B$7 -> 12298.739 | ... T65: ='Expense Assumptions'!Q108*Scenarios!$B$7 -> 13439.164
H66: 0 | I66: 0 | J66: 0 | K66: 0 | L66: 0 | M66: 0 | N66: 0 | O66: 0 | P66: 0 | Q66: 0 | R66: 0 | S66: 0 | T66: 0
C67: Staff costs | H67: =H68+H69+H70 -> 0 | I67: =I68+I69+I70 -> 590383.09 | J67: =J68+J69+J70 -> 1840437 | K67: =K68+K69+K70 -> 1897490.5 | L67: =L68+L69+L70 -> 1956312.8 | M67: =M68+M69+M70 -> 2016958.4 | N67: =N68+N69+N70 -> 2079484.2 | O67: =O68+O69+O70 -> 2143948.2 | ... T67: =T68+T69+T70 -> 2497512.1
C68: Salaries | H68: {=IF(H$8=1,INDEX('Expense Assumptions'!$F$35:$Q$35,MATCH((2000+VALUE(RIGHT(H$6,2))),'Expense Assumptions'!$F$21:$Q$21,0))*Scenarios!$B$7,0)} -> 0 | I68: ='Expense Assumptions'!F35 -> 496999 | J68: {=IF(J$8=1,INDEX('Expense Assumptions'!$F$35:$Q$35,MATCH(J$6,'Expense Assumptions'!$F$20:$Q$20,0))*Scenarios!$B$7,0)} -> 1530000 | K68: {=IF(K$8=1,INDEX('Expense Assumptions'!$F$35:$Q$35,MATCH((2000+VALUE(RIGHT(K$6,2))),'Expense Assumptions'!$F$21:$Q$21,0))*Scenarios!$B$7,0)} -> 1577430 | L68: {=IF(L$8=1,INDEX('Expense Assumptions'!$F$35:$Q$35,MATCH((2000+VALUE(RIGHT(L$6,2))),'Expense Assumptions'!$F$21:$Q$21,0))*Scenarios!$B$7,0)} -> 1626330.3 | M68: {=IF(M$8=1,INDEX('Expense Assumptions'!$F$35:$Q$35,MATCH((2000+VALUE(RIGHT(M$6,2))),'Expense Assumptions'!$F$21:$Q$21,0))*Scenarios!$B$7,0)} -> 1676746.6 | N68: {=IF(N$8=1,INDEX('Expense Assumptions'!$F$35:$Q$35,MATCH((2000+VALUE(RIGHT(N$6,2))),'Expense Assumptions'!$F$21:$Q$21,0))*Scenarios!$B$7,0)} -> 1728725.7 | O68: {=IF(O$8=1,INDEX('Expense Assumptions'!$F$35:$Q$35,MATCH((2000+VALUE(RIGHT(O$6,2))),'Expense Assumptions'!$F$21:$Q$21,0))*Scenarios!$B$7,0)} -> 1782316.2 | P68: {=IF(P$8=1,INDEX('Expense Assumptions'!$F$35:$Q$35,MATCH((2000+VALUE(RIGHT(P$6,2))),'Expense Assumptions'!$F$21:$Q$21,0))*Scenarios!$B$7,0)} -> 1837568 | Q68: {=IF(Q$8=1,INDEX('Expense Assumptions'!$F$35:$Q$35,MATCH((2000+VALUE(RIGHT(Q$6,2))),'Expense Assumptions'!$F$21:$Q$21,0))*Scenarios!$B$7,0)} -> 1894532.6 | R68: {=IF(R$8=1,INDEX('Expense Assumptions'!$F$35:$Q$35,MATCH((2000+VALUE(RIGHT(R$6,2))),'Expense Assumptions'!$F$21:$Q$21,0))*Scenarios!$B$7,0)} -> 1953263.1 | S68: {=IF(S$8=1,INDEX('Expense Assumptions'!$F$35:$Q$35,MATCH((2000+VALUE(RIGHT(S$6,2))),'Expense Assumptions'!$F$21:$Q$21,0))*Scenarios!$B$7,0)} -> 2013814.3 | T68: {=IF(T$8=1,INDEX('Expense Assumptions'!$F$35:$R$35,MATCH((2000+VALUE(RIGHT(T$6,2))),'Expense Assumptions'!$F$21:$R$21,0))*Scenarios!$B$7,0)} -> 2076242.5
C69: Oncosts | H69: {=IF(H$8=1,INDEX('Expense Assumptions'!$F$51:$Q$51,MATCH((2000+VALUE(RIGHT(H$6,2))),'Expense Assumptions'!$F$21:$Q$21,0))*Scenarios!$B$7,0)} -> 0 | I69: ='Expense Assumptions'!F51 -> 93384.09 | J69: {=IF(J$8=1,INDEX('Expense Assumptions'!$F$51:$Q$51,MATCH((2000+VALUE(RIGHT(J$6,2))),'Expense Assumptions'!$F$21:$Q$21,0))*Scenarios!$B$7,0)} -> 274350 | K69: {=IF(K$8=1,INDEX('Expense Assumptions'!$F$51:$Q$51,MATCH((2000+VALUE(RIGHT(K$6,2))),'Expense Assumptions'!$F$21:$Q$21,0))*Scenarios!$B$7,0)} -> 282854.85 | L69: {=IF(L$8=1,INDEX('Expense Assumptions'!$F$51:$Q$51,MATCH((2000+VALUE(RIGHT(L$6,2))),'Expense Assumptions'!$F$21:$Q$21,0))*Scenarios!$B$7,0)} -> 291623.35 | M69: {=IF(M$8=1,INDEX('Expense Assumptions'!$F$51:$Q$51,MATCH((2000+VALUE(RIGHT(M$6,2))),'Expense Assumptions'!$F$21:$Q$21,0))*Scenarios!$B$7,0)} -> 300663.67 | N69: {=IF(N$8=1,INDEX('Expense Assumptions'!$F$51:$Q$51,MATCH((2000+VALUE(RIGHT(N$6,2))),'Expense Assumptions'!$F$21:$Q$21,0))*Scenarios!$B$7,0)} -> 309984.25 | O69: {=IF(O$8=1,INDEX('Expense Assumptions'!$F$51:$Q$51,MATCH((2000+VALUE(RIGHT(O$6,2))),'Expense Assumptions'!$F$21:$Q$21,0))*Scenarios!$B$7,0)} -> 319593.76 | P69: {=IF(P$8=1,INDEX('Expense Assumptions'!$F$51:$Q$51,MATCH((2000+VALUE(RIGHT(P$6,2))),'Expense Assumptions'!$F$21:$Q$21,0))*Scenarios!$B$7,0)} -> 329501.17 | Q69: {=IF(Q$8=1,INDEX('Expense Assumptions'!$F$51:$Q$51,MATCH((2000+VALUE(RIGHT(Q$6,2))),'Expense Assumptions'!$F$21:$Q$21,0))*Scenarios!$B$7,0)} -> 339715.7 | ... S69: {=IF(S$8=1,INDEX('Expense Assumptions'!$F$51:$Q$51,MATCH((2000+VALUE(RIGHT(S$6,2))),'Expense Assumptions'!$F$21:$Q$21,0))*Scenarios!$B$7,0)} -> 361104.54 | T69: {=IF(T$8=1,INDEX('Expense Assumptions'!$F$51:$R$51,MATCH((2000+VALUE(RIGHT(T$6,2))),'Expense Assumptions'!$F$21:$R$21,0))*Scenarios!$B$7,0)} -> 372298.78
C70: Training | H70: =IF(H8=1,Inputs!$E$461*(H68+H69),0) -> 0 | I70: =IF(I8=1,Inputs!$E$461*(I68+I69),0) -> 0 | J70: =IF(J8=1,Inputs!$E$461*(J68+J69),0) -> 36087 | K70: =IF(K8=1,Inputs!$E$461*(K68+K69),0) -> 37205.697 | L70: =IF(L8=1,Inputs!$E$461*(L68+L69),0) -> 38359.074 | M70: =IF(M8=1,Inputs!$E$461*(M68+M69),0) -> 39548.205 | N70: =IF(N8=1,Inputs!$E$461*(N68+N69),0) -> 40774.199 | O70: =IF(O8=1,Inputs!$E$461*(O68+O69),0) -> 42038.199 | ... T70: =IF(T8=1,Inputs!$E$461*(T68+T69),0) -> 48970.826
C72: Promoter Loyalty Rebates | H72: =Inputs!$F$756 -> 0 | I72: =Inputs!$G$756 -> 0 | J72: =Inputs!$H$756 -> 208000 | K72: =Inputs!$I$756 -> 366000 | L72: =Inputs!$J$756 -> 372180 | M72: =Inputs!$K$756 -> 454254.48 | N72: =Inputs!$L$756 -> 462122.11 | O72: =Inputs!$M$756 -> 539782.22 | P72: =Inputs!$N$756 -> 641918.3 | Q72: =Inputs!$O$756 -> 654455.85 | R72: =Inputs!$P$756 -> 667369.53 | S72: =Inputs!$Q$756 -> 772004.74 | T72: =Inputs!$R$756 -> 901079.86
C74: Total OPEX | H74: =SUM(H45:H67)+H72 -> 0 | I74: =SUM(I45:I67)+I72 -> 920383.09 | J74: =SUM(J45:J67)+J72 -> 5428826.7 | K74: =SUM(K45:K67)+K72 -> 6176768.3 | L74: =SUM(L45:L67)+L72 -> 6400358.5 | M74: =SUM(M45:M67)+M72 -> 6668534.5 | N74: =SUM(N45:N67)+N72 -> 6864499.9 | O74: =SUM(O45:O67)+O72 -> 7631363.9 | ... T74: =SUM(T45:T67)+T72 -> 8450200.2
C76: EBITDA (before HoldCo Fee) | H76: =IF(H$8=1,H40-H74,0) -> 0 | I76: =IF(I$8=1,I40-I74,0) -> 0 | J76: =IF(J$8=1,J40-J74,0) -> 11174526 | K76: =IF(K$8=1,K40-K74,0) -> 11173832 | L76: =IF(L$8=1,L40-L74,0) -> 11725215 | M76: =IF(M$8=1,M40-M74,0) -> 12603174 | N76: =IF(N$8=1,N40-N74,0) -> 12825139 | O76: =IF(O$8=1,O40-O74,0) -> 12488417 | ... T76: =IF(T$8=1,T40-T74,0) -> 14016377
C77: HoldCo License Fee | J77: =IF(J$8=1,MIN(J$28*Inputs!$E$470+J76*Inputs!$E$471,Inputs!$E$472,MAX(0,Inputs!$E$473-SUM($H77:I77))),0) -> 934172.98 | K77: =IF(K$8=1,MIN(K$28*Inputs!$E$470+K76*Inputs!$E$471,Inputs!$E$472,MAX(0,Inputs!$E$473-SUM($H77:J77))),0) -> 952221.66 | L77: =IF(L$8=1,MIN(L$28*Inputs!$E$470+L76*Inputs!$E$471,Inputs!$E$472,MAX(0,Inputs!$E$473-SUM($H77:K77))),0) -> 998571.17 | M77: =IF(M$8=1,MIN(M$28*Inputs!$E$470+M76*Inputs!$E$471,Inputs!$E$472,MAX(0,Inputs!$E$473-SUM($H77:L77))),0) -> 1000000 | N77: =IF(N$8=1,MIN(N$28*Inputs!$E$470+N76*Inputs!$E$471,Inputs!$E$472,MAX(0,Inputs!$E$473-SUM($H77:M77))),0) -> 1000000 | O77: =IF(O$8=1,MIN(O$28*Inputs!$E$470+O76*Inputs!$E$471,Inputs!$E$472,MAX(0,Inputs!$E$473-SUM($H77:N77))),0) -> 1000000 | P77: =IF(P$8=1,MIN(P$28*Inputs!$E$470+P76*Inputs!$E$471,Inputs!$E$472,MAX(0,Inputs!$E$473-SUM($H77:O77))),0) -> 1000000 | Q77: =IF(Q$8=1,MIN(Q$28*Inputs!$E$470+Q76*Inputs!$E$471,Inputs!$E$472,MAX(0,Inputs!$E$473-SUM($H77:P77))),0) -> 1000000 | ... T77: =IF(T$8=1,MIN(T$28*Inputs!$E$470+T76*Inputs!$E$471,Inputs!$E$472,MAX(0,Inputs!$E$473-SUM($H77:S77))),0) -> 115034.19
B79: EBITDA | H79: =H76-H77 -> 0 | I79: =I76-I77 -> 0 | J79: =J76-J77 -> 10240353 | K79: =K76-K77 -> 10221611 | L79: =L76-L77 -> 10726643 | M79: =M76-M77 -> 11603174 | N79: =N76-N77 -> 11825139 | O79: =O76-O77 -> 11488417 | ... T79: =T76-T77 -> 13901343
C80: EBITDA Margin | H80: =IF(H28=0,"",H79/H28) | I80: =IF(I28=0,"",I79/I28) | J80: =IF(J28=0,"",J79/J28) -> 0.54550241 | K80: =IF(K28=0,"",K79/K28) -> 0.51948311 | L80: =IF(L28=0,"",L79/L28) -> 0.52031879 | M80: =IF(M28=0,"",M79/M28) -> 0.53204494 | N80: =IF(N28=0,"",N79/N28) -> 0.5302573 | O80: =IF(O28=0,"",O79/O28) -> 0.50371632 | ... T80: =IF(T28=0,"",T79/T28) -> 0.54361595
C81: Pre-opening expenses (below EBITDA) | H81: {=IF(H$8=0,INDEX(Cashflow!$D$28:$O$28,MATCH(H$6,Cashflow!$D$7:$O$7,0)),0)} -> 0 | I81: =IF(H$8=0,I74,0) -> 920383.09 | J81: {=IF(J$8=0,INDEX(Cashflow!$D$28:$O$28,MATCH(J$6,Cashflow!$D$7:$O$7,0)),0)} -> 0 | K81: {=IF(K$8=0,INDEX(Cashflow!$D$28:$O$28,MATCH(K$6,Cashflow!$D$7:$O$7,0)),0)} -> 0 | L81: {=IF(L$8=0,INDEX(Cashflow!$D$28:$O$28,MATCH(L$6,Cashflow!$D$7:$O$7,0)),0)} -> 0 | M81: {=IF(M$8=0,INDEX(Cashflow!$D$28:$O$28,MATCH(M$6,Cashflow!$D$7:$O$7,0)),0)} -> 0 | N81: {=IF(N$8=0,INDEX(Cashflow!$D$28:$O$28,MATCH(N$6,Cashflow!$D$7:$O$7,0)),0)} -> 0 | O81: {=IF(O$8=0,INDEX(Cashflow!$D$28:$O$28,MATCH(O$6,Cashflow!$D$7:$O$7,0)),0)} -> 0 | P81: {=IF(P$8=0,INDEX(Cashflow!$D$28:$O$28,MATCH(P$6,Cashflow!$D$7:$O$7,0)),0)} -> 0 | Q81: {=IF(Q$8=0,INDEX(Cashflow!$D$28:$O$28,MATCH(Q$6,Cashflow!$D$7:$O$7,0)),0)} -> 0 | R81: {=IF(R$8=0,INDEX(Cashflow!$D$28:$O$28,MATCH(R$6,Cashflow!$D$7:$O$7,0)),0)} -> 0 | S81: {=IF(S$8=0,INDEX(Cashflow!$D$28:$Q$28,MATCH(S$6,Cashflow!$D$7:$Q$7,0)),0)} -> 0 | T81: {=IF(T$8=0,INDEX(Cashflow!$D$28:$Q$28,MATCH(T$6,Cashflow!$D$7:$Q$7,0)),0)} -> 0
C83: Depreciation | H83: ='Construction Timeline'!E235 -> 0 | I83: ='Construction Timeline'!F235 -> 0 | J83: ='Construction Timeline'!G235 -> 988076.25 | K83: ='Construction Timeline'!H235 -> 988076.25 | L83: ='Construction Timeline'!I235 -> 988076.25 | M83: ='Construction Timeline'!J235 -> 988076.25 | N83: ='Construction Timeline'!K235 -> 988076.25 | O83: ='Construction Timeline'!L235 -> 988076.25 | ... R83: ='Construction Timeline'!O235 -> 988076.25 | S83: ='Construction Timeline'!S235 -> 988076.25 | T83: ='Construction Timeline'!T235 -> 988076.25
B85: EBIT | H85: =H79-H81-H83 -> 0 | I85: =I79-I81-I83 -> -920383.09 | J85: =J79-J81-J83 -> 9252276.9 | K85: =K79-K81-K83 -> 9233534.4 | L85: =L79-L81-L83 -> 9738567.2 | M85: =M79-M81-M83 -> 10615097 | N85: =N79-N81-N83 -> 10837063 | O85: =O79-O81-O83 -> 10500341 | ... T85: =T79-T81-T83 -> 12913266
C87: Net interest expense | G87: =IF(G$8=1,Debt!H57+Debt!H82,0) -> 0 | H87: {=IF(H$8=1,INDEX(Debt!$H$119:$S$119,MATCH(H$6,Debt!$H$14:$S$14,0)),0)} -> 0 | I87: =Debt!J119 -> 543161.6 | J87: {=IF(J$8=1,INDEX(Debt!$H$119:$S$119,MATCH(J$6,Debt!$H$14:$S$14,0)),0)} -> 1050198.2 | K87: {=IF(K$8=1,INDEX(Debt!$H$119:$S$119,MATCH(K$6,Debt!$H$14:$S$14,0)),0)} -> 950693.62 | L87: {=IF(L$8=1,INDEX(Debt!$H$119:$S$119,MATCH(L$6,Debt!$H$14:$S$14,0)),0)} -> 823934.47 | M87: {=IF(M$8=1,INDEX(Debt!$H$119:$S$119,MATCH(M$6,Debt!$H$14:$S$14,0)),0)} -> 697175.33 | N87: {=IF(N$8=1,INDEX(Debt!$H$119:$S$119,MATCH(N$6,Debt!$H$14:$S$14,0)),0)} -> 570416.18 | O87: {=IF(O$8=1,INDEX(Debt!$H$119:$S$119,MATCH(O$6,Debt!$H$14:$S$14,0)),0)} -> 443657.03 | P87: {=IF(P$8=1,INDEX(Debt!$H$119:$S$119,MATCH(P$6,Debt!$H$14:$S$14,0)),0)} -> 316897.88 | Q87: {=IF(Q$8=1,INDEX(Debt!$H$119:$S$119,MATCH(Q$6,Debt!$H$14:$S$14,0)),0)} -> 190138.73 | R87: {=IF(R$8=1,INDEX(Debt!$H$119:$S$119,MATCH(R$6,Debt!$H$14:$S$14,0)),0)} -> 63379.575 | S87: {=IF(S$8=1,INDEX(Debt!$H$119:$U$119,MATCH(S$6,Debt!$H$14:$U$14,0)),0)} -> 0 | T87: {=IF(S$8=1,INDEX(Debt!$H$119:$U$119,MATCH(S$6,Debt!$H$14:$U$14,0)),0)} -> 0
B89: PBT | H89: =H85-H87 -> 0 | I89: =I85-I87 -> -1463544.7 | J89: =J85-J87 -> 8202078.7 | K89: =K85-K87 -> 8282840.7 | L89: =L85-L87 -> 8914632.8 | M89: =M85-M87 -> 9917922.1 | N89: =N85-N87 -> 10266647 | O89: =O85-O87 -> 10056684 | ... T89: =T85-T87 -> 12913266
B91: Tax | C91: Income tax | H91: =IF(H89>0,MAX(0,H89-G92)*Inputs!$E$482,0) -> 0 | I91: =IF(I89>0,MAX(0,I89-H92)*Inputs!$E$482,0) -> 0 | J91: =IF(J89>0,MAX(0,J89-I92)*Inputs!$E$482,0) -> 2021560.2 | K91: =IF(K89>0,MAX(0,K89-J92)*Inputs!$E$482,0) -> 2484852.2 | L91: =IF(L89>0,MAX(0,L89-K92)*Inputs!$E$482,0) -> 2674389.8 | M91: =IF(M89>0,MAX(0,M89-L92)*Inputs!$E$482,0) -> 2975376.6 | N91: =IF(N89>0,MAX(0,N89-M92)*Inputs!$E$482,0) -> 3079994 | O91: =IF(O89>0,MAX(0,O89-N92)*Inputs!$E$482,0) -> 3017005.2 | ... T91: =IF(T89>0,MAX(0,T89-S92)*Inputs!$E$482,0) -> 3873979.9
C92: Tax loss carry-forward (end) | H92: =MAX(0,G92+MAX(0,-H89)-MIN(G92,MAX(0,H89))) -> 0 | I92: =MAX(0,H92+MAX(0,-I89)-MIN(H92,MAX(0,I89))) -> 1463544.7 | J92: =MAX(0,I92+MAX(0,-J89)-MIN(I92,MAX(0,J89))) -> 0 | K92: =MAX(0,J92+MAX(0,-K89)-MIN(J92,MAX(0,K89))) -> 0 | L92: =MAX(0,K92+MAX(0,-L89)-MIN(K92,MAX(0,L89))) -> 0 | M92: =MAX(0,L92+MAX(0,-M89)-MIN(L92,MAX(0,M89))) -> 0 | N92: =MAX(0,M92+MAX(0,-N89)-MIN(M92,MAX(0,N89))) -> 0 | O92: =MAX(0,N92+MAX(0,-O89)-MIN(N92,MAX(0,O89))) -> 0 | ... R92: =MAX(0,Q92+MAX(0,-R89)-MIN(Q92,MAX(0,R89))) -> 0
B95: NPAT | C95: Net profit after tax | H95: =H89-H91 -> 0 | I95: =I89-I91 -> -1463544.7 | J95: =J89-J91 -> 6180518.5 | K95: =K89-K91 -> 5797988.5 | L95: =L89-L91 -> 6240242.9 | M95: =M89-M91 -> 6942545.4 | N95: =N89-N91 -> 7186652.7 | O95: =O89-O91 -> 7039678.9 | ... T95: =T89-T91 -> 9039286.5
C96: NPAT % | I96: =IF(I28>0,I95/I28,"NA") -> NA | J96: =IF(J28>0,J95/J28,"NA") -> 0.3292355 | K96: =IF(K28>0,K95/K28,"NA") -> 0.29466561 | L96: =IF(L28>0,L95/L28,"NA") -> 0.30269634 | M96: =IF(M28>0,M95/M28,"NA") -> 0.3183393 | N96: =IF(N28>0,N95/N28,"NA") -> 0.32226048 | O96: =IF(O28>0,O95/O28,"NA") -> 0.3086588 | P96: =IF(P28>0,P95/P28,"NA") -> 0.30791736 | ... T96: =IF(T28>0,T95/T28,"NA") -> 0.35348387
B97: COMMUNITY FUND CALCULATION | I97: ($1,463,545) | J97: $6,468,368 | K97: $6,092,158 | L97: $6,548,705 | M97: $7,225,218 | N97: $7,461,219 | O97: $7,317,771 | P97: $7,456,118 | Q97: $7,688,934 | R97: $7,925,696 | S97: $8,060,127 | T97: $8,646,463
C98: Total Tickets Sold | J98: ='Calendar Assumptions'!F53 -> 406491.1 | K98: ='Calendar Assumptions'!G53 -> 415120.52 | L98: ='Calendar Assumptions'!H53 -> 423749.94 | M98: ='Calendar Assumptions'!I53 -> 454180 | N98: ='Calendar Assumptions'!J53 -> 454180 | O98: ='Calendar Assumptions'!K53 -> 454180 | P98: ='Calendar Assumptions'!L53 -> 454180 | Q98: ='Calendar Assumptions'!M53 -> 454180 | ... T98: ='Calendar Assumptions'!P53 -> 454180
C99: Community Fund Contribution per Ticket | H99: =Inputs!$E$722 -> 0.25 | I99: =Inputs!$E$722 -> 0.25 | J99: =Inputs!$E$722 -> 0.25 | K99: =Inputs!$E$722 -> 0.25 | L99: =Inputs!$E$722 -> 0.25 | M99: =Inputs!$E$722 -> 0.25 | N99: =Inputs!$E$722 -> 0.25 | O99: =Inputs!$E$722 -> 0.25 | ... T99: =Inputs!$E$722 -> 0.25
C100: Community Fund Allocation | H100: =H98*H99 -> 0 | I100: =I98*I99 -> 0 | J100: =J98*J99 -> 101622.77 | K100: =K98*K99 -> 103780.13 | L100: =L98*L99 -> 105937.49 | M100: =M98*M99 -> 113545 | N100: =N98*N99 -> 113545 | O100: =O98*O99 -> 113545 | ... T100: =T98*T99 -> 113545
B102: Transfer to Community Fund | H102: =H100 -> 0 | I102: =I100 -> 0 | J102: =J100 -> 101622.77 | K102: =K100 -> 103780.13 | L102: =L100 -> 105937.49 | M102: =M100 -> 113545 | N102: =N100 -> 113545 | O102: =O100 -> 113545 | ... T102: =T100 -> 113545
B105: Dividends | H105: =IF((Cashflow!E23+SUM(Cashflow!E27:E32)+Cashflow!E34+'Balance Sheet'!F10+Inputs!E802)>Inputs!E802,IF(H95>0,Inputs!$E$486*H95+Cashflow!E36,0),0) -> 0 | I105: =IF((Cashflow!F23+SUM(Cashflow!F27:F32)+Cashflow!F34+'Balance Sheet'!G10+Inputs!F802)>Inputs!F802,IF(I95>0,Inputs!$E$486*I95+Cashflow!F36,0),0) -> 0 | J105: =IF((Cashflow!G23+SUM(Cashflow!G27:G32)+Cashflow!G34+'Balance Sheet'!H10+Inputs!G802)>Inputs!G802,IF(J95>0,Inputs!$E$486*J95+Cashflow!G36,0),0) -> 3847688.2 | K105: =IF((Cashflow!H23+SUM(Cashflow!H27:H32)+Cashflow!H34+'Balance Sheet'!I10+Inputs!H802)>Inputs!H802,IF(K95>0,Inputs!$E$486*K95+Cashflow!H36,0),0) -> 4625550.2 | L105: =IF((Cashflow!I23+SUM(Cashflow!I27:I32)+Cashflow!I34+'Balance Sheet'!J10+Inputs!I802)>Inputs!I802,IF(L95>0,Inputs!$E$486*L95+Cashflow!I36,0),0) -> 4933391.9 | M105: =IF((Cashflow!J23+SUM(Cashflow!J27:J32)+Cashflow!J34+'Balance Sheet'!K10+Inputs!J802)>Inputs!J802,IF(M95>0,Inputs!$E$486*M95+Cashflow!J36,0),0) -> 5478014.2 | N105: =IF((Cashflow!K23+SUM(Cashflow!K27:K32)+Cashflow!K34+'Balance Sheet'!L10+Inputs!K802)>Inputs!K802,IF(N95>0,Inputs!$E$486*N95+Cashflow!K36,0),0) -> 5724980.5 | O105: =IF((Cashflow!L23+SUM(Cashflow!L27:L32)+Cashflow!L34+'Balance Sheet'!M10+Inputs!L802)>Inputs!L802,IF(O95>0,Inputs!$E$486*O95+Cashflow!L36,0),0) -> 5653138 | ... T105: =IF((Cashflow!Q23+SUM(Cashflow!Q27:Q32)+Cashflow!Q34+'Balance Sheet'!R10+Inputs!Q802)>Inputs!Q802,IF(T95>0,Inputs!$E$486*T95+Cashflow!Q36,0),0) -> 7152677.1
A108: Debt Service Coverage Ratio | B108: DSCR | H108: =IF((H112+H113)=0,"",(H109-H111)/ABS(H112+H113)) | I108: =IF((I112+I113)=0,"",(I109-I111)/ABS(I112+I113)) -> 0 | J108: =IF((J112+J113)=0,"",(J109-J111+J110)/ABS(J112+J113)) -> 3.748065 | K108: =IF((K112+K113)=0,"",(K109-K111+K110)/ABS(K112+K113)) -> 3.0466904 | L108: =IF((L112+L113)=0,"",(L109-L111+L110)/ABS(L112+L113)) -> 3.3189554 | M108: =IF((M112+M113)=0,"",(M109-M111+M110)/ABS(M112+M113)) -> 3.7480419 | N108: =IF((N112+N113)=0,"",(N109-N111+N110)/ABS(N112+N113)) -> 4.0469539 | O108: =IF((O112+O113)=0,"",(O109-O111+O110)/ABS(O112+O113)) -> 4.1874724 | P108: =IF((P112+P113)=0,"",(P109-P111+P110)/ABS(P112+P113)) -> 4.457472 | Q108: =IF((Q112+Q113)=0,"",(Q109-Q111+Q110)/ABS(Q112+Q113)) -> 4.8337591 | ... T108: =IF((T112+T113)=0,"",(T109-T111+T110)/ABS(T112+T113))
C109: EBITDA (Less Taxes) | H109: =H79-H91 -> 0 | I109: =I79-I91 -> 0 | J109: =J79-J91 -> 8218793 | K109: =K79-K91 -> 7736758.4 | L109: =L79-L91 -> 8052253.7 | M109: =M79-M91 -> 8627797 | N109: =N79-N91 -> 8745145.1 | O109: =O79-O91 -> 8471412.1 | ... T109: =T79-T91 -> 10027363
C110: Net Working Capital Adjustment | H110: =Cashflow!E36 -> 0 | I110: =Cashflow!F36 -> 0 | J110: =Cashflow!G36 -> -1096726.6 | K110: =Cashflow!H36 -> -12840.594 | L110: =Cashflow!I36 -> -58802.416 | M110: =Cashflow!J36 -> -76022.193 | N110: =Cashflow!K36 -> -24341.653 | O110: =Cashflow!L36 -> 21394.902 | ... T110: =Cashflow!Q36 -> -78752.097
C111: Capex | I111: =IF(I8=1,-I28*Inputs!$E$462*Scenarios!$B$10,0) -> 0 | J111: =Cashflow!G27 -> 0 | K111: =Cashflow!H27 -> 0 | L111: =Cashflow!I27 -> 0 | M111: =Cashflow!J27 -> 0 | N111: =Cashflow!K27 -> 0 | O111: =Cashflow!L27 -> 0 | P111: =Cashflow!M27 -> 0 | Q111: =Cashflow!N27 -> 0 | ... T111: =Cashflow!Q27 -> 0
C112: Principal | H112: {=INDEX(Debt!$H$56:$S$56,MATCH(H$6,Debt!$H$14:$S$14,0))} -> 0 | I112: {=INDEX(Debt!$H$56:$S$56,MATCH(I$6,Debt!$H$14:$S$14,0))} -> 0 | J112: {=INDEX(Debt!$H$118:$U$118,MATCH(J$6,Debt!$H$14:$U$14,0))} -> 850000 | K112: {=INDEX(Debt!$H$118:$U$118,MATCH(K$6,Debt!$H$14:$U$14,0))} -> 1584489.4 | L112: {=INDEX(Debt!$H$118:$U$118,MATCH(L$6,Debt!$H$14:$U$14,0))} -> 1584489.4 | M112: {=INDEX(Debt!$H$118:$U$118,MATCH(M$6,Debt!$H$14:$U$14,0))} -> 1584489.4 | N112: {=INDEX(Debt!$H$118:$U$118,MATCH(N$6,Debt!$H$14:$U$14,0))} -> 1584489.4 | O112: {=INDEX(Debt!$H$118:$U$118,MATCH(O$6,Debt!$H$14:$U$14,0))} -> 1584489.4 | P112: {=INDEX(Debt!$H$118:$U$118,MATCH(P$6,Debt!$H$14:$U$14,0))} -> 1584489.4 | Q112: {=INDEX(Debt!$H$118:$U$118,MATCH(Q$6,Debt!$H$14:$U$14,0))} -> 1584489.4 | ... T112: {=INDEX(Debt!$H$118:$U$118,MATCH(T$6,Debt!$H$14:$U$14,0))} -> 0
C113: Interest | H113: {=INDEX(Debt!$H$57:$S$57,MATCH(H$6,Debt!$H$14:$S$14,0))} -> 0 | I113: {=INDEX(Debt!$H$119:$U$119,MATCH(I$6,Debt!$H$14:$U$14,0))} -> 543161.6 | J113: {=INDEX(Debt!$H$119:$U$119,MATCH(J$6,Debt!$H$14:$U$14,0))} -> 1050198.2 | K113: {=INDEX(Debt!$H$119:$U$119,MATCH(K$6,Debt!$H$14:$U$14,0))} -> 950693.62 | L113: {=INDEX(Debt!$H$119:$U$119,MATCH(L$6,Debt!$H$14:$U$14,0))} -> 823934.47 | M113: {=INDEX(Debt!$H$119:$U$119,MATCH(M$6,Debt!$H$14:$U$14,0))} -> 697175.33 | N113: {=INDEX(Debt!$H$119:$U$119,MATCH(N$6,Debt!$H$14:$U$14,0))} -> 570416.18 | O113: {=INDEX(Debt!$H$119:$U$119,MATCH(O$6,Debt!$H$14:$U$14,0))} -> 443657.03 | P113: {=INDEX(Debt!$H$119:$U$119,MATCH(P$6,Debt!$H$14:$U$14,0))} -> 316897.88 | ... T113: {=INDEX(Debt!$H$119:$U$119,MATCH(T$6,Debt!$H$14:$U$14,0))} -> 0
A116: CHECKS ONLY FOR REFERENCE
C120: Check | D120: Overall | G120: =G6 -> FY25 | H120: =H6 -> FY26 | I120: =I6 -> FY27 | J120: =J6 -> FY28 | K120: =K6 -> FY29 | L120: =L6 -> FY30 | M120: =M6 -> FY31 | N120: =N6 -> FY32 | ... T120: =T6 -> FY38
B121: REVENUE
C122: VHA | D122: {=IF(SUMPRODUCT(ABS(G122:R122))<1,0,SUMPRODUCT(ABS(G122:R122)))} -> 0 | G122: {=G14-IF(G$8=1,IFERROR(INDEX('Revenue Assumptions'!$F$108:$P$108,MATCH(G$6,'Revenue Assumptions'!$F$34:$P$34,0))*Scenarios!$B$6,0),0)} -> 0 | H122: {=H14-IF(H$8=1,IFERROR(INDEX('Revenue Assumptions'!$F$108:$P$108,MATCH(H$6,'Revenue Assumptions'!$F$34:$P$34,0))*Scenarios!$B$6,0),0)} -> 0 | I122: {=I14-IF(I$8=1,IFERROR(INDEX('Revenue Assumptions'!$F$108:$P$108,MATCH(I$6,'Revenue Assumptions'!$F$34:$P$34,0))*Scenarios!$B$6,0),0)} -> 0 | J122: {=J14-IF(J$8=1,IFERROR(INDEX('Revenue Assumptions'!$F$108:$P$108,MATCH(J$6,'Revenue Assumptions'!$F$34:$P$34,0))*Scenarios!$B$6,0),0)} -> 0 | K122: {=K14-IF(K$8=1,IFERROR(INDEX('Revenue Assumptions'!$F$108:$P$108,MATCH(K$6,'Revenue Assumptions'!$F$34:$P$34,0))*Scenarios!$B$6,0),0)} -> 0 | L122: {=L14-IF(L$8=1,IFERROR(INDEX('Revenue Assumptions'!$F$108:$P$108,MATCH(L$6,'Revenue Assumptions'!$F$34:$P$34,0))*Scenarios!$B$6,0),0)} -> 0 | M122: {=M14-IF(M$8=1,IFERROR(INDEX('Revenue Assumptions'!$F$108:$P$108,MATCH(M$6,'Revenue Assumptions'!$F$34:$P$34,0))*Scenarios!$B$6,0),0)} -> 0 | N122: {=N14-IF(N$8=1,IFERROR(INDEX('Revenue Assumptions'!$F$108:$P$108,MATCH(N$6,'Revenue Assumptions'!$F$34:$P$34,0))*Scenarios!$B$6,0),0)} -> 0 | ... T122: {=T14-IF(T$8=1,IFERROR(INDEX('Revenue Assumptions'!$F$108:$P$108,MATCH(T$6,'Revenue Assumptions'!$F$34:$P$34,0))*Scenarios!$B$6,0),0)} -> 0
C123: Premium Sales | D123: {=IF(SUMPRODUCT(ABS(G123:R123))<1,0,SUMPRODUCT(ABS(G123:R123)))} -> 0 | G123: {=G15-IF(G$8=1,IFERROR(INDEX('Revenue Assumptions'!$F$124:$P$124,MATCH(G$6,'Revenue Assumptions'!$F$34:$P$34,0))*Scenarios!$B$6,0),0)} -> 0 | H123: {=H15-IF(H$8=1,IFERROR(INDEX('Revenue Assumptions'!$F$124:$P$124,MATCH(H$6,'Revenue Assumptions'!$F$34:$P$34,0))*Scenarios!$B$6,0),0)} -> 0 | I123: {=I15-IF(I$8=1,IFERROR(INDEX('Revenue Assumptions'!$F$124:$P$124,MATCH(I$6,'Revenue Assumptions'!$F$34:$P$34,0))*Scenarios!$B$6,0),0)} -> 0 | J123: {=J15-IF(J$8=1,IFERROR(INDEX('Revenue Assumptions'!$F$124:$P$124,MATCH(J$6,'Revenue Assumptions'!$F$34:$P$34,0))*Scenarios!$B$6,0),0)} -> 0 | K123: {=K15-IF(K$8=1,IFERROR(INDEX('Revenue Assumptions'!$F$124:$P$124,MATCH(K$6,'Revenue Assumptions'!$F$34:$P$34,0))*Scenarios!$B$6,0),0)} -> 0 | L123: {=L15-IF(L$8=1,IFERROR(INDEX('Revenue Assumptions'!$F$124:$P$124,MATCH(L$6,'Revenue Assumptions'!$F$34:$P$34,0))*Scenarios!$B$6,0),0)} -> 0 | M123: {=M15-IF(M$8=1,IFERROR(INDEX('Revenue Assumptions'!$F$124:$P$124,MATCH(M$6,'Revenue Assumptions'!$F$34:$P$34,0))*Scenarios!$B$6,0),0)} -> 0 | N123: {=N15-IF(N$8=1,IFERROR(INDEX('Revenue Assumptions'!$F$124:$P$124,MATCH(N$6,'Revenue Assumptions'!$F$34:$P$34,0))*Scenarios!$B$6,0),0)} -> 0 | ... T123: {=T15-IF(T$8=1,IFERROR(INDEX('Revenue Assumptions'!$F$124:$P$124,MATCH(T$6,'Revenue Assumptions'!$F$34:$P$34,0))*Scenarios!$B$6,0),0)} -> 0
C124: Premium F&B | D124: {=IF(SUMPRODUCT(ABS(G124:R124))<1,0,SUMPRODUCT(ABS(G124:R124)))} -> 0 | G124: {=G16-IF(G$8=1,IFERROR(INDEX('Revenue Assumptions'!$F$159:$P$159,MATCH(G$6,'Revenue Assumptions'!$F$34:$P$34,0))*Scenarios!$B$6,0),0)} -> 0 | H124: {=H16-IF(H$8=1,IFERROR(INDEX('Revenue Assumptions'!$F$159:$P$159,MATCH(H$6,'Revenue Assumptions'!$F$34:$P$34,0))*Scenarios!$B$6,0),0)} -> 0 | I124: {=I16-IF(I$8=1,IFERROR(INDEX('Revenue Assumptions'!$F$159:$P$159,MATCH(I$6,'Revenue Assumptions'!$F$34:$P$34,0))*Scenarios!$B$6,0),0)} -> 0 | J124: {=J16-IF(J$8=1,IFERROR(INDEX('Revenue Assumptions'!$F$159:$P$159,MATCH(J$6,'Revenue Assumptions'!$F$34:$P$34,0))*Scenarios!$B$6,0),0)} -> 0 | K124: {=K16-IF(K$8=1,IFERROR(INDEX('Revenue Assumptions'!$F$159:$P$159,MATCH(K$6,'Revenue Assumptions'!$F$34:$P$34,0))*Scenarios!$B$6,0),0)} -> 0 | L124: {=L16-IF(L$8=1,IFERROR(INDEX('Revenue Assumptions'!$F$159:$P$159,MATCH(L$6,'Revenue Assumptions'!$F$34:$P$34,0))*Scenarios!$B$6,0),0)} -> 0 | M124: {=M16-IF(M$8=1,IFERROR(INDEX('Revenue Assumptions'!$F$159:$P$159,MATCH(M$6,'Revenue Assumptions'!$F$34:$P$34,0))*Scenarios!$B$6,0),0)} -> 0 | N124: {=N16-IF(N$8=1,IFERROR(INDEX('Revenue Assumptions'!$F$159:$P$159,MATCH(N$6,'Revenue Assumptions'!$F$34:$P$34,0))*Scenarios!$B$6,0),0)} -> 0 | ... T124: {=T16-IF(T$8=1,IFERROR(INDEX('Revenue Assumptions'!$F$159:$P$159,MATCH(T$6,'Revenue Assumptions'!$F$34:$P$34,0))*Scenarios!$B$6,0),0)} -> 0
C125: F&B | D125: {=IF(SUMPRODUCT(ABS(G125:R125))<1,0,SUMPRODUCT(ABS(G125:R125)))} -> 0 | G125: {=G17-IF(G$8=1,IFERROR(INDEX('Revenue Assumptions'!$F$141:$P$141,MATCH(G$6,'Revenue Assumptions'!$F$34:$P$34,0))*Scenarios!$B$6,0),0)} -> 0 | H125: {=H17-IF(H$8=1,IFERROR(INDEX('Revenue Assumptions'!$F$141:$P$141,MATCH(H$6,'Revenue Assumptions'!$F$34:$P$34,0))*Scenarios!$B$6,0),0)} -> 0 | I125: {=I17-IF(I$8=1,IFERROR(INDEX('Revenue Assumptions'!$F$141:$P$141,MATCH(I$6,'Revenue Assumptions'!$F$34:$P$34,0))*Scenarios!$B$6,0),0)} -> 0 | J125: {=J17-IF(J$8=1,IFERROR(INDEX('Revenue Assumptions'!$F$141:$P$141,MATCH(J$6,'Revenue Assumptions'!$F$34:$P$34,0))*Scenarios!$B$6,0),0)} -> 0 | K125: {=K17-IF(K$8=1,IFERROR(INDEX('Revenue Assumptions'!$F$141:$P$141,MATCH(K$6,'Revenue Assumptions'!$F$34:$P$34,0))*Scenarios!$B$6,0),0)} -> 0 | L125: {=L17-IF(L$8=1,IFERROR(INDEX('Revenue Assumptions'!$F$141:$P$141,MATCH(L$6,'Revenue Assumptions'!$F$34:$P$34,0))*Scenarios!$B$6,0),0)} -> 0 | M125: {=M17-IF(M$8=1,IFERROR(INDEX('Revenue Assumptions'!$F$141:$P$141,MATCH(M$6,'Revenue Assumptions'!$F$34:$P$34,0))*Scenarios!$B$6,0),0)} -> 0 | N125: {=N17-IF(N$8=1,IFERROR(INDEX('Revenue Assumptions'!$F$141:$P$141,MATCH(N$6,'Revenue Assumptions'!$F$34:$P$34,0))*Scenarios!$B$6,0),0)} -> 0 | ... T125: {=T17-IF(T$8=1,IFERROR(INDEX('Revenue Assumptions'!$F$141:$P$141,MATCH(T$6,'Revenue Assumptions'!$F$34:$P$34,0))*Scenarios!$B$6,0),0)} -> 0
C126: Sponsorship | D126: {=IF(SUMPRODUCT(ABS(G126:R126))<1,0,SUMPRODUCT(ABS(G126:R126)))} -> 0 | G126: {=G24-IF(G$8=1,IFERROR(INDEX('Revenue Assumptions'!$F$175:$P$175,MATCH(G$6,'Revenue Assumptions'!$F$34:$P$34,0))*Scenarios!$B$6,0),0)} -> 0 | H126: {=H24-IF(H$8=1,IFERROR(INDEX('Revenue Assumptions'!$F$175:$P$175,MATCH(H$6,'Revenue Assumptions'!$F$34:$P$34,0))*Scenarios!$B$6,0),0)} -> 0 | I126: {=I24-IF(I$8=1,IFERROR(INDEX('Revenue Assumptions'!$F$175:$P$175,MATCH(I$6,'Revenue Assumptions'!$F$34:$P$34,0))*Scenarios!$B$6,0),0)} -> 0 | J126: {=J24-IF(J$8=1,IFERROR(INDEX('Revenue Assumptions'!$F$175:$P$175,MATCH(J$6,'Revenue Assumptions'!$F$34:$P$34,0))*Scenarios!$B$6,0),0)} -> 0 | K126: {=K24-IF(K$8=1,IFERROR(INDEX('Revenue Assumptions'!$F$175:$P$175,MATCH(K$6,'Revenue Assumptions'!$F$34:$P$34,0))*Scenarios!$B$6,0),0)} -> 0 | L126: {=L24-IF(L$8=1,IFERROR(INDEX('Revenue Assumptions'!$F$175:$P$175,MATCH(L$6,'Revenue Assumptions'!$F$34:$P$34,0))*Scenarios!$B$6,0),0)} -> 0 | M126: {=M24-IF(M$8=1,IFERROR(INDEX('Revenue Assumptions'!$F$175:$P$175,MATCH(M$6,'Revenue Assumptions'!$F$34:$P$34,0))*Scenarios!$B$6,0),0)} -> 0 | N126: {=N24-IF(N$8=1,IFERROR(INDEX('Revenue Assumptions'!$F$175:$P$175,MATCH(N$6,'Revenue Assumptions'!$F$34:$P$34,0))*Scenarios!$B$6,0),0)} -> 0 | ... T126: {=T24-IF(T$8=1,IFERROR(INDEX('Revenue Assumptions'!$F$175:$P$175,MATCH(T$6,'Revenue Assumptions'!$F$34:$P$34,0))*Scenarios!$B$6,0),0)} -> 0
C127: Advertising | D127: {=IF(SUMPRODUCT(ABS(G127:R127))<1,0,SUMPRODUCT(ABS(G127:R127)))} -> 0 | G127: {=G25-IF(G$8=1,IFERROR(INDEX('Revenue Assumptions'!$F$183:$P$183,MATCH(G$6,'Revenue Assumptions'!$F$34:$P$34,0))*Scenarios!$B$6,0),0)} -> 0 | H127: {=H25-IF(H$8=1,IFERROR(INDEX('Revenue Assumptions'!$F$183:$P$183,MATCH(H$6,'Revenue Assumptions'!$F$34:$P$34,0))*Scenarios!$B$6,0),0)} -> 0 | I127: {=I25-IF(I$8=1,IFERROR(INDEX('Revenue Assumptions'!$F$183:$P$183,MATCH(I$6,'Revenue Assumptions'!$F$34:$P$34,0))*Scenarios!$B$6,0),0)} -> 0 | J127: {=J25-IF(J$8=1,IFERROR(INDEX('Revenue Assumptions'!$F$183:$P$183,MATCH(J$6,'Revenue Assumptions'!$F$34:$P$34,0))*Scenarios!$B$6,0),0)} -> 0 | K127: {=K25-IF(K$8=1,IFERROR(INDEX('Revenue Assumptions'!$F$183:$P$183,MATCH(K$6,'Revenue Assumptions'!$F$34:$P$34,0))*Scenarios!$B$6,0),0)} -> 0 | L127: {=L25-IF(L$8=1,IFERROR(INDEX('Revenue Assumptions'!$F$183:$P$183,MATCH(L$6,'Revenue Assumptions'!$F$34:$P$34,0))*Scenarios!$B$6,0),0)} -> 0 | M127: {=M25-IF(M$8=1,IFERROR(INDEX('Revenue Assumptions'!$F$183:$P$183,MATCH(M$6,'Revenue Assumptions'!$F$34:$P$34,0))*Scenarios!$B$6,0),0)} -> 0 | N127: {=N25-IF(N$8=1,IFERROR(INDEX('Revenue Assumptions'!$F$183:$P$183,MATCH(N$6,'Revenue Assumptions'!$F$34:$P$34,0))*Scenarios!$B$6,0),0)} -> 0 | ... T127: {=T25-IF(T$8=1,IFERROR(INDEX('Revenue Assumptions'!$F$183:$P$183,MATCH(T$6,'Revenue Assumptions'!$F$34:$P$34,0))*Scenarios!$B$6,0),0)} -> 0
C128: Merchandise | D128: {=IF(SUMPRODUCT(ABS(G128:R128))<1,0,SUMPRODUCT(ABS(G128:R128)))} -> 0 | G128: {=G18-IF(G$8=1,IFERROR(INDEX('Calendar Assumptions'!$F$54:$P$54,MATCH(G$6,'Calendar Assumptions'!$F$4:$P$4,0))*Inputs!$E$360*Scenarios!$B$6,0),0)} -> 0 | H128: {=H18-IF(H$8=1,IFERROR(INDEX('Calendar Assumptions'!$F$54:$P$54,MATCH(H$6,'Calendar Assumptions'!$F$4:$P$4,0))*Inputs!$E$360*Scenarios!$B$6,0),0)} -> 0 | I128: {=I18-IF(I$8=1,IFERROR(INDEX('Calendar Assumptions'!$F$54:$P$54,MATCH(I$6,'Calendar Assumptions'!$F$4:$P$4,0))*Inputs!$E$360*Scenarios!$B$6,0),0)} -> 0 | J128: {=J18-IF(J$8=1,IFERROR(INDEX('Calendar Assumptions'!$F$54:$P$54,MATCH(J$6,'Calendar Assumptions'!$F$4:$P$4,0))*Inputs!$E$360*Scenarios!$B$6,0),0)} -> 0 | K128: {=K18-IF(K$8=1,IFERROR(INDEX('Calendar Assumptions'!$F$54:$P$54,MATCH(K$6,'Calendar Assumptions'!$F$4:$P$4,0))*Inputs!$E$360*Scenarios!$B$6,0),0)} -> 0 | L128: {=L18-IF(L$8=1,IFERROR(INDEX('Calendar Assumptions'!$F$54:$P$54,MATCH(L$6,'Calendar Assumptions'!$F$4:$P$4,0))*Inputs!$E$360*Scenarios!$B$6,0),0)} -> 0 | M128: {=M18-IF(M$8=1,IFERROR(INDEX('Calendar Assumptions'!$F$54:$P$54,MATCH(M$6,'Calendar Assumptions'!$F$4:$P$4,0))*Inputs!$E$360*Scenarios!$B$6,0),0)} -> 0 | N128: {=N18-IF(N$8=1,IFERROR(INDEX('Calendar Assumptions'!$F$54:$P$54,MATCH(N$6,'Calendar Assumptions'!$F$4:$P$4,0))*Inputs!$E$360*Scenarios!$B$6,0),0)} -> 0 | ... T128: {=T18-IF(T$8=1,IFERROR(INDEX('Calendar Assumptions'!$F$54:$P$54,MATCH(T$6,'Calendar Assumptions'!$F$4:$P$4,0))*Inputs!$E$360*Scenarios!$B$6,0),0)} -> 0
...

Sheet Balance Sheet
A1: Balance Sheet
A2: THE BEND Live House
B4: FY Start | F4: ='P&L'!G4 -> 45689 | G4: ='P&L'!H4 -> 45839 | H4: ='P&L'!I4 -> 46204 | I4: ='P&L'!J4 -> 46569 | J4: ='P&L'!K4 -> 46935 | K4: ='P&L'!L4 -> 47300 | L4: ='P&L'!M4 -> 47665 | M4: ='P&L'!N4 -> 48030 | ... S4: ='P&L'!T4 -> 50222
B5: FY End | F5: ='P&L'!G5 -> 45838 | G5: ='P&L'!H5 -> 46203 | H5: ='P&L'!I5 -> 46568 | I5: ='P&L'!J5 -> 46934 | J5: ='P&L'!K5 -> 47299 | K5: ='P&L'!L5 -> 47664 | L5: ='P&L'!M5 -> 48029 | M5: ='P&L'!N5 -> 48395 | ... S5: ='P&L'!T5 -> 50586
B6: Year | F6: ='P&L'!G6 -> FY25 | G6: ='P&L'!H6 -> FY26 | H6: ='P&L'!I6 -> FY27 | I6: ='P&L'!J6 -> FY28 | J6: ='P&L'!K6 -> FY29 | K6: ='P&L'!L6 -> FY30 | L6: ='P&L'!M6 -> FY31 | M6: ='P&L'!N6 -> FY32 | ... S6: ='P&L'!T6 -> FY38
B8: ASSETS
C9: Current Assets
D10: Cash | F10: =Cashflow!D38 -> 0 | G10: =Cashflow!E38 -> 0 | H10: =Cashflow!F38 -> 452228.4 | I10: =Cashflow!G38 -> 1724785.6 | J10: =Cashflow!H38 -> 2184190 | K10: =Cashflow!I38 -> 2729888 | L10: =Cashflow!J38 -> 3408439 | M10: =Cashflow!K38 -> 4135811.4 | ... S10: =Cashflow!Q38 -> 12278575
D11: Community Fund Reserve (Restricted Cash) | F11: 0 | G11: =F11 -> 0 | H11: {=G11-INDEX(Cashflow!$D$34:$O$34,MATCH(H$6,Cashflow!$D$7:$O$7,0))} -> 0 | I11: {=H11-INDEX(Cashflow!$D$34:$O$34,MATCH(I$6,Cashflow!$D$7:$O$7,0))} -> 101622.77 | J11: {=I11-INDEX(Cashflow!$D$34:$O$34,MATCH(J$6,Cashflow!$D$7:$O$7,0))} -> 205402.9 | K11: {=J11-INDEX(Cashflow!$D$34:$O$34,MATCH(K$6,Cashflow!$D$7:$O$7,0))} -> 311340.39 | L11: {=K11-INDEX(Cashflow!$D$34:$O$34,MATCH(L$6,Cashflow!$D$7:$O$7,0))} -> 424885.39 | M11: {=L11-INDEX(Cashflow!$D$34:$O$34,MATCH(M$6,Cashflow!$D$7:$O$7,0))} -> 538430.39 | N11: {=M11-INDEX(Cashflow!$D$34:$O$34,MATCH(N$6,Cashflow!$D$7:$O$7,0))} -> 651975.39 | O11: {=N11-INDEX(Cashflow!$D$34:$O$34,MATCH(O$6,Cashflow!$D$7:$O$7,0))} -> 765520.39 | ... Q11: {=P11-INDEX(Cashflow!$D$34:$O$34,MATCH(Q$6,Cashflow!$D$7:$O$7,0))} -> 992610.39 | R11: {=Q11-INDEX(Cashflow!$D$34:$Q$34,MATCH(R$6,Cashflow!$D$7:$Q$7,0))} -> 1106155.4 | S11: {=R11-INDEX(Cashflow!$D$34:$Q$34,MATCH(S$6,Cashflow!$D$7:$Q$7,0))} -> 1219700.4
D12: Accounts receivable | F12: {=INDEX(Cashflow!$D$53:$O$53,MATCH(F$6,Cashflow!$D$43:$O$43,0))} -> 0 | G12: {=INDEX(Cashflow!$D$53:$O$53,MATCH(G$6,Cashflow!$D$43:$O$43,0))} -> 0 | H12: {=INDEX(Cashflow!$D$53:$O$53,MATCH(H$6,Cashflow!$D$43:$O$43,0))} -> 0 | I12: {=INDEX(Cashflow!$D$53:$O$53,MATCH(I$6,Cashflow!$D$43:$O$43,0))} -> 1542931.5 | J12: {=INDEX(Cashflow!$D$53:$O$53,MATCH(J$6,Cashflow!$D$43:$O$43,0))} -> 1617246.8 | K12: {=INDEX(Cashflow!$D$53:$O$53,MATCH(K$6,Cashflow!$D$43:$O$43,0))} -> 1694426.5 | L12: {=INDEX(Cashflow!$D$53:$O$53,MATCH(L$6,Cashflow!$D$43:$O$43,0))} -> 1792490.5 | M12: {=INDEX(Cashflow!$D$53:$O$53,MATCH(M$6,Cashflow!$D$43:$O$43,0))} -> 1832938.9 | ... Q12: {=INDEX(Cashflow!$D$53:$O$53,MATCH(Q$6,Cashflow!$D$43:$O$43,0))} -> 2006953.2 | R12: {=INDEX(Cashflow!$D$53:$Q$53,MATCH(R$6,Cashflow!$D$43:$Q$43,0))} -> 2053694.4 | S12: {=INDEX(Cashflow!$D$53:$Q$53,MATCH(S$6,Cashflow!$D$43:$Q$43,0))} -> 2101807.5
D13: Inventory | F13: {=INDEX(Cashflow!$D$54:$O$54,MATCH(F$6,Cashflow!$D$43:$O$43,0))} -> 0 | G13: {=INDEX(Cashflow!$D$54:$O$54,MATCH(G$6,Cashflow!$D$43:$O$43,0))} -> 0 | H13: {=INDEX(Cashflow!$D$54:$O$54,MATCH(H$6,Cashflow!$D$43:$O$43,0))} -> 0 | I13: {=INDEX(Cashflow!$D$54:$O$54,MATCH(I$6,Cashflow!$D$43:$O$43,0))} -> 178272.38 | J13: {=INDEX(Cashflow!$D$54:$O$54,MATCH(J$6,Cashflow!$D$43:$O$43,0))} -> 191170 | K13: {=INDEX(Cashflow!$D$54:$O$54,MATCH(K$6,Cashflow!$D$43:$O$43,0))} -> 204653.32 | L13: {=INDEX(Cashflow!$D$54:$O$54,MATCH(L$6,Cashflow!$D$43:$O$43,0))} -> 208514.5 | M13: {=INDEX(Cashflow!$D$54:$O$54,MATCH(M$6,Cashflow!$D$43:$O$43,0))} -> 214612.42 | ... Q13: {=INDEX(Cashflow!$D$54:$O$54,MATCH(Q$6,Cashflow!$D$43:$O$43,0))} -> 240889.17 | R13: {=INDEX(Cashflow!$D$54:$Q$54,MATCH(R$6,Cashflow!$D$43:$Q$43,0))} -> 247958.33 | S13: {=INDEX(Cashflow!$D$54:$Q$54,MATCH(S$6,Cashflow!$D$43:$Q$43,0))} -> 255239.56
C15: Total current assets | F15: =SUM(F10:F13) -> 0 | G15: =SUM(G10:G13) -> 0 | H15: =SUM(H10:H13) -> 452228.4 | I15: =SUM(I10:I13) -> 3547612.2 | J15: =SUM(J10:J13) -> 4198009.7 | K15: =SUM(K10:K13) -> 4940308.2 | L15: =SUM(L10:L13) -> 5834329.4 | M15: =SUM(M10:M13) -> 6721793.1 | ... S15: =SUM(S10:S13) -> 15855323
C17: Non-Current Assets
D18: Lease deposit / bond | F18: ='Construction Timeline'!D225 -> 0 | G18: ='Construction Timeline'!E225 -> 0 | H18: ='Construction Timeline'!F225 -> 819000 | I18: ='Construction Timeline'!G225 -> 819000 | J18: ='Construction Timeline'!H225 -> 819000 | K18: ='Construction Timeline'!I225 -> 819000 | L18: ='Construction Timeline'!J225 -> 819000 | M18: ='Construction Timeline'!K225 -> 819000 | ... Q18: ='Construction Timeline'!O225 -> 819000 | R18: ='Construction Timeline'!S225 -> 819000 | S18: ='Construction Timeline'!T225 -> 819000
D19: Work in Progress (WIP) | F19: ='Construction Timeline'!D221 -> 0 | G19: ='Construction Timeline'!E221 -> 0 | H19: ='Construction Timeline'!F221 -> 19761525 | I19: ='Construction Timeline'!G221 -> 0 | J19: ='Construction Timeline'!H221 -> 0 | K19: ='Construction Timeline'!I221 -> 0 | L19: ='Construction Timeline'!J221 -> 0 | M19: ='Construction Timeline'!K221 -> 0 | ... Q19: ='Construction Timeline'!O221 -> 0 | R19: ='Construction Timeline'!S221 -> 0 | S19: ='Construction Timeline'!T221 -> 0
D20: Property, Plant & Equipment (gross) | F20: ='Construction Timeline'!D232 -> 0 | G20: ='Construction Timeline'!E232 -> 0 | H20: ='Construction Timeline'!F232 -> 0 | I20: =H19 -> 19761525 | J20: ='Construction Timeline'!H232 -> 19761525 | K20: ='Construction Timeline'!I232 -> 19761525 | L20: ='Construction Timeline'!J232 -> 19761525 | M20: ='Construction Timeline'!K232 -> 19761525 | N20: ='Construction Timeline'!L232 -> 19761525 | O20: ='Construction Timeline'!M232 -> 19761525 | P20: ='Construction Timeline'!N232 -> 19761525 | Q20: ='Construction Timeline'!O232 -> 19761525 | R20: ='Construction Timeline'!S232 -> 19761525 | S20: ='Construction Timeline'!T232 -> 19761525
D21: Accumulated depreciation | F21: 0 | G21: =F21 -> 0 | H21: 0 | I21: {=H21-INDEX('P&L'!$G$83:$R$83,MATCH(I$6,'P&L'!$G$6:$R$6,0))} -> -988076.25 | J21: {=I21-INDEX('P&L'!$G$83:$R$83,MATCH(J$6,'P&L'!$G$6:$R$6,0))} -> -1976152.5 | K21: {=J21-INDEX('P&L'!$G$83:$R$83,MATCH(K$6,'P&L'!$G$6:$R$6,0))} -> -2964228.8 | L21: {=K21-INDEX('P&L'!$G$83:$R$83,MATCH(L$6,'P&L'!$G$6:$R$6,0))} -> -3952305 | M21: {=L21-INDEX('P&L'!$G$83:$R$83,MATCH(M$6,'P&L'!$G$6:$R$6,0))} -> -4940381.2 | N21: {=M21-INDEX('P&L'!$G$83:$R$83,MATCH(N$6,'P&L'!$G$6:$R$6,0))} -> -5928457.5 | O21: {=N21-INDEX('P&L'!$G$83:$R$83,MATCH(O$6,'P&L'!$G$6:$R$6,0))} -> -6916533.8 | P21: {=O21-INDEX('P&L'!$G$83:$R$83,MATCH(P$6,'P&L'!$G$6:$R$6,0))} -> -7904610 | Q21: {=P21-INDEX('P&L'!$G$83:$R$83,MATCH(Q$6,'P&L'!$G$6:$R$6,0))} -> -8892686.2 | R21: {=Q21-INDEX('P&L'!$G$83:$T$83,MATCH(R$6,'P&L'!$G$6:$T$6,0))} -> -9880762.5 | S21: {=R21-INDEX('P&L'!$G$83:$T$83,MATCH(S$6,'P&L'!$G$6:$T$6,0))} -> -10868839
D22: PPE (net) | F22: ='Construction Timeline'!D238 -> 0 | G22: ='Construction Timeline'!E238 -> 0 | H22: ='Construction Timeline'!F238 -> 0 | I22: =I20+I21 -> 18773449 | J22: =J20+J21 -> 17785372 | K22: =K20+K21 -> 16797296 | L22: =L20+L21 -> 15809220 | M22: =M20+M21 -> 14821144 | N22: =N20+N21 -> 13833068 | O22: =O20+O21 -> 12844991 | P22: =P20+P21 -> 11856915 | ... S22: =S20+S21 -> 8892686.2
C23: Total Non-Current Assets | F23: =F18+F19+F22 -> 0 | G23: =G18+G19+G22 -> 0 | H23: =H18+H19+H22 -> 20580525 | I23: =I18+I19+I22 -> 19592449 | J23: =J18+J19+J22 -> 18604372 | K23: =K18+K19+K22 -> 17616296 | L23: =L18+L19+L22 -> 16628220 | M23: =M18+M19+M22 -> 15640144 | ... S23: =S18+S19+S22 -> 9711686.2
C25: Total Assets | F25: =F15+F23 -> 0 | G25: =G15+G23 -> 0 | H25: =H15+H23 -> 21032753 | I25: =I15+I23 -> 23140061 | J25: =J15+J23 -> 22802382 | K25: =K15+K23 -> 22556604 | L25: =L15+L23 -> 22462549 | M25: =M15+M23 -> 22361937 | ... S25: =S15+S23 -> 25567009
C26: NWC (AR + Inv – AP – Deferred rev) | F26: {=F12+F13-IFERROR(INDEX(Cashflow!$D$55:$O$55,MATCH(F$6,Cashflow!$D$43:$O$43,0)),0)-F33} -> 0 | G26: {=G12+G13-IFERROR(INDEX(Cashflow!$D$55:$O$55,MATCH(G$6,Cashflow!$D$43:$O$43,0)),0)-G33} -> 0 | H26: {=H12+H13-IFERROR(INDEX(Cashflow!$D$55:$O$55,MATCH(H$6,Cashflow!$D$43:$O$43,0)),0)-H33} -> 0 | I26: {=I12+I13-IFERROR(INDEX(Cashflow!$D$55:$O$55,MATCH(I$6,Cashflow!$D$43:$O$43,0)),0)-I33} -> 1096726.6 | J26: {=J12+J13-IFERROR(INDEX(Cashflow!$D$55:$O$55,MATCH(J$6,Cashflow!$D$43:$O$43,0)),0)-J33} -> 1109567.2 | K26: {=K12+K13-IFERROR(INDEX(Cashflow!$D$55:$O$55,MATCH(K$6,Cashflow!$D$43:$O$43,0)),0)-K33} -> 1168369.6 | L26: {=L12+L13-IFERROR(INDEX(Cashflow!$D$55:$O$55,MATCH(L$6,Cashflow!$D$43:$O$43,0)),0)-L33} -> 1244391.8 | M26: {=M12+M13-IFERROR(INDEX(Cashflow!$D$55:$O$55,MATCH(M$6,Cashflow!$D$43:$O$43,0)),0)-M33} -> 1268733.4 | ... Q26: {=Q12+Q13-IFERROR(INDEX(Cashflow!$D$55:$O$55,MATCH(Q$6,Cashflow!$D$43:$O$43,0)),0)-Q33} -> 1310065.1 | R26: {=R12+R13-IFERROR(INDEX(Cashflow!$D$55:$Q$55,MATCH(R$6,Cashflow!$D$43:$Q$43,0)),0)-R33} -> 1328518.4 | S26: {=S12+S13-IFERROR(INDEX(Cashflow!$D$55:$Q$55,MATCH(S$6,Cashflow!$D$43:$Q$43,0)),0)-S33} -> 1407270.5
B28: LIABILITIES
C29: Current Liabilities
D30: Accounts payable / accruals | F30: {=IFERROR(INDEX(Cashflow!$D$55:$O$55,MATCH(F$6,Cashflow!$D$43:$O$43,0)),0)} -> 0 | G30: {=IFERROR(INDEX(Cashflow!$D$55:$O$55,MATCH(G$6,Cashflow!$D$43:$O$43,0)),0)} -> 0 | H30: {=IFERROR(INDEX(Cashflow!$D$55:$O$55,MATCH(H$6,Cashflow!$D$43:$O$43,0)),0)} -> 0 | I30: {=IFERROR(INDEX(Cashflow!$D$55:$O$55,MATCH(I$6,Cashflow!$D$43:$O$43,0)),0)} -> 624477.31 | J30: {=IFERROR(INDEX(Cashflow!$D$55:$O$55,MATCH(J$6,Cashflow!$D$43:$O$43,0)),0)} -> 698849.59 | K30: {=IFERROR(INDEX(Cashflow!$D$55:$O$55,MATCH(K$6,Cashflow!$D$43:$O$43,0)),0)} -> 730710.18 | L30: {=IFERROR(INDEX(Cashflow!$D$55:$O$55,MATCH(L$6,Cashflow!$D$43:$O$43,0)),0)} -> 756613.23 | M30: {=IFERROR(INDEX(Cashflow!$D$55:$O$55,MATCH(M$6,Cashflow!$D$43:$O$43,0)),0)} -> 778817.89 | ... Q30: {=IFERROR(INDEX(Cashflow!$D$55:$O$55,MATCH(Q$6,Cashflow!$D$43:$O$43,0)),0)} -> 937777.28 | R30: {=IFERROR(INDEX(Cashflow!$D$55:$Q$55,MATCH(R$6,Cashflow!$D$43:$Q$43,0)),0)} -> 973134.3 | S30: {=IFERROR(INDEX(Cashflow!$D$55:$Q$55,MATCH(S$6,Cashflow!$D$43:$Q$43,0)),0)} -> 949776.57
D31: Borrowings – current | F31: {=INDEX(Debt!$H$49:$S$49, MATCH(F$6, Debt!$H$14:$S$14,0))} -> 0 | G31: {=INDEX(Debt!$H$49:$S$49, MATCH(G$6, Debt!$H$14:$S$14,0))} -> 0 | H31: {=INDEX(Debt!$H$49:$S$49,MATCH(H$6,Debt!$H$14:$S$14,0))+IFERROR(INDEX(Debt!$H$84:$S$84,MATCH(H$6,Debt!$H$74:$S$74,0)),0)} -> 850000 | I31: {=INDEX(Debt!$H$49:$S$49,MATCH(I$6,Debt!$H$14:$S$14,0))+IFERROR(INDEX(Debt!$H$84:$S$84,MATCH(I$6,Debt!$H$74:$S$74,0)),0)} -> 1584489.4 | J31: {=INDEX(Debt!$H$49:$S$49,MATCH(J$6,Debt!$H$14:$S$14,0))+IFERROR(INDEX(Debt!$H$84:$S$84,MATCH(J$6,Debt!$H$74:$S$74,0)),0)} -> 1584489.4 | K31: {=INDEX(Debt!$H$49:$S$49,MATCH(K$6,Debt!$H$14:$S$14,0))+IFERROR(INDEX(Debt!$H$84:$S$84,MATCH(K$6,Debt!$H$74:$S$74,0)),0)} -> 1584489.4 | L31: {=INDEX(Debt!$H$49:$S$49,MATCH(L$6,Debt!$H$14:$S$14,0))+IFERROR(INDEX(Debt!$H$84:$S$84,MATCH(L$6,Debt!$H$74:$S$74,0)),0)} -> 1584489.4 | M31: {=INDEX(Debt!$H$49:$S$49,MATCH(M$6,Debt!$H$14:$S$14,0))+IFERROR(INDEX(Debt!$H$84:$S$84,MATCH(M$6,Debt!$H$74:$S$74,0)),0)} -> 1584489.4 | N31: {=INDEX(Debt!$H$49:$S$49,MATCH(N$6,Debt!$H$14:$S$14,0))+IFERROR(INDEX(Debt!$H$84:$S$84,MATCH(N$6,Debt!$H$74:$S$74,0)),0)} -> 1584489.4 | O31: {=INDEX(Debt!$H$49:$S$49,MATCH(O$6,Debt!$H$14:$S$14,0))+IFERROR(INDEX(Debt!$H$84:$S$84,MATCH(O$6,Debt!$H$74:$S$74,0)),0)} -> 1584489.4 | ... Q31: {=INDEX(Debt!$H$49:$S$49,MATCH(Q$6,Debt!$H$14:$S$14,0))+IFERROR(INDEX(Debt!$H$84:$S$84,MATCH(Q$6,Debt!$H$74:$S$74,0)),0)} -> 0 | R31: {=INDEX(Debt!$H$49:$U$49,MATCH(R$6,Debt!$H$14:$U$14,0))+IFERROR(INDEX(Debt!$H$84:$U$84,MATCH(R$6,Debt!$H$74:$U$74,0)),0)} -> 0 | S31: {=INDEX(Debt!$H$49:$U$49,MATCH(S$6,Debt!$H$14:$U$14,0))+IFERROR(INDEX(Debt!$H$84:$U$84,MATCH(S$6,Debt!$H$74:$U$74,0)),0)} -> 0
D32: Interest payable (accrued) | F32: 0 | G32: 0 | H32: 0 | I32: 0 | J32: 0 | K32: 0 | L32: 0 | M32: 0 | N32: 0 | O32: 0 | P32: 0 | Q32: 0 | R32: =Q32+'P&L'!S87+Cashflow!P31 -> 0 | S32: =R32+'P&L'!T87+Cashflow!Q31 -> 0
D33: Customer deposits / deferred revenue | F33: {=INDEX(Cashflow!$D$21:$O$21, MATCH(F$6,Cashflow!$D$7:$O$7,0))-IF(F$6=Inputs!$E$488,Inputs!$H$533*SUM(Cashflow!$D$21:$O$21),0)} -> 0 | G33: {=F33+INDEX(Cashflow!$D$21:$O$21, MATCH(G$6,Cashflow!$D$7:$O$7,0))-IF(G$6=Inputs!$E$488,Inputs!$H$533*SUM(Cashflow!$D$21:$O$21),0)} -> 0 | H33: {=G33+INDEX(Cashflow!$D$21:$O$21, MATCH(H$6,Cashflow!$D$7:$O$7,0))-IF(H$6=Inputs!$E$488,Inputs!$H$533*SUM(Cashflow!$D$21:$O$21),0)} -> 0 | I33: {=H33+INDEX(Cashflow!$D$21:$O$21, MATCH(I$6,Cashflow!$D$7:$O$7,0))-IF(I$6=Inputs!$E$488,Inputs!$H$533*SUM(Cashflow!$D$21:$O$21),0)} -> 0 | J33: {=I33+INDEX(Cashflow!$D$21:$O$21, MATCH(J$6,Cashflow!$D$7:$O$7,0))-IF(J$6=Inputs!$E$488,Inputs!$H$533*SUM(Cashflow!$D$21:$O$21),0)} -> 0 | K33: {=J33+INDEX(Cashflow!$D$21:$O$21, MATCH(K$6,Cashflow!$D$7:$O$7,0))-IF(K$6=Inputs!$E$488,Inputs!$H$533*SUM(Cashflow!$D$21:$O$21),0)} -> 0 | L33: {=K33+INDEX(Cashflow!$D$21:$O$21, MATCH(L$6,Cashflow!$D$7:$O$7,0))-IF(L$6=Inputs!$E$488,Inputs!$H$533*SUM(Cashflow!$D$21:$O$21),0)} -> 0 | M33: {=L33+INDEX(Cashflow!$D$21:$O$21, MATCH(M$6,Cashflow!$D$7:$O$7,0))-IF(M$6=Inputs!$E$488,Inputs!$H$533*SUM(Cashflow!$D$21:$O$21),0)} -> 0 | N33: {=M33+INDEX(Cashflow!$D$21:$O$21, MATCH(N$6,Cashflow!$D$7:$O$7,0))-IF(N$6=Inputs!$E$488,Inputs!$H$533*SUM(Cashflow!$D$21:$O$21),0)} -> 0 | ... Q33: {=P33+INDEX(Cashflow!$D$21:$O$21, MATCH(Q$6,Cashflow!$D$7:$O$7,0))-IF(Q$6=Inputs!$E$488,Inputs!$H$533*SUM(Cashflow!$D$21:$O$21),0)} -> 0 | R33: {=Q33+INDEX(Cashflow!$D$21:$Q$21,MATCH(R$6,Cashflow!$D$7:$Q$7,0))-IF(R$6=Inputs!$E$488,Inputs!$H$533*SUM(Cashflow!$D$21:$Q$21),0)} -> 0 | S33: {=R33+INDEX(Cashflow!$D$21:$Q$21,MATCH(S$6,Cashflow!$D$7:$Q$7,0))-IF(S$6=Inputs!$E$488,Inputs!$H$533*SUM(Cashflow!$D$21:$Q$21),0)} -> 0
C34: ="Total "&C29 -> Total Current Liabilities | F34: =F30+F31+F32+F33 -> 0 | G34: =G30+G31+G32+G33 -> 0 | H34: =H30+H31+H32+H33 -> 850000 | I34: =I30+I31+I32+I33 -> 2208966.7 | J34: =J30+J31+J32+J33 -> 2283339 | K34: =K30+K31+K32+K33 -> 2315199.6 | L34: =L30+L31+L32+L33 -> 2341102.6 | M34: =M30+M31+M32+M33 -> 2363307.3 | ... S34: =S30+S31+S32+S33 -> 949776.57
C36: Non-Current Liabilities
D37: Borrowings – non-current | F37: {=INDEX(Debt!$H$50:$S$50, MATCH(F$6, Debt!$H$14:$S$14,0))} -> 0 | G37: {=INDEX(Debt!$H$50:$S$50, MATCH(G$6, Debt!$H$14:$S$14,0))} -> 0 | H37: {=INDEX(Debt!$H$50:$S$50,MATCH(H$6,Debt!$H$14:$S$14,0))+IFERROR(INDEX(Debt!$H$85:$S$85,MATCH(H$6,Debt!$H$74:$S$74,0)),0)} -> 12675915 | I37: {=INDEX(Debt!$H$50:$S$50,MATCH(I$6,Debt!$H$14:$S$14,0))+IFERROR(INDEX(Debt!$H$85:$S$85,MATCH(I$6,Debt!$H$74:$S$74,0)),0)} -> 11091426 | J37: {=INDEX(Debt!$H$50:$S$50,MATCH(J$6,Debt!$H$14:$S$14,0))+IFERROR(INDEX(Debt!$H$85:$S$85,MATCH(J$6,Debt!$H$74:$S$74,0)),0)} -> 9506936.2 | K37: {=INDEX(Debt!$H$50:$S$50,MATCH(K$6,Debt!$H$14:$S$14,0))+IFERROR(INDEX(Debt!$H$85:$S$85,MATCH(K$6,Debt!$H$74:$S$74,0)),0)} -> 7922446.9 | L37: {=INDEX(Debt!$H$50:$S$50,MATCH(L$6,Debt!$H$14:$S$14,0))+IFERROR(INDEX(Debt!$H$85:$S$85,MATCH(L$6,Debt!$H$74:$S$74,0)),0)} -> 6337957.5 | M37: {=INDEX(Debt!$H$50:$S$50,MATCH(M$6,Debt!$H$14:$S$14,0))+IFERROR(INDEX(Debt!$H$85:$S$85,MATCH(M$6,Debt!$H$74:$S$74,0)),0)} -> 4753468.1 | N37: {=INDEX(Debt!$H$50:$S$50,MATCH(N$6,Debt!$H$14:$S$14,0))+IFERROR(INDEX(Debt!$H$85:$S$85,MATCH(N$6,Debt!$H$74:$S$74,0)),0)} -> 3168978.8 | O37: {=INDEX(Debt!$H$50:$S$50,MATCH(O$6,Debt!$H$14:$S$14,0))+IFERROR(INDEX(Debt!$H$85:$S$85,MATCH(O$6,Debt!$H$74:$S$74,0)),0)} -> 1584489.4 | ... Q37: {=INDEX(Debt!$H$50:$S$50,MATCH(Q$6,Debt!$H$14:$S$14,0))+IFERROR(INDEX(Debt!$H$85:$S$85,MATCH(Q$6,Debt!$H$74:$S$74,0)),0)} -> 0 | R37: {=INDEX(Debt!$H$50:$U$50,MATCH(R$6,Debt!$H$14:$U$14,0))+IFERROR(INDEX(Debt!$H$85:$U$85,MATCH(R$6,Debt!$H$74:$U$74,0)),0)} -> 0 | S37: {=INDEX(Debt!$H$50:$U$50,MATCH(S$6,Debt!$H$14:$U$14,0))+IFERROR(INDEX(Debt!$H$85:$U$85,MATCH(S$6,Debt!$H$74:$U$74,0)),0)} -> 0
C38: ="Total " &C36 -> Total Non-Current Liabilities | F38: =SUM(F37) -> 0 | G38: =SUM(G37) -> 0 | H38: =SUM(H37) -> 12675915 | I38: =SUM(I37) -> 11091426 | J38: =SUM(J37) -> 9506936.2 | K38: =SUM(K37) -> 7922446.9 | L38: =SUM(L37) -> 6337957.5 | M38: =SUM(M37) -> 4753468.1 | ... S38: =SUM(S37) -> 0
C39: Total Liabilities | F39: =F34+F38 -> 0 | G39: =G34+G38 -> 0 | H39: =H34+H38 -> 13525915 | I39: =I34+I38 -> 13300392 | J39: =J34+J38 -> 11790275 | K39: =K34+K38 -> 10237646 | L39: =L34+L38 -> 8679060.1 | M39: =M34+M38 -> 7116775.4 | ... S39: =S34+S38 -> 949776.57
B41: EQUITY
C42: Contributed equity | F42: {=INDEX(Cashflow!$D$89:$O$89,MATCH(F$6,Cashflow!$D$7:$O$7,0))} -> 0 | G42: {=INDEX(Cashflow!$D$89:$O$89,MATCH(G$6,Cashflow!$D$7:$O$7,0))} -> 0 | H42: {=INDEX(Cashflow!$D$89:$O$89,MATCH(H$6,Cashflow!$D$7:$O$7,0))} -> 8970383.1 | I42: {=INDEX(Cashflow!$D$89:$O$89,MATCH(I$6,Cashflow!$D$7:$O$7,0))} -> 8970383.1 | J42: {=INDEX(Cashflow!$D$89:$O$89,MATCH(J$6,Cashflow!$D$7:$O$7,0))} -> 8970383.1 | K42: {=INDEX(Cashflow!$D$89:$O$89,MATCH(K$6,Cashflow!$D$7:$O$7,0))} -> 8970383.1 | L42: {=INDEX(Cashflow!$D$89:$O$89,MATCH(L$6,Cashflow!$D$7:$O$7,0))} -> 8970383.1 | M42: {=INDEX(Cashflow!$D$89:$O$89,MATCH(M$6,Cashflow!$D$7:$O$7,0))} -> 8970383.1 | ... Q42: {=INDEX(Cashflow!$D$89:$O$89,MATCH(Q$6,Cashflow!$D$7:$O$7,0))} -> 8970383.1 | R42: {=INDEX(Cashflow!$D$89:$Q$89,MATCH(R$6,Cashflow!$D$7:$Q$7,0))} -> 8970383.1 | S42: {=INDEX(Cashflow!$D$89:$Q$89,MATCH(S$6,Cashflow!$D$7:$Q$7,0))} -> 8970383.1
C43: Retained earnings | F43: {=INDEX('P&L'!$G$95:$R$95,MATCH(F$6,'P&L'!$G$6:$R$6,0))-INDEX('P&L'!$G$104:$R$104,MATCH(F$6,'P&L'!$G$6:$R$6,0))} -> 0 | G43: {=F43+INDEX('P&L'!$G$95:$T$95,MATCH(G$6,'P&L'!$G$6:$T$6,0))-INDEX('P&L'!$G$105:$T$105,MATCH(G$6,'P&L'!$G$6:$T$6,0))} -> 0 | H43: {=G43+INDEX('P&L'!$G$95:$T$95,MATCH(H$6,'P&L'!$G$6:$T$6,0))-INDEX('P&L'!$G$105:$T$105,MATCH(H$6,'P&L'!$G$6:$T$6,0))} -> -1463544.7 | I43: {=H43+INDEX('P&L'!$G$95:$T$95,MATCH(I$6,'P&L'!$G$6:$T$6,0))-INDEX('P&L'!$G$105:$T$105,MATCH(I$6,'P&L'!$G$6:$T$6,0))} -> 869285.6 | J43: {=I43+INDEX('P&L'!$G$95:$T$95,MATCH(J$6,'P&L'!$G$6:$T$6,0))-INDEX('P&L'!$G$105:$T$105,MATCH(J$6,'P&L'!$G$6:$T$6,0))} -> 2041723.9 | K43: {=J43+INDEX('P&L'!$G$95:$T$95,MATCH(K$6,'P&L'!$G$6:$T$6,0))-INDEX('P&L'!$G$105:$T$105,MATCH(K$6,'P&L'!$G$6:$T$6,0))} -> 3348574.9 | L43: {=K43+INDEX('P&L'!$G$95:$T$95,MATCH(L$6,'P&L'!$G$6:$T$6,0))-INDEX('P&L'!$G$105:$T$105,MATCH(L$6,'P&L'!$G$6:$T$6,0))} -> 4813106.2 | M43: {=L43+INDEX('P&L'!$G$95:$T$95,MATCH(M$6,'P&L'!$G$6:$T$6,0))-INDEX('P&L'!$G$105:$T$105,MATCH(M$6,'P&L'!$G$6:$T$6,0))} -> 6274778.4 | N43: {=M43+INDEX('P&L'!$G$95:$T$95,MATCH(N$6,'P&L'!$G$6:$T$6,0))-INDEX('P&L'!$G$105:$T$105,MATCH(N$6,'P&L'!$G$6:$T$6,0))} -> 7661319.2 | ... S43: {=R43+INDEX('P&L'!$G$95:$T$95,MATCH(S$6,'P&L'!$G$6:$T$6,0))-INDEX('P&L'!$G$105:$T$105,MATCH(S$6,'P&L'!$G$6:$T$6,0))} -> 15646850
B45: TOTAL Equity | F45: =SUM(F42:F43) -> 0 | G45: =SUM(G42:G43) -> 0 | H45: =SUM(H42:H43) -> 7506838.4 | I45: =SUM(I42:I43) -> 9839668.7 | J45: =SUM(J42:J43) -> 11012107 | K45: =SUM(K42:K43) -> 12318958 | L45: =SUM(L42:L43) -> 13783489 | M45: =SUM(M42:M43) -> 15245161 | ... S45: =SUM(S42:S43) -> 24617233
A48: CHECKS ONLY FOR REFERENCE
B49: Balance Check (Assets – Liabilities – Equity) | F49: =F25-F39-F45 -> 0 | G49: =G25-G39-G45 -> 0 | H49: =H25-H39-H45 -> 0 | I49: =I25-I39-I45 -> 0 | J49: =J25-J39-J45 -> 0 | K49: =K25-K39-K45 -> 0 | L49: =L25-L39-L45 -> 0 | M49: =M25-M39-M45 -> 0 | ... S49: =S25-S39-S45 -> 0
B50: Check Flag | E50: Balance Check Status | F50: =IF(F6=Inputs!$E$488,"N/A (Exit Yr)",IF(ABS(F49)<1,"OK","CHECK")) -> OK | G50: =IF(G6=Inputs!$E$488,"N/A (Exit Yr)",IF(ABS(G49)<1,"OK","CHECK")) -> OK | H50: =IF(H6=Inputs!$E$488,"N/A (Exit Yr)",IF(ABS(H49)<1,"OK","CHECK")) -> OK | I50: =IF(I6=Inputs!$E$488,"N/A (Exit Yr)",IF(ABS(I49)<1,"OK","CHECK")) -> OK | J50: =IF(J6=Inputs!$E$488,"N/A (Exit Yr)",IF(ABS(J49)<1,"OK","CHECK")) -> OK | K50: =IF(K6=Inputs!$E$488,"N/A (Exit Yr)",IF(ABS(K49)<1,"OK","CHECK")) -> OK | L50: =IF(L6=Inputs!$E$488,"N/A (Exit Yr)",IF(ABS(L49)<1,"OK","CHECK")) -> OK | M50: =IF(M6=Inputs!$E$488,"N/A (Exit Yr)",IF(ABS(M49)<1,"OK","CHECK")) -> OK | ... S50: =IF(S6=Inputs!$E$488,"N/A (Exit Yr)",IF(ABS(S49)<1,"OK","CHECK")) -> N/A (Exit Yr)
B52: THREE-STATEMENT INTEGRATION CHECKS
B54: Check | E54: FY25 | F54: FY26 | G54: FY27 | H54: FY28 | I54: FY29 | J54: FY30 | K54: FY31 | L54: FY32 | M54: FY33 | N54: FY34 | O54: FY35 | P54: FY36
B55: 1. Balance Test (A - L - E) | F55: =F49 -> 0 | G55: =G49 -> 0 | H55: =H49 -> 0 | I55: =I49 -> 0 | J55: =J49 -> 0 | K55: =K49 -> 0 | L55: =L49 -> 0 | M55: =M49 -> 0 | ... S55: =S49 -> 0
B56: 2. Cash Tie (BS vs CFS) | F56: =F10-Cashflow!D38 -> 0 | G56: =G10-Cashflow!E38 -> 0 | H56: =H10-Cashflow!F38 -> 0 | I56: =I10-Cashflow!G38 -> 0 | J56: =J10-Cashflow!H38 -> 0 | K56: =K10-Cashflow!I38 -> 0 | L56: =L10-Cashflow!J38 -> 0 | M56: =M10-Cashflow!K38 -> 0 | ... S56: =S10-Cashflow!Q38 -> 0
B57: 3. PPE Tie (BS vs Capex Schedule) | F57: =F22-'Construction Timeline'!D238 -> 0 | G57: =G22-'Construction Timeline'!E238 -> 0 | H57: =H22-'Construction Timeline'!F238 -> 0 | I57: =I22-'Construction Timeline'!G238 -> 0 | J57: =J22-'Construction Timeline'!H238 -> 0 | K57: =K22-'Construction Timeline'!I238 -> 0 | L57: =L22-'Construction Timeline'!J238 -> 0 | M57: =M22-'Construction Timeline'!K238 -> 0 | ... Q57: =Q22-'Construction Timeline'!O238 -> 0 | R57: =R22-'Construction Timeline'!S238 -> 0 | S57: =S22-'Construction Timeline'!T238 -> 0
B59: Overall Model Status | F59: MODEL BALANCED

Sheet Valuations
B1: THE BEND LIVE HOUSE — VALUATIONS
B2: Architecture sheet: valuation approaches, return metrics (IRR/NPV), and sensitivity framework. Calculations will be wired in the next step.
B4: VALUATION CONTROLS & INPUTS
B5: Active Scenario | C5: =Scenarios!B4 -> Base | D5: Pulled from Scenarios toggle (read-only)
B6: Valuation Currency | C6: AUD | D6: Match model currency
B7: Valuation Date | C7: =Inputs!E14 -> 46357 | D7: Leave blank or set to transaction / IC date
B8: Discount Rate Basis | C8: WACC (FCFF) / Ke (Equity) | D8: Choose which return metric you’re presenting
B9: WACC (nominal) | C9: =Inputs!E479 -> 0.1 | D9: Linked to Inputs!E477
B10: Cost of Equity (Ke) | C10: =Inputs!E480 -> 0.15 | D10: Linked to Inputs!E478
B11: Cost of Debt (Kd) | C11: =Debt!C7 -> 0.08 | D11: To be linked to Debt terms
B12: Corporate Tax Rate | C12: =Inputs!E482 -> 0.3 | D12: Linked to Inputs!E480
B13: Exit FY | C13: =Inputs!E488 -> FY38 | D13: Linked to Inputs!E486
B14: Exit Method | C14: ="EBITDA Multiple" -> EBITDA Multiple | D14: Choose primary method
B15: Exit EBITDA Multiple | C15: =Inputs!E483 -> 7 | D15: Linked to Inputs!E481
B16: Mid-year convention | C16: =Inputs!E485 -> No | D16: Linked to Inputs!E483
B19: Metric | C19: Value | D19: Units / Format | E19: Cash Flow Basis | F19: Method / Formula Guidance + Link Source
B20: Project IRR (Unlevered) | C20: =C109 -> 0.24794587 | D20: % | E20: Unlevered | F20: XIRR(unlevered FCF, dates) — exclude debt & equity flows | Source: Cashflow (build Unlevered FCF series)
B21: Project NPV @ WACC | C21: =C91 -> 62301607 | D21: A$ | E21: Unlevered | F21: XNPV(WACC, unlevered FCF, dates) OR PV factors | Source: Valuations DCF block below
B22: Equity IRR (Levered) | C22: =C123 -> 0.33284791 | D22: % | E22: Equity | F22: XIRR(equity cash flows, dates) | Source: Equity injections + distributions + exit equity
B23: Equity NPV @ Ke | C23: =C98 -> 50077920 | D23: A$ | E23: Equity | F23: XNPV(Ke, equity cash flows, dates) | Source: Equity cash flow schedule
B24: Equity MOIC | C24: =C127 -> 17.693182 | D24: x | E24: Equity | F24: (Total distributions + exit equity) / Total equity injected | Source: Dashboard already calculates
B25: Payback Period (Equity) | C25: =C128 -> FY30 | D25: FY | E25: Equity | F25: First year cumulative equity distributions exceed equity injected | Source: To be added (optional)
B26: Yield on Cost (Exit) | C26: =C131 -> 0.70345496 | D26: % | E26: Operating | F26: Stabilised EBITDA / Total Project Cost | Source: Dashboard already calculates
B29: WEIGHTED AVERAGE COST OF CAPITAL (WACC)
B30: Component | C30: Value | D30: Source/Formula
B31: Risk-Free Rate | C31: =Inputs!E490 -> 0.04 | D31: Linked to Inputs!E488
B32: Market Risk Premium | C32: =Inputs!E489 -> 0.065 | D32: Hard-coded: 6.5% historical equity premium (add to Inputs if row available)
B33: Asset Beta (Unlevered) | C33: =Inputs!E492 -> 0.8 | D33: Linked to Inputs!E490
B34: Target D/E Ratio | C34: =Dashboard!J43/Dashboard!J42 -> 1.4130851 | D34: From model capital structure
B35: Tax Rate | C35: =C12 -> 0.3 | D35: Corporate tax rate
B36: Levered Beta | C36: =C33*(1+(1-C35)*C34) -> 1.5913277 | D36: Hamada formula: βu×(1+(1-T)×D/E)
B37: Cost of Equity (Ke) | C37: =C31+C36*C32 -> 0.1434363 | D37: CAPM: Rf + β × MRP
B38: Pre-Tax Cost of Debt (Kd) | C38: =C11 -> 0.08 | D38: From Debt sheet
B39: After-Tax Cost of Debt | C39: =C38*(1-C35) -> 0.056 | D39: Kd × (1-T)
B41: Weight of Equity | C41: =1/(1+C34) -> 0.41440726 | D41: E/(D+E)
B42: Weight of Debt | C42: =C34/(1+C34) -> 0.58559274 | D42: D/(D+E)
B44: WACC (Calculated) | C44: =C41*C37+C42*C39 -> 0.092234237 | D44: We×Ke + Wd×Kd(1-T)
B45: WACC (Input Override) | C45: =C9 -> 0.1 | D45: Manual input for sensitivity
B47: Applied Discount Rate | C47: =C45 -> 0.1 | D47: Uses input WACC for discounting
B50: UNLEVERED DCF VALUATION
B51: Free Cash Flow to Firm (FCFF) Schedule
B53: Metric | C53: ='P&L'!G6 -> FY25 | D53: ='P&L'!H6 -> FY26 | E53: ='P&L'!I6 -> FY27 | F53: ='P&L'!J6 -> FY28 | G53: ='P&L'!K6 -> FY29 | H53: ='P&L'!L6 -> FY30 | I53: ='P&L'!M6 -> FY31 | J53: ='P&L'!N6 -> FY32 | ... P53: ='P&L'!T6 -> FY38
B54: FY End Date | C54: ='P&L'!G5 -> 45838 | D54: ='P&L'!H5 -> 46203 | E54: ='P&L'!I5 -> 46568 | F54: ='P&L'!J5 -> 46934 | G54: ='P&L'!K5 -> 47299 | H54: ='P&L'!L5 -> 47664 | I54: ='P&L'!M5 -> 48029 | J54: ='P&L'!N5 -> 48395 | ... P54: ='P&L'!T5 -> 50586
B55: Period Number | C55: =IF(C54="","",(C54-$C$7)/365) -> -1.4219178 | D55: =IF(D54="","",(D54-$C$7)/365) -> -0.42191781 | E55: =IF(E54="","",(E54-$C$7)/365) -> 0.57808219 | F55: =IF(F54="","",(F54-$C$7)/365) -> 1.5808219 | G55: =IF(G54="","",(G54-$C$7)/365) -> 2.5808219 | H55: =IF(H54="","",(H54-$C$7)/365) -> 3.5808219 | I55: =IF(I54="","",(I54-$C$7)/365) -> 4.5808219 | J55: =IF(J54="","",(J54-$C$7)/365) -> 5.5835616 | ... P55: =IF(P54="","",(P54-$C$7)/365) -> 11.586301
B57: Revenue | C57: ='P&L'!G28 -> 0 | D57: ='P&L'!H28 -> 0 | E57: ='P&L'!I28 -> 0 | F57: ='P&L'!J28 -> 18772333 | G57: ='P&L'!K28 -> 19676502 | H57: ='P&L'!L28 -> 20615522 | I57: ='P&L'!M28 -> 21808635 | J57: ='P&L'!N28 -> 22300757 | ... P57: ='P&L'!T28 -> 25571992
B58: EBITDA | C58: ='P&L'!G79 -> 0 | D58: ='P&L'!H79 -> 0 | E58: ='P&L'!I79 -> 0 | F58: ='P&L'!J79 -> 10240353 | G58: ='P&L'!K79 -> 10221611 | H58: ='P&L'!L79 -> 10726643 | I58: ='P&L'!M79 -> 11603174 | J58: ='P&L'!N79 -> 11825139 | ... P58: ='P&L'!T79 -> 13901343
B59: Less: Depreciation | C59: =-'P&L'!G83 -> 0 | D59: =-'P&L'!H83 -> 0 | E59: =-'P&L'!I83 -> 0 | F59: =-'P&L'!J83 -> -988076.25 | G59: =-'P&L'!K83 -> -988076.25 | H59: =-'P&L'!L83 -> -988076.25 | I59: =-'P&L'!M83 -> -988076.25 | J59: =-'P&L'!N83 -> -988076.25 | ... P59: =-'P&L'!T83 -> -988076.25
B60: EBIT | C60: =C58+C59 -> 0 | D60: =D58+D59 -> 0 | E60: =E58+E59 -> 0 | F60: =F58+F59 -> 9252276.9 | G60: =G58+G59 -> 9233534.4 | H60: =H58+H59 -> 9738567.2 | I60: =I58+I59 -> 10615097 | J60: =J58+J59 -> 10837063 | ... P60: =P58+P59 -> 12913266
B61: Less: Tax on EBIT | C61: =-MAX(0,C60)*$C$35 -> 0 | D61: =-MAX(0,D60)*$C$35 -> 0 | E61: =-MAX(0,E60)*$C$35 -> 0 | F61: =-MAX(0,F60)*$C$35 -> -2775683.1 | G61: =-MAX(0,G60)*$C$35 -> -2770060.3 | H61: =-MAX(0,H60)*$C$35 -> -2921570.2 | I61: =-MAX(0,I60)*$C$35 -> -3184529.2 | J61: =-MAX(0,J60)*$C$35 -> -3251118.8 | ... P61: =-MAX(0,P60)*$C$35 -> -3873979.9
B62: NOPAT | C62: =C60+C61 -> 0 | D62: =D60+D61 -> 0 | E62: =E60+E61 -> 0 | F62: =F60+F61 -> 6476593.9 | G62: =G60+G61 -> 6463474.1 | H62: =H60+H61 -> 6816997.1 | I62: =I60+I61 -> 7430568.2 | J62: =J60+J61 -> 7585944 | ... P62: =P60+P61 -> 9039286.5
B63: Add: Depreciation | C63: ='P&L'!G83 -> 0 | D63: ='P&L'!H83 -> 0 | E63: ='P&L'!I83 -> 0 | F63: ='P&L'!J83 -> 988076.25 | G63: ='P&L'!K83 -> 988076.25 | H63: ='P&L'!L83 -> 988076.25 | I63: ='P&L'!M83 -> 988076.25 | J63: ='P&L'!N83 -> 988076.25 | ... P63: ='P&L'!T83 -> 988076.25
B64: Less: Capex | C64: =Cashflow!D27 -> 0 | D64: =Cashflow!E27 -> 0 | E64: =Cashflow!F27 -> -20580525 | F64: =Cashflow!G27 -> 0 | G64: =Cashflow!H27 -> 0 | H64: =Cashflow!I27 -> 0 | I64: =Cashflow!J27 -> 0 | J64: =Cashflow!K27 -> 0 | ... P64: =Cashflow!Q27 -> 0
B65: Less: Change in NWC | C65: =IFERROR(Cashflow!D36,0) -> 0 | D65: =IFERROR(Cashflow!E36,0) -> 0 | E65: =IFERROR(Cashflow!F36,0) -> 0 | F65: =IFERROR(Cashflow!G36,0) -> -1096726.6 | G65: =IFERROR(Cashflow!H36,0) -> -12840.594 | H65: =IFERROR(Cashflow!I36,0) -> -58802.416 | I65: =IFERROR(Cashflow!J36,0) -> -76022.193 | J65: =IFERROR(Cashflow!K36,0) -> -24341.653 | ... M65: =IFERROR(Cashflow!N36,0) -> -24559.38 | N65: =0 -> 0 | O65: =0 -> 0 | P65: =0 -> 0
B66: Unlevered Free Cash Flow (FCFF) | C66: =C62+C63+C64+C65 -> 0 | D66: =D62+D63+D64+D65 -> 0 | E66: =E62+E63+E64+E65 -> -20580525 | F66: =F62+F63+F64+F65 -> 6367943.5 | G66: =G62+G63+G64+G65 -> 7438709.7 | H66: =H62+H63+H64+H65 -> 7746270.9 | I66: =I62+I63+I64+I65 -> 8342622.2 | J66: =J62+J63+J64+J65 -> 8549678.6 | ... P66: =P62+P63+P64+P65 -> 10027363
B69: TERMINAL VALUE & DISCOUNTING
B71: Exit Year | C71: =C13 -> FY38
B72: Exit EBITDA | C72: =P58 -> 13901343
B73: Exit Multiple | C73: =C15 -> 7
B74: Terminal Value (EV) | C74: =C72*C73 -> 97309399
B76: Discounting Schedule
B77: Metric | C77: =C53 -> FY25 | D77: =D53 -> FY26 | E77: =E53 -> FY27 | F77: =F53 -> FY28 | G77: =G53 -> FY29 | H77: =H53 -> FY30 | I77: =I53 -> FY31 | J77: =J53 -> FY32 | ... P77: =P53 -> FY38
B78: Period (Years) | C78: =C55 -> -1.4219178 | D78: =D55 -> -0.42191781 | E78: =E55 -> 0.57808219 | F78: =F55 -> 1.5808219 | G78: =G55 -> 2.5808219 | H78: =H55 -> 3.5808219 | I78: =I55 -> 4.5808219 | J78: =J55 -> 5.5835616 | ... P78: =P55 -> 11.586301
B79: Discount Factor | C79: =IF(C78="","",1/(1+$C$47)^C78) -> 1.1451358 | D79: =IF(D78="","",1/(1+$C$47)^D78) -> 1.0410326 | E79: =IF(E78="","",1/(1+$C$47)^E78) -> 0.94639323 | F79: =IF(F78="","",1/(1+$C$47)^F78) -> 0.86013285 | G79: =IF(G78="","",1/(1+$C$47)^G78) -> 0.78193896 | H79: =IF(H78="","",1/(1+$C$47)^H78) -> 0.7108536 | I79: =IF(I78="","",1/(1+$C$47)^I78) -> 0.64623054 | J79: =IF(J78="","",1/(1+$C$47)^J78) -> 0.58732893 | ... P79: =IF(P78="","",1/(1+$C$47)^P78) -> 0.33144531
B80: Unlevered FCF | C80: =C66 -> 0 | D80: =D66 -> 0 | E80: =E66 -> -20580525 | F80: =F66 -> 6367943.5 | G80: =G66 -> 7438709.7 | H80: =H66 -> 7746270.9 | I80: =I66 -> 8342622.2 | J80: =J66 -> 8549678.6 | ... P80: =P66 -> 10027363
B81: Terminal Value | C81: =0 -> 0 | D81: =0 -> 0 | E81: =0 -> 0 | F81: =0 -> 0 | G81: =0 -> 0 | H81: =0 -> 0 | I81: =0 -> 0 | J81: =0 -> 0 | ... O81: =0 -> 0 | P81: =$C$74 -> 97309399
B82: PV of FCF | C82: =IF(C79="","",C80*C79) -> 0 | D82: =IF(D79="","",D80*D79) -> 0 | E82: =IF(E79="","",E80*E79) -> -19477270 | F82: =IF(F79="","",F80*F79) -> 5477277.4 | G82: =IF(G79="","",G80*G79) -> 5816616.9 | H82: =IF(H79="","",H80*H79) -> 5506464.5 | I82: =IF(I79="","",I80*I79) -> 5391257.3 | J82: =IF(J79="","",J80*J79) -> 5021473.5 | ... P82: =IF(P79="","",P80*P79) -> 3323522.3
B83: PV of Terminal Value | C83: =IF(C79="","",C81*C79) -> 0 | D83: =IF(D79="","",D81*D79) -> 0 | E83: =IF(E79="","",E81*E79) -> 0 | F83: =IF(F79="","",F81*F79) -> 0 | G83: =IF(G79="","",G81*G79) -> 0 | H83: =IF(H79="","",H81*H79) -> 0 | I83: =IF(I79="","",I81*I79) -> 0 | J83: =IF(J79="","",J81*J79) -> 0 | ... P83: =IF(P79="","",P81*P79) -> 32252744
B86: ENTERPRISE VALUE TO EQUITY VALUE BRIDGE
B88: Component | C88: Value | D88: Notes
B89: Sum of PV of FCF | C89: =SUM(C82:P82) -> 30048863 | D89: Present value of forecast period cash flows
B90: PV of Terminal Value | C90: =SUM(C83:P83) -> 32252744 | D90: Discounted exit value
B91: Enterprise Value (DCF) | C91: =C89+C90 -> 62301607 | D91: Total DCF enterprise value
B93: Less: Net Debt at Valuation Date | C93: =-Debt!J24-Debt!J41 -> -12675915 | D93: Outstanding debt at valuation date
B94: Add: Cash at Valuation Date | C94: ='Balance Sheet'!H10 -> 452228.4 | D94: Available cash balance
B95: Less: Minority Interest | C95: =0 -> 0 | D95: If applicable
B96: Add: Associate Investments | C96: =0 -> 0 | D96: If applicable
B98: Equity Value | C98: =C91+C93+C94+C95+C96 -> 50077920 | D98: EV - Net Debt + Adjustments
B101: RETURN METRICS
B103: Project Returns (Unlevered)
B105: Unlevered Cash Flow Schedule | C105: =C53 -> FY25 | D105: =D53 -> FY26 | E105: =E53 -> FY27 | F105: =F53 -> FY28 | G105: =G53 -> FY29 | H105: =H53 -> FY30 | I105: =I53 -> FY31 | J105: =J53 -> FY32 | ... P105: =P53 -> FY38
B106: Date | C106: =C54 -> 45838 | D106: =D54 -> 46203 | E106: =E54 -> 46568 | F106: =F54 -> 46934 | G106: =G54 -> 47299 | H106: =H54 -> 47664 | I106: =I54 -> 48029 | J106: =J54 -> 48395 | ... P106: =P54 -> 50586
B107: Unlevered CF + TV | C107: =C80+C81 -> 0 | D107: =D80+D81 -> 0 | E107: =E80+E81 -> -20580525 | F107: =F80+F81 -> 6367943.5 | G107: =G80+G81 -> 7438709.7 | H107: =H80+H81 -> 7746270.9 | I107: =I80+I81 -> 8342622.2 | J107: =J80+J81 -> 8549678.6 | ... P107: =P80+P81 -> 1.0733676e+08
B109: Project IRR (Unlevered) | C109: =(C181/C182)^(1/10)-1 -> 0.24794587
B110: Project NPV @ WACC | C110: =C91 -> 62301607 | D110: Present value of all unlevered cash flows
B113: Equity Returns (Levered)
B115: Equity Cash Flow Schedule | C115: =C53 -> FY25 | D115: =D53 -> FY26 | E115: =E53 -> FY27 | F115: =F53 -> FY28 | G115: =G53 -> FY29 | H115: =H53 -> FY30 | I115: =I53 -> FY31 | J115: =J53 -> FY32 | ... P115: =P53 -> FY38
B116: Date | C116: =C106 -> 45838 | D116: =D106 -> 46203 | E116: =E106 -> 46568 | F116: =F106 -> 46934 | G116: =G106 -> 47299 | H116: =H106 -> 47664 | I116: =I106 -> 48029 | J116: =J106 -> 48395 | ... P116: =P106 -> 50586
B117: Equity Injections | C117: =-Cashflow!D16 -> 0 | D117: =-Cashflow!E16 -> 0 | E117: =-Cashflow!F16 -> -8970383.1 | F117: =-Cashflow!G16 -> 0 | G117: =-Cashflow!H16 -> 0 | H117: =-Cashflow!I16 -> 0 | I117: =-Cashflow!J16 -> 0 | J117: =-Cashflow!K16 -> 0 | ... P117: =-Cashflow!Q16 -> 0
B118: Dividends Received | C118: =-Cashflow!D33 -> 0 | D118: =-Cashflow!E33 -> 0 | E118: =-Cashflow!F33 -> 0 | F118: =-Cashflow!G33 -> 3847688.2 | G118: =-Cashflow!H33 -> 4625550.2 | H118: =-Cashflow!I33 -> 4933391.9 | I118: =-Cashflow!J33 -> 5478014.2 | J118: =-Cashflow!K33 -> 5724980.5 | ... P118: =-Cashflow!Q33 -> 7152677.1
B119: Exit Proceeds | C119: =0 -> 0 | D119: =0 -> 0 | E119: =0 -> 0 | F119: =0 -> 0 | G119: =0 -> 0 | H119: =0 -> 0 | I119: =0 -> 0 | J119: =0 -> 0 | ... O119: =0 -> 0 | P119: =C74 -> 97309399
B120: Net Equity Cash Flow | C120: =C117+C118+C119 -> 0 | D120: =D117+D118+D119 -> 0 | E120: =E117+E118+E119 -> -8970383.1 | F120: =F117+F118+F119 -> 3847688.2 | G120: =G117+G118+G119 -> 4625550.2 | H120: =H117+H118+H119 -> 4933391.9 | I120: =I117+I118+I119 -> 5478014.2 | J120: =J117+J118+J119 -> 5724980.5 | ... P120: =P117+P118+P119 -> 1.0446208e+08
B121: Cumulative Equity CF | C121: =C120 -> 0 | D121: =C121+D120 -> 0 | E121: =D121+E120 -> -8970383.1 | F121: =E121+F120 -> -5122694.9 | G121: =F121+G120 -> -497144.64 | H121: =G121+H120 -> 4436247.3 | I121: =H121+I120 -> 9914261.5 | J121: =I121+J120 -> 15639242 | K121: =J121+K120 -> 21292380 | ... P121: =O121+P120 -> 1.4974424e+08
B123: Equity IRR (Levered) | C123: =(C180/C125)^(1/10)-1 -> 0.33284791 | O123: =IFERROR(IRR(C120:P120),"") -> 0.56123651
B124: Equity NPV @ Ke | C124: =C98 -> 50077920 | D124: XNPV at Cost of Equity
B125: Total Equity Invested | C125: =-SUM(C117:P117) -> 8970383.1 | D125: Sum of equity contributions
B126: Total Distributions + Exit | C126: =SUM(C118:P118)+SUM(C119:P119) -> 1.5871462e+08 | D126: Dividends + terminal proceeds
B127: Multiple of Invested Capital (MOIC) | C127: =C180/C125 -> 17.693182 | D127: Total proceeds / Total invested
B128: Payback Period | C128: {=IFERROR(INDEX(C115:P115,MATCH(TRUE(),C121:P121>0,0)),"Not Achieved")} -> FY30 | D128: First FY with positive cumulative equity CF
B130: Yield on Cost (Stabilised) | C130: =H58/Dashboard!J41 -> 0.54280444 | D130: Stabilised EBITDA / Total Capex
B131: Yield on Cost (Exit Year) | C131: =P58/Dashboard!J41 -> 0.70345496 | D131: Exit EBITDA / Total Capex
...

Sheet INPUTS  WORKINGS DETAILS ------

Sheet Inputs
G1: FY (Financial Year): 1 July to 30 June CY (Calendar Year): 1 January to 31 December eg: FY 2028 ends on 30th June 2028 and CY 2028 ends on 31st Dec 2028.
B2: GLOBAL INPUTS
B3: THE BEND Live House: Financial Model
C5: Input | D5: Units | E5: Value | F5: Source | G5: Notes
B7: 1. PROJECT TIMING | I7: FORMAT LEGEND
I8: User Input
C9: Model Start Date | D9: Date | E9: 46054 | G9: Feb-2025 — Model commencement | I9: Formula/Link
C10: Model End Date | D10: Date | E10: 50526 | G10: May-2038 — 12-year horizon | I10: Section
C11: Model Duration | D11: Years | E11: 12 | G11: Total projection period | I11: Sub-Section
C12: Currency | E12: AUD | G12: Australian Dollars | I12: Table Header
I13: Subtotal
C14: Lease Signing Date | D14: Date | E14: 46357 | G14: Dec-2026 — Triggers deposit payment | I14: Total
C15: Possession / Handover Date | D15: Date | E15: 46539 | G15: Jun-2027 — Site access begins | I15: Section Header
C16: Major Capex Start | D16: Date | E16: 46419 | G16: Feb-2027 — Fabrication begins | I16: Model Status: | J16: READY
C17: Major Capex End | D17: Date | E17: =DATE(2027,6,30) -> 46568 | G17: Jun-2027 — Fabrication complete | I17: Total/Subtotal
C18: Construction Start | D18: Date | E18: 46420 | G18: Feb-2027 — On-site assembly
C19: Construction End | D19: Date | E19: 46568 | G19: Jun-2027 — Practical completion
C20: Commissioning Start | D20: Date | E20: 46508 | G20: 46508
C21: Commissioning End | D21: Date | E21: 46568 | G21: 46539
C22: Operations Start | D22: Date | E22: 46569 | G22: Jul-2027 — First revenue month
C23: Exit Year | D23: FY | E23: =E488 -> FY38 | G23: Target exit/valuation date
B24: 2. LEASE ASSUMPTIONS
C26: Lease Commencement | D26: Date | E26: 46419 | G26: Matches Possession Date
C27: Lease Period | D27: Years | E27: 20 | G27: Initial lease term
C29: Operational Months in Year 1 | D29: Months | E29: 6 | G29: Jul-Dec FY27
C30: Rent-Free Period | D30: Months | E30: 18 | G30: Fitout/construction allowance
C31: Base Rent Rate | D31: $/m²/yr | E31: 130 | G31: Per annum rate
C32: Plot Area | D32: m² | E32: 6300 | G32: Total leasable area
C33: Annual Base Rent (Yr 1) | D33: AUD | E33: =E31*E32 -> 819000 | F33: Formula | G33: =E31*E32 -> 819000
C34: Lease Deposit | D34: AUD | E34: =E33 -> 819000 | G34: Equivalent to 1 year rent
C35: Rent Escalation | D35: % p.a. | E35: 0.035 | G35: 3.5% fixed annual increase
C36: Landlord Outgoings | D36: % of rent | E36: 0.15 | G36: 15% additional outgoings
C37: Rent-Free End Date | D37: Date | E37: =EDATE(E26,E30) -> 46966 | F37: Formula | G37: Lease Commencement + Rent-Free Period
C38: Rent Rebate Period | D38: Months | E38: 48 | G38: 48 months at reduced rent after rent-free ends
C39: Rent Rebate Multiplier | D39: x | E39: 0.5 | G39: 50% of normal rent during rebate period
C40: Rent Rebate End Date | D40: Date | E40: =EDATE($E$37,$E$38) -> 48427 | G40: Rent-Free End Date + Rebate Period
C41: Tenant Break Option | D41: Year | E41: 5 | G41: Years from lease start
C42: Break Notice Period | D42: Months | E42: 6 | G42: Required notice
C43: Renewal Option | D43: Years | E43: 5 | G43: Extension available
B44: 3. DEBT & FINANCING
C46: FUNDING SUMMARY
D47: Source | E47: Amount (AUD) | F47: % of Total | G47: Notes
C49: DEBT FACILITIES
D50: DEBT | E50: =E66 -> 11856915 | F50: =IFERROR(E50/$E$60,1) -> 0.52706072
D51: Working Capital Facility | E51: =E96 -> 850000 | F51: =IFERROR(E51/$E$60,1) -> 0.037783994
C52: OTHER COMMITMENTS | D52: Lease Deposit / Rental Bond | E52: =E34 -> 819000 | F52: =IFERROR(E52/$E$60,1) -> 0.03640599
D53: Subtotal Debt | E53: =SUM(E50:E52) -> 13525915 | F53: =IFERROR(E53/$E$60,1) -> 0.6012507
D56: =C114 -> Initial Cash Inflow through advances/deposits via Partnerships | E56: =E114 -> 1500000 | F56: =IFERROR(E56/$E$60,1) -> 0.066677637
C57: EQUITY | D57: PE Equity | E57: =E118 -> 7470383.1 | F57: =IFERROR(E57/$E$60,1) -> 0.33207166
D58: Subtotal Equity | E58: =E56+E57 -> 8970383.1 | F58: =IFERROR(E58/$E$60,1) -> 0.3987493
C60: TOTAL FUNDING REQUIREMENT | D60: TOTAL FUNDING | E60: =E53+E58 -> 22496298 | F60: =IFERROR(E60/$E$60,1) -> 1 | G60: Total project funding requirement
C62: Term Debt (Bank)
C63: Interest Rate | D63: % p.a. | E63: 0.08 | G63: Bank rate
C64: Loan Term | D64: Years | E64: 10 | G64: Amortisation period
C65: LTV Ratio | D65: % | E65: 0.6 | G65: % of capex
C66: Loan Principal | D66: AUD | E66: =E65*E159 -> 11856915 | F66: Formula | G66: LTV × Total Capex
C67: Repayment Type | E67: Amortising | G67: Equal principal repayments
C68: Draw Year | D68: FY | E68: FY27 | G68: Construction period
C69: Interest-Only Period | D69: Months | E69: 18 | G69: Before amortisation starts
C71: Private Debt (PE Loan) | G71: LEGACY — INACTIVE (PE is now equity, see Equity section below)
C72: Interest Rate | D72: % p.a. | E72: 0.12 | G72: 12% PE rate
C73: Loan Term | D73: Years | E73: 10 | G73: 5-year term
C74: LTV Ratio | D74: % | E74: 0 | G74: 20% of capex
C75: Loan Principal | D75: AUD | E75: =(E74*E159)*0 -> 0 | F75: Formula | G75: LTV × Total Capex
C76: Repayment Type | E76: Amortising | G76: Equal principal repayments
C77: Draw Year | D77: FY | E77: FY27 | G77: Construction period
C79: WORKING CAPITAL FACILITY
C80: Pre-revenue operating cost facility — separate from term debt and equity (Wages & Consulting costs)
C82: WC Facility Toggle | D82: On/Off | E82: 1 | G82: 1 = ON, 0 = OFF
C83: Interest Rate | D83: % p.a. | E83: 0.085 | G83: 8.5% - higher than term debt (unsecured/current)
C84: Undrawn Commitment Fee | D84: % p.a. | E84: 0.01 | G84: 1% on undrawn commitment
C87: Facility Start Date | D87: Date | E87: 46327 | G87: 1-Nov-2026— facility available from FY27
C88: Last Draw Date | D88: Date | E88: 46569 | G88: 30-Jun-2027 — last eligible draw (ops start)
C89: Repayment Start Date | D89: Date | E89: 46569 | G89: 1-Jul-2027 — repayment begins at ops start
C90: Final Maturity Date | D90: Date | E90: 46934 | G90: 30-Jun-2028 — clean-down within 12 months of ops
C92: Minimum Cash Threshold | D92: AUD | E92: 50000 | G92: Minimum cash buffer - WC draws when cash falls below this
C93: Repayment Method | D93: Type | E93: Cash Sweep | G93: Cash Sweep or Scheduled
C94: Manual Facility Limit | D94: AUD | E94: 850000 | G94: Manual limit override (if auto-sizing off)
C95: Auto-Size Facility Limit | D95: Toggle | E95: 0 | G95: 1 = auto-size to eligible uses, 0 = use manual limit
C96: Active Facility Limit | D96: AUD | E96: 850000 | F96: Formula | G96: =IF(E77=1,linked,E76) — populated later
C97: Interest Capitalisation Toggle | D97: On/Off | E97: 1 | G97: 0 = pay interest cash, 1 = capitalise to balance
C99: ELIGIBLE PRE-OP USE FLAGS
C106: LTV Ratio | D106: % | E106: 0 | G106: 20% of capex
C107: Loan Principal | D107: AUD | E107: =(E106*E151)*0 -> 0 | F107: Formula | G107: LTV × Total Capex
C108: Repayment Type | E108: Amortising | G108: Equal principal repayments
C109: Draw Year | D109: FY | E109: FY27 | G109: Construction period
C112: 4. EQUITY / SHARE CAPITAL
C113: PE is true share capital — NOT debt. It is not repaid, not amortised, and bears no interest. Equity funds the 20% loan deposit.
C114: Initial Cash Inflow through advances/deposits via Partnerships | D114: AUD | E114: 1500000 | G114: advances/deposits from Partnerships
C115: PE Equity Mode | D115: Toggle | E115: 1 | G115: Controls how PE equity is calculated: 0 = enter a fixed dollar amount; 1 = auto-calculate as a % of total project cost (capex); 2 = % is for ownership reference only, enter amount separately. Default is Mode 1 (% of capex).
C116: PE Equity % | D116: % | E116: 0.4 | G116: PE's share of total project cost. Bank LTV + PE% must = 100%. Currently: 60% bank + 40% PE + 10% initial advances + deposits= 100%.
C117: PE Equity Fixed Amount | D117: AUD | E117: 5000000 | G117: Only used when PE Equity Mode = 0 (fixed dollar). If Mode = 1 or 2, the model calculates the PE amount from the % above. This field is ignored unless Mode = 0.
C118: PE Equity Amount | D118: AUD | E118: =7400000+'Construction Timeline'!E189-E51 -> 7470383.1 | F118: Formula | G118: Auto-calculated PE equity amount based on the mode selected above. This is the actual PE cash injection that flows into the cashflow and balance sheet. PE equity is permanent — never repaid.
C120: Initial Capital + Equity Funding | D120: AUD | E120: =E114+E118+E127+E129 -> 8970383.1 | F120: Formula | G120: Total equity = PE + tranches. Covers total project need (capex + lease deposit) minus bank debt. Bank + Equity = 100% of capex, plus equity covers lease deposit.
C121: Bank Debt % of Total Capex | D121: % | E121: =E65 -> 0.6 | F121: Link | G121: Linked from Term Debt LTV above. Shows bank debt as % of total capex for cross-reference. Bank funds the remaining balance after equity.
C122: Required Loan Deposit / Equity Contribution % | D122: % | E122: 0.2 | G122: Lender requires this % of total capex as upfront equity (deposit) before releasing debt. Funded from total equity.
C123: Required Deposit Amount | D123: AUD | E123: =E122*E159 -> 3952305 | F123: Formula | G123: Formula: Deposit % × Total Capex. This is the minimum equity the bank needs to see committed before it will drawdown the loan.
C125: Equity Injection Timing | G125: Controls WHEN each equity source enters the cashflow. Equity only appears in the period specified below.
C126: Capital Injection Year | D126: FY | E126: FY27 | G126: Equity injects in FY26 (pre-construction) to meet the bank's deposit requirement before the FY27 construction debt drawdown.
C127: Additional Equity Tranche 1 Amount | D127: AUD | E127: 0 | G127: Reserved for future use — if additional equity is needed (e.g. cost overruns, new investor). Set to $0 by default. Change the amount and timing to activate.
...

Sheet Revenue Assumptions
A1: REVENUE ASSUMPTIONS | C1: VHA is Venue Hire Agreement
F3: =F19 -> FY28 | G3: =G19 -> FY29 | H3: =H19 -> FY30 | I3: =I19 -> FY31 | J3: =J19 -> FY32 | K3: =K19 -> FY33 | L3: =L19 -> FY34 | M3: =M19 -> FY35 | ... P3: =P19 -> FY38
B4: VHA Fee | D4: Max Capacity | E4: Ave Capacity
B5: 1 | C5: Music GA (Large) | D5: =Inputs!$E290 -> 5000 | E5: ='Calendar Assumptions'!D41*'Calendar Assumptions'!E41 -> 4000
B6: 2 | C6: Music GA (Medium) | D6: =Inputs!$E291 -> 3000 | E6: ='Calendar Assumptions'!D42*'Calendar Assumptions'!E42 -> 2400
B7: 3 | C7: Music GA (Small) | D7: =Inputs!$E292 -> 1500 | E7: ='Calendar Assumptions'!D43*'Calendar Assumptions'!E43 -> 1350
B8: 4 | C8: EDM | D8: =Inputs!$E293 -> 3500 | E8: ='Calendar Assumptions'!D44*'Calendar Assumptions'!E44 -> 3150
B9: 5 | C9: Music (Seated) | D9: =Inputs!$E294 -> 3500 | E9: ='Calendar Assumptions'!D45*'Calendar Assumptions'!E45 -> 3150
B10: 6 | C10: Comedy (Seated) | D10: =Inputs!$E295 -> 3500 | E10: ='Calendar Assumptions'!D46*'Calendar Assumptions'!E46 -> 3150
B11: 7 | C11: Sports | D11: =Inputs!$E296 -> 3500 | E11: ='Calendar Assumptions'!D47*'Calendar Assumptions'!E47 -> 2800
B12: 8 | C12: MICE | D12: =Inputs!$E297 -> 3500 | E12: ='Calendar Assumptions'!D48*'Calendar Assumptions'!E48 -> 2450
B13: 9 | C13: Community | D13: =Inputs!$E298 -> 2000 | E13: ='Calendar Assumptions'!D49*'Calendar Assumptions'!E49 -> 2000
B14: 10 | C14: Live Site | D14: =Inputs!$E299 -> 2000 | E14: ='Calendar Assumptions'!D50*'Calendar Assumptions'!E50 -> 2000
B15: 11 | C15: Farmers Market | D15: =Inputs!$E300 -> 4000 | E15: ='Calendar Assumptions'!D51*'Calendar Assumptions'!E51 -> 4000
E18: FY
B19: AVERAGE TICKET PRICE | D19: Capacity | F19: ='P&L'!J6 -> FY28 | G19: ='P&L'!K6 -> FY29 | H19: ='P&L'!L6 -> FY30 | I19: ='P&L'!M6 -> FY31 | J19: ='P&L'!N6 -> FY32 | K19: ='P&L'!O6 -> FY33 | L19: ='P&L'!P6 -> FY34 | M19: ='P&L'!Q6 -> FY35 | ... P19: ='P&L'!T6 -> FY38
B21: 1 | C21: Music GA (Large) | D21: ='Calendar Assumptions'!D41*'Calendar Assumptions'!E41 -> 4000 | F21: =Inputs!E310 -> 103 | G21: =F21*(1+Inputs!$E$315) -> 106.09 | H21: =G21*(1+Inputs!$E$315) -> 109.2727 | I21: =H21*(1+Inputs!$E$315) -> 112.55088 | J21: =I21*(1+Inputs!$E$315) -> 115.92741 | K21: =J21*(1+Inputs!$E$315) -> 119.40523 | L21: =K21*(1+Inputs!$E$315) -> 122.98739 | M21: =L21*(1+Inputs!$E$315) -> 126.67701 | N21: =M21*(1+Inputs!$E$315) -> 130.47732 | ... P21: =O21*(1+Inputs!$E$315) -> 138.42339
B22: 2 | C22: Music GA (Medium) | D22: ='Calendar Assumptions'!D42*'Calendar Assumptions'!E42 -> 2400 | F22: =F21 -> 103 | G22: =F22*(1+Inputs!$E$315) -> 106.09 | H22: =G22*(1+Inputs!$E$315) -> 109.2727 | I22: =H22*(1+Inputs!$E$315) -> 112.55088 | J22: =I22*(1+Inputs!$E$315) -> 115.92741 | K22: =J22*(1+Inputs!$E$315) -> 119.40523 | L22: =K22*(1+Inputs!$E$315) -> 122.98739 | M22: =L22*(1+Inputs!$E$315) -> 126.67701 | N22: =M22*(1+Inputs!$E$315) -> 130.47732 | ... P22: =O22*(1+Inputs!$E$315) -> 138.42339
