Workbook
Name Construction_End_Date: Inputs!$E$19
Name Construction_Start_Date: Inputs!$E$18
Name GanttView: 'GANTT – MASTER OPTIONS'!$C$3
Name Model_Start: [1]Inputs!$E$7
Name Model_start: Inputs!$E$9
Name Operations_Start_Date: Inputs!$E$22
Name ProjectStart: MIN(#REF!)
Name RM_BaseEventDays: Inputs!$E$139
Name RM_EventDaysScale: Inputs!$E$276
Name RM_ExitMultiple: Inputs!$E$261
Name RM_HourlyRate: Inputs!$E$223
Name RM_IO_Months: Inputs!$E$57
Name RM_OutgoingsPct: Inputs!$E$36
Name RM_ShiftHours: Inputs!$E$224
Name RM_StaffPerEvent: Inputs!$E$222
Name RM_SustCapexPct: Inputs!$E$246
Name RM_TerminalGrowth: Inputs!$E$265
Name RM_VHA_Cap: Inputs!$E$146
Name RM_VHA_GBO_Fee: Inputs!$E$145
Name SelectedLevel: 'GANTT – MASTER OPTIONS'!$C$7
Name ShowPhaseBands: 'GANTT – MASTER OPTIONS'!$C$10
Name ShowToday: 'GANTT – MASTER OPTIONS'!$C$9
Name TimeScaleSelection: 'GANTT – MASTER OPTIONS'!$C$5
Name Total_Initial_Capex: 'Construction Timeline'!$G$17

Sheet General Information
A1: Integrated Entertainment and Recreational Development
A2: 349 Bridge Street Melbourne
A3: Live House Music Venue - following our discussions there is a need for a 4,000 to 5,000 live venue for the Melbourne market that is suitably located to avoid issues of noise and congestion for the local community. The location within our proposed precinct will provide a beneficial location for this development and allow for the improved development of access to culture, music, entertainment and activity. We are looking forward to understanding more about this concept from you so that we may prepare a joint presentation to Council, Goodman and the State government teams involved in Sport, Education, Tourism, Planning and Labour.
A5: URWLD - an active leisure concept that will house a Sports Climbing Centre of Excellence as well as a range of 15-18 active leisure activities including surfing, scuba, ice climbing, sports climbing, bouldering, canyoning, coasteering, ninja, junior climb academy, and a range of VR activities such as skiing, snowboarding, squirrel suit, tennis, golf and other immersive game concepts. There will also be an eSports arena and concept area and interactive video games concepts. These will be supported by 4 quality, chef curated F&B concepts and 2 event venues. URWLD addresses a key community and society issue of encouraging the entire populace to be active to support lifestyle mindset change and impact the alarming trend of obesity, diabetes and inactivity that threatens our future generations. By providing an accessible environment to help introduce a broad range of activities that encourage movement we will work to address this through our communications and positioning as well as with our event activities, TedTalks hosted and others to promote improving mobility for all age groups
A7: PARKING - we are in discussions with Wilson Parking to JV on a 900 space parking building connected to URWLD to service the precinct as well as to support the government policy on congestion reduction within the CBD. We will provide business day parking with shuttle service into the CBD area to Spencer St transport hub for trains, trams and buses. In the future when the Plummer St Light Rail/Tram is undertaken by state government the proximity will allow us to reduce shuttle services. The parking building will connect to both the live venue and URWLD buildings
A9: COSM - we have an EOI with a group in Melbourne who are negotiating the license for COSM. This is a highly immersive sports and entertainment experience with also educational opportunities for day use. We believe it will be a highly successful component of the precinct. www.cosm.com
A11: Central Park - in keeping with the need for green space and open areas for common use we have allocated space within the site for a central park which we plan to develop with native landscape focus and a central courtyard as a "FOOD TRUCK" park highlighting handheld foods from numerous cultures as part of our F&B offering. This area will also be used for day time and evening buskers for entertainment.
A13: Employment and Community - We believe that our combined development will create almost 1,000 FTE jobs within our precinct and support the planned redevelopment of the Fishermans Bend Urban Renewal Framework by encouraging further state and federal investment in infrastructure of light rail, metro and roads as well as private investor development of the larger sites for increased residential and commercial use of the area.
A15: The zone we are developing will include, on a site of 34,400 square metres:

Sheet Dashboard
A1: PORT MELBOURNE LIVE HOUSE — EXECUTIVE DASHBOARD
A2: Port Melbourne Live House | P2: Active Scenario | Q2: =Scenarios!$B$4 -> Base
P3: Model Health | Q3: =IF('Model Checks'!B24=0,"OK","FAIL") -> OK
B5: Summary
B6: FY | C6: =IFERROR(Cashflow!D$7,"") -> FY25 | D6: =IFERROR(Cashflow!E$7,"") -> FY26 | E6: =IFERROR(Cashflow!F$7,"") -> FY27 | F6: =IFERROR(Cashflow!G$7,"") -> FY28 | G6: =IFERROR(Cashflow!H$7,"") -> FY29 | H6: =IFERROR(Cashflow!I$7,"") -> FY30 | I6: =IFERROR(Cashflow!J$7,"") -> FY31 | J6: =IFERROR(Cashflow!K$7,"") -> FY32 | ... N6: =IFERROR(Cashflow!O$7,"") -> FY36
B7: Revenue | C7: =IFERROR(Cashflow!D$47,"") -> 0 | D7: =IFERROR(Cashflow!E$47,"") -> 0 | E7: =IFERROR(Cashflow!F$47,"") -> 0 | F7: =IFERROR(Cashflow!G$47,"") -> 18192909 | G7: =IFERROR(Cashflow!H$47,"") -> 19173295 | H7: =IFERROR(Cashflow!I$47,"") -> 20282270 | I7: =IFERROR(Cashflow!J$47,"") -> 20817159 | J7: =IFERROR(Cashflow!K$47,"") -> 21296978 | ... N7: =IFERROR(Cashflow!O$47,"") -> 23361053
B8: EBITDA | C8: =IFERROR(Cashflow!D$63,"") -> 0 | D8: =IFERROR(Cashflow!E$63,"") -> 0 | E8: =IFERROR(Cashflow!F$63,"") -> 0 | F8: =IFERROR(Cashflow!G$63,"") -> 13999302 | G8: =IFERROR(Cashflow!H$63,"") -> 14401312 | H8: =IFERROR(Cashflow!I$63,"") -> 15322990 | I8: =IFERROR(Cashflow!J$63,"") -> 15770796 | J8: =IFERROR(Cashflow!K$63,"") -> 16058922 | ... N8: =IFERROR(Cashflow!O$63,"") -> 16893778
B9: Closing Cash | C9: =IFERROR(Cashflow!D37,"") -> 0 | D9: =IFERROR(Cashflow!E37,"") -> 1707500 | E9: =IFERROR(Cashflow!F37,"") -> 16050500 | F9: =IFERROR(Cashflow!G37,"") -> -1231018.3 | G9: =IFERROR(Cashflow!H37,"") -> -396007.99 | H9: =IFERROR(Cashflow!I37,"") -> 513409.17 | I9: =IFERROR(Cashflow!J37,"") -> 1533142.7 | J9: =IFERROR(Cashflow!K37,"") -> 2307422.4 | ... N9: =IFERROR(Cashflow!O37,"") -> 1.4219797e+08
B10: Total Debt | C10: =IFERROR(Debt!H48,0) -> 0 | D10: =IFERROR(Debt!I48,0) -> 0 | E10: =IFERROR(Debt!J48,0) -> 9220500 | F10: =IFERROR(Debt!K48,0) -> 8196000 | G10: =IFERROR(Debt!L48,0) -> 7171500 | H10: =IFERROR(Debt!M48,0) -> 6147000 | I10: =IFERROR(Debt!N48,0) -> 5122500 | J10: =IFERROR(Debt!O48,0) -> 4098000 | ... N10: =IFERROR(Debt!S48,0) -> 0
B11: DSCR | C11: ='P&L'!H106 | D11: ='P&L'!I106 | E11: ='P&L'!J106 -> 0 | F11: ='P&L'!K106 -> 8.3450465 | G11: ='P&L'!L106 -> 9.0195084 | H11: ='P&L'!M106 -> 10.100328 | I11: ='P&L'!N106 -> 10.972249 | J11: ='P&L'!O106 -> 11.831354 | ... N11: ='P&L'!S106 -> 16.294063
B12: ICR | C12: =IFERROR(IF(Debt!H$57=0,"",Cashflow!D$63/Debt!H$57),"") | D12: =IFERROR(IF(Debt!I$57=0,"",Cashflow!E$63/Debt!I$57),"") | E12: =IFERROR(IF(Debt!J$57=0,"",Cashflow!F$63/Debt!J$57),"") -> 0 | F12: =IFERROR(IF(Debt!K$57=0,"",Cashflow!G$63/Debt!K$57),"") -> 20.094884 | G12: =IFERROR(IF(Debt!L$57=0,"",Cashflow!H$63/Debt!L$57),"") -> 23.428196 | H12: =IFERROR(IF(Debt!M$57=0,"",Cashflow!I$63/Debt!M$57),"") -> 28.762604 | I12: =IFERROR(IF(Debt!N$57=0,"",Cashflow!J$63/Debt!N$57),"") -> 34.985571 | J12: =IFERROR(IF(Debt!O$57=0,"",Cashflow!K$63/Debt!O$57),"") -> 43.541355 | ... N12: =IFERROR(IF(Debt!S$57=0,"",Cashflow!O$63/Debt!S$57),"") -> 412.24445
B13: Net Leverage (Net Debt/EBITDA) | C13: =IFERROR(IF(Cashflow!D$63=0,"",((Cashflow!D$70+Cashflow!D$71)-Cashflow!D$38)/Cashflow!D$63),"") | D13: =IFERROR(IF(Cashflow!E$63=0,"",((Cashflow!E$70+Cashflow!E$71)-Cashflow!E$38)/Cashflow!E$63),"") | E13: =IFERROR(IF(Cashflow!F$63=0,"",((Cashflow!F$70+Cashflow!F$71)-Cashflow!F$38)/Cashflow!F$63),"") | F13: =IFERROR(IF(Cashflow!G$63=0,"",((Cashflow!G$70+Cashflow!G$71)-Cashflow!G$38)/Cashflow!G$63),"") -> 0.58545776 | G13: =IFERROR(IF(Cashflow!H$63=0,"",((Cashflow!H$70+Cashflow!H$71)-Cashflow!H$38)/Cashflow!H$63),"") -> 0.49797545 | H13: =IFERROR(IF(Cashflow!I$63=0,"",((Cashflow!I$70+Cashflow!I$71)-Cashflow!I$38)/Cashflow!I$63),"") -> 0.40116192 | I13: =IFERROR(IF(Cashflow!J$63=0,"",((Cashflow!J$70+Cashflow!J$71)-Cashflow!J$38)/Cashflow!J$63),"") -> 0.32480923 | J13: =IFERROR(IF(Cashflow!K$63=0,"",((Cashflow!K$70+Cashflow!K$71)-Cashflow!K$38)/Cashflow!K$63),"") -> 0.25518524 | ... N13: =IFERROR(IF(Cashflow!O$63=0,"",((Cashflow!O$70+Cashflow!O$71)-Cashflow!O$38)/Cashflow!O$63),"") -> 0
A15: PORT MELBOURNE LIVE HOUSE — EXECUTIVE DASHBOARD
A16: Port Melbourne Live House | P16: Active Scenario | Q16: =Scenarios!B4 -> Base
P17: Model Health | Q17: =Q3 -> OK
B19: FINANCIAL SUMMARY
C20: FY25 | D20: FY26 | E20: FY27 | F20: FY28 | G20: FY29 | H20: FY30 | I20: FY31 | J20: FY32 | K20: FY33 | L20: FY34 | M20: FY35 | N20: FY36
B21: Revenue | C21: ='P&L'!I28 -> 0 | D21: ='P&L'!J28 -> 0 | E21: ='P&L'!K28 -> 18192909 | F21: ='P&L'!L28 -> 19173295 | G21: ='P&L'!M28 -> 20282270 | H21: ='P&L'!N28 -> 20817159 | I21: ='P&L'!O28 -> 21296978 | J21: ='P&L'!P28 -> 21790858 | ... M21: ='P&L'!S28 -> 23361053 | N21: ='P&L'!S28 -> 23361053
B22: EBITDA | C22: ='P&L'!I77 -> 0 | D22: ='P&L'!J77 -> 0 | E22: ='P&L'!K77 -> 13999302 | F22: ='P&L'!L77 -> 14401312 | G22: ='P&L'!M77 -> 15322990 | H22: ='P&L'!N77 -> 15770796 | I22: ='P&L'!O77 -> 16058922 | J22: ='P&L'!P77 -> 15923838 | ... M22: ='P&L'!S77 -> 16893778 | N22: ='P&L'!S77 -> 16893778
B23: Closing Cash | C23: ='Balance Sheet'!G10 -> 1707500 | D23: ='Balance Sheet'!H10 -> 16050500 | E23: ='Balance Sheet'!I10 -> -1231018.3 | F23: ='Balance Sheet'!J10 -> -396007.99 | G23: ='Balance Sheet'!K10 -> 513409.17 | H23: ='Balance Sheet'!L10 -> 1533142.7 | I23: ='Balance Sheet'!M10 -> 2307422.4 | J23: ='Balance Sheet'!N10 -> 3446826.6 | ... M23: ='Balance Sheet'!Q10 -> 1.4219797e+08 | N23: ='Balance Sheet'!Q10 -> 1.4219797e+08
B24: Total Debt | C24: =Debt!I24+Debt!I43 -> 0 | D24: =Debt!J24+Debt!J43 -> 9220500 | E24: =Debt!K24+Debt!K43 -> 8196000 | F24: =Debt!L24+Debt!L43 -> 7171500 | G24: =Debt!M24+Debt!M43 -> 6147000 | H24: =Debt!N24+Debt!N43 -> 5122500 | I24: =Debt!O24+Debt!O43 -> 4098000 | J24: =Debt!P24+Debt!P43 -> 3073500 | ... M24: =Debt!S24+Debt!S43 -> 0 | N24: =Debt!S24+Debt!S43 -> 0
B27: DEBT & LEVERAGE | E27: KEY INVESTMENT METRICS
B28: Metric | C28: Value | E28: Metric | F28: Value
B29: Total Debt Facility | C29: =Inputs!E54 -> 10245000 | E29: Total Capex | F29: =Inputs!E113 -> 17075000
B30: Bank Debt | C30: =Inputs!E54 -> 10245000 | E30: Total Equity | F30: =Inputs!E75 -> 7610000
B31: PE Equity | C31: =Inputs!E73 -> 5122500 | E31: Total Debt | F31: =Inputs!E54 -> 10245000
B32: Bank Term (years) | C32: =Inputs!E52 -> 10 | E32: Debt/Equity Ratio | F32: =IF(Inputs!E75>0,Inputs!E54/Inputs!E75,0) -> 1.3462549
B33: PE Equity Injection Year | C33: =Inputs!E86 -> FY27 | E33: Project IRR | F33: =Valuations!C20 -> 0.75463788
B34: Bank Interest Rate | C34: =Inputs!E51 -> 0.08 | E34: Equity IRR | F34: =Valuations!C22 -> 0.36201056
B35: Shareholder Loan Toggle | C35: =IF(Inputs!E88=0,"OFF","ON") -> OFF | E35: MOIC | F35: =Valuations!C24 -> 21.968719
B36: Debt/Total Capex | C36: =(Inputs!E54+Inputs!E63)/Inputs!E113 -> 0.6 | E36: Payback Period | F36: =Valuations!C25 -> FY29
B39: VALUATION SUMMARY
B40: Metric | C40: Value | D40: Notes
B41: WACC | C41: =Valuations!C9 -> 0.1 | D41: Discount rate
B42: Exit Multiple | C42: =Valuations!C15 -> 8 | D42: EBITDA multiple
B43: Exit EBITDA | C43: =Valuations!C72 -> 16893778 | D43: FY36 EBITDA
B44: Terminal Value | C44: =Valuations!C74 -> 1.3515022e+08 | D44: Exit value
B45: Enterprise Value | C45: =Valuations!C91 -> 92246992 | D45: DCF valuation
B46: Net Debt (Exit) | C46: =Valuations!C93+Valuations!C94 -> 6830000 | D46: Debt - Cash at exit
B47: Equity Value | C47: =Valuations!C23 -> 99076992 | D47: EV less Net Debt
B50: RETURN METRICS
B51: Metric | C51: Value | D51: Description
B52: Project IRR | C52: =Valuations!C20 -> 0.75463788 | D52: Unlevered return
B53: Equity IRR | C53: =Valuations!C22 -> 0.36201056 | D53: Levered return
B54: Project NPV @ WACC | C54: =Valuations!C21 -> 92246992 | D54: Value creation
B55: Equity NPV @ Ke | C55: =Valuations!C23 -> 99076992 | D55: Value to equity
B56: MOIC | C56: =Valuations!C24 -> 21.968719 | D56: Cash multiple
B57: Yield on Cost | C57: =Valuations!C26 -> 0.81987128 | D57: Stabilised EBITDA / Capex
B64: DEBT & LEVERAGE | E64: KEY INVESTMENT METRICS | F64: Value
B65: Metric | C65: Value | E65: Metric | F65: Value
B66: Total Debt Facility | C66: =Debt!C5+Debt!D5 -> 10245000 | E66: Total Capex | F66: =Inputs!E113 -> 17075000
B67: Bank Debt | C67: =Debt!C5 -> 10245000 | E67: Equity Required | F67: =SUM(Cashflow!D13:O13) -> 2487500
B68: PE Loan | C68: =Debt!D5 -> 0 | E68: Total Debt | F68: =Debt!C5+Debt!D5 -> 10245000
B69: Bank Term (years) | C69: =Debt!C6 -> 10 | E69: Debt/Equity Ratio | F69: =F68/F67 -> 4.118593
B70: PE Term (years) | C70: =Debt!D6 -> 10 | E70: Project IRR | F70: =Valuations!C109 -> 0.75463788
B71: Bank Interest Rate | C71: =Debt!C7 -> 0.08 | E71: Equity IRR | F71: =Valuations!C123 -> 0.36201056
B72: PE Interest Rate | C72: =Debt!D7 -> 0.12 | E72: MOIC | F72: =Valuations!C127 -> 21.968719
B73: Debt Payoff Year | C73: FY32 | E73: Payback Period | F73: FY34
B74: Debt/Total Capex | C74: =C66/Inputs!E113 -> 0.6
B75: VENUE CAPACITY | E75: PROFITABILITY METRICS (EXIT FY)
B76: Configuration | C76: Capacity | E76: Metric | F76: Value
B77: Music GA (Large) | C77: ='Revenue Assumptions'!D5 -> 5000 | E77: Total Revenue | F77: ='P&L'!S28 -> 23361053
B78: Music GA (Medium) | C78: ='Revenue Assumptions'!D6 -> 3000 | E78: Gross Profit | F78: ='P&L'!S41 -> 23262557
B79: Music GA (Small) | C79: ='Revenue Assumptions'!D7 -> 1500 | E79: Gross Margin % | F79: ='P&L'!S42 -> 0.99578374
B80: EDM/Dance | C80: ='Revenue Assumptions'!D8 -> 3500 | E80: EBITDA | F80: ='P&L'!S77 -> 16893778
B81: Seated Events | C81: ='Revenue Assumptions'!D9 -> 3500 | E81: EBITDA Margin % | F81: ='P&L'!S78 -> 0.72315994
B82: MICE/Corporate | C82: ='Revenue Assumptions'!D12 -> 3500 | E82: NPAT | F82: ='P&L'!S93 -> 11796958
B83: Community | C83: ='Revenue Assumptions'!D13 -> 2000 | E83: Net Margin % | F83: =IF(F77=0,0,F82/F77) -> 0.50498401
B84: Max Capacity | C84: =MAX(C77:C83) -> 5000
B86: PROJECT TIMELINE | E86: REVENUE MIX (EXIT FY)
B87: Milestone | C87: Date | E87: Stream | F87: Value
B88: Model Start | C88: =Inputs!E9 -> 45715 | E88: VHA | F88: =IFERROR(INDEX('P&L'!$H$14:$S$14, MATCH(Inputs!$E$266,'P&L'!$H$6:$S$6,0)),0) -> 7499918.4
B89: Lease Signing | C89: =Inputs!E14 -> 46174 | E89: Premium Sales | F89: =IFERROR(INDEX('P&L'!$H$15:$S$15, MATCH(Inputs!$E$266,'P&L'!$H$6:$S$6,0)),0) -> 1024083.9
B90: Construction Start | C90: =Inputs!E18 -> 46420 | E90: Premium F&B | F90: =IFERROR(INDEX('P&L'!$H$16:$S$16, MATCH(Inputs!$E$266,'P&L'!$H$6:$S$6,0)),0) -> 142788.36
B91: Construction End | C91: =Inputs!E19 -> 46568 | E91: F&B | F91: =IFERROR(INDEX('P&L'!$H$17:$S$17, MATCH(Inputs!$E$266,'P&L'!$H$6:$S$6,0)),0) -> 138629.47
B92: Operations Start | C92: =Inputs!E22 -> 46569 | E92: Merchandise | F92: =IFERROR(INDEX('P&L'!$H$18:$S$18, MATCH(Inputs!$E$266,'P&L'!$H$6:$S$6,0)),0) -> 7152098
B93: Model End | C93: =Inputs!E10 -> 50099 | E93: Equipment Hire | F93: =IFERROR(INDEX('P&L'!$H$20:$S$20, MATCH(Inputs!$E$266,'P&L'!$H$6:$S$6,0)),0) -> 2548000
B94: Exit Year | C94: =Valuations!C13 -> FY36 | E94: Sponsorship | F94: =IFERROR(INDEX('P&L'!$H$24:$S$24, MATCH(Inputs!$E$266,'P&L'!$H$6:$S$6,0)),0) -> 2310396.5
B95: Project Duration | C95: ="12 years" -> 12 years | E95: Advertising | F95: =IFERROR(INDEX('P&L'!$H$25:$S$25, MATCH(Inputs!$E$266,'P&L'!$H$6:$S$6,0)),0) -> 718096.21
B97: OPEX MIX (EXIT FY) | E97: EVENT DAYS MIX (EXIT FY)
B98: Category | C98: Value | E98: Event Type | F98: Days
B99: Staff Costs | C99: =IFERROR(INDEX('P&L'!$H$68:$S$68, MATCH(Inputs!$E$266,'P&L'!$H$6:$S$6,0)),0) -> 2831589.5 | E99: Music GA (all tiers) | F99: =IFERROR((INDEX('Calendar Assumptions'!$F$5:$P$5,MATCH(Inputs!$E$266,'Calendar Assumptions'!$F$4:$P$4,0))+INDEX('Calendar Assumptions'!$F$6:$P$6,MATCH(Inputs!$E$266,'Calendar Assumptions'!$F$4:$P$4,0))+INDEX('Calendar Assumptions'!$F$7:$P$7,MATCH(Inputs!$E$266,'Calendar Assumptions'!$F$4:$P$4,0))),0) -> 52
B100: Lease / Rent | C100: =IFERROR(INDEX('P&L'!$H$45:$S$45, MATCH(Inputs!$E$266,'P&L'!$H$6:$S$6,0)),0) -> 350000 | E100: EDM | F100: =IFERROR(INDEX('Calendar Assumptions'!$F$8:$P$8, MATCH(Inputs!$E$266,'Calendar Assumptions'!$F$4:$P$4,0)),0) -> 18
B101: Utilities | C101: =IFERROR(INDEX('P&L'!$H$46:$S$46, MATCH(Inputs!$E$266,'P&L'!$H$6:$S$6,0)),0) -> 260954.64 | E101: Seated Music | F101: =IFERROR(INDEX('Calendar Assumptions'!$F$9:$P$9, MATCH(Inputs!$E$266,'Calendar Assumptions'!$F$4:$P$4,0)),0) -> 15
B102: Maintenance | C102: 0 | E102: Comedy | F102: =IFERROR(INDEX('Calendar Assumptions'!$F$10:$P$10, MATCH(Inputs!$E$266,'Calendar Assumptions'!$F$4:$P$4,0)),0) -> 15
B103: Marketing | C103: =IFERROR(INDEX('P&L'!$H$48:$S$48, MATCH(Inputs!$E$266,'P&L'!$H$6:$S$6,0)),0) -> 65238.659 | E103: Sports | F103: =IFERROR(INDEX('Calendar Assumptions'!$F$11:$P$11, MATCH(Inputs!$E$266,'Calendar Assumptions'!$F$4:$P$4,0)),0) -> 3
B104: Admin/Legal/Insurance/etc | C104: =IFERROR((INDEX('P&L'!$H$61:$S$61, MATCH(Inputs!$E$266,'P&L'!$H$6:$S$6,0))+INDEX('P&L'!$H$62:$S$62, MATCH(Inputs!$E$266,'P&L'!$H$6:$S$6,0))+INDEX('P&L'!$H$63:$S$63, MATCH(Inputs!$E$266,'P&L'!$H$6:$S$6,0))+INDEX('P&L'!$H$64:$S$64, MATCH(Inputs!$E$266,'P&L'!$H$6:$S$6,0))+INDEX('P&L'!$H$65:$S$65, MATCH(Inputs!$E$266,'P&L'!$H$6:$S$6,0))+INDEX('P&L'!$H$66:$S$66, MATCH(Inputs!$E$266,'P&L'!$H$6:$S$6,0))),0) -> 596519.66 | E104: MICE | F104: =IFERROR(INDEX('Calendar Assumptions'!$F$12:$P$12, MATCH(Inputs!$E$266,'Calendar Assumptions'!$F$4:$P$4,0)),0) -> 29
B105: Other OPEX | C105: 0 | E105: Community | F105: =IFERROR(INDEX('Calendar Assumptions'!$F$13:$P$13, MATCH(Inputs!$E$266,'Calendar Assumptions'!$F$4:$P$4,0)),0) -> 12
E106: Live Site | F106: =IFERROR(INDEX('Calendar Assumptions'!$F$14:$P$14, MATCH(Inputs!$E$266,'Calendar Assumptions'!$F$4:$P$4,0)),0) -> 10
B108: DEBT COVERAGE RATIOS | E108: EVENT INDUSTRY KPIs (EXIT FY)
B109: Metric | C109: Value | E109: Metric | F109: Value | G109: Units
B110: Average DSCR | C110: =AVERAGE('P&L'!K106,'P&L'!L106,'P&L'!M106,'P&L'!N106) -> 9.609283 | E110: Annual Event Days | F110: ='Calendar Assumptions'!N16 -> 180 | G110: days
B111: Minimum DSCR | C111: =MIN('P&L'!K106,'P&L'!L106,'P&L'!M106,'P&L'!N106) -> 8.3450465 | E111: Total Revenue | F111: ='P&L'!S28 -> 23361053 | G111: A$
B112: Average ICR | C112: =AVERAGE('P&L'!K77/'P&L'!K85,'P&L'!L77/'P&L'!L85,'P&L'!M77/'P&L'!M85,'P&L'!N77/'P&L'!N85) -> 26.817814 | E112: Revenue per Event Day | F112: =F111/F110 -> 129783.63 | G112: A$/day
B113: Minimum ICR | C113: =MIN('P&L'!K77/'P&L'!K85,'P&L'!L77/'P&L'!L85,'P&L'!M77/'P&L'!M85,'P&L'!N77/'P&L'!N85) -> 20.094884 | E113: EBITDA per Event Day | F113: ='P&L'!S77/F110 -> 93854.32 | G113: A$/day
E114: Yield on Cost | F114: =Valuations!C26 -> 0.81987128 | G114: %
B118: SENSITIVITY SUMMARY
B119: Enterprise Value Sensitivity (WACC vs Exit Multiple)
B120: EV ($m) | C120: 6.0x | D120: 7.0x | E120: 8.0x | F120: 9.0x | G120: 10.0x
B121: 0.08 | C121: =Valuations!$C$72*6/(1+0.08)^10 -> 46950527 | D121: =Valuations!$C$72*7/(1+0.08)^10 -> 54775615 | E121: =Valuations!$C$72*8/(1+0.08)^10 -> 62600702 | F121: =Valuations!$C$72*9/(1+0.08)^10 -> 70425790 | G121: =Valuations!$C$72*10/(1+0.08)^10 -> 78250878
...

Sheet Valuations
B1: PORT MELBOURNE LIVE HOUSE — VALUATIONS
B2: Architecture sheet: valuation approaches, return metrics (IRR/NPV), and sensitivity framework. Calculations will be wired in the next step.
B4: VALUATION CONTROLS & INPUTS
B5: Active Scenario | C5: =Scenarios!B4 -> Base | D5: Pulled from Scenarios toggle (read-only)
B6: Valuation Currency | C6: AUD | D6: Match model currency
B7: Valuation Date | C7: =Inputs!E14 -> 46174 | D7: Leave blank or set to transaction / IC date
B8: Discount Rate Basis | C8: WACC (FCFF) / Ke (Equity) | D8: Choose which return metric you’re presenting
B9: WACC (nominal) | C9: =Inputs!E257 -> 0.1 | D9: Linked to Inputs!E223
B10: Cost of Equity (Ke) | C10: =Inputs!E258 -> 0.15 | D10: Linked to Inputs!E224
B11: Cost of Debt (Kd) | C11: =Debt!C7 -> 0.08 | D11: To be linked to Debt terms
B12: Corporate Tax Rate | C12: =Inputs!E260 -> 0.3 | D12: Linked to Inputs!E226
B13: Exit FY | C13: =Inputs!E266 -> FY36 | D13: Linked to Inputs!E232
B14: Exit Method | C14: ="EBITDA Multiple" -> EBITDA Multiple | D14: Choose primary method
B15: Exit EBITDA Multiple | C15: =Inputs!E261 -> 8 | D15: Linked to Inputs!E227
B16: Mid-year convention | C16: =Inputs!E263 -> No | D16: Linked to Inputs!E229
B19: Metric | C19: Value | D19: Units / Format | E19: Cash Flow Basis | F19: Method / Formula Guidance + Link Source
B20: Project IRR (Unlevered) | C20: =C109 -> 0.75463788 | D20: % | E20: Unlevered | F20: XIRR(unlevered FCF, dates) — exclude debt & equity flows | Source: Cashflow (build Unlevered FCF series)
B21: Project NPV @ WACC | C21: =C91 -> 92246992 | D21: A$ | E21: Unlevered | F21: XNPV(WACC, unlevered FCF, dates) OR PV factors | Source: Valuations DCF block below
B22: Equity IRR (Levered) | C22: =C123 -> 0.36201056 | D22: % | E22: Equity | F22: XIRR(equity cash flows, dates) | Source: Equity injections + distributions + exit equity
B23: Equity NPV @ Ke | C23: =C98 -> 99076992 | D23: A$ | E23: Equity | F23: XNPV(Ke, equity cash flows, dates) | Source: Equity cash flow schedule
B24: Equity MOIC | C24: =C127 -> 21.968719 | D24: x | E24: Equity | F24: (Total distributions + exit equity) / Total equity injected | Source: Dashboard already calculates
B25: Payback Period (Equity) | C25: =C128 -> FY29 | D25: FY | E25: Equity | F25: First year cumulative equity distributions exceed equity injected | Source: To be added (optional)
B26: Yield on Cost (Stabilised) | C26: =C130 -> 0.81987128 | D26: % | E26: Operating | F26: Stabilised EBITDA / Total Project Cost | Source: Dashboard already calculates
B29: WEIGHTED AVERAGE COST OF CAPITAL (WACC)
B30: Component | C30: Value | D30: Source/Formula
B31: Risk-Free Rate | C31: =Inputs!E267 -> 0.04 | D31: Linked to Inputs!E233
B32: Market Risk Premium | C32: =0.065 -> 0.065 | D32: Hard-coded: 6.5% historical equity premium (add to Inputs if row available)
B33: Asset Beta (Unlevered) | C33: =Inputs!E269 -> 0.8 | D33: Linked to Inputs!E235
B34: Target D/E Ratio | C34: =Dashboard!F68/Dashboard!F67 -> 4.118593 | D34: From model capital structure
B35: Tax Rate | C35: =C12 -> 0.3 | D35: Corporate tax rate
B36: Levered Beta | C36: =C33*(1+(1-C35)*C34) -> 3.1064121 | D36: Hamada formula: βu×(1+(1-T)×D/E)
B37: Cost of Equity (Ke) | C37: =C31+C36*C32 -> 0.24191678 | D37: CAPM: Rf + β × MRP
B38: Pre-Tax Cost of Debt (Kd) | C38: =C11 -> 0.08 | D38: From Debt sheet
B39: After-Tax Cost of Debt | C39: =C38*(1-C35) -> 0.056 | D39: Kd × (1-T)
B41: Weight of Equity | C41: =1/(1+C34) -> 0.19536619 | D41: E/(D+E)
B42: Weight of Debt | C42: =C34/(1+C34) -> 0.80463381 | D42: D/(D+E)
B44: WACC (Calculated) | C44: =C41*C37+C42*C39 -> 0.092321854 | D44: We×Ke + Wd×Kd(1-T)
B45: WACC (Input Override) | C45: =C9 -> 0.1 | D45: Manual input for sensitivity
B47: Applied Discount Rate | C47: =C45 -> 0.1 | D47: Uses input WACC for discounting
B50: UNLEVERED DCF VALUATION
B51: Free Cash Flow to Firm (FCFF) Schedule
B53: Metric | C53: ='P&L'!H6 -> FY25 | D53: ='P&L'!I6 -> FY26 | E53: ='P&L'!J6 -> FY27 | F53: ='P&L'!K6 -> FY28 | G53: ='P&L'!L6 -> FY29 | H53: ='P&L'!M6 -> FY30 | I53: ='P&L'!N6 -> FY31 | J53: ='P&L'!O6 -> FY32 | ... N53: ='P&L'!S6 -> FY36
B54: FY End Date | C54: ='P&L'!H5 -> 45838 | D54: ='P&L'!I5 -> 46203 | E54: ='P&L'!J5 -> 46568 | F54: ='P&L'!K5 -> 46934 | G54: ='P&L'!L5 -> 47299 | H54: ='P&L'!M5 -> 47664 | I54: ='P&L'!N5 -> 48029 | J54: ='P&L'!O5 -> 48395 | ... N54: ='P&L'!S5 -> 49856
B55: Period Number | C55: =IF(C54="","",(C54-$C$7)/365) -> -0.92054795 | D55: =IF(D54="","",(D54-$C$7)/365) -> 0.079452055 | E55: =IF(E54="","",(E54-$C$7)/365) -> 1.0794521 | F55: =IF(F54="","",(F54-$C$7)/365) -> 2.0821918 | G55: =IF(G54="","",(G54-$C$7)/365) -> 3.0821918 | H55: =IF(H54="","",(H54-$C$7)/365) -> 4.0821918 | I55: =IF(I54="","",(I54-$C$7)/365) -> 5.0821918 | J55: =IF(J54="","",(J54-$C$7)/365) -> 6.0849315 | ... N55: =IF(N54="","",(N54-$C$7)/365) -> 10.087671
B57: Revenue | C57: ='P&L'!H28 -> 0 | D57: ='P&L'!I28 -> 0 | E57: ='P&L'!J28 -> 0 | F57: ='P&L'!K28 -> 18192909 | G57: ='P&L'!L28 -> 19173295 | H57: ='P&L'!M28 -> 20282270 | I57: ='P&L'!N28 -> 20817159 | J57: ='P&L'!O28 -> 21296978 | ... N57: ='P&L'!S28 -> 23361053
B58: EBITDA | C58: ='P&L'!H77 -> 0 | D58: ='P&L'!I77 -> 0 | E58: ='P&L'!J77 -> 0 | F58: ='P&L'!K77 -> 13999302 | G58: ='P&L'!L77 -> 14401312 | H58: ='P&L'!M77 -> 15322990 | I58: ='P&L'!N77 -> 15770796 | J58: ='P&L'!O77 -> 16058922 | ... N58: ='P&L'!S77 -> 16893778
B59: Less: Depreciation | C59: =-'P&L'!H81 -> 0 | D59: =-'P&L'!I81 -> 0 | E59: =-'P&L'!J81 -> 0 | F59: =-'P&L'!K81 -> 0 | G59: =-'P&L'!L81 -> 0 | H59: =-'P&L'!M81 -> 0 | I59: =-'P&L'!N81 -> 0 | J59: =-'P&L'!O81 -> 0 | ... N59: =-'P&L'!S81 -> 0
B60: EBIT | C60: =C58+C59 -> 0 | D60: =D58+D59 -> 0 | E60: =E58+E59 -> 0 | F60: =F58+F59 -> 13999302 | G60: =G58+G59 -> 14401312 | H60: =H58+H59 -> 15322990 | I60: =I58+I59 -> 15770796 | J60: =J58+J59 -> 16058922 | ... N60: =N58+N59 -> 16893778
B61: Less: Tax on EBIT | C61: =-MAX(0,C60)*$C$35 -> 0 | D61: =-MAX(0,D60)*$C$35 -> 0 | E61: =-MAX(0,E60)*$C$35 -> 0 | F61: =-MAX(0,F60)*$C$35 -> -4199790.6 | G61: =-MAX(0,G60)*$C$35 -> -4320393.7 | H61: =-MAX(0,H60)*$C$35 -> -4596897 | I61: =-MAX(0,I60)*$C$35 -> -4731238.8 | J61: =-MAX(0,J60)*$C$35 -> -4817676.7 | ... N61: =-MAX(0,N60)*$C$35 -> -5068133.3
B62: NOPAT | C62: =C60+C61 -> 0 | D62: =D60+D61 -> 0 | E62: =E60+E61 -> 0 | F62: =F60+F61 -> 9799511.5 | G62: =G60+G61 -> 10080919 | H62: =H60+H61 -> 10726093 | I62: =I60+I61 -> 11039557 | J62: =J60+J61 -> 11241246 | ... N62: =N60+N61 -> 11825644
B63: Add: Depreciation | C63: ='P&L'!H81 -> 0 | D63: ='P&L'!I81 -> 0 | E63: ='P&L'!J81 -> 0 | F63: ='P&L'!K81 -> 0 | G63: ='P&L'!L81 -> 0 | H63: ='P&L'!M81 -> 0 | I63: ='P&L'!N81 -> 0 | J63: ='P&L'!O81 -> 0 | ... N63: ='P&L'!S81 -> 0
B64: Less: Capex | C64: =Cashflow!D26 -> 0 | D64: =Cashflow!E26 -> -780000 | E64: =Cashflow!F26 -> 0 | F64: =Cashflow!G26 -> -17075000 | G64: =Cashflow!H26 -> 0 | H64: =Cashflow!I26 -> 0 | I64: =Cashflow!J26 -> 0 | J64: =Cashflow!K26 -> 0 | ... N64: =Cashflow!O26 -> 0
B65: Less: Change in NWC | C65: =IFERROR(Cashflow!D35,0) -> 0 | D65: =IFERROR(Cashflow!E35,0) -> 0 | E65: =IFERROR(Cashflow!F35,0) -> 0 | F65: =IFERROR(Cashflow!G35,0) -> -981418.65 | G65: =IFERROR(Cashflow!H35,0) -> -9466.7833 | H65: =IFERROR(Cashflow!I35,0) -> -68172.408 | I65: =IFERROR(Cashflow!J35,0) -> -33278.846 | J65: =IFERROR(Cashflow!K35,0) -> -15908.583 | ... M65: =IFERROR(Cashflow!N35,0) -> -20164.518 | N65: =0 -> 0
B66: Unlevered Free Cash Flow (FCFF) | C66: =C62+C63+C64+C65 -> 0 | D66: =D62+D63+D64+D65 -> -780000 | E66: =E62+E63+E64+E65 -> 0 | F66: =F62+F63+F64+F65 -> -8256907.2 | G66: =G62+G63+G64+G65 -> 10071452 | H66: =H62+H63+H64+H65 -> 10657921 | I66: =I62+I63+I64+I65 -> 11006278 | J66: =J62+J63+J64+J65 -> 11225337 | ... N66: =N62+N63+N64+N65 -> 11825644
B69: TERMINAL VALUE & DISCOUNTING
B71: Exit Year | C71: =C13 -> FY36
B72: Exit EBITDA | C72: =N58 -> 16893778
B73: Exit Multiple | C73: =C15 -> 8
B74: Terminal Value (EV) | C74: =C72*C73 -> 1.3515022e+08
B76: Discounting Schedule
B77: Metric | C77: =C53 -> FY25 | D77: =D53 -> FY26 | E77: =E53 -> FY27 | F77: =F53 -> FY28 | G77: =G53 -> FY29 | H77: =H53 -> FY30 | I77: =I53 -> FY31 | J77: =J53 -> FY32 | ... N77: =N53 -> FY36
B78: Period (Years) | C78: =C55 -> -0.92054795 | D78: =D55 -> 0.079452055 | E78: =E55 -> 1.0794521 | F78: =F55 -> 2.0821918 | G78: =G55 -> 3.0821918 | H78: =H55 -> 4.0821918 | I78: =I55 -> 5.0821918 | J78: =J55 -> 6.0849315 | ... N78: =N55 -> 10.087671
B79: Discount Factor | C79: =IF(C78="","",1/(1+$C$47)^C78) -> 1.0917016 | D79: =IF(D78="","",1/(1+$C$47)^D78) -> 0.99245601 | E79: =IF(E78="","",1/(1+$C$47)^E78) -> 0.90223274 | F79: =IF(F78="","",1/(1+$C$47)^F78) -> 0.81999743 | G79: =IF(G78="","",1/(1+$C$47)^G78) -> 0.74545221 | H79: =IF(H78="","",1/(1+$C$47)^H78) -> 0.67768383 | I79: =IF(I78="","",1/(1+$C$47)^I78) -> 0.61607621 | J79: =IF(J78="","",1/(1+$C$47)^J78) -> 0.55992305 | ... N79: =IF(N78="","",1/(1+$C$47)^N78) -> 0.38233513
B80: Unlevered FCF | C80: =C66 -> 0 | D80: =D66 -> -780000 | E80: =E66 -> 0 | F80: =F66 -> -8256907.2 | G80: =G66 -> 10071452 | H80: =H66 -> 10657921 | I80: =I66 -> 11006278 | J80: =J66 -> 11225337 | ... N80: =N66 -> 11825644
B81: Terminal Value | C81: =0 -> 0 | D81: =0 -> 0 | E81: =0 -> 0 | F81: =0 -> 0 | G81: =0 -> 0 | H81: =0 -> 0 | I81: =0 -> 0 | J81: =0 -> 0 | ... M81: =0 -> 0 | N81: =$C$74 -> 1.3515022e+08
B82: PV of FCF | C82: =IF(C79="","",C80*C79) -> 0 | D82: =IF(D79="","",D80*D79) -> -774115.69 | E82: =IF(E79="","",E80*E79) -> 0 | F82: =IF(F79="","",F80*F79) -> -6770642.7 | G82: =IF(G79="","",G80*G79) -> 7507786 | H82: =IF(H79="","",H80*H79) -> 7222700.4 | I82: =IF(I79="","",I80*I79) -> 6780706.2 | J82: =IF(J79="","",J80*J79) -> 6285325 | ... N82: =IF(N79="","",N80*N79) -> 4521359.2
B83: PV of Terminal Value | C83: =IF(C79="","",C81*C79) -> 0 | D83: =IF(D79="","",D81*D79) -> 0 | E83: =IF(E79="","",E81*E79) -> 0 | F83: =IF(F79="","",F81*F79) -> 0 | G83: =IF(G79="","",G81*G79) -> 0 | H83: =IF(H79="","",H81*H79) -> 0 | I83: =IF(I79="","",I81*I79) -> 0 | J83: =IF(J79="","",J81*J79) -> 0 | ... N83: =IF(N79="","",N81*N79) -> 51672677
B86: ENTERPRISE VALUE TO EQUITY VALUE BRIDGE
B88: Component | C88: Value | D88: Notes
B89: Sum of PV of FCF | C89: =SUM(C82:N82) -> 40574315 | D89: Present value of forecast period cash flows
B90: PV of Terminal Value | C90: =SUM(C83:N83) -> 51672677 | D90: Discounted exit value
B91: Enterprise Value (DCF) | C91: =C89+C90 -> 92246992 | D91: Total DCF enterprise value
B93: Less: Net Debt at Valuation Date | C93: =-Debt!J24-Debt!J41 -> -9220500 | D93: Outstanding debt at valuation date
B94: Add: Cash at Valuation Date | C94: ='Balance Sheet'!H10 -> 16050500 | D94: Available cash balance
B95: Less: Minority Interest | C95: =0 -> 0 | D95: If applicable
B96: Add: Associate Investments | C96: =0 -> 0 | D96: If applicable
B98: Equity Value | C98: =C91+C93+C94+C95+C96 -> 99076992 | D98: EV - Net Debt + Adjustments
B101: RETURN METRICS
B103: Project Returns (Unlevered)
B105: Unlevered Cash Flow Schedule | C105: =C53 -> FY25 | D105: =D53 -> FY26 | E105: =E53 -> FY27 | F105: =F53 -> FY28 | G105: =G53 -> FY29 | H105: =H53 -> FY30 | I105: =I53 -> FY31 | J105: =J53 -> FY32 | ... N105: =N53 -> FY36
B106: Date | C106: =C54 -> 45838 | D106: =D54 -> 46203 | E106: =E54 -> 46568 | F106: =F54 -> 46934 | G106: =G54 -> 47299 | H106: =H54 -> 47664 | I106: =I54 -> 48029 | J106: =J54 -> 48395 | ... N106: =N54 -> 49856
B107: Unlevered CF + TV | C107: =C80+C81 -> 0 | D107: =D80+D81 -> -780000 | E107: =E80+E81 -> 0 | F107: =F80+F81 -> -8256907.2 | G107: =G80+G81 -> 10071452 | H107: =H80+H81 -> 10657921 | I107: =I80+I81 -> 11006278 | J107: =J80+J81 -> 11225337 | ... N107: =N80+N81 -> 1.4697587e+08
B109: Project IRR (Unlevered) | C109: =(C181/C182)^(1/10)-1 -> 0.75463788 | D109: Approximate CAGR method
B110: Project NPV @ WACC | C110: =C91 -> 92246992 | D110: Present value of all unlevered cash flows
B113: Equity Returns (Levered)
B115: Equity Cash Flow Schedule | C115: =C53 -> FY25 | D115: =D53 -> FY26 | E115: =E53 -> FY27 | F115: =F53 -> FY28 | G115: =G53 -> FY29 | H115: =H53 -> FY30 | I115: =I53 -> FY31 | J115: =J53 -> FY32 | ... N115: =N53 -> FY36
B116: Date | C116: =C106 -> 45838 | D116: =D106 -> 46203 | E116: =E106 -> 46568 | F116: =F106 -> 46934 | G116: =G106 -> 47299 | H116: =H106 -> 47664 | I116: =I106 -> 48029 | J116: =J106 -> 48395 | ... N116: =N106 -> 49856
B117: Equity Injections | C117: =-Cashflow!D16 -> 0 | D117: =-Cashflow!E16 -> -2487500 | E117: =-Cashflow!F16 -> -5122500 | F117: =-Cashflow!G16 -> 0 | G117: =-Cashflow!H16 -> 0 | H117: =-Cashflow!I16 -> 0 | I117: =-Cashflow!J16 -> 0 | J117: =-Cashflow!K16 -> 0 | ... N117: =-Cashflow!O16 -> 0
B118: Dividends Received | C118: =-Cashflow!D32 -> 0 | D118: =-Cashflow!E32 -> 0 | E118: =-Cashflow!F32 -> 0 | F118: =-Cashflow!G32 -> 7449479.6 | G118: =-Cashflow!H32 -> 7720502.9 | H118: =-Cashflow!I32 -> 8282539.9 | I118: =-Cashflow!J32 -> 8579208.9 | J118: =-Cashflow!K32 -> 8992996.6 | ... M118: =-Cashflow!N32 -> 9197764.2 | N118: =0 -> 0
B119: Exit Proceeds | C119: =0 -> 0 | D119: =0 -> 0 | E119: =0 -> 0 | F119: =0 -> 0 | G119: =0 -> 0 | H119: =0 -> 0 | I119: =0 -> 0 | J119: =0 -> 0 | ... M119: =0 -> 0 | N119: =C74 -> 1.3515022e+08
B120: Net Equity Cash Flow | C120: =C117+C118+C119 -> 0 | D120: =D117+D118+D119 -> -2487500 | E120: =E117+E118+E119 -> -5122500 | F120: =F117+F118+F119 -> 7449479.6 | G120: =G117+G118+G119 -> 7720502.9 | H120: =H117+H118+H119 -> 8282539.9 | I120: =I117+I118+I119 -> 8579208.9 | J120: =J117+J118+J119 -> 8992996.6 | ... N120: =N117+N118+N119 -> 1.3515022e+08
B121: Cumulative Equity CF | C121: =C120 -> 0 | D121: =C121+D120 -> -2487500 | E121: =D121+E120 -> -7610000 | F121: =E121+F120 -> -160520.41 | G121: =F121+G120 -> 7559982.5 | H121: =G121+H120 -> 15842522 | I121: =H121+I120 -> 24421731 | J121: =I121+J120 -> 33414728 | K121: =J121+K120 -> 42171436 | ... N121: =M121+N120 -> 1.9548254e+08
B123: Equity IRR (Levered) | C123: =(C180/C125)^(1/10)-1 -> 0.36201056 | D123: Approximate CAGR method | O123: =ISERROR(IRR(D120:N120)) -> FALSE
B124: Equity NPV @ Ke | C124: =C98 -> 99076992 | D124: XNPV at Cost of Equity
B125: Total Equity Invested | C125: =-SUM(C117:N117) -> 7610000 | D125: Sum of equity contributions
B126: Total Distributions + Exit | C126: =SUM(C118:N118)+SUM(C119:N119) -> 2.0309254e+08 | D126: Dividends + terminal proceeds
B127: Multiple of Invested Capital (MOIC) | C127: =C180/C125 -> 21.968719 | D127: Total proceeds / Total invested
B128: Payback Period | C128: {=IFERROR(INDEX(C115:N115,MATCH(TRUE,C121:N121>0,0)),"Not Achieved")} -> FY29 | D128: First FY with positive cumulative equity CF
B130: Yield on Cost (Stabilised) | C130: =F58/Dashboard!F66 -> 0.81987128 | D130: Stabilised EBITDA / Total Capex
B133: SENSITIVITY ANALYSIS
...

Sheet VBA
A1: Paste this into a VBA Module (Alt+F11 > Insert > Module)
A3: Sub RecalcAndCheck()
A4: Application.CalculateFull
A5: If Sheets("Model Checks").Range("B2").Value > 1 Then MsgBox "Balance Sheet Error!"
A6: End Sub

Sheet Scenarios
A1: SCENARIO MANAGER
A2: Port Melbourne Live House - Dynamic Scenario Analysis
A4: ACTIVE SCENARIO | B4: Base | D4: SCENARIO DEFINITIONS
A5: APPLIED MULTIPLIERS | D5: Scenario | E5: Rev Mult | F5: Cost Mult | G5: Delay (m) | H5: Int Δ (bps) | I5: Capex Mult | J5: Infl Mult | K5: Days Mult | L5: Event Days
A6: Revenue Multiplier | B6: =Inputs!E272 -> 1 | D6: Base | E6: 1 | F6: 1 | G6: 0 | H6: 0 | I6: 1 | J6: 1 | K6: 1 | L6: 120
A7: Cost Multiplier | B7: =Inputs!E273 -> 1 | D7: Optimistic | E7: 1.1 | F7: 0.95 | G7: 0 | H7: 0 | I7: 0.95 | J7: 0.95 | K7: 1.25 | L7: 150
A8: Opening Delay (months) | B8: =Inputs!E277 -> 0 | D8: Pessimistic | E8: 0.85 | F8: 1.1 | G8: 0 | H8: 0 | I8: 1.1 | J8: 1.05 | K8: 0.75 | L8: 90
A9: Interest Rate Delta (bps) | B9: =Inputs!E278 -> 0 | D9: Delayed Opening +3m | E9: 1 | F9: 1 | G9: 3 | H9: 0 | I9: 1 | J9: 1 | K9: 1 | L9: 120
A10: Capex Multiplier | B10: =Inputs!E274 -> 1 | D10: Delayed Opening +6m | E10: 1 | F10: 1 | G10: 6 | H10: 0 | I10: 1 | J10: 1 | K10: 1 | L10: 120
A11: Inflation Multiplier | B11: =Inputs!E275 -> 1 | D11: Higher Capex +10% | E11: 1 | F11: 1 | G11: 0 | H11: 0 | I11: 1.1 | J11: 1 | K11: 1 | L11: 120
A12: Event Days Multiplier | B12: =Inputs!E276 -> 1 | D12: Higher Capex +20% | E12: 1 | F12: 1 | G12: 0 | H12: 0 | I12: 1.2 | J12: 1 | K12: 1 | L12: 120
D13: Sponsorship Underperformance | E13: 0.9 | F13: 1 | G13: 0 | H13: 0 | I13: 1 | J13: 1 | K13: 1 | L13: 120
A15: SCENARIO IMPACT PREVIEW | H15: QUICK SCENARIO COMPARISON
A16: Metric | B16: Base Case | C16: Scenario Value | D16: Variance | E16: % Change | F16: Status | H16: Scenario | I16: Revenue Impact | J16: Cost Impact | K16: IRR Impact | L16: Risk Level
A17: Total Revenue (Exit FY) | B17: =IFERROR(Dashboard!N7/B6,Dashboard!N7) -> 23361053 | C17: =Dashboard!N7 -> 23361053 | D17: =C17-B17 -> 0 | E17: =IFERROR(D17/B17,0) -> 0 | F17: =IF(E17>0.02,"▲ Up",IF(E17<-0.02,"▼ Down","◆ Same")) -> ◆ Same | H17: Base | I17: 0 | J17: 0 | K17: Baseline | L17: ●●○○○
A18: EBITDA (Exit FY) | B18: =IFERROR(Dashboard!N7/B6 - (Dashboard!N7-Dashboard!N8)/B7, Dashboard!N8) -> 16893778 | C18: =Dashboard!N8 -> 16893778 | D18: =C18-B18 -> 0 | E18: =IFERROR(D18/B18,0) -> 0 | F18: =IF(E18>0.02,"▲ Up",IF(E18<-0.02,"▼ Down","◆ Same")) -> ◆ Same | H18: Optimistic | I18: 0.1 | J18: -0.05 | K18: =3-5% -> 2.95 | L18: ●○○○○
A19: Project IRR | B19: =Valuations!C20 -> 0.75463788 | C19: =Valuations!C20 -> 0.75463788 | D19: =C19-B19 -> 0 | E19: =IFERROR(D19/B19,0) -> 0 | F19: =IF(E19>0.02,"▲ Up",IF(E19<-0.02,"▼ Down","◆ Same")) -> ◆ Same | H19: Pessimistic | I19: -0.15 | J19: 0.1 | K19: =-5-8% -> -5.08 | L19: ●●●●○
A20: Equity IRR | B20: =Valuations!C22 -> 0.36201056 | C20: =Valuations!C22 -> 0.36201056 | D20: =C20-B20 -> 0 | E20: =IFERROR(D20/B20,0) -> 0 | F20: =IF(E20>0.02,"▲ Up",IF(E20<-0.02,"▼ Down","◆ Same")) -> ◆ Same | H20: Delayed +3m | I20: 0 | J20: 0 | K20: =-1-2% -> -1.02 | L20: ●●●○○
A21: Total Capex | B21: =Inputs!E113 -> 17075000 | C21: =Inputs!E113*B10 -> 17075000 | D21: =C21-B21 -> 0 | E21: =IFERROR(D21/B21,0) -> 0 | F21: =IF(E21>0.02,"▼ Up (Bad)",IF(E21<-0.02,"▲ Down (Good)","◆ Same")) -> ◆ Same | H21: Delayed +6m | I21: 0 | J21: 0 | K21: =-2-4% -> -2.04 | L21: ●●●●○
A22: Debt Service Coverage | B22: =Dashboard!F11 -> 8.3450465 | C22: =Dashboard!F11 -> 8.3450465 | D22: =C22-B22 -> 0 | E22: =IFERROR(D22/B22,0) -> 0 | F22: =IF(E22>0.02,"▲ Up",IF(E22<-0.02,"▼ Down","◆ Same")) -> ◆ Same | H22: Capex +10% | I22: 0 | J22: 0.1 | K22: =-2-3% -> -2.03 | L22: ●●●○○
A23: Payback Period | B23: =Valuations!C25 -> FY29 | C23: =Valuations!C25 -> FY29 | D23: =IFERROR(VALUE(RIGHT(C23,2))-VALUE(RIGHT(B23,2)),0) -> 0 | E23: ="N/A" -> N/A | F23: ="-" -> - | H23: Capex +20% | I23: 0 | J23: 0.2 | K23: =-4-5% -> -4.05 | L23: ●●●●○
A24: Sens Exit Multiple Multiplier | B24: =Inputs!E287 -> 1 | H24: Sponsorship Under | I24: -0.1 | J24: 0 | K24: =-2-3% -> -2.03 | L24: ●●●○○
A25: SENSITIVITY OVERRIDES
A26: Override Parameter | B26: Value
A27: Event Days Override | B27: =Inputs!E282 -> 1
A28: Avg Rev/Event Override | B28: =Inputs!E283 -> 1
A29: Non-event Rev Override | B29: =Inputs!E284 -> 1
A30: Capex Override | B30: =Inputs!E274 -> 1
A31: Lease Cost Override | B31: =Inputs!E285 -> 1
A32: WACC Override | B32: =Inputs!E286 -> 1
A33: Exit Multiple Override | B33: =Inputs!E287 -> 1
A35: INSTRUCTIONS
A36: 1. Select a scenario from the dropdown in cell B4
A37: 2. The model will automatically recalculate all P&L, Balance Sheet, and Cash Flow projections
A38: 3. Review the Scenario Impact Preview (rows 17-23) to see key metric changes
A39: 4. Use Sensitivity Overrides (rows 27-33) for fine-tuning individual parameters
A40: 5. The Dashboard and Valuations tabs will reflect the selected scenario

Sheet Inputs
G1: v35 | 04/03/2026
B2: GLOBAL INPUTS
B3: Port Melbourne Live House — Financial Model
C5: Input | D5: Units | E5: Value | F5: Source | G5: Notes
B7: 1. PROJECT TIMING | I7: FORMAT LEGEND
I8: User Input
C9: Model Start Date | D9: Date | E9: 45715 | G9: Feb-2025 — Model commencement | I9: Formula/Link
C10: Model End Date | D10: Date | E10: 50099 | G10: Feb-2037 — 12-year horizon | I10: Section
C11: Model Duration | D11: Years | E11: 12 | G11: Total projection period | I11: Sub-Section
C12: Currency | E12: AUD | G12: Australian Dollars | I12: Table Header
I13: Subtotal
C14: Lease Signing Date | D14: Date | E14: 46174 | G14: Apr-2026 — Triggers deposit payment | I14: Total
C15: Possession / Handover Date | D15: Date | E15: 46419 | G15: Feb-2027 — Site access begins | I15: Section Header
C16: Major Capex Start | D16: Date | E16: 46266 | G16: Sept-2026 — Fabrication begins | I16: Model Status: | J16: READY
C17: Major Capex End | D17: Date | E17: =DATE(2027,6,30) -> 46568 | G17: Jun-2026 — Fabrication complete | I17: Total/Subtotal
C18: Construction Start | D18: Date | E18: 46420 | G18: Feb-2027 — On-site assembly
C19: Construction End | D19: Date | E19: 46568 | G19: Jun-2027 — Practical completion
C20: Commissioning Start | D20: Date | E20: 46508 | G20: 46508
C21: Commissioning End | D21: Date | E21: 46568 | G21: 46539
C22: Operations Start | D22: Date | E22: 46569 | G22: Jul-2027 — First revenue month
C23: Exit Year | D23: FY | E23: FY34 | G23: Target exit/valuation date
B24: 2. LEASE ASSUMPTIONS
C26: Lease Commencement | D26: Date | E26: 46419 | G26: Matches Possession Date
C27: Lease Period | D27: Years | E27: 10 | G27: Initial lease term
C28: Months in Year 1 | D28: Months | E28: 11 | G28: Partial first year
C29: Operational Months in Year 1 | D29: Months | E29: 6 | G29: Jul-Dec FY27
C30: Rent-Free Period | D30: Months | E30: 18 | G30: Fitout/construction allowance
C31: Base Rent Rate | D31: $/m²/yr | E31: 156 | G31: Per annum rate
C32: Plot Area | D32: m² | E32: 5000 | G32: Total leasable area
C33: Annual Base Rent (Yr 1) | D33: AUD | E33: 780000 | F33: Formula | G33: =E31*E32 -> 780000
C34: Lease Deposit | D34: AUD | E34: 780000 | G34: Equivalent to 1 year rent
C35: Rent Escalation | D35: % p.a. | E35: 0.035 | G35: 3.5% fixed annual increase
C36: Landlord Outgoings | D36: % of rent | E36: 0.15 | G36: 15% additional outgoings
C37: Rent-Free End Date | D37: Date | E37: =EDATE(E26,E30) -> 46966 | F37: Formula | G37: Lease Commencement + Rent-Free Period
C38: Rent Rebate Period | D38: Months | E38: 48 | G38: 48 months at reduced rent after rent-free ends
C39: Rent Rebate Multiplier | D39: x | E39: 0.5 | G39: 50% of normal rent during rebate period
C40: Rent Rebate End Date | D40: Date | E40: =EDATE($E$37,$E$38) -> 48427 | G40: Rent-Free End Date + Rebate Period
C41: Tenant Break Option | D41: Year | E41: 5 | G41: Years from lease start
C42: Break Notice Period | D42: Months | E42: 6 | G42: Required notice
C43: Renewal Option | D43: Years | E43: 5 | G43: Extension available
B44: 3. DEBT & FINANCING
D46: DEBT | E46: =E54 -> 10245000 | F46: =E46/$E$48 -> 0.57378885
D47: Equity | E47: =E75 -> 7610000 | F47: =E47/$E$48 -> 0.42621115
D48: Total | E48: =SUM(E46:E47) -> 17855000
C50: Term Debt (Bank)
C51: Interest Rate | D51: % p.a. | E51: 0.08 | G51: 8% bank rate
C52: Loan Term | D52: Years | E52: 10 | G52: 5-year amortising
C53: LTV Ratio | D53: % | E53: 0.6 | G53: 60% of capex
C54: Loan Principal | D54: AUD | E54: =E53*E113 -> 10245000 | F54: Formula | G54: LTV × Total Capex
C55: Repayment Type | E55: Amortising | G55: Equal principal repayments
C56: Draw Year | D56: FY | E56: FY27 | G56: Construction period
C57: Interest-Only Period | D57: Months | E57: 18 | G57: Before amortisation starts
C59: Private Debt (PE Loan) | G59: LEGACY — INACTIVE (PE is now equity, see Equity section below)
C60: Interest Rate | D60: % p.a. | E60: 0.12 | G60: 12% PE rate
C61: Loan Term | D61: Years | E61: 10 | G61: 5-year term
C62: LTV Ratio | D62: % | E62: 0 | G62: 20% of capex
C63: Loan Principal | D63: AUD | E63: =(E62*E113)*0 -> 0 | F63: Formula | G63: LTV × Total Capex
C64: Repayment Type | E64: Amortising | G64: Equal principal repayments
C65: Draw Year | D65: FY | E65: FY27 | G65: Construction period
C67: 4. EQUITY / SHARE CAPITAL
C68: PE is true share capital — NOT debt. It is not repaid, not amortised, and bears no interest. Founder equity funds the 20% loan deposit.
C69: Seed Capital | D69: AUD | E69: =(1-E53-E71)*E113+E34 -> 2487500 | G69: Auto-calculated: Founder equity covers the residual after Bank (60%) and PE (30%), PLUS the lease deposit ($780K). Formula: (1 - Bank LTV - PE%) × Capex + Lease Deposit.
C70: PE Equity Mode | D70: Toggle | E70: 1 | G70: Controls how PE equity is calculated: 0 = enter a fixed dollar amount; 1 = auto-calculate as a % of total project cost (capex); 2 = % is for ownership reference only, enter amount separately. Default is Mode 1 (% of capex).
C71: PE Equity % | D71: % | E71: 0.3 | G71: PE's share of total project cost. Bank LTV + PE% + Founder% must = 100%. Currently: 60% bank + 30% PE + 10% founder = 100%.
C72: PE Equity Fixed Amount | D72: AUD | E72: 5122500 | G72: Only used when PE Equity Mode = 0 (fixed dollar). If Mode = 1 or 2, the model calculates the PE amount from the % above. This field is ignored unless Mode = 0.
C73: PE Equity Amount | D73: AUD | E73: =IF(E70=0,E72,IF(E70=1,E71*E113,E72)) -> 5122500 | F73: Formula | G73: Auto-calculated PE equity amount based on the mode selected above. This is the actual PE cash injection that flows into the cashflow and balance sheet. PE equity is permanent — never repaid.
C75: Total Equity Funding | D75: AUD | E75: =E69+E73+E82+E84 -> 7610000 | F75: Formula | G75: Total equity = Founder + PE + tranches. Covers total project need (capex + lease deposit) minus bank debt. Bank + Equity = 100% of capex, plus equity covers lease deposit.
C76: Bank Debt % of Total Capex | D76: % | E76: =E53 -> 0.6 | F76: Link | G76: Linked from Term Debt LTV above. Shows bank debt as % of total capex for cross-reference. Bank funds the remaining balance after equity.
C77: Required Loan Deposit / Equity Contribution % | D77: % | E77: 0.2 | G77: Lender requires this % of total capex as upfront equity (deposit) before releasing debt. Funded from total equity (Founder + PE).
C78: Required Deposit Amount | D78: AUD | E78: =E77*E113 -> 3415000 | F78: Formula | G78: Formula: Deposit % × Total Capex. This is the minimum equity the bank needs to see committed before it will drawdown the loan. Funded by Founder / Seed Capital.
C80: Equity Injection Timing | G80: Controls WHEN each equity source enters the cashflow. Equity only appears in the period specified below.
C81: Founder / Seed Equity Injection Year | D81: FY | E81: FY26 | G81: Founder equity injects in FY26 (pre-construction) to meet the bank's deposit requirement before the FY27 construction debt drawdown.
C82: Additional Equity Tranche 1 Amount | D82: AUD | E82: 0 | G82: Reserved for future use — if additional equity is needed (e.g. cost overruns, new investor). Set to $0 by default. Change the amount and timing to activate.
C83: Additional Equity Tranche 1 Timing | D83: FY | E83: FY27 | G83: Year tranche 1 would be injected. Only active if the amount above is > $0.
C84: Additional Equity Tranche 2 Amount | D84: AUD | E84: 0 | G84: Second reserve tranche for future flexibility. Set to $0 by default. Same logic as Tranche 1.
C85: Additional Equity Tranche 2 Timing | D85: FY | E85: FY28 | G85: Year tranche 2 would be injected. Only active if the amount above is > $0.
C86: PE Equity Injection Year | D86: FY | E86: FY27 | G86: PE equity injects in FY27 alongside the bank debt drawdown during the construction year. PE funds are permanent share capital — no repayment schedule.
C88: Shareholder Loan Toggle | D88: Toggle | E88: 0 | G88: Future flexibility: if set to 1 (ON), PE would be treated as a shareholder loan (with repayment). Currently OFF — PE is pure equity with no debt characteristics. Do not change without building a separate loan schedule.
C89: Management / Other Equity | D89: AUD | E89: 0 | G89: Optional — for future management equity participation, employee equity schemes, or other co-investors. Set to $0 by default.
C90: Management / Other Equity Timing | D90: FY | E90: FY27 | G90: Year management/other equity would be injected. Only active if the amount above is > $0.
C94: Bank Covenants
C95: Minimum DSCR | D95: x | E95: 1.2 | G95: Debt service coverage
C96: Minimum ICR | D96: x | E96: 2 | G96: Interest coverage
C97: Maximum Net Leverage | D97: x | E97: 4.5 | G97: Net Debt / EBITDA
C98: Equity Timing
C99: Equity Draw Year | D99: FY | E99: FY26 | G99: Year equity is received (end of FY)
B101: 4. CAPITAL EXPENDITURE
C103: Consultants | D103: AUD | E103: 1270000 | G103: Project management, surveys, design
C104: Structure | D104: AUD | E104: 7280000 | G104: Building structure & shell
C105: Civil | D105: AUD | E105: 1105000 | G105: Site works & foundations
C106: ICT | D106: AUD | E106: 420000 | G106: IT infrastructure
C107: FF&E | D107: AUD | E107: 1200000 | G107: Furniture, fixtures & equipment
C108: Services | D108: AUD | E108: 4950000 | G108: MEP & specialist services
C109: Security | D109: AUD | E109: 220000 | G109: Security systems
C110: Finance Costs | D110: AUD | E110: 130000 | G110: Arrangement fees
C111: Subtotal | D111: AUD | E111: =SUM(E103:E110) -> 16575000 | F111: Formula | G111: Total
C112: Miscellaneous / Contingency | D112: AUD | E112: 500000 | G112: ~2.5% contingency
C113: Total Construction Capex | D113: AUD | E113: =E112+E111 -> 17075000 | F113: Formula | G113: =E111+E112 -> 17075000
C115: Construction Risk Factors
C116: Contingency % | D116: % of Capex | E116: 0.1 | G116: 10% standard allowance
...

Sheet Construction Timeline
C2: Initial CAPEX
D5: Capex
D6: Consultants | G6: 1270000
D7: Structure | G7: 7280000
D8: Civil | G8: 1105000
D9: ICT | G9: 420000
D10: FF&E | G10: 1200000
D11: Services | G11: 4950000
D12: Security | G12: 220000
D13: Finance | G13: 130000
D14: Total | E14: AUD | G14: =SUM(G6:G13) -> 16575000
D16: Miscellaneous | E16: AUD | G16: 500000
C17: Total initial CAPEX | D17: Total initial CAPEX | E17: AUD | G17: =SUM(G16) -> 500000
Z18: Toilets
Z19: For a 5,000 cap venue with swing flexibility
C20: Pre-lease works | Z20: 7–8 toilet containers total, typically:
I21: Design Development | K21: Fabrication and Shipping | P21: Handover, Construction, Mobisation and Commissioning Period | Z21: 5–6 × 40’ WC blocks
C22: CONSULTANTS | E22: AUD | I22: P1 (Feb-25) | J22: P2 (Mar-25) | K22: P3 (Apr-25) | L22: P4 (May-25) | M22: P5 (Jun-25) | N22: P6 (Jul-25) | O22: P7 (Aug-25) | P22: P8 (Sep-25) | Q22: P9 (Oct-25) | R22: P10 (Nov-25) | S22: P11 (Dec-25) | T22: P12 (Jan-26) | U22: P13 (Feb-26) | V22: Totals | Z22: 0–1 × 20’ WC block
D23: Project Management | G23: 800000 | I23: 61538 | J23: 61538 | K23: 61538 | L23: 61538 | M23: 61538 | N23: 61538 | O23: 61538 | P23: 61538 | Q23: 61538 | R23: 61538 | S23: 61538 | T23: 61538 | U23: 61538 | V23: 800000 | W23: =IF(ABS(V23-G23)<1,"OK","Check") -> OK | Z23: 2–3 × 40’ urinal blocks
D24: Building Surveyor | G24: 50000 | I24: 20000 | J24: 10000 | K24: 0 | L24: 0 | M24: 0 | N24: 0 | O24: 0 | P24: 10000 | Q24: 0 | R24: 0 | S24: 0 | T24: 0 | U24: 10000 | V24: 50000 | W24: =IF(ABS(V24-G24)<1,"OK","Check") -> OK | Z24: Design for ~55 WC cubicles total, ~40–60 urinals, 4–6 accessible distributed.
D25: Acoustics | G25: 75000 | I25: 10000 | J25: 25000 | K25: 0 | L25: 0 | M25: 0 | N25: 0 | O25: 10000 | P25: 0 | Q25: 0 | R25: 0 | S25: 0 | T25: 10000 | U25: 20000 | V25: 75000 | W25: =IF(ABS(V25-G25)<1,"OK","Check") -> OK
D26: Fire | G26: 50000 | I26: 10000 | J26: 20000 | K26: 0 | L26: 0 | M26: 10000 | N26: 0 | O26: 0 | P26: 0 | Q26: 0 | R26: 0 | S26: 0 | T26: 0 | U26: 10000 | V26: 50000 | W26: =IF(ABS(V26-G26)<1,"OK","Check") -> OK
D27: Licenscing | G27: 45000 | I27: 15000 | J27: 0 | K27: 0 | L27: 0 | M27: 15000 | N27: 0 | O27: 0 | P27: 0 | Q27: 0 | R27: 0 | S27: 0 | T27: 0 | U27: 15000 | V27: 45000 | W27: =IF(ABS(V27-G27)<1,"OK","Check") -> OK
D28: Crowd Dynamics | G28: 40000 | I28: 0 | J28: 20000 | K28: 0 | L28: 0 | M28: 5000 | N28: 0 | O28: 0 | P28: 0 | Q28: 5000 | R28: 0 | S28: 5000 | T28: 0 | U28: 5000 | V28: 40000 | W28: =IF(ABS(V28-G28)<1,"OK","Check") -> OK
D29: Environmental | G29: 30000 | I29: 0 | J29: 20000 | K29: 0 | L29: 0 | M29: 0 | N29: 0 | O29: 0 | P29: 0 | Q29: 0 | R29: 0 | S29: 0 | T29: 0 | U29: 10000 | V29: 30000 | W29: =IF(ABS(V29-G29)<1,"OK","Check") -> OK
D30: Architecture and ID | G30: 100000 | I30: 0 | J30: 25000 | K30: 25000 | L30: 10000 | M30: 0 | N30: 0 | O30: 15000 | P30: 15000 | Q30: 0 | R30: 0 | S30: 0 | T30: 0 | U30: 10000 | V30: 100000 | W30: =IF(ABS(V30-G30)<1,"OK","Check") -> OK
D31: ICT | G31: 50000 | I31: 0 | J31: 15000 | K31: 0 | L31: 10000 | M31: 0 | N31: 0 | O31: 0 | P31: 0 | Q31: 15000 | R31: 0 | S31: 0 | T31: 10000 | U31: 0 | V31: 50000 | W31: =IF(ABS(V31-G31)<1,"OK","Check") -> OK
D32: Transportation | G32: 30000 | I32: 0 | J32: 20000 | K32: 0 | L32: 0 | M32: 0 | N32: 0 | O32: 0 | P32: 0 | Q32: 0 | R32: 0 | S32: 0 | T32: 0 | U32: 10000 | V32: 30000 | W32: =IF(ABS(V32-G32)<1,"OK","Check") -> OK
D33: Total initial capex for Consultancts | G33: =SUM(G23:G32) -> 1270000 | I33: =SUM(I23:I32) -> 116538 | J33: =SUM(J23:J32) -> 216538 | K33: =SUM(K23:K32) -> 86538 | L33: =SUM(L23:L32) -> 81538 | M33: =SUM(M23:M32) -> 91538 | N33: =SUM(N23:N32) -> 61538 | O33: =SUM(O23:O32) -> 86538 | P33: =SUM(P23:P32) -> 86538 | ... V33: =SUM(V23:V32) -> 1270000 | W33: =IF(ABS(V33-G33)<1,"OK","Check") -> OK
C35: STRUCTURE
D36: Performance area | G36: 3400000 | I36: 0 | J36: 0 | K36: 0 | L36: 680000 | M36: 680000 | N36: 1360000 | O36: 0 | P36: 340000 | Q36: 0 | R36: 0 | S36: 0 | T36: 0 | U36: 340000 | V36: 3400000 | W36: =IF(ABS(V36-G36)<1,"OK","Check") -> OK
D37: Venue Façade (inc Lighting) | G37: 2600000 | I37: 0 | J37: 0 | K37: 0 | L37: 0 | M37: 0 | N37: 260000 | O37: 1820000 | P37: 390000 | Q37: 0 | R37: 0 | S37: 0 | T37: 0 | U37: 130000 | V37: 2600000 | W37: =IF(ABS(V37-G37)<1,"OK","Check") -> OK
D38: Concessions | G38: 250000 | I38: 0 | J38: 0 | K38: 0 | L38: 0 | M38: 0 | N38: 25000 | O38: 150000 | P38: 0 | Q38: 25000 | R38: 0 | S38: 0 | T38: 25000 | U38: 25000 | V38: 250000 | W38: =IF(ABS(V38-G38)<1,"OK","Check") -> OK
D39: BoH Dressing Rooms | G39: 200000 | I39: 0 | J39: 0 | K39: 0 | L39: 0 | M39: 0 | N39: 20000 | O39: 80000 | P39: 0 | Q39: 20000 | R39: 0 | S39: 0 | T39: 70000 | U39: 10000 | V39: 200000 | W39: =IF(ABS(V39-G39)<1,"OK","Check") -> OK
D40: Venue Management Offices | G40: 200000 | I40: 0 | J40: 0 | K40: 0 | L40: 0 | M40: 0 | N40: 20000 | O40: 80000 | P40: 0 | Q40: 20000 | R40: 0 | S40: 0 | T40: 70000 | U40: 10000 | V40: 200000 | W40: =IF(ABS(V40-G40)<1,"OK","Check") -> OK
D41: Toilets | G41: 230000 | I41: 0 | J41: 0 | K41: 0 | L41: 0 | M41: 0 | N41: 46000 | O41: 138000 | P41: 0 | Q41: 34500 | R41: 0 | S41: 0 | T41: 0 | U41: 11500 | V41: 230000 | W41: =IF(ABS(V41-G41)<1,"OK","Check") -> OK
D42: Premium | G42: 300000 | I42: 0 | J42: 0 | K42: 0 | L42: 0 | M42: 0 | N42: 60000 | O42: 150000 | P42: 0 | Q42: 0 | R42: 0 | S42: 0 | T42: 0 | U42: 90000 | V42: 300000 | W42: =IF(ABS(V42-G42)<1,"OK","Check") -> OK
D43: First Aid | G43: 30000 | I43: 0 | J43: 0 | K43: 0 | L43: 0 | M43: 0 | N43: 6000 | O43: 12000 | P43: 0 | Q43: 3000 | R43: 0 | S43: 0 | T43: 0 | U43: 9000 | V43: 30000 | W43: =IF(ABS(V43-G43)<1,"OK","Check") -> OK
D44: Storage Block & Workshop | G44: 70000 | I44: 0 | J44: 0 | K44: 0 | L44: 0 | M44: 0 | N44: 14000 | O44: 42000 | P44: 0 | Q44: 7000 | R44: 0 | S44: 0 | T44: 0 | U44: 7000 | V44: 70000 | W44: =IF(ABS(V44-G44)<1,"OK","Check") -> OK
D45: Total initial capex for structure | E45: AUD | G45: =SUM(G36:G44) -> 7280000 | I45: =SUM(I36:I44) -> 0 | J45: =SUM(J36:J44) -> 0 | K45: =SUM(K36:K44) -> 0 | L45: =SUM(L36:L44) -> 680000 | M45: =SUM(M36:M44) -> 680000 | N45: =SUM(N36:N44) -> 1811000 | O45: =SUM(O36:O44) -> 2472000 | P45: =SUM(P36:P44) -> 730000 | ... V45: =SUM(V36:V44) -> 7280000 | W45: =IF(ABS(V45-G45)<1,"OK","Check") -> OK
C47: CIVIL
D48: Sewer Connections | G48: 80000 | I48: 0 | J48: 0 | K48: 0 | L48: 0 | M48: 0 | N48: 0 | O48: 0 | P48: 0 | Q48: 0 | R48: 80000 | S48: 0 | T48: 0 | U48: 0 | V48: 80000 | W48: =IF(ABS(V48-G48)<1,"OK","Check") -> OK
D49: Site base/hardstand | G49: 500000 | I49: 0 | J49: 0 | K49: 0 | L49: 0 | M49: 0 | N49: 0 | O49: 0 | P49: 0 | Q49: 500000 | R49: 0 | S49: 0 | T49: 0 | U49: 0 | V49: 500000 | W49: =IF(ABS(V49-G49)<1,"OK","Check") -> OK
D50: Internal External Fencing | G50: 100000 | I50: 0 | J50: 0 | K50: 0 | L50: 0 | M50: 0 | N50: 0 | O50: 0 | P50: 0 | Q50: 0 | R50: 0 | S50: 0 | T50: 100000 | U50: 0 | V50: 100000 | W50: =IF(ABS(V50-G50)<1,"OK","Check") -> OK
D51: Bin wash | G51: 50000 | I51: 0 | J51: 0 | K51: 0 | L51: 0 | M51: 0 | N51: 0 | O51: 0 | P51: 0 | Q51: 0 | R51: 50000 | S51: 0 | T51: 0 | U51: 0 | V51: 50000 | W51: =IF(ABS(V51-G51)<1,"OK","Check") -> OK
D52: External greenscape | G52: 75000 | I52: 0 | J52: 0 | K52: 0 | L52: 0 | M52: 0 | N52: 0 | O52: 0 | P52: 0 | Q52: 0 | R52: 0 | S52: 0 | T52: 75000 | U52: 0 | V52: 75000 | W52: =IF(ABS(V52-G52)<1,"OK","Check") -> OK
D53: Internal and external floor | G53: 200000 | I53: 0 | J53: 0 | K53: 0 | L53: 0 | M53: 0 | N53: 0 | O53: 0 | P53: 0 | Q53: 0 | R53: 0 | S53: 0 | T53: 200000 | U53: 0 | V53: 200000 | W53: =IF(ABS(V53-G53)<1,"OK","Check") -> OK
D54: Site drainage | G54: 100000 | I54: 0 | J54: 0 | K54: 0 | L54: 0 | M54: 0 | N54: 0 | O54: 0 | P54: 0 | Q54: 100000 | R54: 0 | S54: 0 | T54: 0 | U54: 0 | V54: 100000 | W54: =IF(ABS(V54-G54)<1,"OK","Check") -> OK
D55: Total initial capex for Civil | E55: AUD | G55: =SUM(G48:G54) -> 1105000 | I55: =SUM(I48:I54) -> 0 | J55: =SUM(J48:J54) -> 0 | K55: =SUM(K48:K54) -> 0 | L55: =SUM(L48:L54) -> 0 | M55: =SUM(M48:M54) -> 0 | N55: =SUM(N48:N54) -> 0 | O55: =SUM(O48:O54) -> 0 | P55: =SUM(P48:P54) -> 0 | ... V55: =SUM(V48:V54) -> 1105000 | W55: =IF(ABS(V55-G55)<1,"OK","Check") -> OK
W56: =IF(ABS(V56-G56)<1,"OK","Check") -> OK
C57: ICT
D58: Induction platform (lease) | G58: 0 | I58: 0 | J58: 0 | K58: 0 | L58: 0 | M58: 0 | N58: 0 | O58: 0 | P58: 0 | Q58: 0 | R58: 0 | S58: 0 | T58: 0 | U58: 0 | V58: 0 | W58: =IF(ABS(V58-G58)<1,"OK","Check") -> OK
D59: Wifi (public and LAN) | G59: 150000 | I59: 0 | J59: 0 | K59: 0 | L59: 0 | M59: 0 | N59: 0 | O59: 0 | P59: 0 | Q59: 0 | R59: 0 | S59: 0 | T59: 150000 | U59: 0 | V59: 150000 | W59: =IF(ABS(V59-G59)<1,"OK","Check") -> OK
D60: Website | G60: 30000 | I60: 0 | J60: 0 | K60: 0 | L60: 30000 | M60: 0 | N60: 0 | O60: 0 | P60: 0 | Q60: 0 | R60: 0 | S60: 0 | T60: 0 | U60: 0 | V60: 30000 | W60: =IF(ABS(V60-G60)<1,"OK","Check") -> OK
D61: Socials (nil) | G61: 15000 | I61: 0 | J61: 0 | K61: 0 | L61: 15000 | M61: 0 | N61: 0 | O61: 0 | P61: 0 | Q61: 0 | R61: 0 | S61: 0 | T61: 0 | U61: 0 | V61: 15000 | W61: =IF(ABS(V61-G61)<1,"OK","Check") -> OK
D62: Venue Management Venue Ops (lease) | G62: 0 | I62: 0 | J62: 0 | K62: 0 | L62: 0 | M62: 0 | N62: 0 | O62: 0 | P62: 0 | Q62: 0 | R62: 0 | S62: 0 | T62: 0 | U62: 0 | V62: 0 | W62: =IF(ABS(V62-G62)<1,"OK","Check") -> OK
D63: BMS | G63: 0 | I63: 0 | J63: 0 | K63: 0 | L63: 0 | M63: 0 | N63: 0 | O63: 0 | P63: 0 | Q63: 0 | R63: 0 | S63: 0 | T63: 0 | U63: 0 | V63: 0 | W63: =IF(ABS(V63-G63)<1,"OK","Check") -> OK
D64: Access Control | G64: 150000 | I64: 0 | J64: 0 | K64: 0 | L64: 0 | M64: 0 | N64: 0 | O64: 0 | P64: 0 | Q64: 0 | R64: 0 | S64: 150000 | T64: 0 | U64: 0 | V64: 150000 | W64: =IF(ABS(V64-G64)<1,"OK","Check") -> OK
D65: Ticketing (Supplier) | G65: 0 | I65: 0 | J65: 0 | K65: 0 | L65: 0 | M65: 0 | N65: 0 | O65: 0 | P65: 0 | Q65: 0 | R65: 0 | S65: 0 | T65: 0 | U65: 0 | V65: 0 | W65: =IF(ABS(V65-G65)<1,"OK","Check") -> OK
D66: Venue telephone system (VoIP) | G66: 75000 | I66: 0 | J66: 0 | K66: 0 | L66: 0 | M66: 0 | N66: 0 | O66: 0 | P66: 0 | Q66: 0 | R66: 0 | S66: 75000 | T66: 0 | U66: 0 | V66: 75000 | W66: =IF(ABS(V66-G66)<1,"OK","Check") -> OK
D67: CMS | G67: 0 | I67: 0 | J67: 0 | K67: 0 | L67: 0 | M67: 0 | N67: 0 | O67: 0 | P67: 0 | Q67: 0 | R67: 0 | S67: 0 | T67: 0 | U67: 0 | V67: 0 | W67: =IF(ABS(V67-G67)<1,"OK","Check") -> OK
D68: Total initial capex for ICT | E68: AUD | G68: =SUM(G58:G67) -> 420000 | I68: =SUM(I58:I67) -> 0 | J68: =SUM(J58:J67) -> 0 | K68: =SUM(K58:K67) -> 0 | L68: =SUM(L58:L67) -> 45000 | M68: =SUM(M58:M67) -> 0 | N68: =SUM(N58:N67) -> 0 | O68: =SUM(O58:O67) -> 0 | P68: =SUM(P58:P67) -> 0 | ... V68: =SUM(V58:V67) -> 420000 | W68: =IF(ABS(V68-G68)<1,"OK","Check") -> OK
W69: =IF(ABS(V69-G69)<1,"OK","Check") -> OK
C70: FF&E
D71: Rigging | G71: 0 | I71: 0 | J71: 0 | K71: 0 | L71: 0 | M71: 0 | N71: 0 | O71: 0 | P71: 0 | Q71: 0 | R71: 0 | S71: 0 | T71: 0 | U71: 0 | V71: 0 | W71: =IFERROR(IF(V71=G71, "OK", "Check"),"") -> OK
D72: 3T motors and controllers | I72: 0 | J72: 0 | K72: 0 | L72: 0 | M72: 0 | N72: 0 | O72: 0 | P72: 0 | Q72: 0 | R72: 0 | S72: 0 | T72: 0 | U72: 0 | V72: 0 | W72: =IFERROR(IF(V72=G72, "OK", "Check"),"") -> OK
D73: Truss | I73: 0 | J73: 0 | K73: 0 | L73: 0 | M73: 0 | N73: 0 | O73: 0 | P73: 0 | Q73: 0 | R73: 0 | S73: 0 | T73: 0 | U73: 0 | V73: 0 | W73: =IFERROR(IF(V73=G73, "OK", "Check"),"") -> OK
D74: motor controllers | I74: 0 | J74: 0 | K74: 0 | L74: 0 | M74: 0 | N74: 0 | O74: 0 | P74: 0 | Q74: 0 | R74: 0 | S74: 0 | T74: 0 | U74: 0 | V74: 0 | W74: =IFERROR(IF(V74=G74, "OK", "Check"),"") -> OK
D75: Consoles | G75: 0 | I75: 0 | J75: 0 | K75: 0 | L75: 0 | M75: 0 | N75: 0 | O75: 0 | P75: 0 | Q75: 0 | R75: 0 | S75: 0 | T75: 0 | U75: 0 | V75: 0 | W75: =IFERROR(IF(V75=G75, "OK", "Check"),"") -> OK
D76: House sound system | G76: 100000 | I76: 0 | J76: 0 | K76: 0 | L76: 0 | M76: 0 | N76: 0 | O76: 0 | P76: 20000 | Q76: 0 | R76: 0 | S76: 40000 | T76: 20000 | U76: 20000 | V76: 100000 | W76: =IFERROR(IF(V76=G76, "OK", "Check"),"") -> OK
D77: Stage | G77: 250000 | I77: 0 | J77: 0 | K77: 0 | L77: 0 | M77: 0 | N77: 0 | O77: 0 | P77: 0 | Q77: 0 | R77: 25000 | S77: 225000 | T77: 0 | U77: 0 | V77: 250000 | W77: =IFERROR(IF(V77=G77, "OK", "Check"),"") -> OK
D78: Barrier | G78: 70000 | I78: 0 | J78: 0 | K78: 0 | L78: 0 | M78: 0 | N78: 0 | O78: 0 | P78: 0 | Q78: 0 | R78: 7000 | S78: 63000 | T78: 0 | U78: 0 | V78: 70000 | W78: =IFERROR(IF(V78=G78, "OK", "Check"),"") -> OK
D79: DB's | G79: 30000 | I79: 0 | J79: 0 | K79: 0 | L79: 0 | M79: 0 | N79: 0 | O79: 0 | P79: 0 | Q79: 0 | R79: 0 | S79: 0 | T79: 30000 | U79: 0 | V79: 30000 | W79: =IFERROR(IF(V79=G79, "OK", "Check"),"") -> OK
D80: Cables and fittings | G80: 30000 | I80: 0 | J80: 0 | K80: 0 | L80: 0 | M80: 0 | N80: 0 | O80: 0 | P80: 0 | Q80: 0 | R80: 0 | S80: 0 | T80: 30000 | U80: 0 | V80: 30000 | W80: =IFERROR(IF(V80=G80, "OK", "Check"),"") -> OK
D81: Forklift | G81: 30000 | I81: 0 | J81: 0 | K81: 0 | L81: 0 | M81: 0 | N81: 0 | O81: 30000 | P81: 0 | Q81: 0 | R81: 0 | S81: 0 | T81: 0 | U81: 0 | V81: 30000 | W81: =IFERROR(IF(V81=G81, "OK", "Check"),"") -> OK
D82: MWEP | G82: 20000 | I82: 0 | J82: 0 | K82: 0 | L82: 0 | M82: 0 | N82: 0 | O82: 20000 | P82: 0 | Q82: 0 | R82: 0 | S82: 0 | T82: 0 | U82: 0 | V82: 20000 | W82: =IFERROR(IF(V82=G82, "OK", "Check"),"") -> OK
D83: Portable Scaffold tower | G83: 10000 | I83: 0 | J83: 0 | K83: 0 | L83: 0 | M83: 0 | N83: 0 | O83: 10000 | P83: 0 | Q83: 0 | R83: 0 | S83: 0 | T83: 0 | U83: 0 | V83: 10000 | W83: =IFERROR(IF(V83=G83, "OK", "Check"),"") -> OK
D84: Reduced mode curtians | G84: 30000 | I84: 0 | J84: 0 | K84: 0 | L84: 0 | M84: 0 | N84: 0 | O84: 0 | P84: 0 | Q84: 6000 | R84: 0 | S84: 24000 | T84: 0 | U84: 0 | V84: 30000 | W84: =IFERROR(IF(V84=G84, "OK", "Check"),"") -> OK
D85: Singage | G85: 70000 | I85: 0 | J85: 0 | K85: 0 | L85: 0 | M85: 0 | N85: 0 | O85: 0 | P85: 0 | Q85: 14000 | R85: 0 | S85: 56000 | T85: 0 | U85: 0 | V85: 70000 | W85: =IFERROR(IF(V85=G85, "OK", "Check"),"") -> OK
D86: Retractables | G86: 150000 | I86: 0 | J86: 0 | K86: 0 | L86: 0 | M86: 0 | N86: 0 | O86: 0 | P86: 0 | Q86: 30000 | R86: 0 | S86: 120000 | T86: 0 | U86: 0 | V86: 150000 | W86: =IFERROR(IF(V86=G86, "OK", "Check"),"") -> OK
... D93: Internal LED Screen (TV's) | G93: 50000 | I93: 0 | J93: 0 | K93: 0 | L93: 0 | M93: 0 | N93: 0 | O93: 0 | P93: 0 | Q93: 0 | R93: 0 | S93: 0 | T93: 50000 | U93: 0 | V93: 50000 | W93: =IFERROR(IF(V93=G93, "OK", "Check"),"") -> OK
D94: Internal LED wall | I94: 0 | J94: 0 | K94: 0 | L94: 0 | M94: 0 | N94: 0 | O94: 0 | P94: 0 | Q94: 0 | R94: 0 | S94: 0 | T94: 0 | U94: 0 | V94: 0 | W94: =IFERROR(IF(V94=G94, "OK", "Check"),"") -> OK
D95: Outdoor LED wall | I95: 0 | J95: 0 | K95: 0 | L95: 0 | M95: 0 | N95: 0 | O95: 0 | P95: 0 | Q95: 0 | R95: 0 | S95: 0 | T95: 0 | U95: 0 | V95: 0 | W95: =IFERROR(IF(V95=G95, "OK", "Check"),"") -> OK
D96: Outdoor furniture | G96: 100000 | I96: 0 | J96: 0 | K96: 0 | L96: 0 | M96: 0 | N96: 0 | O96: 0 | P96: 0 | Q96: 0 | R96: 0 | S96: 20000 | T96: 0 | U96: 80000 | V96: 100000 | W96: =IFERROR(IF(V96=G96, "OK", "Check"),"") -> OK
D97: Rain water detention tanks | G97: 70000 | I97: 0 | J97: 0 | K97: 0 | L97: 0 | M97: 0 | N97: 0 | O97: 0 | P97: 0 | Q97: 0 | R97: 70000 | S97: 0 | T97: 0 | U97: 0 | V97: 70000 | W97: =IFERROR(IF(V97=G97, "OK", "Check"),"") -> OK
D98: Solar roof | G98: 0 | I98: 0 | J98: 0 | K98: 0 | L98: 0 | M98: 0 | N98: 0 | O98: 0 | P98: 0 | Q98: 0 | R98: 0 | S98: 0 | T98: 0 | U98: 0 | V98: 0 | W98: =IF(ABS(V98-G98)<1,"OK","Check") -> OK
D99: Total initial capex for fitout | E99: AUD | G99: =SUM(G96:G98) -> 170000 | I99: =SUM(I71:I98) -> 0 | J99: =SUM(J71:J98) -> 0 | K99: =SUM(K71:K98) -> 0 | L99: =SUM(L71:L98) -> 0 | M99: =SUM(M71:M98) -> 0 | N99: =SUM(N71:N98) -> 0 | O99: =SUM(O71:O98) -> 60000 | P99: =SUM(P71:P98) -> 20000 | ... V99: =SUM(V71:V98) -> 1200000 | W99: =IFERROR(IF(SUM(V71:V98)=G99, "OK", "Check"),"") -> Check
C101: SERVICES
D102: Mechanical plant | G102: 3000000 | I102: 0 | J102: 0 | K102: 0 | L102: 0 | M102: 0 | N102: 300000 | O102: 0 | P102: 0 | Q102: 900000 | R102: 1200000 | S102: 600000 | T102: 0 | U102: 0 | V102: 3000000 | W102: =IFERROR(IF(V102=G102, "OK", "Check"),"") -> OK
D103: AHU's | G103: 0 | I103: 0 | J103: 0 | K103: 0 | L103: 0 | M103: 0 | N103: 0 | O103: 0 | P103: 0 | Q103: 0 | R103: 0 | S103: 0 | T103: 0 | U103: 0 | V103: 0 | W103: =IFERROR(IF(V103=G103, "OK", "Check"),"") -> OK
D104: Fire system | G104: 800000 | I104: 0 | J104: 0 | K104: 0 | L104: 0 | M104: 0 | N104: 320000 | O104: 0 | P104: 0 | Q104: 0 | R104: 0 | S104: 480000 | T104: 0 | U104: 0 | V104: 800000 | W104: =IFERROR(IF(V104=G104, "OK", "Check"),"") -> OK
D105: House Lighting | G105: 100000 | I105: 0 | J105: 0 | K105: 0 | L105: 0 | M105: 0 | N105: 0 | O105: 0 | P105: 0 | Q105: 0 | R105: 0 | S105: 100000 | T105: 0 | U105: 0 | V105: 100000 | W105: =IFERROR(IF(V105=G105, "OK", "Check"),"") -> OK
D106: Emergency Lighting | G106: 100000 | I106: 0 | J106: 0 | K106: 0 | L106: 0 | M106: 0 | N106: 0 | O106: 0 | P106: 0 | Q106: 0 | R106: 0 | S106: 100000 | T106: 0 | U106: 0 | V106: 100000 | W106: =IFERROR(IF(V106=G106, "OK", "Check"),"") -> OK
D107: UPS | G107: 50000 | I107: 0 | J107: 0 | K107: 0 | L107: 0 | M107: 0 | N107: 0 | O107: 0 | P107: 0 | Q107: 0 | R107: 0 | S107: 50000 | T107: 0 | U107: 0 | V107: 50000 | W107: =IFERROR(IF(V107=G107, "OK", "Check"),"") -> OK
D108: Accoustic treament | G108: 700000 | I108: 0 | J108: 0 | K108: 0 | L108: 0 | M108: 0 | N108: 0 | O108: 0 | P108: 0 | Q108: 0 | R108: 140000 | S108: 560000 | T108: 0 | U108: 0 | V108: 700000 | W108: =IFERROR(IF(V108=G108, "OK", "Check"),"") -> OK
D109: Internal Distribution System and Boards | G109: 100000 | I109: 0 | J109: 0 | K109: 0 | L109: 0 | M109: 0 | N109: 0 | O109: 0 | P109: 0 | Q109: 0 | R109: 100000 | S109: 0 | T109: 0 | U109: 0 | V109: 100000 | W109: =IFERROR(IF(V109=G109, "OK", "Check"),"") -> OK
D110: External façade LED aspect lighting | G110: 0 | I110: 0 | J110: 0 | K110: 0 | L110: 0 | M110: 0 | N110: 0 | O110: 0 | P110: 0 | Q110: 0 | R110: 0 | S110: 0 | T110: 0 | U110: 0 | V110: 0 | W110: =IFERROR(IF(V110=G110, "OK", "Check"),"") -> OK
D111: External Lighting | G111: 100000 | I111: 0 | J111: 0 | K111: 0 | L111: 0 | M111: 0 | N111: 0 | O111: 0 | P111: 0 | Q111: 0 | R111: 0 | S111: 100000 | T111: 0 | U111: 0 | V111: 100000 | W111: =IF(ABS(V111-G111)<1,"OK","Check") -> OK
D112: Total initial capex for Services | E112: AUD | G112: 4950000 | I112: =SUM(I102:I111) -> 0 | J112: =SUM(J102:J111) -> 0 | K112: =SUM(K102:K111) -> 0 | L112: =SUM(L102:L111) -> 0 | M112: =SUM(M102:M111) -> 0 | N112: =SUM(N102:N111) -> 620000 | O112: =SUM(O102:O111) -> 0 | P112: =SUM(P102:P111) -> 0 | ... V112: =SUM(V102:V111) -> 4950000 | W112: =IFERROR(IF(SUM(V102:V111)=G112, "OK", "Check"),"") -> OK
C114: SECURITY
...

Sheet P&L
A1: Profit & Loss Statement
A2: Port Melbourne Live House
G4: FY START | H4: =Model_start -> 45715 | I4: =H5+1 -> 45839 | J4: =I5+1 -> 46204 | K4: =J5+1 -> 46569 | L4: =K5+1 -> 46935 | M4: =L5+1 -> 47300 | N4: =M5+1 -> 47665 | O4: =N5+1 -> 48030 | P4: =O5+1 -> 48396 | ... S4: =R5+1 -> 49491
G5: FY END | H5: =DATE(YEAR(H4) + (MONTH(H4)>=7), 6, 30) -> 45838 | I5: =DATE(YEAR(I4) + (MONTH(I4)>=7), 6, 30) -> 46203 | J5: =DATE(YEAR(J4) + (MONTH(J4)>=7), 6, 30) -> 46568 | K5: =DATE(YEAR(K4) + (MONTH(K4)>=7), 6, 30) -> 46934 | L5: =DATE(YEAR(L4) + (MONTH(L4)>=7), 6, 30) -> 47299 | M5: =DATE(YEAR(M4) + (MONTH(M4)>=7), 6, 30) -> 47664 | N5: =DATE(YEAR(N4) + (MONTH(N4)>=7), 6, 30) -> 48029 | O5: =DATE(YEAR(O4) + (MONTH(O4)>=7), 6, 30) -> 48395 | ... S5: =DATE(YEAR(S4) + (MONTH(S4)>=7), 6, 30) -> 49856
G6: Year | H6: ="FY"&RIGHT(YEAR(H5)+(MONTH(H5)>6),2) -> FY25 | I6: ="FY"&RIGHT(YEAR(I5)+(MONTH(I5)>6),2) -> FY26 | J6: ="FY"&RIGHT(YEAR(J5)+(MONTH(J5)>6),2) -> FY27 | K6: ="FY"&RIGHT(YEAR(K5)+(MONTH(K5)>6),2) -> FY28 | L6: ="FY"&RIGHT(YEAR(L5)+(MONTH(L5)>6),2) -> FY29 | M6: ="FY"&RIGHT(YEAR(M5)+(MONTH(M5)>6),2) -> FY30 | N6: ="FY"&RIGHT(YEAR(N5)+(MONTH(N5)>6),2) -> FY31 | O6: ="FY"&RIGHT(YEAR(O5)+(MONTH(O5)>6),2) -> FY32 | ... S6: ="FY"&RIGHT(YEAR(S5)+(MONTH(S5)>6),2) -> FY36
C8: Ops Flag | D8: =Inputs!E22 -> 46569 | H8: =IF(H$5>$D$8,1,0) -> 0 | I8: =IF(I$5>$D$8,1,0) -> 0 | J8: =IF(J$5>$D$8,1,0) -> 0 | K8: =IF(K$5>$D$8,1,0) -> 1 | L8: =IF(L$5>$D$8,1,0) -> 1 | M8: =IF(M$5>$D$8,1,0) -> 1 | N8: =IF(N$5>$D$8,1,0) -> 1 | O8: =IF(O$5>$D$8,1,0) -> 1 | ... S8: =IF(S$5>$D$8,1,0) -> 1
C9: Construciton Flag | D9: =Inputs!E18 -> 46420 | H9: =IF(H8=1,0,IF(AND(H$5>=$D$9,H$5<=$D$10),1,0)) -> 0 | I9: =IF(I8=1,0,IF(AND(I$5>=$D$9,I$5<=$D$10),1,0)) -> 0 | J9: =IF(J8=1,0,IF(AND(J$5>=$D$9,J$5<=$D$10),1,0)) -> 1 | K9: =IF(K8=1,0,IF(AND(K$5>=$D$9,K$5<=$D$10),1,0)) -> 0 | L9: =IF(L8=1,0,IF(AND(L$5>=$D$9,L$5<=$D$10),1,0)) -> 0 | M9: =IF(M8=1,0,IF(AND(M$5>=$D$9,M$5<=$D$10),1,0)) -> 0 | N9: =IF(N8=1,0,IF(AND(N$5>=$D$9,N$5<=$D$10),1,0)) -> 0 | O9: =IF(O8=1,0,IF(AND(O$5>=$D$9,O$5<=$D$10),1,0)) -> 0 | ... S9: =IF(S8=1,0,IF(AND(S$5>=$D$9,S$5<=$D$10),1,0)) -> 0
C10: =Inputs!D17 -> Date | D10: =Inputs!E19 -> 46568
B12: REVENUE
C13: Event day revenue
C14: VHA | H14: =(IF(H8=1,INDEX('Revenue Assumptions'!$F$108:$P$108,MATCH((2000+VALUE(RIGHT(H$6,2))),'Revenue Assumptions'!$F$35:$P$35,0))*Scenarios!$B$6,0)) -> 0 | I14: =(IF(I8=1,INDEX('Revenue Assumptions'!$F$108:$P$108,MATCH((2000+VALUE(RIGHT(I$6,2))),'Revenue Assumptions'!$F$35:$P$35,0))*Scenarios!$B$6,0)) -> 0 | J14: =(IF(J8=1,INDEX('Revenue Assumptions'!$F$108:$P$108,MATCH((2000+VALUE(RIGHT(J$6,2))),'Revenue Assumptions'!$F$35:$P$35,0))*Scenarios!$B$6,0)) -> 0 | K14: =(IF(K8=1,INDEX('Revenue Assumptions'!$F$108:$P$108,MATCH((2000+VALUE(RIGHT(K$6,2))),'Revenue Assumptions'!$F$35:$P$35,0))*Scenarios!$B$6,0)) -> 5428852.5 | L14: =(IF(L8=1,INDEX('Revenue Assumptions'!$F$108:$P$108,MATCH((2000+VALUE(RIGHT(L$6,2))),'Revenue Assumptions'!$F$35:$P$35,0))*Scenarios!$B$6,0)) -> 5879207.5 | M14: =(IF(M8=1,INDEX('Revenue Assumptions'!$F$108:$P$108,MATCH((2000+VALUE(RIGHT(M$6,2))),'Revenue Assumptions'!$F$35:$P$35,0))*Scenarios!$B$6,0)) -> 6281388.4 | N14: =(IF(N8=1,INDEX('Revenue Assumptions'!$F$108:$P$108,MATCH((2000+VALUE(RIGHT(N$6,2))),'Revenue Assumptions'!$F$35:$P$35,0))*Scenarios!$B$6,0)) -> 6469770.2 | O14: =(IF(O8=1,INDEX('Revenue Assumptions'!$F$108:$P$108,MATCH((2000+VALUE(RIGHT(O$6,2))),'Revenue Assumptions'!$F$35:$P$35,0))*Scenarios!$B$6,0)) -> 6663803.4 | ... S14: =(IF(S8=1,INDEX('Revenue Assumptions'!$F$108:$P$108,MATCH((2000+VALUE(RIGHT(S$6,2))),'Revenue Assumptions'!$F$35:$P$35,0))*Scenarios!$B$6,0)) -> 7499918.4
C15: Premium Sales | H15: =(IF(H8=1,INDEX('Revenue Assumptions'!$F$124:$P$124,MATCH((2000+VALUE(RIGHT(H$6,2))),'Revenue Assumptions'!$F$35:$P$35,0))*Scenarios!$B$6,0)) -> 0 | I15: =(IF(I8=1,INDEX('Revenue Assumptions'!$F$124:$P$124,MATCH((2000+VALUE(RIGHT(I$6,2))),'Revenue Assumptions'!$F$35:$P$35,0))*Scenarios!$B$6,0)) -> 0 | J15: =(IF(J8=1,INDEX('Revenue Assumptions'!$F$124:$P$124,MATCH((2000+VALUE(RIGHT(J$6,2))),'Revenue Assumptions'!$F$35:$P$35,0))*Scenarios!$B$6,0)) -> 0 | K15: =(IF(K8=1,INDEX('Revenue Assumptions'!$F$124:$P$124,MATCH((2000+VALUE(RIGHT(K$6,2))),'Revenue Assumptions'!$F$35:$P$35,0))*Scenarios!$B$6,0)) -> 754257.03 | L15: =(IF(L8=1,INDEX('Revenue Assumptions'!$F$124:$P$124,MATCH((2000+VALUE(RIGHT(L$6,2))),'Revenue Assumptions'!$F$35:$P$35,0))*Scenarios!$B$6,0)) -> 832673.89 | M15: =(IF(M8=1,INDEX('Revenue Assumptions'!$F$124:$P$124,MATCH((2000+VALUE(RIGHT(M$6,2))),'Revenue Assumptions'!$F$35:$P$35,0))*Scenarios!$B$6,0)) -> 857654.1 | N15: =(IF(N8=1,INDEX('Revenue Assumptions'!$F$124:$P$124,MATCH((2000+VALUE(RIGHT(N$6,2))),'Revenue Assumptions'!$F$35:$P$35,0))*Scenarios!$B$6,0)) -> 883383.73 | O15: =(IF(O8=1,INDEX('Revenue Assumptions'!$F$124:$P$124,MATCH((2000+VALUE(RIGHT(O$6,2))),'Revenue Assumptions'!$F$35:$P$35,0))*Scenarios!$B$6,0)) -> 909885.24 | ... S15: =(IF(S8=1,INDEX('Revenue Assumptions'!$F$124:$P$124,MATCH((2000+VALUE(RIGHT(S$6,2))),'Revenue Assumptions'!$F$35:$P$35,0))*Scenarios!$B$6,0)) -> 1024083.9
C16: Premium F&B | H16: =(IF(H8=1,INDEX('Revenue Assumptions'!$F$159:$P$159,MATCH((2000+VALUE(RIGHT(H$6,2))),'Revenue Assumptions'!$F$35:$P$35,0))*Scenarios!$B$6,0)) -> 0 | I16: =(IF(I8=1,INDEX('Revenue Assumptions'!$F$159:$P$159,MATCH((2000+VALUE(RIGHT(I$6,2))),'Revenue Assumptions'!$F$35:$P$35,0))*Scenarios!$B$6,0)) -> 0 | J16: =(IF(J8=1,INDEX('Revenue Assumptions'!$F$159:$P$159,MATCH((2000+VALUE(RIGHT(J$6,2))),'Revenue Assumptions'!$F$35:$P$35,0))*Scenarios!$B$6,0)) -> 0 | K16: =(IF(K8=1,INDEX('Revenue Assumptions'!$F$159:$P$159,MATCH((2000+VALUE(RIGHT(K$6,2))),'Revenue Assumptions'!$F$35:$P$35,0))*Scenarios!$B$6,0)) -> 111570.94 | L16: =(IF(L8=1,INDEX('Revenue Assumptions'!$F$159:$P$159,MATCH((2000+VALUE(RIGHT(L$6,2))),'Revenue Assumptions'!$F$35:$P$35,0))*Scenarios!$B$6,0)) -> 119583 | M16: =(IF(M8=1,INDEX('Revenue Assumptions'!$F$159:$P$159,MATCH((2000+VALUE(RIGHT(M$6,2))),'Revenue Assumptions'!$F$35:$P$35,0))*Scenarios!$B$6,0)) -> 119583 | N16: =(IF(N8=1,INDEX('Revenue Assumptions'!$F$159:$P$159,MATCH((2000+VALUE(RIGHT(N$6,2))),'Revenue Assumptions'!$F$35:$P$35,0))*Scenarios!$B$6,0)) -> 123170.49 | O16: =(IF(O8=1,INDEX('Revenue Assumptions'!$F$159:$P$159,MATCH((2000+VALUE(RIGHT(O$6,2))),'Revenue Assumptions'!$F$35:$P$35,0))*Scenarios!$B$6,0)) -> 126865.6 | ... S16: =(IF(S8=1,INDEX('Revenue Assumptions'!$F$159:$P$159,MATCH((2000+VALUE(RIGHT(S$6,2))),'Revenue Assumptions'!$F$35:$P$35,0))*Scenarios!$B$6,0)) -> 142788.36
C17: F&B | H17: =(IF(H8=1,INDEX('Revenue Assumptions'!$F$141:$P$141,MATCH((2000+VALUE(RIGHT(H$6,2))),'Revenue Assumptions'!$F$35:$P$35,0))*Scenarios!$B$6,0)) -> 0 | I17: =(IF(I8=1,INDEX('Revenue Assumptions'!$F$141:$P$141,MATCH((2000+VALUE(RIGHT(I$6,2))),'Revenue Assumptions'!$F$35:$P$35,0))*Scenarios!$B$6,0)) -> 0 | J17: =(IF(J8=1,INDEX('Revenue Assumptions'!$F$141:$P$141,MATCH((2000+VALUE(RIGHT(J$6,2))),'Revenue Assumptions'!$F$35:$P$35,0))*Scenarios!$B$6,0)) -> 0 | K17: ='Revenue Assumptions'!F159 -> 106115.4 | L17: ='Revenue Assumptions'!G159 -> 111570.94 | M17: ='Revenue Assumptions'!H159 -> 119583 | N17: ='Revenue Assumptions'!I159 -> 119583 | O17: ='Revenue Assumptions'!J159 -> 123170.49 | P17: ='Revenue Assumptions'!K159 -> 126865.6 | Q17: ='Revenue Assumptions'!L159 -> 130671.57 | R17: ='Revenue Assumptions'!M159 -> 134591.72 | S17: ='Revenue Assumptions'!N159 -> 138629.47
C18: Merchandise | H18: =IF(H$8=1,INDEX('Calendar Assumptions'!$F$52:$Q$52,MATCH((2000+VALUE(RIGHT(H$6,2))),'Calendar Assumptions'!$F$2:$Q$2,0))*Inputs!$E$192*Scenarios!$B$6,0) -> 0 | I18: =IF(I$8=1,INDEX('Calendar Assumptions'!$F$52:$Q$52,MATCH((2000+VALUE(RIGHT(I$6,2))),'Calendar Assumptions'!$F$2:$Q$2,0))*Inputs!$E$192*Scenarios!$B$6,0) -> 0 | J18: =IF(J$8=1,INDEX('Calendar Assumptions'!$F$52:$Q$52,MATCH((2000+VALUE(RIGHT(J$6,2))),'Calendar Assumptions'!$F$2:$Q$2,0))*Inputs!$E$192*Scenarios!$B$6,0) -> 0 | K18: ='Revenue Assumptions'!F141 -> 5342413.7 | L18: ='Revenue Assumptions'!G141 -> 5635293.4 | M18: ='Revenue Assumptions'!H141 -> 6039971.5 | N18: ='Revenue Assumptions'!I141 -> 6169462.6 | O18: ='Revenue Assumptions'!J141 -> 6354546.5 | P18: ='Revenue Assumptions'!K141 -> 6545182.9 | Q18: ='Revenue Assumptions'!L141 -> 6741538.3 | R18: ='Revenue Assumptions'!M141 -> 6943784.5 | S18: ='Revenue Assumptions'!N141 -> 7152098
C19: Facilities Fee | H19: =IF(H$8=1,INDEX('Calendar Assumptions'!$F$16:$Q$16,MATCH((2000+VALUE(RIGHT(H$6,2))),'Calendar Assumptions'!$F$2:$Q$2,0))*Inputs!$E$194*Scenarios!$B$6,0) -> 0 | I19: =IF(I$8=1,INDEX('Calendar Assumptions'!$F$16:$Q$16,MATCH((2000+VALUE(RIGHT(I$6,2))),'Calendar Assumptions'!$F$2:$Q$2,0))*Inputs!$E$194*Scenarios!$B$6,0) -> 0 | J19: =IF(J$8=1,INDEX('Calendar Assumptions'!$F$16:$Q$16,MATCH((2000+VALUE(RIGHT(J$6,2))),'Calendar Assumptions'!$F$2:$Q$2,0))*Inputs!$E$194*Scenarios!$B$6,0) -> 0 | K19: =Inputs!$E$192*'Calendar Assumptions'!F52 -> 1635202.9 | L19: =Inputs!$E$192*'Calendar Assumptions'!G52 -> 1669916.7 | M19: =Inputs!$E$192*'Calendar Assumptions'!H52 -> 1704630.5 | N19: =Inputs!$E$192*'Calendar Assumptions'!I52 -> 1827042.3 | O19: =Inputs!$E$192*'Calendar Assumptions'!J52 -> 1827042.3 | P19: =Inputs!$E$192*'Calendar Assumptions'!K52 -> 1827042.3 | Q19: =Inputs!$E$192*'Calendar Assumptions'!L52 -> 1827042.3 | R19: =Inputs!$E$192*'Calendar Assumptions'!M52 -> 1827042.3 | S19: =Inputs!$E$192*'Calendar Assumptions'!N52 -> 1827042.3
C20: Equipment Hire | H20: =IF(H$8=1,INDEX('Calendar Assumptions'!$F$83:$Q$83,MATCH((2000+VALUE(RIGHT(H$6,2))),'Calendar Assumptions'!$F$2:$Q$2,0))*Scenarios!$B$6,0) -> 0 | I20: =IF(I$8=1,INDEX('Calendar Assumptions'!$F$83:$Q$83,MATCH((2000+VALUE(RIGHT(I$6,2))),'Calendar Assumptions'!$F$2:$Q$2,0))*Scenarios!$B$6,0) -> 0 | J20: =IF(J$8=1,INDEX('Calendar Assumptions'!$F$83:$Q$83,MATCH((2000+VALUE(RIGHT(J$6,2))),'Calendar Assumptions'!$F$2:$Q$2,0))*Scenarios!$B$6,0) -> 0 | K20: ='Calendar Assumptions'!G83 -> 2328872 | L20: ='Calendar Assumptions'!H83 -> 2377284 | M20: ='Calendar Assumptions'!I83 -> 2548000 | N20: ='Calendar Assumptions'!J83 -> 2548000 | O20: ='Calendar Assumptions'!K83 -> 2548000 | P20: ='Calendar Assumptions'!L83 -> 2548000 | Q20: ='Calendar Assumptions'!M83 -> 2548000 | R20: ='Calendar Assumptions'!N83 -> 2548000 | S20: ='Calendar Assumptions'!O83 -> 2548000
C21: ="Total "& C13 -> Total Event day revenue | H21: =SUM(H14:H20) -> 0 | I21: =SUM(I14:I20) -> 0 | J21: =SUM(J14:J20) -> 0 | K21: =SUM(K14:K20) -> 15707284 | L21: =SUM(L14:L20) -> 16625529 | M21: =SUM(M14:M20) -> 17670811 | N21: =SUM(N14:N20) -> 18140412 | O21: =SUM(O14:O20) -> 18553313 | ... S21: =SUM(S14:S20) -> 20332560
C23: Non-event day revenue
C24: Sponorship | H24: =IF(H8=1,INDEX('Revenue Assumptions'!$F$175:$P$175,MATCH((2000+VALUE(RIGHT(H$6,2))),'Revenue Assumptions'!$F$35:$P$35,0))*Scenarios!$B$6,0) -> 0 | I24: =IF(I8=1,INDEX('Revenue Assumptions'!$F$175:$P$175,MATCH((2000+VALUE(RIGHT(I$6,2))),'Revenue Assumptions'!$F$35:$P$35,0))*Scenarios!$B$6,0) -> 0 | J24: =IF(J8=1,INDEX('Revenue Assumptions'!$F$175:$P$175,MATCH((2000+VALUE(RIGHT(J$6,2))),'Revenue Assumptions'!$F$35:$P$35,0))*Scenarios!$B$6,0) -> 0 | K24: =IF(K8=1,INDEX('Revenue Assumptions'!$F$175:$P$175,MATCH((2000+VALUE(RIGHT(K$6,2))),'Revenue Assumptions'!$F$35:$P$35,0))*Scenarios!$B$6,0) -> 1896250 | L24: =IF(L8=1,INDEX('Revenue Assumptions'!$F$175:$P$175,MATCH((2000+VALUE(RIGHT(L$6,2))),'Revenue Assumptions'!$F$35:$P$35,0))*Scenarios!$B$6,0) -> 1943656.2 | M24: =IF(M8=1,INDEX('Revenue Assumptions'!$F$175:$P$175,MATCH((2000+VALUE(RIGHT(M$6,2))),'Revenue Assumptions'!$F$35:$P$35,0))*Scenarios!$B$6,0) -> 1992247.7 | N24: =IF(N8=1,INDEX('Revenue Assumptions'!$F$175:$P$175,MATCH((2000+VALUE(RIGHT(N$6,2))),'Revenue Assumptions'!$F$35:$P$35,0))*Scenarios!$B$6,0) -> 2042053.8 | O24: =IF(O8=1,INDEX('Revenue Assumptions'!$F$175:$P$175,MATCH((2000+VALUE(RIGHT(O$6,2))),'Revenue Assumptions'!$F$35:$P$35,0))*Scenarios!$B$6,0) -> 2093105.2 | ... S24: =IF(S8=1,INDEX('Revenue Assumptions'!$F$175:$P$175,MATCH((2000+VALUE(RIGHT(S$6,2))),'Revenue Assumptions'!$F$35:$P$35,0))*Scenarios!$B$6,0) -> 2310396.5
C25: Advertising | H25: =(IF(H8=1,INDEX('Revenue Assumptions'!$F$183:$P$183,MATCH((2000+VALUE(RIGHT(H$6,2))),'Revenue Assumptions'!$F$35:$P$35,0))*Scenarios!$B$6,0)) -> 0 | I25: =(IF(I8=1,INDEX('Revenue Assumptions'!$F$183:$P$183,MATCH((2000+VALUE(RIGHT(I$6,2))),'Revenue Assumptions'!$F$35:$P$35,0))*Scenarios!$B$6,0)) -> 0 | J25: =(IF(J8=1,INDEX('Revenue Assumptions'!$F$183:$P$183,MATCH((2000+VALUE(RIGHT(J$6,2))),'Revenue Assumptions'!$F$35:$P$35,0))*Scenarios!$B$6,0)) -> 0 | K25: =(IF(K8=1,INDEX('Revenue Assumptions'!$F$183:$P$183,MATCH((2000+VALUE(RIGHT(K$6,2))),'Revenue Assumptions'!$F$35:$P$35,0))*Scenarios!$B$6,0)) -> 589375 | L25: =(IF(L8=1,INDEX('Revenue Assumptions'!$F$183:$P$183,MATCH((2000+VALUE(RIGHT(L$6,2))),'Revenue Assumptions'!$F$35:$P$35,0))*Scenarios!$B$6,0)) -> 604109.37 | M25: =(IF(M8=1,INDEX('Revenue Assumptions'!$F$183:$P$183,MATCH((2000+VALUE(RIGHT(M$6,2))),'Revenue Assumptions'!$F$35:$P$35,0))*Scenarios!$B$6,0)) -> 619212.11 | N25: =(IF(N8=1,INDEX('Revenue Assumptions'!$F$183:$P$183,MATCH((2000+VALUE(RIGHT(N$6,2))),'Revenue Assumptions'!$F$35:$P$35,0))*Scenarios!$B$6,0)) -> 634692.41 | O25: =(IF(O8=1,INDEX('Revenue Assumptions'!$F$183:$P$183,MATCH((2000+VALUE(RIGHT(O$6,2))),'Revenue Assumptions'!$F$35:$P$35,0))*Scenarios!$B$6,0)) -> 650559.72 | ... S25: =(IF(S8=1,INDEX('Revenue Assumptions'!$F$183:$P$183,MATCH((2000+VALUE(RIGHT(S$6,2))),'Revenue Assumptions'!$F$35:$P$35,0))*Scenarios!$B$6,0)) -> 718096.21
C26: ="Total "& C23 -> Total Non-event day revenue | H26: =H24+H25 -> 0 | I26: =I24+I25 -> 0 | J26: =J24+J25 -> 0 | K26: =K24+K25 -> 2485625 | L26: =L24+L25 -> 2547765.6 | M26: =M24+M25 -> 2611459.8 | N26: =N24+N25 -> 2676746.3 | O26: =O24+O25 -> 2743664.9 | ... S26: =S24+S25 -> 3028492.7
C28: Total Revenue | H28: =H21+H26 -> 0 | I28: =I21+I26 -> 0 | J28: =J21+J26 -> 0 | K28: =K21+K26 -> 18192909 | L28: =L21+L26 -> 19173295 | M28: =M21+M26 -> 20282270 | N28: =N21+N26 -> 20817159 | O28: =O21+O26 -> 21296978 | ... S28: =S21+S26 -> 23361053
B30: COGS
C31: Food & Beverage
C32: CoG F&B (GA) | H32: =H17*Inputs!$E$250*Scenarios!$B$7 -> 0 | I32: =I17*Inputs!$E$250*Scenarios!$B$7 -> 0 | J32: =J17*Inputs!$E$250*Scenarios!$B$7 -> 0 | K32: =K17*Inputs!$E$250*Scenarios!$B$7 -> 31834.62 | L32: =L17*Inputs!$E$250*Scenarios!$B$7 -> 33471.282 | M32: =M17*Inputs!$E$250*Scenarios!$B$7 -> 35874.9 | N32: =N17*Inputs!$E$250*Scenarios!$B$7 -> 35874.9 | O32: =O17*Inputs!$E$250*Scenarios!$B$7 -> 36951.147 | ... S32: =S17*Inputs!$E$250*Scenarios!$B$7 -> 41588.841
C33: CoG F&B (Premium) | H33: =H16*Inputs!$E$250*Scenarios!$B$7 -> 0 | I33: =I16*Inputs!$E$250*Scenarios!$B$7 -> 0 | J33: =J16*Inputs!$E$250*Scenarios!$B$7 -> 0 | K33: =K16*Inputs!$E$250*Scenarios!$B$7 -> 33471.282 | L33: =L16*Inputs!$E$250*Scenarios!$B$7 -> 35874.9 | M33: =M16*Inputs!$E$250*Scenarios!$B$7 -> 35874.9 | N33: =N16*Inputs!$E$250*Scenarios!$B$7 -> 36951.147 | O33: =O16*Inputs!$E$250*Scenarios!$B$7 -> 38059.681 | ... S33: =S16*Inputs!$E$250*Scenarios!$B$7 -> 42836.507
C34: Consumables | H34: =(H16+H17)*Inputs!$E$251*Scenarios!$B$7 -> 0 | I34: =(I16+I17)*Inputs!$E$251*Scenarios!$B$7 -> 0 | J34: =(J16+J17)*Inputs!$E$251*Scenarios!$B$7 -> 0 | K34: =(K16+K17)*Inputs!$E$251*Scenarios!$B$7 -> 10884.317 | L34: =(L16+L17)*Inputs!$E$251*Scenarios!$B$7 -> 11557.697 | M34: =(M16+M17)*Inputs!$E$251*Scenarios!$B$7 -> 11958.3 | N34: =(N16+N17)*Inputs!$E$251*Scenarios!$B$7 -> 12137.675 | O34: =(O16+O17)*Inputs!$E$251*Scenarios!$B$7 -> 12501.805 | ... S34: =(S16+S17)*Inputs!$E$251*Scenarios!$B$7 -> 14070.891
C35: F&B RM | H35: =0 -> 0 | I35: =0 -> 0 | J35: =0 -> 0 | K35: =0 -> 0 | L35: =0 -> 0 | M35: =0 -> 0 | N35: =0 -> 0 | O35: =0 -> 0 | ... S35: =0 -> 0
C36: Total COGS | H36: =SUM(H32:H35) -> 0 | I36: =SUM(I32:I35) -> 0 | J36: =SUM(J32:J35) -> 0 | K36: =SUM(K32:K35) -> 76190.219 | L36: =SUM(L32:L35) -> 80903.879 | M36: =SUM(M32:M35) -> 83708.1 | N36: =SUM(N32:N35) -> 84963.721 | O36: =SUM(O32:O35) -> 87512.633 | ... S36: =SUM(S32:S35) -> 98496.24
J37: =SUM(J33:J36) -> 0
C38: COGS Margin | H38: =IF(H28=0,"",H36/H28) | I38: =IF(I28=0,"",I36/I28) | J38: =IF(J28=0,"",J36/J28) | K38: =IF(K28=0,"",K36/K28) -> 0.0041879073 | L38: =IF(L28=0,"",L36/L28) -> 0.0042196127 | M38: =IF(M28=0,"",M36/M28) -> 0.0041271563 | N38: =IF(N28=0,"",N36/N28) -> 0.0040814274 | O38: =IF(O28=0,"",O36/O28) -> 0.0041091573 | ... S38: =IF(S28=0,"",S36/S28) -> 0.0042162585
B40: GROSS PROFIT
C41: Gross Profit | H41: =H28-H36 -> 0 | I41: =I28-I36 -> 0 | J41: =J28-J36 -> 0 | K41: =K28-K36 -> 18116719 | L41: =L28-L36 -> 19092391 | M41: =M28-M36 -> 20198562 | N41: =N28-N36 -> 20732195 | O41: =O28-O36 -> 21209466 | ... S41: =S28-S36 -> 23262557
C42: GPM | H42: =IF(H28=0,"",H41/H28) | I42: =IF(I28=0,"",I41/I28) | J42: =IF(J28=0,"",J41/J28) | K42: =IF(K28=0,"",K41/K28) -> 0.99581209 | L42: =IF(L28=0,"",L41/L28) -> 0.99578039 | M42: =IF(M28=0,"",M41/M28) -> 0.99587284 | N42: =IF(N28=0,"",N41/N28) -> 0.99591857 | O42: =IF(O28=0,"",O41/O28) -> 0.99589084 | ... S42: =IF(S28=0,"",S41/S28) -> 0.99578374
B44: OPERATING EXPENSES
C45: Leased equipment | H45: =IF(H$8=1,Inputs!$E$227*Scenarios!$B$7,0) -> 0 | I45: =IF(I$8=1,Inputs!$E$227*Scenarios!$B$7,0) -> 0 | J45: =IF(J$8=1,Inputs!$E$227*Scenarios!$B$7,0) -> 0 | K45: =IF(K$8=1,Inputs!$E$227*Scenarios!$B$7,0) -> 350000 | L45: =IF(L$8=1,Inputs!$E$227*Scenarios!$B$7,0) -> 350000 | M45: =IF(M$8=1,Inputs!$E$227*Scenarios!$B$7,0) -> 350000 | N45: =IF(N$8=1,Inputs!$E$227*Scenarios!$B$7,0) -> 350000 | O45: =IF(O$8=1,Inputs!$E$227*Scenarios!$B$7,0) -> 350000 | ... S45: =IF(S$8=1,Inputs!$E$227*Scenarios!$B$7,0) -> 350000
C46: Utilities | H46: =IF(H8=1,Inputs!$E$228*(1+Inputs!$E$310)^((2000+VALUE(RIGHT(H$6,2)))-2027)*Scenarios!$B$7,0) -> 0 | I46: =IF(I8=1,Inputs!$E$228*(1+Inputs!$E$310)^((2000+VALUE(RIGHT(I$6,2)))-2027)*Scenarios!$B$7,0) -> 0 | J46: =IF(J8=1,Inputs!$E$228*(1+Inputs!$E$310)^((2000+VALUE(RIGHT(J$6,2)))-2027)*Scenarios!$B$7,0) -> 0 | K46: =IF(K8=1,Inputs!$E$228*(1+Inputs!$E$310)^((2000+VALUE(RIGHT(K$6,2)))-2027)*Scenarios!$B$7,0) -> 206000 | L46: =IF(L8=1,Inputs!$E$228*(1+Inputs!$E$310)^((2000+VALUE(RIGHT(L$6,2)))-2027)*Scenarios!$B$7,0) -> 212180 | M46: =IF(M8=1,Inputs!$E$228*(1+Inputs!$E$310)^((2000+VALUE(RIGHT(M$6,2)))-2027)*Scenarios!$B$7,0) -> 218545.4 | N46: =IF(N8=1,Inputs!$E$228*(1+Inputs!$E$310)^((2000+VALUE(RIGHT(N$6,2)))-2027)*Scenarios!$B$7,0) -> 225101.76 | O46: =IF(O8=1,Inputs!$E$228*(1+Inputs!$E$310)^((2000+VALUE(RIGHT(O$6,2)))-2027)*Scenarios!$B$7,0) -> 231854.81 | ... S46: =IF(S8=1,Inputs!$E$228*(1+Inputs!$E$310)^((2000+VALUE(RIGHT(S$6,2)))-2027)*Scenarios!$B$7,0) -> 260954.64
C47: Maintenance (R&M) | H47: =IF(H8=1,INDEX('Expense Assumptions'!$F$86:$Q$86,MATCH((2000+VALUE(RIGHT(H$6,2))),'Expense Assumptions'!$F$21:$Q$21,0))*Scenarios!$B$7,0) -> 0 | I47: =IF(I8=1,INDEX('Expense Assumptions'!$F$86:$Q$86,MATCH((2000+VALUE(RIGHT(I$6,2))),'Expense Assumptions'!$F$21:$Q$21,0))*Scenarios!$B$7,0) -> 0 | J47: =IF(J8=1,INDEX('Expense Assumptions'!$F$86:$Q$86,MATCH((2000+VALUE(RIGHT(J$6,2))),'Expense Assumptions'!$F$21:$Q$21,0))*Scenarios!$B$7,0) -> 0 | K47: =IF(K8=1,INDEX('Expense Assumptions'!$F$86:$Q$86,MATCH((2000+VALUE(RIGHT(K$6,2))),'Expense Assumptions'!$F$21:$Q$21,0))*Scenarios!$B$7,0) -> 149350 | L47: =IF(L8=1,INDEX('Expense Assumptions'!$F$86:$Q$86,MATCH((2000+VALUE(RIGHT(L$6,2))),'Expense Assumptions'!$F$21:$Q$21,0))*Scenarios!$B$7,0) -> 153830.5 | M47: =IF(M8=1,INDEX('Expense Assumptions'!$F$86:$Q$86,MATCH((2000+VALUE(RIGHT(M$6,2))),'Expense Assumptions'!$F$21:$Q$21,0))*Scenarios!$B$7,0) -> 158445.42 | N47: =IF(N8=1,INDEX('Expense Assumptions'!$F$86:$Q$86,MATCH((2000+VALUE(RIGHT(N$6,2))),'Expense Assumptions'!$F$21:$Q$21,0))*Scenarios!$B$7,0) -> 163198.78 | O47: =IF(O8=1,INDEX('Expense Assumptions'!$F$86:$Q$86,MATCH((2000+VALUE(RIGHT(O$6,2))),'Expense Assumptions'!$F$21:$Q$21,0))*Scenarios!$B$7,0) -> 168094.74 | ... S47: =IF(S8=1,INDEX('Expense Assumptions'!$F$86:$Q$86,MATCH((2000+VALUE(RIGHT(S$6,2))),'Expense Assumptions'!$F$21:$Q$21,0))*Scenarios!$B$7,0) -> 189192.11
C48: Marketing | H48: =IF(H8=1,Inputs!$E$229*(1+Inputs!$E$308)^((2000+VALUE(RIGHT(H$6,2)))-2027)*Scenarios!$B$7,0) -> 0 | I48: =IF(I8=1,Inputs!$E$229*(1+Inputs!$E$308)^((2000+VALUE(RIGHT(I$6,2)))-2027)*Scenarios!$B$7,0) -> 0 | J48: =IF(J8=1,Inputs!$E$229*(1+Inputs!$E$308)^((2000+VALUE(RIGHT(J$6,2)))-2027)*Scenarios!$B$7,0) -> 0 | K48: =IF(K8=1,Inputs!$E$229*(1+Inputs!$E$308)^((2000+VALUE(RIGHT(K$6,2)))-2027)*Scenarios!$B$7,0) -> 51500 | L48: =IF(L8=1,Inputs!$E$229*(1+Inputs!$E$308)^((2000+VALUE(RIGHT(L$6,2)))-2027)*Scenarios!$B$7,0) -> 53045 | M48: =IF(M8=1,Inputs!$E$229*(1+Inputs!$E$308)^((2000+VALUE(RIGHT(M$6,2)))-2027)*Scenarios!$B$7,0) -> 54636.35 | N48: =IF(N8=1,Inputs!$E$229*(1+Inputs!$E$308)^((2000+VALUE(RIGHT(N$6,2)))-2027)*Scenarios!$B$7,0) -> 56275.44 | O48: =IF(O8=1,Inputs!$E$229*(1+Inputs!$E$308)^((2000+VALUE(RIGHT(O$6,2)))-2027)*Scenarios!$B$7,0) -> 57963.704 | ... S48: =IF(S8=1,Inputs!$E$229*(1+Inputs!$E$308)^((2000+VALUE(RIGHT(S$6,2)))-2027)*Scenarios!$B$7,0) -> 65238.659
C49: T&E | H49: =IF(H$8=1,Inputs!$E$232*(1+Inputs!$E$308)^((2000+VALUE(RIGHT(H$6,2)))-2027)*Scenarios!$B$7,0) -> 0 | I49: =IF(I$8=1,Inputs!$E$232*(1+Inputs!$E$308)^((2000+VALUE(RIGHT(I$6,2)))-2027)*Scenarios!$B$7,0) -> 0 | J49: =IF(J$8=1,Inputs!$E$232*(1+Inputs!$E$308)^((2000+VALUE(RIGHT(J$6,2)))-2027)*Scenarios!$B$7,0) -> 0 | K49: =IF(K$8=1,Inputs!$E$232*(1+Inputs!$E$308)^((2000+VALUE(RIGHT(K$6,2)))-2027)*Scenarios!$B$7,0) -> 51500 | L49: =IF(L$8=1,Inputs!$E$232*(1+Inputs!$E$308)^((2000+VALUE(RIGHT(L$6,2)))-2027)*Scenarios!$B$7,0) -> 53045 | M49: =IF(M$8=1,Inputs!$E$232*(1+Inputs!$E$308)^((2000+VALUE(RIGHT(M$6,2)))-2027)*Scenarios!$B$7,0) -> 54636.35 | N49: =IF(N$8=1,Inputs!$E$232*(1+Inputs!$E$308)^((2000+VALUE(RIGHT(N$6,2)))-2027)*Scenarios!$B$7,0) -> 56275.44 | O49: =IF(O$8=1,Inputs!$E$232*(1+Inputs!$E$308)^((2000+VALUE(RIGHT(O$6,2)))-2027)*Scenarios!$B$7,0) -> 57963.704 | ... S49: =IF(S$8=1,Inputs!$E$232*(1+Inputs!$E$308)^((2000+VALUE(RIGHT(S$6,2)))-2027)*Scenarios!$B$7,0) -> 65238.659
C50: Uniforms | H50: =IF(H$8=1,Inputs!$E$240*(1+Inputs!$E$308)^((2000+VALUE(RIGHT(H$6,2)))-2027)*Scenarios!$B$7,0) -> 0 | I50: =IF(I$8=1,Inputs!$E$240*(1+Inputs!$E$308)^((2000+VALUE(RIGHT(I$6,2)))-2027)*Scenarios!$B$7,0) -> 0 | J50: =IF(J$8=1,Inputs!$E$240*(1+Inputs!$E$308)^((2000+VALUE(RIGHT(J$6,2)))-2027)*Scenarios!$B$7,0) -> 0 | K50: =IF(K$8=1,Inputs!$E$240*(1+Inputs!$E$308)^((2000+VALUE(RIGHT(K$6,2)))-2027)*Scenarios!$B$7,0) -> 6437.5 | L50: =IF(L$8=1,Inputs!$E$240*(1+Inputs!$E$308)^((2000+VALUE(RIGHT(L$6,2)))-2027)*Scenarios!$B$7,0) -> 6630.625 | M50: =IF(M$8=1,Inputs!$E$240*(1+Inputs!$E$308)^((2000+VALUE(RIGHT(M$6,2)))-2027)*Scenarios!$B$7,0) -> 6829.5437 | N50: =IF(N$8=1,Inputs!$E$240*(1+Inputs!$E$308)^((2000+VALUE(RIGHT(N$6,2)))-2027)*Scenarios!$B$7,0) -> 7034.4301 | O50: =IF(O$8=1,Inputs!$E$240*(1+Inputs!$E$308)^((2000+VALUE(RIGHT(O$6,2)))-2027)*Scenarios!$B$7,0) -> 7245.463 | ... S50: =IF(S$8=1,Inputs!$E$240*(1+Inputs!$E$308)^((2000+VALUE(RIGHT(S$6,2)))-2027)*Scenarios!$B$7,0) -> 8154.8324
C51: Dues and subscriptions | H51: =IF(H$8=1,Inputs!$E$241*(1+Inputs!$E$308)^((2000+VALUE(RIGHT(H$6,2)))-2027)*Scenarios!$B$7,0) -> 0 | I51: =IF(I$8=1,Inputs!$E$241*(1+Inputs!$E$308)^((2000+VALUE(RIGHT(I$6,2)))-2027)*Scenarios!$B$7,0) -> 0 | J51: =IF(J$8=1,Inputs!$E$241*(1+Inputs!$E$308)^((2000+VALUE(RIGHT(J$6,2)))-2027)*Scenarios!$B$7,0) -> 0 | K51: =IF(K$8=1,Inputs!$E$241*(1+Inputs!$E$308)^((2000+VALUE(RIGHT(K$6,2)))-2027)*Scenarios!$B$7,0) -> 20600 | L51: =IF(L$8=1,Inputs!$E$241*(1+Inputs!$E$308)^((2000+VALUE(RIGHT(L$6,2)))-2027)*Scenarios!$B$7,0) -> 21218 | M51: =IF(M$8=1,Inputs!$E$241*(1+Inputs!$E$308)^((2000+VALUE(RIGHT(M$6,2)))-2027)*Scenarios!$B$7,0) -> 21854.54 | N51: =IF(N$8=1,Inputs!$E$241*(1+Inputs!$E$308)^((2000+VALUE(RIGHT(N$6,2)))-2027)*Scenarios!$B$7,0) -> 22510.176 | O51: =IF(O$8=1,Inputs!$E$241*(1+Inputs!$E$308)^((2000+VALUE(RIGHT(O$6,2)))-2027)*Scenarios!$B$7,0) -> 23185.481 | ... S51: =IF(S$8=1,Inputs!$E$241*(1+Inputs!$E$308)^((2000+VALUE(RIGHT(S$6,2)))-2027)*Scenarios!$B$7,0) -> 26095.464
C52: Licenses | H52: =IF(H$8=1,Inputs!$E$233*(1+Inputs!$E$308)^((2000+VALUE(RIGHT(H$6,2)))-2027)*Scenarios!$B$7,0) -> 0 | I52: =IF(I$8=1,Inputs!$E$233*(1+Inputs!$E$308)^((2000+VALUE(RIGHT(I$6,2)))-2027)*Scenarios!$B$7,0) -> 0 | J52: =IF(J$8=1,Inputs!$E$233*(1+Inputs!$E$308)^((2000+VALUE(RIGHT(J$6,2)))-2027)*Scenarios!$B$7,0) -> 0 | K52: =IF(K$8=1,Inputs!$E$233*(1+Inputs!$E$308)^((2000+VALUE(RIGHT(K$6,2)))-2027)*Scenarios!$B$7,0) -> 51500 | L52: =IF(L$8=1,Inputs!$E$233*(1+Inputs!$E$308)^((2000+VALUE(RIGHT(L$6,2)))-2027)*Scenarios!$B$7,0) -> 53045 | M52: =IF(M$8=1,Inputs!$E$233*(1+Inputs!$E$308)^((2000+VALUE(RIGHT(M$6,2)))-2027)*Scenarios!$B$7,0) -> 54636.35 | N52: =IF(N$8=1,Inputs!$E$233*(1+Inputs!$E$308)^((2000+VALUE(RIGHT(N$6,2)))-2027)*Scenarios!$B$7,0) -> 56275.44 | O52: =IF(O$8=1,Inputs!$E$233*(1+Inputs!$E$308)^((2000+VALUE(RIGHT(O$6,2)))-2027)*Scenarios!$B$7,0) -> 57963.704 | ... S52: =IF(S$8=1,Inputs!$E$233*(1+Inputs!$E$308)^((2000+VALUE(RIGHT(S$6,2)))-2027)*Scenarios!$B$7,0) -> 65238.659
C53: Pest control | H53: =IF(H$8=1,Inputs!$E$237*(1+Inputs!$E$308)^((2000+VALUE(RIGHT(H$6,2)))-2027)*Scenarios!$B$7,0) -> 0 | I53: =IF(I$8=1,Inputs!$E$237*(1+Inputs!$E$308)^((2000+VALUE(RIGHT(I$6,2)))-2027)*Scenarios!$B$7,0) -> 0 | J53: =IF(J$8=1,Inputs!$E$237*(1+Inputs!$E$308)^((2000+VALUE(RIGHT(J$6,2)))-2027)*Scenarios!$B$7,0) -> 0 | K53: =IF(K$8=1,Inputs!$E$237*(1+Inputs!$E$308)^((2000+VALUE(RIGHT(K$6,2)))-2027)*Scenarios!$B$7,0) -> 5150 | L53: =IF(L$8=1,Inputs!$E$237*(1+Inputs!$E$308)^((2000+VALUE(RIGHT(L$6,2)))-2027)*Scenarios!$B$7,0) -> 5304.5 | M53: =IF(M$8=1,Inputs!$E$237*(1+Inputs!$E$308)^((2000+VALUE(RIGHT(M$6,2)))-2027)*Scenarios!$B$7,0) -> 5463.635 | N53: =IF(N$8=1,Inputs!$E$237*(1+Inputs!$E$308)^((2000+VALUE(RIGHT(N$6,2)))-2027)*Scenarios!$B$7,0) -> 5627.544 | O53: =IF(O$8=1,Inputs!$E$237*(1+Inputs!$E$308)^((2000+VALUE(RIGHT(O$6,2)))-2027)*Scenarios!$B$7,0) -> 5796.3704 | ... S53: =IF(S$8=1,Inputs!$E$237*(1+Inputs!$E$308)^((2000+VALUE(RIGHT(S$6,2)))-2027)*Scenarios!$B$7,0) -> 6523.8659
C54: Security Monitoring | H54: =IF(H$8=1,Inputs!$E$238*(1+Inputs!$E$308)^((2000+VALUE(RIGHT(H$6,2)))-2027)*Scenarios!$B$7,0) -> 0 | I54: =IF(I$8=1,Inputs!$E$238*(1+Inputs!$E$308)^((2000+VALUE(RIGHT(I$6,2)))-2027)*Scenarios!$B$7,0) -> 0 | J54: =IF(J$8=1,Inputs!$E$238*(1+Inputs!$E$308)^((2000+VALUE(RIGHT(J$6,2)))-2027)*Scenarios!$B$7,0) -> 0 | K54: =IF(K$8=1,Inputs!$E$238*(1+Inputs!$E$308)^((2000+VALUE(RIGHT(K$6,2)))-2027)*Scenarios!$B$7,0) -> 46350 | L54: =IF(L$8=1,Inputs!$E$238*(1+Inputs!$E$308)^((2000+VALUE(RIGHT(L$6,2)))-2027)*Scenarios!$B$7,0) -> 47740.5 | M54: =IF(M$8=1,Inputs!$E$238*(1+Inputs!$E$308)^((2000+VALUE(RIGHT(M$6,2)))-2027)*Scenarios!$B$7,0) -> 49172.715 | N54: =IF(N$8=1,Inputs!$E$238*(1+Inputs!$E$308)^((2000+VALUE(RIGHT(N$6,2)))-2027)*Scenarios!$B$7,0) -> 50647.896 | O54: =IF(O$8=1,Inputs!$E$238*(1+Inputs!$E$308)^((2000+VALUE(RIGHT(O$6,2)))-2027)*Scenarios!$B$7,0) -> 52167.333 | ... S54: =IF(S$8=1,Inputs!$E$238*(1+Inputs!$E$308)^((2000+VALUE(RIGHT(S$6,2)))-2027)*Scenarios!$B$7,0) -> 58714.793
C55: Trash Removal/Cleaning (non-event day) | H55: =IF(H$8=1,Inputs!$E$239*(1+Inputs!$E$308)^((2000+VALUE(RIGHT(H$6,2)))-2027)*Scenarios!$B$7,0) -> 0 | I55: =IF(I$8=1,Inputs!$E$239*(1+Inputs!$E$308)^((2000+VALUE(RIGHT(I$6,2)))-2027)*Scenarios!$B$7,0) -> 0 | J55: =IF(J$8=1,Inputs!$E$239*(1+Inputs!$E$308)^((2000+VALUE(RIGHT(J$6,2)))-2027)*Scenarios!$B$7,0) -> 0 | K55: =IF(K$8=1,Inputs!$E$239*(1+Inputs!$E$308)^((2000+VALUE(RIGHT(K$6,2)))-2027)*Scenarios!$B$7,0) -> 46350 | L55: =IF(L$8=1,Inputs!$E$239*(1+Inputs!$E$308)^((2000+VALUE(RIGHT(L$6,2)))-2027)*Scenarios!$B$7,0) -> 47740.5 | M55: =IF(M$8=1,Inputs!$E$239*(1+Inputs!$E$308)^((2000+VALUE(RIGHT(M$6,2)))-2027)*Scenarios!$B$7,0) -> 49172.715 | N55: =IF(N$8=1,Inputs!$E$239*(1+Inputs!$E$308)^((2000+VALUE(RIGHT(N$6,2)))-2027)*Scenarios!$B$7,0) -> 50647.896 | O55: =IF(O$8=1,Inputs!$E$239*(1+Inputs!$E$308)^((2000+VALUE(RIGHT(O$6,2)))-2027)*Scenarios!$B$7,0) -> 52167.333 | ... S55: =IF(S$8=1,Inputs!$E$239*(1+Inputs!$E$308)^((2000+VALUE(RIGHT(S$6,2)))-2027)*Scenarios!$B$7,0) -> 58714.793
C56: Health & Safety | H56: =IF(H$8=1,Inputs!$E$236*(1+Inputs!$E$308)^((2000+VALUE(RIGHT(H$6,2)))-2027)*Scenarios!$B$7,0) -> 0 | I56: =IF(I$8=1,Inputs!$E$236*(1+Inputs!$E$308)^((2000+VALUE(RIGHT(I$6,2)))-2027)*Scenarios!$B$7,0) -> 0 | J56: =IF(J$8=1,Inputs!$E$236*(1+Inputs!$E$308)^((2000+VALUE(RIGHT(J$6,2)))-2027)*Scenarios!$B$7,0) -> 0 | K56: =IF(K$8=1,Inputs!$E$236*(1+Inputs!$E$308)^((2000+VALUE(RIGHT(K$6,2)))-2027)*Scenarios!$B$7,0) -> 51500 | L56: =IF(L$8=1,Inputs!$E$236*(1+Inputs!$E$308)^((2000+VALUE(RIGHT(L$6,2)))-2027)*Scenarios!$B$7,0) -> 53045 | M56: =IF(M$8=1,Inputs!$E$236*(1+Inputs!$E$308)^((2000+VALUE(RIGHT(M$6,2)))-2027)*Scenarios!$B$7,0) -> 54636.35 | N56: =IF(N$8=1,Inputs!$E$236*(1+Inputs!$E$308)^((2000+VALUE(RIGHT(N$6,2)))-2027)*Scenarios!$B$7,0) -> 56275.44 | O56: =IF(O$8=1,Inputs!$E$236*(1+Inputs!$E$308)^((2000+VALUE(RIGHT(O$6,2)))-2027)*Scenarios!$B$7,0) -> 57963.704 | ... S56: =IF(S$8=1,Inputs!$E$236*(1+Inputs!$E$308)^((2000+VALUE(RIGHT(S$6,2)))-2027)*Scenarios!$B$7,0) -> 65238.659
C57: Sponsorship Commission (15%) | H57: =IF(H8=1,Inputs!$E$184*H24,0) -> 0 | I57: =IF(I8=1,Inputs!$E$184*I24,0) -> 0 | J57: =IF(J8=1,Inputs!$E$184*J24,0) -> 0 | K57: =IF(K8=1,Inputs!$E$184*K24,0) -> 284437.5 | L57: =IF(L8=1,Inputs!$E$184*L24,0) -> 291548.44 | M57: =IF(M8=1,Inputs!$E$184*M24,0) -> 298837.15 | N57: =IF(N8=1,Inputs!$E$184*N24,0) -> 306308.08 | O57: =IF(O8=1,Inputs!$E$184*O24,0) -> 313965.78 | ... S57: =IF(S8=1,Inputs!$E$184*S24,0) -> 346559.47
C58: Sponsorship Activation (5%) | H58: =IF(H8=1,Inputs!$E$185*H24,0) -> 0 | I58: =IF(I8=1,Inputs!$E$185*I24,0) -> 0 | J58: =IF(J8=1,Inputs!$E$185*J24,0) -> 0 | K58: =IF(K8=1,Inputs!$E$185*K24,0) -> 94812.5 | L58: =IF(L8=1,Inputs!$E$185*L24,0) -> 97182.812 | M58: =IF(M8=1,Inputs!$E$185*M24,0) -> 99612.383 | N58: =IF(N8=1,Inputs!$E$185*N24,0) -> 102102.69 | O58: =IF(O8=1,Inputs!$E$185*O24,0) -> 104655.26 | ... S58: =IF(S8=1,Inputs!$E$185*S24,0) -> 115519.82
C59: Lease deposit | H59: =0 -> 0 | I59: =0 -> 0 | J59: =0 -> 0 | K59: =0 -> 0 | L59: =0 -> 0 | M59: =0 -> 0 | N59: =0 -> 0 | O59: =0 -> 0 | ... S59: =0 -> 0
C60: ='Expense Assumptions'!C61 -> Annual Venue Lease | H60: =IF(H8=1,INDEX('Expense Assumptions'!$F$61:$Q$61,MATCH((2000+VALUE(RIGHT(H$6,2))),'Expense Assumptions'!$F$21:$Q$21,0))*Scenarios!$B$7,0) -> 0 | I60: =IF(I8=1,INDEX('Expense Assumptions'!$F$61:$Q$61,MATCH((2000+VALUE(RIGHT(I$6,2))),'Expense Assumptions'!$F$21:$Q$21,0))*Scenarios!$B$7,0) -> 0 | J60: =IF(J8=1,INDEX('Expense Assumptions'!$F$61:$Q$61,MATCH((2000+VALUE(RIGHT(J$6,2))),'Expense Assumptions'!$F$21:$Q$21,0))*Scenarios!$B$7,0) -> 0 | K60: =IF(K8=1,INDEX('Expense Assumptions'!$F$61:$Q$61,MATCH((2000+VALUE(RIGHT(K$6,2))),'Expense Assumptions'!$F$21:$Q$21,0))*Scenarios!$B$7,0) -> 0 | L60: =IF(L8=1,INDEX('Expense Assumptions'!$F$61:$Q$61,MATCH((2000+VALUE(RIGHT(L$6,2))),'Expense Assumptions'!$F$21:$Q$21,0))*Scenarios!$B$7,0) -> 357500 | M60: =IF(M8=1,INDEX('Expense Assumptions'!$F$61:$Q$61,MATCH((2000+VALUE(RIGHT(M$6,2))),'Expense Assumptions'!$F$21:$Q$21,0))*Scenarios!$B$7,0) -> 402512.5 | N60: =IF(N8=1,INDEX('Expense Assumptions'!$F$61:$Q$61,MATCH((2000+VALUE(RIGHT(N$6,2))),'Expense Assumptions'!$F$21:$Q$21,0))*Scenarios!$B$7,0) -> 416600.44 | O60: =IF(O8=1,INDEX('Expense Assumptions'!$F$61:$Q$61,MATCH((2000+VALUE(RIGHT(O$6,2))),'Expense Assumptions'!$F$21:$Q$21,0))*Scenarios!$B$7,0) -> 431181.45 | ... S60: =IF(S8=1,INDEX('Expense Assumptions'!$F$61:$Q$61,MATCH((2000+VALUE(RIGHT(S$6,2))),'Expense Assumptions'!$F$21:$Q$21,0))*Scenarios!$B$7,0) -> 989581.27
C61: Landlord Outgoings | H61: =IF(H$8=1,H$60*RM_OutgoingsPct,0) -> 0 | I61: =IF(I$8=1,I$60*RM_OutgoingsPct,0) -> 0 | J61: =IF(J$8=1,J$60*RM_OutgoingsPct,0) -> 0 | K61: =IF(K$8=1,K$60*RM_OutgoingsPct,0) -> 0 | L61: =IF(L$8=1,L$60*RM_OutgoingsPct,0) -> 53625 | M61: =IF(M$8=1,M$60*RM_OutgoingsPct,0) -> 60376.875 | N61: =IF(N$8=1,N$60*RM_OutgoingsPct,0) -> 62490.066 | O61: =IF(O$8=1,O$60*RM_OutgoingsPct,0) -> 64677.218 | ... S61: =IF(S$8=1,S$60*RM_OutgoingsPct,0) -> 148437.19
C62: Administrative / Legal / Other | H62: =IF(H8=1,Inputs!$E$231*(1+Inputs!$E$308)^((2000+VALUE(RIGHT(H$6,2)))-2027)*Scenarios!$B$7,0) -> 0 | I62: =IF(I8=1,Inputs!$E$231*(1+Inputs!$E$308)^((2000+VALUE(RIGHT(I$6,2)))-2027)*Scenarios!$B$7,0) -> 0 | J62: =IF(J8=1,Inputs!$E$231*(1+Inputs!$E$308)^((2000+VALUE(RIGHT(J$6,2)))-2027)*Scenarios!$B$7,0) -> 0 | K62: =IF(K8=1,Inputs!$E$231*(1+Inputs!$E$308)^((2000+VALUE(RIGHT(K$6,2)))-2027)*Scenarios!$B$7,0) -> 103000 | L62: =IF(L8=1,Inputs!$E$231*(1+Inputs!$E$308)^((2000+VALUE(RIGHT(L$6,2)))-2027)*Scenarios!$B$7,0) -> 106090 | M62: =IF(M8=1,Inputs!$E$231*(1+Inputs!$E$308)^((2000+VALUE(RIGHT(M$6,2)))-2027)*Scenarios!$B$7,0) -> 109272.7 | N62: =IF(N8=1,Inputs!$E$231*(1+Inputs!$E$308)^((2000+VALUE(RIGHT(N$6,2)))-2027)*Scenarios!$B$7,0) -> 112550.88 | O62: =IF(O8=1,Inputs!$E$231*(1+Inputs!$E$308)^((2000+VALUE(RIGHT(O$6,2)))-2027)*Scenarios!$B$7,0) -> 115927.41 | ... S62: =IF(S8=1,Inputs!$E$231*(1+Inputs!$E$308)^((2000+VALUE(RIGHT(S$6,2)))-2027)*Scenarios!$B$7,0) -> 130477.32
C63: Insurance | H63: =IF(H8=1,Inputs!$E$230*(1+Inputs!$E$311)^((2000+VALUE(RIGHT(H$6,2)))-2027)*Scenarios!$B$7,0) -> 0 | I63: =IF(I8=1,Inputs!$E$230*(1+Inputs!$E$311)^((2000+VALUE(RIGHT(I$6,2)))-2027)*Scenarios!$B$7,0) -> 0 | J63: =IF(J8=1,Inputs!$E$230*(1+Inputs!$E$311)^((2000+VALUE(RIGHT(J$6,2)))-2027)*Scenarios!$B$7,0) -> 0 | K63: =IF(K8=1,Inputs!$E$230*(1+Inputs!$E$311)^((2000+VALUE(RIGHT(K$6,2)))-2027)*Scenarios!$B$7,0) -> 105000 | L63: =IF(L8=1,Inputs!$E$230*(1+Inputs!$E$311)^((2000+VALUE(RIGHT(L$6,2)))-2027)*Scenarios!$B$7,0) -> 110250 | M63: =IF(M8=1,Inputs!$E$230*(1+Inputs!$E$311)^((2000+VALUE(RIGHT(M$6,2)))-2027)*Scenarios!$B$7,0) -> 115762.5 | N63: =IF(N8=1,Inputs!$E$230*(1+Inputs!$E$311)^((2000+VALUE(RIGHT(N$6,2)))-2027)*Scenarios!$B$7,0) -> 121550.62 | O63: =IF(O8=1,Inputs!$E$230*(1+Inputs!$E$311)^((2000+VALUE(RIGHT(O$6,2)))-2027)*Scenarios!$B$7,0) -> 127628.16 | ... S63: =IF(S8=1,Inputs!$E$230*(1+Inputs!$E$311)^((2000+VALUE(RIGHT(S$6,2)))-2027)*Scenarios!$B$7,0) -> 155132.82
C64: Bad debts | H64: =IF(H8=1,H28*Inputs!$E$244*Scenarios!$B$7,0) -> 0 | I64: =IF(I8=1,I28*Inputs!$E$244*Scenarios!$B$7,0) -> 0 | J64: =IF(J8=1,J28*Inputs!$E$244*Scenarios!$B$7,0) -> 0 | K64: =IF(K8=1,K28*Inputs!$E$244*Scenarios!$B$7,0) -> 90964.547 | L64: =IF(L8=1,L28*Inputs!$E$244*Scenarios!$B$7,0) -> 95866.475 | M64: =IF(M8=1,M28*Inputs!$E$244*Scenarios!$B$7,0) -> 101411.35 | N64: =IF(N8=1,N28*Inputs!$E$244*Scenarios!$B$7,0) -> 104085.79 | O64: =IF(O8=1,O28*Inputs!$E$244*Scenarios!$B$7,0) -> 106484.89 | ... S64: =IF(S8=1,S28*Inputs!$E$244*Scenarios!$B$7,0) -> 116805.27
C65: Audit | H65: =IF(H$8=1,Inputs!$E$234*(1+Inputs!$E$308)^((2000+VALUE(RIGHT(H$6,2)))-2027)*Scenarios!$B$7,0) -> 0 | I65: =IF(I$8=1,Inputs!$E$234*(1+Inputs!$E$308)^((2000+VALUE(RIGHT(I$6,2)))-2027)*Scenarios!$B$7,0) -> 0 | J65: =IF(J$8=1,Inputs!$E$234*(1+Inputs!$E$308)^((2000+VALUE(RIGHT(J$6,2)))-2027)*Scenarios!$B$7,0) -> 0 | K65: =IF(K$8=1,Inputs!$E$234*(1+Inputs!$E$308)^((2000+VALUE(RIGHT(K$6,2)))-2027)*Scenarios!$B$7,0) -> 25750 | L65: =IF(L$8=1,Inputs!$E$234*(1+Inputs!$E$308)^((2000+VALUE(RIGHT(L$6,2)))-2027)*Scenarios!$B$7,0) -> 26522.5 | M65: =IF(M$8=1,Inputs!$E$234*(1+Inputs!$E$308)^((2000+VALUE(RIGHT(M$6,2)))-2027)*Scenarios!$B$7,0) -> 27318.175 | N65: =IF(N$8=1,Inputs!$E$234*(1+Inputs!$E$308)^((2000+VALUE(RIGHT(N$6,2)))-2027)*Scenarios!$B$7,0) -> 28137.72 | O65: =IF(O$8=1,Inputs!$E$234*(1+Inputs!$E$308)^((2000+VALUE(RIGHT(O$6,2)))-2027)*Scenarios!$B$7,0) -> 28981.852 | ... S65: =IF(S$8=1,Inputs!$E$234*(1+Inputs!$E$308)^((2000+VALUE(RIGHT(S$6,2)))-2027)*Scenarios!$B$7,0) -> 32619.33
C66: Payroll Processing | H66: =IF(H$8=1,Inputs!$E$235*(1+Inputs!$E$308)^((2000+VALUE(RIGHT(H$6,2)))-2027)*Scenarios!$B$7,0) -> 0 | I66: =IF(I$8=1,Inputs!$E$235*(1+Inputs!$E$308)^((2000+VALUE(RIGHT(I$6,2)))-2027)*Scenarios!$B$7,0) -> 0 | J66: =IF(J$8=1,Inputs!$E$235*(1+Inputs!$E$308)^((2000+VALUE(RIGHT(J$6,2)))-2027)*Scenarios!$B$7,0) -> 0 | K66: =IF(K$8=1,Inputs!$E$235*(1+Inputs!$E$308)^((2000+VALUE(RIGHT(K$6,2)))-2027)*Scenarios!$B$7,0) -> 10300 | L66: =IF(L$8=1,Inputs!$E$235*(1+Inputs!$E$308)^((2000+VALUE(RIGHT(L$6,2)))-2027)*Scenarios!$B$7,0) -> 10609 | M66: =IF(M$8=1,Inputs!$E$235*(1+Inputs!$E$308)^((2000+VALUE(RIGHT(M$6,2)))-2027)*Scenarios!$B$7,0) -> 10927.27 | N66: =IF(N$8=1,Inputs!$E$235*(1+Inputs!$E$308)^((2000+VALUE(RIGHT(N$6,2)))-2027)*Scenarios!$B$7,0) -> 11255.088 | O66: =IF(O$8=1,Inputs!$E$235*(1+Inputs!$E$308)^((2000+VALUE(RIGHT(O$6,2)))-2027)*Scenarios!$B$7,0) -> 11592.741 | ... S66: =IF(S$8=1,Inputs!$E$235*(1+Inputs!$E$308)^((2000+VALUE(RIGHT(S$6,2)))-2027)*Scenarios!$B$7,0) -> 13047.732
H67: 0 | I67: 0 | J67: 0 | K67: 0 | L67: 0 | M67: 0 | N67: 0 | O67: 0 | P67: 0 | Q67: 0 | R67: 0 | S67: 0
C68: Staff costs | H68: =H69+H70+H71 -> 0 | I68: =I69+I70+I71 -> 0 | J68: =J69+J70+J71 -> 0 | K68: =K69+K70+K71 -> 2217997.1 | L68: =L69+L70+L71 -> 2286755 | M68: =M69+M70+M71 -> 2357644.4 | N68: =N69+N70+N71 -> 2430731.4 | O68: =O69+O70+O71 -> 2506084 | ... S68: =S69+S70+S71 -> 2831589.5
C69: Salaries | H69: =IF(H$8=1,INDEX('Expense Assumptions'!$F$35:$Q$35,MATCH((2000+VALUE(RIGHT(H$6,2))),'Expense Assumptions'!$F$21:$Q$21,0))*Scenarios!$B$7,0) -> 0 | I69: =IF(I$8=1,INDEX('Expense Assumptions'!$F$35:$Q$35,MATCH((2000+VALUE(RIGHT(I$6,2))),'Expense Assumptions'!$F$21:$Q$21,0))*Scenarios!$B$7,0) -> 0 | J69: =IF(J$8=1,INDEX('Expense Assumptions'!$F$35:$Q$35,MATCH((2000+VALUE(RIGHT(J$6,2))),'Expense Assumptions'!$F$21:$Q$21,0))*Scenarios!$B$7,0) -> 0 | K69: =IF(K$8=1,INDEX('Expense Assumptions'!$F$35:$Q$35,MATCH((2000+VALUE(RIGHT(K$6,2))),'Expense Assumptions'!$F$21:$Q$21,0))*Scenarios!$B$7,0) -> 1860284.8 | L69: =IF(L$8=1,INDEX('Expense Assumptions'!$F$35:$Q$35,MATCH((2000+VALUE(RIGHT(L$6,2))),'Expense Assumptions'!$F$21:$Q$21,0))*Scenarios!$B$7,0) -> 1917953.7 | M69: =IF(M$8=1,INDEX('Expense Assumptions'!$F$35:$Q$35,MATCH((2000+VALUE(RIGHT(M$6,2))),'Expense Assumptions'!$F$21:$Q$21,0))*Scenarios!$B$7,0) -> 1977410.2 | N69: =IF(N$8=1,INDEX('Expense Assumptions'!$F$35:$Q$35,MATCH((2000+VALUE(RIGHT(N$6,2))),'Expense Assumptions'!$F$21:$Q$21,0))*Scenarios!$B$7,0) -> 2038710 | O69: =IF(O$8=1,INDEX('Expense Assumptions'!$F$35:$Q$35,MATCH((2000+VALUE(RIGHT(O$6,2))),'Expense Assumptions'!$F$21:$Q$21,0))*Scenarios!$B$7,0) -> 2101910 | ... S69: =IF(S$8=1,INDEX('Expense Assumptions'!$F$35:$Q$35,MATCH((2000+VALUE(RIGHT(S$6,2))),'Expense Assumptions'!$F$21:$Q$21,0))*Scenarios!$B$7,0) -> 2374918.8
C70: Oncosts | H70: =IF(H$8=1,INDEX('Expense Assumptions'!$F$51:$Q$51,MATCH((2000+VALUE(RIGHT(H$6,2))),'Expense Assumptions'!$F$21:$Q$21,0))*Scenarios!$B$7,0) -> 0 | I70: =IF(I$8=1,INDEX('Expense Assumptions'!$F$51:$Q$51,MATCH((2000+VALUE(RIGHT(I$6,2))),'Expense Assumptions'!$F$21:$Q$21,0))*Scenarios!$B$7,0) -> 0 | J70: =IF(J$8=1,INDEX('Expense Assumptions'!$F$51:$Q$51,MATCH((2000+VALUE(RIGHT(J$6,2))),'Expense Assumptions'!$F$21:$Q$21,0))*Scenarios!$B$7,0) -> 0 | K70: =IF(K$8=1,INDEX('Expense Assumptions'!$F$51:$Q$51,MATCH((2000+VALUE(RIGHT(K$6,2))),'Expense Assumptions'!$F$21:$Q$21,0))*Scenarios!$B$7,0) -> 335751.85 | L70: =IF(L$8=1,INDEX('Expense Assumptions'!$F$51:$Q$51,MATCH((2000+VALUE(RIGHT(L$6,2))),'Expense Assumptions'!$F$21:$Q$21,0))*Scenarios!$B$7,0) -> 346160.16 | M70: =IF(M$8=1,INDEX('Expense Assumptions'!$F$51:$Q$51,MATCH((2000+VALUE(RIGHT(M$6,2))),'Expense Assumptions'!$F$21:$Q$21,0))*Scenarios!$B$7,0) -> 356891.12 | N70: =IF(N$8=1,INDEX('Expense Assumptions'!$F$51:$Q$51,MATCH((2000+VALUE(RIGHT(N$6,2))),'Expense Assumptions'!$F$21:$Q$21,0))*Scenarios!$B$7,0) -> 367954.75 | O70: =IF(O$8=1,INDEX('Expense Assumptions'!$F$51:$Q$51,MATCH((2000+VALUE(RIGHT(O$6,2))),'Expense Assumptions'!$F$21:$Q$21,0))*Scenarios!$B$7,0) -> 379361.35 | ... S70: =IF(S$8=1,INDEX('Expense Assumptions'!$F$51:$Q$51,MATCH((2000+VALUE(RIGHT(S$6,2))),'Expense Assumptions'!$F$21:$Q$21,0))*Scenarios!$B$7,0) -> 428635.11
C71: Training | H71: =IF(H8=1,Inputs!$E$245*(H69+H70),0) -> 0 | I71: =IF(I8=1,Inputs!$E$245*(I69+I70),0) -> 0 | J71: =IF(J8=1,Inputs!$E$245*(J69+J70),0) -> 0 | K71: =IF(K8=1,Inputs!$E$245*(K69+K70),0) -> 21960.367 | L71: =IF(L8=1,Inputs!$E$245*(L69+L70),0) -> 22641.138 | M71: =IF(M8=1,Inputs!$E$245*(M69+M70),0) -> 23343.014 | N71: =IF(N8=1,Inputs!$E$245*(N69+N70),0) -> 24066.647 | O71: =IF(O8=1,Inputs!$E$245*(O69+O70),0) -> 24812.713 | ... S71: =IF(S8=1,Inputs!$E$245*(S69+S70),0) -> 28035.539
C73: Promoter Loyalty Rebates | H73: =Inputs!$E$516 -> 0 | I73: =Inputs!$F$516 -> 0 | J73: =Inputs!$G$516 -> 0 | K73: =Inputs!$H$516 -> 148917.91 | L73: =Inputs!$I$516 -> 198305.03 | M73: =Inputs!$J$516 -> 213867.61 | N73: =Inputs!$K$516 -> 165715.97 | O73: =Inputs!$L$516 -> 216998.14 | P73: =Inputs!$M$516 -> 229335.41 | Q73: =Inputs!$N$516 -> 242217.66 | R73: =Inputs!$O$516 -> 255666.51 | S73: =Inputs!$P$516 -> 269704.33
C75: Total OPEX | H75: =H45+H46+H47+H48+H49+H50+H51+H52+H53+H54+H55+H56+H57+H58+H59+H60+H61+H62+H63+H64+H65+H66+H68+H73 -> 0 | I75: =I45+I46+I47+I48+I49+I50+I51+I52+I53+I54+I55+I56+I57+I58+I59+I60+I61+I62+I63+I64+I65+I66+I68+I73 -> 0 | J75: =J45+J46+J47+J48+J49+J50+J51+J52+J53+J54+J55+J56+J57+J58+J59+J60+J61+J62+J63+J64+J65+J66+J68+J73 -> 0 | K75: =K45+K46+K47+K48+K49+K50+K51+K52+K53+K54+K55+K56+K57+K58+K59+K60+K61+K62+K63+K64+K65+K66+K68+K73 -> 4117417 | L75: =L45+L46+L47+L48+L49+L50+L51+L52+L53+L54+L55+L56+L57+L58+L59+L60+L61+L62+L63+L64+L65+L66+L68+L73 -> 4691078.9 | M75: =M45+M46+M47+M48+M49+M50+M51+M52+M53+M54+M55+M56+M57+M58+M59+M60+M61+M62+M63+M64+M65+M66+M68+M73 -> 4875572.3 | N75: =N45+N46+N47+N48+N49+N50+N51+N52+N53+N54+N55+N56+N57+N58+N59+N60+N61+N62+N63+N64+N65+N66+N68+N73 -> 4961398.9 | O75: =O45+O46+O47+O48+O49+O50+O51+O52+O53+O54+O55+O56+O57+O58+O59+O60+O61+O62+O63+O64+O65+O66+O68+O73 -> 5150543.3 | ... S75: =S45+S46+S47+S48+S49+S50+S51+S52+S53+S54+S55+S56+S57+S58+S59+S60+S61+S62+S63+S64+S65+S66+S68+S73 -> 6368779.2
B77: EBITDA | H77: =H41-H75 -> 0 | I77: =I41-I75 -> 0 | J77: =J41-J75 -> 0 | K77: =K41-K75 -> 13999302 | L77: =L41-L75 -> 14401312 | M77: =M41-M75 -> 15322990 | N77: =N41-N75 -> 15770796 | O77: =O41-O75 -> 16058922 | ... S77: =S41-S75 -> 16893778
C78: EBITDA Margin | H78: =IF(H28=0,"",H77/H28) | I78: =IF(I28=0,"",I77/I28) | J78: =IF(J28=0,"",J77/J28) | K78: =IF(K28=0,"",K77/K28) -> 0.76949221 | L78: =IF(L28=0,"",L77/L28) -> 0.75111306 | M78: =IF(M28=0,"",M77/M28) -> 0.75548692 | N78: =IF(N28=0,"",N77/N28) -> 0.75758638 | O78: =IF(O28=0,"",O77/O28) -> 0.75404699 | ... S78: =IF(S28=0,"",S77/S28) -> 0.72315994
C79: Pre-opening expenses (below EBITDA) | H79: =IF(H$8=0,INDEX(Cashflow!$D$27:$O$27,MATCH(H$6,Cashflow!$D$7:$O$7,0)),0) -> 0 | I79: =IF(I$8=0,INDEX(Cashflow!$D$27:$O$27,MATCH(I$6,Cashflow!$D$7:$O$7,0)),0) -> 0 | J79: =IF(J$8=0,INDEX(Cashflow!$D$27:$O$27,MATCH(J$6,Cashflow!$D$7:$O$7,0)),0) -> 0 | K79: =IF(K$8=0,INDEX(Cashflow!$D$27:$O$27,MATCH(K$6,Cashflow!$D$7:$O$7,0)),0) -> 0 | L79: =IF(L$8=0,INDEX(Cashflow!$D$27:$O$27,MATCH(L$6,Cashflow!$D$7:$O$7,0)),0) -> 0 | M79: =IF(M$8=0,INDEX(Cashflow!$D$27:$O$27,MATCH(M$6,Cashflow!$D$7:$O$7,0)),0) -> 0 | N79: =IF(N$8=0,INDEX(Cashflow!$D$27:$O$27,MATCH(N$6,Cashflow!$D$7:$O$7,0)),0) -> 0 | O79: =IF(O$8=0,INDEX(Cashflow!$D$27:$O$27,MATCH(O$6,Cashflow!$D$7:$O$7,0)),0) -> 0 | ... S79: =IF(S$8=0,INDEX(Cashflow!$D$27:$O$27,MATCH(S$6,Cashflow!$D$7:$O$7,0)),0) -> 0
C81: Depreciation | H81: ='Construction Timeline'!D180 -> 0 | I81: ='Construction Timeline'!E180 -> 0 | J81: ='Construction Timeline'!F180 -> 0 | K81: ='Construction Timeline'!G180 -> 0 | L81: ='Construction Timeline'!H180 -> 0 | M81: ='Construction Timeline'!I180 -> 0 | N81: ='Construction Timeline'!J180 -> 0 | O81: ='Construction Timeline'!K180 -> 0 | ... S81: ='Construction Timeline'!O180 -> 0
B83: EBIT | H83: =H77-H79-H81 -> 0 | I83: =I77-I79-I81 -> 0 | J83: =J77-J79-J81 -> 0 | K83: =K77-K79-K81 -> 13999302 | L83: =L77-L79-L81 -> 14401312 | M83: =M77-M79-M81 -> 15322990 | N83: =N77-N79-N81 -> 15770796 | O83: =O77-O79-O81 -> 16058922 | ... S83: =S77-S79-S81 -> 16893778
C85: Net interest expense | H85: =IF(H$8=1,Debt!H57,0) -> 0 | I85: =IF(I$8=1,Debt!I57,0) -> 0 | J85: =IF(J$8=1,Debt!J57,0) -> 0 | K85: =IF(K$8=1,Debt!K57,0) -> 696660 | L85: =IF(L$8=1,Debt!L57,0) -> 614700 | M85: =IF(M$8=1,Debt!M57,0) -> 532740 | N85: =IF(N$8=1,Debt!N57,0) -> 450780 | O85: =IF(O$8=1,Debt!O57,0) -> 368820 | ... S85: =IF(S$8=1,Debt!S57,0) -> 40980
B87: PBT | H87: =H83-H85 -> 0 | I87: =I83-I85 -> 0 | J87: =J83-J85 -> 0 | K87: =K83-K85 -> 13302642 | L87: =L83-L85 -> 13786612 | M87: =M83-M85 -> 14790250 | N87: =N83-N85 -> 15320016 | O87: =O77-O79-O81 -> 16058922 | P87: =P83-P85 -> 15636978 | Q87: =Q83-Q85 -> 16005573 | R87: =R83-R85 -> 16424579 | S87: =S83-S85 -> 16852798
B89: Tax | C89: Income tax | H89: =MAX(0,H87)*Inputs!$E$260 -> 0 | I89: =IF(I87>0,MAX(0,I87-H90)*Inputs!$E$260,0) -> 0 | J89: =IF(J87>0,MAX(0,J87-I90)*Inputs!$E$260,0) -> 0 | K89: =IF(K87>0,MAX(0,K87-J90)*Inputs!$E$260,0) -> 3990792.6 | L89: =IF(L87>0,MAX(0,L87-K90)*Inputs!$E$260,0) -> 4135983.7 | M89: =IF(M87>0,MAX(0,M87-L90)*Inputs!$E$260,0) -> 4437075 | N89: =IF(N87>0,MAX(0,N87-M90)*Inputs!$E$260,0) -> 4596004.8 | O89: =IF(O87>0,MAX(0,O87-N90)*Inputs!$E$260,0) -> 4817676.7 | P89: =IF(P87>0,MAX(0,P87-O90)*Inputs!$E$260,0) -> 4691093.5 | ... S89: =IF(S87>0,MAX(0,S87-R90)*Inputs!$E$260,0) -> 5055839.3
C90: Tax loss carry-forward (end) | H90: =MAX(0,-H87) -> 0 | I90: =MAX(0,H90+MAX(0,-I87)-MIN(H90,MAX(0,I87))) -> 0 | J90: =MAX(0,I90+MAX(0,-J87)-MIN(I90,MAX(0,J87))) -> 0 | K90: =MAX(0,J90+MAX(0,-K87)-MIN(J90,MAX(0,K87))) -> 0 | L90: =MAX(0,K90+MAX(0,-L87)-MIN(K90,MAX(0,L87))) -> 0 | M90: =MAX(0,L90+MAX(0,-M87)-MIN(L90,MAX(0,M87))) -> 0 | N90: =MAX(0,M90+MAX(0,-N87)-MIN(M90,MAX(0,N87))) -> 0 | O90: =MAX(0,N90+MAX(0,-O87)-MIN(N90,MAX(0,O87))) -> 0 | P90: =MAX(0,O90+MAX(0,-P87)-MIN(O90,MAX(0,P87))) -> 0 | ... S90: =MAX(0,R90+MAX(0,-S87)-MIN(R90,MAX(0,S87))) -> 0
B93: NPAT | C93: Net profit after tax | H93: =H87-H89 -> 0 | I93: =I87-I89 -> 0 | J93: =J87-J89 -> 0 | K93: =K87-K89 -> 9311849.5 | L93: =L87-L89 -> 9650628.6 | M93: =M87-M89 -> 10353175 | N93: =N87-N89 -> 10724011 | O93: =O87-O89 -> 11241246 | ... S93: =S87-S89 -> 11796958
B95: COMMUNITY FUND CALCULATION
C96: Total Tickets Sold | K96: ='Calendar Assumptions'!G52 -> 556638.89 | L96: ='Calendar Assumptions'!H52 -> 568210.16 | M96: ='Calendar Assumptions'!I52 -> 609014.1 | N96: ='Calendar Assumptions'!J52 -> 609014.1 | O96: ='Calendar Assumptions'!K52 -> 609014.1 | P96: ='Calendar Assumptions'!L52 -> 609014.1 | Q96: ='Calendar Assumptions'!M52 -> 609014.1 | R96: ='Calendar Assumptions'!N52 -> 609014.1 | S96: ='Calendar Assumptions'!O52 -> 609014.1
C97: Community Fund Contribution per Ticket | H97: =Inputs!$E$482 -> 0.25 | I97: =Inputs!$E$482 -> 0.25 | J97: =Inputs!$E$482 -> 0.25 | K97: =Inputs!$E$482 -> 0.25 | L97: =Inputs!$E$482 -> 0.25 | M97: =Inputs!$E$482 -> 0.25 | N97: =Inputs!$E$482 -> 0.25 | O97: =Inputs!$E$482 -> 0.25 | ... S97: =Inputs!$E$482 -> 0.25
C98: Community Fund Allocation | H98: =H96*H97 -> 0 | I98: =I96*I97 -> 0 | J98: =J96*J97 -> 0 | K98: =K96*K97 -> 139159.72 | L98: =L96*L97 -> 142052.54 | M98: =M96*M97 -> 152253.52 | N98: =N96*N97 -> 152253.52 | O98: =O96*O97 -> 152253.52 | ... S98: =S96*S97 -> 152253.52
B100: Transfer to Community Fund | H100: =H98 -> 0 | I100: =I98 -> 0 | J100: =J98 -> 0 | K100: =K98 -> 139159.72 | L100: =L98 -> 142052.54 | M100: =M98 -> 152253.52 | N100: =N98 -> 152253.52 | O100: =O98 -> 152253.52 | ... S100: =S98 -> 152253.52
B102: Dividends | H102: =IF(H93>0,(Inputs!$E$264*'P&L'!H93),0) -> 0 | I102: =IF(I93>0,(Inputs!$E$264*'P&L'!I93),0) -> 0 | J102: =IF(J93>0,(Inputs!$E$264*'P&L'!J93),0) -> 0 | K102: =IF(K93>0,(Inputs!$E$264*'P&L'!K93),0) -> 7449479.6 | L102: =IF(L93>0,(Inputs!$E$264*'P&L'!L93),0) -> 7720502.9 | M102: =IF(M93>0,(Inputs!$E$264*'P&L'!M93),0) -> 8282539.9 | N102: =IF(N93>0,(Inputs!$E$264*'P&L'!N93),0) -> 8579208.9 | O102: =IF(O93>0,(Inputs!$E$264*'P&L'!O93),0) -> 8992996.6 | ... S102: =IF(S93>0,(Inputs!$E$264*'P&L'!S93),0) -> 9437566.7
B106: DSCR | H106: =IF((H109+H110)=0,"",(H107-H108)/ABS(H109+H110)) | I106: =IF((I109+I110)=0,"",(I107-I108)/ABS(I109+I110)) | J106: =IF((J109+J110)=0,"",(J107-J108)/ABS(J109+J110)) -> 0 | K106: =IF((K109+K110)=0,"",(K107-K108)/ABS(K109+K110)) -> 8.3450465 | L106: =IF((L109+L110)=0,"",(L107-L108)/ABS(L109+L110)) -> 9.0195084 | M106: =IF((M109+M110)=0,"",(M107-M108)/ABS(M109+M110)) -> 10.100328 | N106: =IF((N109+N110)=0,"",(N107-N108)/ABS(N109+N110)) -> 10.972249 | O106: =IF((O109+O110)=0,"",(O107-O108)/ABS(O109+O110)) -> 11.831354 | ... S106: =IF((S109+S110)=0,"",(S107-S108)/ABS(S109+S110)) -> 16.294063
C107: EBITDA | H107: =H77 -> 0 | I107: =I77 -> 0 | J107: =J77 -> 0 | K107: =K77 -> 13999302 | L107: =L77 -> 14401312 | M107: =M77 -> 15322990 | N107: =N77 -> 15770796 | O107: =O77 -> 16058922 | ... S107: =S77 -> 16893778
C108: Growth Capex | H108: =IF(H8=1,-H28*Inputs!$E$246*Scenarios!$B$10,0) -> 0 | I108: =IF(I8=1,-I28*Inputs!$E$246*Scenarios!$B$10,0) -> 0 | J108: =IF(J8=1,-J28*Inputs!$E$246*Scenarios!$B$10,0) -> 0 | K108: =IF(K8=1,-K28*Inputs!$E$246*Scenarios!$B$10,0) -> -363858.19 | L108: =IF(L8=1,-L28*Inputs!$E$246*Scenarios!$B$10,0) -> -383465.9 | M108: =IF(M8=1,-M28*Inputs!$E$246*Scenarios!$B$10,0) -> -405645.41 | N108: =IF(N8=1,-N28*Inputs!$E$246*Scenarios!$B$10,0) -> -416343.17 | O108: =IF(O8=1,-O28*Inputs!$E$246*Scenarios!$B$10,0) -> -425939.57 | ... S108: =IF(S8=1,-S28*Inputs!$E$246*Scenarios!$B$10,0) -> -467221.06
C109: Principal | H109: =INDEX(Debt!$H$56:$S$56,MATCH(H$6,Debt!$H$14:$S$14,0)) -> 0 | I109: =INDEX(Debt!$H$56:$S$56,MATCH(I$6,Debt!$H$14:$S$14,0)) -> 0 | J109: =INDEX(Debt!$H$56:$S$56,MATCH(J$6,Debt!$H$14:$S$14,0)) -> 1024500 | K109: =INDEX(Debt!$H$56:$S$56,MATCH(K$6,Debt!$H$14:$S$14,0)) -> 1024500 | L109: =INDEX(Debt!$H$56:$S$56,MATCH(L$6,Debt!$H$14:$S$14,0)) -> 1024500 | M109: =INDEX(Debt!$H$56:$S$56,MATCH(M$6,Debt!$H$14:$S$14,0)) -> 1024500 | N109: =INDEX(Debt!$H$56:$S$56,MATCH(N$6,Debt!$H$14:$S$14,0)) -> 1024500 | O109: =INDEX(Debt!$H$56:$S$56,MATCH(O$6,Debt!$H$14:$S$14,0)) -> 1024500 | ... S109: =INDEX(Debt!$H$56:$S$56,MATCH(S$6,Debt!$H$14:$S$14,0)) -> 1024500
C110: Interest | H110: =INDEX(Debt!$H$57:$S$57,MATCH(H$6,Debt!$H$14:$S$14,0)) -> 0 | I110: =INDEX(Debt!$H$57:$S$57,MATCH(I$6,Debt!$H$14:$S$14,0)) -> 0 | J110: =INDEX(Debt!$H$57:$S$57,MATCH(J$6,Debt!$H$14:$S$14,0)) -> 368820 | K110: =INDEX(Debt!$H$57:$S$57,MATCH(K$6,Debt!$H$14:$S$14,0)) -> 696660 | L110: =INDEX(Debt!$H$57:$S$57,MATCH(L$6,Debt!$H$14:$S$14,0)) -> 614700 | M110: =INDEX(Debt!$H$57:$S$57,MATCH(M$6,Debt!$H$14:$S$14,0)) -> 532740 | N110: =INDEX(Debt!$H$57:$S$57,MATCH(N$6,Debt!$H$14:$S$14,0)) -> 450780 | O110: =INDEX(Debt!$H$57:$S$57,MATCH(O$6,Debt!$H$14:$S$14,0)) -> 368820 | ... S110: =INDEX(Debt!$H$57:$S$57,MATCH(S$6,Debt!$H$14:$S$14,0)) -> 40980

Sheet Balance Sheet
A1: Balance Sheet
A2: Port Melbourne Live House
B4: FY Start | F4: ='P&L'!H4 -> 45715 | G4: ='P&L'!I4 -> 45839 | H4: ='P&L'!J4 -> 46204 | I4: ='P&L'!K4 -> 46569 | J4: ='P&L'!L4 -> 46935 | K4: ='P&L'!M4 -> 47300 | L4: ='P&L'!N4 -> 47665 | M4: ='P&L'!O4 -> 48030 | ... Q4: ='P&L'!S4 -> 49491
B5: FY End | F5: ='P&L'!H5 -> 45838 | G5: ='P&L'!I5 -> 46203 | H5: ='P&L'!J5 -> 46568 | I5: ='P&L'!K5 -> 46934 | J5: ='P&L'!L5 -> 47299 | K5: ='P&L'!M5 -> 47664 | L5: ='P&L'!N5 -> 48029 | M5: ='P&L'!O5 -> 48395 | ... Q5: ='P&L'!S5 -> 49856
B6: Year | F6: ='P&L'!H6 -> FY25 | G6: ='P&L'!I6 -> FY26 | H6: ='P&L'!J6 -> FY27 | I6: ='P&L'!K6 -> FY28 | J6: ='P&L'!L6 -> FY29 | K6: ='P&L'!M6 -> FY30 | L6: ='P&L'!N6 -> FY31 | M6: ='P&L'!O6 -> FY32 | ... Q6: ='P&L'!S6 -> FY36
B8: ASSETS
C9: Current Assets
D10: Cash | F10: =Cashflow!D37 -> 0 | G10: =Cashflow!E37 -> 1707500 | H10: =Cashflow!F37 -> 16050500 | I10: =Cashflow!G37 -> -1231018.3 | J10: =Cashflow!H37 -> -396007.99 | K10: =Cashflow!I37 -> 513409.17 | L10: =Cashflow!J37 -> 1533142.7 | M10: =Cashflow!K37 -> 2307422.4 | ... Q10: =Cashflow!O37 -> 1.4219797e+08
D11: Community Fund Reserve (Restricted Cash) | F11: =0 -> 0 | G11: =F11 -> 0 | H11: =G11 -> 0 | I11: =H11+'P&L'!K100 -> 139159.72 | J11: =I11+'P&L'!L100 -> 281212.26 | K11: =J11+'P&L'!M100 -> 433465.79 | L11: =K11+'P&L'!N100 -> 585719.31 | M11: =L11+'P&L'!O100 -> 737972.84 | N11: =M11+'P&L'!P100 -> 890226.36 | O11: =N11+'P&L'!Q100 -> 1042479.9 | P11: =O11+'P&L'!R100 -> 1194733.4 | Q11: =P11+'P&L'!S100 -> 1346986.9
D12: Accounts receivable | F12: =INDEX(Cashflow!$D$52:$O$52,MATCH(F$6,Cashflow!$D$42:$O$42,0)) -> 0 | G12: =INDEX(Cashflow!$D$52:$O$52,MATCH(G$6,Cashflow!$D$42:$O$42,0)) -> 0 | H12: =INDEX(Cashflow!$D$52:$O$52,MATCH(H$6,Cashflow!$D$42:$O$42,0)) -> 0 | I12: =INDEX(Cashflow!$D$52:$O$52,MATCH(I$6,Cashflow!$D$42:$O$42,0)) -> 1495307.6 | J12: =INDEX(Cashflow!$D$52:$O$52,MATCH(J$6,Cashflow!$D$42:$O$42,0)) -> 1575887.3 | K12: =INDEX(Cashflow!$D$52:$O$52,MATCH(K$6,Cashflow!$D$42:$O$42,0)) -> 1667035.9 | L12: =INDEX(Cashflow!$D$52:$O$52,MATCH(L$6,Cashflow!$D$42:$O$42,0)) -> 1710999.3 | M12: =INDEX(Cashflow!$D$52:$O$52,MATCH(M$6,Cashflow!$D$42:$O$42,0)) -> 1750436.6 | ... Q12: =INDEX(Cashflow!$D$52:$O$52,MATCH(Q$6,Cashflow!$D$42:$O$42,0)) -> 1920086.6
D13: Inventory | F13: =INDEX(Cashflow!$D$53:$O$53,MATCH(F$6,Cashflow!$D$42:$O$42,0)) -> 0 | G13: =INDEX(Cashflow!$D$53:$O$53,MATCH(G$6,Cashflow!$D$42:$O$42,0)) -> 0 | H13: =INDEX(Cashflow!$D$53:$O$53,MATCH(H$6,Cashflow!$D$42:$O$42,0)) -> 0 | I13: =INDEX(Cashflow!$D$53:$O$53,MATCH(I$6,Cashflow!$D$42:$O$42,0)) -> 3131.1049 | J13: =INDEX(Cashflow!$D$53:$O$53,MATCH(J$6,Cashflow!$D$42:$O$42,0)) -> 3324.8169 | K13: =INDEX(Cashflow!$D$53:$O$53,MATCH(K$6,Cashflow!$D$42:$O$42,0)) -> 3440.0589 | L13: =INDEX(Cashflow!$D$53:$O$53,MATCH(L$6,Cashflow!$D$42:$O$42,0)) -> 3491.6598 | M13: =INDEX(Cashflow!$D$53:$O$53,MATCH(M$6,Cashflow!$D$42:$O$42,0)) -> 3596.4096 | ... Q13: =INDEX(Cashflow!$D$53:$O$53,MATCH(Q$6,Cashflow!$D$42:$O$42,0)) -> 4047.7907
C15: Total current assets | F15: =SUM(F10:F13) -> 0 | G15: =SUM(G10:G13) -> 1707500 | H15: =SUM(H10:H13) -> 16050500 | I15: =SUM(I10:I13) -> 406580.19 | J15: =SUM(J10:J13) -> 1464416.3 | K15: =SUM(K10:K13) -> 2617350.9 | L15: =SUM(L10:L13) -> 3833353 | M15: =SUM(M10:M13) -> 4799428.2 | ... Q15: =SUM(Q10:Q13) -> 1.4546909e+08
C17: Non-Current Assets
D18: Lease deposit / bond | F18: ='Construction Timeline'!D170 -> 0 | G18: ='Construction Timeline'!E170 -> 780000 | H18: ='Construction Timeline'!F170 -> 780000 | I18: ='Construction Timeline'!G170 -> 780000 | J18: ='Construction Timeline'!H170 -> 780000 | K18: ='Construction Timeline'!I170 -> 780000 | L18: ='Construction Timeline'!J170 -> 780000 | M18: ='Construction Timeline'!K170 -> 780000 | ... Q18: ='Construction Timeline'!O170 -> 780000
D19: Work in Progress (WIP) | F19: ='Construction Timeline'!D166 -> 0 | G19: ='Construction Timeline'!E166 -> 0 | H19: ='Construction Timeline'!F166 -> 0 | I19: ='Construction Timeline'!G166 -> 17758000 | J19: ='Construction Timeline'!H166 -> 17758000 | K19: ='Construction Timeline'!I166 -> 17758000 | L19: ='Construction Timeline'!J166 -> 17758000 | M19: ='Construction Timeline'!K166 -> 17758000 | ... Q19: ='Construction Timeline'!O166 -> 17758000
D20: Property, Plant & Equipment (gross) | F20: ='Construction Timeline'!D177 -> 0 | G20: ='Construction Timeline'!E177 -> 0 | H20: ='Construction Timeline'!F177 -> 0 | I20: ='Construction Timeline'!G177 -> 0 | J20: ='Construction Timeline'!H177 -> 0 | K20: ='Construction Timeline'!I177 -> 0 | L20: ='Construction Timeline'!J177 -> 0 | M20: ='Construction Timeline'!K177 -> 0 | ... Q20: ='Construction Timeline'!O177 -> 0
D21: Accumulated depreciation | F21: =-'Construction Timeline'!D181 -> 0 | G21: =-'Construction Timeline'!E181 -> 0 | H21: =-'Construction Timeline'!F181 -> 0 | I21: =-'Construction Timeline'!G181 -> 0 | J21: =-'Construction Timeline'!H181 -> 0 | K21: =-'Construction Timeline'!I181 -> 0 | L21: =-'Construction Timeline'!J181 -> 0 | M21: =-'Construction Timeline'!K181 -> 0 | ... Q21: =-'Construction Timeline'!O181 -> 0
D22: PPE (net) | F22: ='Construction Timeline'!D183 -> 0 | G22: ='Construction Timeline'!E183 -> 0 | H22: ='Construction Timeline'!F183 -> 0 | I22: ='Construction Timeline'!G183 -> 0 | J22: ='Construction Timeline'!H183 -> 0 | K22: ='Construction Timeline'!I183 -> 0 | L22: ='Construction Timeline'!J183 -> 0 | M22: ='Construction Timeline'!K183 -> 0 | ... Q22: ='Construction Timeline'!O183 -> 0
C23: Total Non-Current Assets | F23: =F18+F19+F22 -> 0 | G23: =G18+G19+G22 -> 780000 | H23: =H18+H19+H22 -> 780000 | I23: =I18+I19+I22 -> 18538000 | J23: =J18+J19+J22 -> 18538000 | K23: =K18+K19+K22 -> 18538000 | L23: =L18+L19+L22 -> 18538000 | M23: =M18+M19+M22 -> 18538000 | ... Q23: =Q18+Q19+Q22 -> 18538000
C25: Total Assets | F25: =F15+F23 -> 0 | G25: =G15+G23 -> 2487500 | H25: =H15+H23 -> 16830500 | I25: =I15+I23 -> 18944580 | J25: =J15+J23 -> 20002416 | K25: =K15+K23 -> 21155351 | L25: =L15+L23 -> 22371353 | M25: =M15+M23 -> 23337428 | ... Q25: =Q15+Q23 -> 1.6400709e+08
C26: NWC (AR + Inv – AP – Deferred rev) | F26: =F12+F13-IFERROR(INDEX(Cashflow!$D$54:$O$54,MATCH(F$6,Cashflow!$D$42:$O$42,0)),0)-F32 -> 0 | G26: =G12+G13-IFERROR(INDEX(Cashflow!$D$54:$O$54,MATCH(G$6,Cashflow!$D$42:$O$42,0)),0)-G32 -> 0 | H26: =H12+H13-IFERROR(INDEX(Cashflow!$D$54:$O$54,MATCH(H$6,Cashflow!$D$42:$O$42,0)),0)-H32 -> 0 | I26: =I12+I13-IFERROR(INDEX(Cashflow!$D$54:$O$54,MATCH(I$6,Cashflow!$D$42:$O$42,0)),0)-I32 -> 981418.65 | J26: =J12+J13-IFERROR(INDEX(Cashflow!$D$54:$O$54,MATCH(J$6,Cashflow!$D$42:$O$42,0)),0)-J32 -> 990885.44 | K26: =K12+K13-IFERROR(INDEX(Cashflow!$D$54:$O$54,MATCH(K$6,Cashflow!$D$42:$O$42,0)),0)-K32 -> 1059057.8 | L26: =L12+L13-IFERROR(INDEX(Cashflow!$D$54:$O$54,MATCH(L$6,Cashflow!$D$42:$O$42,0)),0)-L32 -> 1092336.7 | M26: =M12+M13-IFERROR(INDEX(Cashflow!$D$54:$O$54,MATCH(M$6,Cashflow!$D$42:$O$42,0)),0)-M32 -> 1108245.3 | ... Q26: =Q12+Q13-IFERROR(INDEX(Cashflow!$D$54:$O$54,MATCH(Q$6,Cashflow!$D$42:$O$42,0)),0)-Q32 -> 1126799
B28: LIABILITIES
C29: Current Liabilities
D30: Accounts payable / accruals | F30: =IFERROR(F25-(F31+F36+F32)-F44,0) -> 0 | G30: =IFERROR(G25-(G31+G36+G32)-G44,0) -> 0 | H30: =IFERROR(H25-(H31+H36+H32)-H44,0) -> 0 | I30: =IFERROR(I25-(I31+I36+I32)-I44,0) -> 1415370 | J30: =IFERROR(J25-(J31+J36+J32)-J44,0) -> 1709633 | K30: =IFERROR(K25-(K31+K36+K32)-K44,0) -> 1968686.1 | L30: =IFERROR(L25-(L31+L36+L32)-L44,0) -> 2216639.5 | M30: =IFERROR(M25-(M31+M36+M32)-M44,0) -> 2111219.1 | ... Q30: =IFERROR(Q25-(Q31+Q36+Q32)-Q44,0) -> 1.3839911e+08
D31: Borrowings – current | F31: =INDEX(Debt!$H$49:$S$49, MATCH(F$6, Debt!$H$14:$S$14,0)) -> 0 | G31: =INDEX(Debt!$H$49:$S$49, MATCH(G$6, Debt!$H$14:$S$14,0)) -> 0 | H31: =INDEX(Debt!$H$49:$S$49, MATCH(H$6, Debt!$H$14:$S$14,0)) -> 1024500 | I31: =INDEX(Debt!$H$49:$S$49, MATCH(I$6, Debt!$H$14:$S$14,0)) -> 1024500 | J31: =INDEX(Debt!$H$49:$S$49, MATCH(J$6, Debt!$H$14:$S$14,0)) -> 1024500 | K31: =INDEX(Debt!$H$49:$S$49, MATCH(K$6, Debt!$H$14:$S$14,0)) -> 1024500 | L31: =INDEX(Debt!$H$49:$S$49, MATCH(L$6, Debt!$H$14:$S$14,0)) -> 1024500 | M31: =INDEX(Debt!$H$49:$S$49, MATCH(M$6, Debt!$H$14:$S$14,0)) -> 1024500 | ... Q31: =INDEX(Debt!$H$49:$S$49, MATCH(Q$6, Debt!$H$14:$S$14,0)) -> 0
D32: Customer deposits / deferred revenue | F32: =INDEX(Cashflow!$D$20:$O$20, MATCH(F$6,Cashflow!$D$7:$O$7,0))-IF(F$6=Inputs!$E$266,Inputs!$H$306*SUM(Cashflow!$D$20:$O$20),0) -> 0 | G32: =F32+INDEX(Cashflow!$D$20:$O$20, MATCH(G$6,Cashflow!$D$7:$O$7,0))-IF(G$6=Inputs!$E$266,Inputs!$H$306*SUM(Cashflow!$D$20:$O$20),0) -> 0 | H32: =G32+INDEX(Cashflow!$D$20:$O$20, MATCH(H$6,Cashflow!$D$7:$O$7,0))-IF(H$6=Inputs!$E$266,Inputs!$H$306*SUM(Cashflow!$D$20:$O$20),0) -> 0 | I32: =H32+INDEX(Cashflow!$D$20:$O$20, MATCH(I$6,Cashflow!$D$7:$O$7,0))-IF(I$6=Inputs!$E$266,Inputs!$H$306*SUM(Cashflow!$D$20:$O$20),0) -> 0 | J32: =I32+INDEX(Cashflow!$D$20:$O$20, MATCH(J$6,Cashflow!$D$7:$O$7,0))-IF(J$6=Inputs!$E$266,Inputs!$H$306*SUM(Cashflow!$D$20:$O$20),0) -> 0 | K32: =J32+INDEX(Cashflow!$D$20:$O$20, MATCH(K$6,Cashflow!$D$7:$O$7,0))-IF(K$6=Inputs!$E$266,Inputs!$H$306*SUM(Cashflow!$D$20:$O$20),0) -> 0 | L32: =K32+INDEX(Cashflow!$D$20:$O$20, MATCH(L$6,Cashflow!$D$7:$O$7,0))-IF(L$6=Inputs!$E$266,Inputs!$H$306*SUM(Cashflow!$D$20:$O$20),0) -> 0 | M32: =L32+INDEX(Cashflow!$D$20:$O$20, MATCH(M$6,Cashflow!$D$7:$O$7,0))-IF(M$6=Inputs!$E$266,Inputs!$H$306*SUM(Cashflow!$D$20:$O$20),0) -> 0 | N32: =M32+INDEX(Cashflow!$D$20:$O$20, MATCH(N$6,Cashflow!$D$7:$O$7,0))-IF(N$6=Inputs!$E$266,Inputs!$H$306*SUM(Cashflow!$D$20:$O$20),0) -> 0 | ... Q32: =P32+INDEX(Cashflow!$D$20:$O$20, MATCH(Q$6,Cashflow!$D$7:$O$7,0))-IF(Q$6=Inputs!$E$266,Inputs!$H$306*SUM(Cashflow!$D$20:$O$20),0) -> 0
C33: ="Total "&C29 -> Total Current Liabilities | F33: =F30+F31+F32 -> 0 | G33: =G30+G31+G32 -> 0 | H33: =H30+H31+H32 -> 1024500 | I33: =I30+I31+I32 -> 2439870 | J33: =J30+J31+J32 -> 2734133 | K33: =K30+K31+K32 -> 2993186.1 | L33: =L30+L31+L32 -> 3241139.5 | M33: =M30+M31+M32 -> 3135719.1 | ... Q33: =Q30+Q31+Q32 -> 1.3839911e+08
C35: Non-Current Liabilities
D36: Borrowings – non-current | F36: =INDEX(Debt!$H$50:$S$50, MATCH(F$6, Debt!$H$14:$S$14,0)) -> 0 | G36: =INDEX(Debt!$H$50:$S$50, MATCH(G$6, Debt!$H$14:$S$14,0)) -> 0 | H36: =INDEX(Debt!$H$50:$S$50, MATCH(H$6, Debt!$H$14:$S$14,0)) -> 8196000 | I36: =INDEX(Debt!$H$50:$S$50, MATCH(I$6, Debt!$H$14:$S$14,0)) -> 7171500 | J36: =INDEX(Debt!$H$50:$S$50, MATCH(J$6, Debt!$H$14:$S$14,0)) -> 6147000 | K36: =INDEX(Debt!$H$50:$S$50, MATCH(K$6, Debt!$H$14:$S$14,0)) -> 5122500 | L36: =INDEX(Debt!$H$50:$S$50, MATCH(L$6, Debt!$H$14:$S$14,0)) -> 4098000 | M36: =INDEX(Debt!$H$50:$S$50, MATCH(M$6, Debt!$H$14:$S$14,0)) -> 3073500 | ... Q36: =INDEX(Debt!$H$50:$S$50, MATCH(Q$6, Debt!$H$14:$S$14,0)) -> 0
C37: ="Total " &C35 -> Total Non-Current Liabilities | F37: =SUM(F36:F36) -> 0 | G37: =SUM(G36:G36) -> 0 | H37: =SUM(H36:H36) -> 8196000 | I37: =SUM(I36:I36) -> 7171500 | J37: =SUM(J36:J36) -> 6147000 | K37: =SUM(K36:K36) -> 5122500 | L37: =SUM(L36:L36) -> 4098000 | M37: =SUM(M36:M36) -> 3073500 | ... Q37: =SUM(Q36:Q36) -> 0
C38: Total Liabilities | F38: =F33+F37 -> 0 | G38: =G33+G37 -> 0 | H38: =H33+H37 -> 9220500 | I38: =I33+I37 -> 9611370 | J38: =J33+J37 -> 8881133 | K38: =K33+K37 -> 8115686.1 | L38: =L33+L37 -> 7339139.5 | M38: =M33+M37 -> 6209219.1 | ... Q38: =Q33+Q37 -> 1.3839911e+08
B40: EQUITY
C41: Contributed equity | F41: =INDEX(Cashflow!$D$95:$O$95,MATCH(F$6,Cashflow!$D$7:$O$7,0)) -> 0 | G41: =INDEX(Cashflow!$D$95:$O$95,MATCH(G$6,Cashflow!$D$7:$O$7,0)) -> 2487500 | H41: =INDEX(Cashflow!$D$95:$O$95,MATCH(H$6,Cashflow!$D$7:$O$7,0)) -> 7610000 | I41: =INDEX(Cashflow!$D$95:$O$95,MATCH(I$6,Cashflow!$D$7:$O$7,0)) -> 7610000 | J41: =INDEX(Cashflow!$D$95:$O$95,MATCH(J$6,Cashflow!$D$7:$O$7,0)) -> 7610000 | K41: =INDEX(Cashflow!$D$95:$O$95,MATCH(K$6,Cashflow!$D$7:$O$7,0)) -> 7610000 | L41: =INDEX(Cashflow!$D$95:$O$95,MATCH(L$6,Cashflow!$D$7:$O$7,0)) -> 7610000 | M41: =INDEX(Cashflow!$D$95:$O$95,MATCH(M$6,Cashflow!$D$7:$O$7,0)) -> 7610000 | ... Q41: =INDEX(Cashflow!$D$95:$O$95,MATCH(Q$6,Cashflow!$D$7:$O$7,0)) -> 7610000
C42: Retained earnings | F42: =INDEX('P&L'!$H$93:$S$93, MATCH(F$6,'P&L'!$H$6:$S$6,0))-INDEX('P&L'!$H$102:$S$102, MATCH(F$6,'P&L'!$H$6:$S$6,0))-INDEX('P&L'!$H$100:$S$100, MATCH(F$6,'P&L'!$H$6:$S$6,0)) -> 0 | G42: =F42+INDEX('P&L'!$H$93:$S$93, MATCH(G$6,'P&L'!$H$6:$S$6,0))-INDEX('P&L'!$H$102:$S$102, MATCH(G$6,'P&L'!$H$6:$S$6,0))-INDEX('P&L'!$H$100:$S$100, MATCH(G$6,'P&L'!$H$6:$S$6,0)) -> 0 | H42: =G42+INDEX('P&L'!$H$93:$S$93, MATCH(H$6,'P&L'!$H$6:$S$6,0))-INDEX('P&L'!$H$102:$S$102, MATCH(H$6,'P&L'!$H$6:$S$6,0))-INDEX('P&L'!$H$100:$S$100, MATCH(H$6,'P&L'!$H$6:$S$6,0)) -> 0 | I42: =H42+INDEX('P&L'!$H$93:$S$93, MATCH(I$6,'P&L'!$H$6:$S$6,0))-INDEX('P&L'!$H$102:$S$102, MATCH(I$6,'P&L'!$H$6:$S$6,0))-INDEX('P&L'!$H$100:$S$100, MATCH(I$6,'P&L'!$H$6:$S$6,0)) -> 1723210.2 | J42: =I42+INDEX('P&L'!$H$93:$S$93, MATCH(J$6,'P&L'!$H$6:$S$6,0))-INDEX('P&L'!$H$102:$S$102, MATCH(J$6,'P&L'!$H$6:$S$6,0))-INDEX('P&L'!$H$100:$S$100, MATCH(J$6,'P&L'!$H$6:$S$6,0)) -> 3511283.4 | K42: =J42+INDEX('P&L'!$H$93:$S$93, MATCH(K$6,'P&L'!$H$6:$S$6,0))-INDEX('P&L'!$H$102:$S$102, MATCH(K$6,'P&L'!$H$6:$S$6,0))-INDEX('P&L'!$H$100:$S$100, MATCH(K$6,'P&L'!$H$6:$S$6,0)) -> 5429664.8 | L42: =K42+INDEX('P&L'!$H$93:$S$93, MATCH(L$6,'P&L'!$H$6:$S$6,0))-INDEX('P&L'!$H$102:$S$102, MATCH(L$6,'P&L'!$H$6:$S$6,0))-INDEX('P&L'!$H$100:$S$100, MATCH(L$6,'P&L'!$H$6:$S$6,0)) -> 7422213.5 | M42: =L42+INDEX('P&L'!$H$93:$S$93, MATCH(M$6,'P&L'!$H$6:$S$6,0))-INDEX('P&L'!$H$102:$S$102, MATCH(M$6,'P&L'!$H$6:$S$6,0))-INDEX('P&L'!$H$100:$S$100, MATCH(M$6,'P&L'!$H$6:$S$6,0)) -> 9518209.1 | N42: =M42+INDEX('P&L'!$H$93:$S$93, MATCH(N$6,'P&L'!$H$6:$S$6,0))-INDEX('P&L'!$H$102:$S$102, MATCH(N$6,'P&L'!$H$6:$S$6,0))-INDEX('P&L'!$H$100:$S$100, MATCH(N$6,'P&L'!$H$6:$S$6,0)) -> 11555133 | ... Q42: =P42+INDEX('P&L'!$H$93:$S$93, MATCH(Q$6,'P&L'!$H$6:$S$6,0))-INDEX('P&L'!$H$102:$S$102, MATCH(Q$6,'P&L'!$H$6:$S$6,0))-INDEX('P&L'!$H$100:$S$100, MATCH(Q$6,'P&L'!$H$6:$S$6,0)) -> 17997985
B44: TOTAL Equity | F44: =SUM(F41:F42) -> 0 | G44: =SUM(G41:G42) -> 2487500 | H44: =SUM(H41:H42) -> 7610000 | I44: =SUM(I41:I42) -> 9333210.2 | J44: =SUM(J41:J42) -> 11121283 | K44: =SUM(K41:K42) -> 13039665 | L44: =SUM(L41:L42) -> 15032214 | M44: =SUM(M41:M42) -> 17128209 | ... Q44: =SUM(Q41:Q42) -> 25607985
B46: Balance Check (Assets – Liabilities – Equity) | F46: =F25-F38-F44 -> 0 | G46: =G25-G38-G44 -> 0 | H46: =H25-H38-H44 -> 0 | I46: =I25-I38-I44 -> 0 | J46: =J25-J38-J44 -> 0 | K46: =K25-K38-K44 -> 0 | L46: =L25-L38-L44 -> 0 | M46: =M25-M38-M44 -> 0 | ... Q46: =Q25-Q38-Q44 -> 0
B47: Check Flag | F47: =IF(ABS(F46)<1,"OK","CHECK") -> OK | G47: =IF(ABS(G46)<1,"OK","CHECK") -> OK | H47: =IF(ABS(H46)<1,"OK","CHECK") -> OK | I47: =IF(ABS(I46)<1,"OK","CHECK") -> OK | J47: =IF(ABS(J46)<1,"OK","CHECK") -> OK | K47: =IF(ABS(K46)<1,"OK","CHECK") -> OK | L47: =IF(ABS(L46)<1,"OK","CHECK") -> OK | M47: =IF(ABS(M46)<1,"OK","CHECK") -> OK | ... Q47: =IF(ABS(Q46)<1,"OK","CHECK") -> OK
B49: THREE-STATEMENT INTEGRATION CHECKS
B51: Check | E51: FY25 | F51: FY26 | G51: FY27 | H51: FY28 | I51: FY29 | J51: FY30 | K51: FY31 | L51: FY32 | M51: FY33 | N51: FY34 | O51: FY35 | P51: FY36
B52: 1. Balance Test (A - L - E) | F52: =F46 -> 0 | G52: =G46 -> 0 | H52: =H46 -> 0 | I52: =I46 -> 0 | J52: =J46 -> 0 | K52: =K46 -> 0 | L52: =L46 -> 0 | M52: =M46 -> 0 | ... Q52: =Q46 -> 0
B53: 2. Cash Tie (BS vs CFS) | F53: =F10-Cashflow!D37 -> 0 | G53: =G10-Cashflow!E37 -> 0 | H53: =H10-Cashflow!F37 -> 0 | I53: =I10-Cashflow!G37 -> 0 | J53: =J10-Cashflow!H37 -> 0 | K53: =K10-Cashflow!I37 -> 0 | L53: =L10-Cashflow!J37 -> 0 | M53: =M10-Cashflow!K37 -> 0 | ... Q53: =Q10-Cashflow!O37 -> 0
B54: 3. PPE Tie (BS vs Capex Schedule) | F54: =F22-'Construction Timeline'!D183 -> 0 | G54: =G22-'Construction Timeline'!E183 -> 0 | H54: =H22-'Construction Timeline'!F183 -> 0 | I54: =I22-'Construction Timeline'!G183 -> 0 | J54: =J22-'Construction Timeline'!H183 -> 0 | K54: =K22-'Construction Timeline'!I183 -> 0 | L54: =L22-'Construction Timeline'!J183 -> 0 | M54: =M22-'Construction Timeline'!K183 -> 0 | ... Q54: =Q22-'Construction Timeline'!O183 -> 0
B56: Overall Model Status | F56: MODEL BALANCED

Sheet Cashflow
A1: Annual Cashflow Waterfall (AUD)
A2: Port Melbourne Live House | Z2: =D13 -> 0
C4: Currency | D4: AUD
C5: FY Start | D5: ='P&L'!H4 -> 45715 | E5: ='P&L'!I4 -> 45839 | F5: ='P&L'!J4 -> 46204 | G5: ='P&L'!K4 -> 46569 | H5: ='P&L'!L4 -> 46935 | I5: ='P&L'!M4 -> 47300 | J5: ='P&L'!N4 -> 47665 | K5: ='P&L'!O4 -> 48030 | ... O5: ='P&L'!S4 -> 49491
C6: FY End | D6: ='P&L'!H5 -> 45838 | E6: ='P&L'!I5 -> 46203 | F6: ='P&L'!J5 -> 46568 | G6: ='P&L'!K5 -> 46934 | H6: ='P&L'!L5 -> 47299 | I6: ='P&L'!M5 -> 47664 | J6: ='P&L'!N5 -> 48029 | K6: ='P&L'!O5 -> 48395 | ... O6: ='P&L'!S5 -> 49856
C7: Year | D7: ='P&L'!H6 -> FY25 | E7: ='P&L'!I6 -> FY26 | F7: ='P&L'!J6 -> FY27 | G7: ='P&L'!K6 -> FY28 | H7: ='P&L'!L6 -> FY29 | I7: ='P&L'!M6 -> FY30 | J7: ='P&L'!N6 -> FY31 | K7: ='P&L'!O6 -> FY32 | ... O7: ='P&L'!S6 -> FY36
A10: Opening Cash Balance | D10: 0 | E10: =Cashflow!D37 -> 0 | F10: =E37 -> 1707500 | G10: =F37 -> 16050500 | H10: =G37 -> -1231018.3 | I10: =H37 -> -396007.99 | J10: =I37 -> 513409.17 | K10: =J37 -> 1533142.7 | L10: =K37 -> 2307422.4 | M10: =L37 -> 3446826.6 | ... O10: =N37 -> 5787287.4
A12: INFLOWS
A13: Founder / Seed Equity Inflow | D13: =IF(D7=Inputs!$E$81,Inputs!$E$69,0) -> 0 | E13: =IF(E7=Inputs!$E$81,Inputs!$E$69,0) -> 2487500 | F13: =IF(F7=Inputs!$E$81,Inputs!$E$69,0) -> 0 | G13: =IF(G7=Inputs!$E$81,Inputs!$E$69,0) -> 0 | H13: =IF(H7=Inputs!$E$81,Inputs!$E$69,0) -> 0 | I13: =IF(I7=Inputs!$E$81,Inputs!$E$69,0) -> 0 | J13: =IF(J7=Inputs!$E$81,Inputs!$E$69,0) -> 0 | K13: =IF(K7=Inputs!$E$81,Inputs!$E$69,0) -> 0 | ... O13: =IF(O7=Inputs!$E$81,Inputs!$E$69,0) -> 0
A14: PE Equity Inflow | D14: =IF(AND(D7=Inputs!$E$86,Inputs!$E$88=0),Inputs!$E$73,0) -> 0 | E14: =IF(AND(E7=Inputs!$E$86,Inputs!$E$88=0),Inputs!$E$73,0) -> 0 | F14: =IF(AND(F7=Inputs!$E$86,Inputs!$E$88=0),Inputs!$E$73,0) -> 5122500 | G14: =IF(AND(G7=Inputs!$E$86,Inputs!$E$88=0),Inputs!$E$73,0) -> 0 | H14: =IF(AND(H7=Inputs!$E$86,Inputs!$E$88=0),Inputs!$E$73,0) -> 0 | I14: =IF(AND(I7=Inputs!$E$86,Inputs!$E$88=0),Inputs!$E$73,0) -> 0 | J14: =IF(AND(J7=Inputs!$E$86,Inputs!$E$88=0),Inputs!$E$73,0) -> 0 | K14: =IF(AND(K7=Inputs!$E$86,Inputs!$E$88=0),Inputs!$E$73,0) -> 0 | ... O14: =IF(AND(O7=Inputs!$E$86,Inputs!$E$88=0),Inputs!$E$73,0) -> 0
A15: Additional Equity Tranches | D15: =IF(D7=Inputs!$E$83,Inputs!$E$82,0)+IF(D7=Inputs!$E$85,Inputs!$E$84,0)+IF(D7=Inputs!$E$90,Inputs!$E$89,0) -> 0 | E15: =IF(E7=Inputs!$E$83,Inputs!$E$82,0)+IF(E7=Inputs!$E$85,Inputs!$E$84,0)+IF(E7=Inputs!$E$90,Inputs!$E$89,0) -> 0 | F15: =IF(F7=Inputs!$E$83,Inputs!$E$82,0)+IF(F7=Inputs!$E$85,Inputs!$E$84,0)+IF(F7=Inputs!$E$90,Inputs!$E$89,0) -> 0 | G15: =IF(G7=Inputs!$E$83,Inputs!$E$82,0)+IF(G7=Inputs!$E$85,Inputs!$E$84,0)+IF(G7=Inputs!$E$90,Inputs!$E$89,0) -> 0 | H15: =IF(H7=Inputs!$E$83,Inputs!$E$82,0)+IF(H7=Inputs!$E$85,Inputs!$E$84,0)+IF(H7=Inputs!$E$90,Inputs!$E$89,0) -> 0 | I15: =IF(I7=Inputs!$E$83,Inputs!$E$82,0)+IF(I7=Inputs!$E$85,Inputs!$E$84,0)+IF(I7=Inputs!$E$90,Inputs!$E$89,0) -> 0 | J15: =IF(J7=Inputs!$E$83,Inputs!$E$82,0)+IF(J7=Inputs!$E$85,Inputs!$E$84,0)+IF(J7=Inputs!$E$90,Inputs!$E$89,0) -> 0 | K15: =IF(K7=Inputs!$E$83,Inputs!$E$82,0)+IF(K7=Inputs!$E$85,Inputs!$E$84,0)+IF(K7=Inputs!$E$90,Inputs!$E$89,0) -> 0 | ... O15: =IF(O7=Inputs!$E$83,Inputs!$E$82,0)+IF(O7=Inputs!$E$85,Inputs!$E$84,0)+IF(O7=Inputs!$E$90,Inputs!$E$89,0) -> 0
A16: Total Equity Inflow | D16: =D13+D14+D15 -> 0 | E16: =E13+E14+E15 -> 2487500 | F16: =F13+F14+F15 -> 5122500 | G16: =G13+G14+G15 -> 0 | H16: =H13+H14+H15 -> 0 | I16: =I13+I14+I15 -> 0 | J16: =J13+J14+J15 -> 0 | K16: =K13+K14+K15 -> 0 | ... O16: =O13+O14+O15 -> 0
A18: Debt drawdowns – Bank (from Debt) | D18: =IFERROR(Debt!H20,0) -> 0 | E18: =IFERROR(Debt!I20,0) -> 0 | F18: =IFERROR(Debt!J20,0) -> 10245000 | G18: =IFERROR(Debt!K20,0) -> 0 | H18: =IFERROR(Debt!L20,0) -> 0 | I18: =IFERROR(Debt!M20,0) -> 0 | J18: =IFERROR(Debt!N20,0) -> 0 | K18: =IFERROR(Debt!O20,0) -> 0 | ... O18: =IFERROR(Debt!S20,0) -> 0
A19: PE Loan drawdowns – LEGACY INACTIVE | D19: =0 -> 0 | E19: =0 -> 0 | F19: =0 -> 0 | G19: =0 -> 0 | H19: =0 -> 0 | I19: =0 -> 0 | J19: =0 -> 0 | K19: =0 -> 0 | ... O19: =0 -> 0
A20: Pre-op revenue (from Cashflow) | D20: =SUMIF(Timing!$C$6:$Q$6,D7,Timing!$C$22:$Q$22) -> 0 | E20: =SUMIF(Timing!$C$6:$Q$6,E7,Timing!$C$22:$Q$22) -> 0 | F20: =SUMIF(Timing!$C$6:$Q$6,F7,Timing!$C$22:$Q$22) -> 0 | G20: =SUMIF(Timing!$C$6:$Q$6,G7,Timing!$C$22:$Q$22) -> 0 | H20: =SUMIF(Timing!$C$6:$Q$6,H7,Timing!$C$22:$Q$22) -> 0 | I20: =SUMIF(Timing!$C$6:$Q$6,I7,Timing!$C$22:$Q$22) -> 0 | J20: =SUMIF(Timing!$C$6:$Q$6,J7,Timing!$C$22:$Q$22) -> 0 | K20: =SUMIF(Timing!$C$6:$Q$6,K7,Timing!$C$22:$Q$22) -> 0 | ... O20: =SUMIF(Timing!$C$6:$Q$6,O7,Timing!$C$22:$Q$22) -> 0
A21: Operational revenue (from P&L) | D21: =IFERROR('P&L'!H28,0) -> 0 | E21: =IFERROR('P&L'!I28,0) -> 0 | F21: =IFERROR('P&L'!J28,0) -> 0 | G21: =IFERROR('P&L'!K28,0) -> 18192909 | H21: =IFERROR('P&L'!L28,0) -> 19173295 | I21: =IFERROR('P&L'!M28,0) -> 20282270 | J21: =IFERROR('P&L'!N28,0) -> 20817159 | K21: =IFERROR('P&L'!O28,0) -> 21296978 | ... O21: =IFERROR('P&L'!S28,0) -> 23361053
A22: Total inflows | D22: =D16+D18+D19+D20+D21 -> 0 | E22: =E16+E18+E19+E20+E21 -> 2487500 | F22: =F16+F18+F19+F20+F21 -> 15367500 | G22: =G16+G18+G19+G20+G21 -> 18192909 | H22: =H16+H18+H19+H20+H21 -> 19173295 | I22: =I16+I18+I19+I20+I21 -> 20282270 | J22: =J16+J18+J19+J20+J21 -> 20817159 | K22: =K16+K18+K19+K20+K21 -> 21296978 | ... O22: =O16+O18+O19+O20+O21 -> 23361053
A23: Terminal value + bond return | D23: =IF(D$7=Inputs!$E$266,D63*Valuations!$C$15,0) -> 0 | E23: =IF(E$7=Inputs!$E$266,E63*Valuations!$C$15,0) -> 0 | F23: =IF(F$7=Inputs!$E$266,F63*Valuations!$C$15,0) -> 0 | G23: =IF(G$7=Inputs!$E$266,G63*Valuations!$C$15,0) -> 0 | H23: =IF(H$7=Inputs!$E$266,H63*Valuations!$C$15,0) -> 0 | I23: =IF(I$7=Inputs!$E$266,I63*Valuations!$C$15,0) -> 0 | J23: =IF(J$7=Inputs!$E$266,J63*Valuations!$C$15,0) -> 0 | K23: =IF(K$7=Inputs!$E$266,K63*Valuations!$C$15,0) -> 0 | ... N23: =IF(N$7=Inputs!$E$266,N63*Valuations!$C$15,0) -> 0 | O23: =O63*Valuations!$C$15 -> 1.3515022e+08
A25: OUTFLOWS (shown as negatives)
A26: Capex (annualised from Construction Timeline) | D26: =-'Construction Timeline'!D172 -> 0 | E26: =-'Construction Timeline'!E172 -> -780000 | F26: =-'Construction Timeline'!F172 -> 0 | G26: =-'Construction Timeline'!G172 -> -17075000 | H26: =-'Construction Timeline'!H172 -> 0 | I26: =-'Construction Timeline'!I172 -> 0 | J26: =-'Construction Timeline'!J172 -> 0 | K26: =-'Construction Timeline'!K172 -> 0 | ... O26: =-'Construction Timeline'!O172 -> 0
A27: Pre-op expenses excl. capex (from Cashflow) | D27: =-SUMIF(Timing!$C$6:$Q$6,D7,Timing!$C$23:$Q$23) -> 0 | E27: =-SUMIF(Timing!$C$6:$Q$6,E7,Timing!$C$23:$Q$23) -> 0 | F27: =-SUMIF(Timing!$C$6:$Q$6,F7,Timing!$C$23:$Q$23) -> 0 | G27: =-SUMIF(Timing!$C$6:$Q$6,G7,Timing!$C$23:$Q$23) -> 0 | H27: =-SUMIF(Timing!$C$6:$Q$6,H7,Timing!$C$23:$Q$23) -> 0 | I27: =-SUMIF(Timing!$C$6:$Q$6,I7,Timing!$C$23:$Q$23) -> 0 | J27: =-SUMIF(Timing!$C$6:$Q$6,J7,Timing!$C$23:$Q$23) -> 0 | K27: =-SUMIF(Timing!$C$6:$Q$6,K7,Timing!$C$23:$Q$23) -> 0 | ... O27: =-SUMIF(Timing!$C$6:$Q$6,O7,Timing!$C$23:$Q$23) -> 0
A28: Operating expenses (excl lease/outgoings) – from P&L | D28: =IFERROR(-('P&L'!H75-'P&L'!H60-'P&L'!H61),0) -> 0 | E28: =IFERROR(-('P&L'!I75-'P&L'!I60-'P&L'!I61),0) -> 0 | F28: =IFERROR(-('P&L'!J75-'P&L'!J60-'P&L'!J61),0) -> 0 | G28: =IFERROR(-('P&L'!K75-'P&L'!K60-'P&L'!K61),0) -> -4117417 | H28: =IFERROR(-('P&L'!L75-'P&L'!L60-'P&L'!L61),0) -> -4279953.9 | I28: =IFERROR(-('P&L'!M75-'P&L'!M60-'P&L'!M61),0) -> -4412682.9 | J28: =IFERROR(-('P&L'!N75-'P&L'!N60-'P&L'!N61),0) -> -4482308.4 | K28: =IFERROR(-('P&L'!O75-'P&L'!O60-'P&L'!O61),0) -> -4654684.6 | ... O28: =IFERROR(-('P&L'!S75-'P&L'!S60-'P&L'!S61),0) -> -5230760.7
A29: Lease payments (venue lease + outgoings) – from P&L | D29: =IFERROR(-('P&L'!H60+'P&L'!H61),0) -> 0 | E29: =IFERROR(-('P&L'!I60+'P&L'!I61),0) -> 0 | F29: =IFERROR(-('P&L'!J60+'P&L'!J61),0) -> 0 | G29: =IFERROR(-('P&L'!K60+'P&L'!K61),0) -> 0 | H29: =IFERROR(-('P&L'!L60+'P&L'!L61),0) -> -411125 | I29: =IFERROR(-('P&L'!M60+'P&L'!M61),0) -> -462889.38 | J29: =IFERROR(-('P&L'!N60+'P&L'!N61),0) -> -479090.5 | K29: =IFERROR(-('P&L'!O60+'P&L'!O61),0) -> -495858.67 | ... O29: =IFERROR(-('P&L'!S60+'P&L'!S61),0) -> -1138018.5
A30: Debt service (principal + interest) – cash (from Debt) | D30: =IFERROR(-INDEX(Debt!$H$58:$S$58,MATCH(D$7,Debt!$H$14:$S$14,0))+IF(D$5<Inputs!$E$22,INDEX(Debt!$H$57:$S$57,MATCH(D$7,Debt!$H$14:$S$14,0)),0),0) -> 0 | E30: =IFERROR(-INDEX(Debt!$H$58:$S$58,MATCH(E$7,Debt!$H$14:$S$14,0))+IF(E$5<Inputs!$E$22,INDEX(Debt!$H$57:$S$57,MATCH(E$7,Debt!$H$14:$S$14,0)),0),0) -> 0 | F30: =IFERROR(-INDEX(Debt!$H$58:$S$58,MATCH(F$7,Debt!$H$14:$S$14,0))+IF(F$5<Inputs!$E$22,INDEX(Debt!$H$57:$S$57,MATCH(F$7,Debt!$H$14:$S$14,0)),0),0) -> -1024500 | G30: =IFERROR(-INDEX(Debt!$H$58:$S$58,MATCH(G$7,Debt!$H$14:$S$14,0))+IF(G$5<Inputs!$E$22,INDEX(Debt!$H$57:$S$57,MATCH(G$7,Debt!$H$14:$S$14,0)),0),0) -> -1721160 | H30: =IFERROR(-INDEX(Debt!$H$58:$S$58,MATCH(H$7,Debt!$H$14:$S$14,0))+IF(H$5<Inputs!$E$22,INDEX(Debt!$H$57:$S$57,MATCH(H$7,Debt!$H$14:$S$14,0)),0),0) -> -1639200 | I30: =IFERROR(-INDEX(Debt!$H$58:$S$58,MATCH(I$7,Debt!$H$14:$S$14,0))+IF(I$5<Inputs!$E$22,INDEX(Debt!$H$57:$S$57,MATCH(I$7,Debt!$H$14:$S$14,0)),0),0) -> -1557240 | J30: =IFERROR(-INDEX(Debt!$H$58:$S$58,MATCH(J$7,Debt!$H$14:$S$14,0))+IF(J$5<Inputs!$E$22,INDEX(Debt!$H$57:$S$57,MATCH(J$7,Debt!$H$14:$S$14,0)),0),0) -> -1475280 | K30: =IFERROR(-INDEX(Debt!$H$58:$S$58,MATCH(K$7,Debt!$H$14:$S$14,0))+IF(K$5<Inputs!$E$22,INDEX(Debt!$H$57:$S$57,MATCH(K$7,Debt!$H$14:$S$14,0)),0),0) -> -1393320 | ... O30: =IFERROR(-INDEX(Debt!$H$58:$S$58,MATCH(O$7,Debt!$H$14:$S$14,0))+IF(O$5<Inputs!$E$22,INDEX(Debt!$H$57:$S$57,MATCH(O$7,Debt!$H$14:$S$14,0)),0),0) -> -1065480
A31: Taxes (from P&L if modelled) | D31: =-INDEX('P&L'!$H$89:$S$89,MATCH(D$7,'P&L'!$H$6:$S$6,0)) -> 0 | E31: =-INDEX('P&L'!$H$89:$S$89,MATCH(E$7,'P&L'!$H$6:$S$6,0)) -> 0 | F31: =-INDEX('P&L'!$H$89:$S$89,MATCH(F$7,'P&L'!$H$6:$S$6,0)) -> 0 | G31: =-INDEX('P&L'!$H$89:$S$89,MATCH(G$7,'P&L'!$H$6:$S$6,0)) -> -3990792.6 | H31: =-INDEX('P&L'!$H$89:$S$89,MATCH(H$7,'P&L'!$H$6:$S$6,0)) -> -4135983.7 | I31: =-INDEX('P&L'!$H$89:$S$89,MATCH(I$7,'P&L'!$H$6:$S$6,0)) -> -4437075 | J31: =-INDEX('P&L'!$H$89:$S$89,MATCH(J$7,'P&L'!$H$6:$S$6,0)) -> -4596004.8 | K31: =-INDEX('P&L'!$H$89:$S$89,MATCH(K$7,'P&L'!$H$6:$S$6,0)) -> -4817676.7 | ... O31: =-INDEX('P&L'!$H$89:$S$89,MATCH(O$7,'P&L'!$H$6:$S$6,0)) -> -5055839.3
A32: Dividends | D32: =-'P&L'!H102 -> 0 | E32: =-'P&L'!I102 -> 0 | F32: =-'P&L'!J102 -> 0 | G32: =-'P&L'!K102 -> -7449479.6 | H32: =-'P&L'!L102 -> -7720502.9 | I32: =-'P&L'!M102 -> -8282539.9 | J32: =-'P&L'!N102 -> -8579208.9 | K32: =-'P&L'!O102 -> -8992996.6 | ... O32: =-'P&L'!S102 -> -9437566.7
A33: Transfer to Community Fund (Restricted Cash) | D33: =IFERROR(-'P&L'!H100,0) -> 0 | E33: =IFERROR(-'P&L'!I100,0) -> 0 | F33: =IFERROR(-'P&L'!J100,0) -> 0 | G33: =IFERROR(-'P&L'!K100,0) -> -139159.72 | H33: =IFERROR(-'P&L'!L100,0) -> -142052.54 | I33: =IFERROR(-'P&L'!M100,0) -> -152253.52 | J33: =IFERROR(-'P&L'!N100,0) -> -152253.52 | K33: =IFERROR(-'P&L'!O100,0) -> -152253.52 | ... O33: =IFERROR(-'P&L'!S100,0) -> -152253.52
A34: Total outflows | D34: =D26+D27+D28+D29+D30+D31+D32+D33 -> 0 | E34: =E26+E27+E28+E29+E30+E31+E32+E33 -> -780000 | F34: =F26+F27+F28+F29+F30+F31+F32+F33 -> -1024500 | G34: =G26+G27+G28+G29+G30+G31+G32+G33 -> -34493009 | H34: =H26+H27+H28+H29+H30+H31+H32+H33 -> -18328818 | I34: =I26+I27+I28+I29+I30+I31+I32+I33 -> -19304681 | J34: =J26+J27+J28+J29+J30+J31+J32+J33 -> -19764146 | K34: =K26+K27+K28+K29+K30+K31+K32+K33 -> -20506790 | ... O34: =O26+O27+O28+O29+O30+O31+O32+O33 -> -22079919
A35: Net working capital movement (ΔWC) | D35: =-('Balance Sheet'!F26) -> 0 | E35: =-('Balance Sheet'!G26-'Balance Sheet'!F26) -> 0 | F35: =-('Balance Sheet'!H26-'Balance Sheet'!G26) -> 0 | G35: =-('Balance Sheet'!I26-'Balance Sheet'!H26) -> -981418.65 | H35: =-('Balance Sheet'!J26-'Balance Sheet'!I26) -> -9466.7833 | I35: =-('Balance Sheet'!K26-'Balance Sheet'!J26) -> -68172.408 | J35: =-('Balance Sheet'!L26-'Balance Sheet'!K26) -> -33278.846 | K35: =-('Balance Sheet'!M26-'Balance Sheet'!L26) -> -15908.583 | L35: =-('Balance Sheet'!N26-'Balance Sheet'!M26) -> 36842.765 | ... O35: =-('Balance Sheet'!Q26-'Balance Sheet'!P26) -> -20673.514
A36: Net Cash Flow | D36: =D22+D23+D34+D35 -> 0 | E36: =E22+E23+E34+E35 -> 1707500 | F36: =F22+F23+F34+F35 -> 14343000 | G36: =G22+G23+G34+G35 -> -17281518 | H36: =H22+H23+H34+H35 -> 835010.27 | I36: =I22+I23+I34+I35 -> 909417.15 | J36: =J22+J23+J34+J35 -> 1019733.6 | K36: =K22+K23+K34+K35 -> 774279.67 | ... O36: =O22+O23+O34+O35 -> 1.3641068e+08
A37: Closing Cash Balance | D37: =D10+D36 -> 0 | E37: =E10+E36 -> 1707500 | F37: =F10+F36 -> 16050500 | G37: =G10+G36 -> -1231018.3 | H37: =H10+H36 -> -396007.99 | I37: =I10+I36 -> 513409.17 | J37: =J10+J36 -> 1533142.7 | K37: =K10+K36 -> 2307422.4 | ... O37: =O10+O36 -> 1.4219797e+08
A38: Cash tie (CFS - BS cash) | D38: =D37-'Balance Sheet'!F10 -> 0 | E38: =E37-'Balance Sheet'!G10 -> 0 | F38: =F37-'Balance Sheet'!H10 -> 0 | G38: =G37-'Balance Sheet'!I10 -> 0 | H38: =H37-'Balance Sheet'!J10 -> 0 | I38: =I37-'Balance Sheet'!K10 -> 0 | J38: =J37-'Balance Sheet'!L10 -> 0 | K38: =K37-'Balance Sheet'!M10 -> 0 | ... O38: =O37-'Balance Sheet'!Q10 -> 0
A39: Cash tie (Waterfall - BS cash) | D39: =D10+D36-D37 -> 0 | E39: =E10+E36-E37 -> 0 | F39: =F10+F36-F37 -> 0 | G39: =G10+G36-G37 -> 0 | H39: =H10+H36-H37 -> 0 | I39: =I10+I36-I37 -> 0 | J39: =J10+J36-J37 -> 0 | K39: =K10+K36-K37 -> 0 | ... O39: =O10+O36-O37 -> 0
A42: Year | D42: =D7 -> FY25 | E42: =E7 -> FY26 | F42: =F7 -> FY27 | G42: =G7 -> FY28 | H42: =H7 -> FY29 | I42: =I7 -> FY30 | J42: =J7 -> FY31 | K42: =K7 -> FY32 | ... O42: =O7 -> FY36
A43: FY Start | D43: =D5 -> 45715 | E43: =E5 -> 45839 | F43: =F5 -> 46204 | G43: =G5 -> 46569 | H43: =H5 -> 46935 | I43: =I5 -> 47300 | J43: =J5 -> 47665 | K43: =K5 -> 48030 | ... O43: =O5 -> 49491
A44: FY End | D44: =D6 -> 45838 | E44: =E6 -> 46203 | F44: =F6 -> 46568 | G44: =G6 -> 46934 | H44: =H6 -> 47299 | I44: =I6 -> 47664 | J44: =J6 -> 48029 | K44: =K6 -> 48395 | ... O44: =O6 -> 49856
A46: DRIVERS
A47: Revenue | D47: =IFERROR('P&L'!H28,0) -> 0 | E47: =IFERROR('P&L'!I28,0) -> 0 | F47: =IFERROR('P&L'!J28,0) -> 0 | G47: =IFERROR('P&L'!K28,0) -> 18192909 | H47: =IFERROR('P&L'!L28,0) -> 19173295 | I47: =IFERROR('P&L'!M28,0) -> 20282270 | J47: =IFERROR('P&L'!N28,0) -> 20817159 | K47: =IFERROR('P&L'!O28,0) -> 21296978 | ... O47: =IFERROR('P&L'!S28,0) -> 23361053
A48: COGS | D48: =IFERROR('P&L'!H36,0) -> 0 | E48: =IFERROR('P&L'!I36,0) -> 0 | F48: =IFERROR('P&L'!J36,0) -> 0 | G48: =IFERROR('P&L'!K36,0) -> 76190.219 | H48: =IFERROR('P&L'!L36,0) -> 80903.879 | I48: =IFERROR('P&L'!M36,0) -> 83708.1 | J48: =IFERROR('P&L'!N36,0) -> 84963.721 | K48: =IFERROR('P&L'!O36,0) -> 87512.633 | ... O48: =IFERROR('P&L'!S36,0) -> 98496.24
A49: OPEX (cash, excl dep'n) | D49: =IFERROR('P&L'!H75,0) -> 0 | E49: =IFERROR('P&L'!I75,0) -> 0 | F49: =IFERROR('P&L'!J75,0) -> 0 | G49: =IFERROR('P&L'!K75,0) -> 4117417 | H49: =IFERROR('P&L'!L75,0) -> 4691078.9 | I49: =IFERROR('P&L'!M75,0) -> 4875572.3 | J49: =IFERROR('P&L'!N75,0) -> 4961398.9 | K49: =IFERROR('P&L'!O75,0) -> 5150543.3 | ... O49: =IFERROR('P&L'!S75,0) -> 6368779.2
A51: BALANCES
A52: Accounts receivable | D52: =(D47/365)*Inputs!$E$300 -> 0 | E52: =(E47/365)*Inputs!$E$300 -> 0 | F52: =(F47/365)*Inputs!$E$300 -> 0 | G52: =(G47/365)*Inputs!$E$300 -> 1495307.6 | H52: =(H47/365)*Inputs!$E$300 -> 1575887.3 | I52: =(I47/365)*Inputs!$E$300 -> 1667035.9 | J52: =(J47/365)*Inputs!$E$300 -> 1710999.3 | K52: =(K47/365)*Inputs!$E$300 -> 1750436.6 | ... O52: =(O47/365)*Inputs!$E$300 -> 1920086.6
A53: Inventory | D53: =(D48/365)*Inputs!$E$302 -> 0 | E53: =(E48/365)*Inputs!$E$302 -> 0 | F53: =(F48/365)*Inputs!$E$302 -> 0 | G53: =(G48/365)*Inputs!$E$302 -> 3131.1049 | H53: =(H48/365)*Inputs!$E$302 -> 3324.8169 | I53: =(I48/365)*Inputs!$E$302 -> 3440.0589 | J53: =(J48/365)*Inputs!$E$302 -> 3491.6598 | K53: =(K48/365)*Inputs!$E$302 -> 3596.4096 | ... O53: =(O48/365)*Inputs!$E$302 -> 4047.7907
A54: Accounts payable | D54: =(((D48+D49)/365))*Inputs!$E$301 -> 0 | E54: =(((E48+E49)/365))*Inputs!$E$301 -> 0 | F54: =(((F48+F49)/365))*Inputs!$E$301 -> 0 | G54: =(((G48+G49)/365))*Inputs!$E$301 -> 517020.07 | H54: =(((H48+H49)/365))*Inputs!$E$301 -> 588326.64 | I54: =(((I48+I49)/365))*Inputs!$E$301 -> 611418.13 | J54: =(((J48+J49)/365))*Inputs!$E$301 -> 622154.3 | K54: =(((K48+K49)/365))*Inputs!$E$301 -> 645787.71 | ... O54: =(((O48+O49)/365))*Inputs!$E$301 -> 797335.32
A56: CASHFLOW IMPACT (positive = inflow)
A57: Change in AR | D57: =-D52 -> 0 | E57: =-(E52-D52) -> 0 | F57: =-(F52-E52) -> 0 | G57: =-(G52-F52) -> -1495307.6 | H57: =-(H52-G52) -> -80579.639 | I57: =-(I52-H52) -> -91148.654 | J57: =-(J52-I52) -> -43963.42 | K57: =-(K52-J52) -> -39437.246 | L57: =-(L52-K52) -> -40592.86 | ... O57: =-(O52-N52) -> -44267.626
A58: Change in Inventory | D58: =-D53 -> 0 | E58: =-(E53-D53) -> 0 | F58: =-(F53-E53) -> 0 | G58: =-(G53-F53) -> -3131.1049 | H58: =-(H53-G53) -> -193.71205 | I58: =-(I53-H53) -> -115.24197 | J58: =-(J53-I53) -> -51.600884 | K58: =-(K53-J53) -> -104.74979 | L58: =-(L53-K53) -> -107.89229 | ... O58: =-(O53-N53) -> -117.89682
A59: Change in AP | D59: =D54 -> 0 | E59: =(E54-D54) -> 0 | F59: =(F54-E54) -> 0 | G59: =(G54-F54) -> 517020.07 | H59: =(H54-G54) -> 71306.568 | I59: =(I54-H54) -> 23091.488 | J59: =(J54-I54) -> 10736.175 | K59: =(K54-J54) -> 23633.413 | L59: =(L54-K54) -> 77543.517 | ... O59: =(O54-N54) -> 23712.009
A60: Net working capital change | D60: =D36 -> 0 | E60: =E36 -> 1707500 | F60: =F36 -> 14343000 | G60: =G36 -> -17281518 | H60: =H36 -> 835010.27 | I60: =I36 -> 909417.15 | J60: =J36 -> 1019733.6 | K60: =K36 -> 774279.67 | ... O60: =O36 -> 1.3641068e+08
A62: KEY METRICS
A63: EBITDA (from P&L) | D63: =IFERROR('P&L'!H77,0) -> 0 | E63: =IFERROR('P&L'!I77,0) -> 0 | F63: =IFERROR('P&L'!J77,0) -> 0 | G63: =IFERROR('P&L'!K77,0) -> 13999302 | H63: =IFERROR('P&L'!L77,0) -> 14401312 | I63: =IFERROR('P&L'!M77,0) -> 15322990 | J63: =IFERROR('P&L'!N77,0) -> 15770796 | K63: =IFERROR('P&L'!O77,0) -> 16058922 | ... O63: =IFERROR('P&L'!S77,0) -> 16893778
A64: Debt Service (cash) – positive | D64: =ABS(D30) -> 0 | E64: =ABS(E30) -> 0 | F64: =ABS(F30) -> 1024500 | G64: =ABS(G30) -> 1721160 | H64: =ABS(H30) -> 1639200 | I64: =ABS(I30) -> 1557240 | J64: =ABS(J30) -> 1475280 | K64: =ABS(K30) -> 1393320 | ... O64: =ABS(O30) -> 1065480
A65: DSCR = CFADS / Debt Service | D65: =IF(OR(D64=0,D63=0),"",(D63+D31+D35)/D64) | E65: =IF(OR(E64=0,E63=0),"",(E63+E31+E35)/E64) | F65: =IF(OR(F64=0,F63=0),"",(F63+F31+F35)/F64) | G65: =IF(OR(G64=0,G63=0),"",(G63+G31+G35)/G64) -> 5.2447715 | H65: =IF(OR(H64=0,H63=0),"",(H63+H31+H35)/H64) -> 6.2566263 | I65: =IF(OR(I64=0,I63=0),"",(I63+I31+I35)/I64) -> 6.9467407 | J65: =IF(OR(J64=0,J63=0),"",(J63+J31+J35)/J64) -> 7.552134 | K65: =IF(OR(K64=0,K63=0),"",(K63+K31+K35)/K64) -> 8.0565392 | ... O65: =IF(OR(O64=0,O63=0),"",(O63+O31+O35)/O64) -> 11.091025
A66: Minimum Closing Cash (FY27–FY37) | D66: =IF(D$6>=Inputs!$E$9,Inputs!$E$304,0) -> 100000 | E66: =IF(E$6>=Inputs!$E$9,Inputs!$E$304,0) -> 100000 | F66: =IF(F$6>=Inputs!$E$9,Inputs!$E$304,0) -> 100000 | G66: =IF(G$6>=Inputs!$E$9,Inputs!$E$304,0) -> 100000 | H66: =IF(H$6>=Inputs!$E$9,Inputs!$E$304,0) -> 100000 | I66: =IF(I$6>=Inputs!$E$9,Inputs!$E$304,0) -> 100000 | J66: =IF(J$6>=Inputs!$E$9,Inputs!$E$304,0) -> 100000 | K66: =IF(K$6>=Inputs!$E$9,Inputs!$E$304,0) -> 100000 | ... O66: =IF(O$6>=Inputs!$E$9,Inputs!$E$304,0) -> 100000
A67: Funding Surplus / (Shortfall) | D67: =MAX(0,D66-D37) -> 100000 | E67: =MAX(0,E66-E37) -> 0 | F67: =MAX(0,F66-F37) -> 0 | G67: =MAX(0,G66-G37) -> 1331018.3 | H67: =MAX(0,H66-H37) -> 496007.99 | I67: =MAX(0,I66-I37) -> 0 | J67: =MAX(0,J66-J37) -> 0 | K67: =MAX(0,K66-K37) -> 0 | ... O67: =MAX(0,O66-O37) -> 0
A68: Funding Status | D68: =IF(D67>0,"Shortfall",IF(D37<0,"Negative Cash","OK")) -> Shortfall | E68: =IF(E67>0,"Shortfall",IF(E37<0,"Negative Cash","OK")) -> OK | F68: =IF(F67>0,"Shortfall",IF(F37<0,"Negative Cash","OK")) -> OK | G68: =IF(G67>0,"Shortfall",IF(G37<0,"Negative Cash","OK")) -> Shortfall | H68: =IF(H67>0,"Shortfall",IF(H37<0,"Negative Cash","OK")) -> Shortfall | I68: =IF(I67>0,"Shortfall",IF(I37<0,"Negative Cash","OK")) -> OK | J68: =IF(J67>0,"Shortfall",IF(J37<0,"Negative Cash","OK")) -> OK | K68: =IF(K67>0,"Shortfall",IF(K37<0,"Negative Cash","OK")) -> OK | ... O68: =IF(O67>0,"Shortfall",IF(O37<0,"Negative Cash","OK")) -> OK
A70: Total current borrowings (next 12 months) | D70: =IFERROR(Debt!H49,0) -> 0 | E70: =IFERROR(Debt!I49,0) -> 0 | F70: =IFERROR(Debt!J49,0) -> 1024500 | G70: =IFERROR(Debt!K49,0) -> 1024500 | H70: =IFERROR(Debt!L49,0) -> 1024500 | I70: =IFERROR(Debt!M49,0) -> 1024500 | J70: =IFERROR(Debt!N49,0) -> 1024500 | K70: =IFERROR(Debt!O49,0) -> 1024500 | ... O70: =IFERROR(Debt!S49,0) -> 0
A71: Total non-current borrowings | D71: =IFERROR(Debt!H50,0) -> 0 | E71: =IFERROR(Debt!I50,0) -> 0 | F71: =IFERROR(Debt!J50,0) -> 8196000 | G71: =IFERROR(Debt!K50,0) -> 7171500 | H71: =IFERROR(Debt!L50,0) -> 6147000 | I71: =IFERROR(Debt!M50,0) -> 5122500 | J71: =IFERROR(Debt!N50,0) -> 4098000 | K71: =IFERROR(Debt!O50,0) -> 3073500 | ... O71: =IFERROR(Debt!S50,0) -> 0
A79: Unlevered FCF | D79: =D26+D63-D99+D35 -> 0 | E79: =E26+E63-E99+E35 -> -780000 | F79: =F26+F63-F99+F35 -> 0 | G79: =G26+G63-G99+G35 -> -4057116.5 | H79: =H26+H63-H99+H35 -> 14391845 | I79: =I26+I63-I99+I35 -> 15254818 | J79: =J26+J63-J99+J35 -> 15737517 | K79: =K26+K63-K99+K35 -> 16043014 | ... N79: =N26+N63-N99+N35 -> 16527354 | O79: =O26+O63-O99+O35+O23 -> 1.5202333e+08
A80: Equity CF | D80: =-D16 -> 0 | E80: =-E16 -> -2487500 | F80: =-F16 -> -5122500 | G80: =-G16 -> 0 | H80: =-H16 -> 0 | I80: =-I16 -> 0 | J80: =-J16 -> 0 | K80: =-K16 -> 0 | ... N80: =-N16 -> 0 | O80: =-O16+O23 -> 1.3515022e+08
A86: EQUITY SCHEDULE
A87: Year | D87: =D7 -> FY25 | E87: =E7 -> FY26 | F87: =F7 -> FY27 | G87: =G7 -> FY28 | H87: =H7 -> FY29 | I87: =I7 -> FY30 | J87: =J7 -> FY31 | K87: =K7 -> FY32 | ... O87: =O7 -> FY36
A89: Opening Contributed Equity | D89: 0 | E89: =D95 -> 0 | F89: =E95 -> 2487500 | G89: =F95 -> 7610000 | H89: =G95 -> 7610000 | I89: =H95 -> 7610000 | J89: =I95 -> 7610000 | K89: =J95 -> 7610000 | L89: =K95 -> 7610000 | ... O89: =N95 -> 7610000
A90: Founder / Seed Equity Injected | D90: =D13 -> 0 | E90: =E13 -> 2487500 | F90: =F13 -> 0 | G90: =G13 -> 0 | H90: =H13 -> 0 | I90: =I13 -> 0 | J90: =J13 -> 0 | K90: =K13 -> 0 | ... O90: =O13 -> 0
A91: PE Equity Injected | D91: =D14 -> 0 | E91: =E14 -> 0 | F91: =F14 -> 5122500 | G91: =G14 -> 0 | H91: =H14 -> 0 | I91: =I14 -> 0 | J91: =J14 -> 0 | K91: =K14 -> 0 | ... O91: =O14 -> 0
A92: Other Equity Injected | D92: =D15 -> 0 | E92: =E15 -> 0 | F92: =F15 -> 0 | G92: =G15 -> 0 | H92: =H15 -> 0 | I92: =I15 -> 0 | J92: =J15 -> 0 | K92: =K15 -> 0 | ... O92: =O15 -> 0
A93: Total New Equity | D93: =D90+D91+D92 -> 0 | E93: =E90+E91+E92 -> 2487500 | F93: =F90+F91+F92 -> 5122500 | G93: =G90+G91+G92 -> 0 | H93: =H90+H91+H92 -> 0 | I93: =I90+I91+I92 -> 0 | J93: =J90+J91+J92 -> 0 | K93: =K90+K91+K92 -> 0 | ... O93: =O90+O91+O92 -> 0
A94: Distributions / Buybacks | D94: 0 | E94: 0 | F94: 0 | G94: 0 | H94: 0 | I94: 0 | J94: 0 | K94: 0 | L94: 0 | M94: 0 | N94: 0 | O94: 0
A95: Closing Contributed Equity | D95: =D89+D93+D94 -> 0 | E95: =E89+E93+E94 -> 2487500 | F95: =F89+F93+F94 -> 7610000 | G95: =G89+G93+G94 -> 7610000 | H95: =H89+H93+H94 -> 7610000 | I95: =I89+I93+I94 -> 7610000 | J95: =J89+J93+J94 -> 7610000 | K95: =K89+K93+K94 -> 7610000 | ... O95: =O89+O93+O94 -> 7610000
A97: Cumulative Contributed Equity | D97: =D95 -> 0 | E97: =E95 -> 2487500 | F97: =F95 -> 7610000 | G97: =G95 -> 7610000 | H97: =H95 -> 7610000 | I97: =I95 -> 7610000 | J97: =J95 -> 7610000 | K97: =K95 -> 7610000 | ... O97: =O95 -> 7610000

Sheet Debt
A2: Port Melbourne Live House
B4: Inputs (linked from Summary) | C4: Term Debt | D4: PE Loan
C5: =Inputs!E54 -> 10245000 | D5: =Inputs!E63 -> 0
B6: =Inputs!D52 -> Years | C6: =Inputs!E52 -> 10 | D6: =Inputs!E61 -> 10
B7: =Inputs!D53 -> % | C7: =Inputs!E51 -> 0.08 | D7: =Inputs!E60 -> 0.12
B8: =Inputs!D54 -> AUD | C8: =Inputs!E56 -> FY27 | D8: =Inputs!E65 -> FY27
B9: =Inputs!D55 -> 0 | C9: Amortising | D9: =Inputs!$G$61 -> 5-year term
B11: Term Debt
H12: ='P&L'!H4 -> 45715 | I12: ='P&L'!I4 -> 45839 | J12: ='P&L'!J4 -> 46204 | K12: ='P&L'!K4 -> 46569 | L12: ='P&L'!L4 -> 46935 | M12: ='P&L'!M4 -> 47300 | N12: ='P&L'!N4 -> 47665 | O12: ='P&L'!O4 -> 48030 | ... S12: ='P&L'!S4 -> 49491
B13: Draw year | H13: ='P&L'!H5 -> 45838 | I13: ='P&L'!I5 -> 46203 | J13: ='P&L'!J5 -> 46568 | K13: ='P&L'!K5 -> 46934 | L13: ='P&L'!L5 -> 47299 | M13: ='P&L'!M5 -> 47664 | N13: ='P&L'!N5 -> 48029 | O13: ='P&L'!O5 -> 48395 | ... S13: ='P&L'!S5 -> 49856
H14: ='P&L'!H6 -> FY25 | I14: ='P&L'!I6 -> FY26 | J14: ='P&L'!J6 -> FY27 | K14: ='P&L'!K6 -> FY28 | L14: ='P&L'!L6 -> FY29 | M14: ='P&L'!M6 -> FY30 | N14: ='P&L'!N6 -> FY31 | O14: ='P&L'!O6 -> FY32 | ... S14: ='P&L'!S6 -> FY36
B15: Start flag | H15: =IF(AND(COLUMN(H14)>=COLUMN($H$14)+MATCH($C$8,$H$14:$S$14,0)-1, COLUMN(H14)<COLUMN($H$14)+MATCH($C$8,$H$14:$S$14,0)-1+$C$6), 1, 0) -> 0 | I15: =IF(AND(COLUMN(I14)>=COLUMN($H$14)+MATCH($C$8,$H$14:$S$14,0)-1, COLUMN(I14)<COLUMN($H$14)+MATCH($C$8,$H$14:$S$14,0)-1+$C$6), 1, 0) -> 0 | J15: =IF(AND(COLUMN(J14)>=COLUMN($H$14)+MATCH($C$8,$H$14:$S$14,0)-1, COLUMN(J14)<COLUMN($H$14)+MATCH($C$8,$H$14:$S$14,0)-1+$C$6), 1, 0) -> 1 | K15: =IF(AND(COLUMN(K14)>=COLUMN($H$14)+MATCH($C$8,$H$14:$S$14,0)-1, COLUMN(K14)<COLUMN($H$14)+MATCH($C$8,$H$14:$S$14,0)-1+$C$6), 1, 0) -> 1 | L15: =IF(AND(COLUMN(L14)>=COLUMN($H$14)+MATCH($C$8,$H$14:$S$14,0)-1, COLUMN(L14)<COLUMN($H$14)+MATCH($C$8,$H$14:$S$14,0)-1+$C$6), 1, 0) -> 1 | M15: =IF(AND(COLUMN(M14)>=COLUMN($H$14)+MATCH($C$8,$H$14:$S$14,0)-1, COLUMN(M14)<COLUMN($H$14)+MATCH($C$8,$H$14:$S$14,0)-1+$C$6), 1, 0) -> 1 | N15: =IF(AND(COLUMN(N14)>=COLUMN($H$14)+MATCH($C$8,$H$14:$S$14,0)-1, COLUMN(N14)<COLUMN($H$14)+MATCH($C$8,$H$14:$S$14,0)-1+$C$6), 1, 0) -> 1 | O15: =IF(AND(COLUMN(O14)>=COLUMN($H$14)+MATCH($C$8,$H$14:$S$14,0)-1, COLUMN(O14)<COLUMN($H$14)+MATCH($C$8,$H$14:$S$14,0)-1+$C$6), 1, 0) -> 1 | ... S15: =IF(AND(COLUMN(S14)>=COLUMN($H$14)+MATCH($C$8,$H$14:$S$14,0)-1, COLUMN(S14)<COLUMN($H$14)+MATCH($C$8,$H$14:$S$14,0)-1+$C$6), 1, 0) -> 1
B16: End flag | H16: =IF(AND(H15=1, H24=0), 1, 0) -> 0 | I16: =IF(AND(I15=1, I24=0), 1, 0) -> 0 | J16: =IF(AND(J15=1, J24=0), 1, 0) -> 0 | K16: =IF(AND(K15=1, K24=0), 1, 0) -> 0 | L16: =IF(AND(L15=1, L24=0), 1, 0) -> 0 | M16: =IF(AND(M15=1, M24=0), 1, 0) -> 0 | N16: =IF(AND(N15=1, N24=0), 1, 0) -> 0 | O16: =IF(AND(O15=1, O24=0), 1, 0) -> 0 | ... S16: =IF(AND(S15=1, S24=0), 1, 0) -> 1
B18: Opening balance | H18: =IF(H$15=0,0,IF(COLUMNS($H18:H18)=MATCH($C$8,$H$14:$S$14,0),0,INDEX($H$24:$S$24,COLUMNS($H18:H18)-1))) -> 0 | I18: =IF(I$15=0,0,IF(COLUMNS($H18:I18)=MATCH($C$8,$H$14:$S$14,0),0,INDEX($H$24:$S$24,COLUMNS($H18:I18)-1))) -> 0 | J18: =IF(J15=0,0,0) -> 0 | K18: =IF(K15=0,0,J24) -> 9220500 | L18: =IF(L15=0,0,K24) -> 8196000 | M18: =IF(M15=0,0,L24) -> 7171500 | N18: =IF(N15=0,0,M24) -> 6147000 | O18: =IF(O15=0,0,N24) -> 5122500 | P18: =IF(P15=0,0,O24) -> 4098000 | Q18: =IF(Q15=0,0,P24) -> 3073500 | R18: =IF(R15=0,0,Q24) -> 2049000 | S18: =IF(S15=0,0,R24) -> 1024500
B19: Repayment type | C19: Amortising
B20: Drawdown | H20: =IF(H$15=0,0,IF(COLUMNS($H20:H20)=MATCH($C$8,$H$14:$S$14,0),$C$5,0)) -> 0 | I20: =IF(I$15=0,0,IF(COLUMNS($H20:I20)=MATCH($C$8,$H$14:$S$14,0),$C$5,0)) -> 0 | J20: =IF(J$15=0,0,IF(COLUMNS($H20:J20)=MATCH($C$8,$H$14:$S$14,0),$C$5,0)) -> 10245000 | K20: =IF(K$15=0,0,IF(COLUMNS($H20:K20)=MATCH($C$8,$H$14:$S$14,0),$C$5,0)) -> 0 | L20: =IF(L$15=0,0,IF(COLUMNS($H20:L20)=MATCH($C$8,$H$14:$S$14,0),$C$5,0)) -> 0 | M20: =IF(M$15=0,0,IF(COLUMNS($H20:M20)=MATCH($C$8,$H$14:$S$14,0),$C$5,0)) -> 0 | N20: =IF(N$15=0,0,IF(COLUMNS($H20:N20)=MATCH($C$8,$H$14:$S$14,0),$C$5,0)) -> 0 | O20: =IF(O$15=0,0,IF(COLUMNS($H20:O20)=MATCH($C$8,$H$14:$S$14,0),$C$5,0)) -> 0 | ... S20: =IF(S$15=0,0,IF(COLUMNS($H20:S20)=MATCH($C$8,$H$14:$S$14,0),$C$5,0)) -> 0
B21: Principal repayment | H21: =IF(H$15=0,0,IF(OR($C$9="Bullet",$C$9="Interest-only"),IF($C$9="Bullet",IF(H$16=1,H$18+H$20,0),0),IF(OR($C$9="Amortising",$C$9="Amortizing"),IF(H$15=1,IF((COLUMNS($H21:H21)-MATCH($C$8,$H$14:$S$14,0)+1)<=ROUNDUP(RM_IO_Months/12,0),0,IF(H$16=1,H$18+H$20,MIN(H$18+H$20,IF(($C$7-ROUNDUP(RM_IO_Months/12,0))<=0,H$18+H$20,$C$5/($C$7-ROUNDUP(RM_IO_Months/12,0)))))),0),0))) -> 0 | I21: =IF(I$15=0,0,IF(OR($C$9="Bullet",$C$9="Interest-only"),IF($C$9="Bullet",IF(I$16=1,I$18+I$20,0),0),IF(OR($C$9="Amortising",$C$9="Amortizing"),IF(I$15=1,IF((COLUMNS($H21:I21)-MATCH($C$8,$H$14:$S$14,0)+1)<=ROUNDUP(RM_IO_Months/12,0),0,IF(I$16=1,I$18+I$20,MIN(I$18+I$20,IF(($C$7-ROUNDUP(RM_IO_Months/12,0))<=0,I$18+I$20,$C$5/($C$7-ROUNDUP(RM_IO_Months/12,0)))))),0),0))) -> 0 | J21: =IF(J15=0,0,$C$5/$C$6) -> 1024500 | K21: =IF(K15=0,0,$C$5/$C$6) -> 1024500 | L21: =IF(L15=0,0,$C$5/$C$6) -> 1024500 | M21: =IF(M15=0,0,$C$5/$C$6) -> 1024500 | N21: =IF(N15=0,0,$C$5/$C$6) -> 1024500 | O21: =IF(O15=0,0,$C$5/$C$6) -> 1024500 | P21: =IF(P15=0,0,$C$5/$C$6) -> 1024500 | Q21: =IF(Q15=0,0,$C$5/$C$6) -> 1024500 | ... S21: =IF(S15=0,0,$C$5/$C$6) -> 1024500
B22: Interest paid | H22: =IF(H$15=0,0,((H$18+H$24)/2)*$C$7) -> 0 | I22: =IF(I$15=0,0,((I$18+I$24)/2)*$C$7) -> 0 | J22: =IF(J15=0,0,((J18+J24)/2)*$C$7) -> 368820 | K22: =IF(K15=0,0,((K18+K24)/2)*$C$7) -> 696660 | L22: =IF(L15=0,0,((L18+L24)/2)*$C$7) -> 614700 | M22: =IF(M15=0,0,((M18+M24)/2)*$C$7) -> 532740 | N22: =IF(N15=0,0,((N18+N24)/2)*$C$7) -> 450780 | O22: =IF(O15=0,0,((O18+O24)/2)*$C$7) -> 368820 | P22: =IF(P15=0,0,((P18+P24)/2)*$C$7) -> 286860 | Q22: =IF(Q15=0,0,((Q18+Q24)/2)*$C$7) -> 204900 | ... S22: =IF(S15=0,0,((S18+S24)/2)*$C$7) -> 40980
B23: Total debt service | H23: =H$21+H$22 -> 0 | I23: =I$21+I$22 -> 0 | J23: =J$21+J$22 -> 1393320 | K23: =K$21+K$22 -> 1721160 | L23: =L$21+L$22 -> 1639200 | M23: =M$21+M$22 -> 1557240 | N23: =N$21+N$22 -> 1475280 | O23: =O$21+O$22 -> 1393320 | ... S23: =S$21+S$22 -> 1065480
B24: Closing balance | H24: =IF(H$15=0,0,MAX(0,H$18+H$20-H$21)) -> 0 | I24: =IF(I$15=0,0,MAX(0,I$18+I$20-I$21)) -> 0 | J24: =IF(J15=0,0,J18+J20-J21) -> 9220500 | K24: =IF(K15=0,0,K18+K20-K21) -> 8196000 | L24: =IF(L15=0,0,L18+L20-L21) -> 7171500 | M24: =IF(M15=0,0,M18+M20-M21) -> 6147000 | N24: =IF(N15=0,0,N18+N20-N21) -> 5122500 | O24: =IF(O15=0,0,O18+O20-O21) -> 4098000 | P24: =IF(P15=0,0,P18+P20-P21) -> 3073500 | Q24: =IF(Q15=0,0,Q18+Q20-Q21) -> 2049000 | ... S24: =IF(S15=0,0,S18+S20-S21) -> 0
B25: Current portion (next 12 months) | H25: =IF(H$15=0,0,IF(H$24=0,0,IF(H$16=1,0,MIN(H$24,IFERROR(INDEX($H$21:$S$21,COLUMNS($H25:H25)+1),0))))) -> 0 | I25: =IF(I$15=0,0,IF(I$24=0,0,IF(I$16=1,0,MIN(I$24,IFERROR(INDEX($H$21:$S$21,COLUMNS($H25:I25)+1),0))))) -> 0 | J25: =IF(J$15=0,0,IF(J$24=0,0,IF(J$16=1,0,MIN(J$24,IFERROR(INDEX($H$21:$S$21,COLUMNS($H25:J25)+1),0))))) -> 1024500 | K25: =IF(K$15=0,0,IF(K$24=0,0,IF(K$16=1,0,MIN(K$24,IFERROR(INDEX($H$21:$S$21,COLUMNS($H25:K25)+1),0))))) -> 1024500 | L25: =IF(L$15=0,0,IF(L$24=0,0,IF(L$16=1,0,MIN(L$24,IFERROR(INDEX($H$21:$S$21,COLUMNS($H25:L25)+1),0))))) -> 1024500 | M25: =IF(M$15=0,0,IF(M$24=0,0,IF(M$16=1,0,MIN(M$24,IFERROR(INDEX($H$21:$S$21,COLUMNS($H25:M25)+1),0))))) -> 1024500 | N25: =IF(N$15=0,0,IF(N$24=0,0,IF(N$16=1,0,MIN(N$24,IFERROR(INDEX($H$21:$S$21,COLUMNS($H25:N25)+1),0))))) -> 1024500 | O25: =IF(O$15=0,0,IF(O$24=0,0,IF(O$16=1,0,MIN(O$24,IFERROR(INDEX($H$21:$S$21,COLUMNS($H25:O25)+1),0))))) -> 1024500 | ... S25: =IF(S$15=0,0,IF(S$24=0,0,IF(S$16=1,0,MIN(S$24,IFERROR(INDEX($H$21:$S$21,COLUMNS($H25:S25)+1),0))))) -> 0
B26: Non-current portion | H26: =MAX(0,H$24-H$25) -> 0 | I26: =MAX(0,I$24-I$25) -> 0 | J26: =MAX(0,J$24-J$25) -> 8196000 | K26: =MAX(0,K$24-K$25) -> 7171500 | L26: =MAX(0,L$24-L$25) -> 6147000 | M26: =MAX(0,M$24-M$25) -> 5122500 | N26: =MAX(0,N$24-N$25) -> 4098000 | O26: =MAX(0,O$24-O$25) -> 3073500 | ... S26: =MAX(0,S$24-S$25) -> 0
B32: Private Equity Debt — LEGACY INACTIVE (PE is now equity) | H32: =H12 -> 45715 | I32: =I12 -> 45839 | J32: =J12 -> 46204 | K32: =K12 -> 46569 | L32: =L12 -> 46935 | M32: =M12 -> 47300 | N32: =N12 -> 47665 | O32: =O12 -> 48030 | ... S32: =S12 -> 49491
H33: =H13 -> 45838 | I33: =I13 -> 46203 | J33: =J13 -> 46568 | K33: =K13 -> 46934 | L33: =L13 -> 47299 | M33: =M13 -> 47664 | N33: =N13 -> 48029 | O33: =O13 -> 48395 | ... S33: =S13 -> 49856
H34: =H14 -> FY25 | I34: =I14 -> FY26 | J34: =J14 -> FY27 | K34: =K14 -> FY28 | L34: =L14 -> FY29 | M34: =M14 -> FY30 | N34: =N14 -> FY31 | O34: =O14 -> FY32 | ... S34: =S14 -> FY36
B36: Drawdown (PE) | H36: =H$44 -> 0 | I36: =I$44 -> 0 | J36: =J$44 -> 0 | K36: =K$44 -> 0 | L36: =L$44 -> 0 | M36: =M$44 -> 0 | N36: =N$44 -> 0 | O36: =O$44 -> 0 | ... S36: =S$44 -> 0
B37: Start flag | H37: =IF(AND(COLUMN(H34)>=COLUMN($H$34)+MATCH($D$8,$H$34:$S$34,0)-1, COLUMN(H34)<COLUMN($H$34)+MATCH($D$8,$H$34:$S$34,0)-1+$D$6), 1, 0) -> 0 | I37: =IF(AND(COLUMN(I34)>=COLUMN($H$34)+MATCH($D$8,$H$34:$S$34,0)-1, COLUMN(I34)<COLUMN($H$34)+MATCH($D$8,$H$34:$S$34,0)-1+$D$6), 1, 0) -> 0 | J37: =IF(AND(COLUMN(J34)>=COLUMN($H$34)+MATCH($D$8,$H$34:$S$34,0)-1, COLUMN(J34)<COLUMN($H$34)+MATCH($D$8,$H$34:$S$34,0)-1+$D$6), 1, 0) -> 1 | K37: =IF(AND(COLUMN(K34)>=COLUMN($H$34)+MATCH($D$8,$H$34:$S$34,0)-1, COLUMN(K34)<COLUMN($H$34)+MATCH($D$8,$H$34:$S$34,0)-1+$D$6), 1, 0) -> 1 | L37: =IF(AND(COLUMN(L34)>=COLUMN($H$34)+MATCH($D$8,$H$34:$S$34,0)-1, COLUMN(L34)<COLUMN($H$34)+MATCH($D$8,$H$34:$S$34,0)-1+$D$6), 1, 0) -> 1 | M37: =IF(AND(COLUMN(M34)>=COLUMN($H$34)+MATCH($D$8,$H$34:$S$34,0)-1, COLUMN(M34)<COLUMN($H$34)+MATCH($D$8,$H$34:$S$34,0)-1+$D$6), 1, 0) -> 1 | N37: =IF(AND(COLUMN(N34)>=COLUMN($H$34)+MATCH($D$8,$H$34:$S$34,0)-1, COLUMN(N34)<COLUMN($H$34)+MATCH($D$8,$H$34:$S$34,0)-1+$D$6), 1, 0) -> 1 | O37: =IF(AND(COLUMN(O34)>=COLUMN($H$34)+MATCH($D$8,$H$34:$S$34,0)-1, COLUMN(O34)<COLUMN($H$34)+MATCH($D$8,$H$34:$S$34,0)-1+$D$6), 1, 0) -> 1 | ... S37: =IF(AND(COLUMN(S34)>=COLUMN($H$34)+MATCH($D$8,$H$34:$S$34,0)-1, COLUMN(S34)<COLUMN($H$34)+MATCH($D$8,$H$34:$S$34,0)-1+$D$6), 1, 0) -> 1
B38: End flag | H38: =IF(AND(H37=1, H47=0), 1, 0) -> 0 | I38: =IF(AND(I37=1, I47=0), 1, 0) -> 0 | J38: =IF(AND(J37=1, J47=0), 1, 0) -> 1 | K38: =IF(AND(K37=1, K47=0), 1, 0) -> 1 | L38: =IF(AND(L37=1, L47=0), 1, 0) -> 1 | M38: =IF(AND(M37=1, M47=0), 1, 0) -> 1 | N38: =IF(AND(N37=1, N47=0), 1, 0) -> 1 | O38: =IF(AND(O37=1, O47=0), 1, 0) -> 1 | ... S38: =IF(AND(S37=1, S47=0), 1, 0) -> 1
B40: Principal repayment (PE) – output | H40: =H$45 -> 0 | I40: =I$45 -> 0 | J40: =J$45 -> 0 | K40: =K$45 -> 0 | L40: =L$45 -> 0 | M40: =M$45 -> 0 | N40: =N$45 -> 0 | O40: =O$45 -> 0 | ... S40: =S$45 -> 0
B41: Private facility loan (PE) schedule
B42: Opening balance (PE) | H42: =IF(H$37=0,0,IF(COLUMNS($H42:H42)=MATCH($D$8,$H$34:$S$34,0),0,INDEX($H$47:$S$47,COLUMNS($H42:H42)-1))) -> 0 | I42: =IF(I$37=0,0,IF(COLUMNS($H42:I42)=MATCH($D$8,$H$34:$S$34,0),0,INDEX($H$47:$S$47,COLUMNS($H42:I42)-1))) -> 0 | J42: =IF(J37=0,0,0) -> 0 | K42: =IF(K37=0,0,J47) -> 0 | L42: =IF(L37=0,0,K47) -> 0 | M42: =IF(M37=0,0,L47) -> 0 | N42: =IF(N37=0,0,M47) -> 0 | O42: =IF(O37=0,0,N47) -> 0 | P42: =IF(P$37=0,0,IF(COLUMNS($H42:P42)=MATCH($D$8,$H$34:$S$34,0),0,INDEX($H$47:$S$47,COLUMNS($H42:P42)-1))) -> 0 | Q42: =IF(Q$37=0,0,IF(COLUMNS($H42:Q42)=MATCH($D$8,$H$34:$S$34,0),0,INDEX($H$47:$S$47,COLUMNS($H42:Q42)-1))) -> 0 | R42: =IF(R$37=0,0,IF(COLUMNS($H42:R42)=MATCH($D$8,$H$34:$S$34,0),0,INDEX($H$47:$S$47,COLUMNS($H42:R42)-1))) -> 0 | S42: =IF(S$37=0,0,IF(COLUMNS($H42:S42)=MATCH($D$8,$H$34:$S$34,0),0,INDEX($H$47:$S$47,COLUMNS($H42:S42)-1))) -> 0
B43: Repayment type | C43: Amortising
B44: Drawdown | H44: =IF(H$37=0,0,IF(COLUMNS($H44:H44)=MATCH($D$8,$H$34:$S$34,0),$D$5,0)) -> 0 | I44: =IF(I$37=0,0,IF(COLUMNS($H44:I44)=MATCH($D$8,$H$34:$S$34,0),$D$5,0)) -> 0 | J44: =IF(J$37=0,0,IF(COLUMNS($H44:J44)=MATCH($D$8,$H$34:$S$34,0),$D$5,0)) -> 0 | K44: =IF(K$37=0,0,IF(COLUMNS($H44:K44)=MATCH($D$8,$H$34:$S$34,0),$D$5,0)) -> 0 | L44: =IF(L$37=0,0,IF(COLUMNS($H44:L44)=MATCH($D$8,$H$34:$S$34,0),$D$5,0)) -> 0 | M44: =IF(M$37=0,0,IF(COLUMNS($H44:M44)=MATCH($D$8,$H$34:$S$34,0),$D$5,0)) -> 0 | N44: =IF(N$37=0,0,IF(COLUMNS($H44:N44)=MATCH($D$8,$H$34:$S$34,0),$D$5,0)) -> 0 | O44: =IF(O$37=0,0,IF(COLUMNS($H44:O44)=MATCH($D$8,$H$34:$S$34,0),$D$5,0)) -> 0 | ... S44: =IF(S$37=0,0,IF(COLUMNS($H44:S44)=MATCH($D$8,$H$34:$S$34,0),$D$5,0)) -> 0
B45: Principal repayment | H45: =IF(H$37=0,0,IF(OR($D$9="Bullet",$D$9="Interest-only"),IF($D$9="Bullet",IF(H$38=1,H$42+H$44,0),0),IF(OR($D$9="Amortising",$D$9="Amortizing"),IF(H$37=1,IF((COLUMNS($H45:H45)-MATCH($D$8,$H$34:$S$34,0)+1)<=ROUNDUP(RM_IO_Months/12,0),0,IF(H$38=1,H$42+H$44,MIN(H$42+H$44,IF(($D$7-ROUNDUP(RM_IO_Months/12,0))<=0,H$42+H$44,$D$5/($D$7-ROUNDUP(RM_IO_Months/12,0)))))),0),0))) -> 0 | I45: =IF(I$37=0,0,IF(OR($D$9="Bullet",$D$9="Interest-only"),IF($D$9="Bullet",IF(I$38=1,I$42+I$44,0),0),IF(OR($D$9="Amortising",$D$9="Amortizing"),IF(I$37=1,IF((COLUMNS($H45:I45)-MATCH($D$8,$H$34:$S$34,0)+1)<=ROUNDUP(RM_IO_Months/12,0),0,IF(I$38=1,I$42+I$44,MIN(I$42+I$44,IF(($D$7-ROUNDUP(RM_IO_Months/12,0))<=0,I$42+I$44,$D$5/($D$7-ROUNDUP(RM_IO_Months/12,0)))))),0),0))) -> 0 | J45: =IF(J37=0,0,$D$5/$D$6) -> 0 | K45: =IF(K37=0,0,$D$5/$D$6) -> 0 | L45: =IF(L37=0,0,$D$5/$D$6) -> 0 | M45: =IF(M37=0,0,$D$5/$D$6) -> 0 | N45: =IF(N37=0,0,$D$5/$D$6) -> 0 | O45: =IF(O37=0,0,$D$5/$D$6) -> 0 | P45: =IF(P$37=0,0,IF(OR($D$9="Bullet",$D$9="Interest-only"),IF($D$9="Bullet",IF(P$38=1,P$42+P$44,0),0),IF(OR($D$9="Amortising",$D$9="Amortizing"),IF(P$37=1,IF((COLUMNS($H45:P45)-MATCH($D$8,$H$34:$S$34,0)+1)<=ROUNDUP(RM_IO_Months/12,0),0,IF(P$38=1,P$42+P$44,MIN(P$42+P$44,IF(($D$7-ROUNDUP(RM_IO_Months/12,0))<=0,P$42+P$44,$D$5/($D$7-ROUNDUP(RM_IO_Months/12,0)))))),0),0))) -> 0 | Q45: =IF(Q$37=0,0,IF(OR($D$9="Bullet",$D$9="Interest-only"),IF($D$9="Bullet",IF(Q$38=1,Q$42+Q$44,0),0),IF(OR($D$9="Amortising",$D$9="Amortizing"),IF(Q$37=1,IF((COLUMNS($H45:Q45)-MATCH($D$8,$H$34:$S$34,0)+1)<=ROUNDUP(RM_IO_Months/12,0),0,IF(Q$38=1,Q$42+Q$44,MIN(Q$42+Q$44,IF(($D$7-ROUNDUP(RM_IO_Months/12,0))<=0,Q$42+Q$44,$D$5/($D$7-ROUNDUP(RM_IO_Months/12,0)))))),0),0))) -> 0 | R45: =IF(R$37=0,0,IF(OR($D$9="Bullet",$D$9="Interest-only"),IF($D$9="Bullet",IF(R$38=1,R$42+R$44,0),0),IF(OR($D$9="Amortising",$D$9="Amortizing"),IF(R$37=1,IF((COLUMNS($H45:R45)-MATCH($D$8,$H$34:$S$34,0)+1)<=ROUNDUP(RM_IO_Months/12,0),0,IF(R$38=1,R$42+R$44,MIN(R$42+R$44,IF(($D$7-ROUNDUP(RM_IO_Months/12,0))<=0,R$42+R$44,$D$5/($D$7-ROUNDUP(RM_IO_Months/12,0)))))),0),0))) -> 0 | S45: =IF(S$37=0,0,IF(OR($D$9="Bullet",$D$9="Interest-only"),IF($D$9="Bullet",IF(S$38=1,S$42+S$44,0),0),IF(OR($D$9="Amortising",$D$9="Amortizing"),IF(S$37=1,IF((COLUMNS($H45:S45)-MATCH($D$8,$H$34:$S$34,0)+1)<=ROUNDUP(RM_IO_Months/12,0),0,IF(S$38=1,S$42+S$44,MIN(S$42+S$44,IF(($D$7-ROUNDUP(RM_IO_Months/12,0))<=0,S$42+S$44,$D$5/($D$7-ROUNDUP(RM_IO_Months/12,0)))))),0),0))) -> 0
B46: Interest paid | H46: =IF(H$37=0,0,((H$42+H$47)/2)*$D$7) -> 0 | I46: =IF(I$37=0,0,((I$42+I$47)/2)*$D$7) -> 0 | J46: =IF(J37=0,0,((J42+J47)/2)*$D$7) -> 0 | K46: =IF(K37=0,0,((K42+K47)/2)*$D$7) -> 0 | L46: =IF(L37=0,0,((L42+L47)/2)*$D$7) -> 0 | M46: =IF(M37=0,0,((M42+M47)/2)*$D$7) -> 0 | N46: =IF(N37=0,0,((N42+N47)/2)*$D$7) -> 0 | O46: =IF(O$37=0,0,((O$42+O$47)/2)*$D$7) -> 0 | P46: =IF(P$37=0,0,((P$42+P$47)/2)*$D$7) -> 0 | Q46: =IF(Q$37=0,0,((Q$42+Q$47)/2)*$D$7) -> 0 | R46: =IF(R$37=0,0,((R$42+R$47)/2)*$D$7) -> 0 | S46: =IF(S$37=0,0,((S$42+S$47)/2)*$D$7) -> 0
B47: Closing balance | H47: =IF(H$37=0,0,MAX(0,H$42+H$44-H$45)) -> 0 | I47: =IF(I$37=0,0,MAX(0,I$42+I$44-I$45)) -> 0 | J47: =IF(J37=0,0,J42+J44-J45) -> 0 | K47: =IF(K37=0,0,K42+K44-K45) -> 0 | L47: =IF(L37=0,0,L42+L44-L45) -> 0 | M47: =IF(M37=0,0,M42+M44-M45) -> 0 | N47: =IF(N37=0,0,N42+N44-N45) -> 0 | O47: =IF(O37=0,0,MAX(0,ROUND(O42+O44-O45,2))) -> 0 | P47: =IF(P$37=0,0,MAX(0,P$42+P$44-P$45)) -> 0 | Q47: =IF(Q$37=0,0,MAX(0,Q$42+Q$44-Q$45)) -> 0 | R47: =IF(R$37=0,0,MAX(0,R$42+R$44-R$45)) -> 0 | S47: =IF(S$37=0,0,MAX(0,S$42+S$44-S$45)) -> 0
B48: Total borrowings (closing balance) | H48: =H$24+H$47 -> 0 | I48: =I$24+I$47 -> 0 | J48: =J$24+J$47 -> 9220500 | K48: =K$24+K$47 -> 8196000 | L48: =L$24+L$47 -> 7171500 | M48: =M$24+M$47 -> 6147000 | N48: =N$24+N$47 -> 5122500 | O48: =O$24+O$47 -> 4098000 | ... S48: =S$24+S$47 -> 0
B49: Total current borrowings (next 12 months) | H49: =H$25+H$51 -> 0 | I49: =I$25+I$51 -> 0 | J49: =J$25+J$51 -> 1024500 | K49: =K$25+K$51 -> 1024500 | L49: =L$25+L$51 -> 1024500 | M49: =M$25+M$51 -> 1024500 | N49: =N$25+N$51 -> 1024500 | O49: =O$25+O$51 -> 1024500 | ... S49: =S$25+S$51 -> 0
B50: Total non-current borrowings | H50: =MAX(0,H$48-H$49) -> 0 | I50: =MAX(0,I$48-I$49) -> 0 | J50: =MAX(0,J$48-J$49) -> 8196000 | K50: =MAX(0,K$48-K$49) -> 7171500 | L50: =MAX(0,L$48-L$49) -> 6147000 | M50: =MAX(0,M$48-M$49) -> 5122500 | N50: =MAX(0,N$48-N$49) -> 4098000 | O50: =MAX(0,O$48-O$49) -> 3073500 | ... S50: =MAX(0,S$48-S$49) -> 0
B51: Current portion – PE (next 12 months) | H51: =IF(H$37=0,0,IF(H$47=0,0,IF(H$38=1,0,MIN(H$47,IFERROR(INDEX($H$45:$S$45,COLUMNS($H51:H51)+1),0))))) -> 0 | I51: =IF(I$37=0,0,IF(I$47=0,0,IF(I$38=1,0,MIN(I$47,IFERROR(INDEX($H$45:$S$45,COLUMNS($H51:I51)+1),0))))) -> 0 | J51: =IF(J$37=0,0,IF(J$47=0,0,IF(J$38=1,0,MIN(J$47,IFERROR(INDEX($H$45:$S$45,COLUMNS($H51:J51)+1),0))))) -> 0 | K51: =IF(K$37=0,0,IF(K$47=0,0,IF(K$38=1,0,MIN(K$47,IFERROR(INDEX($H$45:$S$45,COLUMNS($H51:K51)+1),0))))) -> 0 | L51: =IF(L$37=0,0,IF(L$47=0,0,IF(L$38=1,0,MIN(L$47,IFERROR(INDEX($H$45:$S$45,COLUMNS($H51:L51)+1),0))))) -> 0 | M51: =IF(M$37=0,0,IF(M$47=0,0,IF(M$38=1,0,MIN(M$47,IFERROR(INDEX($H$45:$S$45,COLUMNS($H51:M51)+1),0))))) -> 0 | N51: =IF(N$37=0,0,IF(N$47=0,0,IF(N$38=1,0,MIN(N$47,IFERROR(INDEX($H$45:$S$45,COLUMNS($H51:N51)+1),0))))) -> 0 | O51: =IF(O$37=0,0,IF(O$47=0,0,IF(O$38=1,0,MIN(O$47,IFERROR(INDEX($H$45:$S$45,COLUMNS($H51:O51)+1),0))))) -> 0 | ... S51: =IF(S$37=0,0,IF(S$47=0,0,IF(S$38=1,0,MIN(S$47,IFERROR(INDEX($H$45:$S$45,COLUMNS($H51:S51)+1),0))))) -> 0
B54: Summary
B55: Drawdowns – total | H55: =H$20+H$44 -> 0 | I55: =I$20+I$44 -> 0 | J55: =J$20+J$44 -> 10245000 | K55: =K$20+K$44 -> 0 | L55: =L$20+L$44 -> 0 | M55: =M$20+M$44 -> 0 | N55: =N$20+N$44 -> 0 | O55: =O$20+O$44 -> 0 | ... S55: =S$20+S$44 -> 0
B56: Principal repaid – total | H56: =H$21+H$45 -> 0 | I56: =I$21+I$45 -> 0 | J56: =J$21+J$45 -> 1024500 | K56: =K$21+K$45 -> 1024500 | L56: =L$21+L$45 -> 1024500 | M56: =M$21+M$45 -> 1024500 | N56: =N$21+N$45 -> 1024500 | O56: =O$21+O$45 -> 1024500 | ... S56: =S$21+S$45 -> 1024500
B57: Interest paid – total | H57: =H$22+H$46 -> 0 | I57: =I$22+I$46 -> 0 | J57: =J$22+J$46 -> 368820 | K57: =K$22+K$46 -> 696660 | L57: =L$22+L$46 -> 614700 | M57: =M$22+M$46 -> 532740 | N57: =N$22+N$46 -> 450780 | O57: =O$22+O$46 -> 368820 | ... S57: =S$22+S$46 -> 40980
B58: Debt service (principal + interest) – total (cash) | H58: =H56+H57 -> 0 | I58: =I56+I57 -> 0 | J58: =J56+J57 -> 1393320 | K58: =K56+K57 -> 1721160 | L58: =L56+L57 -> 1639200 | M58: =M56+M57 -> 1557240 | N58: =N56+N57 -> 1475280 | O58: =O56+O57 -> 1393320 | ... S58: =S56+S57 -> 1065480

Sheet Revenue Assumptions
A1: REVENUE ASSUMPTIONS
B4: VHA Fee | D4: Capacity
B5: 1 | C5: Music GA | D5: =Inputs!$E$127 -> 5000
B6: 2 | C6: Music GA | D6: =Inputs!$E$128 -> 3000
B7: 3 | C7: Music GA | D7: =Inputs!$E$129 -> 1500
B8: 4 | C8: EDM | D8: =Inputs!$E$130 -> 3500
B9: 5 | C9: Music (Seated) | D9: =Inputs!$E$131 -> 3500
B10: 6 | C10: Comedy (Seated) | D10: =Inputs!$E$132 -> 3500
B11: 7 | C11: Sports | D11: =Inputs!$E$133 -> 3500
B12: 8 | C12: MICE | D12: =Inputs!$E$134 -> 3500
B13: 9 | C13: Community | D13: =Inputs!$E$135 -> 2000
B14: 10 | C14: Live Site | D14: =Inputs!$E$136 -> 2000
B15: 11 | C15: Farmers Market | D15: =Inputs!$E$137 -> 4000
E18: FY | F18: ='P&L'!J6 -> FY27 | G18: ='P&L'!K6 -> FY28 | H18: ='P&L'!L6 -> FY29 | I18: ='P&L'!M6 -> FY30 | J18: ='P&L'!N6 -> FY31 | K18: ='P&L'!O6 -> FY32 | L18: ='P&L'!P6 -> FY33 | M18: ='P&L'!Q6 -> FY34 | ... O18: ='P&L'!S6 -> FY36
B19: AVERAGE TICKET PRICE | D19: Capacity | F19: 2027 | G19: =F19+1 -> 2028 | H19: =G19+1 -> 2029 | I19: =H19+1 -> 2030 | J19: =I19+1 -> 2031 | K19: =J19+1 -> 2032 | L19: =K19+1 -> 2033 | M19: =L19+1 -> 2034 | N19: =M19+1 -> 2035 | O19: =N19+1 -> 2036
F20: =INDEX('P&L'!$H$8:$S$8,MATCH(F$18,'P&L'!$H$6:$S$6,0)) -> 0 | G20: =INDEX('P&L'!$H$8:$S$8,MATCH(G$18,'P&L'!$H$6:$S$6,0)) -> 1 | H20: =INDEX('P&L'!$H$8:$S$8,MATCH(H$18,'P&L'!$H$6:$S$6,0)) -> 1 | I20: =INDEX('P&L'!$H$8:$S$8,MATCH(I$18,'P&L'!$H$6:$S$6,0)) -> 1 | J20: =INDEX('P&L'!$H$8:$S$8,MATCH(J$18,'P&L'!$H$6:$S$6,0)) -> 1 | K20: =INDEX('P&L'!$H$8:$S$8,MATCH(K$18,'P&L'!$H$6:$S$6,0)) -> 1 | L20: =INDEX('P&L'!$H$8:$S$8,MATCH(L$18,'P&L'!$H$6:$S$6,0)) -> 1 | M20: =INDEX('P&L'!$H$8:$S$8,MATCH(M$18,'P&L'!$H$6:$S$6,0)) -> 1 | ... O20: =INDEX('P&L'!$H$8:$S$8,MATCH(O$18,'P&L'!$H$6:$S$6,0)) -> 1
B22: 1 | C22: Music GA | D22: =Inputs!$E$127 -> 5000 | F22: 100 | G22: =F22*(1+Inputs!$E$152) -> 103 | H22: =G22*(1+Inputs!$E$152) -> 106.09 | I22: =H22*(1+Inputs!$E$152) -> 109.2727 | J22: =I22*(1+Inputs!$E$152) -> 112.55088 | K22: =J22*(1+Inputs!$E$152) -> 115.92741 | L22: =K22*(1+Inputs!$E$152) -> 119.40523 | M22: =L22*(1+Inputs!$E$152) -> 122.98739 | N22: =M22*(1+Inputs!$E$152) -> 126.67701 | O22: =N22*(1+Inputs!$E$152) -> 130.47732
B23: 2 | C23: Music GA | D23: =Inputs!$E$128 -> 3000 | F23: 100 | G23: =F23*(1+Inputs!$E$152) -> 103 | H23: =G23*(1+Inputs!$E$152) -> 106.09 | I23: =H23*(1+Inputs!$E$152) -> 109.2727 | J23: =I23*(1+Inputs!$E$152) -> 112.55088 | K23: =J23*(1+Inputs!$E$152) -> 115.92741 | L23: =K23*(1+Inputs!$E$152) -> 119.40523 | M23: =L23*(1+Inputs!$E$152) -> 122.98739 | N23: =M23*(1+Inputs!$E$152) -> 126.67701 | O23: =N23*(1+Inputs!$E$152) -> 130.47732
B24: 3 | C24: Music GA | D24: =Inputs!$E$129 -> 1500 | F24: 85 | G24: =F24*(1+Inputs!$E$152) -> 87.55 | H24: =G24*(1+Inputs!$E$152) -> 90.1765 | I24: =H24*(1+Inputs!$E$152) -> 92.881795 | J24: =I24*(1+Inputs!$E$152) -> 95.668249 | K24: =J24*(1+Inputs!$E$152) -> 98.538296 | L24: =K24*(1+Inputs!$E$152) -> 101.49445 | M24: =L24*(1+Inputs!$E$152) -> 104.53928 | N24: =M24*(1+Inputs!$E$152) -> 107.67546 | O24: =N24*(1+Inputs!$E$152) -> 110.90572
B25: 4 | C25: EDM | D25: =Inputs!$E$130 -> 3500 | F25: 120 | G25: =F25*(1+Inputs!$E$152) -> 123.6 | H25: =G25*(1+Inputs!$E$152) -> 127.308 | I25: =H25*(1+Inputs!$E$152) -> 131.12724 | J25: =I25*(1+Inputs!$E$152) -> 135.06106 | K25: =J25*(1+Inputs!$E$152) -> 139.11289 | L25: =K25*(1+Inputs!$E$152) -> 143.28628 | M25: =L25*(1+Inputs!$E$152) -> 147.58486 | N25: =M25*(1+Inputs!$E$152) -> 152.01241 | O25: =N25*(1+Inputs!$E$152) -> 156.57278
B26: 5 | C26: Music (Seated) | D26: =Inputs!$E$131 -> 3500 | F26: 100 | G26: =F26*(1+Inputs!$E$152) -> 103 | H26: =G26*(1+Inputs!$E$152) -> 106.09 | I26: =H26*(1+Inputs!$E$152) -> 109.2727 | J26: =I26*(1+Inputs!$E$152) -> 112.55088 | K26: =J26*(1+Inputs!$E$152) -> 115.92741 | L26: =K26*(1+Inputs!$E$152) -> 119.40523 | M26: =L26*(1+Inputs!$E$152) -> 122.98739 | N26: =M26*(1+Inputs!$E$152) -> 126.67701 | O26: =N26*(1+Inputs!$E$152) -> 130.47732
B27: 6 | C27: Comedy (Seated) | D27: =Inputs!$E$132 -> 3500 | F27: 100 | G27: =F27*(1+Inputs!$E$152) -> 103 | H27: =G27*(1+Inputs!$E$152) -> 106.09 | I27: =H27*(1+Inputs!$E$152) -> 109.2727 | J27: =I27*(1+Inputs!$E$152) -> 112.55088 | K27: =J27*(1+Inputs!$E$152) -> 115.92741 | L27: =K27*(1+Inputs!$E$152) -> 119.40523 | M27: =L27*(1+Inputs!$E$152) -> 122.98739 | N27: =M27*(1+Inputs!$E$152) -> 126.67701 | O27: =N27*(1+Inputs!$E$152) -> 130.47732
B28: 7 | C28: Sports | D28: =Inputs!$E$133 -> 3500 | F28: 110 | G28: =F28*(1+Inputs!$E$152) -> 113.3 | H28: =G28*(1+Inputs!$E$152) -> 116.699 | I28: =H28*(1+Inputs!$E$152) -> 120.19997 | J28: =I28*(1+Inputs!$E$152) -> 123.80597 | K28: =J28*(1+Inputs!$E$152) -> 127.52015 | L28: =K28*(1+Inputs!$E$152) -> 131.34575 | M28: =L28*(1+Inputs!$E$152) -> 135.28613 | N28: =M28*(1+Inputs!$E$152) -> 139.34471 | O28: =N28*(1+Inputs!$E$152) -> 143.52505
B29: 8 | C29: MICE | D29: =Inputs!$E$134 -> 3500 | F29: =0 -> 0 | G29: =F29*(1+Inputs!$E$152) -> 0 | H29: =G29*(1+Inputs!$E$152) -> 0 | I29: =H29*(1+Inputs!$E$152) -> 0 | J29: =I29*(1+Inputs!$E$152) -> 0 | K29: =J29*(1+Inputs!$E$152) -> 0 | L29: =K29*(1+Inputs!$E$152) -> 0 | M29: =L29*(1+Inputs!$E$152) -> 0 | N29: =M29*(1+Inputs!$E$152) -> 0 | O29: =N29*(1+Inputs!$E$152) -> 0
B30: 9 | C30: Community | D30: =Inputs!$E$135 -> 2000 | F30: =0 -> 0 | G30: =F30*(1+Inputs!$E$152) -> 0 | H30: =G30*(1+Inputs!$E$152) -> 0 | I30: =H30*(1+Inputs!$E$152) -> 0 | J30: =I30*(1+Inputs!$E$152) -> 0 | K30: =J30*(1+Inputs!$E$152) -> 0 | L30: =K30*(1+Inputs!$E$152) -> 0 | M30: =L30*(1+Inputs!$E$152) -> 0 | N30: =M30*(1+Inputs!$E$152) -> 0 | O30: =N30*(1+Inputs!$E$152) -> 0
B31: 10 | C31: Live Site | D31: =Inputs!$E$136 -> 2000 | F31: =0 -> 0 | G31: =F31*(1+Inputs!$E$152) -> 0 | H31: =G31*(1+Inputs!$E$152) -> 0 | I31: =H31*(1+Inputs!$E$152) -> 0 | J31: =I31*(1+Inputs!$E$152) -> 0 | K31: =J31*(1+Inputs!$E$152) -> 0 | L31: =K31*(1+Inputs!$E$152) -> 0 | M31: =L31*(1+Inputs!$E$152) -> 0 | N31: =M31*(1+Inputs!$E$152) -> 0 | O31: =N31*(1+Inputs!$E$152) -> 0
B32: 11 | C32: Farmers Market | D32: =Inputs!$E$137 -> 4000 | F32: =0 -> 0 | G32: =F32*(1+Inputs!$E$152) -> 0 | H32: =G32*(1+Inputs!$E$152) -> 0 | I32: =H32*(1+Inputs!$E$152) -> 0 | J32: =I32*(1+Inputs!$E$152) -> 0 | K32: =J32*(1+Inputs!$E$152) -> 0 | L32: =K32*(1+Inputs!$E$152) -> 0 | M32: =L32*(1+Inputs!$E$152) -> 0 | N32: =M32*(1+Inputs!$E$152) -> 0 | O32: =N32*(1+Inputs!$E$152) -> 0
E34: FY | F34: ='P&L'!J6 -> FY27 | G34: ='P&L'!K6 -> FY28 | H34: ='P&L'!L6 -> FY29 | I34: ='P&L'!M6 -> FY30 | J34: ='P&L'!N6 -> FY31 | K34: ='P&L'!O6 -> FY32 | L34: ='P&L'!P6 -> FY33 | M34: ='P&L'!Q6 -> FY34 | ... O34: ='P&L'!S6 -> FY36
B35: GBO VHA PER EVENT | D35: Capacity | F35: =F19 -> 2027 | G35: =G19 -> 2028 | H35: =H19 -> 2029 | I35: =I19 -> 2030 | J35: =J19 -> 2031 | K35: =K19 -> 2032 | L35: =L19 -> 2033 | M35: =M19 -> 2034 | ... O35: =O19 -> 2036
B37: 1 | C37: Music GA | D37: =Inputs!$E$127 -> 5000 | F37: =F22*$D22*'Calendar Assumptions'!$E$41*RM_VHA_GBO_Fee -> 52000 | G37: =G22*$D22*'Calendar Assumptions'!$E$41*RM_VHA_GBO_Fee -> 53560 | H37: =H22*$D22*'Calendar Assumptions'!$E$41*RM_VHA_GBO_Fee -> 55166.8 | I37: =I22*$D22*'Calendar Assumptions'!$E$41*RM_VHA_GBO_Fee -> 56821.804 | J37: =J22*$D22*'Calendar Assumptions'!$E$41*RM_VHA_GBO_Fee -> 58526.458 | K37: =K22*$D22*'Calendar Assumptions'!$E$41*RM_VHA_GBO_Fee -> 60282.252 | L37: =L22*$D22*'Calendar Assumptions'!$E$41*RM_VHA_GBO_Fee -> 62090.719 | M37: =M22*$D22*'Calendar Assumptions'!$E$41*RM_VHA_GBO_Fee -> 63953.441 | ... O37: =O22*$D22*'Calendar Assumptions'!$E$41*RM_VHA_GBO_Fee -> 67848.206
B38: 2 | C38: Music GA | D38: =Inputs!$E$128 -> 3000 | F38: =F23*$D23*'Calendar Assumptions'!$E$42*RM_VHA_GBO_Fee -> 31200 | G38: =G23*$D23*'Calendar Assumptions'!$E$42*RM_VHA_GBO_Fee -> 32136 | H38: =H23*$D23*'Calendar Assumptions'!$E$42*RM_VHA_GBO_Fee -> 33100.08 | I38: =I23*$D23*'Calendar Assumptions'!$E$42*RM_VHA_GBO_Fee -> 34093.082 | J38: =J23*$D23*'Calendar Assumptions'!$E$42*RM_VHA_GBO_Fee -> 35115.875 | K38: =K23*$D23*'Calendar Assumptions'!$E$42*RM_VHA_GBO_Fee -> 36169.351 | L38: =L23*$D23*'Calendar Assumptions'!$E$42*RM_VHA_GBO_Fee -> 37254.432 | M38: =M23*$D23*'Calendar Assumptions'!$E$42*RM_VHA_GBO_Fee -> 38372.065 | ... O38: =O23*$D23*'Calendar Assumptions'!$E$42*RM_VHA_GBO_Fee -> 40708.923
B39: 3 | C39: Music GA | D39: =Inputs!$E$129 -> 1500 | F39: =F24*$D24*'Calendar Assumptions'!$E$43*RM_VHA_GBO_Fee -> 14917.5 | G39: =G24*$D24*'Calendar Assumptions'!$E$43*RM_VHA_GBO_Fee -> 15365.025 | H39: =H24*$D24*'Calendar Assumptions'!$E$43*RM_VHA_GBO_Fee -> 15825.976 | I39: =I24*$D24*'Calendar Assumptions'!$E$43*RM_VHA_GBO_Fee -> 16300.755 | J39: =J24*$D24*'Calendar Assumptions'!$E$43*RM_VHA_GBO_Fee -> 16789.778 | K39: =K24*$D24*'Calendar Assumptions'!$E$43*RM_VHA_GBO_Fee -> 17293.471 | L39: =L24*$D24*'Calendar Assumptions'!$E$43*RM_VHA_GBO_Fee -> 17812.275 | M39: =M24*$D24*'Calendar Assumptions'!$E$43*RM_VHA_GBO_Fee -> 18346.643 | ... O39: =O24*$D24*'Calendar Assumptions'!$E$43*RM_VHA_GBO_Fee -> 19463.954
B40: 4 | C40: EDM | D40: =Inputs!$E$130 -> 3500 | F40: =F25*$D25*'Calendar Assumptions'!$E$44*RM_VHA_GBO_Fee -> 49140 | G40: =G25*$D25*'Calendar Assumptions'!$E$44*RM_VHA_GBO_Fee -> 50614.2 | H40: =H25*$D25*'Calendar Assumptions'!$E$44*RM_VHA_GBO_Fee -> 52132.626 | I40: =I25*$D25*'Calendar Assumptions'!$E$44*RM_VHA_GBO_Fee -> 53696.605 | J40: =J25*$D25*'Calendar Assumptions'!$E$44*RM_VHA_GBO_Fee -> 55307.503 | K40: =K25*$D25*'Calendar Assumptions'!$E$44*RM_VHA_GBO_Fee -> 56966.728 | L40: =L25*$D25*'Calendar Assumptions'!$E$44*RM_VHA_GBO_Fee -> 58675.73 | M40: =M25*$D25*'Calendar Assumptions'!$E$44*RM_VHA_GBO_Fee -> 60436.002 | ... O40: =O25*$D25*'Calendar Assumptions'!$E$44*RM_VHA_GBO_Fee -> 64116.554
B41: 5 | C41: Music (Seated) | D41: =Inputs!$E$131 -> 3500 | F41: =F26*$D26*'Calendar Assumptions'!$E$45*RM_VHA_GBO_Fee -> 40950 | G41: =G26*$D26*'Calendar Assumptions'!$E$45*RM_VHA_GBO_Fee -> 42178.5 | H41: =H26*$D26*'Calendar Assumptions'!$E$45*RM_VHA_GBO_Fee -> 43443.855 | I41: =I26*$D26*'Calendar Assumptions'!$E$45*RM_VHA_GBO_Fee -> 44747.171 | J41: =J26*$D26*'Calendar Assumptions'!$E$45*RM_VHA_GBO_Fee -> 46089.586 | K41: =K26*$D26*'Calendar Assumptions'!$E$45*RM_VHA_GBO_Fee -> 47472.273 | L41: =L26*$D26*'Calendar Assumptions'!$E$45*RM_VHA_GBO_Fee -> 48896.442 | M41: =M26*$D26*'Calendar Assumptions'!$E$45*RM_VHA_GBO_Fee -> 50363.335 | ... O41: =O26*$D26*'Calendar Assumptions'!$E$45*RM_VHA_GBO_Fee -> 53430.462
B42: 6 | C42: Comedy (Seated) | D42: =Inputs!$E$132 -> 3500 | F42: =F27*$D27*'Calendar Assumptions'!$E$46*RM_VHA_GBO_Fee -> 40950 | G42: =G27*$D27*'Calendar Assumptions'!$E$46*RM_VHA_GBO_Fee -> 42178.5 | H42: =H27*$D27*'Calendar Assumptions'!$E$46*RM_VHA_GBO_Fee -> 43443.855 | I42: =I27*$D27*'Calendar Assumptions'!$E$46*RM_VHA_GBO_Fee -> 44747.171 | J42: =J27*$D27*'Calendar Assumptions'!$E$46*RM_VHA_GBO_Fee -> 46089.586 | K42: =K27*$D27*'Calendar Assumptions'!$E$46*RM_VHA_GBO_Fee -> 47472.273 | L42: =L27*$D27*'Calendar Assumptions'!$E$46*RM_VHA_GBO_Fee -> 48896.442 | M42: =M27*$D27*'Calendar Assumptions'!$E$46*RM_VHA_GBO_Fee -> 50363.335 | ... O42: =O27*$D27*'Calendar Assumptions'!$E$46*RM_VHA_GBO_Fee -> 53430.462
B43: 7 | C43: Sports | D43: =Inputs!$E$133 -> 3500 | F43: =F28*$D28*'Calendar Assumptions'!$E$47*RM_VHA_GBO_Fee -> 40040 | G43: =G28*$D28*'Calendar Assumptions'!$E$47*RM_VHA_GBO_Fee -> 41241.2 | H43: =H28*$D28*'Calendar Assumptions'!$E$47*RM_VHA_GBO_Fee -> 42478.436 | I43: =I28*$D28*'Calendar Assumptions'!$E$47*RM_VHA_GBO_Fee -> 43752.789 | J43: =J28*$D28*'Calendar Assumptions'!$E$47*RM_VHA_GBO_Fee -> 45065.373 | K43: =K28*$D28*'Calendar Assumptions'!$E$47*RM_VHA_GBO_Fee -> 46417.334 | L43: =L28*$D28*'Calendar Assumptions'!$E$47*RM_VHA_GBO_Fee -> 47809.854 | M43: =M28*$D28*'Calendar Assumptions'!$E$47*RM_VHA_GBO_Fee -> 49244.15 | ... O43: =O28*$D28*'Calendar Assumptions'!$E$47*RM_VHA_GBO_Fee -> 52243.118
B44: 8 | C44: MICE | D44: =Inputs!$E$134 -> 3500 | F44: =F29*$D29*'Calendar Assumptions'!$E$48*RM_VHA_GBO_Fee -> 0 | G44: =G29*$D29*'Calendar Assumptions'!$E$48*RM_VHA_GBO_Fee -> 0 | H44: =H29*$D29*'Calendar Assumptions'!$E$48*RM_VHA_GBO_Fee -> 0 | I44: =I29*$D29*'Calendar Assumptions'!$E$48*RM_VHA_GBO_Fee -> 0 | J44: =J29*$D29*'Calendar Assumptions'!$E$48*RM_VHA_GBO_Fee -> 0 | K44: =K29*$D29*'Calendar Assumptions'!$E$48*RM_VHA_GBO_Fee -> 0 | L44: =L29*$D29*'Calendar Assumptions'!$E$48*RM_VHA_GBO_Fee -> 0 | M44: =M29*$D29*'Calendar Assumptions'!$E$48*RM_VHA_GBO_Fee -> 0 | ... O44: =O29*$D29*'Calendar Assumptions'!$E$48*RM_VHA_GBO_Fee -> 0
B45: 9 | C45: Community | D45: =Inputs!$E$135 -> 2000 | F45: =F30*$D30*'Calendar Assumptions'!$E$49*RM_VHA_GBO_Fee -> 0 | G45: =G30*$D30*'Calendar Assumptions'!$E$49*RM_VHA_GBO_Fee -> 0 | H45: =H30*$D30*'Calendar Assumptions'!$E$49*RM_VHA_GBO_Fee -> 0 | I45: =I30*$D30*'Calendar Assumptions'!$E$49*RM_VHA_GBO_Fee -> 0 | J45: =J30*$D30*'Calendar Assumptions'!$E$49*RM_VHA_GBO_Fee -> 0 | K45: =K30*$D30*'Calendar Assumptions'!$E$49*RM_VHA_GBO_Fee -> 0 | L45: =L30*$D30*'Calendar Assumptions'!$E$49*RM_VHA_GBO_Fee -> 0 | M45: =M30*$D30*'Calendar Assumptions'!$E$49*RM_VHA_GBO_Fee -> 0 | ... O45: =O30*$D30*'Calendar Assumptions'!$E$49*RM_VHA_GBO_Fee -> 0
B46: 10 | C46: Live Site | D46: =Inputs!$E$136 -> 2000 | F46: =F31*$D31*'Calendar Assumptions'!$E$50*RM_VHA_GBO_Fee -> 0 | G46: =G31*$D31*'Calendar Assumptions'!$E$50*RM_VHA_GBO_Fee -> 0 | H46: =H31*$D31*'Calendar Assumptions'!$E$50*RM_VHA_GBO_Fee -> 0 | I46: =I31*$D31*'Calendar Assumptions'!$E$50*RM_VHA_GBO_Fee -> 0 | J46: =J31*$D31*'Calendar Assumptions'!$E$50*RM_VHA_GBO_Fee -> 0 | K46: =K31*$D31*'Calendar Assumptions'!$E$50*RM_VHA_GBO_Fee -> 0 | L46: =L31*$D31*'Calendar Assumptions'!$E$50*RM_VHA_GBO_Fee -> 0 | M46: =M31*$D31*'Calendar Assumptions'!$E$50*RM_VHA_GBO_Fee -> 0 | ... O46: =O31*$D31*'Calendar Assumptions'!$E$50*RM_VHA_GBO_Fee -> 0
B47: 11 | C47: Farmers Market | D47: =Inputs!$E$137 -> 4000 | F47: =F32*$D32*'Calendar Assumptions'!$E$51*RM_VHA_GBO_Fee -> 0 | G47: =G32*$D32*'Calendar Assumptions'!$E$51*RM_VHA_GBO_Fee -> 0 | H47: =H32*$D32*'Calendar Assumptions'!$E$51*RM_VHA_GBO_Fee -> 0 | I47: =I32*$D32*'Calendar Assumptions'!$E$51*RM_VHA_GBO_Fee -> 0 | J47: =J32*$D32*'Calendar Assumptions'!$E$51*RM_VHA_GBO_Fee -> 0 | K47: =K32*$D32*'Calendar Assumptions'!$E$51*RM_VHA_GBO_Fee -> 0 | L47: =L32*$D32*'Calendar Assumptions'!$E$51*RM_VHA_GBO_Fee -> 0 | M47: =M32*$D32*'Calendar Assumptions'!$E$51*RM_VHA_GBO_Fee -> 0 | ... O47: =O32*$D32*'Calendar Assumptions'!$E$51*RM_VHA_GBO_Fee -> 0
B49: ANNUAL GBO VHA | D49: Capacity | F49: =F34 -> FY27 | G49: =G34 -> FY28 | H49: =H34 -> FY29 | I49: =I34 -> FY30 | J49: =J34 -> FY31 | K49: =K34 -> FY32 | L49: =L34 -> FY33 | M49: =M34 -> FY34 | ... O49: =O34 -> FY36
B51: 1 | C51: Music GA | D51: =Inputs!$E$127 -> 5000 | F51: =F$20*F22*'Calendar Assumptions'!F41*RM_VHA_GBO_Fee -> 0 | G51: =G$20*G22*'Calendar Assumptions'!G41*RM_VHA_GBO_Fee -> 910787.8 | H51: =H$20*H22*'Calendar Assumptions'!H41*RM_VHA_GBO_Fee -> 977941.86 | I51: =I$20*I22*'Calendar Assumptions'!I41*RM_VHA_GBO_Fee -> 1079614.3 | J51: =J$20*J22*'Calendar Assumptions'!J41*RM_VHA_GBO_Fee -> 1112002.7 | K51: =K$20*K22*'Calendar Assumptions'!K41*RM_VHA_GBO_Fee -> 1145362.8 | L51: =L$20*L22*'Calendar Assumptions'!L41*RM_VHA_GBO_Fee -> 1179723.7 | M51: =M$20*M22*'Calendar Assumptions'!M41*RM_VHA_GBO_Fee -> 1215115.4 | ... O51: =O$20*O22*'Calendar Assumptions'!O41*RM_VHA_GBO_Fee -> 1289115.9
B52: 2 | C52: Music GA | D52: =Inputs!$E$128 -> 3000 | F52: =F$20*F23*'Calendar Assumptions'!F42*RM_VHA_GBO_Fee -> 0 | G52: =G$20*G23*'Calendar Assumptions'!G42*RM_VHA_GBO_Fee -> 528701.47 | H52: =H$20*H23*'Calendar Assumptions'!H42*RM_VHA_GBO_Fee -> 555882.74 | I52: =I$20*I23*'Calendar Assumptions'!I42*RM_VHA_GBO_Fee -> 613675.48 | J52: =J$20*J23*'Calendar Assumptions'!J42*RM_VHA_GBO_Fee -> 632085.75 | K52: =K$20*K23*'Calendar Assumptions'!K42*RM_VHA_GBO_Fee -> 651048.32 | L52: =L$20*L23*'Calendar Assumptions'!L42*RM_VHA_GBO_Fee -> 670579.77 | M52: =M$20*M23*'Calendar Assumptions'!M42*RM_VHA_GBO_Fee -> 690697.16 | ... O52: =O$20*O23*'Calendar Assumptions'!O42*RM_VHA_GBO_Fee -> 732760.62
B53: 3 | C53: Music GA | D53: =Inputs!$E$129 -> 1500 | F53: =F$20*F24*'Calendar Assumptions'!F43*RM_VHA_GBO_Fee -> 0 | G53: =G$20*G24*'Calendar Assumptions'!G43*RM_VHA_GBO_Fee -> 210654.49 | H53: =H$20*H24*'Calendar Assumptions'!H43*RM_VHA_GBO_Fee -> 221484.53 | I53: =I$20*I24*'Calendar Assumptions'!I43*RM_VHA_GBO_Fee -> 244511.33 | J53: =J$20*J24*'Calendar Assumptions'!J43*RM_VHA_GBO_Fee -> 251846.67 | K53: =K$20*K24*'Calendar Assumptions'!K43*RM_VHA_GBO_Fee -> 259402.07 | L53: =L$20*L24*'Calendar Assumptions'!L43*RM_VHA_GBO_Fee -> 267184.13 | M53: =M$20*M24*'Calendar Assumptions'!M43*RM_VHA_GBO_Fee -> 275199.65 | ... O53: =O$20*O24*'Calendar Assumptions'!O43*RM_VHA_GBO_Fee -> 291959.31
B54: 4 | C54: EDM | D54: =Inputs!$E$130 -> 3500 | F54: =F$20*F25*'Calendar Assumptions'!F44*RM_VHA_GBO_Fee -> 0 | G54: =G$20*G25*'Calendar Assumptions'!G44*RM_VHA_GBO_Fee -> 832704.82 | H54: =H$20*H25*'Calendar Assumptions'!H44*RM_VHA_GBO_Fee -> 875515.32 | I54: =I$20*I25*'Calendar Assumptions'!I44*RM_VHA_GBO_Fee -> 966538.89 | J54: =J$20*J25*'Calendar Assumptions'!J44*RM_VHA_GBO_Fee -> 995535.05 | K54: =K$20*K25*'Calendar Assumptions'!K44*RM_VHA_GBO_Fee -> 1025401.1 | L54: =L$20*L25*'Calendar Assumptions'!L44*RM_VHA_GBO_Fee -> 1056163.1 | M54: =M$20*M25*'Calendar Assumptions'!M44*RM_VHA_GBO_Fee -> 1087848 | ... O54: =O$20*O25*'Calendar Assumptions'!O44*RM_VHA_GBO_Fee -> 1154098
B55: 5 | C55: Music (Seated) | D55: =Inputs!$E$131 -> 3500 | F55: =F$20*F26*'Calendar Assumptions'!F45*RM_VHA_GBO_Fee -> 0 | G55: =G$20*G26*'Calendar Assumptions'!G45*RM_VHA_GBO_Fee -> 578267.23 | H55: =H$20*H26*'Calendar Assumptions'!H45*RM_VHA_GBO_Fee -> 607996.75 | I55: =I$20*I26*'Calendar Assumptions'!I45*RM_VHA_GBO_Fee -> 671207.56 | J55: =J$20*J26*'Calendar Assumptions'!J45*RM_VHA_GBO_Fee -> 691343.79 | K55: =K$20*K26*'Calendar Assumptions'!K45*RM_VHA_GBO_Fee -> 712084.1 | L55: =L$20*L26*'Calendar Assumptions'!L45*RM_VHA_GBO_Fee -> 733446.62 | M55: =M$20*M26*'Calendar Assumptions'!M45*RM_VHA_GBO_Fee -> 755450.02 | ... O55: =O$20*O26*'Calendar Assumptions'!O45*RM_VHA_GBO_Fee -> 801456.93
B56: 6 | C56: Comedy (Seated) | D56: =Inputs!$E$132 -> 3500 | F56: =F$20*F27*'Calendar Assumptions'!F46*RM_VHA_GBO_Fee -> 0 | G56: =G$20*G27*'Calendar Assumptions'!G46*RM_VHA_GBO_Fee -> 578267.23 | H56: =H$20*H27*'Calendar Assumptions'!H46*RM_VHA_GBO_Fee -> 607996.75 | I56: =I$20*I27*'Calendar Assumptions'!I46*RM_VHA_GBO_Fee -> 671207.56 | J56: =J$20*J27*'Calendar Assumptions'!J46*RM_VHA_GBO_Fee -> 691343.79 | K56: =K$20*K27*'Calendar Assumptions'!K46*RM_VHA_GBO_Fee -> 712084.1 | L56: =L$20*L27*'Calendar Assumptions'!L46*RM_VHA_GBO_Fee -> 733446.62 | M56: =M$20*M27*'Calendar Assumptions'!M46*RM_VHA_GBO_Fee -> 755450.02 | ... O56: =O$20*O27*'Calendar Assumptions'!O46*RM_VHA_GBO_Fee -> 801456.93
B57: 7 | C57: Sports | D57: =Inputs!$E$133 -> 3500 | F57: =F$20*F28*'Calendar Assumptions'!F47*RM_VHA_GBO_Fee -> 0 | G57: =G$20*G28*'Calendar Assumptions'!G47*RM_VHA_GBO_Fee -> 113083.37 | H57: =H$20*H28*'Calendar Assumptions'!H47*RM_VHA_GBO_Fee -> 118897.14 | I57: =I$20*I28*'Calendar Assumptions'!I47*RM_VHA_GBO_Fee -> 131258.37 | J57: =J$20*J28*'Calendar Assumptions'!J47*RM_VHA_GBO_Fee -> 135196.12 | K57: =K$20*K28*'Calendar Assumptions'!K47*RM_VHA_GBO_Fee -> 139252 | L57: =L$20*L28*'Calendar Assumptions'!L47*RM_VHA_GBO_Fee -> 143429.56 | M57: =M$20*M28*'Calendar Assumptions'!M47*RM_VHA_GBO_Fee -> 147732.45 | ... O57: =O$20*O28*'Calendar Assumptions'!O47*RM_VHA_GBO_Fee -> 156729.35
B58: 8 | C58: MICE | D58: =Inputs!$E$134 -> 3500 | F58: =F$20*F29*'Calendar Assumptions'!F48*RM_VHA_GBO_Fee -> 0 | G58: =G$20*G29*'Calendar Assumptions'!G48*RM_VHA_GBO_Fee -> 0 | H58: =H$20*H29*'Calendar Assumptions'!H48*RM_VHA_GBO_Fee -> 0 | I58: =I$20*I29*'Calendar Assumptions'!I48*RM_VHA_GBO_Fee -> 0 | J58: =J$20*J29*'Calendar Assumptions'!J48*RM_VHA_GBO_Fee -> 0 | K58: =K$20*K29*'Calendar Assumptions'!K48*RM_VHA_GBO_Fee -> 0 | L58: =L$20*L29*'Calendar Assumptions'!L48*RM_VHA_GBO_Fee -> 0 | M58: =M$20*M29*'Calendar Assumptions'!M48*RM_VHA_GBO_Fee -> 0 | ... O58: =O$20*O29*'Calendar Assumptions'!O48*RM_VHA_GBO_Fee -> 0
B59: 9 | C59: Community | D59: =Inputs!$E$135 -> 2000 | F59: =F$20*F30*'Calendar Assumptions'!F49*RM_VHA_GBO_Fee -> 0 | G59: =G$20*G30*'Calendar Assumptions'!G49*RM_VHA_GBO_Fee -> 0 | H59: =H$20*H30*'Calendar Assumptions'!H49*RM_VHA_GBO_Fee -> 0 | I59: =I$20*I30*'Calendar Assumptions'!I49*RM_VHA_GBO_Fee -> 0 | J59: =J$20*J30*'Calendar Assumptions'!J49*RM_VHA_GBO_Fee -> 0 | K59: =K$20*K30*'Calendar Assumptions'!K49*RM_VHA_GBO_Fee -> 0 | L59: =L$20*L30*'Calendar Assumptions'!L49*RM_VHA_GBO_Fee -> 0 | M59: =M$20*M30*'Calendar Assumptions'!M49*RM_VHA_GBO_Fee -> 0 | ... O59: =O$20*O30*'Calendar Assumptions'!O49*RM_VHA_GBO_Fee -> 0
