Workbook
Name CF_Report?: Summary!$A$37
Name ConstDebt_Payoff: Underwriting!$E$75
Name CU?: Underwriting!$EQ$207
Name Dbl_Promote?: Underwriting!$A$220
Name Debt_LTC_Actual: Underwriting!$F$61
Name Debt_LTC_Target: Underwriting!$C$61
Name Debt_Total: Underwriting!$I$61
Name Dev_Spread: Underwriting!$I$5
Name EGR_0: Underwriting!$L$130
Name Equity_Total: Underwriting!$I$60
Name Fixed_Variable: Underwriting!$A$62
Name Interest_Const_Loan: Underwriting!$E$65
Name Interest_Mezz_Loan: Underwriting!$E$66
Name Investment_Name: Underwriting!$E$9
Name Items_Hard_Costs: Underwriting!$ER$38
Name Items_Industrial_Tenants: Underwriting!$I$91
Name Items_Land_Costs: Underwriting!$ER$31
Name Items_Opex: Underwriting!$ER$138
Name Items_Soft_Costs: Underwriting!$ER$47
Name Land_Value: Underwriting!$I$27
Name LeaseUp_Formula: Underwriting!$L$89
Name Mgmt_Fee_0: Underwriting!$L$135
Name Mgmt_Fee_Pct: Underwriting!$G$135
Name Nav_Development_CF: Underwriting!$B$23:$I$85
Name Nav_Industrial_Expenses: Underwriting!$B$132:$I$141
Name Nav_Industrial_Reserves: Underwriting!$B$142:$I$151
Name Nav_Investment_Description: Underwriting!$B$8:$I$21
Name Nav_Operating_CF: Underwriting!$B$86:$I$158
Name Nav_Operating_Expenses_Summary: Underwriting!$B$152:$I$155
Name Nav_Residual_CF: Underwriting!$B$159:$I$193
Name Nav_Sensitivity: Underwriting!$B$269:$I$286
Name Nav_Waterfall_CF: Underwriting!$B$194:$I$246
Name OpEx_6: Underwriting!$I$152
Name OpEx_7: Underwriting!$I$153
Name OpEx_Ins: Underwriting!$I$155
Name OpEx_MgtFee: Underwriting!$I$154
Name Perm_Debt?: Underwriting!$A$79
Name PermDebt_Fund: Underwriting!$C$82
Name PermDebt_Payoff: Underwriting!$C$83
Name Project_Cost_Total: Underwriting!$I$57
Name Proxy_Fee: Underwriting!$G$290
Name Range_Building_Type: Data!$B$25:INDEX(Data!$B$25:$B$46,COUNTA(Data!$B$25:$B$46))
Name Range_Debt: Underwriting!$L$75:INDEX(Underwriting!$L$75:$EN$75,1,Timing_Reversion_Month+1)
Name Range_Equity: Underwriting!$L$69:INDEX(Underwriting!$L$69:$EN$69,1,Timing_Reversion_Month+1)
Name Range_LeaseUp: Underwriting!$M$89:$EN$89
Name Range_Levered_CF: Underwriting!$L$212:INDEX(Underwriting!$L$212:$EN$212,1,Timing_Reversion_Month+1)
Name Range_Months: Underwriting!$L$86:INDEX(Underwriting!$L$86:$EN$86,1,Timing_Reversion_Month+1)
Name Range_NOI: Underwriting!$L$140:INDEX(Underwriting!$L$140:$EN$140,1,Timing_Reversion_Month+1)
Name Range_PermDebt: Underwriting!$80:$84
Name Range_PermDS: Underwriting!$156:$157
Name Range_Tenant_Type: Data!$D$25:INDEX(Data!$D$25:$D$46,COUNTA(Data!$D$25:$D$46))
Name Range_Total_Cost: Underwriting!$L$57:INDEX(Underwriting!$L$57:$EN$57,1,Timing_Reversion_Month+1)
Name Recalc?: Underwriting!$C$292
Name Recalc_Const: Underwriting!$C$290
Name Recalc_Mgmt: Underwriting!$C$291
Name Rel_2nd_Promote: Underwriting!$A$247:$A$267
Name Rel_Calc: Underwriting!$EP$1:$JX$1
Name Rel_EGR_ProForma: Underwriting!$I$130
Name Rel_End: Underwriting!$A$287
Name Rel_Hard_Costs: Underwriting!$A$38

Sheet Summary
B2: =Underwriting!B2 -> THE BEND ENTERTAINMENT PRECINCT | S2: =UPPER(Underwriting!I2) -> MAYABAY ACTIVE (MELBOURNE) PTY LTD
B3: =Underwriting!E11&", "&Underwriting!I10 -> Port Melbourne, VIC | S3: ="ANALYSIS START - "&UPPER(TEXT(Underwriting!E13,"MMM YYYY")) -> ANALYSIS START - JUL 2026
B4: INVESTMENT DESCRIPTION | Q4: Run Residual Land Value Tool
B5: Address | F5: =Underwriting!E10&", "&Underwriting!E11&" "&Underwriting!I10 -> Port Melbourne, Port Melbourne VIC | G5: STRENGTHS | N5: MODEL GOVERNANCE & CONTROL STATUS
B6: ="Net Rentable Area ("&Unit_Type&")" -> Net Rentable Area (M2) | F6: ='VALUATION & RETURNS'!$CS$38 -> 78470.38 | G6: Large Fishermans Bend urban-renewal location | N6: Purpose | O6: Integrated development, debt, valuation and investor-return model for The Bend Precinct.
B7: Land Area | F7: =Underwriting!$E$17 -> 8.5004251 | G7: Diversified leisure, PBSA and ancillary uses | N7: Audience | O7: Management, prospective investors and lenders; not a substitute for legal, tax, valuation or lender advice.
B8: Retail Type | F8: ="Mixed-use entertainment, leisure, PBSA and ancillary precinct" -> Mixed-use entertainment, leisure, PBSA and ancillary precinct | G8: Integrated property and operating schedules | N8: Version | O8: V16 | 1 Aug 2026 | Phase 11 exact S-curve compatibility modernisation applied; full desktop-Excel recalculation remains required.
B9: # of Retail Buildings | F9: ="Multiple component buildings — see component tabs" -> Multiple component buildings — see component tabs | G9: Livehouse is quick to market operation. | N9: Input hub | O9: PROJECT INPUTS is the sole ProjectCo assumption hub. Detailed source-evidence rows remain read-only and are not calculation inputs.
B10: Parking (Surfaces + Structured) | F10: =SUM(Underwriting!$E$20:$E$21) -> 353.11671 | G10: Reduced single-use concentration risk | N10: Scenario control | O10: Authoritative ProjectCo scenario: PROJECT INPUTS!B8. VALUATION & RETURNS!CR7 and INVESTOR REPORT!I3 are formula-linked displays.
B11: Analysis Start | E11: 1 | F11: =Underwriting!$E$13 -> 46204 | G11: Sustainability and green-building objectives | N11: Period status | O11: Forecast-only base model. Explicit Actual / Forecast classification is shown at Underwriting!L4:EN4.
B12: Construction Start | E12: 1 | F12: =Underwriting!$E$13 -> 46204 | G12: WEAKNESSES | N12: Balance sheet control | O12: =IFERROR(IF(MAX(MAX('Financial Statements'!$G$50:$X$50),-MIN('Financial Statements'!$G$50:$X$50))<=1,"PASS","FAIL"),"PENDING RECALC") -> FAIL
B13: Construction End | E13: =Timing_Construction_End -> 36 | F13: =EOMONTH(Underwriting!$E$13,Underwriting!$D$88-2) -> 47299 | G13: Commercial assumptions remain provisional | N13: Sources and uses control | O13: =IFERROR(IF(ABS(Underwriting!$I$57-SUM(Underwriting!$I$69,Underwriting!$I$75))<0.01,"PASS","FAIL"),"PENDING RECALC") -> FAIL
B14: Operation Begin | E14: =Timing_Operation_Begin_Month -> 37 | F14: =EOMONTH(F13,1) -> 47330 | G14: Independent valuation evidence required | N14: Debt roll-forward control | O14: =IFERROR(IF(AND(MAX(MAX(DEBT!$F$96:$DV$96),-MIN(DEBT!$F$96:$DV$96))<=0.01,MAX(MAX(DEBT!$F$136:$DV$136),-MIN(DEBT!$F$136:$DV$136))<=0.01),"PASS","FAIL"),"PENDING RECALC") -> FAIL
B15: Stabilization | E15: =Stabilization_1st_Month -> 49 | F15: =EOMONTH(Underwriting!$E$13,Underwriting!$D$89-1) -> 47695 | G15: Executed lender terms remain outstanding | N15: Macros / calculation | O15: Existing VBA retained. Full recalculation is forced on open; external reliance remains gated until owner decisions and specialist tax, lender, valuation and QS confirmation are complete.
B16: Sale Date | E16: =Timing_Reversion_Month -> 61 | F16: =Underwriting!$I$15 -> 48030 | G16: Final QS scope and cost sign-off required | N16: Macro modules | O16: ThisWorkbook; Sheet modules; General; Budget; Sensitivity; Returns; Operating; PermDebt.
F17: Tax, GST and depreciation assumptions require specialist advice | G17: Tax and GST assumptions require specialist advice | N17: Open commercial items | O17: OWNER DECISIONS: executed lender terms; written Australian tax/GST advice; independent property valuation; approved OpCo margin and multiple; final QS cost plan; executed shareholder and waterfall terms.
F18: Returns remain sensitive to cost, timing, stabilisation and exit-yield assumptions | G18: Exit yield remains a material sensitivity | N18: Governance record | O18: 30 Jul 2026: FAST/SAVi/project-finance best practice and official Australian benchmark/regulatory research applied through source records, detailed evidence checklists and fail-safe release gates. Public research has not been treated as executed project evidence.
A19: 0 | B19: KEY ASSUMPTIONS & RETURN METRICS | Q19: TENANT ANALYSIS REPORT: | R19: Hide | S19: Show
B20: Growth Rates - Income / Expense | G20: =TEXT(Underwriting!G105,"0.00%")&" / "&TEXT(Underwriting!F138,"0.00%") -> 3.50% / 0.00% | H20: PRO FORMA | L20: =+Underwriting!H165 -> STABILIZED (UNTRENDED) | M20: =+Underwriting!I165 -> SALE | N20: PARTNERSHIP RETURNS | Q20: ROI | R20: EMx | S20: IRR
B21: ="Effective Rent / "&Unit_Type -> Effective Rent / M2 | G21: =Underwriting!H105 -> 194.72316 | H21: Effective Gross Revenue | L21: =+Underwriting!H171 -> 48830200 | M21: =+Underwriting!I171 -> 52215580 | N21: Limited Partners | Q21: =Underwriting!G223 -> 1.3761098 | R21: =Underwriting!H223 -> 3.6516198 | S21: =Underwriting!I223 -> 4.7683716e-09
B22: General Vacancy & Credit Loss | G22: =Underwriting!G129 -> 0 | H22: - Operating Expenses | L22: =+Underwriting!H177 -> 3288278.6 | M22: =+Underwriting!I177 -> 3454747.7 | N22: General Partner / Sponsor | Q22: =Underwriting!G224 -> NA | R22: =Underwriting!H224 -> NA | S22: =Underwriting!I224 -> NA
B23: Expense Recovery Ratio | G23: =IF(Underwriting!$I$138=0,"",Underwriting!$I$120/Underwriting!$I$138) -> 1 | H23: Net Operating Income | L23: =L21-L22 -> 45541922 | M23: =M21-M22 -> 48760833 | N23: =Underwriting!B225 | Q23: =Underwriting!G225 | R23: =Underwriting!H225 | S23: =Underwriting!I225
B24: CapEx Reserve % of NOI | G24: =IF(Underwriting!$I$140=0,"",OpEx_7/Underwriting!$I$140) -> 0 | H24: - Capital Expenditures | L24: =+Underwriting!H183 -> 0 | M24: =+Underwriting!I183 -> 0 | N24: PROPERTY RETURNS | Q24: ROI | R24: EMx | S24: IRR
B25: ="Leasing Cost Reserve / "&Unit_Type&" / Yr" -> Leasing Cost Reserve / M2 / Yr | G25: =+Underwriting!H151 -> 0 | H25: Cash Flow from Operations | L25: =L23-L24 -> 45541922 | M25: =M23-M24 -> 48760833 | N25: Unlevered | Q25: =IFERROR(IF(Underwriting!$I$49=0,"",Underwriting!$I$211/Underwriting!$I$49),"") -> 1.0011752 | R25: =Underwriting!G211 -> 2.3177032 | S25: =Underwriting!H211 -> 0.26738072
H26: Cap Rate | L26: =Underwriting!H189 -> 0.067008197 | M26: =Underwriting!I189 -> 0.0675 | N26: Levered | Q26: =IFERROR(IF(Equity_Total=0,"",Underwriting!$I$212/Equity_Total),"") -> 1.7496555 | R26: =Underwriting!G212 -> 3.6516198 | S26: =Underwriting!H212 -> 2.9802322e-09
B27: Reversion Net Proceeds (After Selling Costs) | G27: =Underwriting!E190 -> 7.0793505e+08 | H27: Valuation | L27: =Underwriting!H191 -> 6.7964703e+08 | M27: =Underwriting!I191 -> 7.2238271e+08 | N27: DEVELOPMENT RETURNS | R27: =PROPER(Underwriting!H214) -> Stabilized (Untrended) | S27: =PROPER(Underwriting!I214) -> Sale
B28: =IF(Perm_Debt?,"Permanent Loan Payoff","Construction Loan Payoff") -> Construction Loan Payoff | G28: =IFERROR(IF(Perm_Debt?,Underwriting!$I$83,-Underwriting!$I$75),"") -> -2.3520265e+08 | H28: % of Total Project Cost | L28: =L27/$M$36 -> 1.514174 | M28: =M27/$M$36 -> 1.609384 | N28: =Underwriting!B215 -> Yield-on-Cost | R28: =Underwriting!H215 -> 0.10146207 | S28: =Underwriting!I215 -> 0.10863342
B29: Equity Proceeds from Sale | G29: =IFERROR(Underwriting!$E$192,"") -> 4.727324e+08 | H29: ="Valuation/"&Unit_Type -> Valuation/M2 | L29: =L27/Units -> 8661.192 | M29: =M27/Units -> 9205.801 | N29: =Underwriting!B216 -> Market Cap Rate | R29: =Underwriting!H216 -> 0.067008197 | S29: =Underwriting!I216 -> 0.0675
N30: =Underwriting!B217 -> Development Spread | R30: =Underwriting!H217 -> 344.5387 | S30: =Underwriting!I217 -> 411.33423
B31: SOURCES | E31: % | F31: /Unit | G31: Amount | H31: USES | K31: % | L31: ="/Buildable "&Unit_Type -> /Buildable M2 | M31: Amount | N31: =Underwriting!$C$271 -> Vacancy
B32: =Underwriting!B61 -> Construction Debt | E32: =IF(IF(Dbl_Promote?=1,$G$36,$G$35)=0,"",G32/IF(Dbl_Promote?=1,$G$36,$G$35)) -> 0.51818608 | F32: =IFERROR(G32/Units,"") -> 2997.3431 | G32: =IFERROR(Debt_Total,0) -> 2.3520265e+08 | H32: =Underwriting!B26 -> Land Costs | K32: =M32/$M$36 -> 0.20567814 | L32: =M32/Units -> 1176.4949 | M32: =Underwriting!I31 -> 92320000 | N32: SENSITIVITY | Q32: Exit Cap Rate | R32: =Underwriting!H271 -> Dev. Spread | S32: =Underwriting!I271 -> Levered EMx
B33: Limited Partners | E33: =IF(IF(Dbl_Promote?=1,$G$36,$G$35)=0,"",G33/IF(Dbl_Promote?=1,$G$36,$G$35)) -> 0.48181392 | F33: =IFERROR(G33/Units,"") -> 2786.9557 | G33: =Underwriting!D223 -> 2.1869347e+08 | H33: =Underwriting!B33 -> 0 | K33: =M33/$M$36 -> 0.79432186 | L33: =M33/Units -> 4543.5824 | M33: =Underwriting!I38 -> 3.5653664e+08 | N33: =Underwriting!B272 -> Base Case | Q33: =Underwriting!G272 -> 0.0675 | R33: =Underwriting!H272 -> 411.33423 | S33: =Underwriting!I272 -> 3.6516198
B34: General Partner / Sponsor | E34: =IF(IF(Dbl_Promote?=1,$G$36,$G$35)=0,"",G34/IF(Dbl_Promote?=1,$G$36,$G$35)) -> 0 | F34: =IFERROR(G34/Units,"") -> 0 | G34: =Underwriting!D224 -> 0 | H34: =Underwriting!B40 -> 0 | K34: =M34/$M$36 -> 0 | L34: =M34/Units -> 0 | M34: =Underwriting!I47 -> 0 | N34: =Underwriting!B273 -> Downside #1 | Q34: =Underwriting!G273 -> 0.06 | R34: =Underwriting!H273 -> 486.33423 | S34: =Underwriting!I273 -> 4.2734712
B35: =IF(Dbl_Promote?=1,Underwriting!B225,"Total Sources") -> Total Sources | E35: =IF(IF(Dbl_Promote?=1,$G$36,$G$35)=0,"",G35/IF(Dbl_Promote?=1,$G$36,$G$35)) -> 1 | F35: =IFERROR(G35/Units,"") -> 5784.2988 | G35: =IFERROR(IF(B36="",SUM(G32:G34),Underwriting!$D$225),SUM(G32:G34)) -> 4.5389613e+08 | H35: =Underwriting!B51 -> 0 | K35: =M35/$M$36 -> 0 | L35: =M35/Units -> 0 | M35: =Underwriting!I55 -> 0 | N35: =Underwriting!B274 -> Downside #2 | Q35: =Underwriting!G274 -> 0.0625 | R35: =Underwriting!H274 -> 461.33423 | S35: =Underwriting!I274 -> 4.0496047
B36: =IF(Dbl_Promote?=1,"Total Sources","") | E36: =IF(Dbl_Promote?=1,G36/$G$36,"") | F36: =IFERROR(G36/Units,"") | G36: =IF(B36="","",SUM(G32:G35)) | H36: Total Uses | K36: =M36/$M$36 -> 1 | L36: =SUM(L32:L35) -> 5720.0772 | M36: =SUM(M32:M35) -> 4.4885664e+08 | N36: =Underwriting!B275 -> Downside #3 | Q36: =Underwriting!G275 -> 0.065 | R36: =Underwriting!H275 -> 436.33423 | S36: =Underwriting!I275 -> 3.8429587
A37: 0 | B37: PROPERTY-LEVEL CASH FLOW | Q37: ANNUAL CASH FLOW REPORT: | R37: Hide | S37: Show
S86: 0.33

Sheet Underwriting
B2: =UPPER(Investment_Name) -> THE BEND ENTERTAINMENT PRECINCT | D2: =IFERROR(IF(Recalc?,"","CLICK TO RECALCULATE"),"CLICK TO RECALCULATE") -> CLICK TO RECALCULATE | I2: Mayabay Active (Melbourne) Pty Ltd | K2: Analysis Year | L2: =ROUNDUP(L3/12,0) -> 0 | M2: =ROUNDUP(M3/12,0) -> 1 | N2: =ROUNDUP(N3/12,0) -> 1 | O2: =ROUNDUP(O3/12,0) -> 1 | P2: =ROUNDUP(P3/12,0) -> 1 | Q2: =ROUNDUP(Q3/12,0) -> 1 | R2: =ROUNDUP(R3/12,0) -> 1 | S2: =ROUNDUP(S3/12,0) -> 1 | ... EN2: =ROUNDUP(EN3/12,0) -> 11 | EV2: =L2 -> 0 | EW2: =M2 -> 1 | EX2: =N2 -> 1 | EY2: =O2 -> 1 | EZ2: =P2 -> 1 | FA2: =Q2 -> 1 | FB2: =R2 -> 1 | FC2: =S2 -> 1 | ... JX2: =EN2 -> 11 | KF2: =EV2 -> 0 | KG2: =EW2 -> 1 | KH2: =EX2 -> 1 | KI2: =EY2 -> 1 | KJ2: =EZ2 -> 1 | KK2: =FA2 -> 1 | KL2: =FB2 -> 1 | KM2: =FC2 -> 1 | ... PH2: =JX2 -> 11
K3: Analysis Month | L3: =COLUMN()-COLUMN($L$3) -> 0 | M3: =COLUMN()-COLUMN($L$3) -> 1 | N3: =COLUMN()-COLUMN($L$3) -> 2 | O3: =COLUMN()-COLUMN($L$3) -> 3 | P3: =COLUMN()-COLUMN($L$3) -> 4 | Q3: =COLUMN()-COLUMN($L$3) -> 5 | R3: =COLUMN()-COLUMN($L$3) -> 6 | S3: =COLUMN()-COLUMN($L$3) -> 7 | ... EN3: =COLUMN()-COLUMN($L$3) -> 132 | EV3: =L3 -> 0 | EW3: =M3 -> 1 | EX3: =N3 -> 2 | EY3: =O3 -> 3 | EZ3: =P3 -> 4 | FA3: =Q3 -> 5 | FB3: =R3 -> 6 | FC3: =S3 -> 7 | ... JX3: =EN3 -> 132 | KF3: =EV3 -> 0 | KG3: =EW3 -> 1 | KH3: =EX3 -> 2 | KI3: =EY3 -> 3 | KJ3: =EZ3 -> 4 | KK3: =FA3 -> 5 | KL3: =FB3 -> 6 | KM3: =FC3 -> 7 | ... PH3: =JX3 -> 132
K4: Actual / Forecast Status | L4: =IF(L$24="","",IF(L$24<=$E$13,"Actual","Forecast")) -> Actual | M4: =IF(M$24="","",IF(M$24<=$E$13,"Actual","Forecast")) -> Forecast | N4: =IF(N$24="","",IF(N$24<=$E$13,"Actual","Forecast")) -> Forecast | O4: =IF(O$24="","",IF(O$24<=$E$13,"Actual","Forecast")) -> Forecast | P4: =IF(P$24="","",IF(P$24<=$E$13,"Actual","Forecast")) -> Forecast | Q4: =IF(Q$24="","",IF(Q$24<=$E$13,"Actual","Forecast")) -> Forecast | R4: =IF(R$24="","",IF(R$24<=$E$13,"Actual","Forecast")) -> Forecast | S4: =IF(S$24="","",IF(S$24<=$E$13,"Actual","Forecast")) -> Forecast | ... EN4: =IF(EN$24="","",IF(EN$24<=$E$13,"Actual","Forecast")) -> Forecast
B5: Levered IRR | C5: =H212 -> 2.9802322e-09 | D5: Levered EMx: | E5: =G212 -> 3.6516198 | F5: =Timing_Reversion_Month -> 61 | H5: Development Spread (Untrended) | I5: =H217 -> 344.5387 | EM5: Hide Calc | EN5: Show Calc | EO5: 1
B8: INVESTMENT DESCRIPTION | I8: M2
B9: Name | E9: ='URWLD COMPANY INPUTS'!$F$37 -> THE BEND Entertainment Precinct | F9: County | I9: [County]
B10: Address | E10: ='URWLD COMPANY INPUTS'!$F$38 -> Port Melbourne | F10: State | I10: =IF($E$10="Port Melbourne","VIC","") -> VIC
B11: City | E11: ='URWLD COMPANY INPUTS'!$F$38 -> Port Melbourne | F11: Zip Code | I11: [Zip Code]
B13: Analysis Begin Date | E13: =DATE(VALUE(RIGHT('URWLD COMPANY INPUTS'!$F$45,4)),VALUE(MID('URWLD COMPANY INPUTS'!$F$45,2,1))*3-2,1) -> 46204 | F13: Country | I13: =IF($E$10<>"","Australia","") -> Australia
B15: Retail Building Type | D15: Neighborhood Center | F15: Sale Date | I15: =EDATE(E13,I16-1) -> 48030
B16: Leasing Strategy | E16: Speculative | F16: Analysis Period | I16: =Timing_Reversion_Month -> 61
B17: Land Area | C17: =IF(Unit_Type="SF",E17*43560,E17*4046.86) -> 34400.03 | D17: =Unit_Type -> M2 | E17: ='URWLD COMPANY INPUTS'!$F$43/4046.8564224 -> 8.5004251 | F17: Suites/Tenants | I17: =COUNTA($B$93:$B$105)-1 -> 12
B18: ="Gross Buildable (NRA - "&Unit_Type&")" -> Gross Buildable (NRA - M2) | E18: =I18 -> 78470.38 | F18: ="Net Rentable (NRA - "&Unit_Type&")" -> Net Rentable (NRA - M2) | I18: =SUM(E93:E104) -> 78470.38
B19: # of Buildings | E19: 4 | F19: Building Coverage (Assumes one-story bldgs) | I19: =Units_SF_M2/C17 -> 2.2811137
B20: Surface Parking Spaces | E20: =Units_SF_M2/1000*0.5 -> 39.23519 | F20: Efficiency Ratio | I20: =Units_SF_M2/E18 -> 1
B21: Structured Parking Spaces | E21: =Units_SF_M2/1000*4 -> 313.88152 | F21: ="Parking Ratio (Per "&Unit_Type&")" -> Parking Ratio (Per M2) | I21: =(E21+E20)/(Units_SF_M2/1000) -> 4.5
B23: INVESTMENT PERIOD CASH FLOWS | K23: Analysis Month | L23: =COLUMN()-COLUMN($L$23) -> 0 | M23: =COLUMN()-COLUMN($L$23) -> 1 | N23: =COLUMN()-COLUMN($L$23) -> 2 | O23: =COLUMN()-COLUMN($L$23) -> 3 | P23: =COLUMN()-COLUMN($L$23) -> 4 | Q23: =COLUMN()-COLUMN($L$23) -> 5 | R23: =COLUMN()-COLUMN($L$23) -> 6 | S23: =COLUMN()-COLUMN($L$23) -> 7 | ... EN23: =COLUMN()-COLUMN($L$23) -> 132 | EP23: S-CURVE CALCULATION | EV23: =L23 -> 0 | EW23: =M23 -> 1 | EX23: =N23 -> 2 | EY23: =O23 -> 3 | EZ23: =P23 -> 4 | FA23: =Q23 -> 5 | FB23: =R23 -> 6 | FC23: =S23 -> 7 | ... JX23: =EN23 -> 132 | JZ23: GROWTH/DECLINE CALCULATION | KF23: =EV23 -> 0 | KG23: =EW23 -> 1 | KH23: =EX23 -> 2 | KI23: =EY23 -> 3 | KJ23: =EZ23 -> 4 | KK23: =FA23 -> 5 | KL23: =FB23 -> 6 | KM23: =FC23 -> 7 | ... PH23: =JX23 -> 132
B24: SOURCES AND USES | K24: Analysis Date | L24: =EOMONTH($E$13,COLUMN()-COLUMN($L$24)-1) -> 46203 | M24: =EOMONTH($E$13,COLUMN()-COLUMN($L$24)-1) -> 46234 | N24: =EOMONTH($E$13,COLUMN()-COLUMN($L$24)-1) -> 46265 | O24: =EOMONTH($E$13,COLUMN()-COLUMN($L$24)-1) -> 46295 | P24: =EOMONTH($E$13,COLUMN()-COLUMN($L$24)-1) -> 46326 | Q24: =EOMONTH($E$13,COLUMN()-COLUMN($L$24)-1) -> 46356 | R24: =EOMONTH($E$13,COLUMN()-COLUMN($L$24)-1) -> 46387 | S24: =EOMONTH($E$13,COLUMN()-COLUMN($L$24)-1) -> 46418 | ... EN24: =EOMONTH($E$13,COLUMN()-COLUMN($L$24)-1) -> 50221 | EP24: Amount | EQ24: Start Period | ER24: End Period | ES24: Months | ET24: Timing | EU24: StDev | EV24: =L24 -> 46203 | EW24: =M24 -> 46234 | EX24: =N24 -> 46265 | EY24: =O24 -> 46295 | EZ24: =P24 -> 46326 | FA24: =Q24 -> 46356 | FB24: =R24 -> 46387 | FC24: =S24 -> 46418 | ... JX24: =EN24 -> 50221 | KF24: =EV24 -> 46203 | KG24: =EW24 -> 46234 | KH24: =EX24 -> 46265 | KI24: =EY24 -> 46295 | KJ24: =EZ24 -> 46326 | KK24: =FA24 -> 46356 | KL24: =FB24 -> 46387 | KM24: =FC24 -> 46418 | ... PH24: =JX24 -> 50221
B25: USES | D25: START | E25: END | F25: METHOD | H25: ="/RENTABLE "&Unit_Type -> /RENTABLE M2 | I25: AMOUNT | K25: Cum. Spent % | L25: =SUM($L$57:L57)/Project_Cost_Total -> 0.20723257 | M25: =SUM($L$57:M57)/Project_Cost_Total -> 0.20919763 | N25: =SUM($L$57:N57)/Project_Cost_Total -> 0.21176691 | O25: =SUM($L$57:O57)/Project_Cost_Total -> 0.21519912 | P25: =SUM($L$57:P57)/Project_Cost_Total -> 0.2198269 | Q25: =SUM($L$57:Q57)/Project_Cost_Total -> 0.22606061 | R25: =SUM($L$57:R57)/Project_Cost_Total -> 0.2343842 | S25: =SUM($L$57:S57)/Project_Cost_Total -> 0.24534022 | ... EN25: =SUM($L$57:EN57)/Project_Cost_Total -> 1 | JZ25: =B25 -> USES | KB25: Start | KC25: End | KD25: Length | KE25: Amount
B26: Land Costs | K26: Spent % | L26: =L25 -> 0.20723257 | M26: =M25-L25 -> 0.0019650559 | N26: =N25-M25 -> 0.0025692809 | O26: =O25-N25 -> 0.0034322136 | P26: =P25-O25 -> 0.0046277776 | Q26: =Q25-P25 -> 0.0062337101 | R26: =R25-Q25 -> 0.0083235906 | S26: =S25-R25 -> 0.010956018 | T26: =T25-S25 -> 0.014161728 | ... EN26: =EN25-EM25 -> 0 | JZ26: =B26 -> Land Costs
C27: 0 | E27: =D27 -> 0 | F27: Straight-Line | G27: =I27/Units_SF_M2 -> 1166.9371 | I27: ='URWLD COMPANY INPUTS'!$D$122*1000000 -> 91570000 | K27: =IF(ROUND(SUM(L27:EN27),0)=ROUND(I27,0),"","Incomplete") | L27: =AND(L$23>=$D27,L$23<=$E27)*(OR($F27="Straight-Line",$F27="Detail")*($I27/$ES27)+($F27="S-Curve")*EV27+OR($F27="Steady Growth",$F27="Steady Decline")*KF27) -> 91570000 | M27: =AND(M$23>=$D27,M$23<=$E27)*(OR($F27="Straight-Line",$F27="Detail")*($I27/$ES27)+($F27="S-Curve")*EW27+OR($F27="Steady Growth",$F27="Steady Decline")*KG27) -> 0 | N27: =AND(N$23>=$D27,N$23<=$E27)*(OR($F27="Straight-Line",$F27="Detail")*($I27/$ES27)+($F27="S-Curve")*EX27+OR($F27="Steady Growth",$F27="Steady Decline")*KH27) -> 0 | O27: =AND(O$23>=$D27,O$23<=$E27)*(OR($F27="Straight-Line",$F27="Detail")*($I27/$ES27)+($F27="S-Curve")*EY27+OR($F27="Steady Growth",$F27="Steady Decline")*KI27) -> 0 | P27: =AND(P$23>=$D27,P$23<=$E27)*(OR($F27="Straight-Line",$F27="Detail")*($I27/$ES27)+($F27="S-Curve")*EZ27+OR($F27="Steady Growth",$F27="Steady Decline")*KJ27) -> 0 | Q27: =AND(Q$23>=$D27,Q$23<=$E27)*(OR($F27="Straight-Line",$F27="Detail")*($I27/$ES27)+($F27="S-Curve")*FA27+OR($F27="Steady Growth",$F27="Steady Decline")*KK27) -> 0 | R27: =AND(R$23>=$D27,R$23<=$E27)*(OR($F27="Straight-Line",$F27="Detail")*($I27/$ES27)+($F27="S-Curve")*FB27+OR($F27="Steady Growth",$F27="Steady Decline")*KL27) -> 0 | S27: =AND(S$23>=$D27,S$23<=$E27)*(OR($F27="Straight-Line",$F27="Detail")*($I27/$ES27)+($F27="S-Curve")*FC27+OR($F27="Steady Growth",$F27="Steady Decline")*KM27) -> 0 | ... EN27: =AND(EN$23>=$D27,EN$23<=$E27)*(OR($F27="Straight-Line",$F27="Detail")*($I27/$ES27)+($F27="S-Curve")*JX27+OR($F27="Steady Growth",$F27="Steady Decline")*PH27) -> 0 | EP27: =I27 -> 91570000 | EQ27: =INDEX($L$24:$EN$24,1,$D27+1) -> 46203 | ER27: =INDEX($L$24:$EN$24,1,$E27+1) -> 46203 | ES27: =+E27-D27+1 -> 1 | ET27: =F27 -> Straight-Line | EU27: =ES27/Scurve_Dist -> 0.16666667 | EV27: =AND($ET27="S-Curve",EV$24>=$EQ27,EV$24<=$ER27)*(NORMDIST((YEAR(EV$24)-YEAR($EQ27))*12+MONTH(EV$24)-MONTH($EQ27)+1,$ES27/2,$EU27,TRUE)-NORMDIST((YEAR(EV$24)-YEAR($EQ27))*12+MONTH(EV$24)-MONTH($EQ27),$ES27/2,$EU27,TRUE))/(1-2*NORMDIST(0,$ES27/2,$EU27,TRUE))*$EP27 -> 0 | EW27: =AND($ET27="S-Curve",EW$24>=$EQ27,EW$24<=$ER27)*(NORMDIST((YEAR(EW$24)-YEAR($EQ27))*12+MONTH(EW$24)-MONTH($EQ27)+1,$ES27/2,$EU27,TRUE)-NORMDIST((YEAR(EW$24)-YEAR($EQ27))*12+MONTH(EW$24)-MONTH($EQ27),$ES27/2,$EU27,TRUE))/(1-2*NORMDIST(0,$ES27/2,$EU27,TRUE))*$EP27 -> 0 | EX27: =AND($ET27="S-Curve",EX$24>=$EQ27,EX$24<=$ER27)*(NORMDIST((YEAR(EX$24)-YEAR($EQ27))*12+MONTH(EX$24)-MONTH($EQ27)+1,$ES27/2,$EU27,TRUE)-NORMDIST((YEAR(EX$24)-YEAR($EQ27))*12+MONTH(EX$24)-MONTH($EQ27),$ES27/2,$EU27,TRUE))/(1-2*NORMDIST(0,$ES27/2,$EU27,TRUE))*$EP27 -> 0 | EY27: =AND($ET27="S-Curve",EY$24>=$EQ27,EY$24<=$ER27)*(NORMDIST((YEAR(EY$24)-YEAR($EQ27))*12+MONTH(EY$24)-MONTH($EQ27)+1,$ES27/2,$EU27,TRUE)-NORMDIST((YEAR(EY$24)-YEAR($EQ27))*12+MONTH(EY$24)-MONTH($EQ27),$ES27/2,$EU27,TRUE))/(1-2*NORMDIST(0,$ES27/2,$EU27,TRUE))*$EP27 -> 0 | EZ27: =AND($ET27="S-Curve",EZ$24>=$EQ27,EZ$24<=$ER27)*(NORMDIST((YEAR(EZ$24)-YEAR($EQ27))*12+MONTH(EZ$24)-MONTH($EQ27)+1,$ES27/2,$EU27,TRUE)-NORMDIST((YEAR(EZ$24)-YEAR($EQ27))*12+MONTH(EZ$24)-MONTH($EQ27),$ES27/2,$EU27,TRUE))/(1-2*NORMDIST(0,$ES27/2,$EU27,TRUE))*$EP27 -> 0 | FA27: =AND($ET27="S-Curve",FA$24>=$EQ27,FA$24<=$ER27)*(NORMDIST((YEAR(FA$24)-YEAR($EQ27))*12+MONTH(FA$24)-MONTH($EQ27)+1,$ES27/2,$EU27,TRUE)-NORMDIST((YEAR(FA$24)-YEAR($EQ27))*12+MONTH(FA$24)-MONTH($EQ27),$ES27/2,$EU27,TRUE))/(1-2*NORMDIST(0,$ES27/2,$EU27,TRUE))*$EP27 -> 0 | FB27: =AND($ET27="S-Curve",FB$24>=$EQ27,FB$24<=$ER27)*(NORMDIST((YEAR(FB$24)-YEAR($EQ27))*12+MONTH(FB$24)-MONTH($EQ27)+1,$ES27/2,$EU27,TRUE)-NORMDIST((YEAR(FB$24)-YEAR($EQ27))*12+MONTH(FB$24)-MONTH($EQ27),$ES27/2,$EU27,TRUE))/(1-2*NORMDIST(0,$ES27/2,$EU27,TRUE))*$EP27 -> 0 | FC27: =AND($ET27="S-Curve",FC$24>=$EQ27,FC$24<=$ER27)*(NORMDIST((YEAR(FC$24)-YEAR($EQ27))*12+MONTH(FC$24)-MONTH($EQ27)+1,$ES27/2,$EU27,TRUE)-NORMDIST((YEAR(FC$24)-YEAR($EQ27))*12+MONTH(FC$24)-MONTH($EQ27),$ES27/2,$EU27,TRUE))/(1-2*NORMDIST(0,$ES27/2,$EU27,TRUE))*$EP27 -> 0 | ... JX27: =AND($ET27="S-Curve",JX$24>=$EQ27,JX$24<=$ER27)*(NORMDIST((YEAR(JX$24)-YEAR($EQ27))*12+MONTH(JX$24)-MONTH($EQ27)+1,$ES27/2,$EU27,TRUE)-NORMDIST((YEAR(JX$24)-YEAR($EQ27))*12+MONTH(JX$24)-MONTH($EQ27),$ES27/2,$EU27,TRUE))/(1-2*NORMDIST(0,$ES27/2,$EU27,TRUE))*$EP27 -> 0 | JZ27: =B27 -> 0 | KB27: =D27 -> 0 | KC27: =E27 -> 0 | KD27: =KC27-KB27+1 -> 1 | KE27: =I27 -> 91570000 | KF27: =AND(KF$23>=$KB27,KF$23<=$KC27)*(IF($F27="Steady Growth",KF$23-$KB27,$KC27-KF$23)+1)/($KD27*($KD27+1)/2)*$KE27 -> 91570000 | KG27: =AND(KG$23>=$KB27,KG$23<=$KC27)*(IF($F27="Steady Growth",KG$23-$KB27,$KC27-KG$23)+1)/($KD27*($KD27+1)/2)*$KE27 -> 0 | KH27: =AND(KH$23>=$KB27,KH$23<=$KC27)*(IF($F27="Steady Growth",KH$23-$KB27,$KC27-KH$23)+1)/($KD27*($KD27+1)/2)*$KE27 -> 0 | KI27: =AND(KI$23>=$KB27,KI$23<=$KC27)*(IF($F27="Steady Growth",KI$23-$KB27,$KC27-KI$23)+1)/($KD27*($KD27+1)/2)*$KE27 -> 0 | KJ27: =AND(KJ$23>=$KB27,KJ$23<=$KC27)*(IF($F27="Steady Growth",KJ$23-$KB27,$KC27-KJ$23)+1)/($KD27*($KD27+1)/2)*$KE27 -> 0 | KK27: =AND(KK$23>=$KB27,KK$23<=$KC27)*(IF($F27="Steady Growth",KK$23-$KB27,$KC27-KK$23)+1)/($KD27*($KD27+1)/2)*$KE27 -> 0 | KL27: =AND(KL$23>=$KB27,KL$23<=$KC27)*(IF($F27="Steady Growth",KL$23-$KB27,$KC27-KL$23)+1)/($KD27*($KD27+1)/2)*$KE27 -> 0 | KM27: =AND(KM$23>=$KB27,KM$23<=$KC27)*(IF($F27="Steady Growth",KM$23-$KB27,$KC27-KM$23)+1)/($KD27*($KD27+1)/2)*$KE27 -> 0 | ... PH27: =AND(PH$23>=$KB27,PH$23<=$KC27)*(IF($F27="Steady Growth",PH$23-$KB27,$KC27-PH$23)+1)/($KD27*($KD27+1)/2)*$KE27 -> 0
B28: Interim site acquisition lease deposit | C28: 0 | E28: 0 | F28: Straight-Line | G28: =I28/Units_SF_M2 -> 9.5577465 | I28: ='URWLD COMPANY INPUTS'!$D$89*1000000 -> 750000 | K28: =IF(ROUND(SUM(L28:EN28),0)=ROUND(I28,0),"","Incomplete") | L28: =AND(L$23>=$D28,L$23<=$E28)*(OR($F28="Straight-Line",$F28="Detail")*($I28/$ES28)+($F28="S-Curve")*EV28+OR($F28="Steady Growth",$F28="Steady Decline")*KF28) -> 750000 | M28: =AND(M$23>=$D28,M$23<=$E28)*(OR($F28="Straight-Line",$F28="Detail")*($I28/$ES28)+($F28="S-Curve")*EW28+OR($F28="Steady Growth",$F28="Steady Decline")*KG28) -> 0 | N28: =AND(N$23>=$D28,N$23<=$E28)*(OR($F28="Straight-Line",$F28="Detail")*($I28/$ES28)+($F28="S-Curve")*EX28+OR($F28="Steady Growth",$F28="Steady Decline")*KH28) -> 0 | O28: =AND(O$23>=$D28,O$23<=$E28)*(OR($F28="Straight-Line",$F28="Detail")*($I28/$ES28)+($F28="S-Curve")*EY28+OR($F28="Steady Growth",$F28="Steady Decline")*KI28) -> 0 | P28: =AND(P$23>=$D28,P$23<=$E28)*(OR($F28="Straight-Line",$F28="Detail")*($I28/$ES28)+($F28="S-Curve")*EZ28+OR($F28="Steady Growth",$F28="Steady Decline")*KJ28) -> 0 | Q28: =AND(Q$23>=$D28,Q$23<=$E28)*(OR($F28="Straight-Line",$F28="Detail")*($I28/$ES28)+($F28="S-Curve")*FA28+OR($F28="Steady Growth",$F28="Steady Decline")*KK28) -> 0 | R28: =AND(R$23>=$D28,R$23<=$E28)*(OR($F28="Straight-Line",$F28="Detail")*($I28/$ES28)+($F28="S-Curve")*FB28+OR($F28="Steady Growth",$F28="Steady Decline")*KL28) -> 0 | S28: =AND(S$23>=$D28,S$23<=$E28)*(OR($F28="Straight-Line",$F28="Detail")*($I28/$ES28)+($F28="S-Curve")*FC28+OR($F28="Steady Growth",$F28="Steady Decline")*KM28) -> 0 | ... EN28: =AND(EN$23>=$D28,EN$23<=$E28)*(OR($F28="Straight-Line",$F28="Detail")*($I28/$ES28)+($F28="S-Curve")*JX28+OR($F28="Steady Growth",$F28="Steady Decline")*PH28) -> 0 | EP28: =I28 -> 750000 | EQ28: =INDEX($L$24:$EN$24,1,$D28+1) -> 46203 | ER28: =INDEX($L$24:$EN$24,1,$E28+1) -> 46203 | ES28: =+E28-D28+1 -> 1 | ET28: =F28 -> Straight-Line | EU28: =ES28/Scurve_Dist -> 0.16666667 | EV28: =AND($ET28="S-Curve",EV$24>=$EQ28,EV$24<=$ER28)*(NORMDIST((YEAR(EV$24)-YEAR($EQ28))*12+MONTH(EV$24)-MONTH($EQ28)+1,$ES28/2,$EU28,TRUE)-NORMDIST((YEAR(EV$24)-YEAR($EQ28))*12+MONTH(EV$24)-MONTH($EQ28),$ES28/2,$EU28,TRUE))/(1-2*NORMDIST(0,$ES28/2,$EU28,TRUE))*$EP28 -> 0 | EW28: =AND($ET28="S-Curve",EW$24>=$EQ28,EW$24<=$ER28)*(NORMDIST((YEAR(EW$24)-YEAR($EQ28))*12+MONTH(EW$24)-MONTH($EQ28)+1,$ES28/2,$EU28,TRUE)-NORMDIST((YEAR(EW$24)-YEAR($EQ28))*12+MONTH(EW$24)-MONTH($EQ28),$ES28/2,$EU28,TRUE))/(1-2*NORMDIST(0,$ES28/2,$EU28,TRUE))*$EP28 -> 0 | EX28: =AND($ET28="S-Curve",EX$24>=$EQ28,EX$24<=$ER28)*(NORMDIST((YEAR(EX$24)-YEAR($EQ28))*12+MONTH(EX$24)-MONTH($EQ28)+1,$ES28/2,$EU28,TRUE)-NORMDIST((YEAR(EX$24)-YEAR($EQ28))*12+MONTH(EX$24)-MONTH($EQ28),$ES28/2,$EU28,TRUE))/(1-2*NORMDIST(0,$ES28/2,$EU28,TRUE))*$EP28 -> 0 | EY28: =AND($ET28="S-Curve",EY$24>=$EQ28,EY$24<=$ER28)*(NORMDIST((YEAR(EY$24)-YEAR($EQ28))*12+MONTH(EY$24)-MONTH($EQ28)+1,$ES28/2,$EU28,TRUE)-NORMDIST((YEAR(EY$24)-YEAR($EQ28))*12+MONTH(EY$24)-MONTH($EQ28),$ES28/2,$EU28,TRUE))/(1-2*NORMDIST(0,$ES28/2,$EU28,TRUE))*$EP28 -> 0 | EZ28: =AND($ET28="S-Curve",EZ$24>=$EQ28,EZ$24<=$ER28)*(NORMDIST((YEAR(EZ$24)-YEAR($EQ28))*12+MONTH(EZ$24)-MONTH($EQ28)+1,$ES28/2,$EU28,TRUE)-NORMDIST((YEAR(EZ$24)-YEAR($EQ28))*12+MONTH(EZ$24)-MONTH($EQ28),$ES28/2,$EU28,TRUE))/(1-2*NORMDIST(0,$ES28/2,$EU28,TRUE))*$EP28 -> 0 | FA28: =AND($ET28="S-Curve",FA$24>=$EQ28,FA$24<=$ER28)*(NORMDIST((YEAR(FA$24)-YEAR($EQ28))*12+MONTH(FA$24)-MONTH($EQ28)+1,$ES28/2,$EU28,TRUE)-NORMDIST((YEAR(FA$24)-YEAR($EQ28))*12+MONTH(FA$24)-MONTH($EQ28),$ES28/2,$EU28,TRUE))/(1-2*NORMDIST(0,$ES28/2,$EU28,TRUE))*$EP28 -> 0 | FB28: =AND($ET28="S-Curve",FB$24>=$EQ28,FB$24<=$ER28)*(NORMDIST((YEAR(FB$24)-YEAR($EQ28))*12+MONTH(FB$24)-MONTH($EQ28)+1,$ES28/2,$EU28,TRUE)-NORMDIST((YEAR(FB$24)-YEAR($EQ28))*12+MONTH(FB$24)-MONTH($EQ28),$ES28/2,$EU28,TRUE))/(1-2*NORMDIST(0,$ES28/2,$EU28,TRUE))*$EP28 -> 0 | FC28: =AND($ET28="S-Curve",FC$24>=$EQ28,FC$24<=$ER28)*(NORMDIST((YEAR(FC$24)-YEAR($EQ28))*12+MONTH(FC$24)-MONTH($EQ28)+1,$ES28/2,$EU28,TRUE)-NORMDIST((YEAR(FC$24)-YEAR($EQ28))*12+MONTH(FC$24)-MONTH($EQ28),$ES28/2,$EU28,TRUE))/(1-2*NORMDIST(0,$ES28/2,$EU28,TRUE))*$EP28 -> 0 | ... JX28: =AND($ET28="S-Curve",JX$24>=$EQ28,JX$24<=$ER28)*(NORMDIST((YEAR(JX$24)-YEAR($EQ28))*12+MONTH(JX$24)-MONTH($EQ28)+1,$ES28/2,$EU28,TRUE)-NORMDIST((YEAR(JX$24)-YEAR($EQ28))*12+MONTH(JX$24)-MONTH($EQ28),$ES28/2,$EU28,TRUE))/(1-2*NORMDIST(0,$ES28/2,$EU28,TRUE))*$EP28 -> 0 | JZ28: =B28 -> Interim site acquisition lease deposit | KB28: =D28 -> 0 | KC28: =E28 -> 0 | KD28: =KC28-KB28+1 -> 1 | KE28: =I28 -> 750000 | KF28: =AND(KF$23>=$KB28,KF$23<=$KC28)*(IF($F28="Steady Growth",KF$23-$KB28,$KC28-KF$23)+1)/($KD28*($KD28+1)/2)*$KE28 -> 750000 | KG28: =AND(KG$23>=$KB28,KG$23<=$KC28)*(IF($F28="Steady Growth",KG$23-$KB28,$KC28-KG$23)+1)/($KD28*($KD28+1)/2)*$KE28 -> 0 | KH28: =AND(KH$23>=$KB28,KH$23<=$KC28)*(IF($F28="Steady Growth",KH$23-$KB28,$KC28-KH$23)+1)/($KD28*($KD28+1)/2)*$KE28 -> 0 | KI28: =AND(KI$23>=$KB28,KI$23<=$KC28)*(IF($F28="Steady Growth",KI$23-$KB28,$KC28-KI$23)+1)/($KD28*($KD28+1)/2)*$KE28 -> 0 | KJ28: =AND(KJ$23>=$KB28,KJ$23<=$KC28)*(IF($F28="Steady Growth",KJ$23-$KB28,$KC28-KJ$23)+1)/($KD28*($KD28+1)/2)*$KE28 -> 0 | KK28: =AND(KK$23>=$KB28,KK$23<=$KC28)*(IF($F28="Steady Growth",KK$23-$KB28,$KC28-KK$23)+1)/($KD28*($KD28+1)/2)*$KE28 -> 0 | KL28: =AND(KL$23>=$KB28,KL$23<=$KC28)*(IF($F28="Steady Growth",KL$23-$KB28,$KC28-KL$23)+1)/($KD28*($KD28+1)/2)*$KE28 -> 0 | KM28: =AND(KM$23>=$KB28,KM$23<=$KC28)*(IF($F28="Steady Growth",KM$23-$KB28,$KC28-KM$23)+1)/($KD28*($KD28+1)/2)*$KE28 -> 0 | ... PH28: =AND(PH$23>=$KB28,PH$23<=$KC28)*(IF($F28="Steady Growth",PH$23-$KB28,$KC28-PH$23)+1)/($KD28*($KD28+1)/2)*$KE28 -> 0
B29: Other acquisition costs | C29: 0 | E29: 0 | F29: Straight-Line | G29: =I29/Units_SF_M2 -> 0 | I29: 0 | K29: =IF(ROUND(SUM(L29:EN29),0)=ROUND(I29,0),"","Incomplete") | L29: =AND(L$23>=$D29,L$23<=$E29)*(OR($F29="Straight-Line",$F29="Detail")*($I29/$ES29)+($F29="S-Curve")*EV29+OR($F29="Steady Growth",$F29="Steady Decline")*KF29) -> 0 | M29: =AND(M$23>=$D29,M$23<=$E29)*(OR($F29="Straight-Line",$F29="Detail")*($I29/$ES29)+($F29="S-Curve")*EW29+OR($F29="Steady Growth",$F29="Steady Decline")*KG29) -> 0 | N29: =AND(N$23>=$D29,N$23<=$E29)*(OR($F29="Straight-Line",$F29="Detail")*($I29/$ES29)+($F29="S-Curve")*EX29+OR($F29="Steady Growth",$F29="Steady Decline")*KH29) -> 0 | O29: =AND(O$23>=$D29,O$23<=$E29)*(OR($F29="Straight-Line",$F29="Detail")*($I29/$ES29)+($F29="S-Curve")*EY29+OR($F29="Steady Growth",$F29="Steady Decline")*KI29) -> 0 | P29: =AND(P$23>=$D29,P$23<=$E29)*(OR($F29="Straight-Line",$F29="Detail")*($I29/$ES29)+($F29="S-Curve")*EZ29+OR($F29="Steady Growth",$F29="Steady Decline")*KJ29) -> 0 | Q29: =AND(Q$23>=$D29,Q$23<=$E29)*(OR($F29="Straight-Line",$F29="Detail")*($I29/$ES29)+($F29="S-Curve")*FA29+OR($F29="Steady Growth",$F29="Steady Decline")*KK29) -> 0 | R29: =AND(R$23>=$D29,R$23<=$E29)*(OR($F29="Straight-Line",$F29="Detail")*($I29/$ES29)+($F29="S-Curve")*FB29+OR($F29="Steady Growth",$F29="Steady Decline")*KL29) -> 0 | S29: =AND(S$23>=$D29,S$23<=$E29)*(OR($F29="Straight-Line",$F29="Detail")*($I29/$ES29)+($F29="S-Curve")*FC29+OR($F29="Steady Growth",$F29="Steady Decline")*KM29) -> 0 | ... EN29: =AND(EN$23>=$D29,EN$23<=$E29)*(OR($F29="Straight-Line",$F29="Detail")*($I29/$ES29)+($F29="S-Curve")*JX29+OR($F29="Steady Growth",$F29="Steady Decline")*PH29) -> 0 | EP29: =I29 -> 0 | EQ29: =INDEX($L$24:$EN$24,1,$D29+1) -> 46203 | ER29: =INDEX($L$24:$EN$24,1,$E29+1) -> 46203 | ES29: =+E29-D29+1 -> 1 | ET29: =F29 -> Straight-Line | EU29: =ES29/Scurve_Dist -> 0.16666667 | EV29: =AND($ET29="S-Curve",EV$24>=$EQ29,EV$24<=$ER29)*(NORMDIST((YEAR(EV$24)-YEAR($EQ29))*12+MONTH(EV$24)-MONTH($EQ29)+1,$ES29/2,$EU29,TRUE)-NORMDIST((YEAR(EV$24)-YEAR($EQ29))*12+MONTH(EV$24)-MONTH($EQ29),$ES29/2,$EU29,TRUE))/(1-2*NORMDIST(0,$ES29/2,$EU29,TRUE))*$EP29 -> 0 | EW29: =AND($ET29="S-Curve",EW$24>=$EQ29,EW$24<=$ER29)*(NORMDIST((YEAR(EW$24)-YEAR($EQ29))*12+MONTH(EW$24)-MONTH($EQ29)+1,$ES29/2,$EU29,TRUE)-NORMDIST((YEAR(EW$24)-YEAR($EQ29))*12+MONTH(EW$24)-MONTH($EQ29),$ES29/2,$EU29,TRUE))/(1-2*NORMDIST(0,$ES29/2,$EU29,TRUE))*$EP29 -> 0 | EX29: =AND($ET29="S-Curve",EX$24>=$EQ29,EX$24<=$ER29)*(NORMDIST((YEAR(EX$24)-YEAR($EQ29))*12+MONTH(EX$24)-MONTH($EQ29)+1,$ES29/2,$EU29,TRUE)-NORMDIST((YEAR(EX$24)-YEAR($EQ29))*12+MONTH(EX$24)-MONTH($EQ29),$ES29/2,$EU29,TRUE))/(1-2*NORMDIST(0,$ES29/2,$EU29,TRUE))*$EP29 -> 0 | EY29: =AND($ET29="S-Curve",EY$24>=$EQ29,EY$24<=$ER29)*(NORMDIST((YEAR(EY$24)-YEAR($EQ29))*12+MONTH(EY$24)-MONTH($EQ29)+1,$ES29/2,$EU29,TRUE)-NORMDIST((YEAR(EY$24)-YEAR($EQ29))*12+MONTH(EY$24)-MONTH($EQ29),$ES29/2,$EU29,TRUE))/(1-2*NORMDIST(0,$ES29/2,$EU29,TRUE))*$EP29 -> 0 | EZ29: =AND($ET29="S-Curve",EZ$24>=$EQ29,EZ$24<=$ER29)*(NORMDIST((YEAR(EZ$24)-YEAR($EQ29))*12+MONTH(EZ$24)-MONTH($EQ29)+1,$ES29/2,$EU29,TRUE)-NORMDIST((YEAR(EZ$24)-YEAR($EQ29))*12+MONTH(EZ$24)-MONTH($EQ29),$ES29/2,$EU29,TRUE))/(1-2*NORMDIST(0,$ES29/2,$EU29,TRUE))*$EP29 -> 0 | FA29: =AND($ET29="S-Curve",FA$24>=$EQ29,FA$24<=$ER29)*(NORMDIST((YEAR(FA$24)-YEAR($EQ29))*12+MONTH(FA$24)-MONTH($EQ29)+1,$ES29/2,$EU29,TRUE)-NORMDIST((YEAR(FA$24)-YEAR($EQ29))*12+MONTH(FA$24)-MONTH($EQ29),$ES29/2,$EU29,TRUE))/(1-2*NORMDIST(0,$ES29/2,$EU29,TRUE))*$EP29 -> 0 | FB29: =AND($ET29="S-Curve",FB$24>=$EQ29,FB$24<=$ER29)*(NORMDIST((YEAR(FB$24)-YEAR($EQ29))*12+MONTH(FB$24)-MONTH($EQ29)+1,$ES29/2,$EU29,TRUE)-NORMDIST((YEAR(FB$24)-YEAR($EQ29))*12+MONTH(FB$24)-MONTH($EQ29),$ES29/2,$EU29,TRUE))/(1-2*NORMDIST(0,$ES29/2,$EU29,TRUE))*$EP29 -> 0 | FC29: =AND($ET29="S-Curve",FC$24>=$EQ29,FC$24<=$ER29)*(NORMDIST((YEAR(FC$24)-YEAR($EQ29))*12+MONTH(FC$24)-MONTH($EQ29)+1,$ES29/2,$EU29,TRUE)-NORMDIST((YEAR(FC$24)-YEAR($EQ29))*12+MONTH(FC$24)-MONTH($EQ29),$ES29/2,$EU29,TRUE))/(1-2*NORMDIST(0,$ES29/2,$EU29,TRUE))*$EP29 -> 0 | ... JX29: =AND($ET29="S-Curve",JX$24>=$EQ29,JX$24<=$ER29)*(NORMDIST((YEAR(JX$24)-YEAR($EQ29))*12+MONTH(JX$24)-MONTH($EQ29)+1,$ES29/2,$EU29,TRUE)-NORMDIST((YEAR(JX$24)-YEAR($EQ29))*12+MONTH(JX$24)-MONTH($EQ29),$ES29/2,$EU29,TRUE))/(1-2*NORMDIST(0,$ES29/2,$EU29,TRUE))*$EP29 -> 0 | JZ29: =B29 -> Other acquisition costs | KB29: =D29 -> 0 | KC29: =E29 -> 0 | KD29: =KC29-KB29+1 -> 1 | KE29: =I29 -> 0 | KF29: =AND(KF$23>=$KB29,KF$23<=$KC29)*(IF($F29="Steady Growth",KF$23-$KB29,$KC29-KF$23)+1)/($KD29*($KD29+1)/2)*$KE29 -> 0 | KG29: =AND(KG$23>=$KB29,KG$23<=$KC29)*(IF($F29="Steady Growth",KG$23-$KB29,$KC29-KG$23)+1)/($KD29*($KD29+1)/2)*$KE29 -> 0 | KH29: =AND(KH$23>=$KB29,KH$23<=$KC29)*(IF($F29="Steady Growth",KH$23-$KB29,$KC29-KH$23)+1)/($KD29*($KD29+1)/2)*$KE29 -> 0 | KI29: =AND(KI$23>=$KB29,KI$23<=$KC29)*(IF($F29="Steady Growth",KI$23-$KB29,$KC29-KI$23)+1)/($KD29*($KD29+1)/2)*$KE29 -> 0 | KJ29: =AND(KJ$23>=$KB29,KJ$23<=$KC29)*(IF($F29="Steady Growth",KJ$23-$KB29,$KC29-KJ$23)+1)/($KD29*($KD29+1)/2)*$KE29 -> 0 | KK29: =AND(KK$23>=$KB29,KK$23<=$KC29)*(IF($F29="Steady Growth",KK$23-$KB29,$KC29-KK$23)+1)/($KD29*($KD29+1)/2)*$KE29 -> 0 | KL29: =AND(KL$23>=$KB29,KL$23<=$KC29)*(IF($F29="Steady Growth",KL$23-$KB29,$KC29-KL$23)+1)/($KD29*($KD29+1)/2)*$KE29 -> 0 | KM29: =AND(KM$23>=$KB29,KM$23<=$KC29)*(IF($F29="Steady Growth",KM$23-$KB29,$KC29-KM$23)+1)/($KD29*($KD29+1)/2)*$KE29 -> 0 | ... PH29: =AND(PH$23>=$KB29,PH$23<=$KC29)*(IF($F29="Steady Growth",PH$23-$KB29,$KC29-PH$23)+1)/($KD29*($KD29+1)/2)*$KE29 -> 0
B30: ARENA grant / development incentive (funding source; excluded from gross cost) | C30: 0 | E30: 0 | F30: Straight-Line | G30: =I30/Units_SF_M2 -> 0 | I30: =MAX(0,'URWLD COMPANY INPUTS'!$D$750*1000000) -> 0 | K30: =IF(ROUND(SUM(L30:EN30),0)=ROUND(I30,0),"","Incomplete") | L30: =AND(L$23>=$D30,L$23<=$E30)*(OR($F30="Straight-Line",$F30="Detail")*($I30/$ES30)+($F30="S-Curve")*EV30+OR($F30="Steady Growth",$F30="Steady Decline")*KF30) -> 0 | M30: =AND(M$23>=$D30,M$23<=$E30)*(OR($F30="Straight-Line",$F30="Detail")*($I30/$ES30)+($F30="S-Curve")*EW30+OR($F30="Steady Growth",$F30="Steady Decline")*KG30) -> 0 | N30: =AND(N$23>=$D30,N$23<=$E30)*(OR($F30="Straight-Line",$F30="Detail")*($I30/$ES30)+($F30="S-Curve")*EX30+OR($F30="Steady Growth",$F30="Steady Decline")*KH30) -> 0 | O30: =AND(O$23>=$D30,O$23<=$E30)*(OR($F30="Straight-Line",$F30="Detail")*($I30/$ES30)+($F30="S-Curve")*EY30+OR($F30="Steady Growth",$F30="Steady Decline")*KI30) -> 0 | P30: =AND(P$23>=$D30,P$23<=$E30)*(OR($F30="Straight-Line",$F30="Detail")*($I30/$ES30)+($F30="S-Curve")*EZ30+OR($F30="Steady Growth",$F30="Steady Decline")*KJ30) -> 0 | Q30: =AND(Q$23>=$D30,Q$23<=$E30)*(OR($F30="Straight-Line",$F30="Detail")*($I30/$ES30)+($F30="S-Curve")*FA30+OR($F30="Steady Growth",$F30="Steady Decline")*KK30) -> 0 | R30: =AND(R$23>=$D30,R$23<=$E30)*(OR($F30="Straight-Line",$F30="Detail")*($I30/$ES30)+($F30="S-Curve")*FB30+OR($F30="Steady Growth",$F30="Steady Decline")*KL30) -> 0 | S30: =AND(S$23>=$D30,S$23<=$E30)*(OR($F30="Straight-Line",$F30="Detail")*($I30/$ES30)+($F30="S-Curve")*FC30+OR($F30="Steady Growth",$F30="Steady Decline")*KM30) -> 0 | ... EN30: =AND(EN$23>=$D30,EN$23<=$E30)*(OR($F30="Straight-Line",$F30="Detail")*($I30/$ES30)+($F30="S-Curve")*JX30+OR($F30="Steady Growth",$F30="Steady Decline")*PH30) -> 0 | EP30: =I30 -> 0 | EQ30: =INDEX($L$24:$EN$24,1,$D30+1) -> 46203 | ER30: =INDEX($L$24:$EN$24,1,$E30+1) -> 46203 | ES30: =+E30-D30+1 -> 1 | ET30: =F30 -> Straight-Line | EU30: =ES30/Scurve_Dist -> 0.16666667 | EV30: =AND($ET30="S-Curve",EV$24>=$EQ30,EV$24<=$ER30)*(NORMDIST((YEAR(EV$24)-YEAR($EQ30))*12+MONTH(EV$24)-MONTH($EQ30)+1,$ES30/2,$EU30,TRUE)-NORMDIST((YEAR(EV$24)-YEAR($EQ30))*12+MONTH(EV$24)-MONTH($EQ30),$ES30/2,$EU30,TRUE))/(1-2*NORMDIST(0,$ES30/2,$EU30,TRUE))*$EP30 -> 0 | EW30: =AND($ET30="S-Curve",EW$24>=$EQ30,EW$24<=$ER30)*(NORMDIST((YEAR(EW$24)-YEAR($EQ30))*12+MONTH(EW$24)-MONTH($EQ30)+1,$ES30/2,$EU30,TRUE)-NORMDIST((YEAR(EW$24)-YEAR($EQ30))*12+MONTH(EW$24)-MONTH($EQ30),$ES30/2,$EU30,TRUE))/(1-2*NORMDIST(0,$ES30/2,$EU30,TRUE))*$EP30 -> 0 | EX30: =AND($ET30="S-Curve",EX$24>=$EQ30,EX$24<=$ER30)*(NORMDIST((YEAR(EX$24)-YEAR($EQ30))*12+MONTH(EX$24)-MONTH($EQ30)+1,$ES30/2,$EU30,TRUE)-NORMDIST((YEAR(EX$24)-YEAR($EQ30))*12+MONTH(EX$24)-MONTH($EQ30),$ES30/2,$EU30,TRUE))/(1-2*NORMDIST(0,$ES30/2,$EU30,TRUE))*$EP30 -> 0 | EY30: =AND($ET30="S-Curve",EY$24>=$EQ30,EY$24<=$ER30)*(NORMDIST((YEAR(EY$24)-YEAR($EQ30))*12+MONTH(EY$24)-MONTH($EQ30)+1,$ES30/2,$EU30,TRUE)-NORMDIST((YEAR(EY$24)-YEAR($EQ30))*12+MONTH(EY$24)-MONTH($EQ30),$ES30/2,$EU30,TRUE))/(1-2*NORMDIST(0,$ES30/2,$EU30,TRUE))*$EP30 -> 0 | EZ30: =AND($ET30="S-Curve",EZ$24>=$EQ30,EZ$24<=$ER30)*(NORMDIST((YEAR(EZ$24)-YEAR($EQ30))*12+MONTH(EZ$24)-MONTH($EQ30)+1,$ES30/2,$EU30,TRUE)-NORMDIST((YEAR(EZ$24)-YEAR($EQ30))*12+MONTH(EZ$24)-MONTH($EQ30),$ES30/2,$EU30,TRUE))/(1-2*NORMDIST(0,$ES30/2,$EU30,TRUE))*$EP30 -> 0 | FA30: =AND($ET30="S-Curve",FA$24>=$EQ30,FA$24<=$ER30)*(NORMDIST((YEAR(FA$24)-YEAR($EQ30))*12+MONTH(FA$24)-MONTH($EQ30)+1,$ES30/2,$EU30,TRUE)-NORMDIST((YEAR(FA$24)-YEAR($EQ30))*12+MONTH(FA$24)-MONTH($EQ30),$ES30/2,$EU30,TRUE))/(1-2*NORMDIST(0,$ES30/2,$EU30,TRUE))*$EP30 -> 0 | FB30: =AND($ET30="S-Curve",FB$24>=$EQ30,FB$24<=$ER30)*(NORMDIST((YEAR(FB$24)-YEAR($EQ30))*12+MONTH(FB$24)-MONTH($EQ30)+1,$ES30/2,$EU30,TRUE)-NORMDIST((YEAR(FB$24)-YEAR($EQ30))*12+MONTH(FB$24)-MONTH($EQ30),$ES30/2,$EU30,TRUE))/(1-2*NORMDIST(0,$ES30/2,$EU30,TRUE))*$EP30 -> 0 | FC30: =AND($ET30="S-Curve",FC$24>=$EQ30,FC$24<=$ER30)*(NORMDIST((YEAR(FC$24)-YEAR($EQ30))*12+MONTH(FC$24)-MONTH($EQ30)+1,$ES30/2,$EU30,TRUE)-NORMDIST((YEAR(FC$24)-YEAR($EQ30))*12+MONTH(FC$24)-MONTH($EQ30),$ES30/2,$EU30,TRUE))/(1-2*NORMDIST(0,$ES30/2,$EU30,TRUE))*$EP30 -> 0 | ... JX30: =AND($ET30="S-Curve",JX$24>=$EQ30,JX$24<=$ER30)*(NORMDIST((YEAR(JX$24)-YEAR($EQ30))*12+MONTH(JX$24)-MONTH($EQ30)+1,$ES30/2,$EU30,TRUE)-NORMDIST((YEAR(JX$24)-YEAR($EQ30))*12+MONTH(JX$24)-MONTH($EQ30),$ES30/2,$EU30,TRUE))/(1-2*NORMDIST(0,$ES30/2,$EU30,TRUE))*$EP30 -> 0 | JZ30: =B30 -> ARENA grant / development incentive (funding source; excluded from gross cost) | KB30: =D30 -> 0 | KC30: =E30 -> 0 | KD30: =KC30-KB30+1 -> 1 | KE30: =I30 -> 0 | KF30: =AND(KF$23>=$KB30,KF$23<=$KC30)*(IF($F30="Steady Growth",KF$23-$KB30,$KC30-KF$23)+1)/($KD30*($KD30+1)/2)*$KE30 -> 0 | KG30: =AND(KG$23>=$KB30,KG$23<=$KC30)*(IF($F30="Steady Growth",KG$23-$KB30,$KC30-KG$23)+1)/($KD30*($KD30+1)/2)*$KE30 -> 0 | KH30: =AND(KH$23>=$KB30,KH$23<=$KC30)*(IF($F30="Steady Growth",KH$23-$KB30,$KC30-KH$23)+1)/($KD30*($KD30+1)/2)*$KE30 -> 0 | KI30: =AND(KI$23>=$KB30,KI$23<=$KC30)*(IF($F30="Steady Growth",KI$23-$KB30,$KC30-KI$23)+1)/($KD30*($KD30+1)/2)*$KE30 -> 0 | KJ30: =AND(KJ$23>=$KB30,KJ$23<=$KC30)*(IF($F30="Steady Growth",KJ$23-$KB30,$KC30-KJ$23)+1)/($KD30*($KD30+1)/2)*$KE30 -> 0 | KK30: =AND(KK$23>=$KB30,KK$23<=$KC30)*(IF($F30="Steady Growth",KK$23-$KB30,$KC30-KK$23)+1)/($KD30*($KD30+1)/2)*$KE30 -> 0 | KL30: =AND(KL$23>=$KB30,KL$23<=$KC30)*(IF($F30="Steady Growth",KL$23-$KB30,$KC30-KL$23)+1)/($KD30*($KD30+1)/2)*$KE30 -> 0 | KM30: =AND(KM$23>=$KB30,KM$23<=$KC30)*(IF($F30="Steady Growth",KM$23-$KB30,$KC30-KM$23)+1)/($KD30*($KD30+1)/2)*$KE30 -> 0 | ... PH30: =AND(PH$23>=$KB30,PH$23<=$KC30)*(IF($F30="Steady Growth",PH$23-$KB30,$KC30-PH$23)+1)/($KD30*($KD30+1)/2)*$KE30 -> 0
B31: Total Land Costs | C31: =MIN(D27:D30) -> 0 | E31: =MAX(E27:E30) -> 0 | F31: =SUM(H27:H30) -> 0 | I31: =SUM(I27:I30) -> 92320000 | K31: =IF(ROUND(SUM(L31:EN31),0)=ROUND(I31,0),"","Incomplete") | L31: =SUM(L27:L30) -> 92320000 | M31: =SUM(M27:M30) -> 0 | N31: =SUM(N27:N30) -> 0 | O31: =SUM(O27:O30) -> 0 | P31: =SUM(P27:P30) -> 0 | Q31: =SUM(Q27:Q30) -> 0 | R31: =SUM(R27:R30) -> 0 | S31: =SUM(S27:S30) -> 0 | ... EN31: =SUM(EN27:EN30) -> 0 | EQ31: # of Land Cost Items | ER31: =COUNTA($B$27:$B$30) -> 3 | JZ31: =B31 -> Total Land Costs
JZ33: =B33 -> 0
C34: 1 | E34: =(VALUE(RIGHT('URWLD COMPANY INPUTS'!$F$46,4))-VALUE(RIGHT('URWLD COMPANY INPUTS'!$F$45,4)))*12+(VALUE(MID('URWLD COMPANY INPUTS'!$F$46,2,1))-VALUE(MID('URWLD COMPANY INPUTS'!$F$45,2,1)))*3+3 -> 36 | F34: S-Curve | G34: =I34/Units_SF_M2 -> 4363.7231 | I34: =('URWLD COMPANY INPUTS'!$E$192/'URWLD COMPANY INPUTS'!$E$53+'URWLD COMPANY INPUTS'!$F$194*'URWLD COMPANY INPUTS'!$E$52/'URWLD COMPANY INPUTS'!$E$53+'URWLD COMPANY INPUTS'!$F$197*'URWLD COMPANY INPUTS'!$E$52/'URWLD COMPANY INPUTS'!$E$53+'URWLD COMPANY INPUTS'!$F$198*'URWLD COMPANY INPUTS'!$E$52/'URWLD COMPANY INPUTS'!$E$53*25%+'URWLD COMPANY INPUTS'!$F$205*'URWLD COMPANY INPUTS'!$E$52/'URWLD COMPANY INPUTS'!$E$53)+SUM('URWLD COMPANY INPUTS'!$D$411:$D$414)+'URWLD COMPANY INPUTS'!$D$597+'URWLD COMPANY INPUTS'!$D$628*50%+'URWLD COMPANY INPUTS'!$D$404*1000000+1200000+SUM('URWLD COMPANY INPUTS'!$D$423:$D$425)+'URWLD COMPANY INPUTS'!$D$604*1000000+'URWLD COMPANY INPUTS'!$D$613*1000000+SUM('URWLD COMPANY INPUTS'!$D$657:$D$665)+SUM('URWLD COMPANY INPUTS'!$D$620:$D$621)*1000000+264000+'URWLD COMPANY INPUTS'!$D$636+'URWLD COMPANY INPUTS'!$D$638+SUM('URWLD COMPANY INPUTS'!$D$703:$D$706)*1000000+SUM('URWLD COMPANY INPUTS'!$D$709,'URWLD COMPANY INPUTS'!$D$712,'URWLD COMPANY INPUTS'!$D$714,'URWLD COMPANY INPUTS'!$D$715,'URWLD COMPANY INPUTS'!$D$718,'URWLD COMPANY INPUTS'!$D$720,'URWLD COMPANY INPUTS'!$D$722,'URWLD COMPANY INPUTS'!$D$724,'URWLD COMPANY INPUTS'!$D$727,'URWLD COMPANY INPUTS'!$D$729,'URWLD COMPANY INPUTS'!$D$731,'URWLD COMPANY INPUTS'!$D$733,'URWLD COMPANY INPUTS'!$D$628,'URWLD COMPANY INPUTS'!$D$736)+850000+1920000-'URWLD COMPANY INPUTS'!$D$703*1000000+18000000+N("Source schedule constants: Genesis C19 residual A$1.2m; convenience E21 A$0.264m; common N159 A$0.85m; common N166 A$1.92m; project management H25 A$18.0m.") -> 3.4242301e+08 | K34: =IF(ROUND(SUM(L34:EN34),0)=ROUND(I34,0),"","Incomplete") | L34: =AND(L$23>=$D34,L$23<=$E34)*(OR($F34="Straight-Line",$F34="Detail")*($I34/$ES34)+($F34="S-Curve")*EV34+OR($F34="Steady Growth",$F34="Steady Decline")*KF34) -> 316264.67 | M34: =AND(M$23>=$D34,M$23<=$E34)*(OR($F34="Straight-Line",$F34="Detail")*($I34/$ES34)+($F34="S-Curve")*EW34+OR($F34="Steady Growth",$F34="Steady Decline")*KG34) -> 500578.94 | N34: =AND(N$23>=$D34,N$23<=$E34)*(OR($F34="Straight-Line",$F34="Detail")*($I34/$ES34)+($F34="S-Curve")*EX34+OR($F34="Steady Growth",$F34="Steady Decline")*KH34) -> 771789.34 | O34: =AND(O$23>=$D34,O$23<=$E34)*(OR($F34="Straight-Line",$F34="Detail")*($I34/$ES34)+($F34="S-Curve")*EY34+OR($F34="Steady Growth",$F34="Steady Decline")*KI34) -> 1159122.4 | P34: =AND(P$23>=$D34,P$23<=$E34)*(OR($F34="Straight-Line",$F34="Detail")*($I34/$ES34)+($F34="S-Curve")*EZ34+OR($F34="Steady Growth",$F34="Steady Decline")*KJ34) -> 1695759.2 | Q34: =AND(Q$23>=$D34,Q$23<=$E34)*(OR($F34="Straight-Line",$F34="Detail")*($I34/$ES34)+($F34="S-Curve")*FA34+OR($F34="Steady Growth",$F34="Steady Decline")*KK34) -> 2416592.7 | R34: =AND(R$23>=$D34,R$23<=$E34)*(OR($F34="Straight-Line",$F34="Detail")*($I34/$ES34)+($F34="S-Curve")*FB34+OR($F34="Steady Growth",$F34="Steady Decline")*KL34) -> 3354649.4 | S34: =AND(S$23>=$D34,S$23<=$E34)*(OR($F34="Straight-Line",$F34="Detail")*($I34/$ES34)+($F34="S-Curve")*FC34+OR($F34="Steady Growth",$F34="Steady Decline")*KM34) -> 4536231.9 | ... EN34: =AND(EN$23>=$D34,EN$23<=$E34)*(OR($F34="Straight-Line",$F34="Detail")*($I34/$ES34)+($F34="S-Curve")*JX34+OR($F34="Steady Growth",$F34="Steady Decline")*PH34) -> 0 | EP34: =I34 -> 3.4242301e+08 | EQ34: =INDEX($L$24:$EN$24,1,$D34+1) -> 46203 | ER34: =INDEX($L$24:$EN$24,1,$E34+1) -> 47299 | ES34: =+E34-D34+1 -> 37 | ET34: =F34 -> S-Curve | EU34: =ES34/Scurve_Dist -> 6.1666667 | EV34: =AND($ET34="S-Curve",EV$24>=$EQ34,EV$24<=$ER34)*(NORMDIST((YEAR(EV$24)-YEAR($EQ34))*12+MONTH(EV$24)-MONTH($EQ34)+1,$ES34/2,$EU34,TRUE)-NORMDIST((YEAR(EV$24)-YEAR($EQ34))*12+MONTH(EV$24)-MONTH($EQ34),$ES34/2,$EU34,TRUE))/(1-2*NORMDIST(0,$ES34/2,$EU34,TRUE))*$EP34 -> 316264.67 | EW34: =AND($ET34="S-Curve",EW$24>=$EQ34,EW$24<=$ER34)*(NORMDIST((YEAR(EW$24)-YEAR($EQ34))*12+MONTH(EW$24)-MONTH($EQ34)+1,$ES34/2,$EU34,TRUE)-NORMDIST((YEAR(EW$24)-YEAR($EQ34))*12+MONTH(EW$24)-MONTH($EQ34),$ES34/2,$EU34,TRUE))/(1-2*NORMDIST(0,$ES34/2,$EU34,TRUE))*$EP34 -> 500578.94 | EX34: =AND($ET34="S-Curve",EX$24>=$EQ34,EX$24<=$ER34)*(NORMDIST((YEAR(EX$24)-YEAR($EQ34))*12+MONTH(EX$24)-MONTH($EQ34)+1,$ES34/2,$EU34,TRUE)-NORMDIST((YEAR(EX$24)-YEAR($EQ34))*12+MONTH(EX$24)-MONTH($EQ34),$ES34/2,$EU34,TRUE))/(1-2*NORMDIST(0,$ES34/2,$EU34,TRUE))*$EP34 -> 771789.34 | EY34: =AND($ET34="S-Curve",EY$24>=$EQ34,EY$24<=$ER34)*(NORMDIST((YEAR(EY$24)-YEAR($EQ34))*12+MONTH(EY$24)-MONTH($EQ34)+1,$ES34/2,$EU34,TRUE)-NORMDIST((YEAR(EY$24)-YEAR($EQ34))*12+MONTH(EY$24)-MONTH($EQ34),$ES34/2,$EU34,TRUE))/(1-2*NORMDIST(0,$ES34/2,$EU34,TRUE))*$EP34 -> 1159122.4 | EZ34: =AND($ET34="S-Curve",EZ$24>=$EQ34,EZ$24<=$ER34)*(NORMDIST((YEAR(EZ$24)-YEAR($EQ34))*12+MONTH(EZ$24)-MONTH($EQ34)+1,$ES34/2,$EU34,TRUE)-NORMDIST((YEAR(EZ$24)-YEAR($EQ34))*12+MONTH(EZ$24)-MONTH($EQ34),$ES34/2,$EU34,TRUE))/(1-2*NORMDIST(0,$ES34/2,$EU34,TRUE))*$EP34 -> 1695759.2 | FA34: =AND($ET34="S-Curve",FA$24>=$EQ34,FA$24<=$ER34)*(NORMDIST((YEAR(FA$24)-YEAR($EQ34))*12+MONTH(FA$24)-MONTH($EQ34)+1,$ES34/2,$EU34,TRUE)-NORMDIST((YEAR(FA$24)-YEAR($EQ34))*12+MONTH(FA$24)-MONTH($EQ34),$ES34/2,$EU34,TRUE))/(1-2*NORMDIST(0,$ES34/2,$EU34,TRUE))*$EP34 -> 2416592.7 | FB34: =AND($ET34="S-Curve",FB$24>=$EQ34,FB$24<=$ER34)*(NORMDIST((YEAR(FB$24)-YEAR($EQ34))*12+MONTH(FB$24)-MONTH($EQ34)+1,$ES34/2,$EU34,TRUE)-NORMDIST((YEAR(FB$24)-YEAR($EQ34))*12+MONTH(FB$24)-MONTH($EQ34),$ES34/2,$EU34,TRUE))/(1-2*NORMDIST(0,$ES34/2,$EU34,TRUE))*$EP34 -> 3354649.4 | FC34: =AND($ET34="S-Curve",FC$24>=$EQ34,FC$24<=$ER34)*(NORMDIST((YEAR(FC$24)-YEAR($EQ34))*12+MONTH(FC$24)-MONTH($EQ34)+1,$ES34/2,$EU34,TRUE)-NORMDIST((YEAR(FC$24)-YEAR($EQ34))*12+MONTH(FC$24)-MONTH($EQ34),$ES34/2,$EU34,TRUE))/(1-2*NORMDIST(0,$ES34/2,$EU34,TRUE))*$EP34 -> 4536231.9 | ... JX34: =AND($ET34="S-Curve",JX$24>=$EQ34,JX$24<=$ER34)*(NORMDIST((YEAR(JX$24)-YEAR($EQ34))*12+MONTH(JX$24)-MONTH($EQ34)+1,$ES34/2,$EU34,TRUE)-NORMDIST((YEAR(JX$24)-YEAR($EQ34))*12+MONTH(JX$24)-MONTH($EQ34),$ES34/2,$EU34,TRUE))/(1-2*NORMDIST(0,$ES34/2,$EU34,TRUE))*$EP34 -> 0 | JZ34: =B34 -> 0 | KB34: =D34 -> 0 | KC34: =E34 -> 36 | KD34: =KC34-KB34+1 -> 37 | KE34: =I34 -> 3.4242301e+08 | KF34: =AND(KF$23>=$KB34,KF$23<=$KC34)*(IF($F34="Steady Growth",KF$23-$KB34,$KC34-KF$23)+1)/($KD34*($KD34+1)/2)*$KE34 -> 18022263 | KG34: =AND(KG$23>=$KB34,KG$23<=$KC34)*(IF($F34="Steady Growth",KG$23-$KB34,$KC34-KG$23)+1)/($KD34*($KD34+1)/2)*$KE34 -> 17535175 | KH34: =AND(KH$23>=$KB34,KH$23<=$KC34)*(IF($F34="Steady Growth",KH$23-$KB34,$KC34-KH$23)+1)/($KD34*($KD34+1)/2)*$KE34 -> 17048087 | KI34: =AND(KI$23>=$KB34,KI$23<=$KC34)*(IF($F34="Steady Growth",KI$23-$KB34,$KC34-KI$23)+1)/($KD34*($KD34+1)/2)*$KE34 -> 16560999 | KJ34: =AND(KJ$23>=$KB34,KJ$23<=$KC34)*(IF($F34="Steady Growth",KJ$23-$KB34,$KC34-KJ$23)+1)/($KD34*($KD34+1)/2)*$KE34 -> 16073911 | KK34: =AND(KK$23>=$KB34,KK$23<=$KC34)*(IF($F34="Steady Growth",KK$23-$KB34,$KC34-KK$23)+1)/($KD34*($KD34+1)/2)*$KE34 -> 15586822 | KL34: =AND(KL$23>=$KB34,KL$23<=$KC34)*(IF($F34="Steady Growth",KL$23-$KB34,$KC34-KL$23)+1)/($KD34*($KD34+1)/2)*$KE34 -> 15099734 | KM34: =AND(KM$23>=$KB34,KM$23<=$KC34)*(IF($F34="Steady Growth",KM$23-$KB34,$KC34-KM$23)+1)/($KD34*($KD34+1)/2)*$KE34 -> 14612646 | ... PH34: =AND(PH$23>=$KB34,PH$23<=$KC34)*(IF($F34="Steady Growth",PH$23-$KB34,$KC34-PH$23)+1)/($KD34*($KD34+1)/2)*$KE34 -> 0
B35: Net infrastructure fund | C35: 1 | E35: =$E$34 -> 36 | F35: Straight-Line | G35: =I35/Units_SF_M2 -> 179.85931 | I35: =SUM('URWLD COMPANY INPUTS'!$D$125:$D$126)*1000000 -> 14113629 | K35: =IF(ROUND(SUM(L35:EN35),0)=ROUND(I35,0),"","Incomplete") | L35: =AND(L$23>=$D35,L$23<=$E35)*(OR($F35="Straight-Line",$F35="Detail")*($I35/$ES35)+($F35="S-Curve")*EV35+OR($F35="Steady Growth",$F35="Steady Decline")*KF35) -> 381449.42 | M35: =AND(M$23>=$D35,M$23<=$E35)*(OR($F35="Straight-Line",$F35="Detail")*($I35/$ES35)+($F35="S-Curve")*EW35+OR($F35="Steady Growth",$F35="Steady Decline")*KG35) -> 381449.42 | N35: =AND(N$23>=$D35,N$23<=$E35)*(OR($F35="Straight-Line",$F35="Detail")*($I35/$ES35)+($F35="S-Curve")*EX35+OR($F35="Steady Growth",$F35="Steady Decline")*KH35) -> 381449.42 | O35: =AND(O$23>=$D35,O$23<=$E35)*(OR($F35="Straight-Line",$F35="Detail")*($I35/$ES35)+($F35="S-Curve")*EY35+OR($F35="Steady Growth",$F35="Steady Decline")*KI35) -> 381449.42 | P35: =AND(P$23>=$D35,P$23<=$E35)*(OR($F35="Straight-Line",$F35="Detail")*($I35/$ES35)+($F35="S-Curve")*EZ35+OR($F35="Steady Growth",$F35="Steady Decline")*KJ35) -> 381449.42 | Q35: =AND(Q$23>=$D35,Q$23<=$E35)*(OR($F35="Straight-Line",$F35="Detail")*($I35/$ES35)+($F35="S-Curve")*FA35+OR($F35="Steady Growth",$F35="Steady Decline")*KK35) -> 381449.42 | R35: =AND(R$23>=$D35,R$23<=$E35)*(OR($F35="Straight-Line",$F35="Detail")*($I35/$ES35)+($F35="S-Curve")*FB35+OR($F35="Steady Growth",$F35="Steady Decline")*KL35) -> 381449.42 | S35: =AND(S$23>=$D35,S$23<=$E35)*(OR($F35="Straight-Line",$F35="Detail")*($I35/$ES35)+($F35="S-Curve")*FC35+OR($F35="Steady Growth",$F35="Steady Decline")*KM35) -> 381449.42 | ... EN35: =AND(EN$23>=$D35,EN$23<=$E35)*(OR($F35="Straight-Line",$F35="Detail")*($I35/$ES35)+($F35="S-Curve")*JX35+OR($F35="Steady Growth",$F35="Steady Decline")*PH35) -> 0 | EP35: =I35 -> 14113629 | EQ35: =INDEX($L$24:$EN$24,1,$D35+1) -> 46203 | ER35: =INDEX($L$24:$EN$24,1,$E35+1) -> 47299 | ES35: =+E35-D35+1 -> 37 | ET35: =F35 -> Straight-Line | EU35: =ES35/Scurve_Dist -> 6.1666667 | EV35: =AND($ET35="S-Curve",EV$24>=$EQ35,EV$24<=$ER35)*(NORMDIST((YEAR(EV$24)-YEAR($EQ35))*12+MONTH(EV$24)-MONTH($EQ35)+1,$ES35/2,$EU35,TRUE)-NORMDIST((YEAR(EV$24)-YEAR($EQ35))*12+MONTH(EV$24)-MONTH($EQ35),$ES35/2,$EU35,TRUE))/(1-2*NORMDIST(0,$ES35/2,$EU35,TRUE))*$EP35 -> 0 | EW35: =AND($ET35="S-Curve",EW$24>=$EQ35,EW$24<=$ER35)*(NORMDIST((YEAR(EW$24)-YEAR($EQ35))*12+MONTH(EW$24)-MONTH($EQ35)+1,$ES35/2,$EU35,TRUE)-NORMDIST((YEAR(EW$24)-YEAR($EQ35))*12+MONTH(EW$24)-MONTH($EQ35),$ES35/2,$EU35,TRUE))/(1-2*NORMDIST(0,$ES35/2,$EU35,TRUE))*$EP35 -> 0 | EX35: =AND($ET35="S-Curve",EX$24>=$EQ35,EX$24<=$ER35)*(NORMDIST((YEAR(EX$24)-YEAR($EQ35))*12+MONTH(EX$24)-MONTH($EQ35)+1,$ES35/2,$EU35,TRUE)-NORMDIST((YEAR(EX$24)-YEAR($EQ35))*12+MONTH(EX$24)-MONTH($EQ35),$ES35/2,$EU35,TRUE))/(1-2*NORMDIST(0,$ES35/2,$EU35,TRUE))*$EP35 -> 0 | EY35: =AND($ET35="S-Curve",EY$24>=$EQ35,EY$24<=$ER35)*(NORMDIST((YEAR(EY$24)-YEAR($EQ35))*12+MONTH(EY$24)-MONTH($EQ35)+1,$ES35/2,$EU35,TRUE)-NORMDIST((YEAR(EY$24)-YEAR($EQ35))*12+MONTH(EY$24)-MONTH($EQ35),$ES35/2,$EU35,TRUE))/(1-2*NORMDIST(0,$ES35/2,$EU35,TRUE))*$EP35 -> 0 | EZ35: =AND($ET35="S-Curve",EZ$24>=$EQ35,EZ$24<=$ER35)*(NORMDIST((YEAR(EZ$24)-YEAR($EQ35))*12+MONTH(EZ$24)-MONTH($EQ35)+1,$ES35/2,$EU35,TRUE)-NORMDIST((YEAR(EZ$24)-YEAR($EQ35))*12+MONTH(EZ$24)-MONTH($EQ35),$ES35/2,$EU35,TRUE))/(1-2*NORMDIST(0,$ES35/2,$EU35,TRUE))*$EP35 -> 0 | FA35: =AND($ET35="S-Curve",FA$24>=$EQ35,FA$24<=$ER35)*(NORMDIST((YEAR(FA$24)-YEAR($EQ35))*12+MONTH(FA$24)-MONTH($EQ35)+1,$ES35/2,$EU35,TRUE)-NORMDIST((YEAR(FA$24)-YEAR($EQ35))*12+MONTH(FA$24)-MONTH($EQ35),$ES35/2,$EU35,TRUE))/(1-2*NORMDIST(0,$ES35/2,$EU35,TRUE))*$EP35 -> 0 | FB35: =AND($ET35="S-Curve",FB$24>=$EQ35,FB$24<=$ER35)*(NORMDIST((YEAR(FB$24)-YEAR($EQ35))*12+MONTH(FB$24)-MONTH($EQ35)+1,$ES35/2,$EU35,TRUE)-NORMDIST((YEAR(FB$24)-YEAR($EQ35))*12+MONTH(FB$24)-MONTH($EQ35),$ES35/2,$EU35,TRUE))/(1-2*NORMDIST(0,$ES35/2,$EU35,TRUE))*$EP35 -> 0 | FC35: =AND($ET35="S-Curve",FC$24>=$EQ35,FC$24<=$ER35)*(NORMDIST((YEAR(FC$24)-YEAR($EQ35))*12+MONTH(FC$24)-MONTH($EQ35)+1,$ES35/2,$EU35,TRUE)-NORMDIST((YEAR(FC$24)-YEAR($EQ35))*12+MONTH(FC$24)-MONTH($EQ35),$ES35/2,$EU35,TRUE))/(1-2*NORMDIST(0,$ES35/2,$EU35,TRUE))*$EP35 -> 0 | ... JX35: =AND($ET35="S-Curve",JX$24>=$EQ35,JX$24<=$ER35)*(NORMDIST((YEAR(JX$24)-YEAR($EQ35))*12+MONTH(JX$24)-MONTH($EQ35)+1,$ES35/2,$EU35,TRUE)-NORMDIST((YEAR(JX$24)-YEAR($EQ35))*12+MONTH(JX$24)-MONTH($EQ35),$ES35/2,$EU35,TRUE))/(1-2*NORMDIST(0,$ES35/2,$EU35,TRUE))*$EP35 -> 0 | JZ35: =B35 -> Net infrastructure fund | KB35: =D35 -> 0 | KC35: =E35 -> 36 | KD35: =KC35-KB35+1 -> 37 | KE35: =I35 -> 14113629 | KF35: =AND(KF$23>=$KB35,KF$23<=$KC35)*(IF($F35="Steady Growth",KF$23-$KB35,$KC35-KF$23)+1)/($KD35*($KD35+1)/2)*$KE35 -> 742822.56 | KG35: =AND(KG$23>=$KB35,KG$23<=$KC35)*(IF($F35="Steady Growth",KG$23-$KB35,$KC35-KG$23)+1)/($KD35*($KD35+1)/2)*$KE35 -> 722746.28 | KH35: =AND(KH$23>=$KB35,KH$23<=$KC35)*(IF($F35="Steady Growth",KH$23-$KB35,$KC35-KH$23)+1)/($KD35*($KD35+1)/2)*$KE35 -> 702669.99 | KI35: =AND(KI$23>=$KB35,KI$23<=$KC35)*(IF($F35="Steady Growth",KI$23-$KB35,$KC35-KI$23)+1)/($KD35*($KD35+1)/2)*$KE35 -> 682593.71 | KJ35: =AND(KJ$23>=$KB35,KJ$23<=$KC35)*(IF($F35="Steady Growth",KJ$23-$KB35,$KC35-KJ$23)+1)/($KD35*($KD35+1)/2)*$KE35 -> 662517.42 | KK35: =AND(KK$23>=$KB35,KK$23<=$KC35)*(IF($F35="Steady Growth",KK$23-$KB35,$KC35-KK$23)+1)/($KD35*($KD35+1)/2)*$KE35 -> 642441.13 | KL35: =AND(KL$23>=$KB35,KL$23<=$KC35)*(IF($F35="Steady Growth",KL$23-$KB35,$KC35-KL$23)+1)/($KD35*($KD35+1)/2)*$KE35 -> 622364.85 | KM35: =AND(KM$23>=$KB35,KM$23<=$KC35)*(IF($F35="Steady Growth",KM$23-$KB35,$KC35-KM$23)+1)/($KD35*($KD35+1)/2)*$KE35 -> 602288.56 | ... PH35: =AND(PH$23>=$KB35,PH$23<=$KC35)*(IF($F35="Steady Growth",PH$23-$KB35,$KC35-PH$23)+1)/($KD35*($KD35+1)/2)*$KE35 -> 0
B36: Development-period operating adjustments (funding bridge only) | C36: 1 | E36: =$E$34 -> 36 | F36: Straight-Line | G36: =I36/Units_SF_M2 -> 0 | I36: =0 -> 0 | K36: =IF(ROUND(SUM(L36:EN36),0)=ROUND(I36,0),"","Incomplete") | L36: =AND(L$23>=$D36,L$23<=$E36)*(OR($F36="Straight-Line",$F36="Detail")*($I36/$ES36)+($F36="S-Curve")*EV36+OR($F36="Steady Growth",$F36="Steady Decline")*KF36) -> 0 | M36: =AND(M$23>=$D36,M$23<=$E36)*(OR($F36="Straight-Line",$F36="Detail")*($I36/$ES36)+($F36="S-Curve")*EW36+OR($F36="Steady Growth",$F36="Steady Decline")*KG36) -> 0 | N36: =AND(N$23>=$D36,N$23<=$E36)*(OR($F36="Straight-Line",$F36="Detail")*($I36/$ES36)+($F36="S-Curve")*EX36+OR($F36="Steady Growth",$F36="Steady Decline")*KH36) -> 0 | O36: =AND(O$23>=$D36,O$23<=$E36)*(OR($F36="Straight-Line",$F36="Detail")*($I36/$ES36)+($F36="S-Curve")*EY36+OR($F36="Steady Growth",$F36="Steady Decline")*KI36) -> 0 | P36: =AND(P$23>=$D36,P$23<=$E36)*(OR($F36="Straight-Line",$F36="Detail")*($I36/$ES36)+($F36="S-Curve")*EZ36+OR($F36="Steady Growth",$F36="Steady Decline")*KJ36) -> 0 | Q36: =AND(Q$23>=$D36,Q$23<=$E36)*(OR($F36="Straight-Line",$F36="Detail")*($I36/$ES36)+($F36="S-Curve")*FA36+OR($F36="Steady Growth",$F36="Steady Decline")*KK36) -> 0 | R36: =AND(R$23>=$D36,R$23<=$E36)*(OR($F36="Straight-Line",$F36="Detail")*($I36/$ES36)+($F36="S-Curve")*FB36+OR($F36="Steady Growth",$F36="Steady Decline")*KL36) -> 0 | S36: =AND(S$23>=$D36,S$23<=$E36)*(OR($F36="Straight-Line",$F36="Detail")*($I36/$ES36)+($F36="S-Curve")*FC36+OR($F36="Steady Growth",$F36="Steady Decline")*KM36) -> 0 | ... EN36: =AND(EN$23>=$D36,EN$23<=$E36)*(OR($F36="Straight-Line",$F36="Detail")*($I36/$ES36)+($F36="S-Curve")*JX36+OR($F36="Steady Growth",$F36="Steady Decline")*PH36) -> 0 | EP36: =I36 -> 0 | EQ36: =INDEX($L$24:$EN$24,1,$D36+1) -> 46203 | ER36: =INDEX($L$24:$EN$24,1,$E36+1) -> 47299 | ES36: =+E36-D36+1 -> 37 | ET36: =F36 -> Straight-Line | EU36: =ES36/Scurve_Dist -> 6.1666667 | EV36: =AND($ET36="S-Curve",EV$24>=$EQ36,EV$24<=$ER36)*(NORMDIST((YEAR(EV$24)-YEAR($EQ36))*12+MONTH(EV$24)-MONTH($EQ36)+1,$ES36/2,$EU36,TRUE)-NORMDIST((YEAR(EV$24)-YEAR($EQ36))*12+MONTH(EV$24)-MONTH($EQ36),$ES36/2,$EU36,TRUE))/(1-2*NORMDIST(0,$ES36/2,$EU36,TRUE))*$EP36 -> 0 | EW36: =AND($ET36="S-Curve",EW$24>=$EQ36,EW$24<=$ER36)*(NORMDIST((YEAR(EW$24)-YEAR($EQ36))*12+MONTH(EW$24)-MONTH($EQ36)+1,$ES36/2,$EU36,TRUE)-NORMDIST((YEAR(EW$24)-YEAR($EQ36))*12+MONTH(EW$24)-MONTH($EQ36),$ES36/2,$EU36,TRUE))/(1-2*NORMDIST(0,$ES36/2,$EU36,TRUE))*$EP36 -> 0 | EX36: =AND($ET36="S-Curve",EX$24>=$EQ36,EX$24<=$ER36)*(NORMDIST((YEAR(EX$24)-YEAR($EQ36))*12+MONTH(EX$24)-MONTH($EQ36)+1,$ES36/2,$EU36,TRUE)-NORMDIST((YEAR(EX$24)-YEAR($EQ36))*12+MONTH(EX$24)-MONTH($EQ36),$ES36/2,$EU36,TRUE))/(1-2*NORMDIST(0,$ES36/2,$EU36,TRUE))*$EP36 -> 0 | EY36: =AND($ET36="S-Curve",EY$24>=$EQ36,EY$24<=$ER36)*(NORMDIST((YEAR(EY$24)-YEAR($EQ36))*12+MONTH(EY$24)-MONTH($EQ36)+1,$ES36/2,$EU36,TRUE)-NORMDIST((YEAR(EY$24)-YEAR($EQ36))*12+MONTH(EY$24)-MONTH($EQ36),$ES36/2,$EU36,TRUE))/(1-2*NORMDIST(0,$ES36/2,$EU36,TRUE))*$EP36 -> 0 | EZ36: =AND($ET36="S-Curve",EZ$24>=$EQ36,EZ$24<=$ER36)*(NORMDIST((YEAR(EZ$24)-YEAR($EQ36))*12+MONTH(EZ$24)-MONTH($EQ36)+1,$ES36/2,$EU36,TRUE)-NORMDIST((YEAR(EZ$24)-YEAR($EQ36))*12+MONTH(EZ$24)-MONTH($EQ36),$ES36/2,$EU36,TRUE))/(1-2*NORMDIST(0,$ES36/2,$EU36,TRUE))*$EP36 -> 0 | FA36: =AND($ET36="S-Curve",FA$24>=$EQ36,FA$24<=$ER36)*(NORMDIST((YEAR(FA$24)-YEAR($EQ36))*12+MONTH(FA$24)-MONTH($EQ36)+1,$ES36/2,$EU36,TRUE)-NORMDIST((YEAR(FA$24)-YEAR($EQ36))*12+MONTH(FA$24)-MONTH($EQ36),$ES36/2,$EU36,TRUE))/(1-2*NORMDIST(0,$ES36/2,$EU36,TRUE))*$EP36 -> 0 | FB36: =AND($ET36="S-Curve",FB$24>=$EQ36,FB$24<=$ER36)*(NORMDIST((YEAR(FB$24)-YEAR($EQ36))*12+MONTH(FB$24)-MONTH($EQ36)+1,$ES36/2,$EU36,TRUE)-NORMDIST((YEAR(FB$24)-YEAR($EQ36))*12+MONTH(FB$24)-MONTH($EQ36),$ES36/2,$EU36,TRUE))/(1-2*NORMDIST(0,$ES36/2,$EU36,TRUE))*$EP36 -> 0 | FC36: =AND($ET36="S-Curve",FC$24>=$EQ36,FC$24<=$ER36)*(NORMDIST((YEAR(FC$24)-YEAR($EQ36))*12+MONTH(FC$24)-MONTH($EQ36)+1,$ES36/2,$EU36,TRUE)-NORMDIST((YEAR(FC$24)-YEAR($EQ36))*12+MONTH(FC$24)-MONTH($EQ36),$ES36/2,$EU36,TRUE))/(1-2*NORMDIST(0,$ES36/2,$EU36,TRUE))*$EP36 -> 0 | ... JX36: =AND($ET36="S-Curve",JX$24>=$EQ36,JX$24<=$ER36)*(NORMDIST((YEAR(JX$24)-YEAR($EQ36))*12+MONTH(JX$24)-MONTH($EQ36)+1,$ES36/2,$EU36,TRUE)-NORMDIST((YEAR(JX$24)-YEAR($EQ36))*12+MONTH(JX$24)-MONTH($EQ36),$ES36/2,$EU36,TRUE))/(1-2*NORMDIST(0,$ES36/2,$EU36,TRUE))*$EP36 -> 0 | JZ36: =B36 -> Development-period operating adjustments (funding bridge only) | KB36: =D36 -> 0 | KC36: =E36 -> 36 | KD36: =KC36-KB36+1 -> 37 | KE36: =I36 -> 0 | KF36: =AND(KF$23>=$KB36,KF$23<=$KC36)*(IF($F36="Steady Growth",KF$23-$KB36,$KC36-KF$23)+1)/($KD36*($KD36+1)/2)*$KE36 -> 0 | KG36: =AND(KG$23>=$KB36,KG$23<=$KC36)*(IF($F36="Steady Growth",KG$23-$KB36,$KC36-KG$23)+1)/($KD36*($KD36+1)/2)*$KE36 -> 0 | KH36: =AND(KH$23>=$KB36,KH$23<=$KC36)*(IF($F36="Steady Growth",KH$23-$KB36,$KC36-KH$23)+1)/($KD36*($KD36+1)/2)*$KE36 -> 0 | KI36: =AND(KI$23>=$KB36,KI$23<=$KC36)*(IF($F36="Steady Growth",KI$23-$KB36,$KC36-KI$23)+1)/($KD36*($KD36+1)/2)*$KE36 -> 0 | KJ36: =AND(KJ$23>=$KB36,KJ$23<=$KC36)*(IF($F36="Steady Growth",KJ$23-$KB36,$KC36-KJ$23)+1)/($KD36*($KD36+1)/2)*$KE36 -> 0 | KK36: =AND(KK$23>=$KB36,KK$23<=$KC36)*(IF($F36="Steady Growth",KK$23-$KB36,$KC36-KK$23)+1)/($KD36*($KD36+1)/2)*$KE36 -> 0 | KL36: =AND(KL$23>=$KB36,KL$23<=$KC36)*(IF($F36="Steady Growth",KL$23-$KB36,$KC36-KL$23)+1)/($KD36*($KD36+1)/2)*$KE36 -> 0 | KM36: =AND(KM$23>=$KB36,KM$23<=$KC36)*(IF($F36="Steady Growth",KM$23-$KB36,$KC36-KM$23)+1)/($KD36*($KD36+1)/2)*$KE36 -> 0 | ... PH36: =AND(PH$23>=$KB36,PH$23<=$KC36)*(IF($F36="Steady Growth",PH$23-$KB36,$KC36-PH$23)+1)/($KD36*($KD36+1)/2)*$KE36 -> 0
B37: Staged operating funding sources (funding bridge only) | C37: =$E$34 -> 36 | E37: =$E$34 -> 36 | F37: Straight-Line | G37: =I37/Units_SF_M2 -> 0 | I37: =0 -> 0 | K37: =IF(ROUND(SUM(L37:EN37),0)=ROUND(I37,0),"","Incomplete") | L37: =AND(L$23>=$D37,L$23<=$E37)*(OR($F37="Straight-Line",$F37="Detail")*($I37/$ES37)+($F37="S-Curve")*EV37+OR($F37="Steady Growth",$F37="Steady Decline")*KF37) -> 0 | M37: =AND(M$23>=$D37,M$23<=$E37)*(OR($F37="Straight-Line",$F37="Detail")*($I37/$ES37)+($F37="S-Curve")*EW37+OR($F37="Steady Growth",$F37="Steady Decline")*KG37) -> 0 | N37: =AND(N$23>=$D37,N$23<=$E37)*(OR($F37="Straight-Line",$F37="Detail")*($I37/$ES37)+($F37="S-Curve")*EX37+OR($F37="Steady Growth",$F37="Steady Decline")*KH37) -> 0 | O37: =AND(O$23>=$D37,O$23<=$E37)*(OR($F37="Straight-Line",$F37="Detail")*($I37/$ES37)+($F37="S-Curve")*EY37+OR($F37="Steady Growth",$F37="Steady Decline")*KI37) -> 0 | P37: =AND(P$23>=$D37,P$23<=$E37)*(OR($F37="Straight-Line",$F37="Detail")*($I37/$ES37)+($F37="S-Curve")*EZ37+OR($F37="Steady Growth",$F37="Steady Decline")*KJ37) -> 0 | Q37: =AND(Q$23>=$D37,Q$23<=$E37)*(OR($F37="Straight-Line",$F37="Detail")*($I37/$ES37)+($F37="S-Curve")*FA37+OR($F37="Steady Growth",$F37="Steady Decline")*KK37) -> 0 | R37: =AND(R$23>=$D37,R$23<=$E37)*(OR($F37="Straight-Line",$F37="Detail")*($I37/$ES37)+($F37="S-Curve")*FB37+OR($F37="Steady Growth",$F37="Steady Decline")*KL37) -> 0 | S37: =AND(S$23>=$D37,S$23<=$E37)*(OR($F37="Straight-Line",$F37="Detail")*($I37/$ES37)+($F37="S-Curve")*FC37+OR($F37="Steady Growth",$F37="Steady Decline")*KM37) -> 0 | ... EN37: =AND(EN$23>=$D37,EN$23<=$E37)*(OR($F37="Straight-Line",$F37="Detail")*($I37/$ES37)+($F37="S-Curve")*JX37+OR($F37="Steady Growth",$F37="Steady Decline")*PH37) -> 0 | EP37: =I37 -> 0 | EQ37: =INDEX($L$24:$EN$24,1,$D37+1) -> 46203 | ER37: =INDEX($L$24:$EN$24,1,$E37+1) -> 47299 | ES37: =+E37-D37+1 -> 37 | ET37: =F37 -> Straight-Line | EU37: =ES37/Scurve_Dist -> 6.1666667 | EV37: =AND($ET37="S-Curve",EV$24>=$EQ37,EV$24<=$ER37)*(NORMDIST((YEAR(EV$24)-YEAR($EQ37))*12+MONTH(EV$24)-MONTH($EQ37)+1,$ES37/2,$EU37,TRUE)-NORMDIST((YEAR(EV$24)-YEAR($EQ37))*12+MONTH(EV$24)-MONTH($EQ37),$ES37/2,$EU37,TRUE))/(1-2*NORMDIST(0,$ES37/2,$EU37,TRUE))*$EP37 -> 0 | EW37: =AND($ET37="S-Curve",EW$24>=$EQ37,EW$24<=$ER37)*(NORMDIST((YEAR(EW$24)-YEAR($EQ37))*12+MONTH(EW$24)-MONTH($EQ37)+1,$ES37/2,$EU37,TRUE)-NORMDIST((YEAR(EW$24)-YEAR($EQ37))*12+MONTH(EW$24)-MONTH($EQ37),$ES37/2,$EU37,TRUE))/(1-2*NORMDIST(0,$ES37/2,$EU37,TRUE))*$EP37 -> 0 | EX37: =AND($ET37="S-Curve",EX$24>=$EQ37,EX$24<=$ER37)*(NORMDIST((YEAR(EX$24)-YEAR($EQ37))*12+MONTH(EX$24)-MONTH($EQ37)+1,$ES37/2,$EU37,TRUE)-NORMDIST((YEAR(EX$24)-YEAR($EQ37))*12+MONTH(EX$24)-MONTH($EQ37),$ES37/2,$EU37,TRUE))/(1-2*NORMDIST(0,$ES37/2,$EU37,TRUE))*$EP37 -> 0 | EY37: =AND($ET37="S-Curve",EY$24>=$EQ37,EY$24<=$ER37)*(NORMDIST((YEAR(EY$24)-YEAR($EQ37))*12+MONTH(EY$24)-MONTH($EQ37)+1,$ES37/2,$EU37,TRUE)-NORMDIST((YEAR(EY$24)-YEAR($EQ37))*12+MONTH(EY$24)-MONTH($EQ37),$ES37/2,$EU37,TRUE))/(1-2*NORMDIST(0,$ES37/2,$EU37,TRUE))*$EP37 -> 0 | EZ37: =AND($ET37="S-Curve",EZ$24>=$EQ37,EZ$24<=$ER37)*(NORMDIST((YEAR(EZ$24)-YEAR($EQ37))*12+MONTH(EZ$24)-MONTH($EQ37)+1,$ES37/2,$EU37,TRUE)-NORMDIST((YEAR(EZ$24)-YEAR($EQ37))*12+MONTH(EZ$24)-MONTH($EQ37),$ES37/2,$EU37,TRUE))/(1-2*NORMDIST(0,$ES37/2,$EU37,TRUE))*$EP37 -> 0 | FA37: =AND($ET37="S-Curve",FA$24>=$EQ37,FA$24<=$ER37)*(NORMDIST((YEAR(FA$24)-YEAR($EQ37))*12+MONTH(FA$24)-MONTH($EQ37)+1,$ES37/2,$EU37,TRUE)-NORMDIST((YEAR(FA$24)-YEAR($EQ37))*12+MONTH(FA$24)-MONTH($EQ37),$ES37/2,$EU37,TRUE))/(1-2*NORMDIST(0,$ES37/2,$EU37,TRUE))*$EP37 -> 0 | FB37: =AND($ET37="S-Curve",FB$24>=$EQ37,FB$24<=$ER37)*(NORMDIST((YEAR(FB$24)-YEAR($EQ37))*12+MONTH(FB$24)-MONTH($EQ37)+1,$ES37/2,$EU37,TRUE)-NORMDIST((YEAR(FB$24)-YEAR($EQ37))*12+MONTH(FB$24)-MONTH($EQ37),$ES37/2,$EU37,TRUE))/(1-2*NORMDIST(0,$ES37/2,$EU37,TRUE))*$EP37 -> 0 | FC37: =AND($ET37="S-Curve",FC$24>=$EQ37,FC$24<=$ER37)*(NORMDIST((YEAR(FC$24)-YEAR($EQ37))*12+MONTH(FC$24)-MONTH($EQ37)+1,$ES37/2,$EU37,TRUE)-NORMDIST((YEAR(FC$24)-YEAR($EQ37))*12+MONTH(FC$24)-MONTH($EQ37),$ES37/2,$EU37,TRUE))/(1-2*NORMDIST(0,$ES37/2,$EU37,TRUE))*$EP37 -> 0 | ... JX37: =AND($ET37="S-Curve",JX$24>=$EQ37,JX$24<=$ER37)*(NORMDIST((YEAR(JX$24)-YEAR($EQ37))*12+MONTH(JX$24)-MONTH($EQ37)+1,$ES37/2,$EU37,TRUE)-NORMDIST((YEAR(JX$24)-YEAR($EQ37))*12+MONTH(JX$24)-MONTH($EQ37),$ES37/2,$EU37,TRUE))/(1-2*NORMDIST(0,$ES37/2,$EU37,TRUE))*$EP37 -> 0 | JZ37: =B37 -> Staged operating funding sources (funding bridge only) | KB37: =D37 -> 0 | KC37: =E37 -> 36 | KD37: =KC37-KB37+1 -> 37 | KE37: =I37 -> 0 | KF37: =AND(KF$23>=$KB37,KF$23<=$KC37)*(IF($F37="Steady Growth",KF$23-$KB37,$KC37-KF$23)+1)/($KD37*($KD37+1)/2)*$KE37 -> 0 | KG37: =AND(KG$23>=$KB37,KG$23<=$KC37)*(IF($F37="Steady Growth",KG$23-$KB37,$KC37-KG$23)+1)/($KD37*($KD37+1)/2)*$KE37 -> 0 | KH37: =AND(KH$23>=$KB37,KH$23<=$KC37)*(IF($F37="Steady Growth",KH$23-$KB37,$KC37-KH$23)+1)/($KD37*($KD37+1)/2)*$KE37 -> 0 | KI37: =AND(KI$23>=$KB37,KI$23<=$KC37)*(IF($F37="Steady Growth",KI$23-$KB37,$KC37-KI$23)+1)/($KD37*($KD37+1)/2)*$KE37 -> 0 | KJ37: =AND(KJ$23>=$KB37,KJ$23<=$KC37)*(IF($F37="Steady Growth",KJ$23-$KB37,$KC37-KJ$23)+1)/($KD37*($KD37+1)/2)*$KE37 -> 0 | KK37: =AND(KK$23>=$KB37,KK$23<=$KC37)*(IF($F37="Steady Growth",KK$23-$KB37,$KC37-KK$23)+1)/($KD37*($KD37+1)/2)*$KE37 -> 0 | KL37: =AND(KL$23>=$KB37,KL$23<=$KC37)*(IF($F37="Steady Growth",KL$23-$KB37,$KC37-KL$23)+1)/($KD37*($KD37+1)/2)*$KE37 -> 0 | KM37: =AND(KM$23>=$KB37,KM$23<=$KC37)*(IF($F37="Steady Growth",KM$23-$KB37,$KC37-KM$23)+1)/($KD37*($KD37+1)/2)*$KE37 -> 0 | ... PH37: =AND(PH$23>=$KB37,PH$23<=$KC37)*(IF($F37="Steady Growth",PH$23-$KB37,$KC37-PH$23)+1)/($KD37*($KD37+1)/2)*$KE37 -> 0
B38: Total Hard Costs | C38: =MIN(D34:D37) -> 0 | E38: =MAX(E34:E37) -> 36 | F38: =SUM(H34:H37) -> 0 | I38: =SUM(I34:I37) -> 3.5653664e+08 | K38: =IF(ROUND(SUM(L38:EN38),0)=ROUND(I38,0),"","Incomplete") | L38: =SUM(L34:L37) -> 697714.09 | M38: =SUM(M34:M37) -> 882028.36 | N38: =SUM(N34:N37) -> 1153238.8 | O38: =SUM(O34:O37) -> 1540571.8 | P38: =SUM(P34:P37) -> 2077208.7 | Q38: =SUM(Q34:Q37) -> 2798042.2 | R38: =SUM(R34:R37) -> 3736098.9 | S38: =SUM(S34:S37) -> 4917681.3 | ... EN38: =SUM(EN34:EN37) -> 0 | EQ38: # of Hard Cost Items | ER38: =COUNTA($B$34:$B$37) -> 3 | JZ38: =B38 -> Total Hard Costs
JZ40: =B40 -> 0
C41: 1 | E41: =$E$34 -> 36 | F41: Straight-Line | G41: =I41/Units_SF_M2 -> 0 | I41: 0 | K41: =IF(ROUND(SUM(L41:EN41),0)=ROUND(I41,0),"","Incomplete") | L41: =AND(L$23>=$D41,L$23<=$E41)*(OR($F41="Straight-Line",$F41="Detail")*($I41/$ES41)+($F41="S-Curve")*EV41+OR($F41="Steady Growth",$F41="Steady Decline")*KF41) -> 0 | M41: =AND(M$23>=$D41,M$23<=$E41)*(OR($F41="Straight-Line",$F41="Detail")*($I41/$ES41)+($F41="S-Curve")*EW41+OR($F41="Steady Growth",$F41="Steady Decline")*KG41) -> 0 | N41: =AND(N$23>=$D41,N$23<=$E41)*(OR($F41="Straight-Line",$F41="Detail")*($I41/$ES41)+($F41="S-Curve")*EX41+OR($F41="Steady Growth",$F41="Steady Decline")*KH41) -> 0 | O41: =AND(O$23>=$D41,O$23<=$E41)*(OR($F41="Straight-Line",$F41="Detail")*($I41/$ES41)+($F41="S-Curve")*EY41+OR($F41="Steady Growth",$F41="Steady Decline")*KI41) -> 0 | P41: =AND(P$23>=$D41,P$23<=$E41)*(OR($F41="Straight-Line",$F41="Detail")*($I41/$ES41)+($F41="S-Curve")*EZ41+OR($F41="Steady Growth",$F41="Steady Decline")*KJ41) -> 0 | Q41: =AND(Q$23>=$D41,Q$23<=$E41)*(OR($F41="Straight-Line",$F41="Detail")*($I41/$ES41)+($F41="S-Curve")*FA41+OR($F41="Steady Growth",$F41="Steady Decline")*KK41) -> 0 | R41: =AND(R$23>=$D41,R$23<=$E41)*(OR($F41="Straight-Line",$F41="Detail")*($I41/$ES41)+($F41="S-Curve")*FB41+OR($F41="Steady Growth",$F41="Steady Decline")*KL41) -> 0 | S41: =AND(S$23>=$D41,S$23<=$E41)*(OR($F41="Straight-Line",$F41="Detail")*($I41/$ES41)+($F41="S-Curve")*FC41+OR($F41="Steady Growth",$F41="Steady Decline")*KM41) -> 0 | ... EN41: =AND(EN$23>=$D41,EN$23<=$E41)*(OR($F41="Straight-Line",$F41="Detail")*($I41/$ES41)+($F41="S-Curve")*JX41+OR($F41="Steady Growth",$F41="Steady Decline")*PH41) -> 0 | EP41: =I41 -> 0 | EQ41: =INDEX($L$24:$EN$24,1,$D41+1) -> 46203 | ER41: =INDEX($L$24:$EN$24,1,$E41+1) -> 47299 | ES41: =+E41-D41+1 -> 37 | ET41: =F41 -> Straight-Line | EU41: =ES41/Scurve_Dist -> 6.1666667 | EV41: =AND($ET41="S-Curve",EV$24>=$EQ41,EV$24<=$ER41)*(NORMDIST((YEAR(EV$24)-YEAR($EQ41))*12+MONTH(EV$24)-MONTH($EQ41)+1,$ES41/2,$EU41,TRUE)-NORMDIST((YEAR(EV$24)-YEAR($EQ41))*12+MONTH(EV$24)-MONTH($EQ41),$ES41/2,$EU41,TRUE))/(1-2*NORMDIST(0,$ES41/2,$EU41,TRUE))*$EP41 -> 0 | EW41: =AND($ET41="S-Curve",EW$24>=$EQ41,EW$24<=$ER41)*(NORMDIST((YEAR(EW$24)-YEAR($EQ41))*12+MONTH(EW$24)-MONTH($EQ41)+1,$ES41/2,$EU41,TRUE)-NORMDIST((YEAR(EW$24)-YEAR($EQ41))*12+MONTH(EW$24)-MONTH($EQ41),$ES41/2,$EU41,TRUE))/(1-2*NORMDIST(0,$ES41/2,$EU41,TRUE))*$EP41 -> 0 | EX41: =AND($ET41="S-Curve",EX$24>=$EQ41,EX$24<=$ER41)*(NORMDIST((YEAR(EX$24)-YEAR($EQ41))*12+MONTH(EX$24)-MONTH($EQ41)+1,$ES41/2,$EU41,TRUE)-NORMDIST((YEAR(EX$24)-YEAR($EQ41))*12+MONTH(EX$24)-MONTH($EQ41),$ES41/2,$EU41,TRUE))/(1-2*NORMDIST(0,$ES41/2,$EU41,TRUE))*$EP41 -> 0 | EY41: =AND($ET41="S-Curve",EY$24>=$EQ41,EY$24<=$ER41)*(NORMDIST((YEAR(EY$24)-YEAR($EQ41))*12+MONTH(EY$24)-MONTH($EQ41)+1,$ES41/2,$EU41,TRUE)-NORMDIST((YEAR(EY$24)-YEAR($EQ41))*12+MONTH(EY$24)-MONTH($EQ41),$ES41/2,$EU41,TRUE))/(1-2*NORMDIST(0,$ES41/2,$EU41,TRUE))*$EP41 -> 0 | EZ41: =AND($ET41="S-Curve",EZ$24>=$EQ41,EZ$24<=$ER41)*(NORMDIST((YEAR(EZ$24)-YEAR($EQ41))*12+MONTH(EZ$24)-MONTH($EQ41)+1,$ES41/2,$EU41,TRUE)-NORMDIST((YEAR(EZ$24)-YEAR($EQ41))*12+MONTH(EZ$24)-MONTH($EQ41),$ES41/2,$EU41,TRUE))/(1-2*NORMDIST(0,$ES41/2,$EU41,TRUE))*$EP41 -> 0 | FA41: =AND($ET41="S-Curve",FA$24>=$EQ41,FA$24<=$ER41)*(NORMDIST((YEAR(FA$24)-YEAR($EQ41))*12+MONTH(FA$24)-MONTH($EQ41)+1,$ES41/2,$EU41,TRUE)-NORMDIST((YEAR(FA$24)-YEAR($EQ41))*12+MONTH(FA$24)-MONTH($EQ41),$ES41/2,$EU41,TRUE))/(1-2*NORMDIST(0,$ES41/2,$EU41,TRUE))*$EP41 -> 0 | FB41: =AND($ET41="S-Curve",FB$24>=$EQ41,FB$24<=$ER41)*(NORMDIST((YEAR(FB$24)-YEAR($EQ41))*12+MONTH(FB$24)-MONTH($EQ41)+1,$ES41/2,$EU41,TRUE)-NORMDIST((YEAR(FB$24)-YEAR($EQ41))*12+MONTH(FB$24)-MONTH($EQ41),$ES41/2,$EU41,TRUE))/(1-2*NORMDIST(0,$ES41/2,$EU41,TRUE))*$EP41 -> 0 | FC41: =AND($ET41="S-Curve",FC$24>=$EQ41,FC$24<=$ER41)*(NORMDIST((YEAR(FC$24)-YEAR($EQ41))*12+MONTH(FC$24)-MONTH($EQ41)+1,$ES41/2,$EU41,TRUE)-NORMDIST((YEAR(FC$24)-YEAR($EQ41))*12+MONTH(FC$24)-MONTH($EQ41),$ES41/2,$EU41,TRUE))/(1-2*NORMDIST(0,$ES41/2,$EU41,TRUE))*$EP41 -> 0 | ... JX41: =AND($ET41="S-Curve",JX$24>=$EQ41,JX$24<=$ER41)*(NORMDIST((YEAR(JX$24)-YEAR($EQ41))*12+MONTH(JX$24)-MONTH($EQ41)+1,$ES41/2,$EU41,TRUE)-NORMDIST((YEAR(JX$24)-YEAR($EQ41))*12+MONTH(JX$24)-MONTH($EQ41),$ES41/2,$EU41,TRUE))/(1-2*NORMDIST(0,$ES41/2,$EU41,TRUE))*$EP41 -> 0 | JZ41: =B41 -> 0 | KB41: =D41 -> 0 | KC41: =E41 -> 36 | KD41: =KC41-KB41+1 -> 37 | KE41: =I41 -> 0 | KF41: =AND(KF$23>=$KB41,KF$23<=$KC41)*(IF($F41="Steady Growth",KF$23-$KB41,$KC41-KF$23)+1)/($KD41*($KD41+1)/2)*$KE41 -> 0 | KG41: =AND(KG$23>=$KB41,KG$23<=$KC41)*(IF($F41="Steady Growth",KG$23-$KB41,$KC41-KG$23)+1)/($KD41*($KD41+1)/2)*$KE41 -> 0 | KH41: =AND(KH$23>=$KB41,KH$23<=$KC41)*(IF($F41="Steady Growth",KH$23-$KB41,$KC41-KH$23)+1)/($KD41*($KD41+1)/2)*$KE41 -> 0 | KI41: =AND(KI$23>=$KB41,KI$23<=$KC41)*(IF($F41="Steady Growth",KI$23-$KB41,$KC41-KI$23)+1)/($KD41*($KD41+1)/2)*$KE41 -> 0 | KJ41: =AND(KJ$23>=$KB41,KJ$23<=$KC41)*(IF($F41="Steady Growth",KJ$23-$KB41,$KC41-KJ$23)+1)/($KD41*($KD41+1)/2)*$KE41 -> 0 | KK41: =AND(KK$23>=$KB41,KK$23<=$KC41)*(IF($F41="Steady Growth",KK$23-$KB41,$KC41-KK$23)+1)/($KD41*($KD41+1)/2)*$KE41 -> 0 | KL41: =AND(KL$23>=$KB41,KL$23<=$KC41)*(IF($F41="Steady Growth",KL$23-$KB41,$KC41-KL$23)+1)/($KD41*($KD41+1)/2)*$KE41 -> 0 | KM41: =AND(KM$23>=$KB41,KM$23<=$KC41)*(IF($F41="Steady Growth",KM$23-$KB41,$KC41-KM$23)+1)/($KD41*($KD41+1)/2)*$KE41 -> 0 | ... PH41: =AND(PH$23>=$KB41,PH$23<=$KC41)*(IF($F41="Steady Growth",PH$23-$KB41,$KC41-PH$23)+1)/($KD41*($KD41+1)/2)*$KE41 -> 0
B42: Included in detailed component CAPEX | C42: 1 | E42: =$E$34 -> 36 | F42: Straight-Line | G42: =I42/Units_SF_M2 -> 0 | I42: 0 | K42: =IF(ROUND(SUM(L42:EN42),0)=ROUND(I42,0),"","Incomplete") | L42: =AND(L$23>=$D42,L$23<=$E42)*(OR($F42="Straight-Line",$F42="Detail")*($I42/$ES42)+($F42="S-Curve")*EV42+OR($F42="Steady Growth",$F42="Steady Decline")*KF42) -> 0 | M42: =AND(M$23>=$D42,M$23<=$E42)*(OR($F42="Straight-Line",$F42="Detail")*($I42/$ES42)+($F42="S-Curve")*EW42+OR($F42="Steady Growth",$F42="Steady Decline")*KG42) -> 0 | N42: =AND(N$23>=$D42,N$23<=$E42)*(OR($F42="Straight-Line",$F42="Detail")*($I42/$ES42)+($F42="S-Curve")*EX42+OR($F42="Steady Growth",$F42="Steady Decline")*KH42) -> 0 | O42: =AND(O$23>=$D42,O$23<=$E42)*(OR($F42="Straight-Line",$F42="Detail")*($I42/$ES42)+($F42="S-Curve")*EY42+OR($F42="Steady Growth",$F42="Steady Decline")*KI42) -> 0 | P42: =AND(P$23>=$D42,P$23<=$E42)*(OR($F42="Straight-Line",$F42="Detail")*($I42/$ES42)+($F42="S-Curve")*EZ42+OR($F42="Steady Growth",$F42="Steady Decline")*KJ42) -> 0 | Q42: =AND(Q$23>=$D42,Q$23<=$E42)*(OR($F42="Straight-Line",$F42="Detail")*($I42/$ES42)+($F42="S-Curve")*FA42+OR($F42="Steady Growth",$F42="Steady Decline")*KK42) -> 0 | R42: =AND(R$23>=$D42,R$23<=$E42)*(OR($F42="Straight-Line",$F42="Detail")*($I42/$ES42)+($F42="S-Curve")*FB42+OR($F42="Steady Growth",$F42="Steady Decline")*KL42) -> 0 | S42: =AND(S$23>=$D42,S$23<=$E42)*(OR($F42="Straight-Line",$F42="Detail")*($I42/$ES42)+($F42="S-Curve")*FC42+OR($F42="Steady Growth",$F42="Steady Decline")*KM42) -> 0 | ... EN42: =AND(EN$23>=$D42,EN$23<=$E42)*(OR($F42="Straight-Line",$F42="Detail")*($I42/$ES42)+($F42="S-Curve")*JX42+OR($F42="Steady Growth",$F42="Steady Decline")*PH42) -> 0 | EP42: =I42 -> 0 | EQ42: =INDEX($L$24:$EN$24,1,$D42+1) -> 46203 | ER42: =INDEX($L$24:$EN$24,1,$E42+1) -> 47299 | ES42: =+E42-D42+1 -> 37 | ET42: =F42 -> Straight-Line | EU42: =ES42/Scurve_Dist -> 6.1666667 | EV42: =AND($ET42="S-Curve",EV$24>=$EQ42,EV$24<=$ER42)*(NORMDIST((YEAR(EV$24)-YEAR($EQ42))*12+MONTH(EV$24)-MONTH($EQ42)+1,$ES42/2,$EU42,TRUE)-NORMDIST((YEAR(EV$24)-YEAR($EQ42))*12+MONTH(EV$24)-MONTH($EQ42),$ES42/2,$EU42,TRUE))/(1-2*NORMDIST(0,$ES42/2,$EU42,TRUE))*$EP42 -> 0 | EW42: =AND($ET42="S-Curve",EW$24>=$EQ42,EW$24<=$ER42)*(NORMDIST((YEAR(EW$24)-YEAR($EQ42))*12+MONTH(EW$24)-MONTH($EQ42)+1,$ES42/2,$EU42,TRUE)-NORMDIST((YEAR(EW$24)-YEAR($EQ42))*12+MONTH(EW$24)-MONTH($EQ42),$ES42/2,$EU42,TRUE))/(1-2*NORMDIST(0,$ES42/2,$EU42,TRUE))*$EP42 -> 0 | EX42: =AND($ET42="S-Curve",EX$24>=$EQ42,EX$24<=$ER42)*(NORMDIST((YEAR(EX$24)-YEAR($EQ42))*12+MONTH(EX$24)-MONTH($EQ42)+1,$ES42/2,$EU42,TRUE)-NORMDIST((YEAR(EX$24)-YEAR($EQ42))*12+MONTH(EX$24)-MONTH($EQ42),$ES42/2,$EU42,TRUE))/(1-2*NORMDIST(0,$ES42/2,$EU42,TRUE))*$EP42 -> 0 | EY42: =AND($ET42="S-Curve",EY$24>=$EQ42,EY$24<=$ER42)*(NORMDIST((YEAR(EY$24)-YEAR($EQ42))*12+MONTH(EY$24)-MONTH($EQ42)+1,$ES42/2,$EU42,TRUE)-NORMDIST((YEAR(EY$24)-YEAR($EQ42))*12+MONTH(EY$24)-MONTH($EQ42),$ES42/2,$EU42,TRUE))/(1-2*NORMDIST(0,$ES42/2,$EU42,TRUE))*$EP42 -> 0 | EZ42: =AND($ET42="S-Curve",EZ$24>=$EQ42,EZ$24<=$ER42)*(NORMDIST((YEAR(EZ$24)-YEAR($EQ42))*12+MONTH(EZ$24)-MONTH($EQ42)+1,$ES42/2,$EU42,TRUE)-NORMDIST((YEAR(EZ$24)-YEAR($EQ42))*12+MONTH(EZ$24)-MONTH($EQ42),$ES42/2,$EU42,TRUE))/(1-2*NORMDIST(0,$ES42/2,$EU42,TRUE))*$EP42 -> 0 | FA42: =AND($ET42="S-Curve",FA$24>=$EQ42,FA$24<=$ER42)*(NORMDIST((YEAR(FA$24)-YEAR($EQ42))*12+MONTH(FA$24)-MONTH($EQ42)+1,$ES42/2,$EU42,TRUE)-NORMDIST((YEAR(FA$24)-YEAR($EQ42))*12+MONTH(FA$24)-MONTH($EQ42),$ES42/2,$EU42,TRUE))/(1-2*NORMDIST(0,$ES42/2,$EU42,TRUE))*$EP42 -> 0 | FB42: =AND($ET42="S-Curve",FB$24>=$EQ42,FB$24<=$ER42)*(NORMDIST((YEAR(FB$24)-YEAR($EQ42))*12+MONTH(FB$24)-MONTH($EQ42)+1,$ES42/2,$EU42,TRUE)-NORMDIST((YEAR(FB$24)-YEAR($EQ42))*12+MONTH(FB$24)-MONTH($EQ42),$ES42/2,$EU42,TRUE))/(1-2*NORMDIST(0,$ES42/2,$EU42,TRUE))*$EP42 -> 0 | FC42: =AND($ET42="S-Curve",FC$24>=$EQ42,FC$24<=$ER42)*(NORMDIST((YEAR(FC$24)-YEAR($EQ42))*12+MONTH(FC$24)-MONTH($EQ42)+1,$ES42/2,$EU42,TRUE)-NORMDIST((YEAR(FC$24)-YEAR($EQ42))*12+MONTH(FC$24)-MONTH($EQ42),$ES42/2,$EU42,TRUE))/(1-2*NORMDIST(0,$ES42/2,$EU42,TRUE))*$EP42 -> 0 | ... JX42: =AND($ET42="S-Curve",JX$24>=$EQ42,JX$24<=$ER42)*(NORMDIST((YEAR(JX$24)-YEAR($EQ42))*12+MONTH(JX$24)-MONTH($EQ42)+1,$ES42/2,$EU42,TRUE)-NORMDIST((YEAR(JX$24)-YEAR($EQ42))*12+MONTH(JX$24)-MONTH($EQ42),$ES42/2,$EU42,TRUE))/(1-2*NORMDIST(0,$ES42/2,$EU42,TRUE))*$EP42 -> 0 | JZ42: =B42 -> Included in detailed component CAPEX | KB42: =D42 -> 0 | KC42: =E42 -> 36 | KD42: =KC42-KB42+1 -> 37 | KE42: =I42 -> 0 | KF42: =AND(KF$23>=$KB42,KF$23<=$KC42)*(IF($F42="Steady Growth",KF$23-$KB42,$KC42-KF$23)+1)/($KD42*($KD42+1)/2)*$KE42 -> 0 | KG42: =AND(KG$23>=$KB42,KG$23<=$KC42)*(IF($F42="Steady Growth",KG$23-$KB42,$KC42-KG$23)+1)/($KD42*($KD42+1)/2)*$KE42 -> 0 | KH42: =AND(KH$23>=$KB42,KH$23<=$KC42)*(IF($F42="Steady Growth",KH$23-$KB42,$KC42-KH$23)+1)/($KD42*($KD42+1)/2)*$KE42 -> 0 | KI42: =AND(KI$23>=$KB42,KI$23<=$KC42)*(IF($F42="Steady Growth",KI$23-$KB42,$KC42-KI$23)+1)/($KD42*($KD42+1)/2)*$KE42 -> 0 | KJ42: =AND(KJ$23>=$KB42,KJ$23<=$KC42)*(IF($F42="Steady Growth",KJ$23-$KB42,$KC42-KJ$23)+1)/($KD42*($KD42+1)/2)*$KE42 -> 0 | KK42: =AND(KK$23>=$KB42,KK$23<=$KC42)*(IF($F42="Steady Growth",KK$23-$KB42,$KC42-KK$23)+1)/($KD42*($KD42+1)/2)*$KE42 -> 0 | KL42: =AND(KL$23>=$KB42,KL$23<=$KC42)*(IF($F42="Steady Growth",KL$23-$KB42,$KC42-KL$23)+1)/($KD42*($KD42+1)/2)*$KE42 -> 0 | KM42: =AND(KM$23>=$KB42,KM$23<=$KC42)*(IF($F42="Steady Growth",KM$23-$KB42,$KC42-KM$23)+1)/($KD42*($KD42+1)/2)*$KE42 -> 0 | ... PH42: =AND(PH$23>=$KB42,PH$23<=$KC42)*(IF($F42="Steady Growth",PH$23-$KB42,$KC42-PH$23)+1)/($KD42*($KD42+1)/2)*$KE42 -> 0
B43: Included in detailed component CAPEX | C43: 1 | E43: =$E$34 -> 36 | F43: Straight-Line | G43: =I43/Units_SF_M2 -> 0 | I43: 0 | K43: =IF(ROUND(SUM(L43:EN43),0)=ROUND(I43,0),"","Incomplete") | L43: =AND(L$23>=$D43,L$23<=$E43)*(OR($F43="Straight-Line",$F43="Detail")*($I43/$ES43)+($F43="S-Curve")*EV43+OR($F43="Steady Growth",$F43="Steady Decline")*KF43) -> 0 | M43: =AND(M$23>=$D43,M$23<=$E43)*(OR($F43="Straight-Line",$F43="Detail")*($I43/$ES43)+($F43="S-Curve")*EW43+OR($F43="Steady Growth",$F43="Steady Decline")*KG43) -> 0 | N43: =AND(N$23>=$D43,N$23<=$E43)*(OR($F43="Straight-Line",$F43="Detail")*($I43/$ES43)+($F43="S-Curve")*EX43+OR($F43="Steady Growth",$F43="Steady Decline")*KH43) -> 0 | O43: =AND(O$23>=$D43,O$23<=$E43)*(OR($F43="Straight-Line",$F43="Detail")*($I43/$ES43)+($F43="S-Curve")*EY43+OR($F43="Steady Growth",$F43="Steady Decline")*KI43) -> 0 | P43: =AND(P$23>=$D43,P$23<=$E43)*(OR($F43="Straight-Line",$F43="Detail")*($I43/$ES43)+($F43="S-Curve")*EZ43+OR($F43="Steady Growth",$F43="Steady Decline")*KJ43) -> 0 | Q43: =AND(Q$23>=$D43,Q$23<=$E43)*(OR($F43="Straight-Line",$F43="Detail")*($I43/$ES43)+($F43="S-Curve")*FA43+OR($F43="Steady Growth",$F43="Steady Decline")*KK43) -> 0 | R43: =AND(R$23>=$D43,R$23<=$E43)*(OR($F43="Straight-Line",$F43="Detail")*($I43/$ES43)+($F43="S-Curve")*FB43+OR($F43="Steady Growth",$F43="Steady Decline")*KL43) -> 0 | S43: =AND(S$23>=$D43,S$23<=$E43)*(OR($F43="Straight-Line",$F43="Detail")*($I43/$ES43)+($F43="S-Curve")*FC43+OR($F43="Steady Growth",$F43="Steady Decline")*KM43) -> 0 | ... EN43: =AND(EN$23>=$D43,EN$23<=$E43)*(OR($F43="Straight-Line",$F43="Detail")*($I43/$ES43)+($F43="S-Curve")*JX43+OR($F43="Steady Growth",$F43="Steady Decline")*PH43) -> 0 | EP43: =I43 -> 0 | EQ43: =INDEX($L$24:$EN$24,1,$D43+1) -> 46203 | ER43: =INDEX($L$24:$EN$24,1,$E43+1) -> 47299 | ES43: =+E43-D43+1 -> 37 | ET43: =F43 -> Straight-Line | EU43: =ES43/Scurve_Dist -> 6.1666667 | EV43: =AND($ET43="S-Curve",EV$24>=$EQ43,EV$24<=$ER43)*(NORMDIST((YEAR(EV$24)-YEAR($EQ43))*12+MONTH(EV$24)-MONTH($EQ43)+1,$ES43/2,$EU43,TRUE)-NORMDIST((YEAR(EV$24)-YEAR($EQ43))*12+MONTH(EV$24)-MONTH($EQ43),$ES43/2,$EU43,TRUE))/(1-2*NORMDIST(0,$ES43/2,$EU43,TRUE))*$EP43 -> 0 | EW43: =AND($ET43="S-Curve",EW$24>=$EQ43,EW$24<=$ER43)*(NORMDIST((YEAR(EW$24)-YEAR($EQ43))*12+MONTH(EW$24)-MONTH($EQ43)+1,$ES43/2,$EU43,TRUE)-NORMDIST((YEAR(EW$24)-YEAR($EQ43))*12+MONTH(EW$24)-MONTH($EQ43),$ES43/2,$EU43,TRUE))/(1-2*NORMDIST(0,$ES43/2,$EU43,TRUE))*$EP43 -> 0 | EX43: =AND($ET43="S-Curve",EX$24>=$EQ43,EX$24<=$ER43)*(NORMDIST((YEAR(EX$24)-YEAR($EQ43))*12+MONTH(EX$24)-MONTH($EQ43)+1,$ES43/2,$EU43,TRUE)-NORMDIST((YEAR(EX$24)-YEAR($EQ43))*12+MONTH(EX$24)-MONTH($EQ43),$ES43/2,$EU43,TRUE))/(1-2*NORMDIST(0,$ES43/2,$EU43,TRUE))*$EP43 -> 0 | EY43: =AND($ET43="S-Curve",EY$24>=$EQ43,EY$24<=$ER43)*(NORMDIST((YEAR(EY$24)-YEAR($EQ43))*12+MONTH(EY$24)-MONTH($EQ43)+1,$ES43/2,$EU43,TRUE)-NORMDIST((YEAR(EY$24)-YEAR($EQ43))*12+MONTH(EY$24)-MONTH($EQ43),$ES43/2,$EU43,TRUE))/(1-2*NORMDIST(0,$ES43/2,$EU43,TRUE))*$EP43 -> 0 | EZ43: =AND($ET43="S-Curve",EZ$24>=$EQ43,EZ$24<=$ER43)*(NORMDIST((YEAR(EZ$24)-YEAR($EQ43))*12+MONTH(EZ$24)-MONTH($EQ43)+1,$ES43/2,$EU43,TRUE)-NORMDIST((YEAR(EZ$24)-YEAR($EQ43))*12+MONTH(EZ$24)-MONTH($EQ43),$ES43/2,$EU43,TRUE))/(1-2*NORMDIST(0,$ES43/2,$EU43,TRUE))*$EP43 -> 0 | FA43: =AND($ET43="S-Curve",FA$24>=$EQ43,FA$24<=$ER43)*(NORMDIST((YEAR(FA$24)-YEAR($EQ43))*12+MONTH(FA$24)-MONTH($EQ43)+1,$ES43/2,$EU43,TRUE)-NORMDIST((YEAR(FA$24)-YEAR($EQ43))*12+MONTH(FA$24)-MONTH($EQ43),$ES43/2,$EU43,TRUE))/(1-2*NORMDIST(0,$ES43/2,$EU43,TRUE))*$EP43 -> 0 | FB43: =AND($ET43="S-Curve",FB$24>=$EQ43,FB$24<=$ER43)*(NORMDIST((YEAR(FB$24)-YEAR($EQ43))*12+MONTH(FB$24)-MONTH($EQ43)+1,$ES43/2,$EU43,TRUE)-NORMDIST((YEAR(FB$24)-YEAR($EQ43))*12+MONTH(FB$24)-MONTH($EQ43),$ES43/2,$EU43,TRUE))/(1-2*NORMDIST(0,$ES43/2,$EU43,TRUE))*$EP43 -> 0 | FC43: =AND($ET43="S-Curve",FC$24>=$EQ43,FC$24<=$ER43)*(NORMDIST((YEAR(FC$24)-YEAR($EQ43))*12+MONTH(FC$24)-MONTH($EQ43)+1,$ES43/2,$EU43,TRUE)-NORMDIST((YEAR(FC$24)-YEAR($EQ43))*12+MONTH(FC$24)-MONTH($EQ43),$ES43/2,$EU43,TRUE))/(1-2*NORMDIST(0,$ES43/2,$EU43,TRUE))*$EP43 -> 0 | ... JX43: =AND($ET43="S-Curve",JX$24>=$EQ43,JX$24<=$ER43)*(NORMDIST((YEAR(JX$24)-YEAR($EQ43))*12+MONTH(JX$24)-MONTH($EQ43)+1,$ES43/2,$EU43,TRUE)-NORMDIST((YEAR(JX$24)-YEAR($EQ43))*12+MONTH(JX$24)-MONTH($EQ43),$ES43/2,$EU43,TRUE))/(1-2*NORMDIST(0,$ES43/2,$EU43,TRUE))*$EP43 -> 0 | JZ43: =B43 -> Included in detailed component CAPEX | KB43: =D43 -> 0 | KC43: =E43 -> 36 | KD43: =KC43-KB43+1 -> 37 | KE43: =I43 -> 0 | KF43: =AND(KF$23>=$KB43,KF$23<=$KC43)*(IF($F43="Steady Growth",KF$23-$KB43,$KC43-KF$23)+1)/($KD43*($KD43+1)/2)*$KE43 -> 0 | KG43: =AND(KG$23>=$KB43,KG$23<=$KC43)*(IF($F43="Steady Growth",KG$23-$KB43,$KC43-KG$23)+1)/($KD43*($KD43+1)/2)*$KE43 -> 0 | KH43: =AND(KH$23>=$KB43,KH$23<=$KC43)*(IF($F43="Steady Growth",KH$23-$KB43,$KC43-KH$23)+1)/($KD43*($KD43+1)/2)*$KE43 -> 0 | KI43: =AND(KI$23>=$KB43,KI$23<=$KC43)*(IF($F43="Steady Growth",KI$23-$KB43,$KC43-KI$23)+1)/($KD43*($KD43+1)/2)*$KE43 -> 0 | KJ43: =AND(KJ$23>=$KB43,KJ$23<=$KC43)*(IF($F43="Steady Growth",KJ$23-$KB43,$KC43-KJ$23)+1)/($KD43*($KD43+1)/2)*$KE43 -> 0 | KK43: =AND(KK$23>=$KB43,KK$23<=$KC43)*(IF($F43="Steady Growth",KK$23-$KB43,$KC43-KK$23)+1)/($KD43*($KD43+1)/2)*$KE43 -> 0 | KL43: =AND(KL$23>=$KB43,KL$23<=$KC43)*(IF($F43="Steady Growth",KL$23-$KB43,$KC43-KL$23)+1)/($KD43*($KD43+1)/2)*$KE43 -> 0 | KM43: =AND(KM$23>=$KB43,KM$23<=$KC43)*(IF($F43="Steady Growth",KM$23-$KB43,$KC43-KM$23)+1)/($KD43*($KD43+1)/2)*$KE43 -> 0 | ... PH43: =AND(PH$23>=$KB43,PH$23<=$KC43)*(IF($F43="Steady Growth",PH$23-$KB43,$KC43-PH$23)+1)/($KD43*($KD43+1)/2)*$KE43 -> 0
B44: Included in detailed component CAPEX | C44: 1 | E44: =$E$34 -> 36 | F44: Straight-Line | G44: =I44/Units_SF_M2 -> 0 | I44: 0 | K44: =IF(ROUND(SUM(L44:EN44),0)=ROUND(I44,0),"","Incomplete") | L44: =AND(L$23>=$D44,L$23<=$E44)*(OR($F44="Straight-Line",$F44="Detail")*($I44/$ES44)+($F44="S-Curve")*EV44+OR($F44="Steady Growth",$F44="Steady Decline")*KF44) -> 0 | M44: =AND(M$23>=$D44,M$23<=$E44)*(OR($F44="Straight-Line",$F44="Detail")*($I44/$ES44)+($F44="S-Curve")*EW44+OR($F44="Steady Growth",$F44="Steady Decline")*KG44) -> 0 | N44: =AND(N$23>=$D44,N$23<=$E44)*(OR($F44="Straight-Line",$F44="Detail")*($I44/$ES44)+($F44="S-Curve")*EX44+OR($F44="Steady Growth",$F44="Steady Decline")*KH44) -> 0 | O44: =AND(O$23>=$D44,O$23<=$E44)*(OR($F44="Straight-Line",$F44="Detail")*($I44/$ES44)+($F44="S-Curve")*EY44+OR($F44="Steady Growth",$F44="Steady Decline")*KI44) -> 0 | P44: =AND(P$23>=$D44,P$23<=$E44)*(OR($F44="Straight-Line",$F44="Detail")*($I44/$ES44)+($F44="S-Curve")*EZ44+OR($F44="Steady Growth",$F44="Steady Decline")*KJ44) -> 0 | Q44: =AND(Q$23>=$D44,Q$23<=$E44)*(OR($F44="Straight-Line",$F44="Detail")*($I44/$ES44)+($F44="S-Curve")*FA44+OR($F44="Steady Growth",$F44="Steady Decline")*KK44) -> 0 | R44: =AND(R$23>=$D44,R$23<=$E44)*(OR($F44="Straight-Line",$F44="Detail")*($I44/$ES44)+($F44="S-Curve")*FB44+OR($F44="Steady Growth",$F44="Steady Decline")*KL44) -> 0 | S44: =AND(S$23>=$D44,S$23<=$E44)*(OR($F44="Straight-Line",$F44="Detail")*($I44/$ES44)+($F44="S-Curve")*FC44+OR($F44="Steady Growth",$F44="Steady Decline")*KM44) -> 0 | ... EN44: =AND(EN$23>=$D44,EN$23<=$E44)*(OR($F44="Straight-Line",$F44="Detail")*($I44/$ES44)+($F44="S-Curve")*JX44+OR($F44="Steady Growth",$F44="Steady Decline")*PH44) -> 0 | EP44: =I44 -> 0 | EQ44: =INDEX($L$24:$EN$24,1,$D44+1) -> 46203 | ER44: =INDEX($L$24:$EN$24,1,$E44+1) -> 47299 | ES44: =+E44-D44+1 -> 37 | ET44: =F44 -> Straight-Line | EU44: =ES44/Scurve_Dist -> 6.1666667 | EV44: =AND($ET44="S-Curve",EV$24>=$EQ44,EV$24<=$ER44)*(NORMDIST((YEAR(EV$24)-YEAR($EQ44))*12+MONTH(EV$24)-MONTH($EQ44)+1,$ES44/2,$EU44,TRUE)-NORMDIST((YEAR(EV$24)-YEAR($EQ44))*12+MONTH(EV$24)-MONTH($EQ44),$ES44/2,$EU44,TRUE))/(1-2*NORMDIST(0,$ES44/2,$EU44,TRUE))*$EP44 -> 0 | EW44: =AND($ET44="S-Curve",EW$24>=$EQ44,EW$24<=$ER44)*(NORMDIST((YEAR(EW$24)-YEAR($EQ44))*12+MONTH(EW$24)-MONTH($EQ44)+1,$ES44/2,$EU44,TRUE)-NORMDIST((YEAR(EW$24)-YEAR($EQ44))*12+MONTH(EW$24)-MONTH($EQ44),$ES44/2,$EU44,TRUE))/(1-2*NORMDIST(0,$ES44/2,$EU44,TRUE))*$EP44 -> 0 | EX44: =AND($ET44="S-Curve",EX$24>=$EQ44,EX$24<=$ER44)*(NORMDIST((YEAR(EX$24)-YEAR($EQ44))*12+MONTH(EX$24)-MONTH($EQ44)+1,$ES44/2,$EU44,TRUE)-NORMDIST((YEAR(EX$24)-YEAR($EQ44))*12+MONTH(EX$24)-MONTH($EQ44),$ES44/2,$EU44,TRUE))/(1-2*NORMDIST(0,$ES44/2,$EU44,TRUE))*$EP44 -> 0 | EY44: =AND($ET44="S-Curve",EY$24>=$EQ44,EY$24<=$ER44)*(NORMDIST((YEAR(EY$24)-YEAR($EQ44))*12+MONTH(EY$24)-MONTH($EQ44)+1,$ES44/2,$EU44,TRUE)-NORMDIST((YEAR(EY$24)-YEAR($EQ44))*12+MONTH(EY$24)-MONTH($EQ44),$ES44/2,$EU44,TRUE))/(1-2*NORMDIST(0,$ES44/2,$EU44,TRUE))*$EP44 -> 0 | EZ44: =AND($ET44="S-Curve",EZ$24>=$EQ44,EZ$24<=$ER44)*(NORMDIST((YEAR(EZ$24)-YEAR($EQ44))*12+MONTH(EZ$24)-MONTH($EQ44)+1,$ES44/2,$EU44,TRUE)-NORMDIST((YEAR(EZ$24)-YEAR($EQ44))*12+MONTH(EZ$24)-MONTH($EQ44),$ES44/2,$EU44,TRUE))/(1-2*NORMDIST(0,$ES44/2,$EU44,TRUE))*$EP44 -> 0 | FA44: =AND($ET44="S-Curve",FA$24>=$EQ44,FA$24<=$ER44)*(NORMDIST((YEAR(FA$24)-YEAR($EQ44))*12+MONTH(FA$24)-MONTH($EQ44)+1,$ES44/2,$EU44,TRUE)-NORMDIST((YEAR(FA$24)-YEAR($EQ44))*12+MONTH(FA$24)-MONTH($EQ44),$ES44/2,$EU44,TRUE))/(1-2*NORMDIST(0,$ES44/2,$EU44,TRUE))*$EP44 -> 0 | FB44: =AND($ET44="S-Curve",FB$24>=$EQ44,FB$24<=$ER44)*(NORMDIST((YEAR(FB$24)-YEAR($EQ44))*12+MONTH(FB$24)-MONTH($EQ44)+1,$ES44/2,$EU44,TRUE)-NORMDIST((YEAR(FB$24)-YEAR($EQ44))*12+MONTH(FB$24)-MONTH($EQ44),$ES44/2,$EU44,TRUE))/(1-2*NORMDIST(0,$ES44/2,$EU44,TRUE))*$EP44 -> 0 | FC44: =AND($ET44="S-Curve",FC$24>=$EQ44,FC$24<=$ER44)*(NORMDIST((YEAR(FC$24)-YEAR($EQ44))*12+MONTH(FC$24)-MONTH($EQ44)+1,$ES44/2,$EU44,TRUE)-NORMDIST((YEAR(FC$24)-YEAR($EQ44))*12+MONTH(FC$24)-MONTH($EQ44),$ES44/2,$EU44,TRUE))/(1-2*NORMDIST(0,$ES44/2,$EU44,TRUE))*$EP44 -> 0 | ... JX44: =AND($ET44="S-Curve",JX$24>=$EQ44,JX$24<=$ER44)*(NORMDIST((YEAR(JX$24)-YEAR($EQ44))*12+MONTH(JX$24)-MONTH($EQ44)+1,$ES44/2,$EU44,TRUE)-NORMDIST((YEAR(JX$24)-YEAR($EQ44))*12+MONTH(JX$24)-MONTH($EQ44),$ES44/2,$EU44,TRUE))/(1-2*NORMDIST(0,$ES44/2,$EU44,TRUE))*$EP44 -> 0 | JZ44: =B44 -> Included in detailed component CAPEX | KB44: =D44 -> 0 | KC44: =E44 -> 36 | KD44: =KC44-KB44+1 -> 37 | KE44: =I44 -> 0 | KF44: =AND(KF$23>=$KB44,KF$23<=$KC44)*(IF($F44="Steady Growth",KF$23-$KB44,$KC44-KF$23)+1)/($KD44*($KD44+1)/2)*$KE44 -> 0 | KG44: =AND(KG$23>=$KB44,KG$23<=$KC44)*(IF($F44="Steady Growth",KG$23-$KB44,$KC44-KG$23)+1)/($KD44*($KD44+1)/2)*$KE44 -> 0 | KH44: =AND(KH$23>=$KB44,KH$23<=$KC44)*(IF($F44="Steady Growth",KH$23-$KB44,$KC44-KH$23)+1)/($KD44*($KD44+1)/2)*$KE44 -> 0 | KI44: =AND(KI$23>=$KB44,KI$23<=$KC44)*(IF($F44="Steady Growth",KI$23-$KB44,$KC44-KI$23)+1)/($KD44*($KD44+1)/2)*$KE44 -> 0 | KJ44: =AND(KJ$23>=$KB44,KJ$23<=$KC44)*(IF($F44="Steady Growth",KJ$23-$KB44,$KC44-KJ$23)+1)/($KD44*($KD44+1)/2)*$KE44 -> 0 | KK44: =AND(KK$23>=$KB44,KK$23<=$KC44)*(IF($F44="Steady Growth",KK$23-$KB44,$KC44-KK$23)+1)/($KD44*($KD44+1)/2)*$KE44 -> 0 | KL44: =AND(KL$23>=$KB44,KL$23<=$KC44)*(IF($F44="Steady Growth",KL$23-$KB44,$KC44-KL$23)+1)/($KD44*($KD44+1)/2)*$KE44 -> 0 | KM44: =AND(KM$23>=$KB44,KM$23<=$KC44)*(IF($F44="Steady Growth",KM$23-$KB44,$KC44-KM$23)+1)/($KD44*($KD44+1)/2)*$KE44 -> 0 | ... PH44: =AND(PH$23>=$KB44,PH$23<=$KC44)*(IF($F44="Steady Growth",PH$23-$KB44,$KC44-PH$23)+1)/($KD44*($KD44+1)/2)*$KE44 -> 0
B45: Included in detailed component CAPEX | C45: 1 | E45: =$E$34 -> 36 | F45: Straight-Line | G45: =I45/Units_SF_M2 -> 0 | I45: 0 | K45: =IF(ROUND(SUM(L45:EN45),0)=ROUND(I45,0),"","Incomplete") | L45: =AND(L$23>=$D45,L$23<=$E45)*(OR($F45="Straight-Line",$F45="Detail")*($I45/$ES45)+($F45="S-Curve")*EV45+OR($F45="Steady Growth",$F45="Steady Decline")*KF45) -> 0 | M45: =AND(M$23>=$D45,M$23<=$E45)*(OR($F45="Straight-Line",$F45="Detail")*($I45/$ES45)+($F45="S-Curve")*EW45+OR($F45="Steady Growth",$F45="Steady Decline")*KG45) -> 0 | N45: =AND(N$23>=$D45,N$23<=$E45)*(OR($F45="Straight-Line",$F45="Detail")*($I45/$ES45)+($F45="S-Curve")*EX45+OR($F45="Steady Growth",$F45="Steady Decline")*KH45) -> 0 | O45: =AND(O$23>=$D45,O$23<=$E45)*(OR($F45="Straight-Line",$F45="Detail")*($I45/$ES45)+($F45="S-Curve")*EY45+OR($F45="Steady Growth",$F45="Steady Decline")*KI45) -> 0 | P45: =AND(P$23>=$D45,P$23<=$E45)*(OR($F45="Straight-Line",$F45="Detail")*($I45/$ES45)+($F45="S-Curve")*EZ45+OR($F45="Steady Growth",$F45="Steady Decline")*KJ45) -> 0 | Q45: =AND(Q$23>=$D45,Q$23<=$E45)*(OR($F45="Straight-Line",$F45="Detail")*($I45/$ES45)+($F45="S-Curve")*FA45+OR($F45="Steady Growth",$F45="Steady Decline")*KK45) -> 0 | R45: =AND(R$23>=$D45,R$23<=$E45)*(OR($F45="Straight-Line",$F45="Detail")*($I45/$ES45)+($F45="S-Curve")*FB45+OR($F45="Steady Growth",$F45="Steady Decline")*KL45) -> 0 | S45: =AND(S$23>=$D45,S$23<=$E45)*(OR($F45="Straight-Line",$F45="Detail")*($I45/$ES45)+($F45="S-Curve")*FC45+OR($F45="Steady Growth",$F45="Steady Decline")*KM45) -> 0 | ... EN45: =AND(EN$23>=$D45,EN$23<=$E45)*(OR($F45="Straight-Line",$F45="Detail")*($I45/$ES45)+($F45="S-Curve")*JX45+OR($F45="Steady Growth",$F45="Steady Decline")*PH45) -> 0 | EP45: =I45 -> 0 | EQ45: =INDEX($L$24:$EN$24,1,$D45+1) -> 46203 | ER45: =INDEX($L$24:$EN$24,1,$E45+1) -> 47299 | ES45: =+E45-D45+1 -> 37 | ET45: =F45 -> Straight-Line | EU45: =ES45/Scurve_Dist -> 6.1666667 | EV45: =AND($ET45="S-Curve",EV$24>=$EQ45,EV$24<=$ER45)*(NORMDIST((YEAR(EV$24)-YEAR($EQ45))*12+MONTH(EV$24)-MONTH($EQ45)+1,$ES45/2,$EU45,TRUE)-NORMDIST((YEAR(EV$24)-YEAR($EQ45))*12+MONTH(EV$24)-MONTH($EQ45),$ES45/2,$EU45,TRUE))/(1-2*NORMDIST(0,$ES45/2,$EU45,TRUE))*$EP45 -> 0 | EW45: =AND($ET45="S-Curve",EW$24>=$EQ45,EW$24<=$ER45)*(NORMDIST((YEAR(EW$24)-YEAR($EQ45))*12+MONTH(EW$24)-MONTH($EQ45)+1,$ES45/2,$EU45,TRUE)-NORMDIST((YEAR(EW$24)-YEAR($EQ45))*12+MONTH(EW$24)-MONTH($EQ45),$ES45/2,$EU45,TRUE))/(1-2*NORMDIST(0,$ES45/2,$EU45,TRUE))*$EP45 -> 0 | EX45: =AND($ET45="S-Curve",EX$24>=$EQ45,EX$24<=$ER45)*(NORMDIST((YEAR(EX$24)-YEAR($EQ45))*12+MONTH(EX$24)-MONTH($EQ45)+1,$ES45/2,$EU45,TRUE)-NORMDIST((YEAR(EX$24)-YEAR($EQ45))*12+MONTH(EX$24)-MONTH($EQ45),$ES45/2,$EU45,TRUE))/(1-2*NORMDIST(0,$ES45/2,$EU45,TRUE))*$EP45 -> 0 | EY45: =AND($ET45="S-Curve",EY$24>=$EQ45,EY$24<=$ER45)*(NORMDIST((YEAR(EY$24)-YEAR($EQ45))*12+MONTH(EY$24)-MONTH($EQ45)+1,$ES45/2,$EU45,TRUE)-NORMDIST((YEAR(EY$24)-YEAR($EQ45))*12+MONTH(EY$24)-MONTH($EQ45),$ES45/2,$EU45,TRUE))/(1-2*NORMDIST(0,$ES45/2,$EU45,TRUE))*$EP45 -> 0 | EZ45: =AND($ET45="S-Curve",EZ$24>=$EQ45,EZ$24<=$ER45)*(NORMDIST((YEAR(EZ$24)-YEAR($EQ45))*12+MONTH(EZ$24)-MONTH($EQ45)+1,$ES45/2,$EU45,TRUE)-NORMDIST((YEAR(EZ$24)-YEAR($EQ45))*12+MONTH(EZ$24)-MONTH($EQ45),$ES45/2,$EU45,TRUE))/(1-2*NORMDIST(0,$ES45/2,$EU45,TRUE))*$EP45 -> 0 | FA45: =AND($ET45="S-Curve",FA$24>=$EQ45,FA$24<=$ER45)*(NORMDIST((YEAR(FA$24)-YEAR($EQ45))*12+MONTH(FA$24)-MONTH($EQ45)+1,$ES45/2,$EU45,TRUE)-NORMDIST((YEAR(FA$24)-YEAR($EQ45))*12+MONTH(FA$24)-MONTH($EQ45),$ES45/2,$EU45,TRUE))/(1-2*NORMDIST(0,$ES45/2,$EU45,TRUE))*$EP45 -> 0 | FB45: =AND($ET45="S-Curve",FB$24>=$EQ45,FB$24<=$ER45)*(NORMDIST((YEAR(FB$24)-YEAR($EQ45))*12+MONTH(FB$24)-MONTH($EQ45)+1,$ES45/2,$EU45,TRUE)-NORMDIST((YEAR(FB$24)-YEAR($EQ45))*12+MONTH(FB$24)-MONTH($EQ45),$ES45/2,$EU45,TRUE))/(1-2*NORMDIST(0,$ES45/2,$EU45,TRUE))*$EP45 -> 0 | FC45: =AND($ET45="S-Curve",FC$24>=$EQ45,FC$24<=$ER45)*(NORMDIST((YEAR(FC$24)-YEAR($EQ45))*12+MONTH(FC$24)-MONTH($EQ45)+1,$ES45/2,$EU45,TRUE)-NORMDIST((YEAR(FC$24)-YEAR($EQ45))*12+MONTH(FC$24)-MONTH($EQ45),$ES45/2,$EU45,TRUE))/(1-2*NORMDIST(0,$ES45/2,$EU45,TRUE))*$EP45 -> 0 | ... JX45: =AND($ET45="S-Curve",JX$24>=$EQ45,JX$24<=$ER45)*(NORMDIST((YEAR(JX$24)-YEAR($EQ45))*12+MONTH(JX$24)-MONTH($EQ45)+1,$ES45/2,$EU45,TRUE)-NORMDIST((YEAR(JX$24)-YEAR($EQ45))*12+MONTH(JX$24)-MONTH($EQ45),$ES45/2,$EU45,TRUE))/(1-2*NORMDIST(0,$ES45/2,$EU45,TRUE))*$EP45 -> 0 | JZ45: =B45 -> Included in detailed component CAPEX | KB45: =D45 -> 0 | KC45: =E45 -> 36 | KD45: =KC45-KB45+1 -> 37 | KE45: =I45 -> 0 | KF45: =AND(KF$23>=$KB45,KF$23<=$KC45)*(IF($F45="Steady Growth",KF$23-$KB45,$KC45-KF$23)+1)/($KD45*($KD45+1)/2)*$KE45 -> 0 | KG45: =AND(KG$23>=$KB45,KG$23<=$KC45)*(IF($F45="Steady Growth",KG$23-$KB45,$KC45-KG$23)+1)/($KD45*($KD45+1)/2)*$KE45 -> 0 | KH45: =AND(KH$23>=$KB45,KH$23<=$KC45)*(IF($F45="Steady Growth",KH$23-$KB45,$KC45-KH$23)+1)/($KD45*($KD45+1)/2)*$KE45 -> 0 | KI45: =AND(KI$23>=$KB45,KI$23<=$KC45)*(IF($F45="Steady Growth",KI$23-$KB45,$KC45-KI$23)+1)/($KD45*($KD45+1)/2)*$KE45 -> 0 | KJ45: =AND(KJ$23>=$KB45,KJ$23<=$KC45)*(IF($F45="Steady Growth",KJ$23-$KB45,$KC45-KJ$23)+1)/($KD45*($KD45+1)/2)*$KE45 -> 0 | KK45: =AND(KK$23>=$KB45,KK$23<=$KC45)*(IF($F45="Steady Growth",KK$23-$KB45,$KC45-KK$23)+1)/($KD45*($KD45+1)/2)*$KE45 -> 0 | KL45: =AND(KL$23>=$KB45,KL$23<=$KC45)*(IF($F45="Steady Growth",KL$23-$KB45,$KC45-KL$23)+1)/($KD45*($KD45+1)/2)*$KE45 -> 0 | KM45: =AND(KM$23>=$KB45,KM$23<=$KC45)*(IF($F45="Steady Growth",KM$23-$KB45,$KC45-KM$23)+1)/($KD45*($KD45+1)/2)*$KE45 -> 0 | ... PH45: =AND(PH$23>=$KB45,PH$23<=$KC45)*(IF($F45="Steady Growth",PH$23-$KB45,$KC45-PH$23)+1)/($KD45*($KD45+1)/2)*$KE45 -> 0
B46: Included in detailed component CAPEX | C46: =I46/SUM(I41:I44,I38,I31) -> 0 | D46: 1 | E46: =$E$34 -> 36 | F46: Straight-Line | G46: =I46/Units_SF_M2 -> 0 | I46: 0 | K46: =IF(ROUND(SUM(L46:EN46),0)=ROUND(I46,0),"","Incomplete") | L46: =AND(L$23>=$D46,L$23<=$E46)*(OR($F46="Straight-Line",$F46="Detail")*($I46/$ES46)+($F46="S-Curve")*EV46+OR($F46="Steady Growth",$F46="Steady Decline")*KF46) -> 0 | M46: =AND(M$23>=$D46,M$23<=$E46)*(OR($F46="Straight-Line",$F46="Detail")*($I46/$ES46)+($F46="S-Curve")*EW46+OR($F46="Steady Growth",$F46="Steady Decline")*KG46) -> 0 | N46: =AND(N$23>=$D46,N$23<=$E46)*(OR($F46="Straight-Line",$F46="Detail")*($I46/$ES46)+($F46="S-Curve")*EX46+OR($F46="Steady Growth",$F46="Steady Decline")*KH46) -> 0 | O46: =AND(O$23>=$D46,O$23<=$E46)*(OR($F46="Straight-Line",$F46="Detail")*($I46/$ES46)+($F46="S-Curve")*EY46+OR($F46="Steady Growth",$F46="Steady Decline")*KI46) -> 0 | P46: =AND(P$23>=$D46,P$23<=$E46)*(OR($F46="Straight-Line",$F46="Detail")*($I46/$ES46)+($F46="S-Curve")*EZ46+OR($F46="Steady Growth",$F46="Steady Decline")*KJ46) -> 0 | Q46: =AND(Q$23>=$D46,Q$23<=$E46)*(OR($F46="Straight-Line",$F46="Detail")*($I46/$ES46)+($F46="S-Curve")*FA46+OR($F46="Steady Growth",$F46="Steady Decline")*KK46) -> 0 | R46: =AND(R$23>=$D46,R$23<=$E46)*(OR($F46="Straight-Line",$F46="Detail")*($I46/$ES46)+($F46="S-Curve")*FB46+OR($F46="Steady Growth",$F46="Steady Decline")*KL46) -> 0 | S46: =AND(S$23>=$D46,S$23<=$E46)*(OR($F46="Straight-Line",$F46="Detail")*($I46/$ES46)+($F46="S-Curve")*FC46+OR($F46="Steady Growth",$F46="Steady Decline")*KM46) -> 0 | ... EN46: =AND(EN$23>=$D46,EN$23<=$E46)*(OR($F46="Straight-Line",$F46="Detail")*($I46/$ES46)+($F46="S-Curve")*JX46+OR($F46="Steady Growth",$F46="Steady Decline")*PH46) -> 0 | EP46: =I46 -> 0 | EQ46: =INDEX($L$24:$EN$24,1,$D46+1) -> 46234 | ER46: =INDEX($L$24:$EN$24,1,$E46+1) -> 47299 | ES46: =+E46-D46+1 -> 36 | ET46: =F46 -> Straight-Line | EU46: =ES46/Scurve_Dist -> 6 | EV46: =AND($ET46="S-Curve",EV$24>=$EQ46,EV$24<=$ER46)*(NORMDIST((YEAR(EV$24)-YEAR($EQ46))*12+MONTH(EV$24)-MONTH($EQ46)+1,$ES46/2,$EU46,TRUE)-NORMDIST((YEAR(EV$24)-YEAR($EQ46))*12+MONTH(EV$24)-MONTH($EQ46),$ES46/2,$EU46,TRUE))/(1-2*NORMDIST(0,$ES46/2,$EU46,TRUE))*$EP46 -> 0 | EW46: =AND($ET46="S-Curve",EW$24>=$EQ46,EW$24<=$ER46)*(NORMDIST((YEAR(EW$24)-YEAR($EQ46))*12+MONTH(EW$24)-MONTH($EQ46)+1,$ES46/2,$EU46,TRUE)-NORMDIST((YEAR(EW$24)-YEAR($EQ46))*12+MONTH(EW$24)-MONTH($EQ46),$ES46/2,$EU46,TRUE))/(1-2*NORMDIST(0,$ES46/2,$EU46,TRUE))*$EP46 -> 0 | EX46: =AND($ET46="S-Curve",EX$24>=$EQ46,EX$24<=$ER46)*(NORMDIST((YEAR(EX$24)-YEAR($EQ46))*12+MONTH(EX$24)-MONTH($EQ46)+1,$ES46/2,$EU46,TRUE)-NORMDIST((YEAR(EX$24)-YEAR($EQ46))*12+MONTH(EX$24)-MONTH($EQ46),$ES46/2,$EU46,TRUE))/(1-2*NORMDIST(0,$ES46/2,$EU46,TRUE))*$EP46 -> 0 | EY46: =AND($ET46="S-Curve",EY$24>=$EQ46,EY$24<=$ER46)*(NORMDIST((YEAR(EY$24)-YEAR($EQ46))*12+MONTH(EY$24)-MONTH($EQ46)+1,$ES46/2,$EU46,TRUE)-NORMDIST((YEAR(EY$24)-YEAR($EQ46))*12+MONTH(EY$24)-MONTH($EQ46),$ES46/2,$EU46,TRUE))/(1-2*NORMDIST(0,$ES46/2,$EU46,TRUE))*$EP46 -> 0 | EZ46: =AND($ET46="S-Curve",EZ$24>=$EQ46,EZ$24<=$ER46)*(NORMDIST((YEAR(EZ$24)-YEAR($EQ46))*12+MONTH(EZ$24)-MONTH($EQ46)+1,$ES46/2,$EU46,TRUE)-NORMDIST((YEAR(EZ$24)-YEAR($EQ46))*12+MONTH(EZ$24)-MONTH($EQ46),$ES46/2,$EU46,TRUE))/(1-2*NORMDIST(0,$ES46/2,$EU46,TRUE))*$EP46 -> 0 | FA46: =AND($ET46="S-Curve",FA$24>=$EQ46,FA$24<=$ER46)*(NORMDIST((YEAR(FA$24)-YEAR($EQ46))*12+MONTH(FA$24)-MONTH($EQ46)+1,$ES46/2,$EU46,TRUE)-NORMDIST((YEAR(FA$24)-YEAR($EQ46))*12+MONTH(FA$24)-MONTH($EQ46),$ES46/2,$EU46,TRUE))/(1-2*NORMDIST(0,$ES46/2,$EU46,TRUE))*$EP46 -> 0 | FB46: =AND($ET46="S-Curve",FB$24>=$EQ46,FB$24<=$ER46)*(NORMDIST((YEAR(FB$24)-YEAR($EQ46))*12+MONTH(FB$24)-MONTH($EQ46)+1,$ES46/2,$EU46,TRUE)-NORMDIST((YEAR(FB$24)-YEAR($EQ46))*12+MONTH(FB$24)-MONTH($EQ46),$ES46/2,$EU46,TRUE))/(1-2*NORMDIST(0,$ES46/2,$EU46,TRUE))*$EP46 -> 0 | FC46: =AND($ET46="S-Curve",FC$24>=$EQ46,FC$24<=$ER46)*(NORMDIST((YEAR(FC$24)-YEAR($EQ46))*12+MONTH(FC$24)-MONTH($EQ46)+1,$ES46/2,$EU46,TRUE)-NORMDIST((YEAR(FC$24)-YEAR($EQ46))*12+MONTH(FC$24)-MONTH($EQ46),$ES46/2,$EU46,TRUE))/(1-2*NORMDIST(0,$ES46/2,$EU46,TRUE))*$EP46 -> 0 | ... JX46: =AND($ET46="S-Curve",JX$24>=$EQ46,JX$24<=$ER46)*(NORMDIST((YEAR(JX$24)-YEAR($EQ46))*12+MONTH(JX$24)-MONTH($EQ46)+1,$ES46/2,$EU46,TRUE)-NORMDIST((YEAR(JX$24)-YEAR($EQ46))*12+MONTH(JX$24)-MONTH($EQ46),$ES46/2,$EU46,TRUE))/(1-2*NORMDIST(0,$ES46/2,$EU46,TRUE))*$EP46 -> 0 | JZ46: =B46 -> Included in detailed component CAPEX | KB46: =D46 -> 1 | KC46: =E46 -> 36 | KD46: =KC46-KB46+1 -> 36 | KE46: =I46 -> 0 | KF46: =AND(KF$23>=$KB46,KF$23<=$KC46)*(IF($F46="Steady Growth",KF$23-$KB46,$KC46-KF$23)+1)/($KD46*($KD46+1)/2)*$KE46 -> 0 | KG46: =AND(KG$23>=$KB46,KG$23<=$KC46)*(IF($F46="Steady Growth",KG$23-$KB46,$KC46-KG$23)+1)/($KD46*($KD46+1)/2)*$KE46 -> 0 | KH46: =AND(KH$23>=$KB46,KH$23<=$KC46)*(IF($F46="Steady Growth",KH$23-$KB46,$KC46-KH$23)+1)/($KD46*($KD46+1)/2)*$KE46 -> 0 | KI46: =AND(KI$23>=$KB46,KI$23<=$KC46)*(IF($F46="Steady Growth",KI$23-$KB46,$KC46-KI$23)+1)/($KD46*($KD46+1)/2)*$KE46 -> 0 | KJ46: =AND(KJ$23>=$KB46,KJ$23<=$KC46)*(IF($F46="Steady Growth",KJ$23-$KB46,$KC46-KJ$23)+1)/($KD46*($KD46+1)/2)*$KE46 -> 0 | KK46: =AND(KK$23>=$KB46,KK$23<=$KC46)*(IF($F46="Steady Growth",KK$23-$KB46,$KC46-KK$23)+1)/($KD46*($KD46+1)/2)*$KE46 -> 0 | KL46: =AND(KL$23>=$KB46,KL$23<=$KC46)*(IF($F46="Steady Growth",KL$23-$KB46,$KC46-KL$23)+1)/($KD46*($KD46+1)/2)*$KE46 -> 0 | KM46: =AND(KM$23>=$KB46,KM$23<=$KC46)*(IF($F46="Steady Growth",KM$23-$KB46,$KC46-KM$23)+1)/($KD46*($KD46+1)/2)*$KE46 -> 0 | ... PH46: =AND(PH$23>=$KB46,PH$23<=$KC46)*(IF($F46="Steady Growth",PH$23-$KB46,$KC46-PH$23)+1)/($KD46*($KD46+1)/2)*$KE46 -> 0
B47: Total Soft Costs | C47: =MIN(D41:D46) -> 1 | E47: =MAX(E41:E46) -> 36 | F47: =SUM(H41:H46) -> 0 | I47: =SUM(I41:I46) -> 0 | K47: =IF(ROUND(SUM(L47:EN47),0)=ROUND(I47,0),"","Incomplete") | L47: =SUM(L41:L46) -> 0 | M47: =SUM(M41:M46) -> 0 | N47: =SUM(N41:N46) -> 0 | O47: =SUM(O41:O46) -> 0 | P47: =SUM(P41:P46) -> 0 | Q47: =SUM(Q41:Q46) -> 0 | R47: =SUM(R41:R46) -> 0 | S47: =SUM(S41:S46) -> 0 | ... EN47: =SUM(EN41:EN46) -> 0 | EQ47: # of Soft Cost Items | ER47: =COUNTA($B$41:$B$46) -> 5
C49: =+H47+H38+H31 -> 0 | I49: =+I47+I38+I31 -> 4.4885664e+08 | M49: =+N47+N38+N31 -> 1153238.8 | N49: =+O47+O38+O31 -> 1540571.8 | O49: =+P47+P38+P31 -> 2077208.7 | P49: =+Q47+Q38+Q31 -> 2798042.2 | Q49: =+R47+R38+R31 -> 3736098.9 | R49: =+S47+S38+S31 -> 4917681.3 | S49: =+T47+T38+T31 -> 6356585.4 | T49: =+U47+U38+U31 -> 8048084.8 | ... AQ49: =+AR47+AR38+AR31 -> 2077208.7 | AR49: =+AR47+AR38+AR31 -> 2077208.7 | AS49: =+AS47+AS38+AS31 -> 1540571.8 | AT49: =+AT47+AT38+AT31 -> 1153238.8 | AU49: =+AU47+AU38+AU31 -> 882028.36 | AV49: =+AV47+AV38+AV31 -> 697714.09 | AW49: =+AW47+AW38+AW31 -> 0 | AX49: =+AX47+AX38+AX31 -> 0 | AY49: =+AY47+AY38+AY31 -> 0 | ... EN49: =+EN47+EN38+EN31 -> 0
C51: 124 | G51: 125 | EP51: SOURCES AND USES CALCULATIONS | EU51: Total | EV51: =EV3 -> 0 | EW51: =EW3 -> 1 | EX51: =EX3 -> 2 | EY51: =EY3 -> 3 | EZ51: =EZ3 -> 4 | FA51: =FA3 -> 5 | FB51: =FB3 -> 6 | FC51: =FC3 -> 7 | ... JX51: =JX3 -> 132
B52: Financing fees and carry calculated in DEBT | C52: 1 | G52: =I52/Units_SF_M2 -> 0 | I52: 0 | L52: =IF(L$23="","",0) -> 0 | M52: =IF(M$23="","",0) -> 0 | N52: =IF(N$23="","",0) -> 0 | O52: =IF(O$23="","",0) -> 0 | P52: =IF(P$23="","",0) -> 0 | Q52: =IF(Q$23="","",0) -> 0 | R52: =IF(R$23="","",0) -> 0 | S52: =IF(S$23="","",0) -> 0 | ... EN52: =IF(EN$23="","",0) -> 0 | EP52: Total Development Costs (before Carry Costs) | EU52: =SUM(EV52:JX52) -> 4.4885664e+08 | EV52: =L47+L38+L31 -> 93017714 | EW52: =M47+M38+M31 -> 882028.36 | EX52: =N47+N38+N31 -> 1153238.8 | EY52: =O47+O38+O31 -> 1540571.8 | EZ52: =P47+P38+P31 -> 2077208.7 | FA52: =Q47+Q38+Q31 -> 2798042.2 | FB52: =R47+R38+R31 -> 3736098.9 | FC52: =S47+S38+S31 -> 4917681.3 | ... JX52: =EN47+EN38+EN31 -> 0
B53: Other financing costs | C53: 0 | E53: 0 | F53: Straight-Line | G53: =I53/Units_SF_M2 -> 0 | I53: 0 | K53: =IF(ROUND(SUM(L53:EN53),0)=ROUND(I53,0),"","Incomplete") | L53: =IF(L$23="","",0) -> 0 | M53: =IF(M$23="","",0) -> 0 | N53: =IF(N$23="","",0) -> 0 | O53: =IF(O$23="","",0) -> 0 | P53: =IF(P$23="","",0) -> 0 | Q53: =IF(Q$23="","",0) -> 0 | R53: =IF(R$23="","",0) -> 0 | S53: =IF(S$23="","",0) -> 0 | ... EN53: =IF(EN$23="","",0) -> 0 | EP53: Carry Costs | EU53: =SUM(EV53:JX53) -> 0 | EV53: =SUM(L52:L54) -> 0 | EW53: =SUM(M52:M54) -> 0 | EX53: =SUM(N52:N54) -> 0 | EY53: =SUM(O52:O54) -> 0 | EZ53: =SUM(P52:P54) -> 0 | FA53: =SUM(Q52:Q54) -> 0 | FB53: =SUM(R52:R54) -> 0 | FC53: =SUM(S52:S54) -> 0 | ... JX53: =SUM(EN52:EN54) -> 0
B54: Capitalised interest transfer | C54: =I54/Units_SF_M2 -> 0 | I54: 0 | K54: =IF(ROUND(SUM(L54:EN54),0)=ROUND(I54,0),"","Incomplete") | L54: =IF(L$23="","",0) -> 0 | M54: =IF(M$23="","",0) -> 0 | N54: =IF(N$23="","",0) -> 0 | O54: =IF(O$23="","",0) -> 0 | P54: =IF(P$23="","",0) -> 0 | Q54: =IF(Q$23="","",0) -> 0 | R54: =IF(R$23="","",0) -> 0 | S54: =IF(S$23="","",0) -> 0 | ... EN54: =IF(EN$23="","",0) -> 0 | EP54: =B57 -> 0 | EU54: =SUM(EV54:JX54) -> 4.4885664e+08 | EV54: =L57 -> 93017714 | EW54: =M57 -> 882028.36 | EX54: =N57 -> 1153238.8 | EY54: =O57 -> 1540571.8 | EZ54: =P57 -> 2077208.7 | FA54: =Q57 -> 2798042.2 | FB54: =R57 -> 3736098.9 | FC54: =S57 -> 4917681.3 | ... JX54: =EN57 -> 0
B55: Total financing costs | C55: =SUM(H52:H54) -> 0 | I55: =SUM(I52:I54) -> 0 | K55: =IF(ROUND(SUM(L55:EN55),0)=ROUND(I55,0),"","Incomplete") | L55: =SUM(L52:L54) -> 0 | M55: =SUM(M52:M54) -> 0 | N55: =SUM(N52:N54) -> 0 | O55: =SUM(O52:O54) -> 0 | P55: =SUM(P52:P54) -> 0 | Q55: =SUM(Q52:Q54) -> 0 | R55: =SUM(R52:R54) -> 0 | S55: =SUM(S52:S54) -> 0 | ... EN55: =SUM(EN52:EN54) -> 0 | EP55: CASH FLOW BY SOURCE | EU55: Total | EV55: =EV3 -> 0 | EW55: =EW3 -> 1 | EX55: =EX3 -> 2 | EY55: =EY3 -> 3 | EZ55: =EZ3 -> 4 | FA55: =FA3 -> 5 | FB55: =FB3 -> 6 | FC55: =FC3 -> 7 | ... JX55: =JX3 -> 132
EP56: Equity | EU56: =SUM(EV56:JX56) -> 2.1566292e+08 | EV56: =MIN(EU69,EV52+L53) -> 93017714 | EW56: =MIN(EV69,EW52+M53) -> 882028.36 | EX56: =MIN(EW69,EX52+N53) -> 1153238.8 | EY56: =MIN(EX69,EY52+O53) -> 1540571.8 | EZ56: =MIN(EY69,EZ52+P53) -> 2077208.7 | FA56: =MIN(EZ69,FA52+Q53) -> 2798042.2 | FB56: =MIN(FA69,FB52+R53) -> 3736098.9 | FC56: =MIN(FB69,FC52+S53) -> 4917681.3 | ... JX56: =MIN(JW69,JX52+EN53) -> 0
C57: =MIN(D53,D47,D38,D31) -> 0 | E57: =MAX(E53,E47,E38,E31) -> 36 | F57: =H55+H47+H38+H31 -> 0 | I57: =SUM(I31,I38,I47,I55) -> 4.4885664e+08 | K57: =IF(ROUND(SUM(L57:EN57),0)=ROUND(I57,0),"","Incomplete") | L57: =+L55+L47+L38+L31 -> 93017714 | M57: =+M55+M47+M38+M31 -> 882028.36 | N57: =+N55+N47+N38+N31 -> 1153238.8 | O57: =+O55+O47+O38+O31 -> 1540571.8 | P57: =+P55+P47+P38+P31 -> 2077208.7 | Q57: =+Q55+Q47+Q38+Q31 -> 2798042.2 | R57: =+R55+R47+R38+R31 -> 3736098.9 | S57: =+S55+S47+S38+S31 -> 4917681.3 | ... EN57: =+EN55+EN47+EN38+EN31 -> 0 | EP57: Debt w/o interest | EU57: =EU70 -> 2.3319372e+08 | EV57: =MIN(EU70,EV52+L53-EV56) -> 0 | EW57: =MIN(EV70,EW52+M53-EW56) -> 0 | EX57: =MIN(EW70,EX52+N53-EX56) -> 0 | EY57: =MIN(EX70,EY52+O53-EY56) -> 0 | EZ57: =MIN(EY70,EZ52+P53-EZ56) -> 0 | FA57: =MIN(EZ70,FA52+Q53-FA56) -> 0 | FB57: =MIN(FA70,FB52+R53-FB56) -> 0 | FC57: =MIN(FB70,FC52+S53-FC56) -> 0 | ... JX57: =MIN(JW70,JX52+EN53-JX56) -> 0
EP58: Debt Interest Reserve | EU58: =SUM(EV58:JX58) -> 55420204 | EV58: =EV61-EV62 -> 0 | EW58: =EW61-EW62 -> 0 | EX58: =EX61-EX62 -> 0 | EY58: =EY61-EY62 -> 0 | EZ58: =EZ61-EZ62 -> 0 | FA58: =FA61-FA62 -> 0 | FB58: =FB61-FB62 -> 0 | FC58: =FC61-FC62 -> 0 | ... JX58: =JX61-JX62 -> 0
C59: LTC | D59: FUNDING ORDER | E59: ANNUAL RATE | F59: % OF SOURCES | G59: =H25 -> /RENTABLE M2 | I59: AMOUNT | EP59: Debt Operating Shortfall Reserve | ET59: Error Check | EU59: =SUM(EV59:JX59) -> 0 | EV59: =-MIN(L155,0) -> 0 | EW59: =-MIN(M155,0) -> 0 | EX59: =-MIN(N155,0) -> 0 | EY59: =-MIN(O155,0) -> 0 | EZ59: =-MIN(P155,0) -> 0 | FA59: =-MIN(Q155,0) -> 0 | FB59: =-MIN(R155,0) -> 0 | FC59: =-MIN(S155,0) -> 0 | ... JX59: =-MIN(EN155,0) -> 0
C60: 1 | E60: See Waterfall | F60: =I60/Project_Cost_Total -> 0.48047171 | G60: =I60/Units_SF_M2 -> 2748.3353 | I60: =SUM(L69:EN69) -> 2.1566292e+08 | L60: Funding (Construction Loan vs. Mezzanine Loan) | EP60: Total Cash Flow by Source | ET60: =IF(AND(ROUND(EU60,0)=ROUND(SUM($EV$60:$JX$60),0),ROUND(EU60,0)=ROUND(Project_Cost_Total,0)),"OK","ERR") -> ERR | EU60: =SUM(EU56:EU59) -> 5.0427684e+08 | EV60: =SUM(EV56:EV59) -> 93017714 | EW60: =SUM(EW56:EW59) -> 882028.36 | EX60: =SUM(EX56:EX59) -> 1153238.8 | EY60: =SUM(EY56:EY59) -> 1540571.8 | EZ60: =SUM(EZ56:EZ59) -> 2077208.7 | FA60: =SUM(FA56:FA59) -> 2798042.2 | FB60: =SUM(FB56:FB59) -> 3736098.9 | ... JX60: =SUM(JX56:JX59) -> 0
B61: Construction Debt | C61: ='FUNDING & CAP TABLE'!$I$20 -> 0.5 | D61: 2 | E61: =MAX(EV66:JX66) -> 0.065 | F61: =I61/Project_Cost_Total -> 0.52400396 | H61: =I61/Units_SF_M2 -> 2997.3431 | I61: =SUM(DEBT!F81:DV81,DEBT!F82:DV82) -> 2.3520265e+08 | K61: =B65 -> Construction Loan | L61: =IF($D$65=$D$66,SUM(L72:L74)*$EP$61,SUM(L72:L74)*EV88) -> 0 | M61: =IF($D$65=$D$66,SUM(M72:M74)*$EP$61,SUM(M72:M74)*EW88) -> 0 | N61: =IF($D$65=$D$66,SUM(N72:N74)*$EP$61,SUM(N72:N74)*EX88) -> 0 | O61: =IF($D$65=$D$66,SUM(O72:O74)*$EP$61,SUM(O72:O74)*EY88) -> 0 | P61: =IF($D$65=$D$66,SUM(P72:P74)*$EP$61,SUM(P72:P74)*EZ88) -> 0 | Q61: =IF($D$65=$D$66,SUM(Q72:Q74)*$EP$61,SUM(Q72:Q74)*FA88) -> 0 | R61: =IF($D$65=$D$66,SUM(R72:R74)*$EP$61,SUM(R72:R74)*FB88) -> 0 | S61: =IF($D$65=$D$66,SUM(S72:S74)*$EP$61,SUM(S72:S74)*FC88) -> 0 | ... EN61: =IF($D$65=$D$66,SUM(EN72:EN74)*$EP$61,SUM(EN72:EN74)*JX88) -> 0 | EP61: =C65/Debt_LTC_Target -> 1 | ET61: Gross Construction Interest | EU61: =SUM(EV61:JX61) -> 55420204 | EW61: =IF(Perm_Debt?,(M3<=PermDebt_Fund)*SUM($EV57:EV59)*EW66/12,(M3<=Timing_Analysis_End_Month)*SUM($EV57:EV59)*EW66/12) -> 0 | EX61: =IF(Perm_Debt?,(N3<=PermDebt_Fund)*SUM($EV57:EW59)*EX66/12,(N3<=Timing_Analysis_End_Month)*SUM($EV57:EW59)*EX66/12) -> 0 | EY61: =IF(Perm_Debt?,(O3<=PermDebt_Fund)*SUM($EV57:EX59)*EY66/12,(O3<=Timing_Analysis_End_Month)*SUM($EV57:EX59)*EY66/12) -> 0 | EZ61: =IF(Perm_Debt?,(P3<=PermDebt_Fund)*SUM($EV57:EY59)*EZ66/12,(P3<=Timing_Analysis_End_Month)*SUM($EV57:EY59)*EZ66/12) -> 0 | FA61: =IF(Perm_Debt?,(Q3<=PermDebt_Fund)*SUM($EV57:EZ59)*FA66/12,(Q3<=Timing_Analysis_End_Month)*SUM($EV57:EZ59)*FA66/12) -> 0 | FB61: =IF(Perm_Debt?,(R3<=PermDebt_Fund)*SUM($EV57:FA59)*FB66/12,(R3<=Timing_Analysis_End_Month)*SUM($EV57:FA59)*FB66/12) -> 0 | FC61: =IF(Perm_Debt?,(S3<=PermDebt_Fund)*SUM($EV57:FB59)*FC66/12,(S3<=Timing_Analysis_End_Month)*SUM($EV57:FB59)*FC66/12) -> 0 | FD61: =IF(Perm_Debt?,(T3<=PermDebt_Fund)*SUM($EV57:FC59)*FD66/12,(T3<=Timing_Analysis_End_Month)*SUM($EV57:FC59)*FD66/12) -> 0 | ... JX61: =IF(Perm_Debt?,(EN3<=PermDebt_Fund)*SUM($EV57:JW59)*JX66/12,(EN3<=Timing_Analysis_End_Month)*SUM($EV57:JW59)*JX66/12) -> 0
A62: 1 | B62: Total Sources | F62: =SUM(F60:F61) -> 1.0044757 | H62: =SUM(H60:H61) -> 2997.3431 | I62: =SUM(I60:I61) -> 4.5086557e+08 | K62: =B66 -> Mezzanine Loan | L62: =IF($D$65=$D$66,L61/$EP$61*$EP$62,SUM(L72:L74)-L61) -> 16628131 | M62: =IF($D$65=$D$66,M61/$EP$61*$EP$62,SUM(M72:M74)-M61) -> 952590.63 | N62: =IF($D$65=$D$66,N61/$EP$61*$EP$62,SUM(N72:N74)-N61) -> 1153238.8 | O62: =IF($D$65=$D$66,O61/$EP$61*$EP$62,SUM(O72:O74)-O61) -> 1593255.3 | P62: =IF($D$65=$D$66,P61/$EP$61*$EP$62,SUM(P72:P74)-P61) -> 2151126.3 | Q62: =IF($D$65=$D$66,Q61/$EP$61*$EP$62,SUM(Q72:Q74)-Q61) -> 2898639.8 | R62: =IF($D$65=$D$66,R61/$EP$61*$EP$62,SUM(R72:R74)-R61) -> 3868810.1 | S62: =IF($D$65=$D$66,S61/$EP$61*$EP$62,SUM(S72:S74)-S61) -> 5087252.4 | ... EN62: =IF($D$65=$D$66,EN61/$EP$61*$EP$62,SUM(EN72:EN74)-EN61) -> 0 | EP62: =1-EP61 -> 0 | ET62: Lease-up Income Available to Pay Construction Interest | EU62: =SUM(EV62:JX62) -> 0 | EW62: =MIN(EW61,MAX(M155,0))*$F$52 -> 0 | EX62: =MIN(EX61,MAX(N155,0))*$F$52 -> 0 | EY62: =MIN(EY61,MAX(O155,0))*$F$52 -> 0 | EZ62: =MIN(EZ61,MAX(P155,0))*$F$52 -> 0 | FA62: =MIN(FA61,MAX(Q155,0))*$F$52 -> 0 | FB62: =MIN(FB61,MAX(R155,0))*$F$52 -> 0 | FC62: =MIN(FC61,MAX(S155,0))*$F$52 -> 0 | FD62: =MIN(FD61,MAX(T155,0))*$F$52 -> 0 | ... JX62: =MIN(JX61,MAX(EN155,0))*$F$52 -> 0
B64: Construction Debt | C64: LTC | D64: FUNDING ORDER | E64: ANNUAL RATE | F64: % OF SOURCES | G64: /RENTABLE SF | H64: /UNIT | I64: AMOUNT
B65: Construction Loan | C65: =$C$61 -> 0.5 | D65: One | E65: ='URWLD COMPANY INPUTS'!$F$766 -> 0.065 | F65: =(C65/Debt_LTC_Target)*Debt_LTC_Actual -> 0.52400396 | G65: =I65/Units_SF_M2 -> 2997.3431 | H65: =I65/Units -> 2997.3431 | I65: =I61 -> 2.3520265e+08 | K65: =B65 -> Construction Loan | L65: =IF('URWLD COMPANY INPUTS'!$F$766="","",'URWLD COMPANY INPUTS'!$F$766) -> 0.065 | M65: =IF('URWLD COMPANY INPUTS'!$F$766="","",'URWLD COMPANY INPUTS'!$F$766) -> 0.065 | N65: =IF('URWLD COMPANY INPUTS'!$F$766="","",'URWLD COMPANY INPUTS'!$F$766) -> 0.065 | O65: =IF('URWLD COMPANY INPUTS'!$F$766="","",'URWLD COMPANY INPUTS'!$F$766) -> 0.065 | P65: =IF('URWLD COMPANY INPUTS'!$F$766="","",'URWLD COMPANY INPUTS'!$F$766) -> 0.065 | Q65: =IF('URWLD COMPANY INPUTS'!$F$766="","",'URWLD COMPANY INPUTS'!$F$766) -> 0.065 | R65: =IF('URWLD COMPANY INPUTS'!$F$766="","",'URWLD COMPANY INPUTS'!$F$766) -> 0.065 | S65: =IF('URWLD COMPANY INPUTS'!$F$766="","",'URWLD COMPANY INPUTS'!$F$766) -> 0.065 | ... EN65: =IF('URWLD COMPANY INPUTS'!$F$766="","",'URWLD COMPANY INPUTS'!$F$766) -> 0.065
B66: Mezzanine Loan | C66: =Debt_LTC_Target-C65 -> 0 | D66: Two | E66: 0.15 | F66: =(C66/Debt_LTC_Target)*Debt_LTC_Actual -> 0 | G66: =I66/Units_SF_M2 -> 0 | H66: =I66/Units -> 0 | I66: =0 -> 0 | K66: =B66 -> Mezzanine Loan | L66: =Interest_Mezz_Loan -> 0.15 | M66: =Interest_Mezz_Loan -> 0.15 | N66: =Interest_Mezz_Loan -> 0.15 | O66: =Interest_Mezz_Loan -> 0.15 | P66: =Interest_Mezz_Loan -> 0.15 | Q66: =Interest_Mezz_Loan -> 0.15 | R66: =Interest_Mezz_Loan -> 0.15 | S66: =Interest_Mezz_Loan -> 0.15 | ... EN66: =Interest_Mezz_Loan -> 0.15 | ET66: Blended Interest Rate | EV66: =IFERROR((EV67*EV86+EV68*EV87)/SUM(EV86:EV87),EV67) -> 0.065 | EW66: =IFERROR((EW67*EW86+EW68*EW87)/SUM(EW86:EW87),EW67) -> 0.065 | EX66: =IFERROR((EX67*EX86+EX68*EX87)/SUM(EX86:EX87),EX67) -> 0.065 | EY66: =IFERROR((EY67*EY86+EY68*EY87)/SUM(EY86:EY87),EY67) -> 0.065 | EZ66: =IFERROR((EZ67*EZ86+EZ68*EZ87)/SUM(EZ86:EZ87),EZ67) -> 0.065 | FA66: =IFERROR((FA67*FA86+FA68*FA87)/SUM(FA86:FA87),FA67) -> 0.065 | FB66: =IFERROR((FB67*FB86+FB68*FB87)/SUM(FB86:FB87),FB67) -> 0.065 | FC66: =IFERROR((FC67*FC86+FC68*FC87)/SUM(FC86:FC87),FC67) -> 0.065 | ... JX66: =IFERROR((JX67*JX86+JX68*JX87)/SUM(JX86:JX87),JX67) -> 0.065
D67: Fixed | E67: Variable | ET67: Construction Loan Interest Rate | EV67: =IF(Fixed_Variable=1,L65,Interest_Const_Loan) -> 0.065 | EW67: =IF(Fixed_Variable=1,M65,Interest_Const_Loan) -> 0.065 | EX67: =IF(Fixed_Variable=1,N65,Interest_Const_Loan) -> 0.065 | EY67: =IF(Fixed_Variable=1,O65,Interest_Const_Loan) -> 0.065 | EZ67: =IF(Fixed_Variable=1,P65,Interest_Const_Loan) -> 0.065 | FA67: =IF(Fixed_Variable=1,Q65,Interest_Const_Loan) -> 0.065 | FB67: =IF(Fixed_Variable=1,R65,Interest_Const_Loan) -> 0.065 | FC67: =IF(Fixed_Variable=1,S65,Interest_Const_Loan) -> 0.065 | ... JX67: =IF(Fixed_Variable=1,EN65,Interest_Const_Loan) -> 0.065
B68: CASH FLOW OF SOURCES | F68: % OF SOURCES | H68: =+H59 -> 0 | I68: AMOUNT | L68: =L3 -> 0 | M68: =M3 -> 1 | N68: =N3 -> 2 | O68: =O3 -> 3 | P68: =P3 -> 4 | Q68: =Q3 -> 5 | R68: =R3 -> 6 | S68: =S3 -> 7 | ... EN68: =EN3 -> 132 | EP68: BALANCE TRACKING | ET68: Mezzanine Loan Interest Rate | EV68: =IF(Fixed_Variable=1,L66,Interest_Mezz_Loan) -> 0.15 | EW68: =IF(Fixed_Variable=1,M66,Interest_Mezz_Loan) -> 0.15 | EX68: =IF(Fixed_Variable=1,N66,Interest_Mezz_Loan) -> 0.15 | EY68: =IF(Fixed_Variable=1,O66,Interest_Mezz_Loan) -> 0.15 | EZ68: =IF(Fixed_Variable=1,P66,Interest_Mezz_Loan) -> 0.15 | FA68: =IF(Fixed_Variable=1,Q66,Interest_Mezz_Loan) -> 0.15 | FB68: =IF(Fixed_Variable=1,R66,Interest_Mezz_Loan) -> 0.15 | FC68: =IF(Fixed_Variable=1,S66,Interest_Mezz_Loan) -> 0.15 | ... JX68: =IF(Fixed_Variable=1,EN66,Interest_Mezz_Loan) -> 0.15
B69: Total Equity | F69: =I69/Project_Cost_Total -> 0.48047171 | H69: =I69/Units_SF_M2 -> 2748.3353 | I69: =SUM(L69:EN69) -> 2.1566292e+08 | L69: =MAX(0,SUM(L196,L52:L54)-L75) -> 76389583 | M69: =MAX(0,SUM(M196,M52:M54)-M75) -> 0 | N69: =MAX(0,SUM(N196,N52:N54)-N75) -> 0 | O69: =MAX(0,SUM(O196,O52:O54)-O75) -> 0 | P69: =MAX(0,SUM(P196,P52:P54)-P75) -> 0 | Q69: =MAX(0,SUM(Q196,Q52:Q54)-Q75) -> 0 | R69: =MAX(0,SUM(R196,R52:R54)-R75) -> 0 | S69: =MAX(0,SUM(S196,S52:S54)-S75) -> 0 | ... EN69: =MAX(0,SUM(EN196,EN52:EN54)-EN75) -> 0 | EP69: Equity | EU69: =I60 -> 2.1566292e+08 | EV69: =EU69-EV56 -> 1.226452e+08 | EW69: =EV69-EW56 -> 1.2176317e+08 | EX69: =EW69-EX56 -> 1.2060994e+08 | EY69: =EX69-EY56 -> 1.1906936e+08 | EZ69: =EY69-EZ56 -> 1.1699216e+08 | FA69: =EZ69-FA56 -> 1.1419411e+08 | FB69: =FA69-FB56 -> 1.1045801e+08 | FC69: =FB69-FC56 -> 1.0554033e+08 | ... JX69: =JW69-JX56 -> 0
EP70: Debt w/o interest | ET70: Available | EU70: =EU52+I53-EU56 -> 2.3319372e+08 | EV70: =EU70-EV57 -> 2.3319372e+08 | EW70: =EV70-EW57 -> 2.3319372e+08 | EX70: =EW70-EX57 -> 2.3319372e+08 | EY70: =EX70-EY57 -> 2.3319372e+08 | EZ70: =EY70-EZ57 -> 2.3319372e+08 | FA70: =EZ70-FA57 -> 2.3319372e+08 | FB70: =FA70-FB57 -> 2.3319372e+08 | FC70: =FB70-FC57 -> 2.3319372e+08 | ... JX70: =JW70-JX57 -> 3.8766302e-08
B71: Construction Debt | EP71: Debt interest reserve | ET71: Available | EU71: =EU58 -> 55420204 | EV71: =EU71-EV58 -> 55420204 | EW71: =EV71-EW58 -> 55420204 | EX71: =EW71-EX58 -> 55420204 | EY71: =EX71-EY58 -> 55420204 | EZ71: =EY71-EZ58 -> 55420204 | FA71: =EZ71-FA58 -> 55420204 | FB71: =FA71-FB58 -> 55420204 | FC71: =FB71-FC58 -> 55420204 | ... JX71: =JW71-JX58 -> 6.9849193e-09
B72: Construction Debt before Reserves | F72: =I72/Project_Cost_Total -> 0.52400396 | H72: =I72/Units_SF_M2 -> 2997.3431 | I72: =SUM(L72:EN72) -> 2.3520265e+08 | L72: =IF(COUNTIF(DEBT!$F$64:$DV$64,L$24)=0,0,INDEX(DEBT!$F$81:$DV$81,1,MATCH(L$24,DEBT!$F$64:$DV$64,0))) -> 16628131 | M72: =IF(COUNTIF(DEBT!$F$64:$DV$64,M$24)=0,0,INDEX(DEBT!$F$81:$DV$81,1,MATCH(M$24,DEBT!$F$64:$DV$64,0))) -> 952590.63 | N72: =IF(COUNTIF(DEBT!$F$64:$DV$64,N$24)=0,0,INDEX(DEBT!$F$81:$DV$81,1,MATCH(N$24,DEBT!$F$64:$DV$64,0))) -> 1153238.8 | O72: =IF(COUNTIF(DEBT!$F$64:$DV$64,O$24)=0,0,INDEX(DEBT!$F$81:$DV$81,1,MATCH(O$24,DEBT!$F$64:$DV$64,0))) -> 1593255.3 | P72: =IF(COUNTIF(DEBT!$F$64:$DV$64,P$24)=0,0,INDEX(DEBT!$F$81:$DV$81,1,MATCH(P$24,DEBT!$F$64:$DV$64,0))) -> 2151126.3 | Q72: =IF(COUNTIF(DEBT!$F$64:$DV$64,Q$24)=0,0,INDEX(DEBT!$F$81:$DV$81,1,MATCH(Q$24,DEBT!$F$64:$DV$64,0))) -> 2898639.8 | R72: =IF(COUNTIF(DEBT!$F$64:$DV$64,R$24)=0,0,INDEX(DEBT!$F$81:$DV$81,1,MATCH(R$24,DEBT!$F$64:$DV$64,0))) -> 3868810.1 | S72: =IF(COUNTIF(DEBT!$F$64:$DV$64,S$24)=0,0,INDEX(DEBT!$F$81:$DV$81,1,MATCH(S$24,DEBT!$F$64:$DV$64,0))) -> 5087252.4 | ... EN72: =IF(COUNTIF(DEBT!$F$64:$DV$64,EN$24)=0,0,INDEX(DEBT!$F$81:$DV$81,1,MATCH(EN$24,DEBT!$F$64:$DV$64,0))) -> 0 | EP72: Debt with Operating Shortfall | ES72: Error Check | ET72: Available | EU72: =EU59 -> 0 | EV72: =EU72-EV59 -> 0 | EW72: =EV72-EW59 -> 0 | EX72: =EW72-EX59 -> 0 | EY72: =EX72-EY59 -> 0 | EZ72: =EY72-EZ59 -> 0 | FA72: =EZ72-FA59 -> 0 | FB72: =FA72-FB59 -> 0 | FC72: =FB72-FC59 -> 0 | ... JX72: =JW72-JX59 -> 0
B73: Interest Reserve | F73: =I73/Project_Cost_Total -> 0 | H73: =I73/Units_SF_M2 -> 0 | I73: =SUM(L73:EN73) -> 0 | L73: =IF(COUNTIF(DEBT!$F$64:$DV$64,L$24)=0,0,INDEX(DEBT!$F$82:$DV$82,1,MATCH(L$24,DEBT!$F$64:$DV$64,0))) -> 0 | M73: =IF(COUNTIF(DEBT!$F$64:$DV$64,M$24)=0,0,INDEX(DEBT!$F$82:$DV$82,1,MATCH(M$24,DEBT!$F$64:$DV$64,0))) -> 0 | N73: =IF(COUNTIF(DEBT!$F$64:$DV$64,N$24)=0,0,INDEX(DEBT!$F$82:$DV$82,1,MATCH(N$24,DEBT!$F$64:$DV$64,0))) -> 0 | O73: =IF(COUNTIF(DEBT!$F$64:$DV$64,O$24)=0,0,INDEX(DEBT!$F$82:$DV$82,1,MATCH(O$24,DEBT!$F$64:$DV$64,0))) -> 0 | P73: =IF(COUNTIF(DEBT!$F$64:$DV$64,P$24)=0,0,INDEX(DEBT!$F$82:$DV$82,1,MATCH(P$24,DEBT!$F$64:$DV$64,0))) -> 0 | Q73: =IF(COUNTIF(DEBT!$F$64:$DV$64,Q$24)=0,0,INDEX(DEBT!$F$82:$DV$82,1,MATCH(Q$24,DEBT!$F$64:$DV$64,0))) -> 0 | R73: =IF(COUNTIF(DEBT!$F$64:$DV$64,R$24)=0,0,INDEX(DEBT!$F$82:$DV$82,1,MATCH(R$24,DEBT!$F$64:$DV$64,0))) -> 0 | S73: =IF(COUNTIF(DEBT!$F$64:$DV$64,S$24)=0,0,INDEX(DEBT!$F$82:$DV$82,1,MATCH(S$24,DEBT!$F$64:$DV$64,0))) -> 0 | ... EN73: =IF(COUNTIF(DEBT!$F$64:$DV$64,EN$24)=0,0,INDEX(DEBT!$F$82:$DV$82,1,MATCH(EN$24,DEBT!$F$64:$DV$64,0))) -> 0 | EP73: Debt w/o interest | ES73: =IF(MAX(EV73:JX73)=SUM(EV57:JX57),"OK","ERROR") -> OK | ET73: Outstanding | EU73: 0 | EV73: =(EV$55<=Timing_Analysis_End_Month)*(EU73+EV57) -> 0 | EW73: =(EW$55<=Timing_Analysis_End_Month)*(EV73+EW57) -> 0 | EX73: =(EX$55<=Timing_Analysis_End_Month)*(EW73+EX57) -> 0 | EY73: =(EY$55<=Timing_Analysis_End_Month)*(EX73+EY57) -> 0 | EZ73: =(EZ$55<=Timing_Analysis_End_Month)*(EY73+EZ57) -> 0 | FA73: =(FA$55<=Timing_Analysis_End_Month)*(EZ73+FA57) -> 0 | FB73: =(FB$55<=Timing_Analysis_End_Month)*(FA73+FB57) -> 0 | FC73: =(FC$55<=Timing_Analysis_End_Month)*(FB73+FC57) -> 0 | ... JX73: =(JX$55<=Timing_Analysis_End_Month)*(JW73+JX57) -> 0
B74: Operating Shortfall Reserve | E74: PAYOFF MONTH | F74: =I74/Project_Cost_Total -> 0 | H74: =I74/Units_SF_M2 -> 0 | I74: =SUM(L74:EN74) -> 0 | L74: 0 | M74: 0 | N74: 0 | O74: 0 | P74: 0 | Q74: 0 | R74: 0 | S74: 0 | T74: 0 | U74: 0 | V74: 0 | W74: 0 | X74: 0 | Y74: 0 | Z74: 0 | AA74: 0 | AB74: 0 | AC74: 0 | AD74: 0 | AE74: 0 | AF74: 0 | AG74: 0 | AH74: 0 | AI74: 0 | AJ74: 0 | AK74: 0 | AL74: 0 | AM74: 0 | AN74: 0 | AO74: 0 | AP74: 0 | AQ74: 0 | AR74: 0 | AS74: 0 | AT74: 0 | AU74: 0 | AV74: 0 | AW74: 0 | AX74: 0 | AY74: 0 | AZ74: 0 | BA74: 0 | BB74: 0 | BC74: 0 | BD74: 0 | BE74: 0 | BF74: 0 | BG74: 0 | BH74: 0 | BI74: 0 | BJ74: 0 | BK74: 0 | BL74: 0 | BM74: 0 | BN74: 0 | BO74: 0 | BP74: 0 | BQ74: 0 | BR74: 0 | BS74: 0 | BT74: 0 | BU74: 0 | BV74: 0 | BW74: 0 | BX74: 0 | BY74: 0 | BZ74: 0 | CA74: 0 | CB74: 0 | CC74: 0 | CD74: 0 | CE74: 0 | CF74: 0 | CG74: 0 | CH74: 0 | CI74: 0 | CJ74: 0 | CK74: 0 | CL74: 0 | CM74: 0 | CN74: 0 | CO74: 0 | CP74: 0 | CQ74: 0 | CR74: 0 | CS74: 0 | CT74: 0 | CU74: 0 | CV74: 0 | CW74: 0 | CX74: 0 | CY74: 0 | CZ74: 0 | DA74: 0 | DB74: 0 | DC74: 0 | DD74: 0 | DE74: 0 | DF74: 0 | DG74: 0 | DH74: 0 | DI74: 0 | DJ74: 0 | DK74: 0 | DL74: 0 | DM74: 0 | DN74: 0 | DO74: 0 | DP74: 0 | DQ74: 0 | DR74: 0 | DS74: 0 | DT74: 0 | DU74: 0 | DV74: 0 | DW74: 0 | DX74: 0 | DY74: 0 | DZ74: 0 | EA74: 0 | EB74: 0 | EC74: 0 | ED74: 0 | EE74: 0 | EF74: 0 | EG74: 0 | EH74: 0 | EI74: 0 | EJ74: 0 | EK74: 0 | EL74: 0 | EM74: 0 | EN74: 0 | EP74: Debt interest reserve | ES74: =IF(MAX(EV74:JX74)=SUM(EV58:JX58),"OK","ERROR") -> OK | ET74: Outstanding | EU74: 0 | EV74: =+EU74+EV58 -> 0 | EW74: =+EV74+EW58 -> 0 | EX74: =+EW74+EX58 -> 0 | EY74: =+EX74+EY58 -> 0 | EZ74: =+EY74+EZ58 -> 0 | FA74: =+EZ74+FA58 -> 0 | FB74: =+FA74+FB58 -> 0 | FC74: =+FB74+FC58 -> 0 | ... JX74: =+JW74+JX58 -> 55420204
B75: Total Construction Debt | E75: =IF(Perm_Debt?=0,Timing_Reversion_Month,PermDebt_Fund) -> 61 | F75: =I75/Project_Cost_Total -> 0.52400396 | H75: =SUM(H72:H74) -> 2997.3431 | I75: =SUM(I72:I74) -> 2.3520265e+08 | K75: =IF(AND(ROUND(SUM(L75:EN75),0)=ROUND(Debt_Total,0),ROUND(SUM(L61:EN62),0)=ROUND(SUM(I65:I66),0)),"","ERROR") | L75: =SUM(L72:L74) -> 16628131 | M75: =SUM(M72:M74) -> 952590.63 | N75: =SUM(N72:N74) -> 1153238.8 | O75: =SUM(O72:O74) -> 1593255.3 | P75: =SUM(P72:P74) -> 2151126.3 | Q75: =SUM(Q72:Q74) -> 2898639.8 | R75: =SUM(R72:R74) -> 3868810.1 | S75: =SUM(S72:S74) -> 5087252.4 | ... EN75: =SUM(EN72:EN74) -> 0 | EP75: Debt with Operating Shortfall | ES75: =IF(MAX(EV75:JX75)=SUM(EV59:JX59),"OK","ERROR") -> OK | ET75: Outstanding | EU75: 0 | EV75: =+EU75+EV59 -> 0 | EW75: =+EV75+EW59 -> 0 | EX75: =+EW75+EX59 -> 0 | EY75: =+EX75+EY59 -> 0 | EZ75: =+EY75+EZ59 -> 0 | FA75: =+EZ75+FA59 -> 0 | FB75: =+FA75+FB59 -> 0 | FC75: =+FB75+FC59 -> 0 | ... JX75: =+JW75+JX59 -> 0
B77: Total Sources | F77: =I77/Project_Cost_Total -> 1.0044757 | H77: =H75+H69 -> 5745.6784 | I77: =I75+I69 -> 4.5086557e+08 | L77: =+L75+L69 -> 93017714 | M77: =+M75+M69 -> 952590.63 | N77: =+N75+N69 -> 1153238.8 | O77: =+O75+O69 -> 1593255.3 | P77: =+P75+P69 -> 2151126.3 | Q77: =+Q75+Q69 -> 2898639.8 | R77: =+R75+R69 -> 3868810.1 | S77: =+S75+S69 -> 5087252.4 | ... EN77: =+EN75+EN69 -> 0 | EP77: First Loan Draw | EQ77: =MAX(EV77:JX77) -> 16 | EV77: =AND(EV73>0,SUM($EU$77:EU77)=0)*EV51 -> 0 | EW77: =AND(EW73>0,SUM($EU$77:EV77)=0)*EW51 -> 0 | EX77: =AND(EX73>0,SUM($EU$77:EW77)=0)*EX51 -> 0 | EY77: =AND(EY73>0,SUM($EU$77:EX77)=0)*EY51 -> 0 | EZ77: =AND(EZ73>0,SUM($EU$77:EY77)=0)*EZ51 -> 0 | FA77: =AND(FA73>0,SUM($EU$77:EZ77)=0)*FA51 -> 0 | FB77: =AND(FB73>0,SUM($EU$77:FA77)=0)*FB51 -> 0 | FC77: =AND(FC73>0,SUM($EU$77:FB77)=0)*FC51 -> 0 | ... JX77: =AND(JX73>0,SUM($EU$77:JW77)=0)*JX51 -> 0
B78: =IF(Perm_Debt?=0,"PERMANENT DEBT - NOT IN USE","PERMANENT DEBT - ACTIVE") -> PERMANENT DEBT - NOT IN USE | H78: No Perm. Debt | I78: Perm. Debt
A79: 0
C80: % of Stab. Value (LTV) | D80: % OF COST | E80: ANNUAL RATE | F80: INTEREST-ONLY? | G80: AMORT. | H80: PAYMENT | I80: AMOUNT
B81: Permanent Debt | C81: =+I81/Valuation_Trended -> 0.3495615 | D81: =+I81/Project_Cost_Total -> 0.52929693 | E81: ='URWLD COMPANY INPUTS'!$F$766 -> 0.065 | F81: =IF('URWLD COMPANY INPUTS'!$F$770="","",IF('URWLD COMPANY INPUTS'!$F$770="Interest Only","Yes","No")) -> Yes | G81: 30 | H81: =IF(F81="Yes",I81*E81,PMT(E81/12,G81*12,-I81)*12) -> 15442598 | I81: =+I75/(1-H82) -> 2.3757844e+08 | L81: =+L3 -> 0 | M81: =+M3 -> 1 | N81: =+N3 -> 2 | O81: =+O3 -> 3 | P81: =+P3 -> 4 | Q81: =+Q3 -> 5 | R81: =+R3 -> 6 | S81: =+S3 -> 7 | ... EN81: =+EN3 -> 132
B82: Loan Funding | C82: =Stabilization_1st_Month -> 49 | G82: Loan Fees + Closing Costs | H82: ='DATA MAP'!$E$84 -> 0.01 | I82: =-H82*I81 -> -2375784.4 | L82: =(PermDebt_Fund=L3)*Perm_Debt?*$I81*(1-$H$82) -> 0 | M82: =(PermDebt_Fund=M3)*Perm_Debt?*$I81*(1-$H$82) -> 0 | N82: =(PermDebt_Fund=N3)*Perm_Debt?*$I81*(1-$H$82) -> 0 | O82: =(PermDebt_Fund=O3)*Perm_Debt?*$I81*(1-$H$82) -> 0 | P82: =(PermDebt_Fund=P3)*Perm_Debt?*$I81*(1-$H$82) -> 0 | Q82: =(PermDebt_Fund=Q3)*Perm_Debt?*$I81*(1-$H$82) -> 0 | R82: =(PermDebt_Fund=R3)*Perm_Debt?*$I81*(1-$H$82) -> 0 | S82: =(PermDebt_Fund=S3)*Perm_Debt?*$I81*(1-$H$82) -> 0 | ... EN82: =(PermDebt_Fund=EN3)*Perm_Debt?*$I81*(1-$H$82) -> 0
B83: Loan Payoff | C83: =Timing_Reversion_Month -> 61 | G83: ="Debt Service Coverage Ratio (Month "&PermDebt_Fund+1&"):" -> Debt Service Coverage Ratio (Month 50): | H83: =IF(Perm_Debt?=0,"",SUM(INDEX($M$140:$EN$140,1,PermDebt_Fund+1):INDEX($M$140:$EN$140,1,PermDebt_Fund+12))/H81) | I83: =IF(F81="No",PV(E81/12,G81*12-(PermDebt_Payoff-PermDebt_Fund),H81/12),-I81) -> -2.3757844e+08 | L83: =(PermDebt_Payoff=L3)*Perm_Debt?*$I83 -> 0 | M83: =(PermDebt_Payoff=M3)*Perm_Debt?*$I83 -> 0 | N83: =(PermDebt_Payoff=N3)*Perm_Debt?*$I83 -> 0 | O83: =(PermDebt_Payoff=O3)*Perm_Debt?*$I83 -> 0 | P83: =(PermDebt_Payoff=P3)*Perm_Debt?*$I83 -> 0 | Q83: =(PermDebt_Payoff=Q3)*Perm_Debt?*$I83 -> 0 | R83: =(PermDebt_Payoff=R3)*Perm_Debt?*$I83 -> 0 | S83: =(PermDebt_Payoff=S3)*Perm_Debt?*$I83 -> 0 | ... EN83: =(PermDebt_Payoff=EN3)*Perm_Debt?*$I83 -> 0
G84: ="Debt Yield (Month "&PermDebt_Fund+1&"):" -> Debt Yield (Month 50): | H84: =IF(Perm_Debt?=0,"",SUM(INDEX($M$140:$EN$140,1,PermDebt_Fund+1):INDEX($M$140:$EN$140,1,PermDebt_Fund+12))/I81)
ES85: Error Check | ET85: Share | EU85: Amount w/o Int
B86: OPERATING PERIOD CASH FLOWS | K86: Analysis Month | L86: =L23 -> 0 | M86: =M23 -> 1 | N86: =N23 -> 2 | O86: =O23 -> 3 | P86: =P23 -> 4 | Q86: =Q23 -> 5 | R86: =R23 -> 6 | S86: =S23 -> 7 | ... EN86: =EN23 -> 132 | EP86: Construction Loan Balance (w/o interest) | ES86: =IF(ROUND(MAX(EV86:JX86),0)=ROUND(EU86,0),"OK","ERROR") -> ERROR | ET86: =+C65/Debt_LTC_Target -> 1 | EU86: =+$I$72*ET86 -> 2.3520265e+08 | EV86: =MIN(EV73,$EU$86) -> 0 | EW86: =MIN(EW73,$EU$86) -> 0 | EX86: =MIN(EX73,$EU$86) -> 0 | EY86: =MIN(EY73,$EU$86) -> 0 | EZ86: =MIN(EZ73,$EU$86) -> 0 | FA86: =MIN(FA73,$EU$86) -> 0 | FB86: =MIN(FB73,$EU$86) -> 0 | FC86: =MIN(FC73,$EU$86) -> 0 | ... JX86: =MIN(JX73,$EU$86) -> 0
B87: RETAIL INCOME | F87: PROPERTY TAX PHASE IN (% OF FULL TAX BY OPERATING YEAR) | K87: Analysis Date | L87: =L24 -> 46203 | M87: =M24 -> 46234 | N87: =N24 -> 46265 | O87: =O24 -> 46295 | P87: =P24 -> 46326 | Q87: =Q24 -> 46356 | R87: =R24 -> 46387 | S87: =S24 -> 46418 | ... EN87: =EN24 -> 50221 | EP87: Mezzanine Loan Balance (w/o interest) | ES87: =IF(ROUND(MAX(EV87:JX87),0)=ROUND(EU87,0),"OK","ERROR") -> OK | ET87: =1-ET86 -> 0 | EU87: =+$I$72*ET87 -> 0 | EV87: =EV73-EV86 -> 0 | EW87: =EW73-EW86 -> 0 | EX87: =EX73-EX86 -> 0 | EY87: =EY73-EY86 -> 0 | EZ87: =EZ73-EZ86 -> 0 | FA87: =FA73-FA86 -> 0 | FB87: =FB73-FB86 -> 0 | FC87: =FC73-FC86 -> 0 | ... JX87: =JX73-JX86 -> 0
A88: 0 | B88: Operation Begin Month | D88: =(VALUE(RIGHT('URWLD COMPANY INPUTS'!$F$47,4))-VALUE(RIGHT('URWLD COMPANY INPUTS'!$F$45,4)))*12+(VALUE(MID('URWLD COMPANY INPUTS'!$F$47,2,1))-VALUE(MID('URWLD COMPANY INPUTS'!$F$45,2,1)))*3+1 -> 37 | F88: EOY 1 of Op | G88: 0.5 | H88: EOY 3 of Op | I88: 1 | K88: Schedule | L88: =IF(L86<Timing_Operation_Begin_Month,"Const.",IF(L89<1,"Lease-Up","Stabilized")) -> Const. | M88: =IF(M86<Timing_Operation_Begin_Month,"Const.",IF(M89<1,"Lease-Up","Stabilized")) -> Const. | N88: =IF(N86<Timing_Operation_Begin_Month,"Const.",IF(N89<1,"Lease-Up","Stabilized")) -> Const. | O88: =IF(O86<Timing_Operation_Begin_Month,"Const.",IF(O89<1,"Lease-Up","Stabilized")) -> Const. | P88: =IF(P86<Timing_Operation_Begin_Month,"Const.",IF(P89<1,"Lease-Up","Stabilized")) -> Const. | Q88: =IF(Q86<Timing_Operation_Begin_Month,"Const.",IF(Q89<1,"Lease-Up","Stabilized")) -> Const. | R88: =IF(R86<Timing_Operation_Begin_Month,"Const.",IF(R89<1,"Lease-Up","Stabilized")) -> Const. | S88: =IF(S86<Timing_Operation_Begin_Month,"Const.",IF(S89<1,"Lease-Up","Stabilized")) -> Const. | ... EN88: =IF(EN86<Timing_Operation_Begin_Month,"Const.",IF(EN89<1,"Lease-Up","Stabilized")) -> Stabilized | EP88: Share of Required Debt Funding | EV88: =IFERROR(EV86/EV57,0) -> 0 | EW88: =IFERROR((EW86-EV86)/EW57,0) -> 0 | EX88: =IFERROR((EX86-EW86)/EX57,0) -> 0 | EY88: =IFERROR((EY86-EX86)/EY57,0) -> 0 | EZ88: =IFERROR((EZ86-EY86)/EZ57,0) -> 0 | FA88: =IFERROR((FA86-EZ86)/FA57,0) -> 0 | FB88: =IFERROR((FB86-FA86)/FB57,0) -> 0 | FC88: =IFERROR((FC86-FB86)/FC57,0) -> 0 | FD88: =IFERROR((FD86-FC86)/FD57,0) -> 0 | ... JX88: =IFERROR((JX86-JW86)/JX57,0) -> 0
B89: 1st Stabilized Month | D89: =$D$88+12 -> 49 | F89: EOY 2 of Op | G89: 0.75 | H89: EOY 4 of Op | I89: 1 | K89: Leased % | L89: =IF(L$86<Timing_Operation_Begin_Month,0,MIN(1,MAX(0,(L$86-Timing_Operation_Begin_Month)/MAX(1,Stabilization_1st_Month-Timing_Operation_Begin_Month)))) -> 0 | M89: =IF(M$86<Timing_Operation_Begin_Month,0,MIN(1,MAX(0,(M$86-Timing_Operation_Begin_Month)/MAX(1,Stabilization_1st_Month-Timing_Operation_Begin_Month)))) -> 0 | N89: =IF(N$86<Timing_Operation_Begin_Month,0,MIN(1,MAX(0,(N$86-Timing_Operation_Begin_Month)/MAX(1,Stabilization_1st_Month-Timing_Operation_Begin_Month)))) -> 0 | O89: =IF(O$86<Timing_Operation_Begin_Month,0,MIN(1,MAX(0,(O$86-Timing_Operation_Begin_Month)/MAX(1,Stabilization_1st_Month-Timing_Operation_Begin_Month)))) -> 0 | P89: =IF(P$86<Timing_Operation_Begin_Month,0,MIN(1,MAX(0,(P$86-Timing_Operation_Begin_Month)/MAX(1,Stabilization_1st_Month-Timing_Operation_Begin_Month)))) -> 0 | Q89: =IF(Q$86<Timing_Operation_Begin_Month,0,MIN(1,MAX(0,(Q$86-Timing_Operation_Begin_Month)/MAX(1,Stabilization_1st_Month-Timing_Operation_Begin_Month)))) -> 0 | R89: =IF(R$86<Timing_Operation_Begin_Month,0,MIN(1,MAX(0,(R$86-Timing_Operation_Begin_Month)/MAX(1,Stabilization_1st_Month-Timing_Operation_Begin_Month)))) -> 0 | S89: =IF(S$86<Timing_Operation_Begin_Month,0,MIN(1,MAX(0,(S$86-Timing_Operation_Begin_Month)/MAX(1,Stabilization_1st_Month-Timing_Operation_Begin_Month)))) -> 0 | ... EN89: =IF(EN$86<Timing_Operation_Begin_Month,0,MIN(1,MAX(0,(EN$86-Timing_Operation_Begin_Month)/MAX(1,Stabilization_1st_Month-Timing_Operation_Begin_Month)))) -> 1
B91: RETAIL BASE RENTAL INCOME | I91: =COUNTA(I93:I104) -> 12 | K91: Operation Mo | L91: =MAX(L3-Timing_Operation_Begin_Month+1,0) -> 0 | M91: =MAX(M3-Timing_Operation_Begin_Month+1,0) -> 0 | N91: =MAX(N3-Timing_Operation_Begin_Month+1,0) -> 0 | O91: =MAX(O3-Timing_Operation_Begin_Month+1,0) -> 0 | P91: =MAX(P3-Timing_Operation_Begin_Month+1,0) -> 0 | Q91: =MAX(Q3-Timing_Operation_Begin_Month+1,0) -> 0 | R91: =MAX(R3-Timing_Operation_Begin_Month+1,0) -> 0 | S91: =MAX(S3-Timing_Operation_Begin_Month+1,0) -> 0 | ... EN91: =MAX(EN3-Timing_Operation_Begin_Month+1,0) -> 96
B92: SUITE | C92: TENANT | D92: LEASE START | E92: =Unit_Type -> M2 | F92: RENT START | G92: RENT GROWTH % | H92: ="RENT/"&Unit_Type&"/YR" -> RENT/M2/YR | I92: ANNUAL RENT (YR 1) | K92: RENT STEPS | EP92: OCCUPANCY | EQ92: SF | ER92: LEASE START | EU92: % | JZ92: RENT | KA92: =I92 -> ANNUAL RENT (YR 1) | KB92: =F92 -> RENT START | KC92: =G92 -> RENT GROWTH % | KD92: =K92 -> RENT STEPS | KE92: Frequency | KG92: =KG3 -> 1 | KH92: =KH3 -> 2 | KI92: =KI3 -> 3 | KJ92: =KJ3 -> 4 | KK92: =KK3 -> 5 | KL92: =KL3 -> 6 | KM92: =KM3 -> 7 | KN92: =KN3 -> 8 | ... PH92: =PH3 -> 132
B93: URWLD | C93: URWLD | D93: 19 | E93: ='URWLD COMPANY INPUTS'!$F$134 -> 21500 | F93: =D93+3 -> 22 | G93: =IF('INPUT REGISTER'!$F$223="","",'INPUT REGISTER'!$F$223) -> 0.035 | H93: ='INPUT REGISTER'!$F$672 -> 400 | I93: =IF(OR(E93="",H93=""),0,E93*H93) -> 8600000 | K93: Annual | L93: =IF(OR(L$3<$F93,$E93="",$H93=""),0,$E93*$H93/12*(1+$G93)^INT(MAX(0,L$3-$F93)/12)) -> 0 | M93: =IF(OR(M$3<$F93,$E93="",$H93=""),0,$E93*$H93/12*(1+$G93)^INT(MAX(0,M$3-$F93)/12)) -> 0 | N93: =IF(OR(N$3<$F93,$E93="",$H93=""),0,$E93*$H93/12*(1+$G93)^INT(MAX(0,N$3-$F93)/12)) -> 0 | O93: =IF(OR(O$3<$F93,$E93="",$H93=""),0,$E93*$H93/12*(1+$G93)^INT(MAX(0,O$3-$F93)/12)) -> 0 | P93: =IF(OR(P$3<$F93,$E93="",$H93=""),0,$E93*$H93/12*(1+$G93)^INT(MAX(0,P$3-$F93)/12)) -> 0 | Q93: =IF(OR(Q$3<$F93,$E93="",$H93=""),0,$E93*$H93/12*(1+$G93)^INT(MAX(0,Q$3-$F93)/12)) -> 0 | R93: =IF(OR(R$3<$F93,$E93="",$H93=""),0,$E93*$H93/12*(1+$G93)^INT(MAX(0,R$3-$F93)/12)) -> 0 | S93: =IF(OR(S$3<$F93,$E93="",$H93=""),0,$E93*$H93/12*(1+$G93)^INT(MAX(0,S$3-$F93)/12)) -> 0 | ... EN93: =IF(OR(EN$3<$F93,$E93="",$H93=""),0,$E93*$H93/12*(1+$G93)^INT(MAX(0,EN$3-$F93)/12)) -> 976743.1 | EP93: =$B93 -> URWLD | EQ93: =N($E93) -> 21500 | ER93: =$D93 -> 19 | EV93: =(EV$3>=$ER93)*$EQ93 -> 0 | EW93: =(EW$3>=$ER93)*$EQ93 -> 0 | EX93: =(EX$3>=$ER93)*$EQ93 -> 0 | EY93: =(EY$3>=$ER93)*$EQ93 -> 0 | EZ93: =(EZ$3>=$ER93)*$EQ93 -> 0 | FA93: =(FA$3>=$ER93)*$EQ93 -> 0 | FB93: =(FB$3>=$ER93)*$EQ93 -> 0 | FC93: =(FC$3>=$ER93)*$EQ93 -> 0 | ... JX93: =(JX$3>=$ER93)*$EQ93 -> 21500 | JZ93: =$B93 -> URWLD | KA93: =I93 -> 8600000 | KB93: =F93 -> 22 | KC93: =G93 -> 0.035 | KD93: =K93 -> Annual | KE93: =IF(KD93="",1,IFERROR(MAX(1,INDEX(Data!$H$24:$H$33,MATCH(KD93,Data!$G$24:$G$33,0))),1)) -> 1 | KG93: =IF(OR($KA93="",$KB93="",$KE93=""),0,($KB93<=KG$3)*($KA93/12)*(1+$KC93)^(ROUNDUP(MAX(KG$3-$KB93+1,0)/($KE93*12),0)-1)) -> 0 | KH93: =IF(OR($KA93="",$KB93="",$KE93=""),0,($KB93<=KH$3)*($KA93/12)*(1+$KC93)^(ROUNDUP(MAX(KH$3-$KB93+1,0)/($KE93*12),0)-1)) -> 0 | KI93: =IF(OR($KA93="",$KB93="",$KE93=""),0,($KB93<=KI$3)*($KA93/12)*(1+$KC93)^(ROUNDUP(MAX(KI$3-$KB93+1,0)/($KE93*12),0)-1)) -> 0 | KJ93: =IF(OR($KA93="",$KB93="",$KE93=""),0,($KB93<=KJ$3)*($KA93/12)*(1+$KC93)^(ROUNDUP(MAX(KJ$3-$KB93+1,0)/($KE93*12),0)-1)) -> 0 | KK93: =IF(OR($KA93="",$KB93="",$KE93=""),0,($KB93<=KK$3)*($KA93/12)*(1+$KC93)^(ROUNDUP(MAX(KK$3-$KB93+1,0)/($KE93*12),0)-1)) -> 0 | KL93: =IF(OR($KA93="",$KB93="",$KE93=""),0,($KB93<=KL$3)*($KA93/12)*(1+$KC93)^(ROUNDUP(MAX(KL$3-$KB93+1,0)/($KE93*12),0)-1)) -> 0 | KM93: =IF(OR($KA93="",$KB93="",$KE93=""),0,($KB93<=KM$3)*($KA93/12)*(1+$KC93)^(ROUNDUP(MAX(KM$3-$KB93+1,0)/($KE93*12),0)-1)) -> 0 | KN93: =IF(OR($KA93="",$KB93="",$KE93=""),0,($KB93<=KN$3)*($KA93/12)*(1+$KC93)^(ROUNDUP(MAX(KN$3-$KB93+1,0)/($KE93*12),0)-1)) -> 0 | ... PH93: =IF(OR($KA93="",$KB93="",$KE93=""),0,($KB93<=PH$3)*($KA93/12)*(1+$KC93)^(ROUNDUP(MAX(PH$3-$KB93+1,0)/($KE93*12),0)-1)) -> 976743.1
B94: Student Accommodation | C94: Macquarie/IGLU; Brookfield/Journal | D94: 22 | E94: ='URWLD COMPANY INPUTS'!$F$409 -> 20000 | F94: =D94+3 -> 25 | G94: =IF('URWLD COMPANY INPUTS'!$F$113="","",'URWLD COMPANY INPUTS'!$F$113) -> 0.035 | H94: ='INPUT REGISTER'!$F$673 -> 0 | I94: =IF(OR(E94="",H94=""),0,E94*H94) -> 0 | K94: Annual | L94: =IF(OR(L$3<$F94,$E94="",$H94=""),0,$E94*$H94/12*(1+$G94)^INT(MAX(0,L$3-$F94)/12)) -> 0 | M94: =IF(OR(M$3<$F94,$E94="",$H94=""),0,$E94*$H94/12*(1+$G94)^INT(MAX(0,M$3-$F94)/12)) -> 0 | N94: =IF(OR(N$3<$F94,$E94="",$H94=""),0,$E94*$H94/12*(1+$G94)^INT(MAX(0,N$3-$F94)/12)) -> 0 | O94: =IF(OR(O$3<$F94,$E94="",$H94=""),0,$E94*$H94/12*(1+$G94)^INT(MAX(0,O$3-$F94)/12)) -> 0 | P94: =IF(OR(P$3<$F94,$E94="",$H94=""),0,$E94*$H94/12*(1+$G94)^INT(MAX(0,P$3-$F94)/12)) -> 0 | Q94: =IF(OR(Q$3<$F94,$E94="",$H94=""),0,$E94*$H94/12*(1+$G94)^INT(MAX(0,Q$3-$F94)/12)) -> 0 | R94: =IF(OR(R$3<$F94,$E94="",$H94=""),0,$E94*$H94/12*(1+$G94)^INT(MAX(0,R$3-$F94)/12)) -> 0 | S94: =IF(OR(S$3<$F94,$E94="",$H94=""),0,$E94*$H94/12*(1+$G94)^INT(MAX(0,S$3-$F94)/12)) -> 0 | ... EN94: =IF(OR(EN$3<$F94,$E94="",$H94=""),0,$E94*$H94/12*(1+$G94)^INT(MAX(0,EN$3-$F94)/12)) -> 0 | EP94: =$B94 -> Student Accommodation | EQ94: =N($E94) -> 20000 | ER94: =$D94 -> 22 | EV94: =(EV$3>=$ER94)*$EQ94 -> 0 | EW94: =(EW$3>=$ER94)*$EQ94 -> 0 | EX94: =(EX$3>=$ER94)*$EQ94 -> 0 | EY94: =(EY$3>=$ER94)*$EQ94 -> 0 | EZ94: =(EZ$3>=$ER94)*$EQ94 -> 0 | FA94: =(FA$3>=$ER94)*$EQ94 -> 0 | FB94: =(FB$3>=$ER94)*$EQ94 -> 0 | FC94: =(FC$3>=$ER94)*$EQ94 -> 0 | ... JX94: =(JX$3>=$ER94)*$EQ94 -> 20000 | JZ94: =$B94 -> Student Accommodation | KA94: =I94 -> 0 | KB94: =F94 -> 25 | KC94: =G94 -> 0.035 | KD94: =K94 -> Annual | KE94: =IF(KD94="",1,IFERROR(MAX(1,INDEX(Data!$H$24:$H$33,MATCH(KD94,Data!$G$24:$G$33,0))),1)) -> 1 | KG94: =IF(OR($KA94="",$KB94="",$KE94=""),0,($KB94<=KG$3)*($KA94/12)*(1+$KC94)^(ROUNDUP(MAX(KG$3-$KB94+1,0)/($KE94*12),0)-1)) -> 0 | KH94: =IF(OR($KA94="",$KB94="",$KE94=""),0,($KB94<=KH$3)*($KA94/12)*(1+$KC94)^(ROUNDUP(MAX(KH$3-$KB94+1,0)/($KE94*12),0)-1)) -> 0 | KI94: =IF(OR($KA94="",$KB94="",$KE94=""),0,($KB94<=KI$3)*($KA94/12)*(1+$KC94)^(ROUNDUP(MAX(KI$3-$KB94+1,0)/($KE94*12),0)-1)) -> 0 | KJ94: =IF(OR($KA94="",$KB94="",$KE94=""),0,($KB94<=KJ$3)*($KA94/12)*(1+$KC94)^(ROUNDUP(MAX(KJ$3-$KB94+1,0)/($KE94*12),0)-1)) -> 0 | KK94: =IF(OR($KA94="",$KB94="",$KE94=""),0,($KB94<=KK$3)*($KA94/12)*(1+$KC94)^(ROUNDUP(MAX(KK$3-$KB94+1,0)/($KE94*12),0)-1)) -> 0 | KL94: =IF(OR($KA94="",$KB94="",$KE94=""),0,($KB94<=KL$3)*($KA94/12)*(1+$KC94)^(ROUNDUP(MAX(KL$3-$KB94+1,0)/($KE94*12),0)-1)) -> 0 | KM94: =IF(OR($KA94="",$KB94="",$KE94=""),0,($KB94<=KM$3)*($KA94/12)*(1+$KC94)^(ROUNDUP(MAX(KM$3-$KB94+1,0)/($KE94*12),0)-1)) -> 0 | KN94: =IF(OR($KA94="",$KB94="",$KE94=""),0,($KB94<=KN$3)*($KA94/12)*(1+$KC94)^(ROUNDUP(MAX(KN$3-$KB94+1,0)/($KE94*12),0)-1)) -> 0 | ... PH94: =IF(OR($KA94="",$KB94="",$KE94=""),0,($KB94<=PH$3)*($KA94/12)*(1+$KC94)^(ROUNDUP(MAX(PH$3-$KB94+1,0)/($KE94*12),0)-1)) -> 0
B95: LiveHouse | C95: LiveHouse | D95: 22 | E95: ='URWLD COMPANY INPUTS'!$F$595 -> 6500 | F95: =D95+3 -> 25 | G95: =IF('INPUT REGISTER'!$F$374="","",'INPUT REGISTER'!$F$374) -> 0.035 | H95: ='INPUT REGISTER'!$F$674 -> 400 | I95: =IF(OR(E95="",H95=""),0,E95*H95) -> 2600000 | K95: Annual | L95: =IF(OR(L$3<$F95,$E95="",$H95=""),0,$E95*$H95/12*(1+$G95)^INT(MAX(0,L$3-$F95)/12)) -> 0 | M95: =IF(OR(M$3<$F95,$E95="",$H95=""),0,$E95*$H95/12*(1+$G95)^INT(MAX(0,M$3-$F95)/12)) -> 0 | N95: =IF(OR(N$3<$F95,$E95="",$H95=""),0,$E95*$H95/12*(1+$G95)^INT(MAX(0,N$3-$F95)/12)) -> 0 | O95: =IF(OR(O$3<$F95,$E95="",$H95=""),0,$E95*$H95/12*(1+$G95)^INT(MAX(0,O$3-$F95)/12)) -> 0 | P95: =IF(OR(P$3<$F95,$E95="",$H95=""),0,$E95*$H95/12*(1+$G95)^INT(MAX(0,P$3-$F95)/12)) -> 0 | Q95: =IF(OR(Q$3<$F95,$E95="",$H95=""),0,$E95*$H95/12*(1+$G95)^INT(MAX(0,Q$3-$F95)/12)) -> 0 | R95: =IF(OR(R$3<$F95,$E95="",$H95=""),0,$E95*$H95/12*(1+$G95)^INT(MAX(0,R$3-$F95)/12)) -> 0 | S95: =IF(OR(S$3<$F95,$E95="",$H95=""),0,$E95*$H95/12*(1+$G95)^INT(MAX(0,S$3-$F95)/12)) -> 0 | ... EN95: =IF(OR(EN$3<$F95,$E95="",$H95=""),0,$E95*$H95/12*(1+$G95)^INT(MAX(0,EN$3-$F95)/12)) -> 285308.62 | EP95: =$B95 -> LiveHouse | EQ95: =N($E95) -> 6500 | ER95: =$D95 -> 22 | EV95: =(EV$3>=$ER95)*$EQ95 -> 0 | EW95: =(EW$3>=$ER95)*$EQ95 -> 0 | EX95: =(EX$3>=$ER95)*$EQ95 -> 0 | EY95: =(EY$3>=$ER95)*$EQ95 -> 0 | EZ95: =(EZ$3>=$ER95)*$EQ95 -> 0 | FA95: =(FA$3>=$ER95)*$EQ95 -> 0 | FB95: =(FB$3>=$ER95)*$EQ95 -> 0 | FC95: =(FC$3>=$ER95)*$EQ95 -> 0 | ... JX95: =(JX$3>=$ER95)*$EQ95 -> 6500 | JZ95: =$B95 -> LiveHouse | KA95: =I95 -> 2600000 | KB95: =F95 -> 25 | KC95: =G95 -> 0.035 | KD95: =K95 -> Annual | KE95: =IF(KD95="",1,IFERROR(MAX(1,INDEX(Data!$H$24:$H$33,MATCH(KD95,Data!$G$24:$G$33,0))),1)) -> 1 | KG95: =IF(OR($KA95="",$KB95="",$KE95=""),0,($KB95<=KG$3)*($KA95/12)*(1+$KC95)^(ROUNDUP(MAX(KG$3-$KB95+1,0)/($KE95*12),0)-1)) -> 0 | KH95: =IF(OR($KA95="",$KB95="",$KE95=""),0,($KB95<=KH$3)*($KA95/12)*(1+$KC95)^(ROUNDUP(MAX(KH$3-$KB95+1,0)/($KE95*12),0)-1)) -> 0 | KI95: =IF(OR($KA95="",$KB95="",$KE95=""),0,($KB95<=KI$3)*($KA95/12)*(1+$KC95)^(ROUNDUP(MAX(KI$3-$KB95+1,0)/($KE95*12),0)-1)) -> 0 | KJ95: =IF(OR($KA95="",$KB95="",$KE95=""),0,($KB95<=KJ$3)*($KA95/12)*(1+$KC95)^(ROUNDUP(MAX(KJ$3-$KB95+1,0)/($KE95*12),0)-1)) -> 0 | KK95: =IF(OR($KA95="",$KB95="",$KE95=""),0,($KB95<=KK$3)*($KA95/12)*(1+$KC95)^(ROUNDUP(MAX(KK$3-$KB95+1,0)/($KE95*12),0)-1)) -> 0 | KL95: =IF(OR($KA95="",$KB95="",$KE95=""),0,($KB95<=KL$3)*($KA95/12)*(1+$KC95)^(ROUNDUP(MAX(KL$3-$KB95+1,0)/($KE95*12),0)-1)) -> 0 | KM95: =IF(OR($KA95="",$KB95="",$KE95=""),0,($KB95<=KM$3)*($KA95/12)*(1+$KC95)^(ROUNDUP(MAX(KM$3-$KB95+1,0)/($KE95*12),0)-1)) -> 0 | KN95: =IF(OR($KA95="",$KB95="",$KE95=""),0,($KB95<=KN$3)*($KA95/12)*(1+$KC95)^(ROUNDUP(MAX(KN$3-$KB95+1,0)/($KE95*12),0)-1)) -> 0 | ... PH95: =IF(OR($KA95="",$KB95="",$KE95=""),0,($KB95<=PH$3)*($KA95/12)*(1+$KC95)^(ROUNDUP(MAX(PH$3-$KB95+1,0)/($KE95*12),0)-1)) -> 285308.62
B96: Flexible Retail/F&B | C96: Food Truck Park | D96: 25 | E96: ='URWLD COMPANY INPUTS'!$F$626 -> 150 | F96: =D96+3 -> 28 | G96: =IF('INPUT REGISTER'!$F$481="","",'INPUT REGISTER'!$F$481) -> 0.035 | H96: ='INPUT REGISTER'!$F$675 -> 600 | I96: =IF(OR(E96="",H96=""),0,E96*H96) -> 90000 | K96: Annual | L96: =IF(OR(L$3<$F96,$E96="",$H96=""),0,$E96*$H96/12*(1+$G96)^INT(MAX(0,L$3-$F96)/12)) -> 0 | M96: =IF(OR(M$3<$F96,$E96="",$H96=""),0,$E96*$H96/12*(1+$G96)^INT(MAX(0,M$3-$F96)/12)) -> 0 | N96: =IF(OR(N$3<$F96,$E96="",$H96=""),0,$E96*$H96/12*(1+$G96)^INT(MAX(0,N$3-$F96)/12)) -> 0 | O96: =IF(OR(O$3<$F96,$E96="",$H96=""),0,$E96*$H96/12*(1+$G96)^INT(MAX(0,O$3-$F96)/12)) -> 0 | P96: =IF(OR(P$3<$F96,$E96="",$H96=""),0,$E96*$H96/12*(1+$G96)^INT(MAX(0,P$3-$F96)/12)) -> 0 | Q96: =IF(OR(Q$3<$F96,$E96="",$H96=""),0,$E96*$H96/12*(1+$G96)^INT(MAX(0,Q$3-$F96)/12)) -> 0 | R96: =IF(OR(R$3<$F96,$E96="",$H96=""),0,$E96*$H96/12*(1+$G96)^INT(MAX(0,R$3-$F96)/12)) -> 0 | S96: =IF(OR(S$3<$F96,$E96="",$H96=""),0,$E96*$H96/12*(1+$G96)^INT(MAX(0,S$3-$F96)/12)) -> 0 | ... EN96: =IF(OR(EN$3<$F96,$E96="",$H96=""),0,$E96*$H96/12*(1+$G96)^INT(MAX(0,EN$3-$F96)/12)) -> 9876.0678 | EP96: =$B96 -> Flexible Retail/F&B | EQ96: =N($E96) -> 150 | ER96: =$D96 -> 25 | EV96: =(EV$3>=$ER96)*$EQ96 -> 0 | EW96: =(EW$3>=$ER96)*$EQ96 -> 0 | EX96: =(EX$3>=$ER96)*$EQ96 -> 0 | EY96: =(EY$3>=$ER96)*$EQ96 -> 0 | EZ96: =(EZ$3>=$ER96)*$EQ96 -> 0 | FA96: =(FA$3>=$ER96)*$EQ96 -> 0 | FB96: =(FB$3>=$ER96)*$EQ96 -> 0 | FC96: =(FC$3>=$ER96)*$EQ96 -> 0 | ... JX96: =(JX$3>=$ER96)*$EQ96 -> 150 | JZ96: =$B96 -> Flexible Retail/F&B | KA96: =I96 -> 90000 | KB96: =F96 -> 28 | KC96: =G96 -> 0.035 | KD96: =K96 -> Annual | KE96: =IF(KD96="",1,IFERROR(MAX(1,INDEX(Data!$H$24:$H$33,MATCH(KD96,Data!$G$24:$G$33,0))),1)) -> 1 | KG96: =IF(OR($KA96="",$KB96="",$KE96=""),0,($KB96<=KG$3)*($KA96/12)*(1+$KC96)^(ROUNDUP(MAX(KG$3-$KB96+1,0)/($KE96*12),0)-1)) -> 0 | KH96: =IF(OR($KA96="",$KB96="",$KE96=""),0,($KB96<=KH$3)*($KA96/12)*(1+$KC96)^(ROUNDUP(MAX(KH$3-$KB96+1,0)/($KE96*12),0)-1)) -> 0 | KI96: =IF(OR($KA96="",$KB96="",$KE96=""),0,($KB96<=KI$3)*($KA96/12)*(1+$KC96)^(ROUNDUP(MAX(KI$3-$KB96+1,0)/($KE96*12),0)-1)) -> 0 | KJ96: =IF(OR($KA96="",$KB96="",$KE96=""),0,($KB96<=KJ$3)*($KA96/12)*(1+$KC96)^(ROUNDUP(MAX(KJ$3-$KB96+1,0)/($KE96*12),0)-1)) -> 0 | KK96: =IF(OR($KA96="",$KB96="",$KE96=""),0,($KB96<=KK$3)*($KA96/12)*(1+$KC96)^(ROUNDUP(MAX(KK$3-$KB96+1,0)/($KE96*12),0)-1)) -> 0 | KL96: =IF(OR($KA96="",$KB96="",$KE96=""),0,($KB96<=KL$3)*($KA96/12)*(1+$KC96)^(ROUNDUP(MAX(KL$3-$KB96+1,0)/($KE96*12),0)-1)) -> 0 | KM96: =IF(OR($KA96="",$KB96="",$KE96=""),0,($KB96<=KM$3)*($KA96/12)*(1+$KC96)^(ROUNDUP(MAX(KM$3-$KB96+1,0)/($KE96*12),0)-1)) -> 0 | KN96: =IF(OR($KA96="",$KB96="",$KE96=""),0,($KB96<=KN$3)*($KA96/12)*(1+$KC96)^(ROUNDUP(MAX(KN$3-$KB96+1,0)/($KE96*12),0)-1)) -> 0 | ... PH96: =IF(OR($KA96="",$KB96="",$KE96=""),0,($KB96<=PH$3)*($KA96/12)*(1+$KC96)^(ROUNDUP(MAX(PH$3-$KB96+1,0)/($KE96*12),0)-1)) -> 9876.0678
B97: Genesis Health & Fitness | C97: Genesis Health & Fitness | D97: 25 | E97: ='URWLD COMPANY INPUTS'!$F$398 -> 4000 | F97: =D97+3 -> 28 | G97: =IF('INPUT REGISTER'!$F$290="","",'INPUT REGISTER'!$F$290) -> 0.035 | H97: ='INPUT REGISTER'!$F$676 -> 500 | I97: =IF(OR(E97="",H97=""),0,E97*H97) -> 2000000 | K97: Annual | L97: =IF(OR(L$3<$F97,$E97="",$H97=""),0,$E97*$H97/12*(1+$G97)^INT(MAX(0,L$3-$F97)/12)) -> 0 | M97: =IF(OR(M$3<$F97,$E97="",$H97=""),0,$E97*$H97/12*(1+$G97)^INT(MAX(0,M$3-$F97)/12)) -> 0 | N97: =IF(OR(N$3<$F97,$E97="",$H97=""),0,$E97*$H97/12*(1+$G97)^INT(MAX(0,N$3-$F97)/12)) -> 0 | O97: =IF(OR(O$3<$F97,$E97="",$H97=""),0,$E97*$H97/12*(1+$G97)^INT(MAX(0,O$3-$F97)/12)) -> 0 | P97: =IF(OR(P$3<$F97,$E97="",$H97=""),0,$E97*$H97/12*(1+$G97)^INT(MAX(0,P$3-$F97)/12)) -> 0 | Q97: =IF(OR(Q$3<$F97,$E97="",$H97=""),0,$E97*$H97/12*(1+$G97)^INT(MAX(0,Q$3-$F97)/12)) -> 0 | R97: =IF(OR(R$3<$F97,$E97="",$H97=""),0,$E97*$H97/12*(1+$G97)^INT(MAX(0,R$3-$F97)/12)) -> 0 | S97: =IF(OR(S$3<$F97,$E97="",$H97=""),0,$E97*$H97/12*(1+$G97)^INT(MAX(0,S$3-$F97)/12)) -> 0 | ... EN97: =IF(OR(EN$3<$F97,$E97="",$H97=""),0,$E97*$H97/12*(1+$G97)^INT(MAX(0,EN$3-$F97)/12)) -> 219468.17 | EP97: =$B97 -> Genesis Health & Fitness | EQ97: =N($E97) -> 4000 | ER97: =$D97 -> 25 | EV97: =(EV$3>=$ER97)*$EQ97 -> 0 | EW97: =(EW$3>=$ER97)*$EQ97 -> 0 | EX97: =(EX$3>=$ER97)*$EQ97 -> 0 | EY97: =(EY$3>=$ER97)*$EQ97 -> 0 | EZ97: =(EZ$3>=$ER97)*$EQ97 -> 0 | FA97: =(FA$3>=$ER97)*$EQ97 -> 0 | FB97: =(FB$3>=$ER97)*$EQ97 -> 0 | FC97: =(FC$3>=$ER97)*$EQ97 -> 0 | ... JX97: =(JX$3>=$ER97)*$EQ97 -> 4000 | JZ97: =$B97 -> Genesis Health & Fitness | KA97: =I97 -> 2000000 | KB97: =F97 -> 28 | KC97: =G97 -> 0.035 | KD97: =K97 -> Annual | KE97: =IF(KD97="",1,IFERROR(MAX(1,INDEX(Data!$H$24:$H$33,MATCH(KD97,Data!$G$24:$G$33,0))),1)) -> 1 | KG97: =IF(OR($KA97="",$KB97="",$KE97=""),0,($KB97<=KG$3)*($KA97/12)*(1+$KC97)^(ROUNDUP(MAX(KG$3-$KB97+1,0)/($KE97*12),0)-1)) -> 0 | KH97: =IF(OR($KA97="",$KB97="",$KE97=""),0,($KB97<=KH$3)*($KA97/12)*(1+$KC97)^(ROUNDUP(MAX(KH$3-$KB97+1,0)/($KE97*12),0)-1)) -> 0 | KI97: =IF(OR($KA97="",$KB97="",$KE97=""),0,($KB97<=KI$3)*($KA97/12)*(1+$KC97)^(ROUNDUP(MAX(KI$3-$KB97+1,0)/($KE97*12),0)-1)) -> 0 | KJ97: =IF(OR($KA97="",$KB97="",$KE97=""),0,($KB97<=KJ$3)*($KA97/12)*(1+$KC97)^(ROUNDUP(MAX(KJ$3-$KB97+1,0)/($KE97*12),0)-1)) -> 0 | KK97: =IF(OR($KA97="",$KB97="",$KE97=""),0,($KB97<=KK$3)*($KA97/12)*(1+$KC97)^(ROUNDUP(MAX(KK$3-$KB97+1,0)/($KE97*12),0)-1)) -> 0 | KL97: =IF(OR($KA97="",$KB97="",$KE97=""),0,($KB97<=KL$3)*($KA97/12)*(1+$KC97)^(ROUNDUP(MAX(KL$3-$KB97+1,0)/($KE97*12),0)-1)) -> 0 | KM97: =IF(OR($KA97="",$KB97="",$KE97=""),0,($KB97<=KM$3)*($KA97/12)*(1+$KC97)^(ROUNDUP(MAX(KM$3-$KB97+1,0)/($KE97*12),0)-1)) -> 0 | KN97: =IF(OR($KA97="",$KB97="",$KE97=""),0,($KB97<=KN$3)*($KA97/12)*(1+$KC97)^(ROUNDUP(MAX(KN$3-$KB97+1,0)/($KE97*12),0)-1)) -> 0 | ... PH97: =IF(OR($KA97="",$KB97="",$KE97=""),0,($KB97<=PH$3)*($KA97/12)*(1+$KC97)^(ROUNDUP(MAX(PH$3-$KB97+1,0)/($KE97*12),0)-1)) -> 219468.17
B98: Car Park | C98: Secure (Preferred) | D98: 28 | E98: ='URWLD COMPANY INPUTS'!$F$421 -> 19500.38 | F98: =D98+3 -> 31 | G98: =IF('INPUT REGISTER'!$F$345="","",'INPUT REGISTER'!$F$345) -> 0.035 | H98: ='INPUT REGISTER'!$F$677 -> 0 | I98: =IF(OR(E98="",H98=""),0,E98*H98) -> 0 | K98: Annual | L98: =IF(OR(L$3<$F98,$E98="",$H98=""),0,$E98*$H98/12*(1+$G98)^INT(MAX(0,L$3-$F98)/12)) -> 0 | M98: =IF(OR(M$3<$F98,$E98="",$H98=""),0,$E98*$H98/12*(1+$G98)^INT(MAX(0,M$3-$F98)/12)) -> 0 | N98: =IF(OR(N$3<$F98,$E98="",$H98=""),0,$E98*$H98/12*(1+$G98)^INT(MAX(0,N$3-$F98)/12)) -> 0 | O98: =IF(OR(O$3<$F98,$E98="",$H98=""),0,$E98*$H98/12*(1+$G98)^INT(MAX(0,O$3-$F98)/12)) -> 0 | P98: =IF(OR(P$3<$F98,$E98="",$H98=""),0,$E98*$H98/12*(1+$G98)^INT(MAX(0,P$3-$F98)/12)) -> 0 | Q98: =IF(OR(Q$3<$F98,$E98="",$H98=""),0,$E98*$H98/12*(1+$G98)^INT(MAX(0,Q$3-$F98)/12)) -> 0 | R98: =IF(OR(R$3<$F98,$E98="",$H98=""),0,$E98*$H98/12*(1+$G98)^INT(MAX(0,R$3-$F98)/12)) -> 0 | S98: =IF(OR(S$3<$F98,$E98="",$H98=""),0,$E98*$H98/12*(1+$G98)^INT(MAX(0,S$3-$F98)/12)) -> 0 | ... EN98: =IF(OR(EN$3<$F98,$E98="",$H98=""),0,$E98*$H98/12*(1+$G98)^INT(MAX(0,EN$3-$F98)/12)) -> 0 | EP98: =$B98 -> Car Park | EQ98: =N($E98) -> 19500.38 | ER98: =$D98 -> 28 | EV98: =(EV$3>=$ER98)*$EQ98 -> 0 | EW98: =(EW$3>=$ER98)*$EQ98 -> 0 | EX98: =(EX$3>=$ER98)*$EQ98 -> 0 | EY98: =(EY$3>=$ER98)*$EQ98 -> 0 | EZ98: =(EZ$3>=$ER98)*$EQ98 -> 0 | FA98: =(FA$3>=$ER98)*$EQ98 -> 0 | FB98: =(FB$3>=$ER98)*$EQ98 -> 0 | FC98: =(FC$3>=$ER98)*$EQ98 -> 0 | ... JX98: =(JX$3>=$ER98)*$EQ98 -> 19500.38 | JZ98: =$B98 -> Car Park | KA98: =I98 -> 0 | KB98: =F98 -> 31 | KC98: =G98 -> 0.035 | KD98: =K98 -> Annual | KE98: =IF(KD98="",1,IFERROR(MAX(1,INDEX(Data!$H$24:$H$33,MATCH(KD98,Data!$G$24:$G$33,0))),1)) -> 1 | KG98: =IF(OR($KA98="",$KB98="",$KE98=""),0,($KB98<=KG$3)*($KA98/12)*(1+$KC98)^(ROUNDUP(MAX(KG$3-$KB98+1,0)/($KE98*12),0)-1)) -> 0 | KH98: =IF(OR($KA98="",$KB98="",$KE98=""),0,($KB98<=KH$3)*($KA98/12)*(1+$KC98)^(ROUNDUP(MAX(KH$3-$KB98+1,0)/($KE98*12),0)-1)) -> 0 | KI98: =IF(OR($KA98="",$KB98="",$KE98=""),0,($KB98<=KI$3)*($KA98/12)*(1+$KC98)^(ROUNDUP(MAX(KI$3-$KB98+1,0)/($KE98*12),0)-1)) -> 0 | KJ98: =IF(OR($KA98="",$KB98="",$KE98=""),0,($KB98<=KJ$3)*($KA98/12)*(1+$KC98)^(ROUNDUP(MAX(KJ$3-$KB98+1,0)/($KE98*12),0)-1)) -> 0 | KK98: =IF(OR($KA98="",$KB98="",$KE98=""),0,($KB98<=KK$3)*($KA98/12)*(1+$KC98)^(ROUNDUP(MAX(KK$3-$KB98+1,0)/($KE98*12),0)-1)) -> 0 | KL98: =IF(OR($KA98="",$KB98="",$KE98=""),0,($KB98<=KL$3)*($KA98/12)*(1+$KC98)^(ROUNDUP(MAX(KL$3-$KB98+1,0)/($KE98*12),0)-1)) -> 0 | KM98: =IF(OR($KA98="",$KB98="",$KE98=""),0,($KB98<=KM$3)*($KA98/12)*(1+$KC98)^(ROUNDUP(MAX(KM$3-$KB98+1,0)/($KE98*12),0)-1)) -> 0 | KN98: =IF(OR($KA98="",$KB98="",$KE98=""),0,($KB98<=KN$3)*($KA98/12)*(1+$KC98)^(ROUNDUP(MAX(KN$3-$KB98+1,0)/($KE98*12),0)-1)) -> 0 | ... PH98: =IF(OR($KA98="",$KB98="",$KE98=""),0,($KB98<=PH$3)*($KA98/12)*(1+$KC98)^(ROUNDUP(MAX(PH$3-$KB98+1,0)/($KE98*12),0)-1)) -> 0
B99: Snowtunnel | C99: Snowtunnel | D99: 28 | E99: ='URWLD COMPANY INPUTS'!$F$602 -> 3800 | F99: =D99+3 -> 31 | G99: =IF('INPUT REGISTER'!$F$395="","",'INPUT REGISTER'!$F$395) -> 0.035 | H99: ='INPUT REGISTER'!$F$678 -> 500 | I99: =IF(OR(E99="",H99=""),0,E99*H99) -> 1900000 | K99: Annual | L99: =IF(OR(L$3<$F99,$E99="",$H99=""),0,$E99*$H99/12*(1+$G99)^INT(MAX(0,L$3-$F99)/12)) -> 0 | M99: =IF(OR(M$3<$F99,$E99="",$H99=""),0,$E99*$H99/12*(1+$G99)^INT(MAX(0,M$3-$F99)/12)) -> 0 | N99: =IF(OR(N$3<$F99,$E99="",$H99=""),0,$E99*$H99/12*(1+$G99)^INT(MAX(0,N$3-$F99)/12)) -> 0 | O99: =IF(OR(O$3<$F99,$E99="",$H99=""),0,$E99*$H99/12*(1+$G99)^INT(MAX(0,O$3-$F99)/12)) -> 0 | P99: =IF(OR(P$3<$F99,$E99="",$H99=""),0,$E99*$H99/12*(1+$G99)^INT(MAX(0,P$3-$F99)/12)) -> 0 | Q99: =IF(OR(Q$3<$F99,$E99="",$H99=""),0,$E99*$H99/12*(1+$G99)^INT(MAX(0,Q$3-$F99)/12)) -> 0 | R99: =IF(OR(R$3<$F99,$E99="",$H99=""),0,$E99*$H99/12*(1+$G99)^INT(MAX(0,R$3-$F99)/12)) -> 0 | S99: =IF(OR(S$3<$F99,$E99="",$H99=""),0,$E99*$H99/12*(1+$G99)^INT(MAX(0,S$3-$F99)/12)) -> 0 | ... EN99: =IF(OR(EN$3<$F99,$E99="",$H99=""),0,$E99*$H99/12*(1+$G99)^INT(MAX(0,EN$3-$F99)/12)) -> 208494.76 | EP99: =$B99 -> Snowtunnel | EQ99: =N($E99) -> 3800 | ER99: =$D99 -> 28 | EV99: =(EV$3>=$ER99)*$EQ99 -> 0 | EW99: =(EW$3>=$ER99)*$EQ99 -> 0 | EX99: =(EX$3>=$ER99)*$EQ99 -> 0 | EY99: =(EY$3>=$ER99)*$EQ99 -> 0 | EZ99: =(EZ$3>=$ER99)*$EQ99 -> 0 | FA99: =(FA$3>=$ER99)*$EQ99 -> 0 | FB99: =(FB$3>=$ER99)*$EQ99 -> 0 | FC99: =(FC$3>=$ER99)*$EQ99 -> 0 | ... JX99: =(JX$3>=$ER99)*$EQ99 -> 3800 | JZ99: =$B99 -> Snowtunnel | KA99: =I99 -> 1900000 | KB99: =F99 -> 31 | KC99: =G99 -> 0.035 | KD99: =K99 -> Annual | KE99: =IF(KD99="",1,IFERROR(MAX(1,INDEX(Data!$H$24:$H$33,MATCH(KD99,Data!$G$24:$G$33,0))),1)) -> 1 | KG99: =IF(OR($KA99="",$KB99="",$KE99=""),0,($KB99<=KG$3)*($KA99/12)*(1+$KC99)^(ROUNDUP(MAX(KG$3-$KB99+1,0)/($KE99*12),0)-1)) -> 0 | KH99: =IF(OR($KA99="",$KB99="",$KE99=""),0,($KB99<=KH$3)*($KA99/12)*(1+$KC99)^(ROUNDUP(MAX(KH$3-$KB99+1,0)/($KE99*12),0)-1)) -> 0 | KI99: =IF(OR($KA99="",$KB99="",$KE99=""),0,($KB99<=KI$3)*($KA99/12)*(1+$KC99)^(ROUNDUP(MAX(KI$3-$KB99+1,0)/($KE99*12),0)-1)) -> 0 | KJ99: =IF(OR($KA99="",$KB99="",$KE99=""),0,($KB99<=KJ$3)*($KA99/12)*(1+$KC99)^(ROUNDUP(MAX(KJ$3-$KB99+1,0)/($KE99*12),0)-1)) -> 0 | KK99: =IF(OR($KA99="",$KB99="",$KE99=""),0,($KB99<=KK$3)*($KA99/12)*(1+$KC99)^(ROUNDUP(MAX(KK$3-$KB99+1,0)/($KE99*12),0)-1)) -> 0 | KL99: =IF(OR($KA99="",$KB99="",$KE99=""),0,($KB99<=KL$3)*($KA99/12)*(1+$KC99)^(ROUNDUP(MAX(KL$3-$KB99+1,0)/($KE99*12),0)-1)) -> 0 | KM99: =IF(OR($KA99="",$KB99="",$KE99=""),0,($KB99<=KM$3)*($KA99/12)*(1+$KC99)^(ROUNDUP(MAX(KM$3-$KB99+1,0)/($KE99*12),0)-1)) -> 0 | KN99: =IF(OR($KA99="",$KB99="",$KE99=""),0,($KB99<=KN$3)*($KA99/12)*(1+$KC99)^(ROUNDUP(MAX(KN$3-$KB99+1,0)/($KE99*12),0)-1)) -> 0 | ... PH99: =IF(OR($KA99="",$KB99="",$KE99=""),0,($KB99<=PH$3)*($KA99/12)*(1+$KC99)^(ROUNDUP(MAX(PH$3-$KB99+1,0)/($KE99*12),0)-1)) -> 208494.76
B100: Go Kart | C100: Funtime Group | D100: 31 | E100: =IF('URWLD COMPANY INPUTS'!$F$859="","",'URWLD COMPANY INPUTS'!$F$859) | F100: =D100+3 -> 34 | G100: =IF('INPUT REGISTER'!$F$416="","",'INPUT REGISTER'!$F$416) -> 0.035 | H100: ='INPUT REGISTER'!$F$679 -> 500 | I100: =IF(OR(E100="",H100=""),0,E100*H100) -> 0 | K100: Annual | L100: =IF(OR(L$3<$F100,$E100="",$H100=""),0,$E100*$H100/12*(1+$G100)^INT(MAX(0,L$3-$F100)/12)) -> 0 | M100: =IF(OR(M$3<$F100,$E100="",$H100=""),0,$E100*$H100/12*(1+$G100)^INT(MAX(0,M$3-$F100)/12)) -> 0 | N100: =IF(OR(N$3<$F100,$E100="",$H100=""),0,$E100*$H100/12*(1+$G100)^INT(MAX(0,N$3-$F100)/12)) -> 0 | O100: =IF(OR(O$3<$F100,$E100="",$H100=""),0,$E100*$H100/12*(1+$G100)^INT(MAX(0,O$3-$F100)/12)) -> 0 | P100: =IF(OR(P$3<$F100,$E100="",$H100=""),0,$E100*$H100/12*(1+$G100)^INT(MAX(0,P$3-$F100)/12)) -> 0 | Q100: =IF(OR(Q$3<$F100,$E100="",$H100=""),0,$E100*$H100/12*(1+$G100)^INT(MAX(0,Q$3-$F100)/12)) -> 0 | R100: =IF(OR(R$3<$F100,$E100="",$H100=""),0,$E100*$H100/12*(1+$G100)^INT(MAX(0,R$3-$F100)/12)) -> 0 | S100: =IF(OR(S$3<$F100,$E100="",$H100=""),0,$E100*$H100/12*(1+$G100)^INT(MAX(0,S$3-$F100)/12)) -> 0 | ... EN100: =IF(OR(EN$3<$F100,$E100="",$H100=""),0,$E100*$H100/12*(1+$G100)^INT(MAX(0,EN$3-$F100)/12)) -> 0 | EP100: =$B100 -> Go Kart | EQ100: =N($E100) -> 0 | ER100: =$D100 -> 31 | EV100: =(EV$3>=$ER100)*$EQ100 -> 0 | EW100: =(EW$3>=$ER100)*$EQ100 -> 0 | EX100: =(EX$3>=$ER100)*$EQ100 -> 0 | EY100: =(EY$3>=$ER100)*$EQ100 -> 0 | EZ100: =(EZ$3>=$ER100)*$EQ100 -> 0 | FA100: =(FA$3>=$ER100)*$EQ100 -> 0 | FB100: =(FB$3>=$ER100)*$EQ100 -> 0 | FC100: =(FC$3>=$ER100)*$EQ100 -> 0 | ... JX100: =(JX$3>=$ER100)*$EQ100 -> 0 | JZ100: =$B100 -> Go Kart | KA100: =I100 -> 0 | KB100: =F100 -> 34 | KC100: =G100 -> 0.035 | KD100: =K100 -> Annual | KE100: =IF(KD100="",1,IFERROR(MAX(1,INDEX(Data!$H$24:$H$33,MATCH(KD100,Data!$G$24:$G$33,0))),1)) -> 1 | KG100: =IF(OR($KA100="",$KB100="",$KE100=""),0,($KB100<=KG$3)*($KA100/12)*(1+$KC100)^(ROUNDUP(MAX(KG$3-$KB100+1,0)/($KE100*12),0)-1)) -> 0 | KH100: =IF(OR($KA100="",$KB100="",$KE100=""),0,($KB100<=KH$3)*($KA100/12)*(1+$KC100)^(ROUNDUP(MAX(KH$3-$KB100+1,0)/($KE100*12),0)-1)) -> 0 | KI100: =IF(OR($KA100="",$KB100="",$KE100=""),0,($KB100<=KI$3)*($KA100/12)*(1+$KC100)^(ROUNDUP(MAX(KI$3-$KB100+1,0)/($KE100*12),0)-1)) -> 0 | KJ100: =IF(OR($KA100="",$KB100="",$KE100=""),0,($KB100<=KJ$3)*($KA100/12)*(1+$KC100)^(ROUNDUP(MAX(KJ$3-$KB100+1,0)/($KE100*12),0)-1)) -> 0 | KK100: =IF(OR($KA100="",$KB100="",$KE100=""),0,($KB100<=KK$3)*($KA100/12)*(1+$KC100)^(ROUNDUP(MAX(KK$3-$KB100+1,0)/($KE100*12),0)-1)) -> 0 | KL100: =IF(OR($KA100="",$KB100="",$KE100=""),0,($KB100<=KL$3)*($KA100/12)*(1+$KC100)^(ROUNDUP(MAX(KL$3-$KB100+1,0)/($KE100*12),0)-1)) -> 0 | KM100: =IF(OR($KA100="",$KB100="",$KE100=""),0,($KB100<=KM$3)*($KA100/12)*(1+$KC100)^(ROUNDUP(MAX(KM$3-$KB100+1,0)/($KE100*12),0)-1)) -> 0 | KN100: =IF(OR($KA100="",$KB100="",$KE100=""),0,($KB100<=KN$3)*($KA100/12)*(1+$KC100)^(ROUNDUP(MAX(KN$3-$KB100+1,0)/($KE100*12),0)-1)) -> 0 | ... PH100: =IF(OR($KA100="",$KB100="",$KE100=""),0,($KB100<=PH$3)*($KA100/12)*(1+$KC100)^(ROUNDUP(MAX(PH$3-$KB100+1,0)/($KE100*12),0)-1)) -> 0
B101: Landscape-Based Attraction | C101: Operating Group | D101: 31 | E101: ='URWLD COMPANY INPUTS'!$F$611 -> 150 | F101: =D101+3 -> 34 | G101: =IF('INPUT REGISTER'!$F$437="","",'INPUT REGISTER'!$F$437) -> 0.035 | H101: ='INPUT REGISTER'!$F$680 -> 600 | I101: =IF(OR(E101="",H101=""),0,E101*H101) -> 90000 | K101: Annual | L101: =IF(OR(L$3<$F101,$E101="",$H101=""),0,$E101*$H101/12*(1+$G101)^INT(MAX(0,L$3-$F101)/12)) -> 0 | M101: =IF(OR(M$3<$F101,$E101="",$H101=""),0,$E101*$H101/12*(1+$G101)^INT(MAX(0,M$3-$F101)/12)) -> 0 | N101: =IF(OR(N$3<$F101,$E101="",$H101=""),0,$E101*$H101/12*(1+$G101)^INT(MAX(0,N$3-$F101)/12)) -> 0 | O101: =IF(OR(O$3<$F101,$E101="",$H101=""),0,$E101*$H101/12*(1+$G101)^INT(MAX(0,O$3-$F101)/12)) -> 0 | P101: =IF(OR(P$3<$F101,$E101="",$H101=""),0,$E101*$H101/12*(1+$G101)^INT(MAX(0,P$3-$F101)/12)) -> 0 | Q101: =IF(OR(Q$3<$F101,$E101="",$H101=""),0,$E101*$H101/12*(1+$G101)^INT(MAX(0,Q$3-$F101)/12)) -> 0 | R101: =IF(OR(R$3<$F101,$E101="",$H101=""),0,$E101*$H101/12*(1+$G101)^INT(MAX(0,R$3-$F101)/12)) -> 0 | S101: =IF(OR(S$3<$F101,$E101="",$H101=""),0,$E101*$H101/12*(1+$G101)^INT(MAX(0,S$3-$F101)/12)) -> 0 | ... EN101: =IF(OR(EN$3<$F101,$E101="",$H101=""),0,$E101*$H101/12*(1+$G101)^INT(MAX(0,EN$3-$F101)/12)) -> 9876.0678 | EP101: =$B101 -> Landscape-Based Attraction | EQ101: =N($E101) -> 150 | ER101: =$D101 -> 31 | EV101: =(EV$3>=$ER101)*$EQ101 -> 0 | EW101: =(EW$3>=$ER101)*$EQ101 -> 0 | EX101: =(EX$3>=$ER101)*$EQ101 -> 0 | EY101: =(EY$3>=$ER101)*$EQ101 -> 0 | EZ101: =(EZ$3>=$ER101)*$EQ101 -> 0 | FA101: =(FA$3>=$ER101)*$EQ101 -> 0 | FB101: =(FB$3>=$ER101)*$EQ101 -> 0 | FC101: =(FC$3>=$ER101)*$EQ101 -> 0 | ... JX101: =(JX$3>=$ER101)*$EQ101 -> 150 | JZ101: =$B101 -> Landscape-Based Attraction | KA101: =I101 -> 90000 | KB101: =F101 -> 34 | KC101: =G101 -> 0.035 | KD101: =K101 -> Annual | KE101: =IF(KD101="",1,IFERROR(MAX(1,INDEX(Data!$H$24:$H$33,MATCH(KD101,Data!$G$24:$G$33,0))),1)) -> 1 | KG101: =IF(OR($KA101="",$KB101="",$KE101=""),0,($KB101<=KG$3)*($KA101/12)*(1+$KC101)^(ROUNDUP(MAX(KG$3-$KB101+1,0)/($KE101*12),0)-1)) -> 0 | KH101: =IF(OR($KA101="",$KB101="",$KE101=""),0,($KB101<=KH$3)*($KA101/12)*(1+$KC101)^(ROUNDUP(MAX(KH$3-$KB101+1,0)/($KE101*12),0)-1)) -> 0 | KI101: =IF(OR($KA101="",$KB101="",$KE101=""),0,($KB101<=KI$3)*($KA101/12)*(1+$KC101)^(ROUNDUP(MAX(KI$3-$KB101+1,0)/($KE101*12),0)-1)) -> 0 | KJ101: =IF(OR($KA101="",$KB101="",$KE101=""),0,($KB101<=KJ$3)*($KA101/12)*(1+$KC101)^(ROUNDUP(MAX(KJ$3-$KB101+1,0)/($KE101*12),0)-1)) -> 0 | KK101: =IF(OR($KA101="",$KB101="",$KE101=""),0,($KB101<=KK$3)*($KA101/12)*(1+$KC101)^(ROUNDUP(MAX(KK$3-$KB101+1,0)/($KE101*12),0)-1)) -> 0 | KL101: =IF(OR($KA101="",$KB101="",$KE101=""),0,($KB101<=KL$3)*($KA101/12)*(1+$KC101)^(ROUNDUP(MAX(KL$3-$KB101+1,0)/($KE101*12),0)-1)) -> 0 | KM101: =IF(OR($KA101="",$KB101="",$KE101=""),0,($KB101<=KM$3)*($KA101/12)*(1+$KC101)^(ROUNDUP(MAX(KM$3-$KB101+1,0)/($KE101*12),0)-1)) -> 0 | KN101: =IF(OR($KA101="",$KB101="",$KE101=""),0,($KB101<=KN$3)*($KA101/12)*(1+$KC101)^(ROUNDUP(MAX(KN$3-$KB101+1,0)/($KE101*12),0)-1)) -> 0 | ... PH101: =IF(OR($KA101="",$KB101="",$KE101=""),0,($KB101<=PH$3)*($KA101/12)*(1+$KC101)^(ROUNDUP(MAX(PH$3-$KB101+1,0)/($KE101*12),0)-1)) -> 9876.0678
B102: Self-Storage Facility | C102: Storage King | D102: 31 | E102: ='URWLD COMPANY INPUTS'!$F$618 -> 600 | F102: =D102+3 -> 34 | G102: =IF('URWLD COMPANY INPUTS'!$F$113="","",'URWLD COMPANY INPUTS'!$F$113) -> 0.035 | H102: ='INPUT REGISTER'!$F$681 -> 0 | I102: =IF(OR(E102="",H102=""),0,E102*H102) -> 0 | K102: Annual | L102: =IF(OR(L$3<$F102,$E102="",$H102=""),0,$E102*$H102/12*(1+$G102)^INT(MAX(0,L$3-$F102)/12)) -> 0 | M102: =IF(OR(M$3<$F102,$E102="",$H102=""),0,$E102*$H102/12*(1+$G102)^INT(MAX(0,M$3-$F102)/12)) -> 0 | N102: =IF(OR(N$3<$F102,$E102="",$H102=""),0,$E102*$H102/12*(1+$G102)^INT(MAX(0,N$3-$F102)/12)) -> 0 | O102: =IF(OR(O$3<$F102,$E102="",$H102=""),0,$E102*$H102/12*(1+$G102)^INT(MAX(0,O$3-$F102)/12)) -> 0 | P102: =IF(OR(P$3<$F102,$E102="",$H102=""),0,$E102*$H102/12*(1+$G102)^INT(MAX(0,P$3-$F102)/12)) -> 0 | Q102: =IF(OR(Q$3<$F102,$E102="",$H102=""),0,$E102*$H102/12*(1+$G102)^INT(MAX(0,Q$3-$F102)/12)) -> 0 | R102: =IF(OR(R$3<$F102,$E102="",$H102=""),0,$E102*$H102/12*(1+$G102)^INT(MAX(0,R$3-$F102)/12)) -> 0 | S102: =IF(OR(S$3<$F102,$E102="",$H102=""),0,$E102*$H102/12*(1+$G102)^INT(MAX(0,S$3-$F102)/12)) -> 0 | ... EN102: =IF(OR(EN$3<$F102,$E102="",$H102=""),0,$E102*$H102/12*(1+$G102)^INT(MAX(0,EN$3-$F102)/12)) -> 0 | EP102: =$B102 -> Self-Storage Facility | EQ102: =N($E102) -> 600 | ER102: =$D102 -> 31 | EV102: =(EV$3>=$ER102)*$EQ102 -> 0 | EW102: =(EW$3>=$ER102)*$EQ102 -> 0 | EX102: =(EX$3>=$ER102)*$EQ102 -> 0 | EY102: =(EY$3>=$ER102)*$EQ102 -> 0 | EZ102: =(EZ$3>=$ER102)*$EQ102 -> 0 | FA102: =(FA$3>=$ER102)*$EQ102 -> 0 | FB102: =(FB$3>=$ER102)*$EQ102 -> 0 | FC102: =(FC$3>=$ER102)*$EQ102 -> 0 | ... JX102: =(JX$3>=$ER102)*$EQ102 -> 600 | JZ102: =$B102 -> Self-Storage Facility | KA102: =I102 -> 0 | KB102: =F102 -> 34 | KC102: =G102 -> 0.035 | KD102: =K102 -> Annual | KE102: =IF(KD102="",1,IFERROR(MAX(1,INDEX(Data!$H$24:$H$33,MATCH(KD102,Data!$G$24:$G$33,0))),1)) -> 1 | KG102: =IF(OR($KA102="",$KB102="",$KE102=""),0,($KB102<=KG$3)*($KA102/12)*(1+$KC102)^(ROUNDUP(MAX(KG$3-$KB102+1,0)/($KE102*12),0)-1)) -> 0 | KH102: =IF(OR($KA102="",$KB102="",$KE102=""),0,($KB102<=KH$3)*($KA102/12)*(1+$KC102)^(ROUNDUP(MAX(KH$3-$KB102+1,0)/($KE102*12),0)-1)) -> 0 | KI102: =IF(OR($KA102="",$KB102="",$KE102=""),0,($KB102<=KI$3)*($KA102/12)*(1+$KC102)^(ROUNDUP(MAX(KI$3-$KB102+1,0)/($KE102*12),0)-1)) -> 0 | KJ102: =IF(OR($KA102="",$KB102="",$KE102=""),0,($KB102<=KJ$3)*($KA102/12)*(1+$KC102)^(ROUNDUP(MAX(KJ$3-$KB102+1,0)/($KE102*12),0)-1)) -> 0 | KK102: =IF(OR($KA102="",$KB102="",$KE102=""),0,($KB102<=KK$3)*($KA102/12)*(1+$KC102)^(ROUNDUP(MAX(KK$3-$KB102+1,0)/($KE102*12),0)-1)) -> 0 | KL102: =IF(OR($KA102="",$KB102="",$KE102=""),0,($KB102<=KL$3)*($KA102/12)*(1+$KC102)^(ROUNDUP(MAX(KL$3-$KB102+1,0)/($KE102*12),0)-1)) -> 0 | KM102: =IF(OR($KA102="",$KB102="",$KE102=""),0,($KB102<=KM$3)*($KA102/12)*(1+$KC102)^(ROUNDUP(MAX(KM$3-$KB102+1,0)/($KE102*12),0)-1)) -> 0 | KN102: =IF(OR($KA102="",$KB102="",$KE102=""),0,($KB102<=KN$3)*($KA102/12)*(1+$KC102)^(ROUNDUP(MAX(KN$3-$KB102+1,0)/($KE102*12),0)-1)) -> 0 | ... PH102: =IF(OR($KA102="",$KB102="",$KE102=""),0,($KB102<=PH$3)*($KA102/12)*(1+$KC102)^(ROUNDUP(MAX(PH$3-$KB102+1,0)/($KE102*12),0)-1)) -> 0
B103: Convenience Store / Laundromat | C103: 7-Eleven / App Automation | D103: =Timing_Operation_Begin_Month -> 37 | E103: =SUM('URWLD COMPANY INPUTS'!$F$632:$F$633) -> 2120 | F103: =D103+3 -> 40 | G103: =IF('INPUT REGISTER'!$F$495="","",'INPUT REGISTER'!$F$495) -> 0.035 | H103: ='INPUT REGISTER'!$F$682 -> 0 | I103: =IF(OR(E103="",H103=""),0,E103*H103) -> 0 | K103: Annual | L103: =IF(OR(L$3<$F103,$E103="",$H103=""),0,$E103*$H103/12*(1+$G103)^INT(MAX(0,L$3-$F103)/12)) -> 0 | M103: =IF(OR(M$3<$F103,$E103="",$H103=""),0,$E103*$H103/12*(1+$G103)^INT(MAX(0,M$3-$F103)/12)) -> 0 | N103: =IF(OR(N$3<$F103,$E103="",$H103=""),0,$E103*$H103/12*(1+$G103)^INT(MAX(0,N$3-$F103)/12)) -> 0 | O103: =IF(OR(O$3<$F103,$E103="",$H103=""),0,$E103*$H103/12*(1+$G103)^INT(MAX(0,O$3-$F103)/12)) -> 0 | P103: =IF(OR(P$3<$F103,$E103="",$H103=""),0,$E103*$H103/12*(1+$G103)^INT(MAX(0,P$3-$F103)/12)) -> 0 | Q103: =IF(OR(Q$3<$F103,$E103="",$H103=""),0,$E103*$H103/12*(1+$G103)^INT(MAX(0,Q$3-$F103)/12)) -> 0 | R103: =IF(OR(R$3<$F103,$E103="",$H103=""),0,$E103*$H103/12*(1+$G103)^INT(MAX(0,R$3-$F103)/12)) -> 0 | S103: =IF(OR(S$3<$F103,$E103="",$H103=""),0,$E103*$H103/12*(1+$G103)^INT(MAX(0,S$3-$F103)/12)) -> 0 | ... EN103: =IF(OR(EN$3<$F103,$E103="",$H103=""),0,$E103*$H103/12*(1+$G103)^INT(MAX(0,EN$3-$F103)/12)) -> 0 | EP103: =$B103 -> Convenience Store / Laundromat | EQ103: =N($E103) -> 2120 | ER103: =$D103 -> 37 | EV103: =(EV$3>=$ER103)*$EQ103 -> 0 | EW103: =(EW$3>=$ER103)*$EQ103 -> 0 | EX103: =(EX$3>=$ER103)*$EQ103 -> 0 | EY103: =(EY$3>=$ER103)*$EQ103 -> 0 | EZ103: =(EZ$3>=$ER103)*$EQ103 -> 0 | FA103: =(FA$3>=$ER103)*$EQ103 -> 0 | FB103: =(FB$3>=$ER103)*$EQ103 -> 0 | FC103: =(FC$3>=$ER103)*$EQ103 -> 0 | ... JX103: =(JX$3>=$ER103)*$EQ103 -> 2120 | JZ103: =$B103 -> Convenience Store / Laundromat | KA103: =I103 -> 0 | KB103: =F103 -> 40 | KC103: =G103 -> 0.035 | KD103: =K103 -> Annual | KE103: =IF(KD103="",1,IFERROR(MAX(1,INDEX(Data!$H$24:$H$33,MATCH(KD103,Data!$G$24:$G$33,0))),1)) -> 1 | KG103: =IF(OR($KA103="",$KB103="",$KE103=""),0,($KB103<=KG$3)*($KA103/12)*(1+$KC103)^(ROUNDUP(MAX(KG$3-$KB103+1,0)/($KE103*12),0)-1)) -> 0 | KH103: =IF(OR($KA103="",$KB103="",$KE103=""),0,($KB103<=KH$3)*($KA103/12)*(1+$KC103)^(ROUNDUP(MAX(KH$3-$KB103+1,0)/($KE103*12),0)-1)) -> 0 | KI103: =IF(OR($KA103="",$KB103="",$KE103=""),0,($KB103<=KI$3)*($KA103/12)*(1+$KC103)^(ROUNDUP(MAX(KI$3-$KB103+1,0)/($KE103*12),0)-1)) -> 0 | KJ103: =IF(OR($KA103="",$KB103="",$KE103=""),0,($KB103<=KJ$3)*($KA103/12)*(1+$KC103)^(ROUNDUP(MAX(KJ$3-$KB103+1,0)/($KE103*12),0)-1)) -> 0 | KK103: =IF(OR($KA103="",$KB103="",$KE103=""),0,($KB103<=KK$3)*($KA103/12)*(1+$KC103)^(ROUNDUP(MAX(KK$3-$KB103+1,0)/($KE103*12),0)-1)) -> 0 | KL103: =IF(OR($KA103="",$KB103="",$KE103=""),0,($KB103<=KL$3)*($KA103/12)*(1+$KC103)^(ROUNDUP(MAX(KL$3-$KB103+1,0)/($KE103*12),0)-1)) -> 0 | KM103: =IF(OR($KA103="",$KB103="",$KE103=""),0,($KB103<=KM$3)*($KA103/12)*(1+$KC103)^(ROUNDUP(MAX(KM$3-$KB103+1,0)/($KE103*12),0)-1)) -> 0 | KN103: =IF(OR($KA103="",$KB103="",$KE103=""),0,($KB103<=KN$3)*($KA103/12)*(1+$KC103)^(ROUNDUP(MAX(KN$3-$KB103+1,0)/($KE103*12),0)-1)) -> 0 | ... PH103: =IF(OR($KA103="",$KB103="",$KE103=""),0,($KB103<=PH$3)*($KA103/12)*(1+$KC103)^(ROUNDUP(MAX(PH$3-$KB103+1,0)/($KE103*12),0)-1)) -> 0
B104: eBike / eScooter Storage | C104: App Automation | D104: =Timing_Operation_Begin_Month -> 37 | E104: ='URWLD COMPANY INPUTS'!$F$655 -> 150 | F104: =D104+3 -> 40 | G104: =IF('URWLD COMPANY INPUTS'!$F$113="","",'URWLD COMPANY INPUTS'!$F$113) -> 0.035 | H104: ='INPUT REGISTER'!$F$683 -> 0 | I104: =IF(OR(E104="",H104=""),0,E104*H104) -> 0 | K104: Annual | L104: =IF(OR(L$3<$F104,$E104="",$H104=""),0,$E104*$H104/12*(1+$G104)^INT(MAX(0,L$3-$F104)/12)) -> 0 | M104: =IF(OR(M$3<$F104,$E104="",$H104=""),0,$E104*$H104/12*(1+$G104)^INT(MAX(0,M$3-$F104)/12)) -> 0 | N104: =IF(OR(N$3<$F104,$E104="",$H104=""),0,$E104*$H104/12*(1+$G104)^INT(MAX(0,N$3-$F104)/12)) -> 0 | O104: =IF(OR(O$3<$F104,$E104="",$H104=""),0,$E104*$H104/12*(1+$G104)^INT(MAX(0,O$3-$F104)/12)) -> 0 | P104: =IF(OR(P$3<$F104,$E104="",$H104=""),0,$E104*$H104/12*(1+$G104)^INT(MAX(0,P$3-$F104)/12)) -> 0 | Q104: =IF(OR(Q$3<$F104,$E104="",$H104=""),0,$E104*$H104/12*(1+$G104)^INT(MAX(0,Q$3-$F104)/12)) -> 0 | R104: =IF(OR(R$3<$F104,$E104="",$H104=""),0,$E104*$H104/12*(1+$G104)^INT(MAX(0,R$3-$F104)/12)) -> 0 | S104: =IF(OR(S$3<$F104,$E104="",$H104=""),0,$E104*$H104/12*(1+$G104)^INT(MAX(0,S$3-$F104)/12)) -> 0 | ... EN104: =IF(OR(EN$3<$F104,$E104="",$H104=""),0,$E104*$H104/12*(1+$G104)^INT(MAX(0,EN$3-$F104)/12)) -> 0 | EP104: =$B104 -> eBike / eScooter Storage | EQ104: =N($E104) -> 150 | ER104: =$D104 -> 37 | EV104: =(EV$3>=$ER104)*$EQ104 -> 0 | EW104: =(EW$3>=$ER104)*$EQ104 -> 0 | EX104: =(EX$3>=$ER104)*$EQ104 -> 0 | EY104: =(EY$3>=$ER104)*$EQ104 -> 0 | EZ104: =(EZ$3>=$ER104)*$EQ104 -> 0 | FA104: =(FA$3>=$ER104)*$EQ104 -> 0 | FB104: =(FB$3>=$ER104)*$EQ104 -> 0 | FC104: =(FC$3>=$ER104)*$EQ104 -> 0 | ... JX104: =(JX$3>=$ER104)*$EQ104 -> 150 | JZ104: =$B104 -> eBike / eScooter Storage | KA104: =I104 -> 0 | KB104: =F104 -> 40 | KC104: =G104 -> 0.035 | KD104: =K104 -> Annual | KE104: =IF(KD104="",1,IFERROR(MAX(1,INDEX(Data!$H$24:$H$33,MATCH(KD104,Data!$G$24:$G$33,0))),1)) -> 1 | KG104: =IF(OR($KA104="",$KB104="",$KE104=""),0,($KB104<=KG$3)*($KA104/12)*(1+$KC104)^(ROUNDUP(MAX(KG$3-$KB104+1,0)/($KE104*12),0)-1)) -> 0 | KH104: =IF(OR($KA104="",$KB104="",$KE104=""),0,($KB104<=KH$3)*($KA104/12)*(1+$KC104)^(ROUNDUP(MAX(KH$3-$KB104+1,0)/($KE104*12),0)-1)) -> 0 | KI104: =IF(OR($KA104="",$KB104="",$KE104=""),0,($KB104<=KI$3)*($KA104/12)*(1+$KC104)^(ROUNDUP(MAX(KI$3-$KB104+1,0)/($KE104*12),0)-1)) -> 0 | KJ104: =IF(OR($KA104="",$KB104="",$KE104=""),0,($KB104<=KJ$3)*($KA104/12)*(1+$KC104)^(ROUNDUP(MAX(KJ$3-$KB104+1,0)/($KE104*12),0)-1)) -> 0 | KK104: =IF(OR($KA104="",$KB104="",$KE104=""),0,($KB104<=KK$3)*($KA104/12)*(1+$KC104)^(ROUNDUP(MAX(KK$3-$KB104+1,0)/($KE104*12),0)-1)) -> 0 | KL104: =IF(OR($KA104="",$KB104="",$KE104=""),0,($KB104<=KL$3)*($KA104/12)*(1+$KC104)^(ROUNDUP(MAX(KL$3-$KB104+1,0)/($KE104*12),0)-1)) -> 0 | KM104: =IF(OR($KA104="",$KB104="",$KE104=""),0,($KB104<=KM$3)*($KA104/12)*(1+$KC104)^(ROUNDUP(MAX(KM$3-$KB104+1,0)/($KE104*12),0)-1)) -> 0 | KN104: =IF(OR($KA104="",$KB104="",$KE104=""),0,($KB104<=KN$3)*($KA104/12)*(1+$KC104)^(ROUNDUP(MAX(KN$3-$KB104+1,0)/($KE104*12),0)-1)) -> 0 | ... PH104: =IF(OR($KA104="",$KB104="",$KE104=""),0,($KB104<=PH$3)*($KA104/12)*(1+$KC104)^(ROUNDUP(MAX(PH$3-$KB104+1,0)/($KE104*12),0)-1)) -> 0
B105: TOTAL RENTAL INCOME | E105: =SUM(E93:E104) -> 78470.38 | F105: =MIN(F93:F104) -> 22 | G105: =SUMPRODUCT(G93:G104,I93:I104)/I105 -> 0.035 | H105: =I105/E105 -> 194.72316 | I105: =SUM(I93:I104) -> 15280000 | L105: =SUM(L93:L104) -> 0 | M105: =SUM(M93:M104) -> 0 | N105: =SUM(N93:N104) -> 0 | O105: =SUM(O93:O104) -> 0 | P105: =SUM(P93:P104) -> 0 | Q105: =SUM(Q93:Q104) -> 0 | R105: =SUM(R93:R104) -> 0 | S105: =SUM(S93:S104) -> 0 | ... EN105: =SUM(EN93:EN104) -> 1709766.8 | EV105: =SUM(EV93:EV104) -> 0 | EW105: =SUM(EW93:EW104) -> 0 | EX105: =SUM(EX93:EX104) -> 0 | EY105: =SUM(EY93:EY104) -> 0 | EZ105: =SUM(EZ93:EZ104) -> 0 | FA105: =SUM(FA93:FA104) -> 0 | FB105: =SUM(FB93:FB104) -> 0 | FC105: =SUM(FC93:FC104) -> 0 | ... JX105: =SUM(JX93:JX104) -> 78470.38 | JZ105: Total Rental Income | KG105: =SUM(KG93:KG104) -> 0 | KH105: =SUM(KH93:KH104) -> 0 | KI105: =SUM(KI93:KI104) -> 0 | KJ105: =SUM(KJ93:KJ104) -> 0 | KK105: =SUM(KK93:KK104) -> 0 | KL105: =SUM(KL93:KL104) -> 0 | KM105: =SUM(KM93:KM104) -> 0 | KN105: =SUM(KN93:KN104) -> 0 | ... PH105: =SUM(PH93:PH104) -> 1709766.8
B107: RECOVERY INCOME | C107: STATUS | D107: TENANT TYPE | E107: RECOVERY START | F107: RECOVERY % | G107: PRO RATA SHARE | H107: ="REC./"&Unit_Type&"/YR" -> REC./M2/YR | I107: AMOUNT/YR
B108: =C93 -> URWLD | C108: Signed LOI | D108: Anchor | E108: =+F93 -> 22 | F108: 1 | G108: =IFERROR(E93/Units_Ind,0) -> 0.27398873 | H108: =IFERROR(I108/E93,0) -> 41.904711 | I108: =F108*G108*$I$138 -> 900951.29 | L108: =IF(L$3<$E108,0,$G108*$F108*L$138) -> 0 | M108: =IF(M$3<$E108,0,$G108*$F108*M$138) -> 0 | N108: =IF(N$3<$E108,0,$G108*$F108*N$138) -> 0 | O108: =IF(O$3<$E108,0,$G108*$F108*O$138) -> 0 | P108: =IF(P$3<$E108,0,$G108*$F108*P$138) -> 0 | Q108: =IF(Q$3<$E108,0,$G108*$F108*Q$138) -> 0 | R108: =IF(R$3<$E108,0,$G108*$F108*R$138) -> 0 | S108: =IF(S$3<$E108,0,$G108*$F108*S$138) -> 0 | ... EN108: =IF(EN$3<$E108,0,$G108*$F108*EN$138) -> 89245.664
B109: =C94 -> Macquarie/IGLU; Brookfield/Journal | C109: Discussion | D109: Inline | E109: =+F94 -> 25 | F109: 1 | G109: =IFERROR(E94/Units_Ind,0) -> 0.25487324 | H109: =IFERROR(I109/E94,0) -> 41.904711 | I109: =F109*G109*$I$138 -> 838094.23 | L109: =IF(L$3<$E109,0,$G109*$F109*L$138) -> 0 | M109: =IF(M$3<$E109,0,$G109*$F109*M$138) -> 0 | N109: =IF(N$3<$E109,0,$G109*$F109*N$138) -> 0 | O109: =IF(O$3<$E109,0,$G109*$F109*O$138) -> 0 | P109: =IF(P$3<$E109,0,$G109*$F109*P$138) -> 0 | Q109: =IF(Q$3<$E109,0,$G109*$F109*Q$138) -> 0 | R109: =IF(R$3<$E109,0,$G109*$F109*R$138) -> 0 | S109: =IF(S$3<$E109,0,$G109*$F109*S$138) -> 0 | ... EN109: =IF(EN$3<$E109,0,$G109*$F109*EN$138) -> 83019.222
B110: =C95 -> LiveHouse | C110: Discussion | D110: Inline | E110: =+F95 -> 25 | F110: 1 | G110: =IFERROR(E95/Units_Ind,0) -> 0.082833803 | H110: =IFERROR(I110/E95,0) -> 41.904711 | I110: =F110*G110*$I$138 -> 272380.62 | L110: =IF(L$3<$E110,0,$G110*$F110*L$138) -> 0 | M110: =IF(M$3<$E110,0,$G110*$F110*M$138) -> 0 | N110: =IF(N$3<$E110,0,$G110*$F110*N$138) -> 0 | O110: =IF(O$3<$E110,0,$G110*$F110*O$138) -> 0 | P110: =IF(P$3<$E110,0,$G110*$F110*P$138) -> 0 | Q110: =IF(Q$3<$E110,0,$G110*$F110*Q$138) -> 0 | R110: =IF(R$3<$E110,0,$G110*$F110*R$138) -> 0 | S110: =IF(S$3<$E110,0,$G110*$F110*S$138) -> 0 | ... EN110: =IF(EN$3<$E110,0,$G110*$F110*EN$138) -> 26981.247
B111: =C96 -> Food Truck Park | C111: Spec | D111: Inline | E111: =+F96 -> 28 | F111: 1 | G111: =IFERROR(E96/Units_Ind,0) -> 0.0019115493 | H111: =IFERROR(I111/E96,0) -> 41.904711 | I111: =F111*G111*$I$138 -> 6285.7067 | L111: =IF(L$3<$E111,0,$G111*$F111*L$138) -> 0 | M111: =IF(M$3<$E111,0,$G111*$F111*M$138) -> 0 | N111: =IF(N$3<$E111,0,$G111*$F111*N$138) -> 0 | O111: =IF(O$3<$E111,0,$G111*$F111*O$138) -> 0 | P111: =IF(P$3<$E111,0,$G111*$F111*P$138) -> 0 | Q111: =IF(Q$3<$E111,0,$G111*$F111*Q$138) -> 0 | R111: =IF(R$3<$E111,0,$G111*$F111*R$138) -> 0 | S111: =IF(S$3<$E111,0,$G111*$F111*S$138) -> 0 | ... EN111: =IF(EN$3<$E111,0,$G111*$F111*EN$138) -> 622.64417
B112: =C97 -> Genesis Health & Fitness | C112: Discussion | D112: Inline | E112: =+F97 -> 28 | F112: 1 | G112: =IFERROR(E97/Units_Ind,0) -> 0.050974648 | H112: =IFERROR(I112/E97,0) -> 41.904711 | I112: =F112*G112*$I$138 -> 167618.85 | L112: =IF(L$3<$E112,0,$G112*$F112*L$138) -> 0 | M112: =IF(M$3<$E112,0,$G112*$F112*M$138) -> 0 | N112: =IF(N$3<$E112,0,$G112*$F112*N$138) -> 0 | O112: =IF(O$3<$E112,0,$G112*$F112*O$138) -> 0 | P112: =IF(P$3<$E112,0,$G112*$F112*P$138) -> 0 | Q112: =IF(Q$3<$E112,0,$G112*$F112*Q$138) -> 0 | R112: =IF(R$3<$E112,0,$G112*$F112*R$138) -> 0 | S112: =IF(S$3<$E112,0,$G112*$F112*S$138) -> 0 | ... EN112: =IF(EN$3<$E112,0,$G112*$F112*EN$138) -> 16603.844
B113: =C98 -> Secure (Preferred) | C113: Discussion | D113: Inline | E113: =+F98 -> 31 | F113: 1 | G113: =IFERROR(E98/Units_Ind,0) -> 0.24850625 | H113: =IFERROR(I113/E98,0) -> 41.904711 | I113: =F113*G113*$I$138 -> 817157.79 | L113: =IF(L$3<$E113,0,$G113*$F113*L$138) -> 0 | M113: =IF(M$3<$E113,0,$G113*$F113*M$138) -> 0 | N113: =IF(N$3<$E113,0,$G113*$F113*N$138) -> 0 | O113: =IF(O$3<$E113,0,$G113*$F113*O$138) -> 0 | P113: =IF(P$3<$E113,0,$G113*$F113*P$138) -> 0 | Q113: =IF(Q$3<$E113,0,$G113*$F113*Q$138) -> 0 | R113: =IF(R$3<$E113,0,$G113*$F113*R$138) -> 0 | S113: =IF(S$3<$E113,0,$G113*$F113*S$138) -> 0 | ... EN113: =IF(EN$3<$E113,0,$G113*$F113*EN$138) -> 80945.319
B114: =C99 -> Snowtunnel | C114: Discussion | D114: Inline | E114: =+F99 -> 31 | F114: 1 | G114: =IFERROR(E99/Units_Ind,0) -> 0.048425916 | H114: =IFERROR(I114/E99,0) -> 41.904711 | I114: =F114*G114*$I$138 -> 159237.9 | L114: =IF(L$3<$E114,0,$G114*$F114*L$138) -> 0 | M114: =IF(M$3<$E114,0,$G114*$F114*M$138) -> 0 | N114: =IF(N$3<$E114,0,$G114*$F114*N$138) -> 0 | O114: =IF(O$3<$E114,0,$G114*$F114*O$138) -> 0 | P114: =IF(P$3<$E114,0,$G114*$F114*P$138) -> 0 | Q114: =IF(Q$3<$E114,0,$G114*$F114*Q$138) -> 0 | R114: =IF(R$3<$E114,0,$G114*$F114*R$138) -> 0 | S114: =IF(S$3<$E114,0,$G114*$F114*S$138) -> 0 | ... EN114: =IF(EN$3<$E114,0,$G114*$F114*EN$138) -> 15773.652
...

Sheet Annual Cash Flow
B2: =Underwriting!B2 -> THE BEND ENTERTAINMENT PRECINCT | R2: =UPPER(Underwriting!I2) -> MAYABAY ACTIVE (MELBOURNE) PTY LTD
B3: =Underwriting!E11&", "&Underwriting!I10 -> Port Melbourne, VIC | R3: =Summary!S3 -> ANALYSIS START - JUL 2026
B4: ANNUAL CASH FLOW | H4: =IF(H5="","",IF(EOMONTH(G6,12)>H6,"EXIT","")) | I4: =IF(I5="","",IF(EOMONTH(H6,12)>I6,"EXIT","")) | J4: =IF(J5="","",IF(EOMONTH(I6,12)>J6,"EXIT","")) | K4: =IF(K5="","",IF(EOMONTH(J6,12)>K6,"EXIT","")) | L4: =IF(L5="","",IF(EOMONTH(K6,12)>L6,"EXIT","")) | M4: =IF(M5="","",IF(EOMONTH(L6,12)>M6,"EXIT","")) -> EXIT | N4: =IF(N5="","",IF(EOMONTH(M6,12)>N6,"EXIT","")) | O4: =IF(O5="","",IF(EOMONTH(N6,12)>O6,"EXIT","")) | ... R4: =IF(R5="","",IF(EOMONTH(Q6,12)>R6,"EXIT",""))
F5: Analysis Year | G5: 0 | H5: =IF(OR(G5="",G5=MAX($G$46:$EI$46)),"",G5+1) -> 1 | I5: =IF(OR(H5="",H5=MAX($G$46:$EI$46)),"",H5+1) -> 2 | J5: =IF(OR(I5="",I5=MAX($G$46:$EI$46)),"",I5+1) -> 3 | K5: =IF(OR(J5="",J5=MAX($G$46:$EI$46)),"",J5+1) -> 4 | L5: =IF(OR(K5="",K5=MAX($G$46:$EI$46)),"",K5+1) -> 5 | M5: =IF(OR(L5="",L5=MAX($G$46:$EI$46)),"",L5+1) -> 6 | N5: =IF(OR(M5="",M5=MAX($G$46:$EI$46)),"",M5+1) | O5: =IF(OR(N5="",N5=MAX($G$46:$EI$46)),"",N5+1) | ... R5: =IF(OR(Q5="",Q5=MAX($G$46:$EI$46)),"",Q5+1)
F6: Period Ending | G6: =Underwriting!$M$195 -> 46234 | H6: =EOMONTH(G6,12) -> 46599 | I6: =EOMONTH(H6,12) -> 46965 | J6: =EOMONTH(I6,12) -> 47330 | K6: =EOMONTH(J6,12) -> 47695 | L6: =EOMONTH(K6,12) -> 48060 | M6: =MAX(Underwriting!$M$195:$BU$195) -> 48060 | N6: =IF(N5="","",IF(O5="",MAX(Underwriting!$L$195:$EN$195),EOMONTH(M6,12))) | O6: =IF(O5="","",IF(P5="",MAX(Underwriting!$L$195:$EN$195),EOMONTH(N6,12))) | P6: =IF(P5="","",IF(Q5="",MAX(Underwriting!$L$195:$EN$195),EOMONTH(O6,12))) | Q6: =IF(Q5="","",IF(R5="",MAX(Underwriting!$L$195:$EN$195),EOMONTH(P6,12))) | R6: =IF(R5="","",IF(S5="",MAX(Underwriting!$L$195:$EN$195),EOMONTH(Q6,12)))
B7: ANNUAL DEVELOPMENT CASH FLOWS
B8: Land Costs | G8: =IF(G$5="","",SUMIF($G$46:$EI$46,G$5,$G48:$EI48)) -> 92320000 | H8: =IF(H$5="","",SUMIF($G$46:$EI$46,H$5,$G48:$EI48)) -> 0 | I8: =IF(I$5="","",SUMIF($G$46:$EI$46,I$5,$G48:$EI48)) -> 0 | J8: =IF(J$5="","",SUMIF($G$46:$EI$46,J$5,$G48:$EI48)) -> 0 | K8: =IF(K$5="","",SUMIF($G$46:$EI$46,K$5,$G48:$EI48)) -> 0 | L8: =IF(L$5="","",SUMIF($G$46:$EI$46,L$5,$G48:$EI48)) -> 0 | M8: =IF(M$5="","",SUMIF($G$46:$EI$46,M$5,$G48:$EI48)) -> 0 | N8: =IF(N$5="","",SUMIF($G$46:$EI$46,N$5,$G48:$EI48)) | ... R8: =IF(R$5="","",SUMIF($G$46:$EI$46,R$5,$G48:$EI48))
B9: Hard Costs / Development Adjustments | G9: =IF(G$5="","",SUMIF($G$46:$EI$46,G$5,$G49:$EI49)) -> 697714.09 | H9: =IF(H$5="","",SUMIF($G$46:$EI$46,H$5,$G49:$EI49)) -> 67738142 | I9: =IF(I$5="","",SUMIF($G$46:$EI$46,I$5,$G49:$EI49)) -> 2.3388212e+08 | J9: =IF(J$5="","",SUMIF($G$46:$EI$46,J$5,$G49:$EI49)) -> 54218654 | K9: =IF(K$5="","",SUMIF($G$46:$EI$46,K$5,$G49:$EI49)) -> 0 | L9: =IF(L$5="","",SUMIF($G$46:$EI$46,L$5,$G49:$EI49)) -> 0 | M9: =IF(M$5="","",SUMIF($G$46:$EI$46,M$5,$G49:$EI49)) -> 0 | N9: =IF(N$5="","",SUMIF($G$46:$EI$46,N$5,$G49:$EI49)) | ... R9: =IF(R$5="","",SUMIF($G$46:$EI$46,R$5,$G49:$EI49))
B10: Soft Costs | G10: =IF(G$5="","",SUMIF($G$46:$EI$46,G$5,$G50:$EI50)) -> 0 | H10: =IF(H$5="","",SUMIF($G$46:$EI$46,H$5,$G50:$EI50)) -> 0 | I10: =IF(I$5="","",SUMIF($G$46:$EI$46,I$5,$G50:$EI50)) -> 0 | J10: =IF(J$5="","",SUMIF($G$46:$EI$46,J$5,$G50:$EI50)) -> 0 | K10: =IF(K$5="","",SUMIF($G$46:$EI$46,K$5,$G50:$EI50)) -> 0 | L10: =IF(L$5="","",SUMIF($G$46:$EI$46,L$5,$G50:$EI50)) -> 0 | M10: =IF(M$5="","",SUMIF($G$46:$EI$46,M$5,$G50:$EI50)) -> 0 | N10: =IF(N$5="","",SUMIF($G$46:$EI$46,N$5,$G50:$EI50)) | ... R10: =IF(R$5="","",SUMIF($G$46:$EI$46,R$5,$G50:$EI50))
B11: TOTAL PROJECT COST BEFORE FINANCING | G11: =IF(G$5="","",SUM(G8:G10)) -> 93017714 | H11: =IF(H$5="","",SUM(H8:H10)) -> 67738142 | I11: =IF(I$5="","",SUM(I8:I10)) -> 2.3388212e+08 | J11: =IF(J$5="","",SUM(J8:J10)) -> 54218654 | K11: =IF(K$5="","",SUM(K8:K10)) -> 0 | L11: =IF(L$5="","",SUM(L8:L10)) -> 0 | M11: =IF(M$5="","",SUM(M8:M10)) -> 0 | N11: =IF(N$5="","",SUM(N8:N10)) | ... R11: =IF(R$5="","",SUM(R8:R10))
B13: Carry Costs | G13: =IF(G$5="","",SUMIF($G$46:$EI$46,G$5,$G53:$EI53)) -> 0 | H13: =IF(H$5="","",SUMIF($G$46:$EI$46,H$5,$G53:$EI53)) -> 0 | I13: =IF(I$5="","",SUMIF($G$46:$EI$46,I$5,$G53:$EI53)) -> 0 | J13: =IF(J$5="","",SUMIF($G$46:$EI$46,J$5,$G53:$EI53)) -> 0 | K13: =IF(K$5="","",SUMIF($G$46:$EI$46,K$5,$G53:$EI53)) -> 0 | L13: =IF(L$5="","",SUMIF($G$46:$EI$46,L$5,$G53:$EI53)) -> 0 | M13: =IF(M$5="","",SUMIF($G$46:$EI$46,M$5,$G53:$EI53)) -> 0 | N13: =IF(N$5="","",SUMIF($G$46:$EI$46,N$5,$G53:$EI53)) | ... R13: =IF(R$5="","",SUMIF($G$46:$EI$46,R$5,$G53:$EI53))
B15: TOTAL PROJECT COST | G15: =IF(G$5="","",SUMIF($G$46:$EI$46,G$5,$G55:$EI55)) -> 93017714 | H15: =IF(H$5="","",SUMIF($G$46:$EI$46,H$5,$G55:$EI55)) -> 67738142 | I15: =IF(I$5="","",SUMIF($G$46:$EI$46,I$5,$G55:$EI55)) -> 2.3388212e+08 | J15: =IF(J$5="","",SUMIF($G$46:$EI$46,J$5,$G55:$EI55)) -> 54218654 | K15: =IF(K$5="","",SUMIF($G$46:$EI$46,K$5,$G55:$EI55)) -> 0 | L15: =IF(L$5="","",SUMIF($G$46:$EI$46,L$5,$G55:$EI55)) -> 0 | M15: =IF(M$5="","",SUMIF($G$46:$EI$46,M$5,$G55:$EI55)) -> 0 | N15: =IF(N$5="","",SUMIF($G$46:$EI$46,N$5,$G55:$EI55)) | ... R15: =IF(R$5="","",SUMIF($G$46:$EI$46,R$5,$G55:$EI55))
B16: FUNDING TIMING / ELIGIBILITY BRIDGE | G16: =IF(G$5="","",SUMIF($G$46:$EI$46,G$5,$G$59:$EI$59)) -> 0 | H16: =IF(H$5="","",SUMIF($G$46:$EI$46,H$5,$G$59:$EI$59)) -> 2008935.2 | I16: =IF(I$5="","",SUMIF($G$46:$EI$46,I$5,$G$59:$EI$59)) -> 0 | J16: =IF(J$5="","",SUMIF($G$46:$EI$46,J$5,$G$59:$EI$59)) -> 0 | K16: =IF(K$5="","",SUMIF($G$46:$EI$46,K$5,$G$59:$EI$59)) -> 0 | L16: =IF(L$5="","",SUMIF($G$46:$EI$46,L$5,$G$59:$EI$59)) -> 0 | M16: =IF(M$5="","",SUMIF($G$46:$EI$46,M$5,$G$59:$EI$59)) -> 0 | N16: =IF(N$5="","",SUMIF($G$46:$EI$46,N$5,$G$59:$EI$59)) | ... R16: =IF(R$5="","",SUMIF($G$46:$EI$46,R$5,$G$59:$EI$59))
B17: SOURCES | G17: =IF(G$5="","",SUMIF($G$46:$EI$46,G$5,$G57:$EI57)) -> 93017714 | H17: =IF(H$5="","",SUMIF($G$46:$EI$46,H$5,$G57:$EI57)) -> 69747078 | I17: =IF(I$5="","",SUMIF($G$46:$EI$46,I$5,$G57:$EI57)) -> 2.3388212e+08 | J17: =IF(J$5="","",SUMIF($G$46:$EI$46,J$5,$G57:$EI57)) -> 54218654 | K17: =IF(K$5="","",SUMIF($G$46:$EI$46,K$5,$G57:$EI57)) -> 0 | L17: =IF(L$5="","",SUMIF($G$46:$EI$46,L$5,$G57:$EI57)) -> 0 | M17: =IF(M$5="","",SUMIF($G$46:$EI$46,M$5,$G57:$EI57)) -> 0 | N17: =IF(N$5="","",SUMIF($G$46:$EI$46,N$5,$G57:$EI57)) | ... R17: =IF(R$5="","",SUMIF($G$46:$EI$46,R$5,$G57:$EI57))
B18: USES | G18: =IF(G$5="","",SUMIF($G$46:$EI$46,G$5,$G58:$EI58)) -> 93017714 | H18: =IF(H$5="","",SUMIF($G$46:$EI$46,H$5,$G58:$EI58)) -> 67738142 | I18: =IF(I$5="","",SUMIF($G$46:$EI$46,I$5,$G58:$EI58)) -> 2.3388212e+08 | J18: =IF(J$5="","",SUMIF($G$46:$EI$46,J$5,$G58:$EI58)) -> 54218654 | K18: =IF(K$5="","",SUMIF($G$46:$EI$46,K$5,$G58:$EI58)) -> 0 | L18: =IF(L$5="","",SUMIF($G$46:$EI$46,L$5,$G58:$EI58)) -> 0 | M18: =IF(M$5="","",SUMIF($G$46:$EI$46,M$5,$G58:$EI58)) -> 0 | N18: =IF(N$5="","",SUMIF($G$46:$EI$46,N$5,$G58:$EI58)) | ... R18: =IF(R$5="","",SUMIF($G$46:$EI$46,R$5,$G58:$EI58))
B19: SOURCES LESS USES LESS BRIDGE (CHECK) | G19: =IF(G$5="","",G17-G18-G16) -> 0 | H19: =IF(H$5="","",H17-H18-H16) -> -7.4505806e-09 | I19: =IF(I$5="","",I17-I18-I16) -> 0 | J19: =IF(J$5="","",J17-J18-J16) -> 0 | K19: =IF(K$5="","",K17-K18-K16) -> 0 | L19: =IF(L$5="","",L17-L18-L16) -> 0 | M19: =IF(M$5="","",M17-M18-M16) -> 0 | N19: =IF(N$5="","",N17-N18-N16) | ... R19: =IF(R$5="","",R17-R18-R16)
B20: ANNUAL OPERATING CASH FLOWS
B21: =+B61 -> Rental Income | G21: =IF(G$5="","",SUMIF($G$46:$EI$46,G$5,$G61:$EI61)) -> 0 | H21: =IF(H$5="","",SUMIF($G$46:$EI$46,H$5,$G61:$EI61)) -> 0 | I21: =IF(I$5="","",SUMIF($G$46:$EI$46,I$5,$G61:$EI61)) -> 2150000 | J21: =IF(J$5="","",SUMIF($G$46:$EI$46,J$5,$G61:$EI61)) -> 13815250 | K21: =IF(K$5="","",SUMIF($G$46:$EI$46,K$5,$G61:$EI61)) -> 15838784 | L21: =IF(L$5="","",SUMIF($G$46:$EI$46,L$5,$G61:$EI61)) -> 16393141 | M21: =IF(M$5="","",SUMIF($G$46:$EI$46,M$5,$G61:$EI61)) -> 1399019.8 | N21: =IF(N$5="","",SUMIF($G$46:$EI$46,N$5,$G61:$EI61)) | ... R21: =IF(R$5="","",SUMIF($G$46:$EI$46,R$5,$G61:$EI61))
B22: =+B62 -> Recovery Income | G22: =IF(G$5="","",SUMIF($G$46:$EI$46,G$5,$G62:$EI62)) -> 0 | H22: =IF(H$5="","",SUMIF($G$46:$EI$46,H$5,$G62:$EI62)) -> 0 | I22: =IF(I$5="","",SUMIF($G$46:$EI$46,I$5,$G62:$EI62)) -> 0 | J22: =IF(J$5="","",SUMIF($G$46:$EI$46,J$5,$G62:$EI62)) -> 0 | K22: =IF(K$5="","",SUMIF($G$46:$EI$46,K$5,$G62:$EI62)) -> 1505146 | L22: =IF(L$5="","",SUMIF($G$46:$EI$46,L$5,$G62:$EI62)) -> 3370485.6 | M22: =IF(M$5="","",SUMIF($G$46:$EI$46,M$5,$G62:$EI62)) -> 287895.64 | N22: =IF(N$5="","",SUMIF($G$46:$EI$46,N$5,$G62:$EI62)) | ... R22: =IF(R$5="","",SUMIF($G$46:$EI$46,R$5,$G62:$EI62))
B23: =+B63 -> Other Income | G23: =IF(G$5="","",SUMIF($G$46:$EI$46,G$5,$G63:$EI63)) -> 0 | H23: =IF(H$5="","",SUMIF($G$46:$EI$46,H$5,$G63:$EI63)) -> 0 | I23: =IF(I$5="","",SUMIF($G$46:$EI$46,I$5,$G63:$EI63)) -> 0 | J23: =IF(J$5="","",SUMIF($G$46:$EI$46,J$5,$G63:$EI63)) -> 0 | K23: =IF(K$5="","",SUMIF($G$46:$EI$46,K$5,$G63:$EI63)) -> 14025832 | L23: =IF(L$5="","",SUMIF($G$46:$EI$46,L$5,$G63:$EI63)) -> 31018470 | M23: =IF(M$5="","",SUMIF($G$46:$EI$46,M$5,$G63:$EI63)) -> 2649494.3 | N23: =IF(N$5="","",SUMIF($G$46:$EI$46,N$5,$G63:$EI63)) | ... R23: =IF(R$5="","",SUMIF($G$46:$EI$46,R$5,$G63:$EI63))
B24: TOTAL POTENTIAL INCOME | G24: =IF(G$5="","",SUM(G21:G23)) -> 0 | H24: =IF(H$5="","",SUM(H21:H23)) -> 0 | I24: =IF(I$5="","",SUM(I21:I23)) -> 2150000 | J24: =IF(J$5="","",SUM(J21:J23)) -> 13815250 | K24: =IF(K$5="","",SUM(K21:K23)) -> 31369762 | L24: =IF(L$5="","",SUM(L21:L23)) -> 50782097 | M24: =IF(M$5="","",SUM(M21:M23)) -> 4336409.8 | N24: =IF(N$5="","",SUM(N21:N23)) | ... R24: =IF(R$5="","",SUM(R21:R23))
B25: - General Vacancy and Credit Loss | G25: =IF(G$5="","",SUMIF($G$46:$EI$46,G$5,$G65:$EI65)) -> 0 | H25: =IF(H$5="","",SUMIF($G$46:$EI$46,H$5,$G65:$EI65)) -> 0 | I25: =IF(I$5="","",SUMIF($G$46:$EI$46,I$5,$G65:$EI65)) -> 0 | J25: =IF(J$5="","",SUMIF($G$46:$EI$46,J$5,$G65:$EI65)) -> 0 | K25: =IF(K$5="","",SUMIF($G$46:$EI$46,K$5,$G65:$EI65)) -> 0 | L25: =IF(L$5="","",SUMIF($G$46:$EI$46,L$5,$G65:$EI65)) -> 0 | M25: =IF(M$5="","",SUMIF($G$46:$EI$46,M$5,$G65:$EI65)) -> 0 | N25: =IF(N$5="","",SUMIF($G$46:$EI$46,N$5,$G65:$EI65)) | ... R25: =IF(R$5="","",SUMIF($G$46:$EI$46,R$5,$G65:$EI65))
B26: EFFECTIVE GROSS REVENUE | G26: =IF(G$5="","",SUM(G24:G25)) -> 0 | H26: =IF(H$5="","",SUM(H24:H25)) -> 0 | I26: =IF(I$5="","",SUM(I24:I25)) -> 2150000 | J26: =IF(J$5="","",SUM(J24:J25)) -> 13815250 | K26: =IF(K$5="","",SUM(K24:K25)) -> 31369762 | L26: =IF(L$5="","",SUM(L24:L25)) -> 50782097 | M26: =IF(M$5="","",SUM(M24:M25)) -> 4336409.8 | N26: =IF(N$5="","",SUM(N24:N25)) | ... R26: =IF(R$5="","",SUM(R24:R25))
B28: OPERATING EXPENSES
B29: =+B69 -> Source operating costs | G29: =IF(G$5="","",SUMIF($G$46:$EI$46,G$5,$G69:$EI69)) -> 0 | H29: =IF(H$5="","",SUMIF($G$46:$EI$46,H$5,$G69:$EI69)) -> 0 | I29: =IF(I$5="","",SUMIF($G$46:$EI$46,I$5,$G69:$EI69)) -> 0 | J29: =IF(J$5="","",SUMIF($G$46:$EI$46,J$5,$G69:$EI69)) -> 0 | K29: =IF(K$5="","",SUMIF($G$46:$EI$46,K$5,$G69:$EI69)) -> 1507127.7 | L29: =IF(L$5="","",SUMIF($G$46:$EI$46,L$5,$G69:$EI69)) -> 3370485.6 | M29: =IF(M$5="","",SUMIF($G$46:$EI$46,M$5,$G69:$EI69)) -> 287895.64 | N29: =IF(N$5="","",SUMIF($G$46:$EI$46,N$5,$G69:$EI69)) | ... R29: =IF(R$5="","",SUMIF($G$46:$EI$46,R$5,$G69:$EI69))
B30: =+B70 -> Management fee included in source operating costs | G30: =IF(G$5="","",SUMIF($G$46:$EI$46,G$5,$G70:$EI70)) -> 0 | H30: =IF(H$5="","",SUMIF($G$46:$EI$46,H$5,$G70:$EI70)) -> 0 | I30: =IF(I$5="","",SUMIF($G$46:$EI$46,I$5,$G70:$EI70)) -> 0 | J30: =IF(J$5="","",SUMIF($G$46:$EI$46,J$5,$G70:$EI70)) -> 0 | K30: =IF(K$5="","",SUMIF($G$46:$EI$46,K$5,$G70:$EI70)) -> 0 | L30: =IF(L$5="","",SUMIF($G$46:$EI$46,L$5,$G70:$EI70)) -> 0 | M30: =IF(M$5="","",SUMIF($G$46:$EI$46,M$5,$G70:$EI70)) -> 0 | N30: =IF(N$5="","",SUMIF($G$46:$EI$46,N$5,$G70:$EI70)) | ... R30: =IF(R$5="","",SUMIF($G$46:$EI$46,R$5,$G70:$EI70))
B31: =+B71 -> Other operating expenses included in source operating costs | G31: =IF(G$5="","",SUMIF($G$46:$EI$46,G$5,$G71:$EI71)) -> 0 | H31: =IF(H$5="","",SUMIF($G$46:$EI$46,H$5,$G71:$EI71)) -> 0 | I31: =IF(I$5="","",SUMIF($G$46:$EI$46,I$5,$G71:$EI71)) -> 0 | J31: =IF(J$5="","",SUMIF($G$46:$EI$46,J$5,$G71:$EI71)) -> 0 | K31: =IF(K$5="","",SUMIF($G$46:$EI$46,K$5,$G71:$EI71)) -> 0 | L31: =IF(L$5="","",SUMIF($G$46:$EI$46,L$5,$G71:$EI71)) -> 0 | M31: =IF(M$5="","",SUMIF($G$46:$EI$46,M$5,$G71:$EI71)) -> 0 | N31: =IF(N$5="","",SUMIF($G$46:$EI$46,N$5,$G71:$EI71)) | ... R31: =IF(R$5="","",SUMIF($G$46:$EI$46,R$5,$G71:$EI71))
B32: =+B72 -> Property taxes / insurance included in source operating costs | G32: =IF(G$5="","",SUMIF($G$46:$EI$46,G$5,$G72:$EI72)) -> 0 | H32: =IF(H$5="","",SUMIF($G$46:$EI$46,H$5,$G72:$EI72)) -> 0 | I32: =IF(I$5="","",SUMIF($G$46:$EI$46,I$5,$G72:$EI72)) -> 0 | J32: =IF(J$5="","",SUMIF($G$46:$EI$46,J$5,$G72:$EI72)) -> 0 | K32: =IF(K$5="","",SUMIF($G$46:$EI$46,K$5,$G72:$EI72)) -> 0 | L32: =IF(L$5="","",SUMIF($G$46:$EI$46,L$5,$G72:$EI72)) -> 0 | M32: =IF(M$5="","",SUMIF($G$46:$EI$46,M$5,$G72:$EI72)) -> 0 | N32: =IF(N$5="","",SUMIF($G$46:$EI$46,N$5,$G72:$EI72)) | ... R32: =IF(R$5="","",SUMIF($G$46:$EI$46,R$5,$G72:$EI72))
B33: TOTAL OPERATING EXPENSES | G33: =IF(G$5="","",SUM(G29:G32)) -> 0 | H33: =IF(H$5="","",SUM(H29:H32)) -> 0 | I33: =IF(I$5="","",SUM(I29:I32)) -> 0 | J33: =IF(J$5="","",SUM(J29:J32)) -> 0 | K33: =IF(K$5="","",SUM(K29:K32)) -> 1507127.7 | L33: =IF(L$5="","",SUM(L29:L32)) -> 3370485.6 | M33: =IF(M$5="","",SUM(M29:M32)) -> 287895.64 | N33: =IF(N$5="","",SUM(N29:N32)) | ... R33: =IF(R$5="","",SUM(R29:R32))
B35: NET OPERATING INCOME | G35: =IF(G$5="","",G26-G33) -> 0 | H35: =IF(H$5="","",H26-H33) -> 0 | I35: =IF(I$5="","",I26-I33) -> 2150000 | J35: =IF(J$5="","",J26-J33) -> 13815250 | K35: =IF(K$5="","",K26-K33) -> 29862634 | L35: =IF(L$5="","",L26-L33) -> 47411611 | M35: =IF(M$5="","",M26-M33) -> 4048514.1 | N35: =IF(N$5="","",N26-N33) | ... R35: =IF(R$5="","",R26-R33)
B37: CAPITAL EXPENDITURES | G37: =IF(G$5="","",SUMIF($G$46:$EI$46,G$5,$G77:$EI77)) -> 0 | H37: =IF(H$5="","",SUMIF($G$46:$EI$46,H$5,$G77:$EI77)) -> 0 | I37: =IF(I$5="","",SUMIF($G$46:$EI$46,I$5,$G77:$EI77)) -> 0 | J37: =IF(J$5="","",SUMIF($G$46:$EI$46,J$5,$G77:$EI77)) -> 0 | K37: =IF(K$5="","",SUMIF($G$46:$EI$46,K$5,$G77:$EI77)) -> 0 | L37: =IF(L$5="","",SUMIF($G$46:$EI$46,L$5,$G77:$EI77)) -> 0 | M37: =IF(M$5="","",SUMIF($G$46:$EI$46,M$5,$G77:$EI77)) -> 0 | N37: =IF(N$5="","",SUMIF($G$46:$EI$46,N$5,$G77:$EI77)) | ... R37: =IF(R$5="","",SUMIF($G$46:$EI$46,R$5,$G77:$EI77))
B39: CASH FLOW FROM OPERATIONS | G39: =IF(G$5="","",G35-G37) -> 0 | H39: =IF(H$5="","",H35-H37) -> 0 | I39: =IF(I$5="","",I35-I37) -> 2150000 | J39: =IF(J$5="","",J35-J37) -> 13815250 | K39: =IF(K$5="","",K35-K37) -> 29862634 | L39: =IF(L$5="","",L35-L37) -> 47411611 | M39: =IF(M$5="","",M35-M37) -> 4048514.1 | N39: =IF(N$5="","",N35-N37) | ... R39: =IF(R$5="","",R35-R37)
B41: ANNUAL PROPERTY-LEVEL CASH FLOWS
B43: Net Unlevered Cash Flow | G43: =IF(G$5="","",SUMIF($G$46:$EI$46,G$5,$G93:$EI93)) -> -93017714 | H43: =IF(H$5="","",SUMIF($G$46:$EI$46,H$5,$G93:$EI93)) -> -67738142 | I43: =IF(I$5="","",SUMIF($G$46:$EI$46,I$5,$G93:$EI93)) -> -2.3173212e+08 | J43: =IF(J$5="","",SUMIF($G$46:$EI$46,J$5,$G93:$EI93)) -> -40403404 | K43: =IF(K$5="","",SUMIF($G$46:$EI$46,K$5,$G93:$EI93)) -> 29862634 | L43: =IF(L$5="","",SUMIF($G$46:$EI$46,L$5,$G93:$EI93)) -> 47411611 | M43: =IF(M$5="","",SUMIF($G$46:$EI$46,M$5,$G93:$EI93)) -> 7.1198357e+08 | N43: =IF(N$5="","",SUMIF($G$46:$EI$46,N$5,$G93:$EI93)) | ... R43: =IF(R$5="","",SUMIF($G$46:$EI$46,R$5,$G93:$EI93))
B44: Net Levered Cash Flow | G44: =IF(G$5="","",SUMIF($G$46:$EI$46,G$5,$G94:$EI94)) -> -76389583 | H44: =IF(H$5="","",SUMIF($G$46:$EI$46,H$5,$G94:$EI94)) -> 2008935.2 | I44: =IF(I$5="","",SUMIF($G$46:$EI$46,I$5,$G94:$EI94)) -> -1.1140157e+08 | J44: =IF(J$5="","",SUMIF($G$46:$EI$46,J$5,$G94:$EI94)) -> -30866451 | K44: =IF(K$5="","",SUMIF($G$46:$EI$46,K$5,$G94:$EI94)) -> 12975436 | L44: =IF(L$5="","",SUMIF($G$46:$EI$46,L$5,$G94:$EI94)) -> 29393447 | M44: =IF(M$5="","",SUMIF($G$46:$EI$46,M$5,$G94:$EI94)) -> 4.7522601e+08 | N44: =IF(N$5="","",SUMIF($G$46:$EI$46,N$5,$G94:$EI94)) | ... R44: =IF(R$5="","",SUMIF($G$46:$EI$46,R$5,$G94:$EI94))
F46: ANALYSIS YEAR | G46: =IF(G47="","",Underwriting!L2) -> 0 | H46: =IF(H47="","",Underwriting!M2) -> 1 | I46: =IF(I47="","",Underwriting!N2) -> 1 | J46: =IF(J47="","",Underwriting!O2) -> 1 | K46: =IF(K47="","",Underwriting!P2) -> 1 | L46: =IF(L47="","",Underwriting!Q2) -> 1 | M46: =IF(M47="","",Underwriting!R2) -> 1 | N46: =IF(N47="","",Underwriting!S2) -> 1 | ... EI46: =IF(EI47="","",Underwriting!EN2)
B47: MONTHLY DEVELOPMENT CASH FLOWS | F47: MONTH END | G47: =Underwriting!L195 -> 46203 | H47: =Underwriting!M195 -> 46234 | I47: =Underwriting!N195 -> 46265 | J47: =Underwriting!O195 -> 46295 | K47: =Underwriting!P195 -> 46326 | L47: =Underwriting!Q195 -> 46356 | M47: =Underwriting!R195 -> 46387 | N47: =Underwriting!S195 -> 46418 | ... EI47: =Underwriting!EN195
B48: Land Costs | G48: =IF(G$47="","",Underwriting!L31) -> 92320000 | H48: =IF(H$47="","",Underwriting!M31) -> 0 | I48: =IF(I$47="","",Underwriting!N31) -> 0 | J48: =IF(J$47="","",Underwriting!O31) -> 0 | K48: =IF(K$47="","",Underwriting!P31) -> 0 | L48: =IF(L$47="","",Underwriting!Q31) -> 0 | M48: =IF(M$47="","",Underwriting!R31) -> 0 | N48: =IF(N$47="","",Underwriting!S31) -> 0 | ... EI48: =IF(EI$47="","",Underwriting!EN31)
B49: Hard Costs / Development Adjustments | G49: =IF(G$47="","",Underwriting!L38) -> 697714.09 | H49: =IF(H$47="","",Underwriting!M38) -> 882028.36 | I49: =IF(I$47="","",Underwriting!N38) -> 1153238.8 | J49: =IF(J$47="","",Underwriting!O38) -> 1540571.8 | K49: =IF(K$47="","",Underwriting!P38) -> 2077208.7 | L49: =IF(L$47="","",Underwriting!Q38) -> 2798042.2 | M49: =IF(M$47="","",Underwriting!R38) -> 3736098.9 | N49: =IF(N$47="","",Underwriting!S38) -> 4917681.3 | ... EI49: =IF(EI$47="","",Underwriting!EN38)
B50: Soft Costs | G50: =IF(G$47="","",Underwriting!L47) -> 0 | H50: =IF(H$47="","",Underwriting!M47) -> 0 | I50: =IF(I$47="","",Underwriting!N47) -> 0 | J50: =IF(J$47="","",Underwriting!O47) -> 0 | K50: =IF(K$47="","",Underwriting!P47) -> 0 | L50: =IF(L$47="","",Underwriting!Q47) -> 0 | M50: =IF(M$47="","",Underwriting!R47) -> 0 | N50: =IF(N$47="","",Underwriting!S47) -> 0 | ... EI50: =IF(EI$47="","",Underwriting!EN47)
B51: TOTAL PROJECT COST BEFORE FINANCING | G51: =IF(G$47="","",SUM(G48:G50)) -> 93017714 | H51: =IF(H$47="","",SUM(H48:H50)) -> 882028.36 | I51: =IF(I$47="","",SUM(I48:I50)) -> 1153238.8 | J51: =IF(J$47="","",SUM(J48:J50)) -> 1540571.8 | K51: =IF(K$47="","",SUM(K48:K50)) -> 2077208.7 | L51: =IF(L$47="","",SUM(L48:L50)) -> 2798042.2 | M51: =IF(M$47="","",SUM(M48:M50)) -> 3736098.9 | N51: =IF(N$47="","",SUM(N48:N50)) -> 4917681.3 | ... EI51: =IF(EI$47="","",SUM(EI48:EI50))
B53: Carry Costs | G53: =IF(G$47="","",Underwriting!L55) -> 0 | H53: =IF(H$47="","",Underwriting!M55) -> 0 | I53: =IF(I$47="","",Underwriting!N55) -> 0 | J53: =IF(J$47="","",Underwriting!O55) -> 0 | K53: =IF(K$47="","",Underwriting!P55) -> 0 | L53: =IF(L$47="","",Underwriting!Q55) -> 0 | M53: =IF(M$47="","",Underwriting!R55) -> 0 | N53: =IF(N$47="","",Underwriting!S55) -> 0 | ... EI53: =IF(EI$47="","",Underwriting!EN55)
B55: TOTAL PROJECT COST | G55: =IF(G$47="","",G53+G51) -> 93017714 | H55: =IF(H$47="","",H53+H51) -> 882028.36 | I55: =IF(I$47="","",I53+I51) -> 1153238.8 | J55: =IF(J$47="","",J53+J51) -> 1540571.8 | K55: =IF(K$47="","",K53+K51) -> 2077208.7 | L55: =IF(L$47="","",L53+L51) -> 2798042.2 | M55: =IF(M$47="","",M53+M51) -> 3736098.9 | N55: =IF(N$47="","",N53+N51) -> 4917681.3 | ... EI55: =IF(EI$47="","",EI53+EI51)
B57: GROSS SOURCES | G57: =IF(G$47="","",Underwriting!L77) -> 93017714 | H57: =IF(H$47="","",Underwriting!M77) -> 952590.63 | I57: =IF(I$47="","",Underwriting!N77) -> 1153238.8 | J57: =IF(J$47="","",Underwriting!O77) -> 1593255.3 | K57: =IF(K$47="","",Underwriting!P77) -> 2151126.3 | L57: =IF(L$47="","",Underwriting!Q77) -> 2898639.8 | M57: =IF(M$47="","",Underwriting!R77) -> 3868810.1 | N57: =IF(N$47="","",Underwriting!S77) -> 5087252.4 | ... EI57: =IF(EI$47="","",Underwriting!EN77)
B58: USES | G58: =IF(G$47="","",Underwriting!L57) -> 93017714 | H58: =IF(H$47="","",Underwriting!M57) -> 882028.36 | I58: =IF(I$47="","",Underwriting!N57) -> 1153238.8 | J58: =IF(J$47="","",Underwriting!O57) -> 1540571.8 | K58: =IF(K$47="","",Underwriting!P57) -> 2077208.7 | L58: =IF(L$47="","",Underwriting!Q57) -> 2798042.2 | M58: =IF(M$47="","",Underwriting!R57) -> 3736098.9 | N58: =IF(N$47="","",Underwriting!S57) -> 4917681.3 | ... EI58: =IF(EI$47="","",Underwriting!EN57)
B59: GROSS SOURCES LESS USES (TIMING / ELIGIBILITY BRIDGE) | G59: =IF(G$47="","",G57-G58) -> 0 | H59: =IF(H$47="","",H57-H58) -> 70562.269 | I59: =IF(I$47="","",I57-I58) -> 0 | J59: =IF(J$47="","",J57-J58) -> 52683.478 | K59: =IF(K$47="","",K57-K58) -> 73917.593 | L59: =IF(L$47="","",L57-L58) -> 100597.63 | M59: =IF(M$47="","",M57-M58) -> 132711.21 | N59: =IF(N$47="","",N57-N58) -> 169571.13 | ... EI59: =IF(EI$47="","",EI57-EI58)
B60: MONTHLY OPERATING CASH FLOWS | G60: =+G47 -> 46203 | H60: =+H47 -> 46234 | I60: =+I47 -> 46265 | J60: =+J47 -> 46295 | K60: =+K47 -> 46326 | L60: =+L47 -> 46356 | M60: =+M47 -> 46387 | N60: =+N47 -> 46418 | ... EI60: =+EI47
B61: Rental Income | G61: =IF(G$81="","",Underwriting!L105) -> 0 | H61: =IF(H$81="","",Underwriting!M105) -> 0 | I61: =IF(I$81="","",Underwriting!N105) -> 0 | J61: =IF(J$81="","",Underwriting!O105) -> 0 | K61: =IF(K$81="","",Underwriting!P105) -> 0 | L61: =IF(L$81="","",Underwriting!Q105) -> 0 | M61: =IF(M$81="","",Underwriting!R105) -> 0 | N61: =IF(N$81="","",Underwriting!S105) -> 0 | ... EI61: =IF(EI$81="","",Underwriting!EN105)
