Workbook
Name Curr_Unit: InpC!$F$62
Name SMU: InpC!$F$61

Sheet InpC
A1: =RIGHT(CELL("filename", A1), LEN(CELL("filename", A1)) - SEARCH("]", CELL("filename", A1))) -> InpC
F4: ='T&E'!F$12 -> constant | G4: ='T&E'!G$12 -> unit | H4: who | I4: source | J4: comments
A6: TIMING
E8: First date of time ruler | F8: 41639 | G8: date
E10: Financial close date | F10: 41698 | G10: EOM
E11: Length of construction period | F11: 22 | G11: months
E12: Construction period end / conversion date | F12: =EOMONTH(F10, F11) -> 42369 | G12: date
E14: Length of forecast period | F14: 30 | G14: years
E15: Last forecast date | F15: =EOMONTH( F12, 12 * F14 ) -> 53327 | G15: date
E17: Annual CPI inflation rate | F17: 0.025 | G17: p.a.
E18: Price and cost basis date - period ending | F18: 41820 | G18: date
A21: OPERATIONS ASSUMPTIONS
E23: Aircraft capacity - domestic charter | F23: 110 | G23: seats
E24: Aircraft capacity - domestic scheduled | F24: 140 | G24: seats
E25: Aircraft capacity - international chartered | F25: 250 | G25: seats
E26: Aircraft capacity - international scheduled | F26: 280 | G26: seats
E28: Passenger landing tax rate | F28: 22.75 | G28: =Curr_Unit & " / PAx" -> € / PAx
E30: Passenger retail purchases rate | F30: 10.5 | G30: =Curr_Unit & " / PAx" -> € / PAx
E31: Rental revenue sharing percentage | F31: 0.25 | G31: of sales
E33: Variable ground handling charge rate | F33: 340 | G33: =Curr_Unit & " / landing" -> € / landing
E34: Fixed ground handling costs | F34: 3600 | G34: =Curr_Unit & " 000s p.a." -> € 000s p.a.
E35: Airport terminal O&M contract costs | F35: 2400 | G35: =Curr_Unit & " 000s p.a." -> € 000s p.a.
A38: FINANCE, TAX, AND ACCOUNTING
E40: Senior debt coupon base rate | F40: 0.075 | G40: p.a. (semi)
E41: Senior principal repayment selection switch | F41: 5 | G41: switch
E43: =E$12 -> Construction period end / conversion date | F43: =F$12 -> 42369 | G43: =G$12 -> date
E44: Useful life input | F44: 25 | G44: years
E45: Last date of accounting depreciation | F45: =EOMONTH(F43, 12 * F44) -> 51501 | G45: date
E47: Reducing balance rate for tax | F47: 0.05 | G47: of basis
E49: Corporation tax rate | F49: 0.3 | G49: of TI
E50: [Effective P&L tax rate] | F50: 0.3 | G50: of PBT | J50: Presumption that over-life allowances for tax are equivalent to accounting expenses, so effective P&L tax rate should be equivalent to cash tax rate. Need to confirm with client and/or accounting advisor.
A52: EQUITY / RETURN ASSUMPTIONS
E54: Share capital investment requirement | F54: 1000 | G54: =SMU -> € 000s
E55: Shareholder discount rate | F55: 0.13 | G55: p.a. (365)
A59: MODEL CONTROL INPUTS
E61: Standard monetary unit | F61: € 000s | G61: Name
E62: Currency unit | F62: € | G62: Name

Sheet InpS
A1: =RIGHT(CELL("filename", A1), LEN(CELL("filename", A1)) - SEARCH("]", CELL("filename", A1))) -> InpS
E2: ='T&E'!E$24 -> Operating period flag | F2: ='T&E'!F$24 -> 0 | G2: ='T&E'!G$24 -> flag | H2: ='T&E'!H$24 -> 60 | I2: ='T&E'!I$24 -> 0 | J2: ='T&E'!J$24 -> 0 | K2: ='T&E'!K$24 -> 0 | L2: ='T&E'!L$24 -> 0 | ... CA2: ='T&E'!CA$24 -> 0
E3: ='T&E'!E$8 -> Model column counter | F3: ='T&E'!F$8 -> 0 | G3: ='T&E'!G$8 -> 0 | H3: ='T&E'!H$8 -> 0 | I3: ='T&E'!I$8 -> 0 | J3: ='T&E'!J$8 -> 1 | K3: ='T&E'!K$8 -> 2 | L3: ='T&E'!L$8 -> 3 | ... CA3: ='T&E'!CA$8 -> 70
E4: ='T&E'!E$12 -> Model period ending | F4: ='T&E'!F$12 -> constant | G4: ='T&E'!G$12 -> unit | H4: ='T&E'!H$12 -> total | I4: ='T&E'!I$12 -> 0 | J4: ='T&E'!J$12 -> 41639 | K4: ='T&E'!K$12 -> 41820 | L4: ='T&E'!L$12 -> 42004 | ... CA4: ='T&E'!CA$12 -> 54239
A6: ROUTE ASSUMPTIONS
E8: Routes - domestic charter | G8: planes | L8: 15 | M8: 15 | N8: 13 | O8: 13 | P8: 13 | Q8: 13 | R8: 11 | S8: 11 | T8: 11 | U8: 11 | V8: 9 | W8: 9 | X8: 9 | Y8: 9 | Z8: 9 | AA8: 9 | AB8: 9 | AC8: 9 | AD8: 9 | AE8: 9 | AF8: 9 | AG8: 9 | AH8: 9 | AI8: 9 | AJ8: 9 | AK8: 9 | AL8: 9 | AM8: 9 | AN8: 9 | AO8: 9 | AP8: 9 | AQ8: 9 | AR8: 9 | AS8: 9 | AT8: 9 | AU8: 9 | AV8: 9 | AW8: 9 | AX8: 9 | AY8: 9 | AZ8: 9 | BA8: 9 | BB8: 9 | BC8: 9 | BD8: 9 | BE8: 9 | BF8: 9 | BG8: 9 | BH8: 9 | BI8: 9 | BJ8: 9 | BK8: 9 | BL8: 9 | BM8: 9 | BN8: 9 | BO8: 9 | BP8: 9 | BQ8: 9 | BR8: 9 | BS8: 9 | BT8: 9 | BU8: 9 | BV8: 9
E9: Routes - domestic scheduled | G9: planes | L9: 28 | M9: 28 | N9: 24 | O9: 24 | P9: 24 | Q9: 24 | R9: 20 | S9: 20 | T9: 20 | U9: 20 | V9: 20 | W9: 20 | X9: 20 | Y9: 20 | Z9: 20 | AA9: 20 | AB9: 20 | AC9: 20 | AD9: 20 | AE9: 20 | AF9: 20 | AG9: 20 | AH9: 20 | AI9: 20 | AJ9: 20 | AK9: 20 | AL9: 20 | AM9: 20 | AN9: 20 | AO9: 20 | AP9: 20 | AQ9: 20 | AR9: 20 | AS9: 20 | AT9: 20 | AU9: 20 | AV9: 20 | AW9: 20 | AX9: 20 | AY9: 20 | AZ9: 20 | BA9: 20 | BB9: 20 | BC9: 20 | BD9: 20 | BE9: 20 | BF9: 20 | BG9: 20 | BH9: 20 | BI9: 20 | BJ9: 20 | BK9: 20 | BL9: 20 | BM9: 20 | BN9: 20 | BO9: 20 | BP9: 20 | BQ9: 20 | BR9: 20 | BS9: 20 | BT9: 20 | BU9: 20 | BV9: 20
E10: Routes - international charter | G10: planes | L10: 30 | M10: 30 | N10: 30 | O10: 30 | P10: 30 | Q10: 30 | R10: 30 | S10: 30 | T10: 30 | U10: 30 | V10: 30 | W10: 30 | X10: 30 | Y10: 30 | Z10: 30 | AA10: 30 | AB10: 30 | AC10: 30 | AD10: 30 | AE10: 30 | AF10: 30 | AG10: 30 | AH10: 30 | AI10: 30 | AJ10: 30 | AK10: 30 | AL10: 30 | AM10: 30 | AN10: 30 | AO10: 30 | AP10: 30 | AQ10: 30 | AR10: 30 | AS10: 30 | AT10: 30 | AU10: 30 | AV10: 30 | AW10: 30 | AX10: 30 | AY10: 30 | AZ10: 30 | BA10: 30 | BB10: 30 | BC10: 30 | BD10: 30 | BE10: 30 | BF10: 30 | BG10: 30 | BH10: 30 | BI10: 30 | BJ10: 30 | BK10: 30 | BL10: 30 | BM10: 30 | BN10: 30 | BO10: 30 | BP10: 30 | BQ10: 30 | BR10: 30 | BS10: 30 | BT10: 30 | BU10: 30 | BV10: 30
E11: Routes - international scheduled | G11: planes | L11: 12 | M11: 12 | N11: 14 | O11: 14 | P11: 16 | Q11: 16 | R11: 16 | S11: 16 | T11: 16 | U11: 16 | V11: 16 | W11: 16 | X11: 16 | Y11: 16 | Z11: 16 | AA11: 16 | AB11: 16 | AC11: 16 | AD11: 16 | AE11: 16 | AF11: 16 | AG11: 16 | AH11: 16 | AI11: 16 | AJ11: 16 | AK11: 16 | AL11: 16 | AM11: 16 | AN11: 16 | AO11: 16 | AP11: 16 | AQ11: 16 | AR11: 16 | AS11: 16 | AT11: 16 | AU11: 16 | AV11: 16 | AW11: 16 | AX11: 16 | AY11: 16 | AZ11: 16 | BA11: 16 | BB11: 16 | BC11: 16 | BD11: 16 | BE11: 16 | BF11: 16 | BG11: 16 | BH11: 16 | BI11: 16 | BJ11: 16 | BK11: 16 | BL11: 16 | BM11: 16 | BN11: 16 | BO11: 16 | BP11: 16 | BQ11: 16 | BR11: 16 | BS11: 16 | BT11: 16 | BU11: 16 | BV11: 16
E13: Landing frequency - domestic charter | G13: lands / plane | L13: 120 | M13: 120 | N13: 110 | O13: 110 | P13: 110 | Q13: 110 | R13: 100 | S13: 100 | T13: 100 | U13: 100 | V13: 90 | W13: 90 | X13: 90 | Y13: 90 | Z13: 80 | AA13: 80 | AB13: 80 | AC13: 80 | AD13: 80 | AE13: 80 | AF13: 80 | AG13: 80 | AH13: 80 | AI13: 80 | AJ13: 80 | AK13: 80 | AL13: 80 | AM13: 80 | AN13: 80 | AO13: 80 | AP13: 80 | AQ13: 80 | AR13: 80 | AS13: 80 | AT13: 80 | AU13: 80 | AV13: 80 | AW13: 80 | AX13: 80 | AY13: 80 | AZ13: 80 | BA13: 80 | BB13: 80 | BC13: 80 | BD13: 80 | BE13: 80 | BF13: 80 | BG13: 80 | BH13: 80 | BI13: 80 | BJ13: 80 | BK13: 80 | BL13: 80 | BM13: 80 | BN13: 80 | BO13: 80 | BP13: 80 | BQ13: 80 | BR13: 80 | BS13: 80 | BT13: 80 | BU13: 80 | BV13: 80
E14: Landing frequency - domestic scheduled | G14: lands / plane | L14: 250 | M14: 270 | N14: 250 | O14: 270 | P14: 250 | Q14: 270 | R14: 250 | S14: 270 | T14: 250 | U14: 270 | V14: 250 | W14: 270 | X14: 250 | Y14: 270 | Z14: 250 | AA14: 270 | AB14: 250 | AC14: 270 | AD14: 250 | AE14: 270 | AF14: 250 | AG14: 270 | AH14: 250 | AI14: 270 | AJ14: 250 | AK14: 270 | AL14: 250 | AM14: 270 | AN14: 250 | AO14: 270 | AP14: 250 | AQ14: 270 | AR14: 250 | AS14: 270 | AT14: 250 | AU14: 270 | AV14: 250 | AW14: 270 | AX14: 250 | AY14: 270 | AZ14: 250 | BA14: 270 | BB14: 250 | BC14: 270 | BD14: 250 | BE14: 270 | BF14: 250 | BG14: 270 | BH14: 250 | BI14: 250 | BJ14: 270 | BK14: 250 | BL14: 270 | BM14: 250 | BN14: 270 | BO14: 250 | BP14: 270 | BQ14: 250 | BR14: 250 | BS14: 270 | BT14: 270 | BU14: 270 | BV14: 270 | CB14: 270 | CC14: 168 | CD14: 84 | CE14: 168
E15: Landing frequency - international charter | G15: lands / plane | L15: 40 | M15: 40 | N15: 45 | O15: 45 | P15: 50 | Q15: 50 | R15: 55 | S15: 55 | T15: 60 | U15: 60 | V15: 65 | W15: 65 | X15: 70 | Y15: 70 | Z15: 70 | AA15: 70 | AB15: 70 | AC15: 70 | AD15: 70 | AE15: 70 | AF15: 70 | AG15: 70 | AH15: 70 | AI15: 70 | AJ15: 70 | AK15: 70 | AL15: 70 | AM15: 70 | AN15: 70 | AO15: 70 | AP15: 70 | AQ15: 70 | AR15: 70 | AS15: 70 | AT15: 70 | AU15: 70 | AV15: 70 | AW15: 70 | AX15: 70 | AY15: 70 | AZ15: 70 | BA15: 70 | BB15: 70 | BC15: 70 | BD15: 70 | BE15: 70 | BF15: 70 | BG15: 70 | BH15: 70 | BI15: 70 | BJ15: 70 | BK15: 70 | BL15: 70 | BM15: 70 | BN15: 70 | BO15: 70 | BP15: 70 | BQ15: 70 | BR15: 70 | BS15: 70 | BT15: 70 | BU15: 70 | BV15: 70
E16: Landing frequency - international scheduled | G16: lands / plane | L16: 35 | M16: 35 | N16: 45 | O16: 45 | P16: 45 | Q16: 45 | R16: 55 | S16: 55 | T16: 55 | U16: 55 | V16: 55 | W16: 55 | X16: 55 | Y16: 55 | Z16: 55 | AA16: 55 | AB16: 55 | AC16: 55 | AD16: 55 | AE16: 55 | AF16: 55 | AG16: 55 | AH16: 55 | AI16: 55 | AJ16: 55 | AK16: 55 | AL16: 55 | AM16: 55 | AN16: 55 | AO16: 55 | AP16: 55 | AQ16: 55 | AR16: 55 | AS16: 55 | AT16: 55 | AU16: 55 | AV16: 55 | AW16: 55 | AX16: 55 | AY16: 55 | AZ16: 55 | BA16: 55 | BB16: 55 | BC16: 55 | BD16: 55 | BE16: 55 | BF16: 55 | BG16: 55 | BH16: 55 | BI16: 55 | BJ16: 55 | BK16: 55 | BL16: 55 | BM16: 55 | BN16: 55 | BO16: 55 | BP16: 55 | BQ16: 55 | BR16: 55 | BS16: 55 | BT16: 55 | BU16: 55 | BV16: 55
E18: Load factor - domestic charter | G18: % | L18: 0.6 | M18: 0.6 | N18: 0.7 | O18: 0.7 | P18: 0.7 | Q18: 0.7 | R18: 0.7 | S18: 0.7 | T18: 0.7 | U18: 0.7 | V18: 0.7 | W18: 0.7 | X18: 0.7 | Y18: 0.7 | Z18: 0.7 | AA18: 0.7 | AB18: 0.7 | AC18: 0.7 | AD18: 0.79 | AE18: 0.79 | AF18: 0.79 | AG18: 0.79 | AH18: 0.79 | AI18: 0.79 | AJ18: 0.79 | AK18: 0.79 | AL18: 0.79 | AM18: 0.79 | AN18: 0.79 | AO18: 0.79 | AP18: 0.79 | AQ18: 0.79 | AR18: 0.79 | AS18: 0.79 | AT18: 0.79 | AU18: 0.79 | AV18: 0.79 | AW18: 0.79 | AX18: 0.7 | AY18: 0.7 | AZ18: 0.7 | BA18: 0.7 | BB18: 0.7 | BC18: 0.7 | BD18: 0.7 | BE18: 0.7 | BF18: 0.65 | BG18: 0.65 | BH18: 0.65 | BI18: 0.65 | BJ18: 0.6 | BK18: 0.6 | BL18: 0.6 | BM18: 0.6 | BN18: 0.6 | BO18: 0.6 | BP18: 0.6 | BQ18: 0.6 | BR18: 0.6 | BS18: 0.6 | BT18: 0.6 | BU18: 0.6 | BV18: 0.6
E19: Load factor - domestic scheduled | G19: % | L19: 0.7 | M19: 0.7 | N19: 0.7 | O19: 0.7 | P19: 0.7 | Q19: 0.7 | R19: 0.7 | S19: 0.7 | T19: 0.66 | U19: 0.66 | V19: 0.66 | W19: 0.66 | X19: 0.66 | Y19: 0.66 | Z19: 0.66 | AA19: 0.66 | AB19: 0.66 | AC19: 0.66 | AD19: 0.68 | AE19: 0.68 | AF19: 0.68 | AG19: 0.68 | AH19: 0.68 | AI19: 0.68 | AJ19: 0.68 | AK19: 0.68 | AL19: 0.68 | AM19: 0.68 | AN19: 0.7 | AO19: 0.7 | AP19: 0.7 | AQ19: 0.7 | AR19: 0.7 | AS19: 0.7 | AT19: 0.7 | AU19: 0.7 | AV19: 0.7 | AW19: 0.7 | AX19: 0.72 | AY19: 0.72 | AZ19: 0.72 | BA19: 0.72 | BB19: 0.72 | BC19: 0.72 | BD19: 0.72 | BE19: 0.72 | BF19: 0.72 | BG19: 0.72 | BH19: 0.72 | BI19: 0.72 | BJ19: 0.72 | BK19: 0.72 | BL19: 0.72 | BM19: 0.72 | BN19: 0.72 | BO19: 0.72 | BP19: 0.72 | BQ19: 0.72 | BR19: 0.72 | BS19: 0.72 | BT19: 0.72 | BU19: 0.72 | BV19: 0.72
E20: Load factor - international charter | G20: % | L20: 0.65 | M20: 0.6 | N20: 0.65 | O20: 0.6 | P20: 0.65 | Q20: 0.6 | R20: 0.65 | S20: 0.6 | T20: 0.65 | U20: 0.6 | V20: 0.65 | W20: 0.6 | X20: 0.65 | Y20: 0.6 | Z20: 0.65 | AA20: 0.6 | AB20: 0.65 | AC20: 0.6 | AD20: 0.65 | AE20: 0.6 | AF20: 0.65 | AG20: 0.6 | AH20: 0.65 | AI20: 0.6 | AJ20: 0.65 | AK20: 0.6 | AL20: 0.65 | AM20: 0.6 | AN20: 0.65 | AO20: 0.6 | AP20: 0.65 | AQ20: 0.6 | AR20: 0.65 | AS20: 0.6 | AT20: 0.65 | AU20: 0.6 | AV20: 0.65 | AW20: 0.6 | AX20: 0.65 | AY20: 0.6 | AZ20: 0.65 | BA20: 0.6 | BB20: 0.65 | BC20: 0.6 | BD20: 0.65 | BE20: 0.6 | BF20: 0.65 | BG20: 0.6 | BH20: 0.65 | BI20: 0.6 | BJ20: 0.65 | BK20: 0.6 | BL20: 0.65 | BM20: 0.6 | BN20: 0.65 | BO20: 0.6 | BP20: 0.65 | BQ20: 0.6 | BR20: 0.65 | BS20: 0.6 | BT20: 0.6 | BU20: 0.6 | BV20: 0.6 | CB20: 0.55 | CC20: 0.5 | CD20: 0.55 | CE20: 0.5 | CF20: 0.55 | CG20: 0.5 | CH20: 0.55 | CI20: 0.5 | CJ20: 0.55 | CK20: 0.5 | CL20: 0.55 | CM20: 0.5 | CN20: 0.55 | CO20: 0.5
E21: Load factor - international scheduled | G21: % | L21: 0.65 | M21: 0.65 | N21: 0.65 | O21: 0.65 | P21: 0.65 | Q21: 0.65 | R21: 0.65 | S21: 0.65 | T21: 0.65 | U21: 0.65 | V21: 0.65 | W21: 0.65 | X21: 0.65 | Y21: 0.65 | Z21: 0.65 | AA21: 0.65 | AB21: 0.65 | AC21: 0.65 | AD21: 0.65 | AE21: 0.65 | AF21: 0.65 | AG21: 0.65 | AH21: 0.65 | AI21: 0.65 | AJ21: 0.65 | AK21: 0.65 | AL21: 0.65 | AM21: 0.65 | AN21: 0.65 | AO21: 0.65 | AP21: 0.65 | AQ21: 0.65 | AR21: 0.65 | AS21: 0.65 | AT21: 0.65 | AU21: 0.65 | AV21: 0.65 | AW21: 0.65 | AX21: 0.7 | AY21: 0.7 | AZ21: 0.7 | BA21: 0.7 | BB21: 0.7 | BC21: 0.7 | BD21: 0.7 | BE21: 0.7 | BF21: 0.7 | BG21: 0.7 | BH21: 0.7 | BI21: 0.7 | BJ21: 0.7 | BK21: 0.7 | BL21: 0.7 | BM21: 0.7 | BN21: 0.7 | BO21: 0.7 | BP21: 0.7 | BQ21: 0.7 | BR21: 0.7 | BS21: 0.7 | BT21: 0.7 | BU21: 0.7 | BV21: 0.7
A24: DEBT REPAYMENT PROFILES
E26: ='T&E'!E$29 -> Senior debt term / ratio calc date flag | F26: ='T&E'!F$29 -> 0 | G26: ='T&E'!G$29 -> flag | H26: ='T&E'!H$29 -> 40 | I26: ='T&E'!I$29 -> 0 | J26: ='T&E'!J$29 -> 0 | K26: ='T&E'!K$29 -> 0 | L26: ='T&E'!L$29 -> 0 | ... CA26: ='T&E'!CA$29 -> 0
E28: =InpC!E$41 -> Senior principal repayment selection switch | F28: =InpC!F$41 -> 5 | G28: =InpC!G$41 -> switch
E29: Senior debt repayment - 20-year level | H29: =SUM(J29:CA29) -> 1 | O29: =1 / 40 -> 0.025 | P29: =1 / 40 -> 0.025 | Q29: =1 / 40 -> 0.025 | R29: =1 / 40 -> 0.025 | S29: =1 / 40 -> 0.025 | T29: =1 / 40 -> 0.025 | U29: =1 / 40 -> 0.025 | V29: =1 / 40 -> 0.025 | ... BB29: =1 / 40 -> 0.025
E30: Senior debt repayment - 2.0% / 3.0% | H30: =SUM(J30:CA30) -> 1 | O30: 0.02 | P30: 0.02 | Q30: 0.02 | R30: 0.02 | S30: 0.02 | T30: 0.02 | U30: 0.02 | V30: 0.02 | W30: 0.02 | X30: 0.02 | Y30: 0.02 | Z30: 0.02 | AA30: 0.02 | AB30: 0.02 | AC30: 0.02 | AD30: 0.02 | AE30: 0.02 | AF30: 0.02 | AG30: 0.02 | AH30: 0.02 | AI30: 0.03 | AJ30: 0.03 | AK30: 0.03 | AL30: 0.03 | AM30: 0.03 | AN30: 0.03 | AO30: 0.03 | AP30: 0.03 | AQ30: 0.03 | AR30: 0.03 | AS30: 0.03 | AT30: 0.03 | AU30: 0.03 | AV30: 0.03 | AW30: 0.03 | AX30: 0.03 | AY30: 0.03 | AZ30: 0.03 | BA30: 0.03 | BB30: 0.03
E31: Senior debt repayment - 20-year level w/ 3-year grace | H31: =SUM(J31:CA31) -> 1 | O31: 0 | P31: 0 | Q31: 0 | R31: 0 | S31: 0 | T31: 0 | U31: 0 | V31: 0 | W31: =1 / 32 -> 0.03125 | X31: =1 / 32 -> 0.03125 | Y31: =1 / 32 -> 0.03125 | Z31: =1 / 32 -> 0.03125 | AA31: =1 / 32 -> 0.03125 | AB31: =1 / 32 -> 0.03125 | AC31: =1 / 32 -> 0.03125 | AD31: =1 / 32 -> 0.03125 | ... BB31: =1 / 32 -> 0.03125
E32: 20 year - variable profile for ratio demo | H32: =SUM(J32:CA32) -> 1 | O32: 0.005 | P32: 0.005 | Q32: 0.04 | R32: 0.005 | T32: 0.035 | U32: 0.035 | V32: 0.035 | W32: 0.035 | X32: 0.025 | Y32: 0.025 | Z32: 0.025 | AA32: 0.025 | AD32: 0.015 | AE32: 0.015 | AF32: 0 | AG32: 0.025 | AH32: 0.025 | AI32: 0.06 | AJ32: 0.025 | AK32: 0.04 | AL32: 0.04 | AM32: 0.04 | AN32: 0.04 | AO32: 0.04 | AP32: 0.04 | AQ32: 0.025 | AR32: 0.025 | AS32: 0.025 | AT32: 0.025 | AU32: 0.025 | AV32: 0.025 | AW32: 0.025 | AX32: 0.025 | AY32: 0.025 | AZ32: 0.025 | BA32: 0.025 | BB32: 0.025
E33: 20-year sculpted senior debt repayment profile | H33: =SUM(J33:CA33) -> 1 | O33: 0.00941 | P33: 0.01009 | Q33: 0.0112 | R33: 0.00812 | S33: 0.00885 | T33: 0.00823 | U33: 0.00885 | V33: 0.0089 | W33: 0.00953 | X33: 0.01059 | Y33: 0.01305 | Z33: 0.01306 | AA33: 0.01386 | AB33: 0.01421 | AC33: 0.01511 | AD33: 0.01659 | AE33: 0.01769 | AF33: 0.01821 | AG33: 0.01942 | AH33: 0.02003 | AI33: 0.02282 | AJ33: 0.02353 | AK33: 0.02498 | AL33: 0.02579 | AM33: 0.02736 | AN33: 0.02907 | AO33: 0.03086 | AP33: 0.03187 | AQ33: 0.0338 | AR33: 0.03492 | AS33: 0.03699 | AT33: 0.03824 | AU33: 0.04047 | AV33: 0.04185 | AW33: 0.04424 | AX33: 0.04698 | AY33: 0.04967 | AZ33: 0.05133 | BA33: 0.0542 | BB33: 0.05603
E34: blank for insertion | J34: n/a | K34: n/a | L34: n/a | M34: n/a | N34: n/a | O34: n/a | P34: n/a | Q34: n/a | R34: n/a | S34: n/a | T34: n/a | U34: n/a | V34: n/a | W34: n/a | X34: n/a | Y34: n/a | Z34: n/a | AA34: n/a | AB34: n/a | AC34: n/a | AD34: n/a | AE34: n/a | AF34: n/a | AG34: n/a | AH34: n/a | AI34: n/a | AJ34: n/a | AK34: n/a | AL34: n/a | AM34: n/a | AN34: n/a | AO34: n/a | AP34: n/a | AQ34: n/a | AR34: n/a | AS34: n/a | AT34: n/a | AU34: n/a | AV34: n/a | AW34: n/a | AX34: n/a | AY34: n/a | AZ34: n/a | BA34: n/a | BB34: n/a | BC34: n/a | BD34: n/a | BE34: n/a | BF34: n/a | BG34: n/a | BH34: n/a | BI34: n/a | BJ34: n/a | BK34: n/a | BL34: n/a | BM34: n/a | BN34: n/a | BO34: n/a | BP34: n/a | BQ34: n/a | BR34: n/a | BS34: n/a | BT34: n/a | BU34: n/a | BV34: n/a | BW34: n/a | BX34: n/a | BY34: n/a | BZ34: n/a | CA34: n/a
E35: Senior debt repayment profile - saved selection | H35: =SUM(J35:CA35) -> 1 | J35: =INDEX(J29:J34, $F28) -> 0 | K35: =INDEX(K29:K34, $F28) -> 0 | L35: =INDEX(L29:L34, $F28) -> 0 | M35: =INDEX(M29:M34, $F28) -> 0 | N35: =INDEX(N29:N34, $F28) -> 0 | O35: =INDEX(O29:O34, $F28) -> 0.00941 | P35: =INDEX(P29:P34, $F28) -> 0.01009 | Q35: =INDEX(Q29:Q34, $F28) -> 0.0112 | ... CA35: =INDEX(CA29:CA34, $F28) -> 0
E37: =SrDebt!E$52 -> Sculpted repayment profile COPY TARGET | F37: =SrDebt!F$52 -> 0 | G37: =SrDebt!G$52 -> 0 | H37: =SrDebt!H$52 -> 1 | I37: =SrDebt!I$52 -> 0 | J37: =SrDebt!J$52 -> 0 | K37: =SrDebt!K$52 -> 0 | L37: =SrDebt!L$52 -> 0 | ... CA37: =SrDebt!CA$52 -> 0

Sheet ConTime
A1: =RIGHT(CELL("filename", A1), LEN(CELL("filename", A1)) - SEARCH("]", CELL("filename", A1))) -> ConTime
E2: =E$18 -> Construction / availability period flag | F2: =F$18 -> 0 | G2: =G$18 -> 0 | H2: =H$18 -> 22 | I2: =I$18 -> 0 | J2: =J$18 -> 0 | K2: =K$18 -> 1 | L2: =L$18 -> 1 | ... AZ2: =AZ$18 -> 0
E3: =E$8 -> Construction period counter | F3: =F$8 -> 0 | G3: =G$8 -> 0 | H3: =H$8 -> 0 | I3: =I$8 -> 0 | J3: =J$8 -> 1 | K3: =K$8 -> 2 | L3: =L$8 -> 3 | ... AZ3: =AZ$8 -> 43
E4: =E$13 -> Construction period month ending | F4: =F$13 -> 0 | G4: =G$13 -> 0 | H4: =H$13 -> 0 | I4: =I$13 -> 0 | J4: =J$13 -> 41698 | K4: =K$13 -> 41729 | L4: =L$13 -> 41759 | ... AZ4: =AZ$13 -> 42978
A6: BASIC TIMING COMPONENTS
E8: Construction period counter | J8: =I8 + 1 -> 1 | K8: =J8 + 1 -> 2 | L8: =K8 + 1 -> 3 | M8: =L8 + 1 -> 4 | N8: =M8 + 1 -> 5 | O8: =N8 + 1 -> 6 | P8: =O8 + 1 -> 7 | Q8: =P8 + 1 -> 8 | ... AZ8: =AY8 + 1 -> 43
E9: Construction period month no. | J9: =J8 - 1 -> 0 | K9: =K8 - 1 -> 1 | L9: =L8 - 1 -> 2 | M9: =M8 - 1 -> 3 | N9: =N8 - 1 -> 4 | O9: =O8 - 1 -> 5 | P9: =P8 - 1 -> 6 | Q9: =Q8 - 1 -> 7 | ... AZ9: =AZ8 - 1 -> 42
E11: =InpC!E$10 -> Financial close date | F11: =InpC!F$10 -> 41698 | G11: =InpC!G$10 -> EOM
E12: =E$9 -> Construction period month no. | F12: =F$9 -> 0 | G12: =G$9 -> 0 | H12: =H$9 -> 0 | I12: =I$9 -> 0 | J12: =J$9 -> 0 | K12: =K$9 -> 1 | L12: =L$9 -> 2 | ... AZ12: =AZ$9 -> 42
E13: Construction period month ending | J13: =IF( J12 = 0, $F11, EOMONTH(I13, 1)) -> 41698 | K13: =IF( K12 = 0, $F11, EOMONTH(J13, 1)) -> 41729 | L13: =IF( L12 = 0, $F11, EOMONTH(K13, 1)) -> 41759 | M13: =IF( M12 = 0, $F11, EOMONTH(L13, 1)) -> 41790 | N13: =IF( N12 = 0, $F11, EOMONTH(M13, 1)) -> 41820 | O13: =IF( O12 = 0, $F11, EOMONTH(N13, 1)) -> 41851 | P13: =IF( P12 = 0, $F11, EOMONTH(O13, 1)) -> 41882 | Q13: =IF( Q12 = 0, $F11, EOMONTH(P13, 1)) -> 41912 | ... AZ13: =IF( AZ12 = 0, $F11, EOMONTH(AY13, 1)) -> 42978
E15: =InpC!E$10 -> Financial close date | F15: =InpC!F$10 -> 41698 | G15: =InpC!G$10 -> EOM
E16: =InpC!E$12 -> Construction period end / conversion date | F16: =InpC!F$12 -> 42369 | G16: =InpC!G$12 -> date
E17: =E$13 -> Construction period month ending | F17: =F$13 -> 0 | G17: =G$13 -> 0 | H17: =H$13 -> 0 | I17: =I$13 -> 0 | J17: =J$13 -> 41698 | K17: =K$13 -> 41729 | L17: =L$13 -> 41759 | ... AZ17: =AZ$13 -> 42978
E18: Construction / availability period flag | H18: =SUM(J18:AZ18) -> 22 | J18: =IF( AND(J17 > $F15, J17 <= $F16), 1, 0) -> 0 | K18: =IF( AND(K17 > $F15, K17 <= $F16), 1, 0) -> 1 | L18: =IF( AND(L17 > $F15, L17 <= $F16), 1, 0) -> 1 | M18: =IF( AND(M17 > $F15, M17 <= $F16), 1, 0) -> 1 | N18: =IF( AND(N17 > $F15, N17 <= $F16), 1, 0) -> 1 | O18: =IF( AND(O17 > $F15, O17 <= $F16), 1, 0) -> 1 | P18: =IF( AND(P17 > $F15, P17 <= $F16), 1, 0) -> 1 | Q18: =IF( AND(Q17 > $F15, Q17 <= $F16), 1, 0) -> 1 | ... AZ18: =IF( AND(AZ17 > $F15, AZ17 <= $F16), 1, 0) -> 0
E20: =InpC!E$10 -> Financial close date | F20: =InpC!F$10 -> 41698 | G20: =InpC!G$10 -> EOM
E21: =E$13 -> Construction period month ending | F21: =F$13 -> 0 | G21: =G$13 -> 0 | H21: =H$13 -> 0 | I21: =I$13 -> 0 | J21: =J$13 -> 41698 | K21: =K$13 -> 41729 | L21: =L$13 -> 41759 | ... AZ21: =AZ$13 -> 42978
E22: Financial close date flag | H22: =SUM(J22:AZ22) -> 1 | J22: =IF(J21 = $F20, 1, 0) -> 1 | K22: =IF(K21 = $F20, 1, 0) -> 0 | L22: =IF(L21 = $F20, 1, 0) -> 0 | M22: =IF(M21 = $F20, 1, 0) -> 0 | N22: =IF(N21 = $F20, 1, 0) -> 0 | O22: =IF(O21 = $F20, 1, 0) -> 0 | P22: =IF(P21 = $F20, 1, 0) -> 0 | Q22: =IF(Q21 = $F20, 1, 0) -> 0 | ... AZ22: =IF(AZ21 = $F20, 1, 0) -> 0
E24: =InpC!E$12 -> Construction period end / conversion date | F24: =InpC!F$12 -> 42369 | G24: =InpC!G$12 -> date
E25: =E$13 -> Construction period month ending | F25: =F$13 -> 0 | G25: =G$13 -> 0 | H25: =H$13 -> 0 | I25: =I$13 -> 0 | J25: =J$13 -> 41698 | K25: =K$13 -> 41729 | L25: =L$13 -> 41759 | ... AZ25: =AZ$13 -> 42978
E26: Construction period end / conversion date flag | H26: =SUM(J26:AZ26) -> 1 | J26: =IF(J25 = $F24, 1, 0) -> 0 | K26: =IF(K25 = $F24, 1, 0) -> 0 | L26: =IF(L25 = $F24, 1, 0) -> 0 | M26: =IF(M25 = $F24, 1, 0) -> 0 | N26: =IF(N25 = $F24, 1, 0) -> 0 | O26: =IF(O25 = $F24, 1, 0) -> 0 | P26: =IF(P25 = $F24, 1, 0) -> 0 | Q26: =IF(Q25 = $F24, 1, 0) -> 0 | ... AZ26: =IF(AZ25 = $F24, 1, 0) -> 0
E28: =InpC!E$11 -> Length of construction period | F28: =InpC!F$11 -> 22 | G28: =InpC!G$11 -> months
E29: =E$18 -> Construction / availability period flag | F29: =F$18 -> 0 | G29: =G$18 -> 0 | H29: =H$18 -> 22 | I29: =I$18 -> 0 | J29: =J$18 -> 0 | K29: =K$18 -> 1 | L29: =L$18 -> 1 | ... AZ29: =AZ$18 -> 0
E30: Level construction period payment schedule | H30: =SUM(J30:AZ30) -> 1 | J30: =J29 / $F28 -> 0 | K30: =K29 / $F28 -> 0.045454545 | L30: =L29 / $F28 -> 0.045454545 | M30: =M29 / $F28 -> 0.045454545 | N30: =N29 / $F28 -> 0.045454545 | O30: =O29 / $F28 -> 0.045454545 | P30: =P29 / $F28 -> 0.045454545 | Q30: =Q29 / $F28 -> 0.045454545 | ... AZ30: =AZ29 / $F28 -> 0

Sheet ConCost
A1: =RIGHT(CELL("filename", A1), LEN(CELL("filename", A1)) - SEARCH("]", CELL("filename", A1))) -> ConCost
E2: =ConTime!E$18 -> Construction / availability period flag | F2: =ConTime!F$18 -> 0 | G2: =ConTime!G$18 -> 0 | H2: =ConTime!H$18 -> 22 | I2: =ConTime!I$18 -> 0 | J2: =ConTime!J$18 -> 0 | K2: =ConTime!K$18 -> 1 | L2: =ConTime!L$18 -> 1 | ... AZ2: =ConTime!AZ$18 -> 0
E3: =ConTime!E$8 -> Construction period counter | F3: =ConTime!F$8 -> 0 | G3: =ConTime!G$8 -> 0 | H3: =ConTime!H$8 -> 0 | I3: =ConTime!I$8 -> 0 | J3: =ConTime!J$8 -> 1 | K3: =ConTime!K$8 -> 2 | L3: =ConTime!L$8 -> 3 | ... AZ3: =ConTime!AZ$8 -> 43
E4: =ConTime!E$13 -> Construction period month ending | F4: =ConTime!F$13 -> 0 | G4: =ConTime!G$13 -> 0 | H4: =ConTime!H$13 -> 0 | I4: =ConTime!I$13 -> 0 | J4: =ConTime!J$13 -> 41698 | K4: =ConTime!K$13 -> 41729 | L4: =ConTime!L$13 -> 41759 | ... AZ4: =ConTime!AZ$13 -> 42978
A6: CONSTRUCTION COSTS
B8: Base construction costs
E10: EPC contract price | F10: 310000 | G10: =SMU -> € 000s
E11: EPC milestone payment schedule | H11: =SUM(J11:AZ11) -> 1 | J11: 0.15 | K11: 0.03 | L11: 0.03 | M11: 0.03 | N11: 0.03 | O11: 0.03 | P11: 0.03 | Q11: 0.03 | R11: 0.03 | S11: 0.03 | T11: 0.03 | U11: 0.03 | V11: 0.03 | W11: 0.03 | X11: 0.03 | Y11: 0.03 | Z11: 0.03 | AA11: 0.03 | AB11: 0.03 | AC11: 0.03 | AD11: 0.03 | AE11: 0.03 | AF11: =3% + 19% -> 0.22
E12: EPC contract costs | G12: =SMU -> € 000s | H12: =SUM(J12:AZ12) -> 310000 | J12: =$F10 * J11 -> 46500 | K12: =$F10 * K11 -> 9300 | L12: =$F10 * L11 -> 9300 | M12: =$F10 * M11 -> 9300 | N12: =$F10 * N11 -> 9300 | O12: =$F10 * O11 -> 9300 | P12: =$F10 * P11 -> 9300 | Q12: =$F10 * Q11 -> 9300 | ... AZ12: =$F10 * AZ11 -> 0
E14: Development cost reimbursement | F14: 12000 | G14: =SMU -> € 000s
E15: =ConTime!E$22 -> Financial close date flag | F15: =ConTime!F$22 -> 0 | G15: =ConTime!G$22 -> 0 | H15: =ConTime!H$22 -> 1 | I15: =ConTime!I$22 -> 0 | J15: =ConTime!J$22 -> 1 | K15: =ConTime!K$22 -> 0 | L15: =ConTime!L$22 -> 0 | ... AZ15: =ConTime!AZ$22 -> 0
E16: Development cost | G16: =SMU -> € 000s | H16: =SUM(J16:AZ16) -> 12000 | J16: =$F14 * J15 -> 12000 | K16: =$F14 * K15 -> 0 | L16: =$F14 * L15 -> 0 | M16: =$F14 * M15 -> 0 | N16: =$F14 * N15 -> 0 | O16: =$F14 * O15 -> 0 | P16: =$F14 * P15 -> 0 | Q16: =$F14 * Q15 -> 0 | ... AZ16: =$F14 * AZ15 -> 0
E18: O&M mobilization costs input | F18: 8000 | G18: =SMU -> € 000s
E19: =ConTime!E$26 -> Construction period end / conversion date flag | F19: =ConTime!F$26 -> 0 | G19: =ConTime!G$26 -> 0 | H19: =ConTime!H$26 -> 1 | I19: =ConTime!I$26 -> 0 | J19: =ConTime!J$26 -> 0 | K19: =ConTime!K$26 -> 0 | L19: =ConTime!L$26 -> 0 | ... AZ19: =ConTime!AZ$26 -> 0
E20: O&M mobilization costs | G20: =SMU -> € 000s | H20: =SUM(J20:AZ20) -> 8000 | J20: =$F18 * J19 -> 0 | K20: =$F18 * K19 -> 0 | L20: =$F18 * L19 -> 0 | M20: =$F18 * M19 -> 0 | N20: =$F18 * N19 -> 0 | O20: =$F18 * O19 -> 0 | P20: =$F18 * P19 -> 0 | Q20: =$F18 * Q19 -> 0 | ... AZ20: =$F18 * AZ19 -> 0
E22: Owners G&A costs DC input | F22: 5000 | G22: =SMU -> € 000s
E23: =ConTime!E$30 -> Level construction period payment schedule | F23: =ConTime!F$30 -> 0 | G23: =ConTime!G$30 -> 0 | H23: =ConTime!H$30 -> 1 | I23: =ConTime!I$30 -> 0 | J23: =ConTime!J$30 -> 0 | K23: =ConTime!K$30 -> 0.045454545 | L23: =ConTime!L$30 -> 0.045454545 | ... AZ23: =ConTime!AZ$30 -> 0
E24: Owners G&A costs DC | G24: =SMU -> € 000s | H24: =SUM(J24:AZ24) -> 5000 | J24: =$F22 * J23 -> 0 | K24: =$F22 * K23 -> 227.27273 | L24: =$F22 * L23 -> 227.27273 | M24: =$F22 * M23 -> 227.27273 | N24: =$F22 * N23 -> 227.27273 | O24: =$F22 * O23 -> 227.27273 | P24: =$F22 * P23 -> 227.27273 | Q24: =$F22 * Q23 -> 227.27273 | ... AZ24: =$F22 * AZ23 -> 0
E26: =E$12 -> EPC contract costs | F26: =F$12 -> 0 | G26: =G$12 -> € 000s | H26: =H$12 -> 310000 | I26: =I$12 -> 0 | J26: =J$12 -> 46500 | K26: =K$12 -> 9300 | L26: =L$12 -> 9300 | ... AZ26: =AZ$12 -> 0
E27: =E$16 -> Development cost | F27: =F$16 -> 0 | G27: =G$16 -> € 000s | H27: =H$16 -> 12000 | I27: =I$16 -> 0 | J27: =J$16 -> 12000 | K27: =K$16 -> 0 | L27: =L$16 -> 0 | ... AZ27: =AZ$16 -> 0
E28: =E$20 -> O&M mobilization costs | F28: =F$20 -> 0 | G28: =G$20 -> € 000s | H28: =H$20 -> 8000 | I28: =I$20 -> 0 | J28: =J$20 -> 0 | K28: =K$20 -> 0 | L28: =L$20 -> 0 | ... AZ28: =AZ$20 -> 0
E29: =E$24 -> Owners G&A costs DC | F29: =F$24 -> 0 | G29: =G$24 -> € 000s | H29: =H$24 -> 5000 | I29: =I$24 -> 0 | J29: =J$24 -> 0 | K29: =K$24 -> 227.27273 | L29: =L$24 -> 227.27273 | ... AZ29: =AZ$24 -> 0
E30: Base construction costs | G30: =SMU -> € 000s | H30: =SUM(J30:AZ30) -> 335000 | J30: =SUM(J26:J29) -> 58500 | K30: =SUM(K26:K29) -> 9527.2727 | L30: =SUM(L26:L29) -> 9527.2727 | M30: =SUM(M26:M29) -> 9527.2727 | N30: =SUM(N26:N29) -> 9527.2727 | O30: =SUM(O26:O29) -> 9527.2727 | P30: =SUM(P26:P29) -> 9527.2727 | Q30: =SUM(Q26:Q29) -> 9527.2727 | ... AZ30: =SUM(AZ26:AZ29) -> 0
B33: Construction cost contingency
E35: Construction cost contingency | F35: 0.1 | G35: of BCC
E36: =E$30 -> Base construction costs | F36: =F$30 -> 0 | G36: =G$30 -> € 000s | H36: =H$30 -> 335000 | I36: =I$30 -> 0 | J36: =J$30 -> 58500 | K36: =K$30 -> 9527.2727 | L36: =L$30 -> 9527.2727 | ... AZ36: =AZ$30 -> 0
E37: Construction cost contingency | H37: =SUM(J37:AZ37) -> 33500 | J37: =$F35 * J36 -> 5850 | K37: =$F35 * K36 -> 952.72727 | L37: =$F35 * L36 -> 952.72727 | M37: =$F35 * M36 -> 952.72727 | N37: =$F35 * N36 -> 952.72727 | O37: =$F35 * O36 -> 952.72727 | P37: =$F35 * P36 -> 952.72727 | Q37: =$F35 * Q36 -> 952.72727 | ... AZ37: =$F35 * AZ36 -> 0
E39: =E$30 -> Base construction costs | F39: =F$30 -> 0 | G39: =G$30 -> € 000s | H39: =H$30 -> 335000 | I39: =I$30 -> 0 | J39: =J$30 -> 58500 | K39: =K$30 -> 9527.2727 | L39: =L$30 -> 9527.2727 | ... AZ39: =AZ$30 -> 0
E40: =E$37 -> Construction cost contingency | F40: =F$37 -> 0 | G40: =G$37 -> 0 | H40: =H$37 -> 33500 | I40: =I$37 -> 0 | J40: =J$37 -> 5850 | K40: =K$37 -> 952.72727 | L40: =L$37 -> 952.72727 | ... AZ40: =AZ$37 -> 0
E41: Construction costs | G41: =SMU -> € 000s | H41: =SUM(J41:AZ41) -> 368500 | J41: =SUM(J39:J40) -> 64350 | K41: =SUM(K39:K40) -> 10480 | L41: =SUM(L39:L40) -> 10480 | M41: =SUM(M39:M40) -> 10480 | N41: =SUM(N39:N40) -> 10480 | O41: =SUM(O39:O40) -> 10480 | P41: =SUM(P39:P40) -> 10480 | Q41: =SUM(Q39:Q40) -> 10480 | ... AZ41: =SUM(AZ39:AZ40) -> 0
E43: =E$41 -> Construction costs | F43: =F$41 -> 0 | G43: =G$41 -> € 000s | H43: =H$41 -> 368500 | I43: =I$41 -> 0 | J43: =J$41 -> 64350 | K43: =K$41 -> 10480 | L43: =L$41 -> 10480 | ... AZ43: =AZ$41 -> 0
E44: =E43 & " NEG (for XIRR)" -> Construction costs NEG (for XIRR) | G44: =G43 -> € 000s | H44: =SUM(J44:AZ44) -> -368500 | J44: =-1 * J43 -> -64350 | K44: =-1 * K43 -> -10480 | L44: =-1 * L43 -> -10480 | M44: =-1 * M43 -> -10480 | N44: =-1 * N43 -> -10480 | O44: =-1 * O43 -> -10480 | P44: =-1 * P43 -> -10480 | Q44: =-1 * Q43 -> -10480 | ... AZ44: =-1 * AZ43 -> 0

Sheet ConFin
A1: =RIGHT(CELL("filename", A1), LEN(CELL("filename", A1)) - SEARCH("]", CELL("filename", A1))) -> ConFin
E2: =ConTime!E$18 -> Construction / availability period flag | F2: =ConTime!F$18 -> 0 | G2: =ConTime!G$18 -> 0 | H2: =ConTime!H$18 -> 22 | I2: =ConTime!I$18 -> 0 | J2: =ConTime!J$18 -> 0 | K2: =ConTime!K$18 -> 1 | L2: =ConTime!L$18 -> 1 | ... AZ2: =ConTime!AZ$18 -> 0
E3: =ConTime!E$8 -> Construction period counter | F3: =ConTime!F$8 -> 0 | G3: =ConTime!G$8 -> 0 | H3: =ConTime!H$8 -> 0 | I3: =ConTime!I$8 -> 0 | J3: =ConTime!J$8 -> 1 | K3: =ConTime!K$8 -> 2 | L3: =ConTime!L$8 -> 3 | ... AZ3: =ConTime!AZ$8 -> 43
E4: =ConTime!E$13 -> Construction period month ending | F4: =ConTime!F$13 -> 0 | G4: =ConTime!G$13 -> 0 | H4: =ConTime!H$13 -> 0 | I4: =ConTime!I$13 -> 0 | J4: =ConTime!J$13 -> 41698 | K4: =ConTime!K$13 -> 41729 | L4: =ConTime!L$13 -> 41759 | ... AZ4: =ConTime!AZ$13 -> 42978
A6: FINANCE COSTS DC
E8: Arrangement fee rate | F8: 0.02 | G8: of comm
E9: Commitment amount | F9: 390000 | G9: =SMU -> € 000s
E10: =ConTime!E$22 -> Financial close date flag | F10: =ConTime!F$22 -> 0 | G10: =ConTime!G$22 -> 0 | H10: =ConTime!H$22 -> 1 | I10: =ConTime!I$22 -> 0 | J10: =ConTime!J$22 -> 1 | K10: =ConTime!K$22 -> 0 | L10: =ConTime!L$22 -> 0 | ... AZ10: =ConTime!AZ$22 -> 0
E11: Arrangement fees | H11: =SUM(J11:AZ11) -> 7800 | J11: =$F8 * $F9 * J10 -> 7800 | K11: =$F8 * $F9 * K10 -> 0 | L11: =$F8 * $F9 * L10 -> 0 | M11: =$F8 * $F9 * M10 -> 0 | N11: =$F8 * $F9 * N10 -> 0 | O11: =$F8 * $F9 * O10 -> 0 | P11: =$F8 * $F9 * P10 -> 0 | Q11: =$F8 * $F9 * Q10 -> 0 | ... AZ11: =$F8 * $F9 * AZ10 -> 0
E13: Agent bank fee monthly rate | F13: 30 | G13: =SMU & " pcm" -> € 000s pcm
E14: =ConTime!E$18 -> Construction / availability period flag | F14: =ConTime!F$18 -> 0 | G14: =ConTime!G$18 -> 0 | H14: =ConTime!H$18 -> 22 | I14: =ConTime!I$18 -> 0 | J14: =ConTime!J$18 -> 0 | K14: =ConTime!K$18 -> 1 | L14: =ConTime!L$18 -> 1 | ... AZ14: =ConTime!AZ$18 -> 0
E15: [Indexation factor DC] | J15: 1 | K15: 1 | L15: 1 | M15: 1 | N15: 1 | O15: 1 | P15: 1 | Q15: 1 | R15: 1 | S15: 1 | T15: 1 | U15: 1 | V15: 1 | W15: 1 | X15: 1 | Y15: 1 | Z15: 1 | AA15: 1 | AB15: 1 | AC15: 1 | AD15: 1 | AE15: 1 | AF15: 1 | AG15: 1 | AH15: 1 | AI15: 1 | AJ15: 1 | AK15: 1 | AL15: 1 | AM15: 1 | AN15: 1 | AO15: 1 | AP15: 1 | AQ15: 1 | AR15: 1 | AS15: 1 | AT15: 1 | AU15: 1 | AV15: 1 | AW15: 1 | AX15: 1 | AY15: 1 | AZ15: 1
E16: Agent bank fees DC | H16: =SUM(J16:AZ16) -> 660 | J16: =$F13 * J14 * J15 -> 0 | K16: =$F13 * K14 * K15 -> 30 | L16: =$F13 * L14 * L15 -> 30 | M16: =$F13 * M14 * M15 -> 30 | N16: =$F13 * N14 * N15 -> 30 | O16: =$F13 * O14 * O15 -> 30 | P16: =$F13 * P14 * P15 -> 30 | Q16: =$F13 * Q14 * Q15 -> 30 | ... AZ16: =$F13 * AZ14 * AZ15 -> 0
B19: Interest during construction (IDC)
E21: LIBOR + MLA debt base rate | F21: 0.03 | G21: p.a. (360-day)
E22: Construction debt margin | F22: 0.0275 | G22: p.a. (360-day)
E23: [Swap counter-party risk premium] | G23: few basis point
E24: [Contingency for interest rate movements] | G24: 50 bps?
E25: Nominal annual interest rate DC | F25: =SUM(F21:F24) -> 0.0575 | G25: p.a. (360-day)
E27: Days in LIBOR year | F27: 360 | G27: days
E28: Construction debt daily interest rate | F28: =F25 / F27 -> 0.00015972222 | G28: per day
E30: =ConTime!E$13 -> Construction period month ending | F30: =ConTime!F$13 -> 0 | G30: =ConTime!G$13 -> 0 | H30: =ConTime!H$13 -> 0 | I30: =ConTime!I$13 -> 0 | J30: =ConTime!J$13 -> 41698 | K30: =ConTime!K$13 -> 41729 | L30: =ConTime!L$13 -> 41759 | ... AZ30: =ConTime!AZ$13 -> 42978
E31: =ConTime!E$18 -> Construction / availability period flag | F31: =ConTime!F$18 -> 0 | G31: =ConTime!G$18 -> 0 | H31: =ConTime!H$18 -> 22 | I31: =ConTime!I$18 -> 0 | J31: =ConTime!J$18 -> 0 | K31: =ConTime!K$18 -> 1 | L31: =ConTime!L$18 -> 1 | ... AZ31: =ConTime!AZ$18 -> 0
E32: Number of days in period DC | J32: =(J30 - I30) * J31 -> 0 | K32: =(K30 - J30) * K31 -> 31 | L32: =(L30 - K30) * L31 -> 30 | M32: =(M30 - L30) * M31 -> 31 | N32: =(N30 - M30) * N31 -> 30 | O32: =(O30 - N30) * O31 -> 31 | P32: =(P30 - O30) * P31 -> 31 | Q32: =(Q30 - P30) * Q31 -> 30 | ... AZ32: =(AZ30 - AY30) * AZ31 -> 0
E34: =E$28 -> Construction debt daily interest rate | F34: =F$28 -> 0.00015972222 | G34: =G$28 -> per day
E35: =E$86 -> Construction debt balance BEG | F35: =F$86 -> 0 | G35: =G$86 -> 0 | H35: =H$86 -> 0 | I35: =I$86 -> 0 | J35: =J$86 -> 0 | K35: =K$86 -> 57720 | L35: =L$86 -> 66467.395 | ... AZ35: =AZ$86 -> 0
E36: =E$32 -> Number of days in period DC | F36: =F$32 -> 0 | G36: =G$32 -> 0 | H36: =H$32 -> 0 | I36: =I$32 -> 0 | J36: =J$32 -> 0 | K36: =K$32 -> 31 | L36: =L$32 -> 30 | ... AZ36: =AZ$32 -> 0
E37: Interest during construction | H37: =SUM(J37:AZ37) -> 16260.924 | J37: =$F34 * J35 * J36 -> 0 | K37: =$F34 * K35 * K36 -> 285.79417 | L37: =$F34 * L35 * L36 -> 318.4896 | M37: =$F34 * M35 * M36 -> 372.53275 | N37: =$F34 * N35 * N36 -> 402.73469 | O37: =$F34 * O35 * O36 -> 459.89069 | P37: =$F34 * P35 * P36 -> 503.83403 | Q37: =$F34 * Q35 * Q36 -> 530.26141 | ... AZ37: =$F34 * AZ35 * AZ36 -> 0
E39: Interest during construction PASTE before FC hook-up | H39: 15645.761 | J39: 0 | K39: 285.79417 | L39: 316.86333 | M39: 369.05672 | N39: 397.44 | O39: 452.31928 | P39: 493.95056 | Q39: 518.305 | R39: 577.21311 | S39: 598.88167 | T39: 660.47567 | U39: 702.10694 | V39: 671.76356 | W39: 785.3695 | X39: 800.32333 | Y39: 868.63206 | Z39: 880.9 | AA39: 951.89461 | AB39: 993.52589 | AC39: 1001.765 | AD39: 1076.7884 | AE39: 1082.3417 | AF39: 1160.051 | AG39: 0 | AH39: 0 | AI39: 0 | AJ39: 0 | AK39: 0 | AL39: 0 | AM39: 0 | AN39: 0 | AO39: 0 | AP39: 0 | AQ39: 0 | AR39: 0 | AS39: 0 | AT39: 0 | AU39: 0 | AV39: 0 | AW39: 0 | AX39: 0 | AY39: 0 | AZ39: 0
E40: Difference | H40: =SUM(J40:AZ40) -> 615.16233 | J40: =J37 - J39 -> 0 | K40: =K37 - K39 -> 0 | L40: =L37 - L39 -> 1.6262693 | M40: =M37 - M39 -> 3.4760296 | N40: =N37 - N39 -> 5.2946866 | O40: =O37 - O39 -> 7.5714138 | P40: =P37 - P39 -> 9.8834756 | Q40: =Q37 - Q39 -> 11.956407 | ... AZ40: =AZ37 - AZ39 -> 0
B43: Commitement fees
E45: Commitment amount | F45: 390000 | G45: =SMU -> € 000s
E46: =E$86 -> Construction debt balance BEG | F46: =F$86 -> 0 | G46: =G$86 -> 0 | H46: =H$86 -> 0 | I46: =I$86 -> 0 | J46: =J$86 -> 0 | K46: =K$86 -> 57720 | L46: =L$86 -> 66467.395 | ... AZ46: =AZ$86 -> 0
E47: Undrawn construction debt commitment balance | J47: =$F45 - J46 -> 390000 | K47: =$F45 - K46 -> 332280 | L47: =$F45 - L46 -> 323532.6 | M47: =$F45 - M46 -> 314761.97 | N47: =$F45 - N46 -> 305951.02 | O47: =$F45 - O46 -> 297118.85 | P47: =$F45 - P46 -> 288243.9 | Q47: =$F45 - Q46 -> 279336.75 | ... AZ47: =$F45 - AZ46 -> 390000
E49: Commitment fee rate | F49: 0.005 | G49: p.a.
E50: =E$47 -> Undrawn construction debt commitment balance | F50: =F$47 -> 0 | G50: =G$47 -> 0 | H50: =H$47 -> 0 | I50: =I$47 -> 0 | J50: =J$47 -> 390000 | K50: =K$47 -> 332280 | L50: =L$47 -> 323532.6 | ... AZ50: =AZ$47 -> 390000
E51: =ConTime!E$18 -> Construction / availability period flag | F51: =ConTime!F$18 -> 0 | G51: =ConTime!G$18 -> 0 | H51: =ConTime!H$18 -> 22 | I51: =ConTime!I$18 -> 0 | J51: =ConTime!J$18 -> 0 | K51: =ConTime!K$18 -> 1 | L51: =ConTime!L$18 -> 1 | ... AZ51: =ConTime!AZ$18 -> 0
E52: Commitment fees | H52: =SUM(J52:AZ52) -> 2184.0209 | J52: =($F49 / 12) * J50 * J51 -> 0 | K52: =($F49 / 12) * K50 * K51 -> 138.45 | L52: =($F49 / 12) * L50 * L51 -> 134.80525 | M52: =($F49 / 12) * M50 * M51 -> 131.15082 | N52: =($F49 / 12) * N50 * N51 -> 127.47959 | O52: =($F49 / 12) * O50 * O51 -> 123.79952 | P52: =($F49 / 12) * P50 * P51 -> 120.10162 | Q52: =($F49 / 12) * Q50 * Q51 -> 116.39031 | ... AZ52: =($F49 / 12) * AZ50 * AZ51 -> 0
E54: Senior DSRA - Initial balance | F54: 8000 | G54: =SMU -> € 000s
E55: =ConTime!E$26 -> Construction period end / conversion date flag | F55: =ConTime!F$26 -> 0 | G55: =ConTime!G$26 -> 0 | H55: =ConTime!H$26 -> 1 | I55: =ConTime!I$26 -> 0 | J55: =ConTime!J$26 -> 0 | K55: =ConTime!K$26 -> 0 | L55: =ConTime!L$26 -> 0 | ... AZ55: =ConTime!AZ$26 -> 0
E56: Senior DSRA deposits DC | H56: =SUM(J56:AZ56) -> 8000 | J56: =$F54 * J55 -> 0 | K56: =$F54 * K55 -> 0 | L56: =$F54 * L55 -> 0 | M56: =$F54 * M55 -> 0 | N56: =$F54 * N55 -> 0 | O56: =$F54 * O55 -> 0 | P56: =$F54 * P55 -> 0 | Q56: =$F54 * Q55 -> 0 | ... AZ56: =$F54 * AZ55 -> 0
E57: =E56 & " total" -> Senior DSRA deposits DC total | F57: =SUM(J56:AZ56) -> 8000 | G57: =SMU -> € 000s
B60: Finance cost summary
E62: =E$11 -> Arrangement fees | F62: =F$11 -> 0 | G62: =G$11 -> 0 | H62: =H$11 -> 7800 | I62: =I$11 -> 0 | J62: =J$11 -> 7800 | K62: =K$11 -> 0 | L62: =L$11 -> 0 | ... AZ62: =AZ$11 -> 0
E63: =E$16 -> Agent bank fees DC | F63: =F$16 -> 0 | G63: =G$16 -> 0 | H63: =H$16 -> 660 | I63: =I$16 -> 0 | J63: =J$16 -> 0 | K63: =K$16 -> 30 | L63: =L$16 -> 30 | ... AZ63: =AZ$16 -> 0
E64: =E$37 -> Interest during construction | F64: =F$37 -> 0 | G64: =G$37 -> 0 | H64: =H$37 -> 16260.924 | I64: =I$37 -> 0 | J64: =J$37 -> 0 | K64: =K$37 -> 285.79417 | L64: =L$37 -> 318.4896 | ... AZ64: =AZ$37 -> 0
E65: =E$52 -> Commitment fees | F65: =F$52 -> 0 | G65: =G$52 -> 0 | H65: =H$52 -> 2184.0209 | I65: =I$52 -> 0 | J65: =J$52 -> 0 | K65: =K$52 -> 138.45 | L65: =L$52 -> 134.80525 | ... AZ65: =AZ$52 -> 0
E66: =E$56 -> Senior DSRA deposits DC | F66: =F$56 -> 0 | G66: =G$56 -> 0 | H66: =H$56 -> 8000 | I66: =I$56 -> 0 | J66: =J$56 -> 0 | K66: =K$56 -> 0 | L66: =L$56 -> 0 | ... AZ66: =AZ$56 -> 0
E67: Finance costs DC | H67: =SUM(J67:AZ67) -> 34904.945 | J67: =SUM(J62:J66) -> 7800 | K67: =SUM(K62:K66) -> 454.24417 | L67: =SUM(L62:L66) -> 483.29485 | M67: =SUM(M62:M66) -> 533.68357 | N67: =SUM(N62:N66) -> 560.21428 | O67: =SUM(O62:O66) -> 613.69021 | P67: =SUM(P62:P66) -> 653.93566 | Q67: =SUM(Q62:Q66) -> 676.65172 | ... AZ67: =SUM(AZ62:AZ66) -> 0
A70: CONSTRUCTION DEBT BALANCE
E72: =ConCost!E$41 -> Construction costs | F72: =ConCost!F$41 -> 0 | G72: =ConCost!G$41 -> € 000s | H72: =ConCost!H$41 -> 368500 | I72: =ConCost!I$41 -> 0 | J72: =ConCost!J$41 -> 64350 | K72: =ConCost!K$41 -> 10480 | L72: =ConCost!L$41 -> 10480 | ... AZ72: =ConCost!AZ$41 -> 0
E73: =E$67 -> Finance costs DC | F73: =F$67 -> 0 | G73: =G$67 -> 0 | H73: =H$67 -> 34904.945 | I73: =I$67 -> 0 | J73: =J$67 -> 7800 | K73: =K$67 -> 454.24417 | L73: =L$67 -> 483.29485 | ... AZ73: =AZ$67 -> 0
E74: Sources / Uses of cash | H74: =SUM(J74:AZ74) -> 403404.94 | J74: =SUM(J72:J73) -> 72150 | K74: =SUM(K72:K73) -> 10934.244 | L74: =SUM(L72:L73) -> 10963.295 | M74: =SUM(M72:M73) -> 11013.684 | N74: =SUM(N72:N73) -> 11040.214 | O74: =SUM(O72:O73) -> 11093.69 | P74: =SUM(P72:P73) -> 11133.936 | Q74: =SUM(Q72:Q73) -> 11156.652 | ... AZ74: =SUM(AZ72:AZ73) -> 0
E76: Leverage input | F76: 0.8 | G76: of QCR
E77: =E$74 -> Sources / Uses of cash | F77: =F$74 -> 0 | G77: =G$74 -> 0 | H77: =H$74 -> 403404.94 | I77: =I$74 -> 0 | J77: =J$74 -> 72150 | K77: =K$74 -> 10934.244 | L77: =L$74 -> 10963.295 | ... AZ77: =AZ$74 -> 0
E78: Construction debt draws | H78: =SUM(J78:AZ78) -> 322723.96 | J78: =$F76 * J77 -> 57720 | K78: =$F76 * K77 -> 8747.3953 | L78: =$F76 * L77 -> 8770.6359 | M78: =$F76 * M77 -> 8810.9469 | N78: =$F76 * N77 -> 8832.1714 | O78: =$F76 * O77 -> 8874.9522 | P78: =$F76 * P77 -> 8907.1485 | Q78: =$F76 * Q77 -> 8925.3214 | ... AZ78: =$F76 * AZ77 -> 0
E80: =E$86 -> Construction debt balance BEG | F80: =F$86 -> 0 | G80: =G$86 -> 0 | H80: =H$86 -> 0 | I80: =I$86 -> 0 | J80: =J$86 -> 0 | K80: =K$86 -> 57720 | L80: =L$86 -> 66467.395 | ... AZ80: =AZ$86 -> 0
D81: plus: | E81: =E$78 -> Construction debt draws | F81: =F$78 -> 0 | G81: =G$78 -> 0 | H81: =H$78 -> 322723.96 | I81: =I$78 -> 0 | J81: =J$78 -> 57720 | K81: =K$78 -> 8747.3953 | L81: =L$78 -> 8770.6359 | ... AZ81: =AZ$78 -> 0
E82: =ConTime!E$26 -> Construction period end / conversion date flag | F82: =ConTime!F$26 -> 0 | G82: =ConTime!G$26 -> 0 | H82: =ConTime!H$26 -> 1 | I82: =ConTime!I$26 -> 0 | J82: =ConTime!J$26 -> 0 | K82: =ConTime!K$26 -> 0 | L82: =ConTime!L$26 -> 0 | ... AZ82: =ConTime!AZ$26 -> 0
E83: Construction debt converted to term | H83: =SUM(J83:AZ83) -> 322723.96 | J83: =SUM(J80:J81) * J82 -> 0 | K83: =SUM(K80:K81) * K82 -> 0 | L83: =SUM(L80:L81) * L82 -> 0 | M83: =SUM(M80:M81) * M82 -> 0 | N83: =SUM(N80:N81) * N82 -> 0 | O83: =SUM(O80:O81) * O82 -> 0 | P83: =SUM(P80:P81) * P82 -> 0 | Q83: =SUM(Q80:Q81) * Q82 -> 0 | ... AZ83: =SUM(AZ80:AZ81) * AZ82 -> 0
E84: =E83 & " total" -> Construction debt converted to term total | F84: =SUM(J83:AZ83) -> 322723.96 | G84: =SMU -> € 000s
E86: Construction debt balance BEG | J86: =I89 -> 0 | K86: =J89 -> 57720 | L86: =K89 -> 66467.395 | M86: =L89 -> 75238.031 | N86: =M89 -> 84048.978 | O86: =N89 -> 92881.149 | P86: =O89 -> 101756.1 | Q86: =P89 -> 110663.25 | ... AZ86: =AY89 -> 0
D87: plus: | E87: =E$78 -> Construction debt draws | F87: =F$78 -> 0 | G87: =G$78 -> 0 | H87: =H$78 -> 322723.96 | I87: =I$78 -> 0 | J87: =J$78 -> 57720 | K87: =K$78 -> 8747.3953 | L87: =L$78 -> 8770.6359 | ... AZ87: =AZ$78 -> 0
D88: less: | E88: =E$83 -> Construction debt converted to term | F88: =F$83 -> 0 | G88: =G$83 -> 0 | H88: =H$83 -> 322723.96 | I88: =I$83 -> 0 | J88: =J$83 -> 0 | K88: =K$83 -> 0 | L88: =L$83 -> 0 | ... AZ88: =AZ$83 -> 0
E89: Construction debt balance BEG | J89: =J86 + J87 - J88 -> 57720 | K89: =K86 + K87 - K88 -> 66467.395 | L89: =L86 + L87 - L88 -> 75238.031 | M89: =M86 + M87 - M88 -> 84048.978 | N89: =N86 + N87 - N88 -> 92881.149 | O89: =O86 + O87 - O88 -> 101756.1 | P89: =P86 + P87 - P88 -> 110663.25 | Q89: =Q86 + Q87 - Q88 -> 119588.57 | ... AZ89: =AZ86 + AZ87 - AZ88 -> 0
A92: EQUITY INVESTMENT
E94: =E$74 -> Sources / Uses of cash | F94: =F$74 -> 0 | G94: =G$74 -> 0 | H94: =H$74 -> 403404.94 | I94: =I$74 -> 0 | J94: =J$74 -> 72150 | K94: =K$74 -> 10934.244 | L94: =L$74 -> 10963.295 | ... AZ94: =AZ$74 -> 0
D95: less: | E95: =E$78 -> Construction debt draws | F95: =F$78 -> 0 | G95: =G$78 -> 0 | H95: =H$78 -> 322723.96 | I95: =I$78 -> 0 | J95: =J$78 -> 57720 | K95: =K$78 -> 8747.3953 | L95: =L$78 -> 8770.6359 | ... AZ95: =AZ$78 -> 0
E96: Equity investment | H96: =SUM(J96:AZ96) -> 80680.989 | J96: =J94 - J95 -> 14430 | K96: =K94 - K95 -> 2186.8488 | L96: =L94 - L95 -> 2192.659 | M96: =M94 - M95 -> 2202.7367 | N96: =N94 - N95 -> 2208.0429 | O96: =O94 - O95 -> 2218.738 | P96: =P94 - P95 -> 2226.7871 | Q96: =Q94 - Q95 -> 2231.3303 | ... AZ96: =AZ94 - AZ95 -> 0
E97: =E96 & " total" -> Equity investment total | F97: =SUM(J96:AZ96) -> 80680.989 | G97: =SMU -> € 000s
E99: =E$96 -> Equity investment | F99: =F$96 -> 0 | G99: =G$96 -> 0 | H99: =H$96 -> 80680.989 | I99: =I$96 -> 0 | J99: =J$96 -> 14430 | K99: =K$96 -> 2186.8488 | L99: =L$96 -> 2192.659 | ... AZ99: =AZ$96 -> 0
E100: =E99 & " NEG (for XIRR)" -> Equity investment NEG (for XIRR) | G100: =G99 -> 0 | H100: =SUM(J100:AZ100) -> -80680.989 | J100: =-1 * J99 -> -14430 | K100: =-1 * K99 -> -2186.8488 | L100: =-1 * L99 -> -2192.659 | M100: =-1 * M99 -> -2202.7367 | N100: =-1 * N99 -> -2208.0429 | O100: =-1 * O99 -> -2218.738 | P100: =-1 * P99 -> -2226.7871 | Q100: =-1 * Q99 -> -2231.3303 | ... AZ100: =-1 * AZ99 -> 0
A103: PV OF EQUITY INVESTMENT
E105: Shareholder valuation date | F105: 41578 | G105: eom
E106: =ConTime!E$13 -> Construction period month ending | F106: =ConTime!F$13 -> 0 | G106: =ConTime!G$13 -> 0 | H106: =ConTime!H$13 -> 0 | I106: =ConTime!I$13 -> 0 | J106: =ConTime!J$13 -> 41698 | K106: =ConTime!K$13 -> 41729 | L106: =ConTime!L$13 -> 41759 | ... AZ106: =ConTime!AZ$13 -> 42978
E107: Days from valuation date | J107: =J106 - $F105 -> 120 | K107: =K106 - $F105 -> 151 | L107: =L106 - $F105 -> 181 | M107: =M106 - $F105 -> 212 | N107: =N106 - $F105 -> 242 | O107: =O106 - $F105 -> 273 | P107: =P106 - $F105 -> 304 | Q107: =Q106 - $F105 -> 334 | ... AZ107: =AZ106 - $F105 -> 1400
E108: Years from valuation date | J108: =J107 / 365 -> 0.32876712 | K108: =K107 / 365 -> 0.41369863 | L108: =L107 / 365 -> 0.49589041 | M108: =M107 / 365 -> 0.58082192 | N108: =N107 / 365 -> 0.6630137 | O108: =O107 / 365 -> 0.74794521 | P108: =P107 / 365 -> 0.83287671 | Q108: =Q107 / 365 -> 0.91506849 | ... AZ108: =AZ107 / 365 -> 3.8356164
E110: =InpC!E$55 -> Shareholder discount rate | F110: =InpC!F$55 -> 0.13 | G110: =InpC!G$55 -> p.a. (365)
E111: =E108 -> Years from valuation date | F111: =F108 -> 0 | G111: =G108 -> 0 | H111: =H108 -> 0 | I111: =I108 -> 0 | J111: =J108 -> 0.32876712 | K111: =K108 -> 0.41369863 | L111: =L108 -> 0.49589041 | ... AZ111: =AZ108 -> 3.8356164
E112: Shareholder discount factor - monthly | J112: =(1 + $F110) ^ (-1 * J111) -> 0.96061542 | K112: =(1 + $F110) ^ (-1 * K111) -> 0.95069568 | L112: =(1 + $F110) ^ (-1 * L111) -> 0.94119348 | M112: =(1 + $F110) ^ (-1 * M111) -> 0.9314743 | N112: =(1 + $F110) ^ (-1 * N111) -> 0.92216421 | O112: =(1 + $F110) ^ (-1 * O111) -> 0.91264154 | P112: =(1 + $F110) ^ (-1 * P111) -> 0.9032172 | Q112: =(1 + $F110) ^ (-1 * Q111) -> 0.89418955 | ... AZ112: =(1 + $F110) ^ (-1 * AZ111) -> 0.62576526
E114: =E$96 -> Equity investment | F114: =F$96 -> 0 | G114: =G$96 -> 0 | H114: =H$96 -> 80680.989 | I114: =I$96 -> 0 | J114: =J$96 -> 14430 | K114: =K$96 -> 2186.8488 | L114: =L$96 -> 2192.659 | ... AZ114: =AZ$96 -> 0
E115: =E112 -> Shareholder discount factor - monthly | F115: =F112 -> 0 | G115: =G112 -> 0 | H115: =H112 -> 0 | I115: =I112 -> 0 | J115: =J112 -> 0.96061542 | K115: =K112 -> 0.95069568 | L115: =L112 -> 0.94119348 | ... AZ115: =AZ112 -> 0.62576526
E116: Period PVs of investment | H116: =SUM(J116:CA116) -> 69059.673 | J116: =J114 * J115 -> 13861.68 | K116: =K114 * K115 -> 2079.0277 | L116: =L114 * L115 -> 2063.7163 | M116: =M114 * M115 -> 2051.7926 | N116: =N114 * N115 -> 2036.1781 | O116: =O114 * O115 -> 2024.9125 | P116: =P114 * P115 -> 2011.2724 | Q116: =Q114 * Q115 -> 1995.2323 | ... AZ116: =AZ114 * AZ115 -> 0
E117: PV of equity investment | F117: =SUM(J116:CA116) -> 69059.673 | G117: =SMU -> € 000s
A120: ADDITIONS TO FIXED ASSETS DC
E122: =ConCost!E$41 -> Construction costs | F122: =ConCost!F$41 -> 0 | G122: =ConCost!G$41 -> € 000s | H122: =ConCost!H$41 -> 368500 | I122: =ConCost!I$41 -> 0 | J122: =ConCost!J$41 -> 64350 | K122: =ConCost!K$41 -> 10480 | L122: =ConCost!L$41 -> 10480 | ... AZ122: =ConCost!AZ$41 -> 0
E123: =E$11 -> Arrangement fees | F123: =F$11 -> 0 | G123: =G$11 -> 0 | H123: =H$11 -> 7800 | I123: =I$11 -> 0 | J123: =J$11 -> 7800 | K123: =K$11 -> 0 | L123: =L$11 -> 0 | ... AZ123: =AZ$11 -> 0
E124: =E$16 -> Agent bank fees DC | F124: =F$16 -> 0 | G124: =G$16 -> 0 | H124: =H$16 -> 660 | I124: =I$16 -> 0 | J124: =J$16 -> 0 | K124: =K$16 -> 30 | L124: =L$16 -> 30 | ... AZ124: =AZ$16 -> 0
E125: =E$37 -> Interest during construction | F125: =F$37 -> 0 | G125: =G$37 -> 0 | H125: =H$37 -> 16260.924 | I125: =I$37 -> 0 | J125: =J$37 -> 0 | K125: =K$37 -> 285.79417 | L125: =L$37 -> 318.4896 | ... AZ125: =AZ$37 -> 0
E126: =E$52 -> Commitment fees | F126: =F$52 -> 0 | G126: =G$52 -> 0 | H126: =H$52 -> 2184.0209 | I126: =I$52 -> 0 | J126: =J$52 -> 0 | K126: =K$52 -> 138.45 | L126: =L$52 -> 134.80525 | ... AZ126: =AZ$52 -> 0
E127: Additions to fixed assets DC | H127: =SUM(J127:AZ127) -> 395404.94 | J127: =SUM(J122:J126) -> 72150 | K127: =SUM(K122:K126) -> 10934.244 | L127: =SUM(L122:L126) -> 10963.295 | M127: =SUM(M122:M126) -> 11013.684 | N127: =SUM(N122:N126) -> 11040.214 | O127: =SUM(O122:O126) -> 11093.69 | P127: =SUM(P122:P126) -> 11133.936 | Q127: =SUM(Q122:Q126) -> 11156.652 | ... AZ127: =SUM(AZ122:AZ126) -> 0
E128: =E127 & " total" -> Additions to fixed assets DC total | F128: =SUM(J127:AZ127) -> 395404.94 | G128: =SMU -> € 000s

Sheet T&E
A1: =RIGHT(CELL("filename", A1), LEN(CELL("filename", A1)) - SEARCH("]", CELL("filename", A1))) -> T&E
E2: =E$24 -> Operating period flag | F2: =F$24 -> 0 | G2: =G$24 -> flag | H2: =H$24 -> 60 | I2: =I$24 -> 0 | J2: =J$24 -> 0 | K2: =K$24 -> 0 | L2: =L$24 -> 0 | ... CA2: =CA$24 -> 0
E3: ='T&E'!E$8 -> Model column counter | F3: ='T&E'!F$8 -> 0 | G3: ='T&E'!G$8 -> 0 | H3: ='T&E'!H$8 -> 0 | I3: ='T&E'!I$8 -> 0 | J3: ='T&E'!J$8 -> 1 | K3: ='T&E'!K$8 -> 2 | L3: ='T&E'!L$8 -> 3 | ... CA3: ='T&E'!CA$8 -> 70
E4: =E$12 -> Model period ending | F4: =F$12 -> constant | G4: =G$12 -> unit | H4: =H$12 -> total | I4: =I$12 -> 0 | J4: =J$12 -> 41639 | K4: =K$12 -> 41820 | L4: =L$12 -> 42004 | ... CA4: =CA$12 -> 54239
A6: TIME RULER
E8: Model column counter | J8: =I8 + 1 -> 1 | K8: =J8 + 1 -> 2 | L8: =K8 + 1 -> 3 | M8: =L8 + 1 -> 4 | N8: =M8 + 1 -> 5 | O8: =N8 + 1 -> 6 | P8: =O8 + 1 -> 7 | Q8: =P8 + 1 -> 8 | ... CA8: =BZ8 + 1 -> 70
E10: =InpC!E$8 -> First date of time ruler | F10: =InpC!F$8 -> 41639 | G10: =InpC!G$8 -> date
E11: =E$8 -> Model column counter | F11: =F$8 -> 0 | G11: integer | H11: =H$8 -> 0 | I11: =I$8 -> 0 | J11: =J$8 -> 1 | K11: =K$8 -> 2 | L11: =L$8 -> 3 | M11: =M$8 -> 4 | N11: =N$8 -> 5 | O11: =O$8 -> 6 | ... CA11: =CA$8 -> 70
E12: Model period ending | F12: constant | G12: unit | H12: total | J12: =IF( J11 = 1, $F10,EOMONTH( I12, 6 ) ) -> 41639 | K12: =IF( K11 = 1, $F10,EOMONTH( J12, 6 ) ) -> 41820 | L12: =IF( L11 = 1, $F10,EOMONTH( K12, 6 ) ) -> 42004 | M12: =IF( M11 = 1, $F10,EOMONTH( L12, 6 ) ) -> 42185 | N12: =IF( N11 = 1, $F10,EOMONTH( M12, 6 ) ) -> 42369 | O12: =IF( O11 = 1, $F10,EOMONTH( N12, 6 ) ) -> 42551 | P12: =IF( P11 = 1, $F10,EOMONTH( O12, 6 ) ) -> 42735 | Q12: =IF( Q11 = 1, $F10,EOMONTH( P12, 6 ) ) -> 42916 | ... CA12: =IF( CA11 = 1, $F10,EOMONTH( BZ12, 6 ) ) -> 54239
A15: FLAGS
E17: =InpC!E$12 -> Construction period end / conversion date | F17: =InpC!F$12 -> 42369 | G17: =InpC!G$12 -> date
E18: =E$12 -> Model period ending | F18: =F$12 -> constant | G18: =G$12 -> unit | H18: =H$12 -> total | I18: =I$12 -> 0 | J18: =J$12 -> 41639 | K18: =K$12 -> 41820 | L18: =L$12 -> 42004 | ... CA18: =CA$12 -> 54239
E19: Initial operations date flag | G19: flag | H19: =SUM(J19:CA19) -> 1 | J19: =IF(J18 = $F17, 1, 0) -> 0 | K19: =IF(K18 = $F17, 1, 0) -> 0 | L19: =IF(L18 = $F17, 1, 0) -> 0 | M19: =IF(M18 = $F17, 1, 0) -> 0 | N19: =IF(N18 = $F17, 1, 0) -> 1 | O19: =IF(O18 = $F17, 1, 0) -> 0 | P19: =IF(P18 = $F17, 1, 0) -> 0 | Q19: =IF(Q18 = $F17, 1, 0) -> 0 | ... CA19: =IF(CA18 = $F17, 1, 0) -> 0
E21: =InpC!E$12 -> Construction period end / conversion date | F21: =InpC!F$12 -> 42369 | G21: =InpC!G$12 -> date
E22: =InpC!E$15 -> Last forecast date | F22: =InpC!F$15 -> 53327 | G22: =InpC!G$15 -> date
E23: =E$12 -> Model period ending | F23: =F$12 -> constant | G23: =G$12 -> unit | H23: =H$12 -> total | I23: =I$12 -> 0 | J23: =J$12 -> 41639 | K23: =K$12 -> 41820 | L23: =L$12 -> 42004 | ... CA23: =CA$12 -> 54239
E24: Operating period flag | G24: flag | H24: =SUM(J24:CA24) -> 60 | J24: =IF( AND(J23 > $F21, J23 <= $F22), 1, 0) -> 0 | K24: =IF( AND(K23 > $F21, K23 <= $F22), 1, 0) -> 0 | L24: =IF( AND(L23 > $F21, L23 <= $F22), 1, 0) -> 0 | M24: =IF( AND(M23 > $F21, M23 <= $F22), 1, 0) -> 0 | N24: =IF( AND(N23 > $F21, N23 <= $F22), 1, 0) -> 0 | O24: =IF( AND(O23 > $F21, O23 <= $F22), 1, 0) -> 1 | P24: =IF( AND(P23 > $F21, P23 <= $F22), 1, 0) -> 1 | Q24: =IF( AND(Q23 > $F21, Q23 <= $F22), 1, 0) -> 1 | ... CA24: =IF( AND(CA23 > $F21, CA23 <= $F22), 1, 0) -> 0
E26: =InpC!E$12 -> Construction period end / conversion date | F26: =InpC!F$12 -> 42369 | G26: =InpC!G$12 -> date
E27: [Last senior debt repayment date] | F27: 49674 | G27: date
E28: =E$12 -> Model period ending | F28: =F$12 -> constant | G28: =G$12 -> unit | H28: =H$12 -> total | I28: =I$12 -> 0 | J28: =J$12 -> 41639 | K28: =K$12 -> 41820 | L28: =L$12 -> 42004 | ... CA28: =CA$12 -> 54239
E29: Senior debt term / ratio calc date flag | G29: flag | H29: =SUM(J29:CA29) -> 40 | J29: =IF( AND(J28 > $F26, J28 <= $F27), 1, 0) -> 0 | K29: =IF( AND(K28 > $F26, K28 <= $F27), 1, 0) -> 0 | L29: =IF( AND(L28 > $F26, L28 <= $F27), 1, 0) -> 0 | M29: =IF( AND(M28 > $F26, M28 <= $F27), 1, 0) -> 0 | N29: =IF( AND(N28 > $F26, N28 <= $F27), 1, 0) -> 0 | O29: =IF( AND(O28 > $F26, O28 <= $F27), 1, 0) -> 1 | P29: =IF( AND(P28 > $F26, P28 <= $F27), 1, 0) -> 1 | Q29: =IF( AND(Q28 > $F26, Q28 <= $F27), 1, 0) -> 1 | ... CA29: =IF( AND(CA28 > $F26, CA28 <= $F27), 1, 0) -> 0
E31: =InpC!E$12 -> Construction period end / conversion date | F31: =InpC!F$12 -> 42369 | G31: =InpC!G$12 -> date
E32: =InpC!E$45 -> Last date of accounting depreciation | F32: =InpC!F$45 -> 51501 | G32: =InpC!G$45 -> date
E33: =E$12 -> Model period ending | F33: =F$12 -> constant | G33: =G$12 -> unit | H33: =H$12 -> total | I33: =I$12 -> 0 | J33: =J$12 -> 41639 | K33: =K$12 -> 41820 | L33: =L$12 -> 42004 | ... CA33: =CA$12 -> 54239
E34: Accounting useful life period flag | G34: flag | H34: =SUM(J34:CA34) -> 50 | J34: =IF( AND(J33 > $F31, J33 <= $F32), 1, 0) -> 0 | K34: =IF( AND(K33 > $F31, K33 <= $F32), 1, 0) -> 0 | L34: =IF( AND(L33 > $F31, L33 <= $F32), 1, 0) -> 0 | M34: =IF( AND(M33 > $F31, M33 <= $F32), 1, 0) -> 0 | N34: =IF( AND(N33 > $F31, N33 <= $F32), 1, 0) -> 0 | O34: =IF( AND(O33 > $F31, O33 <= $F32), 1, 0) -> 1 | P34: =IF( AND(P33 > $F31, P33 <= $F32), 1, 0) -> 1 | Q34: =IF( AND(Q33 > $F31, Q33 <= $F32), 1, 0) -> 1 | ... CA34: =IF( AND(CA33 > $F31, CA33 <= $F32), 1, 0) -> 0
E36: =InpC!E$15 -> Last forecast date | F36: =InpC!F$15 -> 53327 | G36: =InpC!G$15 -> date
E37: =E$12 -> Model period ending | F37: =F$12 -> constant | G37: =G$12 -> unit | H37: =H$12 -> total | I37: =I$12 -> 0 | J37: =J$12 -> 41639 | K37: =K$12 -> 41820 | L37: =L$12 -> 42004 | ... CA37: =CA$12 -> 54239
E38: Last forecast period flag | G38: flag | H38: =SUM(J38:CA38) -> 1 | J38: =IF(J37 = $F36, 1, 0) -> 0 | K38: =IF(K37 = $F36, 1, 0) -> 0 | L38: =IF(L37 = $F36, 1, 0) -> 0 | M38: =IF(M37 = $F36, 1, 0) -> 0 | N38: =IF(N37 = $F36, 1, 0) -> 0 | O38: =IF(O37 = $F36, 1, 0) -> 0 | P38: =IF(P37 = $F36, 1, 0) -> 0 | Q38: =IF(Q37 = $F36, 1, 0) -> 0 | ... CA38: =IF(CA37 = $F36, 1, 0) -> 0
A41: CPI ESCALATION FACTOR
E43: =InpC!E$17 -> Annual CPI inflation rate | F43: =InpC!F$17 -> 0.025 | G43: =InpC!G$17 -> p.a.
E44: Period CPI inflation rate | F44: =(1 + F43) ^ (1/2) - 1 -> 0.012422837 | G44: per period
E46: =E$44 -> Period CPI inflation rate | F46: =F$44 -> 0.012422837 | G46: =G$44 -> per period
E47: =InpC!E$18 -> Price and cost basis date - period ending | F47: =InpC!F$18 -> 41820 | G47: =InpC!G$18 -> date
E48: =E$12 -> Model period ending | F48: =F$12 -> constant | G48: =G$12 -> unit | H48: =H$12 -> total | I48: =I$12 -> 0 | J48: =J$12 -> 41639 | K48: =K$12 -> 41820 | L48: =L$12 -> 42004 | ... CA48: =CA$12 -> 54239
E49: CPI esc factor | G49: factor | J49: =IF(J48 = $F47, 1, I49 * (1 + $F46)) -> 0 | K49: =IF(K48 = $F47, 1, J49 * (1 + $F46)) -> 1 | L49: =IF(L48 = $F47, 1, K49 * (1 + $F46)) -> 1.0124228 | M49: =IF(M48 = $F47, 1, L49 * (1 + $F46)) -> 1.025 | N49: =IF(N48 = $F47, 1, M49 * (1 + $F46)) -> 1.0377334 | O49: =IF(O48 = $F47, 1, N49 * (1 + $F46)) -> 1.050625 | P49: =IF(P48 = $F47, 1, O49 * (1 + $F46)) -> 1.0636767 | Q49: =IF(Q48 = $F47, 1, P49 * (1 + $F46)) -> 1.0768906 | ... CA49: =IF(CA48 = $F47, 1, BZ49 * (1 + $F46)) -> 2.3153221

Sheet Rev
A1: =RIGHT(CELL("filename", A1), LEN(CELL("filename", A1)) - SEARCH("]", CELL("filename", A1))) -> Rev
E2: ='T&E'!E$24 -> Operating period flag | F2: ='T&E'!F$24 -> 0 | G2: ='T&E'!G$24 -> flag | H2: ='T&E'!H$24 -> 60 | I2: ='T&E'!I$24 -> 0 | J2: ='T&E'!J$24 -> 0 | K2: ='T&E'!K$24 -> 0 | L2: ='T&E'!L$24 -> 0 | ... CA2: ='T&E'!CA$24 -> 0
E3: ='T&E'!E$8 -> Model column counter | F3: ='T&E'!F$8 -> 0 | G3: ='T&E'!G$8 -> 0 | H3: ='T&E'!H$8 -> 0 | I3: ='T&E'!I$8 -> 0 | J3: ='T&E'!J$8 -> 1 | K3: ='T&E'!K$8 -> 2 | L3: ='T&E'!L$8 -> 3 | ... CA3: ='T&E'!CA$8 -> 70
E4: ='T&E'!E$12 -> Model period ending | F4: ='T&E'!F$12 -> constant | G4: ='T&E'!G$12 -> unit | H4: ='T&E'!H$12 -> total | I4: ='T&E'!I$12 -> 0 | J4: ='T&E'!J$12 -> 41639 | K4: ='T&E'!K$12 -> 41820 | L4: ='T&E'!L$12 -> 42004 | ... CA4: ='T&E'!CA$12 -> 54239
A6: PASSENGER LANDING TAX
C8: Landings
E10: =InpS!E$8 -> Routes - domestic charter | F10: =InpS!F$8 -> 0 | G10: =InpS!G$8 -> planes | H10: =InpS!H$8 -> 0 | I10: =InpS!I$8 -> 0 | J10: =InpS!J$8 -> 0 | K10: =InpS!K$8 -> 0 | L10: =InpS!L$8 -> 15 | ... CA10: =InpS!CA$8 -> 0
E11: =InpS!E$13 -> Landing frequency - domestic charter | F11: =InpS!F$13 -> 0 | G11: =InpS!G$13 -> lands / plane | H11: =InpS!H$13 -> 0 | I11: =InpS!I$13 -> 0 | J11: =InpS!J$13 -> 0 | K11: =InpS!K$13 -> 0 | L11: =InpS!L$13 -> 120 | ... CA11: =InpS!CA$13 -> 0
E12: ='T&E'!E$24 -> Operating period flag | F12: ='T&E'!F$24 -> 0 | G12: ='T&E'!G$24 -> flag | H12: ='T&E'!H$24 -> 60 | I12: ='T&E'!I$24 -> 0 | J12: ='T&E'!J$24 -> 0 | K12: ='T&E'!K$24 -> 0 | L12: ='T&E'!L$24 -> 0 | ... CA12: ='T&E'!CA$24 -> 0
E13: Landings - domestic charter | G13: landings | H13: =SUM(J13:CA13) -> 47210 | J13: =J10 * J11 * J12 -> 0 | K13: =K10 * K11 * K12 -> 0 | L13: =L10 * L11 * L12 -> 0 | M13: =M10 * M11 * M12 -> 0 | N13: =N10 * N11 * N12 -> 0 | O13: =O10 * O11 * O12 -> 1430 | P13: =P10 * P11 * P12 -> 1430 | Q13: =Q10 * Q11 * Q12 -> 1430 | ... CA13: =CA10 * CA11 * CA12 -> 0
E15: =InpS!E$9 -> Routes - domestic scheduled | F15: =InpS!F$9 -> 0 | G15: =InpS!G$9 -> planes | H15: =InpS!H$9 -> 0 | I15: =InpS!I$9 -> 0 | J15: =InpS!J$9 -> 0 | K15: =InpS!K$9 -> 0 | L15: =InpS!L$9 -> 28 | ... CA15: =InpS!CA$9 -> 0
E16: =InpS!E$14 -> Landing frequency - domestic scheduled | F16: =InpS!F$14 -> 0 | G16: =InpS!G$14 -> lands / plane | H16: =InpS!H$14 -> 0 | I16: =InpS!I$14 -> 0 | J16: =InpS!J$14 -> 0 | K16: =InpS!K$14 -> 0 | L16: =InpS!L$14 -> 250 | ... CA16: =InpS!CA$14 -> 0 | CB16: 270 | CC16: 168 | CD16: 84 | CE16: 168
E17: ='T&E'!E$24 -> Operating period flag | F17: ='T&E'!F$24 -> 0 | G17: ='T&E'!G$24 -> flag | H17: ='T&E'!H$24 -> 60 | I17: ='T&E'!I$24 -> 0 | J17: ='T&E'!J$24 -> 0 | K17: ='T&E'!K$24 -> 0 | L17: ='T&E'!L$24 -> 0 | ... CA17: ='T&E'!CA$24 -> 0
E18: Landings - domestic scheduled | G18: landings | H18: =SUM(J18:CA18) -> 315560 | J18: =J15 * J16 * J17 -> 0 | K18: =K15 * K16 * K17 -> 0 | L18: =L15 * L16 * L17 -> 0 | M18: =M15 * M16 * M17 -> 0 | N18: =N15 * N16 * N17 -> 0 | O18: =O15 * O16 * O17 -> 6480 | P18: =P15 * P16 * P17 -> 6000 | Q18: =Q15 * Q16 * Q17 -> 6480 | ... CA18: =CA15 * CA16 * CA17 -> 0
E20: =InpS!E$10 -> Routes - international charter | F20: =InpS!F$10 -> 0 | G20: =InpS!G$10 -> planes | H20: =InpS!H$10 -> 0 | I20: =InpS!I$10 -> 0 | J20: =InpS!J$10 -> 0 | K20: =InpS!K$10 -> 0 | L20: =InpS!L$10 -> 30 | ... CA20: =InpS!CA$10 -> 0
E21: =InpS!E$15 -> Landing frequency - international charter | F21: =InpS!F$15 -> 0 | G21: =InpS!G$15 -> lands / plane | H21: =InpS!H$15 -> 0 | I21: =InpS!I$15 -> 0 | J21: =InpS!J$15 -> 0 | K21: =InpS!K$15 -> 0 | L21: =InpS!L$15 -> 40 | ... CA21: =InpS!CA$15 -> 0
E22: ='T&E'!E$24 -> Operating period flag | F22: ='T&E'!F$24 -> 0 | G22: ='T&E'!G$24 -> flag | H22: ='T&E'!H$24 -> 60 | I22: ='T&E'!I$24 -> 0 | J22: ='T&E'!J$24 -> 0 | K22: ='T&E'!K$24 -> 0 | L22: ='T&E'!L$24 -> 0 | ... CA22: ='T&E'!CA$24 -> 0
E23: Landings - international charter | G23: landings | H23: =SUM(J23:CA23) -> 122250 | J23: =J20 * J21 * J22 -> 0 | K23: =K20 * K21 * K22 -> 0 | L23: =L20 * L21 * L22 -> 0 | M23: =M20 * M21 * M22 -> 0 | N23: =N20 * N21 * N22 -> 0 | O23: =O20 * O21 * O22 -> 1350 | P23: =P20 * P21 * P22 -> 1500 | Q23: =Q20 * Q21 * Q22 -> 1500 | ... CA23: =CA20 * CA21 * CA22 -> 0
E25: =InpS!E$11 -> Routes - international scheduled | F25: =InpS!F$11 -> 0 | G25: =InpS!G$11 -> planes | H25: =InpS!H$11 -> 0 | I25: =InpS!I$11 -> 0 | J25: =InpS!J$11 -> 0 | K25: =InpS!K$11 -> 0 | L25: =InpS!L$11 -> 12 | ... CA25: =InpS!CA$11 -> 0
E26: =InpS!E$16 -> Landing frequency - international scheduled | F26: =InpS!F$16 -> 0 | G26: =InpS!G$16 -> lands / plane | H26: =InpS!H$16 -> 0 | I26: =InpS!I$16 -> 0 | J26: =InpS!J$16 -> 0 | K26: =InpS!K$16 -> 0 | L26: =InpS!L$16 -> 35 | ... CA26: =InpS!CA$16 -> 0
E27: ='T&E'!E$24 -> Operating period flag | F27: ='T&E'!F$24 -> 0 | G27: ='T&E'!G$24 -> flag | H27: ='T&E'!H$24 -> 60 | I27: ='T&E'!I$24 -> 0 | J27: ='T&E'!J$24 -> 0 | K27: ='T&E'!K$24 -> 0 | L27: ='T&E'!L$24 -> 0 | ... CA27: ='T&E'!CA$24 -> 0
E28: Landings - international scheduled | G28: landings | H28: =SUM(J28:CA28) -> 52230 | J28: =J25 * J26 * J27 -> 0 | K28: =K25 * K26 * K27 -> 0 | L28: =L25 * L26 * L27 -> 0 | M28: =M25 * M26 * M27 -> 0 | N28: =N25 * N26 * N27 -> 0 | O28: =O25 * O26 * O27 -> 630 | P28: =P25 * P26 * P27 -> 720 | Q28: =Q25 * Q26 * Q27 -> 720 | ... CA28: =CA25 * CA26 * CA27 -> 0
E31: =E$13 -> Landings - domestic charter | F31: =F$13 -> 0 | G31: =G$13 -> landings | H31: =H$13 -> 47210 | I31: =I$13 -> 0 | J31: =J$13 -> 0 | K31: =K$13 -> 0 | L31: =L$13 -> 0 | ... CA31: =CA$13 -> 0
E32: =E$18 -> Landings - domestic scheduled | F32: =F$18 -> 0 | G32: =G$18 -> landings | H32: =H$18 -> 315560 | I32: =I$18 -> 0 | J32: =J$18 -> 0 | K32: =K$18 -> 0 | L32: =L$18 -> 0 | ... CA32: =CA$18 -> 0
E33: =E$23 -> Landings - international charter | F33: =F$23 -> 0 | G33: =G$23 -> landings | H33: =H$23 -> 122250 | I33: =I$23 -> 0 | J33: =J$23 -> 0 | K33: =K$23 -> 0 | L33: =L$23 -> 0 | ... CA33: =CA$23 -> 0
E34: =E$28 -> Landings - international scheduled | F34: =F$28 -> 0 | G34: =G$28 -> landings | H34: =H$28 -> 52230 | I34: =I$28 -> 0 | J34: =J$28 -> 0 | K34: =K$28 -> 0 | L34: =L$28 -> 0 | ... CA34: =CA$28 -> 0
E35: Total landings | G35: landings | H35: =SUM(J35:CA35) -> 537250 | J35: =SUM(J31:J34) -> 0 | K35: =SUM(K31:K34) -> 0 | L35: =SUM(L31:L34) -> 0 | M35: =SUM(M31:M34) -> 0 | N35: =SUM(N31:N34) -> 0 | O35: =SUM(O31:O34) -> 9890 | P35: =SUM(P31:P34) -> 9650 | Q35: =SUM(Q31:Q34) -> 10130 | ... CA35: =SUM(CA31:CA34) -> 0
C38: Passengers per landing
E40: =InpC!E$23 -> Aircraft capacity - domestic charter | F40: =InpC!F$23 -> 110 | G40: =InpC!G$23 -> seats
E41: =InpS!E$18 -> Load factor - domestic charter | F41: =InpS!F$18 -> 0 | G41: =InpS!G$18 -> % | H41: =InpS!H$18 -> 0 | I41: =InpS!I$18 -> 0 | J41: =InpS!J$18 -> 0 | K41: =InpS!K$18 -> 0 | L41: =InpS!L$18 -> 0.6 | ... CA41: =InpS!CA$18 -> 0
E42: ='T&E'!E$24 -> Operating period flag | F42: ='T&E'!F$24 -> 0 | G42: ='T&E'!G$24 -> flag | H42: ='T&E'!H$24 -> 60 | I42: ='T&E'!I$24 -> 0 | J42: ='T&E'!J$24 -> 0 | K42: ='T&E'!K$24 -> 0 | L42: ='T&E'!L$24 -> 0 | ... CA42: ='T&E'!CA$24 -> 0
E43: PAx per landing - domestic charter | G43: PAx / land | J43: =$F40 * J41 * J42 -> 0 | K43: =$F40 * K41 * K42 -> 0 | L43: =$F40 * L41 * L42 -> 0 | M43: =$F40 * M41 * M42 -> 0 | N43: =$F40 * N41 * N42 -> 0 | O43: =$F40 * O41 * O42 -> 77 | P43: =$F40 * P41 * P42 -> 77 | Q43: =$F40 * Q41 * Q42 -> 77 | ... CA43: =$F40 * CA41 * CA42 -> 0
E45: =InpC!E$24 -> Aircraft capacity - domestic scheduled | F45: =InpC!F$24 -> 140 | G45: =InpC!G$24 -> seats
E46: =InpS!E$19 -> Load factor - domestic scheduled | F46: =InpS!F$19 -> 0 | G46: =InpS!G$19 -> % | H46: =InpS!H$19 -> 0 | I46: =InpS!I$19 -> 0 | J46: =InpS!J$19 -> 0 | K46: =InpS!K$19 -> 0 | L46: =InpS!L$19 -> 0.7 | ... CA46: =InpS!CA$19 -> 0
E47: ='T&E'!E$24 -> Operating period flag | F47: ='T&E'!F$24 -> 0 | G47: ='T&E'!G$24 -> flag | H47: ='T&E'!H$24 -> 60 | I47: ='T&E'!I$24 -> 0 | J47: ='T&E'!J$24 -> 0 | K47: ='T&E'!K$24 -> 0 | L47: ='T&E'!L$24 -> 0 | ... CA47: ='T&E'!CA$24 -> 0
E48: PAx per landing - domestic scheduled | G48: PAx / land | J48: =$F45 * J46 * J47 -> 0 | K48: =$F45 * K46 * K47 -> 0 | L48: =$F45 * L46 * L47 -> 0 | M48: =$F45 * M46 * M47 -> 0 | N48: =$F45 * N46 * N47 -> 0 | O48: =$F45 * O46 * O47 -> 98 | P48: =$F45 * P46 * P47 -> 98 | Q48: =$F45 * Q46 * Q47 -> 98 | ... CA48: =$F45 * CA46 * CA47 -> 0
E50: =InpC!E$25 -> Aircraft capacity - international chartered | F50: =InpC!F$25 -> 250 | G50: =InpC!G$25 -> seats
E51: =InpS!E$20 -> Load factor - international charter | F51: =InpS!F$20 -> 0 | G51: =InpS!G$20 -> % | H51: =InpS!H$20 -> 0 | I51: =InpS!I$20 -> 0 | J51: =InpS!J$20 -> 0 | K51: =InpS!K$20 -> 0 | L51: =InpS!L$20 -> 0.65 | ... CA51: =InpS!CA$20 -> 0 | CB51: 0.55 | CC51: 0.5 | CD51: 0.55 | CE51: 0.5 | CF51: 0.55 | CG51: 0.5 | CH51: 0.55 | CI51: 0.5 | CJ51: 0.55 | CK51: 0.5 | CL51: 0.55 | CM51: 0.5 | CN51: 0.55 | CO51: 0.5
E52: ='T&E'!E$24 -> Operating period flag | F52: ='T&E'!F$24 -> 0 | G52: ='T&E'!G$24 -> flag | H52: ='T&E'!H$24 -> 60 | I52: ='T&E'!I$24 -> 0 | J52: ='T&E'!J$24 -> 0 | K52: ='T&E'!K$24 -> 0 | L52: ='T&E'!L$24 -> 0 | ... CA52: ='T&E'!CA$24 -> 0
E53: PAx per landing - international chartered | G53: PAx / land | J53: =$F50 * J51 * J52 -> 0 | K53: =$F50 * K51 * K52 -> 0 | L53: =$F50 * L51 * L52 -> 0 | M53: =$F50 * M51 * M52 -> 0 | N53: =$F50 * N51 * N52 -> 0 | O53: =$F50 * O51 * O52 -> 150 | P53: =$F50 * P51 * P52 -> 162.5 | Q53: =$F50 * Q51 * Q52 -> 150 | ... CA53: =$F50 * CA51 * CA52 -> 0
E55: =InpC!E$26 -> Aircraft capacity - international scheduled | F55: =InpC!F$26 -> 280 | G55: =InpC!G$26 -> seats
E56: =InpS!E$21 -> Load factor - international scheduled | F56: =InpS!F$21 -> 0 | G56: =InpS!G$21 -> % | H56: =InpS!H$21 -> 0 | I56: =InpS!I$21 -> 0 | J56: =InpS!J$21 -> 0 | K56: =InpS!K$21 -> 0 | L56: =InpS!L$21 -> 0.65 | ... CA56: =InpS!CA$21 -> 0
E57: ='T&E'!E$24 -> Operating period flag | F57: ='T&E'!F$24 -> 0 | G57: ='T&E'!G$24 -> flag | H57: ='T&E'!H$24 -> 60 | I57: ='T&E'!I$24 -> 0 | J57: ='T&E'!J$24 -> 0 | K57: ='T&E'!K$24 -> 0 | L57: ='T&E'!L$24 -> 0 | ... CA57: ='T&E'!CA$24 -> 0
E58: PAx per landing - international scheduled | G58: PAx / land | J58: =$F55 * J56 * J57 -> 0 | K58: =$F55 * K56 * K57 -> 0 | L58: =$F55 * L56 * L57 -> 0 | M58: =$F55 * M56 * M57 -> 0 | N58: =$F55 * N56 * N57 -> 0 | O58: =$F55 * O56 * O57 -> 182 | P58: =$F55 * P56 * P57 -> 182 | Q58: =$F55 * Q56 * Q57 -> 182 | ... CA58: =$F55 * CA56 * CA57 -> 0
C61: Passenger traffic (PAx)
E63: =E$13 -> Landings - domestic charter | F63: =F$13 -> 0 | G63: =G$13 -> landings | H63: =H$13 -> 47210 | I63: =I$13 -> 0 | J63: =J$13 -> 0 | K63: =K$13 -> 0 | L63: =L$13 -> 0 | ... CA63: =CA$13 -> 0
E64: =E$43 -> PAx per landing - domestic charter | F64: =F$43 -> 0 | G64: =G$43 -> PAx / land | H64: =H$43 -> 0 | I64: =I$43 -> 0 | J64: =J$43 -> 0 | K64: =K$43 -> 0 | L64: =L$43 -> 0 | ... CA64: =CA$43 -> 0
E65: Passenger traffic - domestic charter | G65: PAx | H65: =SUM(J65:CA65) -> 3658930 | J65: =J63 * J64 -> 0 | K65: =K63 * K64 -> 0 | L65: =L63 * L64 -> 0 | M65: =M63 * M64 -> 0 | N65: =N63 * N64 -> 0 | O65: =O63 * O64 -> 110110 | P65: =P63 * P64 -> 110110 | Q65: =Q63 * Q64 -> 110110 | ... CA65: =CA63 * CA64 -> 0
E67: =E$18 -> Landings - domestic scheduled | F67: =F$18 -> 0 | G67: =G$18 -> landings | H67: =H$18 -> 315560 | I67: =I$18 -> 0 | J67: =J$18 -> 0 | K67: =K$18 -> 0 | L67: =L$18 -> 0 | ... CA67: =CA$18 -> 0
E68: =E$48 -> PAx per landing - domestic scheduled | F68: =F$48 -> 0 | G68: =G$48 -> PAx / land | H68: =H$48 -> 0 | I68: =I$48 -> 0 | J68: =J$48 -> 0 | K68: =K$48 -> 0 | L68: =L$48 -> 0 | ... CA68: =CA$48 -> 0
E69: Passenger traffic - domestic scheduled | G69: PAx | H69: =SUM(J69:CA69) -> 30852640 | J69: =J67 * J68 -> 0 | K69: =K67 * K68 -> 0 | L69: =L67 * L68 -> 0 | M69: =M67 * M68 -> 0 | N69: =N67 * N68 -> 0 | O69: =O67 * O68 -> 635040 | P69: =P67 * P68 -> 588000 | Q69: =Q67 * Q68 -> 635040 | ... CA69: =CA67 * CA68 -> 0
E71: =E$23 -> Landings - international charter | F71: =F$23 -> 0 | G71: =G$23 -> landings | H71: =H$23 -> 122250 | I71: =I$23 -> 0 | J71: =J$23 -> 0 | K71: =K$23 -> 0 | L71: =L$23 -> 0 | ... CA71: =CA$23 -> 0
E72: =E$53 -> PAx per landing - international chartered | F72: =F$53 -> 0 | G72: =G$53 -> PAx / land | H72: =H$53 -> 0 | I72: =I$53 -> 0 | J72: =J$53 -> 0 | K72: =K$53 -> 0 | L72: =L$53 -> 0 | ... CA72: =CA$53 -> 0
E73: Passenger traffic - international charter | G73: PAx | H73: =SUM(J73:CA73) -> 19053750 | J73: =J71 * J72 -> 0 | K73: =K71 * K72 -> 0 | L73: =L71 * L72 -> 0 | M73: =M71 * M72 -> 0 | N73: =N71 * N72 -> 0 | O73: =O71 * O72 -> 202500 | P73: =P71 * P72 -> 243750 | Q73: =Q71 * Q72 -> 225000 | ... CA73: =CA71 * CA72 -> 0
E75: =E$28 -> Landings - international scheduled | F75: =F$28 -> 0 | G75: =G$28 -> landings | H75: =H$28 -> 52230 | I75: =I$28 -> 0 | J75: =J$28 -> 0 | K75: =K$28 -> 0 | L75: =L$28 -> 0 | ... CA75: =CA$28 -> 0
E76: =E$58 -> PAx per landing - international scheduled | F76: =F$58 -> 0 | G76: =G$58 -> PAx / land | H76: =H$58 -> 0 | I76: =I$58 -> 0 | J76: =J$58 -> 0 | K76: =K$58 -> 0 | L76: =L$58 -> 0 | ... CA76: =CA$58 -> 0
E77: Passenger traffic - international scheduled | G77: PAx | H77: =SUM(J77:CA77) -> 9813860 | J77: =J75 * J76 -> 0 | K77: =K75 * K76 -> 0 | L77: =L75 * L76 -> 0 | M77: =M75 * M76 -> 0 | N77: =N75 * N76 -> 0 | O77: =O75 * O76 -> 114660 | P77: =P75 * P76 -> 131040 | Q77: =Q75 * Q76 -> 131040 | ... CA77: =CA75 * CA76 -> 0
E80: =E$65 -> Passenger traffic - domestic charter | F80: =F$65 -> 0 | G80: =G$65 -> PAx | H80: =H$65 -> 3658930 | I80: =I$65 -> 0 | J80: =J$65 -> 0 | K80: =K$65 -> 0 | L80: =L$65 -> 0 | ... CA80: =CA$65 -> 0
E81: =E$69 -> Passenger traffic - domestic scheduled | F81: =F$69 -> 0 | G81: =G$69 -> PAx | H81: =H$69 -> 30852640 | I81: =I$69 -> 0 | J81: =J$69 -> 0 | K81: =K$69 -> 0 | L81: =L$69 -> 0 | ... CA81: =CA$69 -> 0
E82: =E$73 -> Passenger traffic - international charter | F82: =F$73 -> 0 | G82: =G$73 -> PAx | H82: =H$73 -> 19053750 | I82: =I$73 -> 0 | J82: =J$73 -> 0 | K82: =K$73 -> 0 | L82: =L$73 -> 0 | ... CA82: =CA$73 -> 0
E83: =E$77 -> Passenger traffic - international scheduled | F83: =F$77 -> 0 | G83: =G$77 -> PAx | H83: =H$77 -> 9813860 | I83: =I$77 -> 0 | J83: =J$77 -> 0 | K83: =K$77 -> 0 | L83: =L$77 -> 0 | ... CA83: =CA$77 -> 0
E84: Passenger traffic | G84: PAx | H84: =SUM(J84:CA84) -> 63379180 | J84: =SUM(J80:J83) -> 0 | K84: =SUM(K80:K83) -> 0 | L84: =SUM(L80:L83) -> 0 | M84: =SUM(M80:M83) -> 0 | N84: =SUM(N80:N83) -> 0 | O84: =SUM(O80:O83) -> 1062310 | P84: =SUM(P80:P83) -> 1072900 | Q84: =SUM(Q80:Q83) -> 1101190 | ... CA84: =SUM(CA80:CA83) -> 0
B87: Passenger landing tax revenue
E89: =InpC!E$28 -> Passenger landing tax rate | F89: =InpC!F$28 -> 22.75 | G89: =InpC!G$28 -> € / PAx
E90: ='T&E'!E$49 -> CPI esc factor | F90: ='T&E'!F$49 -> 0 | G90: ='T&E'!G$49 -> factor | H90: ='T&E'!H$49 -> 0 | I90: ='T&E'!I$49 -> 0 | J90: ='T&E'!J$49 -> 0 | K90: ='T&E'!K$49 -> 1 | L90: ='T&E'!L$49 -> 1.0124228 | ... CA90: ='T&E'!CA$49 -> 2.3153221
E91: =E$84 -> Passenger traffic | F91: =F$84 -> 0 | G91: =G$84 -> PAx | H91: =H$84 -> 63379180 | I91: =I$84 -> 0 | J91: =J$84 -> 0 | K91: =K$84 -> 0 | L91: =L$84 -> 0 | ... CA91: =CA$84 -> 0
E92: Passenger landing tax revenue | G92: =SMU -> € 000s | H92: =SUM(J92:CA92) -> 2237857.3 | J92: =$F89 * J90 * J91 / 1000 -> 0 | K92: =$F89 * K90 * K91 / 1000 -> 0 | L92: =$F89 * L90 * L91 / 1000 -> 0 | M92: =$F89 * M90 * M91 / 1000 -> 0 | N92: =$F89 * N90 * N91 / 1000 -> 0 | O92: =$F89 * O90 * O91 / 1000 -> 25391.035 | P92: =$F89 * P90 * P91 / 1000 -> 25962.727 | Q92: =$F89 * Q90 * Q91 / 1000 -> 26978.342 | ... CA92: =$F89 * CA90 * CA91 / 1000 -> 0
A95: RETAIL REVENUES
E97: =InpC!E$30 -> Passenger retail purchases rate | F97: =InpC!F$30 -> 10.5 | G97: =InpC!G$30 -> € / PAx
E98: =InpC!E$31 -> Rental revenue sharing percentage | F98: =InpC!F$31 -> 0.25 | G98: =InpC!G$31 -> of sales
E99: ='T&E'!E$49 -> CPI esc factor | F99: ='T&E'!F$49 -> 0 | G99: ='T&E'!G$49 -> factor | H99: ='T&E'!H$49 -> 0 | I99: ='T&E'!I$49 -> 0 | J99: ='T&E'!J$49 -> 0 | K99: ='T&E'!K$49 -> 1 | L99: ='T&E'!L$49 -> 1.0124228 | ... CA99: ='T&E'!CA$49 -> 2.3153221
E100: =E$84 -> Passenger traffic | F100: =F$84 -> 0 | G100: =G$84 -> PAx | H100: =H$84 -> 63379180 | I100: =I$84 -> 0 | J100: =J$84 -> 0 | K100: =K$84 -> 0 | L100: =L$84 -> 0 | ... CA100: =CA$84 -> 0
E101: Retail revenue | G101: =SMU -> € 000s | H101: =SUM(J101:CA101) -> 258214.31 | J101: =$F97 * $F98 * J99 * J100 / 1000 -> 0 | K101: =$F97 * $F98 * K99 * K100 / 1000 -> 0 | L101: =$F97 * $F98 * L99 * L100 / 1000 -> 0 | M101: =$F97 * $F98 * M99 * M100 / 1000 -> 0 | N101: =$F97 * $F98 * N99 * N100 / 1000 -> 0 | O101: =$F97 * $F98 * O99 * O100 / 1000 -> 2929.7348 | P101: =$F97 * $F98 * P99 * P100 / 1000 -> 2995.6993 | Q101: =$F97 * $F98 * Q99 * Q100 / 1000 -> 3112.8856 | ... CA101: =$F97 * $F98 * CA99 * CA100 / 1000 -> 0
A104: CAR PARKING
A109: SUMMARY
E111: =E$92 -> Passenger landing tax revenue | F111: =F$92 -> 0 | G111: =G$92 -> € 000s | H111: =H$92 -> 2237857.3 | I111: =I$92 -> 0 | J111: =J$92 -> 0 | K111: =K$92 -> 0 | L111: =L$92 -> 0 | ... CA111: =CA$92 -> 0
E112: =E$101 -> Retail revenue | F112: =F$101 -> 0 | G112: =G$101 -> € 000s | H112: =H$101 -> 258214.31 | I112: =I$101 -> 0 | J112: =J$101 -> 0 | K112: =K$101 -> 0 | L112: =L$101 -> 0 | ... CA112: =CA$101 -> 0
E113: [Car parking revenue] | G113: =SMU -> € 000s
E114: Operating revenue | G114: =SMU -> € 000s | H114: =SUM(J114:CA114) -> 2496071.6 | J114: =SUM(J111:J113) -> 0 | K114: =SUM(K111:K113) -> 0 | L114: =SUM(L111:L113) -> 0 | M114: =SUM(M111:M113) -> 0 | N114: =SUM(N111:N113) -> 0 | O114: =SUM(O111:O113) -> 28320.77 | P114: =SUM(P111:P113) -> 28958.426 | Q114: =SUM(Q111:Q113) -> 30091.228 | ... CA114: =SUM(CA111:CA113) -> 0

Sheet Opex
A1: =RIGHT(CELL("filename", A1), LEN(CELL("filename", A1)) - SEARCH("]", CELL("filename", A1))) -> Opex
E2: ='T&E'!E$24 -> Operating period flag | F2: ='T&E'!F$24 -> 0 | G2: ='T&E'!G$24 -> flag | H2: ='T&E'!H$24 -> 60 | I2: ='T&E'!I$24 -> 0 | J2: ='T&E'!J$24 -> 0 | K2: ='T&E'!K$24 -> 0 | L2: ='T&E'!L$24 -> 0 | ... CA2: ='T&E'!CA$24 -> 0
E3: ='T&E'!E$8 -> Model column counter | F3: ='T&E'!F$8 -> 0 | G3: ='T&E'!G$8 -> 0 | H3: ='T&E'!H$8 -> 0 | I3: ='T&E'!I$8 -> 0 | J3: ='T&E'!J$8 -> 1 | K3: ='T&E'!K$8 -> 2 | L3: ='T&E'!L$8 -> 3 | ... CA3: ='T&E'!CA$8 -> 70
E4: ='T&E'!E$12 -> Model period ending | F4: ='T&E'!F$12 -> constant | G4: ='T&E'!G$12 -> unit | H4: ='T&E'!H$12 -> total | I4: ='T&E'!I$12 -> 0 | J4: ='T&E'!J$12 -> 41639 | K4: ='T&E'!K$12 -> 41820 | L4: ='T&E'!L$12 -> 42004 | ... CA4: ='T&E'!CA$12 -> 54239
A6: GROUND HANDLING
E8: =InpC!E$33 -> Variable ground handling charge rate | F8: =InpC!F$33 -> 340 | G8: =InpC!G$33 -> € / landing
E9: =Rev!E$35 -> Total landings | F9: =Rev!F$35 -> 0 | G9: =Rev!G$35 -> landings | H9: =Rev!H$35 -> 537250 | I9: =Rev!I$35 -> 0 | J9: =Rev!J$35 -> 0 | K9: =Rev!K$35 -> 0 | L9: =Rev!L$35 -> 0 | ... CA9: =Rev!CA$35 -> 0
E10: ='T&E'!E$49 -> CPI esc factor | F10: ='T&E'!F$49 -> 0 | G10: ='T&E'!G$49 -> factor | H10: ='T&E'!H$49 -> 0 | I10: ='T&E'!I$49 -> 0 | J10: ='T&E'!J$49 -> 0 | K10: ='T&E'!K$49 -> 1 | L10: ='T&E'!L$49 -> 1.0124228 | ... CA10: ='T&E'!CA$49 -> 2.3153221
E11: Variable ground handling costs | G11: =SMU -> € 000s | H11: =SUM(J11:CA11) -> 282201.8 | J11: =$F8 * J9 * J10 / 1000 -> 0 | K11: =$F8 * K9 * K10 / 1000 -> 0 | L11: =$F8 * L9 * L10 / 1000 -> 0 | M11: =$F8 * M9 * M10 / 1000 -> 0 | N11: =$F8 * N9 * N10 / 1000 -> 0 | O11: =$F8 * O9 * O10 / 1000 -> 3532.8316 | P11: =$F8 * P9 * P10 / 1000 -> 3489.9234 | Q11: =$F8 * Q9 * Q10 / 1000 -> 3709.0267 | ... CA11: =$F8 * CA9 * CA10 / 1000 -> 0
E14: =InpC!E$34 -> Fixed ground handling costs | F14: =InpC!F$34 -> 3600 | G14: =InpC!G$34 -> € 000s p.a.
E15: ='T&E'!E$49 -> CPI esc factor | F15: ='T&E'!F$49 -> 0 | G15: ='T&E'!G$49 -> factor | H15: ='T&E'!H$49 -> 0 | I15: ='T&E'!I$49 -> 0 | J15: ='T&E'!J$49 -> 0 | K15: ='T&E'!K$49 -> 1 | L15: ='T&E'!L$49 -> 1.0124228 | ... CA15: ='T&E'!CA$49 -> 2.3153221
E16: ='T&E'!E$24 -> Operating period flag | F16: ='T&E'!F$24 -> 0 | G16: ='T&E'!G$24 -> flag | H16: ='T&E'!H$24 -> 60 | I16: ='T&E'!I$24 -> 0 | J16: ='T&E'!J$24 -> 0 | K16: ='T&E'!K$24 -> 0 | L16: ='T&E'!L$24 -> 0 | ... CA16: ='T&E'!CA$24 -> 0
E17: Fixed ground handling costs | G17: =SMU -> € 000s | H17: =SUM(J17:CA17) -> 167082.41 | J17: =($F14 / 2) * J15 * J16 -> 0 | K17: =($F14 / 2) * K15 * K16 -> 0 | L17: =($F14 / 2) * L15 * L16 -> 0 | M17: =($F14 / 2) * M15 * M16 -> 0 | N17: =($F14 / 2) * N15 * N16 -> 0 | O17: =($F14 / 2) * O15 * O16 -> 1891.125 | P17: =($F14 / 2) * P15 * P16 -> 1914.6181 | Q17: =($F14 / 2) * Q15 * Q16 -> 1938.4031 | ... CA17: =($F14 / 2) * CA15 * CA16 -> 0
A20: O&M CONTRACT
E22: =InpC!E$35 -> Airport terminal O&M contract costs | F22: =InpC!F$35 -> 2400 | G22: =InpC!G$35 -> € 000s p.a.
E23: ='T&E'!E$49 -> CPI esc factor | F23: ='T&E'!F$49 -> 0 | G23: ='T&E'!G$49 -> factor | H23: ='T&E'!H$49 -> 0 | I23: ='T&E'!I$49 -> 0 | J23: ='T&E'!J$49 -> 0 | K23: ='T&E'!K$49 -> 1 | L23: ='T&E'!L$49 -> 1.0124228 | ... CA23: ='T&E'!CA$49 -> 2.3153221
E24: ='T&E'!E$24 -> Operating period flag | F24: ='T&E'!F$24 -> 0 | G24: ='T&E'!G$24 -> flag | H24: ='T&E'!H$24 -> 60 | I24: ='T&E'!I$24 -> 0 | J24: ='T&E'!J$24 -> 0 | K24: ='T&E'!K$24 -> 0 | L24: ='T&E'!L$24 -> 0 | ... CA24: ='T&E'!CA$24 -> 0
E25: O&M contract costs | G25: =SMU -> € 000s | H25: =SUM(J25:CA25) -> 111388.27 | J25: =($F22 / 2) * J23 * J24 -> 0 | K25: =($F22 / 2) * K23 * K24 -> 0 | L25: =($F22 / 2) * L23 * L24 -> 0 | M25: =($F22 / 2) * M23 * M24 -> 0 | N25: =($F22 / 2) * N23 * N24 -> 0 | O25: =($F22 / 2) * O23 * O24 -> 1260.75 | P25: =($F22 / 2) * P23 * P24 -> 1276.4121 | Q25: =($F22 / 2) * Q23 * Q24 -> 1292.2687 | ... CA25: =($F22 / 2) * CA23 * CA24 -> 0
A28: SUMMARY
E30: =E$11 -> Variable ground handling costs | F30: =F$11 -> 0 | G30: =G$11 -> € 000s | H30: =H$11 -> 282201.8 | I30: =I$11 -> 0 | J30: =J$11 -> 0 | K30: =K$11 -> 0 | L30: =L$11 -> 0 | ... CA30: =CA$11 -> 0
E31: =E$17 -> Fixed ground handling costs | F31: =F$17 -> 0 | G31: =G$17 -> € 000s | H31: =H$17 -> 167082.41 | I31: =I$17 -> 0 | J31: =J$17 -> 0 | K31: =K$17 -> 0 | L31: =L$17 -> 0 | ... CA31: =CA$17 -> 0
E32: =E$25 -> O&M contract costs | F32: =F$25 -> 0 | G32: =G$25 -> € 000s | H32: =H$25 -> 111388.27 | I32: =I$25 -> 0 | J32: =J$25 -> 0 | K32: =K$25 -> 0 | L32: =L$25 -> 0 | ... CA32: =CA$25 -> 0
E33: Operating costs POS | G33: =SMU -> € 000s | H33: =SUM(J33:CA33) -> 560672.48 | J33: =SUM(J30:J32) -> 0 | K33: =SUM(K30:K32) -> 0 | L33: =SUM(L30:L32) -> 0 | M33: =SUM(M30:M32) -> 0 | N33: =SUM(N30:N32) -> 0 | O33: =SUM(O30:O32) -> 6684.7066 | P33: =SUM(P30:P32) -> 6680.9536 | Q33: =SUM(Q30:Q32) -> 6939.6986 | ... CA33: =SUM(CA30:CA32) -> 0
E34: =LEFT(E33, LEN(E33) - 4) -> Operating costs | G34: =G33 -> € 000s | H34: =SUM(J34:CA34) -> -560672.48 | J34: =-1 * J33 -> 0 | K34: =-1 * K33 -> 0 | L34: =-1 * L33 -> 0 | M34: =-1 * M33 -> 0 | N34: =-1 * N33 -> 0 | O34: =-1 * O33 -> -6684.7066 | P34: =-1 * P33 -> -6680.9536 | Q34: =-1 * Q33 -> -6939.6986 | ... CA34: =-1 * CA33 -> 0

Sheet FixAsst
A1: =RIGHT(CELL("filename", A1), LEN(CELL("filename", A1)) - SEARCH("]", CELL("filename", A1))) -> FixAsst
E2: ='T&E'!E$24 -> Operating period flag | F2: ='T&E'!F$24 -> 0 | G2: ='T&E'!G$24 -> flag | H2: ='T&E'!H$24 -> 60 | I2: ='T&E'!I$24 -> 0 | J2: ='T&E'!J$24 -> 0 | K2: ='T&E'!K$24 -> 0 | L2: ='T&E'!L$24 -> 0 | ... CA2: ='T&E'!CA$24 -> 0
E3: ='T&E'!E$8 -> Model column counter | F3: ='T&E'!F$8 -> 0 | G3: ='T&E'!G$8 -> 0 | H3: ='T&E'!H$8 -> 0 | I3: ='T&E'!I$8 -> 0 | J3: ='T&E'!J$8 -> 1 | K3: ='T&E'!K$8 -> 2 | L3: ='T&E'!L$8 -> 3 | ... CA3: ='T&E'!CA$8 -> 70
E4: ='T&E'!E$12 -> Model period ending | F4: ='T&E'!F$12 -> constant | G4: ='T&E'!G$12 -> unit | H4: ='T&E'!H$12 -> total | I4: ='T&E'!I$12 -> 0 | J4: ='T&E'!J$12 -> 41639 | K4: ='T&E'!K$12 -> 41820 | L4: ='T&E'!L$12 -> 42004 | ... CA4: ='T&E'!CA$12 -> 54239
A6: BOOK DEPRECIATION
E8: =ConFin!E$128 -> Additions to fixed assets DC total | F8: =ConFin!F$128 -> 395404.94 | G8: =ConFin!G$128 -> € 000s
E9: =InpC!E$44 -> Useful life input | F9: =InpC!F$44 -> 25 | G9: =InpC!G$44 -> years
E10: Period amount of depreciation | F10: =F8 / (2 * F9) -> 7908.0989 | G10: =SMU -> € 000s
E12: =E$10 -> Period amount of depreciation | F12: =F$10 -> 7908.0989 | G12: =G$10 -> € 000s
E13: ='T&E'!E$34 -> Accounting useful life period flag | F13: ='T&E'!F$34 -> 0 | G13: ='T&E'!G$34 -> flag | H13: ='T&E'!H$34 -> 50 | I13: ='T&E'!I$34 -> 0 | J13: ='T&E'!J$34 -> 0 | K13: ='T&E'!K$34 -> 0 | L13: ='T&E'!L$34 -> 0 | ... CA13: ='T&E'!CA$34 -> 0
E14: Book depreciation POS | G14: =SMU -> € 000s | H14: =SUM(J14:CA14) -> 395404.94 | J14: =$F12 * J13 -> 0 | K14: =$F12 * K13 -> 0 | L14: =$F12 * L13 -> 0 | M14: =$F12 * M13 -> 0 | N14: =$F12 * N13 -> 0 | O14: =$F12 * O13 -> 7908.0989 | P14: =$F12 * P13 -> 7908.0989 | Q14: =$F12 * Q13 -> 7908.0989 | ... CA14: =$F12 * CA13 -> 0
E15: =LEFT(E14, LEN(E14) - 4) -> Book depreciation | G15: =G14 -> € 000s | H15: =SUM(J15:CA15) -> -395404.94 | J15: =-1 * J14 -> 0 | K15: =-1 * K14 -> 0 | L15: =-1 * L14 -> 0 | M15: =-1 * M14 -> 0 | N15: =-1 * N14 -> 0 | O15: =-1 * O14 -> -7908.0989 | P15: =-1 * P14 -> -7908.0989 | Q15: =-1 * Q14 -> -7908.0989 | ... CA15: =-1 * CA14 -> 0
A18: NET FIXED ASSET BALANCE
E20: =ConFin!E$128 -> Additions to fixed assets DC total | F20: =ConFin!F$128 -> 395404.94 | G20: =ConFin!G$128 -> € 000s
E21: ='T&E'!E$19 -> Initial operations date flag | F21: ='T&E'!F$19 -> 0 | G21: ='T&E'!G$19 -> flag | H21: ='T&E'!H$19 -> 1 | I21: ='T&E'!I$19 -> 0 | J21: ='T&E'!J$19 -> 0 | K21: ='T&E'!K$19 -> 0 | L21: ='T&E'!L$19 -> 0 | ... CA21: ='T&E'!CA$19 -> 0
E23: Net fixed assets balance BEG | G23: =SMU -> € 000s | J23: =I26 -> 0 | K23: =J26 -> 0 | L23: =K26 -> 0 | M23: =L26 -> 0 | N23: =M26 -> 0 | O23: =N26 -> 395404.94 | P23: =O26 -> 387496.85 | Q23: =P26 -> 379588.75 | ... CA23: =BZ26 -> -2.3101165e-10
D24: plus: | E24: [Ongoing capital expenditure] | G24: =SMU -> € 000s
D25: less: | E25: =E$14 -> Book depreciation POS | F25: =F$14 -> 0 | G25: =G$14 -> € 000s | H25: =H$14 -> 395404.94 | I25: =I$14 -> 0 | J25: =J$14 -> 0 | K25: =K$14 -> 0 | L25: =L$14 -> 0 | ... CA25: =CA$14 -> 0
E26: Net fixed assets balance | G26: =SMU -> € 000s | J26: =IF( J21 = 1, $F20, J23 + J24 - J25) -> 0 | K26: =IF( K21 = 1, $F20, K23 + K24 - K25) -> 0 | L26: =IF( L21 = 1, $F20, L23 + L24 - L25) -> 0 | M26: =IF( M21 = 1, $F20, M23 + M24 - M25) -> 0 | N26: =IF( N21 = 1, $F20, N23 + N24 - N25) -> 395404.94 | O26: =IF( O21 = 1, $F20, O23 + O24 - O25) -> 387496.85 | P26: =IF( P21 = 1, $F20, P23 + P24 - P25) -> 379588.75 | Q26: =IF( Q21 = 1, $F20, Q23 + Q24 - Q25) -> 371680.65 | ... CA26: =IF( CA21 = 1, $F20, CA23 + CA24 - CA25) -> -2.3101165e-10

Sheet SrDebt
A1: =RIGHT(CELL("filename", A1), LEN(CELL("filename", A1)) - SEARCH("]", CELL("filename", A1))) -> SrDebt
E2: ='T&E'!E$24 -> Operating period flag | F2: ='T&E'!F$24 -> 0 | G2: ='T&E'!G$24 -> flag | H2: ='T&E'!H$24 -> 60 | I2: ='T&E'!I$24 -> 0 | J2: ='T&E'!J$24 -> 0 | K2: ='T&E'!K$24 -> 0 | L2: ='T&E'!L$24 -> 0 | ... CA2: ='T&E'!CA$24 -> 0
E3: ='T&E'!E$8 -> Model column counter | F3: ='T&E'!F$8 -> 0 | G3: ='T&E'!G$8 -> 0 | H3: ='T&E'!H$8 -> 0 | I3: ='T&E'!I$8 -> 0 | J3: ='T&E'!J$8 -> 1 | K3: ='T&E'!K$8 -> 2 | L3: ='T&E'!L$8 -> 3 | ... CA3: ='T&E'!CA$8 -> 70
E4: ='T&E'!E$12 -> Model period ending | F4: ='T&E'!F$12 -> constant | G4: ='T&E'!G$12 -> unit | H4: ='T&E'!H$12 -> total | I4: ='T&E'!I$12 -> 0 | J4: ='T&E'!J$12 -> 41639 | K4: ='T&E'!K$12 -> 41820 | L4: ='T&E'!L$12 -> 42004 | ... CA4: ='T&E'!CA$12 -> 54239
A6: INTEREST EXPENSE
E8: ='T&E'!E$29 -> Senior debt term / ratio calc date flag | F8: ='T&E'!F$29 -> 0 | G8: ='T&E'!G$29 -> flag | H8: ='T&E'!H$29 -> 40 | I8: ='T&E'!I$29 -> 0 | J8: ='T&E'!J$29 -> 0 | K8: ='T&E'!K$29 -> 0 | L8: ='T&E'!L$29 -> 0 | ... CA8: ='T&E'!CA$29 -> 0
E9: [Senior debt margin period 1 flag] | H9: =SUM(J9:CA9) -> 10 | O9: 1 | P9: 1 | Q9: 1 | R9: 1 | S9: 1 | T9: 1 | U9: 1 | V9: 1 | W9: 1 | X9: 1
E10: [Senior debt margin period 2 flag] | H10: =SUM(J10:CA10) -> 10 | Y10: 1 | Z10: 1 | AA10: 1 | AB10: 1 | AC10: 1 | AD10: 1 | AE10: 1 | AF10: 1 | AG10: 1 | AH10: 1
E11: Senior debt margin remaining term period | H11: =SUM(J11:CA11) -> 20 | J11: =J8 - SUM(J9:J10) -> 0 | K11: =K8 - SUM(K9:K10) -> 0 | L11: =L8 - SUM(L9:L10) -> 0 | M11: =M8 - SUM(M9:M10) -> 0 | N11: =N8 - SUM(N9:N10) -> 0 | O11: =O8 - SUM(O9:O10) -> 0 | P11: =P8 - SUM(P9:P10) -> 0 | Q11: =Q8 - SUM(Q9:Q10) -> 0 | ... CA11: =CA8 - SUM(CA9:CA10) -> 0
E13: Senior debt risk margin - Period 1 | F13: 0.02 | G13: p.a. (semi)
E14: Senior debt risk margin - Period 2 | F14: 0.015 | G14: p.a. (semi)
E15: Senior debt risk margin - remaining term | F15: 0.01 | G15: p.a. (semi)
E17: =E9 -> [Senior debt margin period 1 flag] | F17: =F9 -> 0 | G17: =G9 -> 0 | H17: =H9 -> 10 | I17: =I9 -> 0 | J17: =J9 -> 0 | K17: =K9 -> 0 | L17: =L9 -> 0 | ... CA17: =CA9 -> 0
E18: =E10 -> [Senior debt margin period 2 flag] | F18: =F10 -> 0 | G18: =G10 -> 0 | H18: =H10 -> 10 | I18: =I10 -> 0 | J18: =J10 -> 0 | K18: =K10 -> 0 | L18: =L10 -> 0 | ... CA18: =CA10 -> 0
E19: =E11 -> Senior debt margin remaining term period | F19: =F11 -> 0 | G19: =G11 -> 0 | H19: =H11 -> 20 | I19: =I11 -> 0 | J19: =J11 -> 0 | K19: =K11 -> 0 | L19: =L11 -> 0 | ... CA19: =CA11 -> 0
E21: Senior term debt risk margin | J21: =SUMPRODUCT($F13:$F15, J17:J19) -> 0 | K21: =SUMPRODUCT($F13:$F15, K17:K19) -> 0 | L21: =SUMPRODUCT($F13:$F15, L17:L19) -> 0 | M21: =SUMPRODUCT($F13:$F15, M17:M19) -> 0 | N21: =SUMPRODUCT($F13:$F15, N17:N19) -> 0 | O21: =SUMPRODUCT($F13:$F15, O17:O19) -> 0.02 | P21: =SUMPRODUCT($F13:$F15, P17:P19) -> 0.02 | Q21: =SUMPRODUCT($F13:$F15, Q17:Q19) -> 0.02 | ... CA21: =SUMPRODUCT($F13:$F15, CA17:CA19) -> 0
E23: =InpC!E$40 -> Senior debt coupon base rate | F23: =InpC!F$40 -> 0.075 | G23: =InpC!G$40 -> p.a. (semi)
E24: =E$21 -> Senior term debt risk margin | F24: =F$21 -> 0 | G24: =G$21 -> 0 | H24: =H$21 -> 0 | I24: =I$21 -> 0 | J24: =J$21 -> 0 | K24: =K$21 -> 0 | L24: =L$21 -> 0 | ... CA24: =CA$21 -> 0
E25: ='T&E'!E$29 -> Senior debt term / ratio calc date flag | F25: ='T&E'!F$29 -> 0 | G25: ='T&E'!G$29 -> flag | H25: ='T&E'!H$29 -> 40 | I25: ='T&E'!I$29 -> 0 | J25: ='T&E'!J$29 -> 0 | K25: ='T&E'!K$29 -> 0 | L25: ='T&E'!L$29 -> 0 | ... CA25: ='T&E'!CA$29 -> 0
E26: Senior debt coupon rate | J26: =($F23 + J24) * J25 -> 0 | K26: =($F23 + K24) * K25 -> 0 | L26: =($F23 + L24) * L25 -> 0 | M26: =($F23 + M24) * M25 -> 0 | N26: =($F23 + N24) * N25 -> 0 | O26: =($F23 + O24) * O25 -> 0.095 | P26: =($F23 + P24) * P25 -> 0.095 | Q26: =($F23 + Q24) * Q25 -> 0.095 | ... CA26: =($F23 + CA24) * CA25 -> 0
E28: =E$26 -> Senior debt coupon rate | F28: =F$26 -> 0 | G28: =G$26 -> 0 | H28: =H$26 -> 0 | I28: =I$26 -> 0 | J28: =J$26 -> 0 | K28: =K$26 -> 0 | L28: =L$26 -> 0 | ... CA28: =CA$26 -> 0
E29: =E$71 -> Senior term debt balance BEG | F29: =F$71 -> 0 | G29: =G$71 -> € 000s | H29: =H$71 -> 0 | I29: =I$71 -> 0 | J29: =J$71 -> 0 | K29: =K$71 -> 0 | L29: =L$71 -> 0 | ... CA29: =CA$71 -> 3.2741809e-11
E30: Senior debt interest expense POS | G30: =SMU -> € 000s | H30: =SUM(J30:CA30) -> 392274.3 | J30: =(J28 / 2) * J29 -> 0 | K30: =(K28 / 2) * K29 -> 0 | L30: =(L28 / 2) * L29 -> 0 | M30: =(M28 / 2) * M29 -> 0 | N30: =(N28 / 2) * N29 -> 0 | O30: =(O28 / 2) * O29 -> 15329.388 | P30: =(P28 / 2) * P29 -> 15185.138 | Q30: =(Q28 / 2) * Q29 -> 15030.465 | ... CA30: =(CA28 / 2) * CA29 -> 0
E31: =LEFT(E30, LEN(E30) - 4) -> Senior debt interest expense | G31: =G30 -> € 000s | H31: =SUM(J31:CA31) -> -392274.3 | J31: =-1 * J30 -> 0 | K31: =-1 * K30 -> 0 | L31: =-1 * L30 -> 0 | M31: =-1 * M30 -> 0 | N31: =-1 * N30 -> 0 | O31: =-1 * O30 -> -15329.388 | P31: =-1 * P30 -> -15185.138 | Q31: =-1 * Q30 -> -15030.465 | ... CA31: =-1 * CA30 -> 0
A34: PRINCIPAL REPAYMENT
E36: Target DSCR guess | F36: 1.3980495 | G36: ratio
E37: =Ratios!E$18 -> CFADS over debt term | F37: =Ratios!F$18 -> 0 | G37: =Ratios!G$18 -> 0 | H37: =Ratios!H$18 -> 999604.92 | I37: =Ratios!I$18 -> 0 | J37: =Ratios!J$18 -> 0 | K37: =Ratios!K$18 -> 0 | L37: =Ratios!L$18 -> 0 | ... CA37: =Ratios!CA$18 -> 0
E38: Target debt service | H38: =SUM(J38:CA38) -> 714999.65 | J38: =J37 / $F36 -> 0 | K38: =K37 / $F36 -> 0 | L38: =L37 / $F36 -> 0 | M38: =M37 / $F36 -> 0 | N38: =N37 / $F36 -> 0 | O38: =O37 / $F36 -> 18364.968 | P38: =P37 / $F36 -> 18443.047 | Q38: =Q37 / $F36 -> 18645.981 | ... CA38: =CA37 / $F36 -> 0
E40: =E$38 -> Target debt service | F40: =F$38 -> 0 | G40: =G$38 -> 0 | H40: =H$38 -> 714999.65 | I40: =I$38 -> 0 | J40: =J$38 -> 0 | K40: =K$38 -> 0 | L40: =L$38 -> 0 | ... CA40: =CA$38 -> 0
D41: less: | E41: =E$30 -> Senior debt interest expense POS | F41: =F$30 -> 0 | G41: =G$30 -> € 000s | H41: =H$30 -> 392274.3 | I41: =I$30 -> 0 | J41: =J$30 -> 0 | K41: =K$30 -> 0 | L41: =L$30 -> 0 | ... CA41: =CA$30 -> 0
E42: Target principal repayment | H42: =SUM(J42:CA42) -> 322725.35 | J42: =J40 - J41 -> 0 | K42: =K40 - K41 -> 0 | L42: =L40 - L41 -> 0 | M42: =M40 - M41 -> 0 | N42: =N40 - N41 -> 0 | O42: =O40 - O41 -> 3035.5801 | P42: =P40 - P41 -> 3257.9086 | Q42: =Q40 - Q41 -> 3615.5158 | ... CA42: =CA40 - CA41 -> 0
E44: =ConFin!E$84 -> Construction debt converted to term total | F44: =ConFin!F$84 -> 322723.96 | G44: =ConFin!G$84 -> € 000s
E45: =E$42 -> Target principal repayment | F45: =F$42 -> 0 | G45: =G$42 -> 0 | H45: =H$42 -> 322725.35 | I45: =I$42 -> 0 | J45: =J$42 -> 0 | K45: =K$42 -> 0 | L45: =L$42 -> 0 | ... CA45: =CA$42 -> 0
E46: Sculpted repayment profile LIVE | H46: =SUM(J46:CA46) -> 1.0000043 | J46: =J45 / $F44 -> 0 | K46: =K45 / $F44 -> 0 | L46: =L45 / $F44 -> 0 | M46: =M45 / $F44 -> 0 | N46: =N45 / $F44 -> 0 | O46: =O45 / $F44 -> 0.0094061195 | P46: =P45 / $F44 -> 0.010095032 | Q46: =Q45 / $F44 -> 0.011203122 | ... CA46: =CA45 / $F44 -> 0
E47: Amplified SET CELL delta = 0 | F47: =10 ^ 8 * ( SUM(J46:CA46) - 1) -> 432.51647 | G47: SET CELL
E49: [Last senior debt repayment date flag] | BB49: 1
E50: =E$46 -> Sculpted repayment profile LIVE | F50: =F$46 -> 0 | G50: =G$46 -> 0 | H50: =H$46 -> 1.0000043 | I50: =I$46 -> 0 | J50: =J$46 -> 0 | K50: =K$46 -> 0 | L50: =L$46 -> 0 | ... CA50: =CA$46 -> 0
E51: Sculpted repayment profile ROUND | H51: =SUM(J51:CA51) -> 1.00001 | J51: =ROUND(J50, 5) -> 0 | K51: =ROUND(K50, 5) -> 0 | L51: =ROUND(L50, 5) -> 0 | M51: =ROUND(M50, 5) -> 0 | N51: =ROUND(N50, 5) -> 0 | O51: =ROUND(O50, 5) -> 0.00941 | P51: =ROUND(P50, 5) -> 0.0101 | Q51: =ROUND(Q50, 5) -> 0.0112 | ... CA51: =ROUND(CA50, 5) -> 0
E52: Sculpted repayment profile COPY TARGET | H52: =SUM(J52:CA52) -> 1 | J52: =IF(J49 = 1, 100% - SUM($I52:I52), J51) -> 0 | K52: =IF(K49 = 1, 100% - SUM($I52:J52), K51) -> 0 | L52: =IF(L49 = 1, 100% - SUM($I52:K52), L51) -> 0 | M52: =IF(M49 = 1, 100% - SUM($I52:L52), M51) -> 0 | N52: =IF(N49 = 1, 100% - SUM($I52:M52), N51) -> 0 | O52: =IF(O49 = 1, 100% - SUM($I52:N52), O51) -> 0.00941 | P52: =IF(P49 = 1, 100% - SUM($I52:O52), P51) -> 0.0101 | Q52: =IF(Q49 = 1, 100% - SUM($I52:P52), Q51) -> 0.0112 | ... CA52: =IF(CA49 = 1, 100% - SUM($I52:BZ52), CA51) -> 0
E54: Use live sculpted profile switch | F54: 0 | G54: 1 = use live
E55: =E$46 -> Sculpted repayment profile LIVE | F55: =F$46 -> 0 | G55: =G$46 -> 0 | H55: =H$46 -> 1.0000043 | I55: =I$46 -> 0 | J55: =J$46 -> 0 | K55: =K$46 -> 0 | L55: =L$46 -> 0 | ... CA55: =CA$46 -> 0
E56: =InpS!E$35 -> Senior debt repayment profile - saved selection | F56: =InpS!F$35 -> 0 | G56: =InpS!G$35 -> 0 | H56: =InpS!H$35 -> 1 | I56: =InpS!I$35 -> 0 | J56: =InpS!J$35 -> 0 | K56: =InpS!K$35 -> 0 | L56: =InpS!L$35 -> 0 | ... CA56: =InpS!CA$35 -> 0
E57: Active senior debt repayment profile | H57: =SUM(J57:CA57) -> 1 | J57: =IF($F54 = 1, J55, J56) -> 0 | K57: =IF($F54 = 1, K55, K56) -> 0 | L57: =IF($F54 = 1, L55, L56) -> 0 | M57: =IF($F54 = 1, M55, M56) -> 0 | N57: =IF($F54 = 1, N55, N56) -> 0 | O57: =IF($F54 = 1, O55, O56) -> 0.00941 | P57: =IF($F54 = 1, P55, P56) -> 0.01009 | Q57: =IF($F54 = 1, Q55, Q56) -> 0.0112 | ... CA57: =IF($F54 = 1, CA55, CA56) -> 0
E59: =ConFin!E$84 -> Construction debt converted to term total | F59: =ConFin!F$84 -> 322723.96 | G59: =ConFin!G$84 -> € 000s
E60: =E$57 -> Active senior debt repayment profile | F60: =F$57 -> 0 | G60: =G$57 -> 0 | H60: =H$57 -> 1 | I60: =I$57 -> 0 | J60: =J$57 -> 0 | K60: =K$57 -> 0 | L60: =L$57 -> 0 | ... CA60: =CA$57 -> 0
E61: ='T&E'!E$24 -> Operating period flag | F61: ='T&E'!F$24 -> 0 | G61: ='T&E'!G$24 -> flag | H61: ='T&E'!H$24 -> 60 | I61: ='T&E'!I$24 -> 0 | J61: ='T&E'!J$24 -> 0 | K61: ='T&E'!K$24 -> 0 | L61: ='T&E'!L$24 -> 0 | ... CA61: ='T&E'!CA$24 -> 0
E62: Senior principal repayment POS | G62: =SMU -> € 000s | H62: =SUM(J62:CA62) -> 322723.96 | J62: =$F59 * J60 * J61 -> 0 | K62: =$F59 * K60 * K61 -> 0 | L62: =$F59 * L60 * L61 -> 0 | M62: =$F59 * M60 * M61 -> 0 | N62: =$F59 * N60 * N61 -> 0 | O62: =$F59 * O60 * O61 -> 3036.8324 | P62: =$F59 * P60 * P61 -> 3256.2847 | Q62: =$F59 * Q60 * Q61 -> 3614.5083 | ... CA62: =$F59 * CA60 * CA61 -> 0
E63: =LEFT(E62, LEN(E62) - 4) -> Senior principal repayment | G63: =G62 -> € 000s | H63: =SUM(J63:CA63) -> -322723.96 | J63: =-1 * J62 -> 0 | K63: =-1 * K62 -> 0 | L63: =-1 * L62 -> 0 | M63: =-1 * M62 -> 0 | N63: =-1 * N62 -> 0 | O63: =-1 * O62 -> -3036.8324 | P63: =-1 * P62 -> -3256.2847 | Q63: =-1 * Q62 -> -3614.5083 | ... CA63: =-1 * CA62 -> 0
A66: SENIOR DEBT BALANCE
E68: =ConFin!E$84 -> Construction debt converted to term total | F68: =ConFin!F$84 -> 322723.96 | G68: =ConFin!G$84 -> € 000s
E69: ='T&E'!E$19 -> Initial operations date flag | F69: ='T&E'!F$19 -> 0 | G69: ='T&E'!G$19 -> flag | H69: ='T&E'!H$19 -> 1 | I69: ='T&E'!I$19 -> 0 | J69: ='T&E'!J$19 -> 0 | K69: ='T&E'!K$19 -> 0 | L69: ='T&E'!L$19 -> 0 | ... CA69: ='T&E'!CA$19 -> 0
E71: Senior term debt balance BEG | G71: =SMU -> € 000s | J71: =I74 -> 0 | K71: =J74 -> 0 | L71: =K74 -> 0 | M71: =L74 -> 0 | N71: =M74 -> 0 | O71: =N74 -> 322723.96 | P71: =O74 -> 319687.12 | Q71: =P74 -> 316430.84 | ... CA71: =BZ74 -> 3.2741809e-11
D72: plus: | E72: [Future debt borrowing] | G72: =SMU -> € 000s
D73: less: | E73: =E$62 -> Senior principal repayment POS | F73: =F$62 -> 0 | G73: =G$62 -> € 000s | H73: =H$62 -> 322723.96 | I73: =I$62 -> 0 | J73: =J$62 -> 0 | K73: =K$62 -> 0 | L73: =L$62 -> 0 | ... CA73: =CA$62 -> 0
E74: Senior term debt balance | G74: =SMU -> € 000s | J74: =IF( J69 = 1, $F68, J71 + J72 - J73) -> 0 | K74: =IF( K69 = 1, $F68, K71 + K72 - K73) -> 0 | L74: =IF( L69 = 1, $F68, L71 + L72 - L73) -> 0 | M74: =IF( M69 = 1, $F68, M71 + M72 - M73) -> 0 | N74: =IF( N69 = 1, $F68, N71 + N72 - N73) -> 322723.96 | O74: =IF( O69 = 1, $F68, O71 + O72 - O73) -> 319687.12 | P74: =IF( P69 = 1, $F68, P71 + P72 - P73) -> 316430.84 | Q74: =IF( Q69 = 1, $F68, Q71 + Q72 - Q73) -> 312816.33 | ... CA74: =IF( CA69 = 1, $F68, CA71 + CA72 - CA73) -> 3.2741809e-11
E77: =E$30 -> Senior debt interest expense POS | F77: =F$30 -> 0 | G77: =G$30 -> € 000s | H77: =H$30 -> 392274.3 | I77: =I$30 -> 0 | J77: =J$30 -> 0 | K77: =K$30 -> 0 | L77: =L$30 -> 0 | ... CA77: =CA$30 -> 0
E78: =E$62 -> Senior principal repayment POS | F78: =F$62 -> 0 | G78: =G$62 -> € 000s | H78: =H$62 -> 322723.96 | I78: =I$62 -> 0 | J78: =J$62 -> 0 | K78: =K$62 -> 0 | L78: =L$62 -> 0 | ... CA78: =CA$62 -> 0
E79: Senior debt service | H79: =SUM(J79:CA79) -> 714998.26 | J79: =SUM(J77:J78) -> 0 | K79: =SUM(K77:K78) -> 0 | L79: =SUM(L77:L78) -> 0 | M79: =SUM(M77:M78) -> 0 | N79: =SUM(N77:N78) -> 0 | O79: =SUM(O77:O78) -> 18366.22 | P79: =SUM(P77:P78) -> 18441.423 | Q79: =SUM(Q77:Q78) -> 18644.973 | ... CA79: =SUM(CA77:CA78) -> 0

Sheet DSRA
A1: =RIGHT(CELL("filename", A1), LEN(CELL("filename", A1)) - SEARCH("]", CELL("filename", A1))) -> DSRA
E2: ='T&E'!E$24 -> Operating period flag | F2: ='T&E'!F$24 -> 0 | G2: ='T&E'!G$24 -> flag | H2: ='T&E'!H$24 -> 60 | I2: ='T&E'!I$24 -> 0 | J2: ='T&E'!J$24 -> 0 | K2: ='T&E'!K$24 -> 0 | L2: ='T&E'!L$24 -> 0 | ... CA2: ='T&E'!CA$24 -> 0
E3: ='T&E'!E$8 -> Model column counter | F3: ='T&E'!F$8 -> 0 | G3: ='T&E'!G$8 -> 0 | H3: ='T&E'!H$8 -> 0 | I3: ='T&E'!I$8 -> 0 | J3: ='T&E'!J$8 -> 1 | K3: ='T&E'!K$8 -> 2 | L3: ='T&E'!L$8 -> 3 | ... CA3: ='T&E'!CA$8 -> 70
E4: ='T&E'!E$12 -> Model period ending | F4: ='T&E'!F$12 -> constant | G4: ='T&E'!G$12 -> unit | H4: ='T&E'!H$12 -> total | I4: ='T&E'!I$12 -> 0 | J4: ='T&E'!J$12 -> 41639 | K4: ='T&E'!K$12 -> 41820 | L4: ='T&E'!L$12 -> 42004 | ... CA4: ='T&E'!CA$12 -> 54239
A6: PRELIM DSRA WORKINGS
E8: =SrDebt!E$79 -> Senior debt service | F8: =SrDebt!F$79 -> 0 | G8: =SrDebt!G$79 -> 0 | H8: =SrDebt!H$79 -> 714998.26 | I8: =SrDebt!I$79 -> 0 | J8: =SrDebt!J$79 -> 0 | K8: =SrDebt!K$79 -> 0 | L8: =SrDebt!L$79 -> 0 | ... CA8: =SrDebt!CA$79 -> 0
E9: ='T&E'!E$24 -> Operating period flag | F9: ='T&E'!F$24 -> 0 | G9: ='T&E'!G$24 -> flag | H9: ='T&E'!H$24 -> 60 | I9: ='T&E'!I$24 -> 0 | J9: ='T&E'!J$24 -> 0 | K9: ='T&E'!K$24 -> 0 | L9: ='T&E'!L$24 -> 0 | ... CA9: ='T&E'!CA$24 -> 0
E10: Target DSRA balance | F10: NEXT | J10: =K8 * J9 -> 0 | K10: =L8 * K9 -> 0 | L10: =M8 * L9 -> 0 | M10: =N8 * M9 -> 0 | N10: =O8 * N9 -> 0 | O10: =P8 * O9 -> 18441.423 | P10: =Q8 * P9 -> 18644.973 | Q10: =R8 * Q9 -> 17479.294 | ... CA10: =CB8 * CA9 -> 0
E12: =E$10 -> Target DSRA balance | F12: =F$10 -> NEXT | G12: =G$10 -> 0 | H12: =H$10 -> 0 | I12: =I$10 -> 0 | J12: =J$10 -> 0 | K12: =K$10 -> 0 | L12: =L$10 -> 0 | ... CA12: =CA$10 -> 0
E13: =E$57 -> Senior DSRA balance BEG | F13: =F$57 -> 0 | G13: =G$57 -> € 000s | H13: =H$57 -> 0 | I13: =I$57 -> 0 | J13: =J$57 -> 0 | K13: =K$57 -> 0 | L13: =L$57 -> 0 | ... CA13: =CA$57 -> 0
E14: Senior DSRA target deposit / (releases) | J14: =J12 - J13 -> 0 | K14: =K12 - K13 -> 0 | L14: =L12 - L13 -> 0 | M14: =M12 - M13 -> 0 | N14: =N12 - N13 -> 0 | O14: =O12 - O13 -> 10441.423 | P14: =P12 - P13 -> 3336.0588 | Q14: =Q12 - Q13 -> -1165.6789 | ... CA14: =CA12 - CA13 -> 0
E16: =E$14 -> Senior DSRA target deposit / (releases) | F16: =F$14 -> 0 | G16: =G$14 -> 0 | H16: =H$14 -> 0 | I16: =I$14 -> 0 | J16: =J$14 -> 0 | K16: =K$14 -> 0 | L16: =L$14 -> 0 | ... CA16: =CA$14 -> 0
E17: Senior DSRA target deposits | H17: =SUM(J17:CA17) -> 17029.2 | J17: =MAX(J16, 0) -> 0 | K17: =MAX(K16, 0) -> 0 | L17: =MAX(L16, 0) -> 0 | M17: =MAX(M16, 0) -> 0 | N17: =MAX(N16, 0) -> 0 | O17: =MAX(O16, 0) -> 10441.423 | P17: =MAX(P16, 0) -> 3336.0588 | Q17: =MAX(Q16, 0) -> 0 | ... CA17: =MAX(CA16, 0) -> 0
E18: Senior DSRA releases | H18: =SUM(J18:CA18) -> 21896.691 | J18: =-1 * MIN(J16, 0) -> 0 | K18: =-1 * MIN(K16, 0) -> 0 | L18: =-1 * MIN(L16, 0) -> 0 | M18: =-1 * MIN(M16, 0) -> 0 | N18: =-1 * MIN(N16, 0) -> 0 | O18: =-1 * MIN(O16, 0) -> 0 | P18: =-1 * MIN(P16, 0) -> 0 | Q18: =-1 * MIN(Q16, 0) -> 1165.6789 | ... CA18: =-1 * MIN(CA16, 0) -> 0
E20: =Equity!E$83 -> Retained cash / (overdraft) balance BEG | F20: =Equity!F$83 -> 0 | G20: =Equity!G$83 -> € 000s | H20: =Equity!H$83 -> 0 | I20: =Equity!I$83 -> 0 | J20: =Equity!J$83 -> 0 | K20: =Equity!K$83 -> 0 | L20: =Equity!L$83 -> 0 | ... CA20: =Equity!CA$83 -> 5.0931703e-11
E21: =Finstat!E$47 -> Cash flow available for senior DSRA | F21: =Finstat!F$47 -> 0 | G21: =Finstat!G$47 -> 0 | H21: =Finstat!H$47 -> 876084.92 | I21: =Finstat!I$47 -> 0 | J21: =Finstat!J$47 -> 0 | K21: =Finstat!K$47 -> 0 | L21: =Finstat!L$47 -> 0 | ... CA21: =Finstat!CA$47 -> 0
E22: Total cash available for DSRA / (shortfall amount) | J22: =SUM(J20:J21) -> 0 | K22: =SUM(K20:K21) -> 0 | L22: =SUM(L20:L21) -> 0 | M22: =SUM(M20:M21) -> 0 | N22: =SUM(N20:N21) -> 0 | O22: =SUM(O20:O21) -> 7308.9143 | P22: =SUM(P20:P21) -> 7342.8699 | Q22: =SUM(Q20:Q21) -> 7423.0311 | ... CA22: =SUM(CA20:CA21) -> 5.0931703e-11
E24: =E$22 -> Total cash available for DSRA / (shortfall amount) | F24: =F$22 -> 0 | G24: =G$22 -> 0 | H24: =H$22 -> 0 | I24: =I$22 -> 0 | J24: =J$22 -> 0 | K24: =K$22 -> 0 | L24: =L$22 -> 0 | ... CA24: =CA$22 -> 5.0931703e-11
E25: Total cash available for senior DSRA deposits | H25: =SUM(J25:CA25) -> 1033914.2 | J25: =MAX(J24, 0) -> 0 | K25: =MAX(K24, 0) -> 0 | L25: =MAX(L24, 0) -> 0 | M25: =MAX(M24, 0) -> 0 | N25: =MAX(N24, 0) -> 0 | O25: =MAX(O24, 0) -> 7308.9143 | P25: =MAX(P24, 0) -> 7342.8699 | Q25: =MAX(Q24, 0) -> 7423.0311 | ... CA25: =MAX(CA24, 0) -> 5.0931703e-11
E26: Senior debt service shortfall amount | H26: =SUM(J26:CA26) -> 0 | J26: =-1 * MIN(J24, 0) -> 0 | K26: =-1 * MIN(K24, 0) -> 0 | L26: =-1 * MIN(L24, 0) -> 0 | M26: =-1 * MIN(M24, 0) -> 0 | N26: =-1 * MIN(N24, 0) -> 0 | O26: =-1 * MIN(O24, 0) -> 0 | P26: =-1 * MIN(P24, 0) -> 0 | Q26: =-1 * MIN(Q24, 0) -> 0 | ... CA26: =-1 * MIN(CA24, 0) -> 0
A29: SENIOR DSRA DEPOSITS
E31: =E$25 -> Total cash available for senior DSRA deposits | F31: =F$25 -> 0 | G31: =G$25 -> 0 | H31: =H$25 -> 1033914.2 | I31: =I$25 -> 0 | J31: =J$25 -> 0 | K31: =K$25 -> 0 | L31: =L$25 -> 0 | ... CA31: =CA$25 -> 5.0931703e-11
E32: =E$17 -> Senior DSRA target deposits | F32: =F$17 -> 0 | G32: =G$17 -> 0 | H32: =H$17 -> 17029.2 | I32: =I$17 -> 0 | J32: =J$17 -> 0 | K32: =K$17 -> 0 | L32: =L$17 -> 0 | ... CA32: =CA$17 -> 0
E33: Senior DSRA deposits POS | H33: =SUM(J33:CA33) -> 13896.691 | J33: =MIN(J31:J32) -> 0 | K33: =MIN(K31:K32) -> 0 | L33: =MIN(L31:L32) -> 0 | M33: =MIN(M31:M32) -> 0 | N33: =MIN(N31:N32) -> 0 | O33: =MIN(O31:O32) -> 7308.9143 | P33: =MIN(P31:P32) -> 3336.0588 | Q33: =MIN(Q31:Q32) -> 0 | ... CA33: =MIN(CA31:CA32) -> 0
E34: =LEFT(E33, LEN(E33) - 4) -> Senior DSRA deposits | G34: =G33 -> 0 | H34: =SUM(J34:CA34) -> -13896.691 | J34: =-1 * J33 -> 0 | K34: =-1 * K33 -> 0 | L34: =-1 * L33 -> 0 | M34: =-1 * M33 -> 0 | N34: =-1 * N33 -> 0 | O34: =-1 * O33 -> -7308.9143 | P34: =-1 * P33 -> -3336.0588 | Q34: =-1 * Q33 -> 0 | ... CA34: =-1 * CA33 -> 0
A37: SENIOR DSRA WITHDRAWALS
E39: =E$57 -> Senior DSRA balance BEG | F39: =F$57 -> 0 | G39: =G$57 -> € 000s | H39: =H$57 -> 0 | I39: =I$57 -> 0 | J39: =J$57 -> 0 | K39: =K$57 -> 0 | L39: =L$57 -> 0 | ... CA39: =CA$57 -> 0
E40: =E$26 -> Senior debt service shortfall amount | F40: =F$26 -> 0 | G40: =G$26 -> 0 | H40: =H$26 -> 0 | I40: =I$26 -> 0 | J40: =J$26 -> 0 | K40: =K$26 -> 0 | L40: =L$26 -> 0 | ... CA40: =CA$26 -> 0
E41: Senior DSRA shortfall withdrawals | H41: =SUM(J41:CA41) -> 0 | J41: =MIN(J39:J40) -> 0 | K41: =MIN(K39:K40) -> 0 | L41: =MIN(L39:L40) -> 0 | M41: =MIN(M39:M40) -> 0 | N41: =MIN(N39:N40) -> 0 | O41: =MIN(O39:O40) -> 0 | P41: =MIN(P39:P40) -> 0 | Q41: =MIN(Q39:Q40) -> 0 | ... CA41: =MIN(CA39:CA40) -> 0
E43: =E$41 -> Senior DSRA shortfall withdrawals | F43: =F$41 -> 0 | G43: =G$41 -> 0 | H43: =H$41 -> 0 | I43: =I$41 -> 0 | J43: =J$41 -> 0 | K43: =K$41 -> 0 | L43: =L$41 -> 0 | ... CA43: =CA$41 -> 0
E44: =E$18 -> Senior DSRA releases | F44: =F$18 -> 0 | G44: =G$18 -> 0 | H44: =H$18 -> 21896.691 | I44: =I$18 -> 0 | J44: =J$18 -> 0 | K44: =K$18 -> 0 | L44: =L$18 -> 0 | ... CA44: =CA$18 -> 0
E45: Senior DSRA withdrawals | H45: =SUM(J45:CA45) -> 21896.691 | J45: =MAX(J43:J44) -> 0 | K45: =MAX(K43:K44) -> 0 | L45: =MAX(L43:L44) -> 0 | M45: =MAX(M43:M44) -> 0 | N45: =MAX(N43:N44) -> 0 | O45: =MAX(O43:O44) -> 0 | P45: =MAX(P43:P44) -> 0 | Q45: =MAX(Q43:Q44) -> 1165.6789 | ... CA45: =MAX(CA43:CA44) -> 0
E47: =E$45 -> Senior DSRA withdrawals | F47: =F$45 -> 0 | G47: =G$45 -> 0 | H47: =H$45 -> 21896.691 | I47: =I$45 -> 0 | J47: =J$45 -> 0 | K47: =K$45 -> 0 | L47: =L$45 -> 0 | ... CA47: =CA$45 -> 0
D48: less: | E48: =E$41 -> Senior DSRA shortfall withdrawals | F48: =F$41 -> 0 | G48: =G$41 -> 0 | H48: =H$41 -> 0 | I48: =I$41 -> 0 | J48: =J$41 -> 0 | K48: =K$41 -> 0 | L48: =L$41 -> 0 | ... CA48: =CA$41 -> 0
E49: Senior DSRA net releases | H49: =SUM(J49:CA49) -> 21896.691 | J49: =J47 - J48 -> 0 | K49: =K47 - K48 -> 0 | L49: =L47 - L48 -> 0 | M49: =M47 - M48 -> 0 | N49: =N47 - N48 -> 0 | O49: =O47 - O48 -> 0 | P49: =P47 - P48 -> 0 | Q49: =Q47 - Q48 -> 1165.6789 | ... CA49: =CA47 - CA48 -> 0
A52: BALANCE
E54: =ConFin!E$57 -> Senior DSRA deposits DC total | F54: =ConFin!F$57 -> 8000 | G54: =ConFin!G$57 -> € 000s
E55: ='T&E'!E$19 -> Initial operations date flag | F55: ='T&E'!F$19 -> 0 | G55: ='T&E'!G$19 -> flag | H55: ='T&E'!H$19 -> 1 | I55: ='T&E'!I$19 -> 0 | J55: ='T&E'!J$19 -> 0 | K55: ='T&E'!K$19 -> 0 | L55: ='T&E'!L$19 -> 0 | ... CA55: ='T&E'!CA$19 -> 0
E57: Senior DSRA balance BEG | G57: =SMU -> € 000s | J57: =I60 -> 0 | K57: =J60 -> 0 | L57: =K60 -> 0 | M57: =L60 -> 0 | N57: =M60 -> 0 | O57: =N60 -> 8000 | P57: =O60 -> 15308.914 | Q57: =P60 -> 18644.973 | ... CA57: =BZ60 -> 0
D58: plus: | E58: =E$33 -> Senior DSRA deposits POS | F58: =F$33 -> 0 | G58: =G$33 -> 0 | H58: =H$33 -> 13896.691 | I58: =I$33 -> 0 | J58: =J$33 -> 0 | K58: =K$33 -> 0 | L58: =L$33 -> 0 | ... CA58: =CA$33 -> 0
D59: less: | E59: =E$45 -> Senior DSRA withdrawals | F59: =F$45 -> 0 | G59: =G$45 -> 0 | H59: =H$45 -> 21896.691 | I59: =I$45 -> 0 | J59: =J$45 -> 0 | K59: =K$45 -> 0 | L59: =L$45 -> 0 | ... CA59: =CA$45 -> 0
E60: Senior DSRA balance | G60: =SMU -> € 000s | J60: =IF( J55 = 1, $F54, J57 + J58 - J59) -> 0 | K60: =IF( K55 = 1, $F54, K57 + K58 - K59) -> 0 | L60: =IF( L55 = 1, $F54, L57 + L58 - L59) -> 0 | M60: =IF( M55 = 1, $F54, M57 + M58 - M59) -> 0 | N60: =IF( N55 = 1, $F54, N57 + N58 - N59) -> 8000 | O60: =IF( O55 = 1, $F54, O57 + O58 - O59) -> 15308.914 | P60: =IF( P55 = 1, $F54, P57 + P58 - P59) -> 18644.973 | Q60: =IF( Q55 = 1, $F54, Q57 + Q58 - Q59) -> 17479.294 | ... CA60: =IF( CA55 = 1, $F54, CA57 + CA58 - CA59) -> 0
A63: SIGN SWITCH
E65: Sign switch line item POS | G65: units | H65: =SUM(J65:CA65) -> 7000 | J65: 100 | K65: 100 | L65: 100 | M65: 100 | N65: 100 | O65: 100 | P65: 100 | Q65: 100 | R65: 100 | S65: 100 | T65: 100 | U65: 100 | V65: 100 | W65: 100 | X65: 100 | Y65: 100 | Z65: 100 | AA65: 100 | AB65: 100 | AC65: 100 | AD65: 100 | AE65: 100 | AF65: 100 | AG65: 100 | AH65: 100 | AI65: 100 | AJ65: 100 | AK65: 100 | AL65: 100 | AM65: 100 | AN65: 100 | AO65: 100 | AP65: 100 | AQ65: 100 | AR65: 100 | AS65: 100 | AT65: 100 | AU65: 100 | AV65: 100 | AW65: 100 | AX65: 100 | AY65: 100 | AZ65: 100 | BA65: 100 | BB65: 100 | BC65: 100 | BD65: 100 | BE65: 100 | BF65: 100 | BG65: 100 | BH65: 100 | BI65: 100 | BJ65: 100 | BK65: 100 | BL65: 100 | BM65: 100 | BN65: 100 | BO65: 100 | BP65: 100 | BQ65: 100 | BR65: 100 | BS65: 100 | BT65: 100 | BU65: 100 | BV65: 100 | BW65: 100 | BX65: 100 | BY65: 100 | BZ65: 100 | CA65: 100
E66: =LEFT(E65, LEN(E65) - 4) -> Sign switch line item | G66: =G65 -> units | H66: =SUM(J66:CA66) -> -7000 | J66: =-1 * J65 -> -100 | K66: =-1 * K65 -> -100 | L66: =-1 * L65 -> -100 | M66: =-1 * M65 -> -100 | N66: =-1 * N65 -> -100 | O66: =-1 * O65 -> -100 | P66: =-1 * P65 -> -100 | Q66: =-1 * Q65 -> -100 | ... CA66: =-1 * CA65 -> -100

Sheet Tax
A1: =RIGHT(CELL("filename", A1), LEN(CELL("filename", A1)) - SEARCH("]", CELL("filename", A1))) -> Tax
E2: ='T&E'!E$24 -> Operating period flag | F2: ='T&E'!F$24 -> 0 | G2: ='T&E'!G$24 -> flag | H2: ='T&E'!H$24 -> 60 | I2: ='T&E'!I$24 -> 0 | J2: ='T&E'!J$24 -> 0 | K2: ='T&E'!K$24 -> 0 | L2: ='T&E'!L$24 -> 0 | ... CA2: ='T&E'!CA$24 -> 0
E3: ='T&E'!E$8 -> Model column counter | F3: ='T&E'!F$8 -> 0 | G3: ='T&E'!G$8 -> 0 | H3: ='T&E'!H$8 -> 0 | I3: ='T&E'!I$8 -> 0 | J3: ='T&E'!J$8 -> 1 | K3: ='T&E'!K$8 -> 2 | L3: ='T&E'!L$8 -> 3 | ... CA3: ='T&E'!CA$8 -> 70
E4: ='T&E'!E$12 -> Model period ending | F4: ='T&E'!F$12 -> constant | G4: ='T&E'!G$12 -> unit | H4: ='T&E'!H$12 -> total | I4: ='T&E'!I$12 -> 0 | J4: ='T&E'!J$12 -> 41639 | K4: ='T&E'!K$12 -> 41820 | L4: ='T&E'!L$12 -> 42004 | ... CA4: ='T&E'!CA$12 -> 54239
A6: TAX DEPRECIATION / CAPITAL ALLOWANCES
E8: =InpC!E$47 -> Reducing balance rate for tax | F8: =InpC!F$47 -> 0.05 | G8: =InpC!G$47 -> of basis
E9: =E$16 -> Remaining tax basis balance BEG | F9: =F$16 -> 0 | G9: =G$16 -> € 000s | H9: =H$16 -> 0 | I9: =I$16 -> 0 | J9: =J$16 -> 0 | K9: =K$16 -> 0 | L9: =L$16 -> 0 | ... CA9: =CA$16 -> 0
E10: ='T&E'!E$38 -> Last forecast period flag | F10: ='T&E'!F$38 -> 0 | G10: ='T&E'!G$38 -> flag | H10: ='T&E'!H$38 -> 1 | I10: ='T&E'!I$38 -> 0 | J10: ='T&E'!J$38 -> 0 | K10: ='T&E'!K$38 -> 0 | L10: ='T&E'!L$38 -> 0 | ... CA10: ='T&E'!CA$38 -> 0
E11: Tax depreciaiton / capital allowances POS | G11: =SMU -> € 000s | H11: =SUM(J11:CA11) -> 395404.94 | J11: =IF(J10 = 1, J9, $F8 * J9) -> 0 | K11: =IF(K10 = 1, K9, $F8 * K9) -> 0 | L11: =IF(L10 = 1, L9, $F8 * L9) -> 0 | M11: =IF(M10 = 1, M9, $F8 * M9) -> 0 | N11: =IF(N10 = 1, N9, $F8 * N9) -> 0 | O11: =IF(O10 = 1, O9, $F8 * O9) -> 19770.247 | P11: =IF(P10 = 1, P9, $F8 * P9) -> 18781.735 | Q11: =IF(Q10 = 1, Q9, $F8 * Q9) -> 17842.648 | ... CA11: =IF(CA10 = 1, CA9, $F8 * CA9) -> 0
E13: =ConFin!E$128 -> Additions to fixed assets DC total | F13: =ConFin!F$128 -> 395404.94 | G13: =ConFin!G$128 -> € 000s
E14: ='T&E'!E$19 -> Initial operations date flag | F14: ='T&E'!F$19 -> 0 | G14: ='T&E'!G$19 -> flag | H14: ='T&E'!H$19 -> 1 | I14: ='T&E'!I$19 -> 0 | J14: ='T&E'!J$19 -> 0 | K14: ='T&E'!K$19 -> 0 | L14: ='T&E'!L$19 -> 0 | ... CA14: ='T&E'!CA$19 -> 0
E16: Remaining tax basis balance BEG | G16: =SMU -> € 000s | J16: =I19 -> 0 | K16: =J19 -> 0 | L16: =K19 -> 0 | M16: =L19 -> 0 | N16: =M19 -> 0 | O16: =N19 -> 395404.94 | P16: =O19 -> 375634.7 | Q16: =P19 -> 356852.96 | ... CA16: =BZ19 -> 0
D17: plus: | E17: [Ongoing capital expenditure] | G17: =SMU -> € 000s
D18: less: | E18: =E$11 -> Tax depreciaiton / capital allowances POS | F18: =F$11 -> 0 | G18: =G$11 -> € 000s | H18: =H$11 -> 395404.94 | I18: =I$11 -> 0 | J18: =J$11 -> 0 | K18: =K$11 -> 0 | L18: =L$11 -> 0 | ... CA18: =CA$11 -> 0
E19: Remaining tax basis balance | G19: =SMU -> € 000s | J19: =IF( J14 = 1, $F13, J16 + J17 - J18) -> 0 | K19: =IF( K14 = 1, $F13, K16 + K17 - K18) -> 0 | L19: =IF( L14 = 1, $F13, L16 + L17 - L18) -> 0 | M19: =IF( M14 = 1, $F13, M16 + M17 - M18) -> 0 | N19: =IF( N14 = 1, $F13, N16 + N17 - N18) -> 395404.94 | O19: =IF( O14 = 1, $F13, O16 + O17 - O18) -> 375634.7 | P19: =IF( P14 = 1, $F13, P16 + P17 - P18) -> 356852.96 | Q19: =IF( Q14 = 1, $F13, Q16 + Q17 - Q18) -> 339010.31 | ... CA19: =IF( CA14 = 1, $F13, CA16 + CA17 - CA18) -> 0
A22: TAXABLE INCOME / PAYMENTS
E24: =Rev!E$114 -> Operating revenue | F24: =Rev!F$114 -> 0 | G24: =Rev!G$114 -> € 000s | H24: =Rev!H$114 -> 2496071.6 | I24: =Rev!I$114 -> 0 | J24: =Rev!J$114 -> 0 | K24: =Rev!K$114 -> 0 | L24: =Rev!L$114 -> 0 | ... CA24: =Rev!CA$114 -> 0
D25: less: | E25: =Opex!E$33 -> Operating costs POS | F25: =Opex!F$33 -> 0 | G25: =Opex!G$33 -> € 000s | H25: =Opex!H$33 -> 560672.48 | I25: =Opex!I$33 -> 0 | J25: =Opex!J$33 -> 0 | K25: =Opex!K$33 -> 0 | L25: =Opex!L$33 -> 0 | ... CA25: =Opex!CA$33 -> 0
D26: less: | E26: =E$11 -> Tax depreciaiton / capital allowances POS | F26: =F$11 -> 0 | G26: =G$11 -> € 000s | H26: =H$11 -> 395404.94 | I26: =I$11 -> 0 | J26: =J$11 -> 0 | K26: =K$11 -> 0 | L26: =L$11 -> 0 | ... CA26: =CA$11 -> 0
D27: less: | E27: =SrDebt!E$30 -> Senior debt interest expense POS | F27: =SrDebt!F$30 -> 0 | G27: =SrDebt!G$30 -> € 000s | H27: =SrDebt!H$30 -> 392274.3 | I27: =SrDebt!I$30 -> 0 | J27: =SrDebt!J$30 -> 0 | K27: =SrDebt!K$30 -> 0 | L27: =SrDebt!L$30 -> 0 | ... CA27: =SrDebt!CA$30 -> 0
E28: Taxable income | G28: =SMU -> € 000s | H28: =SUM(J28:CA28) -> 1147719.9 | J28: =J24 - SUM(J25:J27) -> 0 | K28: =K24 - SUM(K25:K27) -> 0 | L28: =L24 - SUM(L25:L27) -> 0 | M28: =M24 - SUM(M25:M27) -> 0 | N28: =N24 - SUM(N25:N27) -> 0 | O28: =O24 - SUM(O25:O27) -> -13463.572 | P28: =P24 - SUM(P25:P27) -> -11689.4 | Q28: =Q24 - SUM(Q25:Q27) -> -9721.5839 | ... CA28: =CA24 - SUM(CA25:CA27) -> 0
E30: =InpC!E$49 -> Corporation tax rate | F30: =InpC!F$49 -> 0.3 | G30: =InpC!G$49 -> of TI
E31: =E$28 -> Taxable income | F31: =F$28 -> 0 | G31: =G$28 -> € 000s | H31: =H$28 -> 1147719.9 | I31: =I$28 -> 0 | J31: =J$28 -> 0 | K31: =K$28 -> 0 | L31: =L$28 -> 0 | ... CA31: =CA$28 -> 0
E32: [Tax payments POS] | G32: =SMU -> € 000s | H32: =SUM(J32:CA32) -> 344315.97 | J32: =$F30 * J31 -> 0 | K32: =$F30 * K31 -> 0 | L32: =$F30 * L31 -> 0 | M32: =$F30 * M31 -> 0 | N32: =$F30 * N31 -> 0 | O32: =$F30 * O31 -> -4039.0716 | P32: =$F30 * P31 -> -3506.8201 | Q32: =$F30 * Q31 -> -2916.4752 | ... CA32: =$F30 * CA31 -> 0
E33: =LEFT(E32, LEN(E32) - 4) -> [Tax payments | G33: =G32 -> € 000s | H33: =SUM(J33:CA33) -> -344315.97 | J33: =-1 * J32 -> 0 | K33: =-1 * K32 -> 0 | L33: =-1 * L32 -> 0 | M33: =-1 * M32 -> 0 | N33: =-1 * N32 -> 0 | O33: =-1 * O32 -> 4039.0716 | P33: =-1 * P32 -> 3506.8201 | Q33: =-1 * Q32 -> 2916.4752 | ... CA33: =-1 * CA32 -> 0
A36: ACCOUNTING FOR TAX
E38: =InpC!E$50 -> [Effective P&L tax rate] | F38: =InpC!F$50 -> 0.3 | G38: =InpC!G$50 -> of PBT
E39: =Finstat!E$15 -> Profit before tax | F39: =Finstat!F$15 -> 0 | G39: =Finstat!G$15 -> € 000s | H39: =Finstat!H$15 -> 1147719.9 | I39: =Finstat!I$15 -> 0 | J39: =Finstat!J$15 -> 0 | K39: =Finstat!K$15 -> 0 | L39: =Finstat!L$15 -> 0 | ... CA39: =Finstat!CA$15 -> 0
E40: P&L tax charge POS | G40: =SMU -> € 000s | H40: =SUM(J40:CA40) -> 344315.97 | J40: =$F38 * J39 -> 0 | K40: =$F38 * K39 -> 0 | L40: =$F38 * L39 -> 0 | M40: =$F38 * M39 -> 0 | N40: =$F38 * N39 -> 0 | O40: =$F38 * O39 -> -480.42713 | P40: =$F38 * P39 -> -244.72932 | Q40: =$F38 * Q39 -> 63.889601 | ... CA40: =$F38 * CA39 -> 0
E41: =LEFT(E40, LEN(E40) - 4) -> P&L tax charge | G41: =G40 -> € 000s | H41: =SUM(J41:CA41) -> -344315.97 | J41: =-1 * J40 -> 0 | K41: =-1 * K40 -> 0 | L41: =-1 * L40 -> 0 | M41: =-1 * M40 -> 0 | N41: =-1 * N40 -> 0 | O41: =-1 * O40 -> 480.42713 | P41: =-1 * P40 -> 244.72932 | Q41: =-1 * Q40 -> -63.889601 | ... CA41: =-1 * CA40 -> 0
E43: [Deferred tax liability / (asset) - Initial balance] | F43: 0 | G43: € 000s
E44: ='T&E'!E$19 -> Initial operations date flag | F44: ='T&E'!F$19 -> 0 | G44: ='T&E'!G$19 -> flag | H44: ='T&E'!H$19 -> 1 | I44: ='T&E'!I$19 -> 0 | J44: ='T&E'!J$19 -> 0 | K44: ='T&E'!K$19 -> 0 | L44: ='T&E'!L$19 -> 0 | ... CA44: ='T&E'!CA$19 -> 0
E46: Deferred tax liability / (asset) balance BEG | G46: =SMU -> € 000s | J46: =I49 -> 0 | K46: =J49 -> 0 | L46: =K49 -> 0 | M46: =L49 -> 0 | N46: =M49 -> 0 | O46: =N49 -> 0 | P46: =O49 -> 3558.6445 | Q46: =P49 -> 6820.7353 | ... CA46: =BZ49 -> 3.6379788e-11
D47: plus: | E47: =E$40 -> P&L tax charge POS | F47: =F$40 -> 0 | G47: =G$40 -> € 000s | H47: =H$40 -> 344315.97 | I47: =I$40 -> 0 | J47: =J$40 -> 0 | K47: =K$40 -> 0 | L47: =L$40 -> 0 | ... CA47: =CA$40 -> 0
D48: less: | E48: =E$32 -> [Tax payments POS] | F48: =F$32 -> 0 | G48: =G$32 -> € 000s | H48: =H$32 -> 344315.97 | I48: =I$32 -> 0 | J48: =J$32 -> 0 | K48: =K$32 -> 0 | L48: =L$32 -> 0 | ... CA48: =CA$32 -> 0
E49: Deferred tax liability / (asset) balance | G49: =SMU -> € 000s | J49: =IF( J44 = 1, $F43, J46 + J47 - J48) -> 0 | K49: =IF( K44 = 1, $F43, K46 + K47 - K48) -> 0 | L49: =IF( L44 = 1, $F43, L46 + L47 - L48) -> 0 | M49: =IF( M44 = 1, $F43, M46 + M47 - M48) -> 0 | N49: =IF( N44 = 1, $F43, N46 + N47 - N48) -> 0 | O49: =IF( O44 = 1, $F43, O46 + O47 - O48) -> 3558.6445 | P49: =IF( P44 = 1, $F43, P46 + P47 - P48) -> 6820.7353 | Q49: =IF( Q44 = 1, $F43, Q46 + Q47 - Q48) -> 9801.1001 | ... CA49: =IF( CA44 = 1, $F43, CA46 + CA47 - CA48) -> 3.6379788e-11

Sheet Equity
A1: =RIGHT(CELL("filename", A1), LEN(CELL("filename", A1)) - SEARCH("]", CELL("filename", A1))) -> Equity
E2: ='T&E'!E$24 -> Operating period flag | F2: ='T&E'!F$24 -> 0 | G2: ='T&E'!G$24 -> flag | H2: ='T&E'!H$24 -> 60 | I2: ='T&E'!I$24 -> 0 | J2: ='T&E'!J$24 -> 0 | K2: ='T&E'!K$24 -> 0 | L2: ='T&E'!L$24 -> 0 | ... CA2: ='T&E'!CA$24 -> 0
E3: ='T&E'!E$8 -> Model column counter | F3: ='T&E'!F$8 -> 0 | G3: ='T&E'!G$8 -> 0 | H3: ='T&E'!H$8 -> 0 | I3: ='T&E'!I$8 -> 0 | J3: ='T&E'!J$8 -> 1 | K3: ='T&E'!K$8 -> 2 | L3: ='T&E'!L$8 -> 3 | ... CA3: ='T&E'!CA$8 -> 70
E4: ='T&E'!E$12 -> Model period ending | F4: ='T&E'!F$12 -> constant | G4: ='T&E'!G$12 -> unit | H4: ='T&E'!H$12 -> total | I4: ='T&E'!I$12 -> 0 | J4: ='T&E'!J$12 -> 41639 | K4: ='T&E'!K$12 -> 41820 | L4: ='T&E'!L$12 -> 42004 | ... CA4: ='T&E'!CA$12 -> 54239
A6: SHAREHOLDER LOAN
B8: Interest / Coupon
B12: Principal Repayment
E14: =E$83 -> Retained cash / (overdraft) balance BEG | F14: =F$83 -> 0 | G14: =G$83 -> € 000s | H14: =H$83 -> 0 | I14: =I$83 -> 0 | J14: =J$83 -> 0 | K14: =K$83 -> 0 | L14: =L$83 -> 0 | ... CA14: =CA$83 -> 5.0931703e-11
D15: plus: | E15: =Finstat!E$52 -> Cash flow available for shareholder loan | F15: =Finstat!F$52 -> 0 | G15: =Finstat!G$52 -> 0 | H15: =Finstat!H$52 -> 884084.92 | I15: =Finstat!I$52 -> 0 | J15: =Finstat!J$52 -> 0 | K15: =Finstat!K$52 -> 0 | L15: =Finstat!L$52 -> 0 | ... CA15: =Finstat!CA$52 -> 0
E16: Total cash balance available for shareholder loan | J16: =SUM(J14:J15) -> 0 | K16: =SUM(K14:K15) -> 0 | L16: =SUM(L14:L15) -> 0 | M16: =SUM(M14:M15) -> 0 | N16: =SUM(N14:N15) -> 0 | O16: =SUM(O14:O15) -> 0 | P16: =SUM(P14:P15) -> 4006.8111 | Q16: =SUM(Q14:Q15) -> 8588.71 | ... CA16: =SUM(CA14:CA15) -> 5.0931703e-11
E18: =E$16 -> Total cash balance available for shareholder loan | G18: =G$16 -> 0 | H18: =H$16 -> 0 | I18: =I$16 -> 0 | J18: =J$16 -> 0 | K18: =K$16 -> 0 | L18: =L$16 -> 0 | M18: =M$16 -> 0 | N18: =N$16 -> 0 | ... CA18: =CA$16 -> 5.0931703e-11
E19: =E$33 -> Shareholder loan balance BEG | F19: =F$33 -> 0 | G19: =G$33 -> € 000s | H19: =H$33 -> 0 | I19: =I$33 -> 0 | J19: =J$33 -> 0 | K19: =K$33 -> 0 | L19: =L$33 -> 0 | ... CA19: =CA$33 -> 0
E20: Shareholder loan repayment POS | J20: =MIN(J18:J19) -> 0 | K20: =MIN(K18:K19) -> 0 | L20: =MIN(L18:L19) -> 0 | M20: =MIN(M18:M19) -> 0 | N20: =MIN(N18:N19) -> 0 | O20: =MIN(O18:O19) -> 0 | P20: =MIN(P18:P19) -> 4006.8111 | Q20: =MIN(Q18:Q19) -> 8588.71 | ... CA20: =MIN(CA18:CA19) -> 0
E21: =LEFT(E20, LEN(E20) - 4) -> Shareholder loan repayment | G21: =G20 -> 0 | H21: =SUM(J21:CA21) -> -79680.989 | J21: =-1 * J20 -> 0 | K21: =-1 * K20 -> 0 | L21: =-1 * L20 -> 0 | M21: =-1 * M20 -> 0 | N21: =-1 * N20 -> 0 | O21: =-1 * O20 -> 0 | P21: =-1 * P20 -> -4006.8111 | Q21: =-1 * Q20 -> -8588.71 | ... CA21: =-1 * CA20 -> 0
B24: Balance
E26: =ConFin!E$97 -> Equity investment total | F26: =ConFin!F$97 -> 80680.989 | G26: =ConFin!G$97 -> € 000s
D27: less: | E27: =InpC!E$54 -> Share capital investment requirement | F27: =InpC!F$54 -> 1000 | G27: =InpC!G$54 -> € 000s
E28: Amount invested as shareholder loan | F28: =F26 - F27 -> 79680.989 | G28: =SMU -> € 000s
E30: =E$28 -> Amount invested as shareholder loan | F30: =F$28 -> 79680.989 | G30: =G$28 -> € 000s
E31: ='T&E'!E$19 -> Initial operations date flag | F31: ='T&E'!F$19 -> 0 | G31: ='T&E'!G$19 -> flag | H31: ='T&E'!H$19 -> 1 | I31: ='T&E'!I$19 -> 0 | J31: ='T&E'!J$19 -> 0 | K31: ='T&E'!K$19 -> 0 | L31: ='T&E'!L$19 -> 0 | ... CA31: ='T&E'!CA$19 -> 0
E33: Shareholder loan balance BEG | G33: =SMU -> € 000s | J33: =I36 -> 0 | K33: =J36 -> 0 | L33: =K36 -> 0 | M33: =L36 -> 0 | N33: =M36 -> 0 | O33: =N36 -> 79680.989 | P33: =O36 -> 79680.989 | Q33: =P36 -> 75674.178 | ... CA33: =BZ36 -> 0
D34: plus: | E34: [Shareholder loan further funding / roll-ups]
D35: less: | E35: =E$20 -> Shareholder loan repayment POS | F35: =F$20 -> 0 | G35: =G$20 -> 0 | H35: =H$20 -> 0 | I35: =I$20 -> 0 | J35: =J$20 -> 0 | K35: =K$20 -> 0 | L35: =L$20 -> 0 | ... CA35: =CA$20 -> 0
E36: Shareholder loan balance | G36: =SMU -> € 000s | J36: =IF( J31 = 1, $F30, J33 + J34 - J35) -> 0 | K36: =IF( K31 = 1, $F30, K33 + K34 - K35) -> 0 | L36: =IF( L31 = 1, $F30, L33 + L34 - L35) -> 0 | M36: =IF( M31 = 1, $F30, M33 + M34 - M35) -> 0 | N36: =IF( N31 = 1, $F30, N33 + N34 - N35) -> 79680.989 | O36: =IF( O31 = 1, $F30, O33 + O34 - O35) -> 79680.989 | P36: =IF( P31 = 1, $F30, P33 + P34 - P35) -> 75674.178 | Q36: =IF( Q31 = 1, $F30, Q33 + Q34 - Q35) -> 67085.468 | ... CA36: =IF( CA31 = 1, $F30, CA33 + CA34 - CA35) -> 0
A39: SIGN SWITCH
E41: Sign switch line item POS | G41: units | H41: =SUM(J41:CA41) -> 7000 | J41: 100 | K41: 100 | L41: 100 | M41: 100 | N41: 100 | O41: 100 | P41: 100 | Q41: 100 | R41: 100 | S41: 100 | T41: 100 | U41: 100 | V41: 100 | W41: 100 | X41: 100 | Y41: 100 | Z41: 100 | AA41: 100 | AB41: 100 | AC41: 100 | AD41: 100 | AE41: 100 | AF41: 100 | AG41: 100 | AH41: 100 | AI41: 100 | AJ41: 100 | AK41: 100 | AL41: 100 | AM41: 100 | AN41: 100 | AO41: 100 | AP41: 100 | AQ41: 100 | AR41: 100 | AS41: 100 | AT41: 100 | AU41: 100 | AV41: 100 | AW41: 100 | AX41: 100 | AY41: 100 | AZ41: 100 | BA41: 100 | BB41: 100 | BC41: 100 | BD41: 100 | BE41: 100 | BF41: 100 | BG41: 100 | BH41: 100 | BI41: 100 | BJ41: 100 | BK41: 100 | BL41: 100 | BM41: 100 | BN41: 100 | BO41: 100 | BP41: 100 | BQ41: 100 | BR41: 100 | BS41: 100 | BT41: 100 | BU41: 100 | BV41: 100 | BW41: 100 | BX41: 100 | BY41: 100 | BZ41: 100 | CA41: 100
E42: =LEFT(E41, LEN(E41) - 4) -> Sign switch line item | G42: =G41 -> units | H42: =SUM(J42:CA42) -> -7000 | J42: =-1 * J41 -> -100 | K42: =-1 * K41 -> -100 | L42: =-1 * L41 -> -100 | M42: =-1 * M41 -> -100 | N42: =-1 * N41 -> -100 | O42: =-1 * O41 -> -100 | P42: =-1 * P41 -> -100 | Q42: =-1 * Q41 -> -100 | ... CA42: =-1 * CA41 -> -100
A45: SHARE CAPITAL
E47: =E$55 -> Share capital balance BEG | F47: =F$55 -> 0 | G47: =G$55 -> € 000s | H47: =H$55 -> 0 | I47: =I$55 -> 0 | J47: =J$55 -> 0 | K47: =K$55 -> 0 | L47: =L$55 -> 0 | ... CA47: =CA$55 -> 0
E48: ='T&E'!E$38 -> Last forecast period flag | F48: ='T&E'!F$38 -> 0 | G48: ='T&E'!G$38 -> flag | H48: ='T&E'!H$38 -> 1 | I48: ='T&E'!I$38 -> 0 | J48: ='T&E'!J$38 -> 0 | K48: ='T&E'!K$38 -> 0 | L48: ='T&E'!L$38 -> 0 | ... CA48: ='T&E'!CA$38 -> 0
E49: Share capital redemption POS | G49: =SMU -> € 000s | H49: =SUM(J49:CA49) -> 1000 | J49: =J47 * J48 -> 0 | K49: =K47 * K48 -> 0 | L49: =L47 * L48 -> 0 | M49: =M47 * M48 -> 0 | N49: =N47 * N48 -> 0 | O49: =O47 * O48 -> 0 | P49: =P47 * P48 -> 0 | Q49: =Q47 * Q48 -> 0 | ... CA49: =CA47 * CA48 -> 0
E50: =LEFT(E49, LEN(E49) - 4) -> Share capital redemption | G50: =SMU -> € 000s | H50: =SUM(J50:CA50) -> -1000 | J50: =-1 * J49 -> 0 | K50: =-1 * K49 -> 0 | L50: =-1 * L49 -> 0 | M50: =-1 * M49 -> 0 | N50: =-1 * N49 -> 0 | O50: =-1 * O49 -> 0 | P50: =-1 * P49 -> 0 | Q50: =-1 * Q49 -> 0 | ... CA50: =-1 * CA49 -> 0
E52: =InpC!E$54 -> Share capital investment requirement | F52: =InpC!F$54 -> 1000 | G52: =InpC!G$54 -> € 000s
E53: ='T&E'!E$19 -> Initial operations date flag | F53: ='T&E'!F$19 -> 0 | G53: ='T&E'!G$19 -> flag | H53: ='T&E'!H$19 -> 1 | I53: ='T&E'!I$19 -> 0 | J53: ='T&E'!J$19 -> 0 | K53: ='T&E'!K$19 -> 0 | L53: ='T&E'!L$19 -> 0 | ... CA53: ='T&E'!CA$19 -> 0
E55: Share capital balance BEG | G55: =SMU -> € 000s | J55: =I58 -> 0 | K55: =J58 -> 0 | L55: =K58 -> 0 | M55: =L58 -> 0 | N55: =M58 -> 0 | O55: =N58 -> 1000 | P55: =O58 -> 1000 | Q55: =P58 -> 1000 | ... CA55: =BZ58 -> 0
D56: plus: | E56: [Future equity investment] | G56: =SMU -> € 000s
D57: less: | E57: =E$49 -> Share capital redemption POS | F57: =F$49 -> 0 | G57: =G$49 -> € 000s | H57: =H$49 -> 1000 | I57: =I$49 -> 0 | J57: =J$49 -> 0 | K57: =K$49 -> 0 | L57: =L$49 -> 0 | ... CA57: =CA$49 -> 0
E58: Share capital balance | G58: =SMU -> € 000s | J58: =IF( J53 = 1, $F52, J55 + J56 - J57) -> 0 | K58: =IF( K53 = 1, $F52, K55 + K56 - K57) -> 0 | L58: =IF( L53 = 1, $F52, L55 + L56 - L57) -> 0 | M58: =IF( M53 = 1, $F52, M55 + M56 - M57) -> 0 | N58: =IF( N53 = 1, $F52, N55 + N56 - N57) -> 1000 | O58: =IF( O53 = 1, $F52, O55 + O56 - O57) -> 1000 | P58: =IF( P53 = 1, $F52, P55 + P56 - P57) -> 1000 | Q58: =IF( Q53 = 1, $F52, Q55 + Q56 - Q57) -> 1000 | ... CA58: =IF( CA53 = 1, $F52, CA55 + CA56 - CA57) -> 0
A61: DIVIDENDS / RETAINED CASH AND EARNINGS
B63: Dividends Declared and Paid
E65: =E$83 -> Retained cash / (overdraft) balance BEG | F65: =F$83 -> 0 | G65: =G$83 -> € 000s | H65: =H$83 -> 0 | I65: =I$83 -> 0 | J65: =J$83 -> 0 | K65: =K$83 -> 0 | L65: =L$83 -> 0 | ... CA65: =CA$83 -> 5.0931703e-11
D66: plus: | E66: =Finstat!E$59 -> Cash flow available for dividends | F66: =Finstat!F$59 -> 0 | G66: =Finstat!G$59 -> € 000s | H66: =Finstat!H$59 -> 803403.93 | I66: =Finstat!I$59 -> 0 | J66: =Finstat!J$59 -> 0 | K66: =Finstat!K$59 -> 0 | L66: =Finstat!L$59 -> 0 | ... CA66: =Finstat!CA$59 -> 0
E67: Aggregate cash available for dividends | G67: =SMU -> € 000s | J67: =MAX( SUM(J65:J66), 0) -> 0 | K67: =MAX( SUM(K65:K66), 0) -> 0 | L67: =MAX( SUM(L65:L66), 0) -> 0 | M67: =MAX( SUM(M65:M66), 0) -> 0 | N67: =MAX( SUM(N65:N66), 0) -> 0 | O67: =MAX( SUM(O65:O66), 0) -> 0 | P67: =MAX( SUM(P65:P66), 0) -> 0 | Q67: =MAX( SUM(Q65:Q66), 0) -> 0 | ... CA67: =MAX( SUM(CA65:CA66), 0) -> 5.0931703e-11
E69: =E$91 -> Retained earnings balance BEG | F69: =F$91 -> 0 | G69: =G$91 -> € 000s | H69: =H$91 -> 0 | I69: =I$91 -> 0 | J69: =J$91 -> 0 | K69: =K$91 -> 0 | L69: =L$91 -> 0 | ... CA69: =CA$91 -> 0
D70: plus: | E70: =Finstat!E$18 -> Profit after tax | F70: =Finstat!F$18 -> 0 | G70: =Finstat!G$18 -> € 000s | H70: =Finstat!H$18 -> 803403.93 | I70: =Finstat!I$18 -> 0 | J70: =Finstat!J$18 -> 0 | K70: =Finstat!K$18 -> 0 | L70: =Finstat!L$18 -> 0 | ... CA70: =Finstat!CA$18 -> 0
E71: Aggregate earnings available for dividends | F71: MAX( x, 0 ) | G71: =SMU -> € 000s | J71: =MAX( SUM(J69:J70), 0) -> 0 | K71: =MAX( SUM(K69:K70), 0) -> 0 | L71: =MAX( SUM(L69:L70), 0) -> 0 | M71: =MAX( SUM(M69:M70), 0) -> 0 | N71: =MAX( SUM(N69:N70), 0) -> 0 | O71: =MAX( SUM(O69:O70), 0) -> 0 | P71: =MAX( SUM(P69:P70), 0) -> 0 | Q71: =MAX( SUM(Q69:Q70), 0) -> 0 | ... CA71: =MAX( SUM(CA69:CA70), 0) -> 0
E73: =E$67 -> Aggregate cash available for dividends | F73: =F$67 -> 0 | G73: =G$67 -> € 000s | H73: =H$67 -> 0 | I73: =I$67 -> 0 | J73: =J$67 -> 0 | K73: =K$67 -> 0 | L73: =L$67 -> 0 | ... CA73: =CA$67 -> 5.0931703e-11
E74: =E$71 -> Aggregate earnings available for dividends | F74: =F$71 -> MAX( x, 0 ) | G74: =G$71 -> € 000s | H74: =H$71 -> 0 | I74: =I$71 -> 0 | J74: =J$71 -> 0 | K74: =K$71 -> 0 | L74: =L$71 -> 0 | ... CA74: =CA$71 -> 0
E75: Dividends declared / paid POS | G75: =SMU -> € 000s | H75: =SUM(J75:CA75) -> 803403.93 | J75: =MIN(J73:J74) -> 0 | K75: =MIN(K73:K74) -> 0 | L75: =MIN(L73:L74) -> 0 | M75: =MIN(M73:M74) -> 0 | N75: =MIN(N73:N74) -> 0 | O75: =MIN(O73:O74) -> 0 | P75: =MIN(P73:P74) -> 0 | Q75: =MIN(Q73:Q74) -> 0 | ... CA75: =MIN(CA73:CA74) -> 0
B78: Retained Cash and Earnings Balances
E80: [Retained cash - Initial balance] | F80: 0 | G80: € 000s
E81: ='T&E'!E$19 -> Initial operations date flag | F81: ='T&E'!F$19 -> 0 | G81: ='T&E'!G$19 -> flag | H81: ='T&E'!H$19 -> 1 | I81: ='T&E'!I$19 -> 0 | J81: ='T&E'!J$19 -> 0 | K81: ='T&E'!K$19 -> 0 | L81: ='T&E'!L$19 -> 0 | ... CA81: ='T&E'!CA$19 -> 0
E83: Retained cash / (overdraft) balance BEG | G83: =SMU -> € 000s | J83: =I86 -> 0 | K83: =J86 -> 0 | L83: =K86 -> 0 | M83: =L86 -> 0 | N83: =M86 -> 0 | O83: =N86 -> 0 | P83: =O86 -> 0 | Q83: =P86 -> 0 | ... CA83: =BZ86 -> 5.0931703e-11
D84: plus: | E84: =Finstat!E$59 -> Cash flow available for dividends | F84: =Finstat!F$59 -> 0 | G84: =Finstat!G$59 -> € 000s | H84: =Finstat!H$59 -> 803403.93 | I84: =Finstat!I$59 -> 0 | J84: =Finstat!J$59 -> 0 | K84: =Finstat!K$59 -> 0 | L84: =Finstat!L$59 -> 0 | ... CA84: =Finstat!CA$59 -> 0
D85: less: | E85: =E$75 -> Dividends declared / paid POS | F85: =F$75 -> 0 | G85: =G$75 -> € 000s | H85: =H$75 -> 803403.93 | I85: =I$75 -> 0 | J85: =J$75 -> 0 | K85: =K$75 -> 0 | L85: =L$75 -> 0 | ... CA85: =CA$75 -> 0
E86: Retained cash / (overdraft) balance | G86: =SMU -> € 000s | J86: =IF( J81 = 1, $F80, J83 + J84 - J85) -> 0 | K86: =IF( K81 = 1, $F80, K83 + K84 - K85) -> 0 | L86: =IF( L81 = 1, $F80, L83 + L84 - L85) -> 0 | M86: =IF( M81 = 1, $F80, M83 + M84 - M85) -> 0 | N86: =IF( N81 = 1, $F80, N83 + N84 - N85) -> 0 | O86: =IF( O81 = 1, $F80, O83 + O84 - O85) -> 0 | P86: =IF( P81 = 1, $F80, P83 + P84 - P85) -> 0 | Q86: =IF( Q81 = 1, $F80, Q83 + Q84 - Q85) -> 0 | ... CA86: =IF( CA81 = 1, $F80, CA83 + CA84 - CA85) -> 5.0931703e-11
E88: Retained earnings - Initial balance | F88: 0 | G88: € 000s
E89: ='T&E'!E$19 -> Initial operations date flag | F89: ='T&E'!F$19 -> 0 | G89: ='T&E'!G$19 -> flag | H89: ='T&E'!H$19 -> 1 | I89: ='T&E'!I$19 -> 0 | J89: ='T&E'!J$19 -> 0 | K89: ='T&E'!K$19 -> 0 | L89: ='T&E'!L$19 -> 0 | ... CA89: ='T&E'!CA$19 -> 0
E91: Retained earnings balance BEG | G91: =SMU -> € 000s | J91: =I94 -> 0 | K91: =J94 -> 0 | L91: =K94 -> 0 | M91: =L94 -> 0 | N91: =M94 -> 0 | O91: =N94 -> 0 | P91: =O94 -> -1120.9966 | Q91: =P94 -> -1692.0317 | ... CA91: =BZ94 -> 0
D92: plus: | E92: =Finstat!E$18 -> Profit after tax | F92: =Finstat!F$18 -> 0 | G92: =Finstat!G$18 -> € 000s | H92: =Finstat!H$18 -> 803403.93 | I92: =Finstat!I$18 -> 0 | J92: =Finstat!J$18 -> 0 | K92: =Finstat!K$18 -> 0 | L92: =Finstat!L$18 -> 0 | ... CA92: =Finstat!CA$18 -> 0
D93: less: | E93: =E$75 -> Dividends declared / paid POS | F93: =F$75 -> 0 | G93: =G$75 -> € 000s | H93: =H$75 -> 803403.93 | I93: =I$75 -> 0 | J93: =J$75 -> 0 | K93: =K$75 -> 0 | L93: =L$75 -> 0 | ... CA93: =CA$75 -> 0
E94: Retained earnings balance | G94: =SMU -> € 000s | J94: =IF( J89 = 1, $F88, J91 + J92 - J93) -> 0 | K94: =IF( K89 = 1, $F88, K91 + K92 - K93) -> 0 | L94: =IF( L89 = 1, $F88, L91 + L92 - L93) -> 0 | M94: =IF( M89 = 1, $F88, M91 + M92 - M93) -> 0 | N94: =IF( N89 = 1, $F88, N91 + N92 - N93) -> 0 | O94: =IF( O89 = 1, $F88, O91 + O92 - O93) -> -1120.9966 | P94: =IF( P89 = 1, $F88, P91 + P92 - P93) -> -1692.0317 | Q94: =IF( Q89 = 1, $F88, Q91 + Q92 - Q93) -> -1542.956 | ... CA94: =IF( CA89 = 1, $F88, CA91 + CA92 - CA93) -> 0

Sheet Finstat
A1: =RIGHT(CELL("filename", A1), LEN(CELL("filename", A1)) - SEARCH("]", CELL("filename", A1))) -> Finstat
E2: ='T&E'!E$24 -> Operating period flag | G2: ='T&E'!G$24 -> flag | H2: ='T&E'!H$24 -> 60 | J2: ='T&E'!J$24 -> 0 | K2: ='T&E'!K$24 -> 0 | L2: ='T&E'!L$24 -> 0 | M2: ='T&E'!M$24 -> 0 | N2: ='T&E'!N$24 -> 0 | O2: ='T&E'!O$24 -> 1 | P2: ='T&E'!P$24 -> 1 | Q2: ='T&E'!Q$24 -> 1 | ... CA2: ='T&E'!CA$24 -> 0
E3: ='T&E'!E$8 -> Model column counter | J3: ='T&E'!J$8 -> 1 | K3: ='T&E'!K$8 -> 2 | L3: ='T&E'!L$8 -> 3 | M3: ='T&E'!M$8 -> 4 | N3: ='T&E'!N$8 -> 5 | O3: ='T&E'!O$8 -> 6 | P3: ='T&E'!P$8 -> 7 | Q3: ='T&E'!Q$8 -> 8 | ... CA3: ='T&E'!CA$8 -> 70
E4: ='T&E'!E$12 -> Model period ending | F4: ='T&E'!F$12 -> constant | G4: ='T&E'!G$12 -> unit | H4: ='T&E'!H$12 -> total | J4: ='T&E'!J$12 -> 41639 | K4: ='T&E'!K$12 -> 41820 | L4: ='T&E'!L$12 -> 42004 | M4: ='T&E'!M$12 -> 42185 | N4: ='T&E'!N$12 -> 42369 | O4: ='T&E'!O$12 -> 42551 | P4: ='T&E'!P$12 -> 42735 | Q4: ='T&E'!Q$12 -> 42916 | ... CA4: ='T&E'!CA$12 -> 54239
A6: PROFIT AND LOSS
E8: =Rev!E$114 -> Operating revenue | G8: =Rev!G$114 -> € 000s | H8: =Rev!H$114 -> 2496071.6 | J8: =Rev!J$114 -> 0 | K8: =Rev!K$114 -> 0 | L8: =Rev!L$114 -> 0 | M8: =Rev!M$114 -> 0 | N8: =Rev!N$114 -> 0 | O8: =Rev!O$114 -> 28320.77 | P8: =Rev!P$114 -> 28958.426 | Q8: =Rev!Q$114 -> 30091.228 | ... CA8: =Rev!CA$114 -> 0
E9: =Opex!E$34 -> Operating costs | G9: =Opex!G$34 -> € 000s | H9: =Opex!H$34 -> -560672.48 | J9: =Opex!J$34 -> 0 | K9: =Opex!K$34 -> 0 | L9: =Opex!L$34 -> 0 | M9: =Opex!M$34 -> 0 | N9: =Opex!N$34 -> 0 | O9: =Opex!O$34 -> -6684.7066 | P9: =Opex!P$34 -> -6680.9536 | Q9: =Opex!Q$34 -> -6939.6986 | ... CA9: =Opex!CA$34 -> 0
E10: Operating income / EBITDA | G10: =SMU -> € 000s | H10: =SUM(J10:CA10) -> 1935399.1 | J10: =SUM(J8:J9) -> 0 | K10: =SUM(K8:K9) -> 0 | L10: =SUM(L8:L9) -> 0 | M10: =SUM(M8:M9) -> 0 | N10: =SUM(N8:N9) -> 0 | O10: =SUM(O8:O9) -> 21636.063 | P10: =SUM(P8:P9) -> 22277.473 | Q10: =SUM(Q8:Q9) -> 23151.529 | ... CA10: =SUM(CA8:CA9) -> 0
E12: =FixAsst!E$15 -> Book depreciation | G12: =FixAsst!G$15 -> € 000s | H12: =FixAsst!H$15 -> -395404.94 | J12: =FixAsst!J$15 -> 0 | K12: =FixAsst!K$15 -> 0 | L12: =FixAsst!L$15 -> 0 | M12: =FixAsst!M$15 -> 0 | N12: =FixAsst!N$15 -> 0 | O12: =FixAsst!O$15 -> -7908.0989 | P12: =FixAsst!P$15 -> -7908.0989 | Q12: =FixAsst!Q$15 -> -7908.0989 | ... CA12: =FixAsst!CA$15 -> 0
E13: =SrDebt!E$31 -> Senior debt interest expense | G13: =SrDebt!G$31 -> € 000s | H13: =SrDebt!H$31 -> -392274.3 | J13: =SrDebt!J$31 -> 0 | K13: =SrDebt!K$31 -> 0 | L13: =SrDebt!L$31 -> 0 | M13: =SrDebt!M$31 -> 0 | N13: =SrDebt!N$31 -> 0 | O13: =SrDebt!O$31 -> -15329.388 | P13: =SrDebt!P$31 -> -15185.138 | Q13: =SrDebt!Q$31 -> -15030.465 | ... CA13: =SrDebt!CA$31 -> 0
E14: [Shareholder loan interest expense]
E15: Profit before tax | G15: =SMU -> € 000s | H15: =SUM(J15:CA15) -> 1147719.9 | J15: =J10 + SUM(J12:J14) -> 0 | K15: =K10 + SUM(K12:K14) -> 0 | L15: =L10 + SUM(L12:L14) -> 0 | M15: =M10 + SUM(M12:M14) -> 0 | N15: =N10 + SUM(N12:N14) -> 0 | O15: =O10 + SUM(O12:O14) -> -1601.4238 | P15: =P10 + SUM(P12:P14) -> -815.7644 | Q15: =Q10 + SUM(Q12:Q14) -> 212.96534 | ... CA15: =CA10 + SUM(CA12:CA14) -> 0
E17: =Tax!E$41 -> P&L tax charge | G17: =Tax!G$41 -> € 000s | H17: =Tax!H$41 -> -344315.97 | J17: =Tax!J$41 -> 0 | K17: =Tax!K$41 -> 0 | L17: =Tax!L$41 -> 0 | M17: =Tax!M$41 -> 0 | N17: =Tax!N$41 -> 0 | O17: =Tax!O$41 -> 480.42713 | P17: =Tax!P$41 -> 244.72932 | Q17: =Tax!Q$41 -> -63.889601 | ... CA17: =Tax!CA$41 -> 0
E18: Profit after tax | G18: =SMU -> € 000s | H18: =SUM(J18:CA18) -> 803403.93 | J18: =J15 + J17 -> 0 | K18: =K15 + K17 -> 0 | L18: =L15 + L17 -> 0 | M18: =M15 + M17 -> 0 | N18: =N15 + N17 -> 0 | O18: =O15 + O17 -> -1120.9966 | P18: =P15 + P17 -> -571.03508 | Q18: =Q15 + Q17 -> 149.07573 | ... CA18: =CA15 + CA17 -> 0
A21: BALANCE SHEET
E23: =FixAsst!E$26 -> Net fixed assets balance | G23: =FixAsst!G$26 -> € 000s | J23: =FixAsst!J$26 -> 0 | K23: =FixAsst!K$26 -> 0 | L23: =FixAsst!L$26 -> 0 | M23: =FixAsst!M$26 -> 0 | N23: =FixAsst!N$26 -> 395404.94 | O23: =FixAsst!O$26 -> 387496.85 | P23: =FixAsst!P$26 -> 379588.75 | Q23: =FixAsst!Q$26 -> 371680.65 | ... CA23: =FixAsst!CA$26 -> -2.3101165e-10
E24: =DSRA!E$60 -> Senior DSRA balance | F24: =DSRA!F$60 -> 0 | G24: =DSRA!G$60 -> € 000s | H24: =DSRA!H$60 -> 0 | I24: =DSRA!I$60 -> 0 | J24: =DSRA!J$60 -> 0 | K24: =DSRA!K$60 -> 0 | L24: =DSRA!L$60 -> 0 | ... CA24: =DSRA!CA$60 -> 0
E25: =Equity!E$86 -> Retained cash / (overdraft) balance | G25: =Equity!G$86 -> € 000s | J25: =Equity!J$86 -> 0 | K25: =Equity!K$86 -> 0 | L25: =Equity!L$86 -> 0 | M25: =Equity!M$86 -> 0 | N25: =Equity!N$86 -> 0 | O25: =Equity!O$86 -> 0 | P25: =Equity!P$86 -> 0 | Q25: =Equity!Q$86 -> 0 | ... CA25: =Equity!CA$86 -> 5.0931703e-11
E26: Total assets | G26: =SMU -> € 000s | J26: =SUM(J23:J25) -> 0 | K26: =SUM(K23:K25) -> 0 | L26: =SUM(L23:L25) -> 0 | M26: =SUM(M23:M25) -> 0 | N26: =SUM(N23:N25) -> 403404.94 | O26: =SUM(O23:O25) -> 402805.76 | P26: =SUM(P23:P25) -> 398233.72 | Q26: =SUM(Q23:Q25) -> 389159.94 | ... CA26: =SUM(CA23:CA25) -> -1.8007995e-10
E28: =SrDebt!E$74 -> Senior term debt balance | G28: =SrDebt!G$74 -> € 000s | J28: =SrDebt!J$74 -> 0 | K28: =SrDebt!K$74 -> 0 | L28: =SrDebt!L$74 -> 0 | M28: =SrDebt!M$74 -> 0 | N28: =SrDebt!N$74 -> 322723.96 | O28: =SrDebt!O$74 -> 319687.12 | P28: =SrDebt!P$74 -> 316430.84 | Q28: =SrDebt!Q$74 -> 312816.33 | ... CA28: =SrDebt!CA$74 -> 3.2741809e-11
E29: =Tax!E$49 -> Deferred tax liability / (asset) balance | G29: =Tax!G$49 -> € 000s | J29: =Tax!J$49 -> 0 | K29: =Tax!K$49 -> 0 | L29: =Tax!L$49 -> 0 | M29: =Tax!M$49 -> 0 | N29: =Tax!N$49 -> 0 | O29: =Tax!O$49 -> 3558.6445 | P29: =Tax!P$49 -> 6820.7353 | Q29: =Tax!Q$49 -> 9801.1001 | ... CA29: =Tax!CA$49 -> 3.6379788e-11
E30: =Equity!E$36 -> Shareholder loan balance | F30: =Equity!F$36 -> 0 | G30: =Equity!G$36 -> € 000s | H30: =Equity!H$36 -> 0 | I30: =Equity!I$36 -> 0 | J30: =Equity!J$36 -> 0 | K30: =Equity!K$36 -> 0 | L30: =Equity!L$36 -> 0 | ... CA30: =Equity!CA$36 -> 0
E31: =Equity!E$58 -> Share capital balance | G31: =Equity!G$58 -> € 000s | J31: =Equity!J$58 -> 0 | K31: =Equity!K$58 -> 0 | L31: =Equity!L$58 -> 0 | M31: =Equity!M$58 -> 0 | N31: =Equity!N$58 -> 1000 | O31: =Equity!O$58 -> 1000 | P31: =Equity!P$58 -> 1000 | Q31: =Equity!Q$58 -> 1000 | ... CA31: =Equity!CA$58 -> 0
E32: =Equity!E$94 -> Retained earnings balance | G32: =Equity!G$94 -> € 000s | J32: =Equity!J$94 -> 0 | K32: =Equity!K$94 -> 0 | L32: =Equity!L$94 -> 0 | M32: =Equity!M$94 -> 0 | N32: =Equity!N$94 -> 0 | O32: =Equity!O$94 -> -1120.9966 | P32: =Equity!P$94 -> -1692.0317 | Q32: =Equity!Q$94 -> -1542.956 | ... CA32: =Equity!CA$94 -> 0
E33: Total liabilities and shareholder funds | G33: =SMU -> € 000s | J33: =SUM(J28:J32) -> 0 | K33: =SUM(K28:K32) -> 0 | L33: =SUM(L28:L32) -> 0 | M33: =SUM(M28:M32) -> 0 | N33: =SUM(N28:N32) -> 403404.94 | O33: =SUM(O28:O32) -> 402805.76 | P33: =SUM(P28:P32) -> 398233.72 | Q33: =SUM(Q28:Q32) -> 389159.94 | ... CA33: =SUM(CA28:CA32) -> 6.9121597e-11
E35: Balance sheet difference | G35: =SMU -> € 000s | H35: =SUM(J35:CA35) -> 1.2882083e-08 | J35: =ABS( J26 - J33 ) -> 0 | K35: =ABS( K26 - K33 ) -> 0 | L35: =ABS( L26 - L33 ) -> 0 | M35: =ABS( M26 - M33 ) -> 0 | N35: =ABS( N26 - N33 ) -> 0 | O35: =ABS( O26 - O33 ) -> 5.8207661e-11 | P35: =ABS( P26 - P33 ) -> 0 | Q35: =ABS( Q26 - Q33 ) -> 0 | ... CA35: =ABS( CA26 - CA33 ) -> 2.4920155e-10
A38: CASH FLOW PAYMENT CASCADE
E40: =E$10 -> Operating income / EBITDA | G40: =G$10 -> € 000s | H40: =H$10 -> 1935399.1 | J40: =J$10 -> 0 | K40: =K$10 -> 0 | L40: =L$10 -> 0 | M40: =M$10 -> 0 | N40: =N$10 -> 0 | O40: =O$10 -> 21636.063 | P40: =P$10 -> 22277.473 | Q40: =Q$10 -> 23151.529 | ... CA40: =CA$10 -> 0
E41: =Tax!E$33 -> [Tax payments | G41: =Tax!G$33 -> € 000s | H41: =Tax!H$33 -> -344315.97 | J41: =Tax!J$33 -> 0 | K41: =Tax!K$33 -> 0 | L41: =Tax!L$33 -> 0 | M41: =Tax!M$33 -> 0 | N41: =Tax!N$33 -> 0 | O41: =Tax!O$33 -> 4039.0716 | P41: =Tax!P$33 -> 3506.8201 | Q41: =Tax!Q$33 -> 2916.4752 | ... CA41: =Tax!CA$33 -> 0
E42: [Ongoing capital expenditure]
E43: Cash flow available for debt service | H43: =SUM(J43:CA43) -> 1591083.2 | J43: =SUM(J40:J42) -> 0 | K43: =SUM(K40:K42) -> 0 | L43: =SUM(L40:L42) -> 0 | M43: =SUM(M40:M42) -> 0 | N43: =SUM(N40:N42) -> 0 | O43: =SUM(O40:O42) -> 25675.135 | P43: =SUM(P40:P42) -> 25784.293 | Q43: =SUM(Q40:Q42) -> 26068.004 | ... CA43: =SUM(CA40:CA42) -> 0
E45: =SrDebt!E$31 -> Senior debt interest expense | G45: =SrDebt!G$31 -> € 000s | H45: =SrDebt!H$31 -> -392274.3 | J45: =SrDebt!J$31 -> 0 | K45: =SrDebt!K$31 -> 0 | L45: =SrDebt!L$31 -> 0 | M45: =SrDebt!M$31 -> 0 | N45: =SrDebt!N$31 -> 0 | O45: =SrDebt!O$31 -> -15329.388 | P45: =SrDebt!P$31 -> -15185.138 | Q45: =SrDebt!Q$31 -> -15030.465 | ... CA45: =SrDebt!CA$31 -> 0
E46: =SrDebt!E$63 -> Senior principal repayment | G46: =SrDebt!G$63 -> € 000s | H46: =SrDebt!H$63 -> -322723.96 | J46: =SrDebt!J$63 -> 0 | K46: =SrDebt!K$63 -> 0 | L46: =SrDebt!L$63 -> 0 | M46: =SrDebt!M$63 -> 0 | N46: =SrDebt!N$63 -> 0 | O46: =SrDebt!O$63 -> -3036.8324 | P46: =SrDebt!P$63 -> -3256.2847 | Q46: =SrDebt!Q$63 -> -3614.5083 | ... CA46: =SrDebt!CA$63 -> 0
E47: Cash flow available for senior DSRA | H47: =SUM(J47:CA47) -> 876084.92 | J47: =J43 + SUM(J45:J46) -> 0 | K47: =K43 + SUM(K45:K46) -> 0 | L47: =L43 + SUM(L45:L46) -> 0 | M47: =M43 + SUM(M45:M46) -> 0 | N47: =N43 + SUM(N45:N46) -> 0 | O47: =O43 + SUM(O45:O46) -> 7308.9143 | P47: =P43 + SUM(P45:P46) -> 7342.8699 | Q47: =Q43 + SUM(Q45:Q46) -> 7423.0311 | ... CA47: =CA43 + SUM(CA45:CA46) -> 0
E49: =DSRA!E$34 -> Senior DSRA deposits | F49: =DSRA!F$34 -> 0 | G49: =DSRA!G$34 -> 0 | H49: =DSRA!H$34 -> -13896.691 | I49: =DSRA!I$34 -> 0 | J49: =DSRA!J$34 -> 0 | K49: =DSRA!K$34 -> 0 | L49: =DSRA!L$34 -> 0 | ... CA49: =DSRA!CA$34 -> 0
E50: =DSRA!E$48 -> Senior DSRA shortfall withdrawals | F50: =DSRA!F$48 -> 0 | G50: =DSRA!G$48 -> 0 | H50: =DSRA!H$48 -> 0 | I50: =DSRA!I$48 -> 0 | J50: =DSRA!J$48 -> 0 | K50: =DSRA!K$48 -> 0 | L50: =DSRA!L$48 -> 0 | ... CA50: =DSRA!CA$48 -> 0
E51: =DSRA!E$49 -> Senior DSRA net releases | F51: =DSRA!F$49 -> 0 | G51: =DSRA!G$49 -> 0 | H51: =DSRA!H$49 -> 21896.691 | I51: =DSRA!I$49 -> 0 | J51: =DSRA!J$49 -> 0 | K51: =DSRA!K$49 -> 0 | L51: =DSRA!L$49 -> 0 | ... CA51: =DSRA!CA$49 -> 0
E52: Cash flow available for shareholder loan | H52: =SUM(J52:CA52) -> 884084.92 | J52: =J47 + SUM(J49:J51) -> 0 | K52: =K47 + SUM(K49:K51) -> 0 | L52: =L47 + SUM(L49:L51) -> 0 | M52: =M47 + SUM(M49:M51) -> 0 | N52: =N47 + SUM(N49:N51) -> 0 | O52: =O47 + SUM(O49:O51) -> 0 | P52: =P47 + SUM(P49:P51) -> 4006.8111 | Q52: =Q47 + SUM(Q49:Q51) -> 8588.71 | ... CA52: =CA47 + SUM(CA49:CA51) -> 0
E54: [Shareholder loan interest paid]
E55: =Equity!E$21 -> Shareholder loan repayment | F55: =Equity!F$21 -> 0 | G55: =Equity!G$21 -> 0 | H55: =Equity!H$21 -> -79680.989 | I55: =Equity!I$21 -> 0 | J55: =Equity!J$21 -> 0 | K55: =Equity!K$21 -> 0 | L55: =Equity!L$21 -> 0 | ... CA55: =Equity!CA$21 -> 0
E56: Cash flow available to distributions | H56: =SUM(J56:CA56) -> 804403.93 | J56: =J52 + SUM(J54:J55) -> 0 | K56: =K52 + SUM(K54:K55) -> 0 | L56: =L52 + SUM(L54:L55) -> 0 | M56: =M52 + SUM(M54:M55) -> 0 | N56: =N52 + SUM(N54:N55) -> 0 | O56: =O52 + SUM(O54:O55) -> 0 | P56: =P52 + SUM(P54:P55) -> 0 | Q56: =Q52 + SUM(Q54:Q55) -> 0 | ... CA56: =CA52 + SUM(CA54:CA55) -> 0
E58: =Equity!E$50 -> Share capital redemption | G58: =Equity!G$50 -> € 000s | H58: =Equity!H$50 -> -1000 | J58: =Equity!J$50 -> 0 | K58: =Equity!K$50 -> 0 | L58: =Equity!L$50 -> 0 | M58: =Equity!M$50 -> 0 | N58: =Equity!N$50 -> 0 | O58: =Equity!O$50 -> 0 | P58: =Equity!P$50 -> 0 | Q58: =Equity!Q$50 -> 0 | ... CA58: =Equity!CA$50 -> 0
E59: Cash flow available for dividends | G59: =SMU -> € 000s | H59: =SUM(J59:CA59) -> 803403.93 | J59: =J56 + J58 -> 0 | K59: =K56 + K58 -> 0 | L59: =L56 + L58 -> 0 | M59: =M56 + M58 -> 0 | N59: =N56 + N58 -> 0 | O59: =O56 + O58 -> 0 | P59: =P56 + P58 -> 0 | Q59: =Q56 + Q58 -> 0 | ... CA59: =CA56 + CA58 -> 0

Sheet Ratios
A1: =RIGHT(CELL("filename", A1), LEN(CELL("filename", A1)) - SEARCH("]", CELL("filename", A1))) -> Ratios
E2: ='T&E'!E$24 -> Operating period flag | F2: ='T&E'!F$24 -> 0 | G2: ='T&E'!G$24 -> flag | H2: ='T&E'!H$24 -> 60 | I2: ='T&E'!I$24 -> 0 | J2: ='T&E'!J$24 -> 0 | K2: ='T&E'!K$24 -> 0 | L2: ='T&E'!L$24 -> 0 | ... CA2: ='T&E'!CA$24 -> 0
E3: ='T&E'!E$8 -> Model column counter | F3: ='T&E'!F$8 -> 0 | G3: ='T&E'!G$8 -> 0 | H3: ='T&E'!H$8 -> 0 | I3: ='T&E'!I$8 -> 0 | J3: ='T&E'!J$8 -> 1 | K3: ='T&E'!K$8 -> 2 | L3: ='T&E'!L$8 -> 3 | ... CA3: ='T&E'!CA$8 -> 70
E4: ='T&E'!E$12 -> Model period ending | F4: ='T&E'!F$12 -> constant | G4: ='T&E'!G$12 -> unit | H4: ='T&E'!H$12 -> total | I4: ='T&E'!I$12 -> 0 | J4: ='T&E'!J$12 -> 41639 | K4: ='T&E'!K$12 -> 41820 | L4: ='T&E'!L$12 -> 42004 | ... CA4: ='T&E'!CA$12 -> 54239
A6: PERIOD DSCRs
E8: ='T&E'!E$29 -> Senior debt term / ratio calc date flag | F8: ='T&E'!F$29 -> 0 | G8: ='T&E'!G$29 -> flag | H8: ='T&E'!H$29 -> 40 | I8: ='T&E'!I$29 -> 0 | J8: ='T&E'!J$29 -> 0 | K8: ='T&E'!K$29 -> 0 | L8: ='T&E'!L$29 -> 0 | ... CA8: ='T&E'!CA$29 -> 0
E9: =Finstat!E$43 -> Cash flow available for debt service | F9: =Finstat!F$43 -> 0 | G9: =Finstat!G$43 -> 0 | H9: =Finstat!H$43 -> 1591083.2 | I9: =Finstat!I$43 -> 0 | J9: =Finstat!J$43 -> 0 | K9: =Finstat!K$43 -> 0 | L9: =Finstat!L$43 -> 0 | ... CA9: =Finstat!CA$43 -> 0
E10: =SrDebt!E$79 -> Senior debt service | F10: =SrDebt!F$79 -> 0 | G10: =SrDebt!G$79 -> 0 | H10: =SrDebt!H$79 -> 714998.26 | I10: =SrDebt!I$79 -> 0 | J10: =SrDebt!J$79 -> 0 | K10: =SrDebt!K$79 -> 0 | L10: =SrDebt!L$79 -> 0 | ... CA10: =SrDebt!CA$79 -> 0
E11: 6-month HDSCR | J11: =IF(J8 = 1, J9 / J10, "n/a") -> n/a | K11: =IF(K8 = 1, K9 / K10, "n/a") -> n/a | L11: =IF(L8 = 1, L9 / L10, "n/a") -> n/a | M11: =IF(M8 = 1, M9 / M10, "n/a") -> n/a | N11: =IF(N8 = 1, N9 / N10, "n/a") -> n/a | O11: =IF(O8 = 1, O9 / O10, "n/a") -> 1.3979542 | P11: =IF(P8 = 1, P9 / P10, "n/a") -> 1.3981726 | Q11: =IF(Q8 = 1, Q9 / Q10, "n/a") -> 1.3981251 | ... CA11: =IF(CA8 = 1, CA9 / CA10, "n/a") -> n/a
E13: Minimum 6-month HDSCR | F13: =MIN(J11:CA11) -> 1.3979213 | G13: ratio
E14: Simple average of 6-month DSCRs | F14: =AVERAGE(J11:CA11) -> 1.3980517 | G14: bad ratio
E16: =Finstat!E$43 -> Cash flow available for debt service | F16: =Finstat!F$43 -> 0 | G16: =Finstat!G$43 -> 0 | H16: =Finstat!H$43 -> 1591083.2 | I16: =Finstat!I$43 -> 0 | J16: =Finstat!J$43 -> 0 | K16: =Finstat!K$43 -> 0 | L16: =Finstat!L$43 -> 0 | ... CA16: =Finstat!CA$43 -> 0
E17: ='T&E'!E$29 -> Senior debt term / ratio calc date flag | F17: ='T&E'!F$29 -> 0 | G17: ='T&E'!G$29 -> flag | H17: ='T&E'!H$29 -> 40 | I17: ='T&E'!I$29 -> 0 | J17: ='T&E'!J$29 -> 0 | K17: ='T&E'!K$29 -> 0 | L17: ='T&E'!L$29 -> 0 | ... CA17: ='T&E'!CA$29 -> 0
E18: CFADS over debt term | H18: =SUM(J18:CA18) -> 999604.92 | J18: =J16 * J17 -> 0 | K18: =K16 * K17 -> 0 | L18: =L16 * L17 -> 0 | M18: =M16 * M17 -> 0 | N18: =N16 * N17 -> 0 | O18: =O16 * O17 -> 25675.135 | P18: =P16 * P17 -> 25784.293 | Q18: =Q16 * Q17 -> 26068.004 | ... CA18: =CA16 * CA17 -> 0
E19: ="Sum of " & E18 -> Sum of CFADS over debt term | F19: =SUM(J18:CA18) -> 999604.92 | G19: =SMU -> € 000s
E21: =SrDebt!E$79 -> Senior debt service | F21: =SrDebt!F$79 -> 0 | G21: =SrDebt!G$79 -> 0 | H21: =SrDebt!H$79 -> 714998.26 | I21: =SrDebt!I$79 -> 0 | J21: =SrDebt!J$79 -> 0 | K21: =SrDebt!K$79 -> 0 | L21: =SrDebt!L$79 -> 0 | ... CA21: =SrDebt!CA$79 -> 0
E22: ="Sum of " & E21 -> Sum of Senior debt service | F22: =SUM(J21:CA21) -> 714998.26 | G22: =SMU -> € 000s
E24: =E$19 -> Sum of CFADS over debt term | F24: =F$19 -> 999604.92 | G24: =G$19 -> € 000s
E25: =E$22 -> Sum of Senior debt service | F25: =F$22 -> 714998.26 | G25: =G$22 -> € 000s
E26: Weighted average DSCR | F26: =F24 / F25 -> 1.3980522 | G26: ratio
A29: ANNUAL DSCRs
E31: 12-month HDSCR calculation date flag | F31: 0 | G31: flag | H31: 40 | I31: 0 | P31: 1 | Q31: 1 | R31: 1 | S31: 1 | T31: 1 | U31: 1 | V31: 1 | W31: 1 | X31: 1 | Y31: 1 | Z31: 1 | AA31: 1 | AB31: 1 | AC31: 1 | AD31: 1 | AE31: 1 | AF31: 1 | AG31: 1 | AH31: 1 | AI31: 1 | AJ31: 1 | AK31: 1 | AL31: 1 | AM31: 1 | AN31: 1 | AO31: 1 | AP31: 1 | AQ31: 1 | AR31: 1 | AS31: 1 | AT31: 1 | AU31: 1 | AV31: 1 | AW31: 1 | AX31: 1 | AY31: 1 | AZ31: 1 | BA31: 1 | BB31: 1
E32: =Finstat!E$43 -> Cash flow available for debt service | F32: =Finstat!F$43 -> 0 | G32: =Finstat!G$43 -> 0 | H32: =Finstat!H$43 -> 1591083.2 | I32: =Finstat!I$43 -> 0 | J32: =Finstat!J$43 -> 0 | K32: =Finstat!K$43 -> 0 | L32: =Finstat!L$43 -> 0 | ... CA32: =Finstat!CA$43 -> 0
E33: =SrDebt!E$79 -> Senior debt service | F33: =SrDebt!F$79 -> 0 | G33: =SrDebt!G$79 -> 0 | H33: =SrDebt!H$79 -> 714998.26 | I33: =SrDebt!I$79 -> 0 | J33: =SrDebt!J$79 -> 0 | K33: =SrDebt!K$79 -> 0 | L33: =SrDebt!L$79 -> 0 | ... CA33: =SrDebt!CA$79 -> 0
E34: 12-month HDSCR | J34: =IF(J31 = 1, SUM(I32:J32) / SUM(I33:J33), "n/a") -> n/a | K34: =IF(K31 = 1, SUM(J32:K32) / SUM(J33:K33), "n/a") -> n/a | L34: =IF(L31 = 1, SUM(K32:L32) / SUM(K33:L33), "n/a") -> n/a | M34: =IF(M31 = 1, SUM(L32:M32) / SUM(L33:M33), "n/a") -> n/a | N34: =IF(N31 = 1, SUM(M32:N32) / SUM(M33:N33), "n/a") -> n/a | O34: =IF(O31 = 1, SUM(N32:O32) / SUM(N33:O33), "n/a") -> n/a | P34: =IF(P31 = 1, SUM(O32:P32) / SUM(O33:P33), "n/a") -> 1.3980636 | Q34: =IF(Q31 = 1, SUM(P32:Q32) / SUM(P33:Q33), "n/a") -> 1.3981487 | ... CA34: =IF(CA31 = 1, SUM(BZ32:CA32) / SUM(BZ33:CA33), "n/a") -> n/a
E36: ="Minimum " & E34 -> Minimum 12-month HDSCR | F36: =MIN(J34:CA34) -> 1.3979585 | G36: ratio
E38: 12-month FDSCR calculation date flag | F38: 0 | G38: flag | H38: 40 | I38: 0 | N38: 1 | O38: 1 | P38: 1 | Q38: 1 | R38: 1 | S38: 1 | T38: 1 | U38: 1 | V38: 1 | W38: 1 | X38: 1 | Y38: 1 | Z38: 1 | AA38: 1 | AB38: 1 | AC38: 1 | AD38: 1 | AE38: 1 | AF38: 1 | AG38: 1 | AH38: 1 | AI38: 1 | AJ38: 1 | AK38: 1 | AL38: 1 | AM38: 1 | AN38: 1 | AO38: 1 | AP38: 1 | AQ38: 1 | AR38: 1 | AS38: 1 | AT38: 1 | AU38: 1 | AV38: 1 | AW38: 1 | AX38: 1 | AY38: 1 | AZ38: 1 | BA38: 1
E39: =Finstat!E$43 -> Cash flow available for debt service | F39: =Finstat!F$43 -> 0 | G39: =Finstat!G$43 -> 0 | H39: =Finstat!H$43 -> 1591083.2 | I39: =Finstat!I$43 -> 0 | J39: =Finstat!J$43 -> 0 | K39: =Finstat!K$43 -> 0 | L39: =Finstat!L$43 -> 0 | ... CA39: =Finstat!CA$43 -> 0
E40: =SrDebt!E$79 -> Senior debt service | F40: =SrDebt!F$79 -> 0 | G40: =SrDebt!G$79 -> 0 | H40: =SrDebt!H$79 -> 714998.26 | I40: =SrDebt!I$79 -> 0 | J40: =SrDebt!J$79 -> 0 | K40: =SrDebt!K$79 -> 0 | L40: =SrDebt!L$79 -> 0 | ... CA40: =SrDebt!CA$79 -> 0
E41: 12-month FDSCR | J41: =IF(J38 = 1, SUM(K39:L39) / SUM(K40:L40), "n/a") -> n/a | K41: =IF(K38 = 1, SUM(L39:M39) / SUM(L40:M40), "n/a") -> n/a | L41: =IF(L38 = 1, SUM(M39:N39) / SUM(M40:N40), "n/a") -> n/a | M41: =IF(M38 = 1, SUM(N39:O39) / SUM(N40:O40), "n/a") -> n/a | N41: =IF(N38 = 1, SUM(O39:P39) / SUM(O40:P40), "n/a") -> 1.3980636 | O41: =IF(O38 = 1, SUM(P39:Q39) / SUM(P40:Q40), "n/a") -> 1.3981487 | P41: =IF(P38 = 1, SUM(Q39:R39) / SUM(Q40:R40), "n/a") -> 1.3981068 | Q41: =IF(Q38 = 1, SUM(R39:S39) / SUM(R40:S40), "n/a") -> 1.3980074 | ... CA41: =IF(CA38 = 1, SUM(CB39:CC39) / SUM(CB40:CC40), "n/a") -> n/a
E43: ="Minimum " & E41 -> Minimum 12-month FDSCR | F43: =MIN(J41:CA41) -> 1.3979585 | G43: ratio

Sheet Returns
A1: =RIGHT(CELL("filename", A1), LEN(CELL("filename", A1)) - SEARCH("]", CELL("filename", A1))) -> Returns
E2: ='T&E'!E$24 -> Operating period flag | F2: ='T&E'!F$24 -> 0 | G2: ='T&E'!G$24 -> flag | H2: ='T&E'!H$24 -> 60 | I2: ='T&E'!I$24 -> 0 | J2: ='T&E'!J$24 -> 0 | K2: ='T&E'!K$24 -> 0 | L2: ='T&E'!L$24 -> 0 | ... CA2: ='T&E'!CA$24 -> 0
E3: ='T&E'!E$8 -> Model column counter | F3: ='T&E'!F$8 -> 0 | G3: ='T&E'!G$8 -> 0 | H3: ='T&E'!H$8 -> 0 | I3: ='T&E'!I$8 -> 0 | J3: ='T&E'!J$8 -> 1 | K3: ='T&E'!K$8 -> 2 | L3: ='T&E'!L$8 -> 3 | ... CA3: ='T&E'!CA$8 -> 70
E4: ='T&E'!E$12 -> Model period ending | F4: ='T&E'!F$12 -> constant | G4: ='T&E'!G$12 -> unit | H4: ='T&E'!H$12 -> total | I4: ='T&E'!I$12 -> 0 | J4: ='T&E'!J$12 -> 41639 | K4: ='T&E'!K$12 -> 41820 | L4: ='T&E'!L$12 -> 42004 | ... CA4: ='T&E'!CA$12 -> 54239
A6: SHAREHOLDER IRRS
B8: Leveraged analysis
E10: [Shareholder loan interest paid POS]
E11: =Equity!E$20 -> Shareholder loan repayment POS | F11: =Equity!F$20 -> 0 | G11: =Equity!G$20 -> 0 | H11: =Equity!H$20 -> 0 | I11: =Equity!I$20 -> 0 | J11: =Equity!J$20 -> 0 | K11: =Equity!K$20 -> 0 | L11: =Equity!L$20 -> 0 | ... CA11: =Equity!CA$20 -> 0
E12: =Equity!E$49 -> Share capital redemption POS | F12: =Equity!F$49 -> 0 | G12: =Equity!G$49 -> € 000s | H12: =Equity!H$49 -> 1000 | I12: =Equity!I$49 -> 0 | J12: =Equity!J$49 -> 0 | K12: =Equity!K$49 -> 0 | L12: =Equity!L$49 -> 0 | ... CA12: =Equity!CA$49 -> 0
E13: =Equity!E$75 -> Dividends declared / paid POS | F13: =Equity!F$75 -> 0 | G13: =Equity!G$75 -> € 000s | H13: =Equity!H$75 -> 803403.93 | I13: =Equity!I$75 -> 0 | J13: =Equity!J$75 -> 0 | K13: =Equity!K$75 -> 0 | L13: =Equity!L$75 -> 0 | ... CA13: =Equity!CA$75 -> 0
E14: Shareholder distributions | H14: =SUM(J14:CA14) -> 884084.92 | J14: =SUM(J10:J13) -> 0 | K14: =SUM(K10:K13) -> 0 | L14: =SUM(L10:L13) -> 0 | M14: =SUM(M10:M13) -> 0 | N14: =SUM(N10:N13) -> 0 | O14: =SUM(O10:O13) -> 0 | P14: =SUM(P10:P13) -> 4006.8111 | Q14: =SUM(Q10:Q13) -> 8588.71 | ... CA14: =SUM(CA10:CA13) -> 0
E17: =ConTime!E$13 -> Construction period month ending | F17: =ConTime!F$13 -> 0 | G17: =ConTime!G$13 -> 0 | H17: =ConTime!H$13 -> 0 | I17: =ConTime!I$13 -> 0 | J17: =ConTime!J$13 -> 41698 | K17: =ConTime!K$13 -> 41729 | L17: =ConTime!L$13 -> 41759 | ... AZ17: =ConTime!AZ$13 -> 42978
E18: Model period ending | F18: constant | G18: unit | H18: total | I18: 0 | J18: 41639 | K18: 41820 | L18: 42004 | M18: 42185 | N18: 42369 | O18: 42551 | P18: 42735 | Q18: 42916 | R18: 43100 | S18: 43281 | T18: 43465 | U18: 43646 | V18: 43830 | W18: 44012 | X18: 44196 | Y18: 44377 | Z18: 44561 | AA18: 44742 | AB18: 44926 | AC18: 45107 | AD18: 45291 | AE18: 45473 | AF18: 45657 | AG18: 45838 | AH18: 46022 | AI18: 46203 | AJ18: 46387 | AK18: 46568 | AL18: 46752 | AM18: 46934 | AN18: 47118 | AO18: 47299 | AP18: 47483 | AQ18: 47664 | AR18: 47848 | AS18: 48029 | AT18: 48213 | AU18: 48395 | AV18: 48579 | AW18: 48760 | AX18: 48944 | AY18: 49125 | AZ18: 49309 | BA18: 49490 | BB18: 49674 | BC18: 49856 | BD18: 50040 | BE18: 50221 | BF18: 50405 | BG18: 50586 | BH18: 50770 | BI18: 50951 | BJ18: 51135 | BK18: 51317 | BL18: 51501 | BM18: 51682 | BN18: 51866 | BO18: 52047 | BP18: 52231 | BQ18: 52412 | BR18: 52596 | BS18: 52778 | BT18: 52962 | BU18: 53143 | BV18: 53327 | BW18: 53508 | BX18: 53692 | BY18: 53873 | BZ18: 54057 | CA18: 54239
E20: =ConFin!E$100 -> Equity investment NEG (for XIRR) | F20: =ConFin!F$100 -> 0 | G20: =ConFin!G$100 -> 0 | H20: =ConFin!H$100 -> -80680.989 | I20: =ConFin!I$100 -> 0 | J20: =ConFin!J$100 -> -14430 | K20: =ConFin!K$100 -> -2186.8488 | L20: =ConFin!L$100 -> -2192.659 | ... AZ20: =ConFin!AZ$100 -> 0
E21: =E$14 -> Shareholder distributions | F21: =F$14 -> 0 | G21: =G$14 -> 0 | H21: =H$14 -> 884084.92 | I21: =I$14 -> 0 | J21: =J$14 -> 0 | K21: =K$14 -> 0 | L21: =L$14 -> 0 | ... CA21: =CA$14 -> 0
E23: [(Leveraged) Shareholder IRR] | F23: =XIRR(J20:CA21, J17:CA18, 10%) -> 0.15894809 | G23: p.a. (365)
E26: =ConTime!E$13 -> Construction period month ending | F26: =ConTime!F$13 -> 0 | G26: =ConTime!G$13 -> 0 | H26: =ConTime!H$13 -> 0 | I26: =ConTime!I$13 -> 0 | J26: =ConTime!J$13 -> 41698 | K26: =ConTime!K$13 -> 41729 | L26: =ConTime!L$13 -> 41759 | ... AZ26: =ConTime!AZ$13 -> 42978
E27: Model period ending | F27: constant | G27: unit | H27: total | I27: 0 | J27: 41639 | K27: 41820 | L27: 42004 | M27: 42185 | N27: 42369 | O27: 42551 | P27: 42735 | Q27: 42916 | R27: 43100 | S27: 43281 | T27: 43465 | U27: 43646 | V27: 43830 | W27: 44012 | X27: 44196 | Y27: 44377 | Z27: 44561 | AA27: 44742 | AB27: 44926 | AC27: 45107 | AD27: 45291 | AE27: 45473 | AF27: 45657 | AG27: 45838 | AH27: 46022 | AI27: 46203 | AJ27: 46387 | AK27: 46568 | AL27: 46752 | AM27: 46934 | AN27: 47118 | AO27: 47299 | AP27: 47483 | AQ27: 47664 | AR27: 47848 | AS27: 48029 | AT27: 48213 | AU27: 48395 | AV27: 48579 | AW27: 48760 | AX27: 48944 | AY27: 49125 | AZ27: 49309 | BA27: 49490 | BB27: 49674 | BC27: 49856 | BD27: 50040 | BE27: 50221 | BF27: 50405 | BG27: 50586 | BH27: 50770 | BI27: 50951 | BJ27: 51135 | BK27: 51317 | BL27: 51501 | BM27: 51682 | BN27: 51866 | BO27: 52047 | BP27: 52231 | BQ27: 52412 | BR27: 52596 | BS27: 52778 | BT27: 52962 | BU27: 53143 | BV27: 53327 | BW27: 53508 | BX27: 53692 | BY27: 53873 | BZ27: 54057 | CA27: 54239
E29: =ConFin!E$100 -> Equity investment NEG (for XIRR) | F29: =ConFin!F$100 -> 0 | G29: =ConFin!G$100 -> 0 | H29: =ConFin!H$100 -> -80680.989 | I29: =ConFin!I$100 -> 0 | J29: =ConFin!J$100 -> -14430 | K29: =ConFin!K$100 -> -2186.8488 | L29: =ConFin!L$100 -> -2192.659 | ... AZ29: =ConFin!AZ$100 -> 0
E30: =Finstat!E$52 -> Cash flow available for shareholder loan | F30: =Finstat!F$52 -> 0 | G30: =Finstat!G$52 -> 0 | H30: =Finstat!H$52 -> 884084.92 | I30: =Finstat!I$52 -> 0 | J30: =Finstat!J$52 -> 0 | K30: =Finstat!K$52 -> 0 | L30: =Finstat!L$52 -> 0 | ... CA30: =Finstat!CA$52 -> 0
E32: [Unrestricted shareholder IRR] | F32: =XIRR(J29:CA30, J26:CA27, 10%) -> 0.16183788 | G32: p.a. (365)
B35: Unleveraged shareholder IRR
E37: =ConTime!E$13 -> Construction period month ending | F37: =ConTime!F$13 -> 0 | G37: =ConTime!G$13 -> 0 | H37: =ConTime!H$13 -> 0 | I37: =ConTime!I$13 -> 0 | J37: =ConTime!J$13 -> 41698 | K37: =ConTime!K$13 -> 41729 | L37: =ConTime!L$13 -> 41759 | ... AZ37: =ConTime!AZ$13 -> 42978
E38: Model period ending | F38: constant | G38: unit | H38: total | I38: 0 | J38: 41639 | K38: 41820 | L38: 42004 | M38: 42185 | N38: 42369 | O38: 42551 | P38: 42735 | Q38: 42916 | R38: 43100 | S38: 43281 | T38: 43465 | U38: 43646 | V38: 43830 | W38: 44012 | X38: 44196 | Y38: 44377 | Z38: 44561 | AA38: 44742 | AB38: 44926 | AC38: 45107 | AD38: 45291 | AE38: 45473 | AF38: 45657 | AG38: 45838 | AH38: 46022 | AI38: 46203 | AJ38: 46387 | AK38: 46568 | AL38: 46752 | AM38: 46934 | AN38: 47118 | AO38: 47299 | AP38: 47483 | AQ38: 47664 | AR38: 47848 | AS38: 48029 | AT38: 48213 | AU38: 48395 | AV38: 48579 | AW38: 48760 | AX38: 48944 | AY38: 49125 | AZ38: 49309 | BA38: 49490 | BB38: 49674 | BC38: 49856 | BD38: 50040 | BE38: 50221 | BF38: 50405 | BG38: 50586 | BH38: 50770 | BI38: 50951 | BJ38: 51135 | BK38: 51317 | BL38: 51501 | BM38: 51682 | BN38: 51866 | BO38: 52047 | BP38: 52231 | BQ38: 52412 | BR38: 52596 | BS38: 52778 | BT38: 52962 | BU38: 53143 | BV38: 53327 | BW38: 53508 | BX38: 53692 | BY38: 53873 | BZ38: 54057 | CA38: 54239
E40: =ConCost!E$44 -> Construction costs NEG (for XIRR) | F40: =ConCost!F$44 -> 0 | G40: =ConCost!G$44 -> € 000s | H40: =ConCost!H$44 -> -368500 | I40: =ConCost!I$44 -> 0 | J40: =ConCost!J$44 -> -64350 | K40: =ConCost!K$44 -> -10480 | L40: =ConCost!L$44 -> -10480 | ... AZ40: =ConCost!AZ$44 -> 0
E41: =Finstat!E$40 -> Operating income / EBITDA | F41: =Finstat!F$40 -> 0 | G41: =Finstat!G$40 -> € 000s | H41: =Finstat!H$40 -> 1935399.1 | I41: =Finstat!I$40 -> 0 | J41: =Finstat!J$40 -> 0 | K41: =Finstat!K$40 -> 0 | L41: =Finstat!L$40 -> 0 | ... CA41: =Finstat!CA$40 -> 0
E43: [Pre-tax unleveraged IRR] | F43: =XIRR(J40:CA41, J37:CA38, 10%) -> 0.12715839 | G43: p.a. (365)
A46: SHAREHOLDER NPV
E48: Shareholder valuation date | F48: 41578 | G48: eom
E49: Model period ending | F49: constant | G49: unit | H49: total | I49: 0 | J49: 41639 | K49: 41820 | L49: 42004 | M49: 42185 | N49: 42369 | O49: 42551 | P49: 42735 | Q49: 42916 | R49: 43100 | S49: 43281 | T49: 43465 | U49: 43646 | V49: 43830 | W49: 44012 | X49: 44196 | Y49: 44377 | Z49: 44561 | AA49: 44742 | AB49: 44926 | AC49: 45107 | AD49: 45291 | AE49: 45473 | AF49: 45657 | AG49: 45838 | AH49: 46022 | AI49: 46203 | AJ49: 46387 | AK49: 46568 | AL49: 46752 | AM49: 46934 | AN49: 47118 | AO49: 47299 | AP49: 47483 | AQ49: 47664 | AR49: 47848 | AS49: 48029 | AT49: 48213 | AU49: 48395 | AV49: 48579 | AW49: 48760 | AX49: 48944 | AY49: 49125 | AZ49: 49309 | BA49: 49490 | BB49: 49674 | BC49: 49856 | BD49: 50040 | BE49: 50221 | BF49: 50405 | BG49: 50586 | BH49: 50770 | BI49: 50951 | BJ49: 51135 | BK49: 51317 | BL49: 51501 | BM49: 51682 | BN49: 51866 | BO49: 52047 | BP49: 52231 | BQ49: 52412 | BR49: 52596 | BS49: 52778 | BT49: 52962 | BU49: 53143 | BV49: 53327 | BW49: 53508 | BX49: 53692 | BY49: 53873 | BZ49: 54057 | CA49: 54239
E50: Days from valuation date | J50: =J49 - $F48 -> 61 | K50: =K49 - $F48 -> 242 | L50: =L49 - $F48 -> 426 | M50: =M49 - $F48 -> 607 | N50: =N49 - $F48 -> 791 | O50: =O49 - $F48 -> 973 | P50: =P49 - $F48 -> 1157 | Q50: =Q49 - $F48 -> 1338 | ... CA50: =CA49 - $F48 -> 12661
E51: Years from valuation date | J51: =J50 / 365 -> 0.16712329 | K51: =K50 / 365 -> 0.6630137 | L51: =L50 / 365 -> 1.1671233 | M51: =M50 / 365 -> 1.6630137 | N51: =N50 / 365 -> 2.1671233 | O51: =O50 / 365 -> 2.6657534 | P51: =P50 / 365 -> 3.169863 | Q51: =Q50 / 365 -> 3.6657534 | ... CA51: =CA50 / 365 -> 34.687671
E53: =InpC!E$55 -> Shareholder discount rate | F53: =InpC!F$55 -> 0.13 | G53: =InpC!G$55 -> p.a. (365)
E54: =E51 -> Years from valuation date | F54: =F51 -> 0 | G54: =G51 -> 0 | H54: =H51 -> 0 | I54: =I51 -> 0 | J54: =J51 -> 0.16712329 | K54: =K51 -> 0.6630137 | L54: =L51 -> 1.1671233 | ... CA54: =CA51 -> 34.687671
E55: Shareholder discount factor - semi | J55: =(1 + $F53) ^ (-1 * J54) -> 0.97978177 | K55: =(1 + $F53) ^ (-1 * K54) -> 0.92216421 | L55: =(1 + $F53) ^ (-1 * L54) -> 0.86706352 | M55: =(1 + $F53) ^ (-1 * M54) -> 0.81607453 | N55: =(1 + $F53) ^ (-1 * N54) -> 0.76731285 | O55: =(1 + $F53) ^ (-1 * O54) -> 0.72194807 | P55: =(1 + $F53) ^ (-1 * P54) -> 0.67881058 | Q55: =(1 + $F53) ^ (-1 * Q54) -> 0.63889209 | ... CA55: =(1 + $F53) ^ (-1 * CA54) -> 0.014415589
E57: =E$14 -> Shareholder distributions | F57: =F$14 -> 0 | G57: =G$14 -> 0 | H57: =H$14 -> 884084.92 | I57: =I$14 -> 0 | J57: =J$14 -> 0 | K57: =K$14 -> 0 | L57: =L$14 -> 0 | ... CA57: =CA$14 -> 0
E58: =E55 -> Shareholder discount factor - semi | F58: =F55 -> 0 | G58: =G55 -> 0 | H58: =H55 -> 0 | I58: =I55 -> 0 | J58: =J55 -> 0.97978177 | K58: =K55 -> 0.92216421 | L58: =L55 -> 0.86706352 | ... CA58: =CA55 -> 0.014415589
E59: Period PVs of shareholder distributions | H59: =SUM(J59:CA59) -> 92218.688 | J59: =J57 * J58 -> 0 | K59: =K57 * K58 -> 0 | L59: =L57 * L58 -> 0 | M59: =M57 * M58 -> 0 | N59: =N57 * N58 -> 0 | O59: =O57 * O58 -> 0 | P59: =P57 * P58 -> 2719.8658 | Q59: =Q57 * Q58 -> 5487.2589 | ... CA59: =CA57 * CA58 -> 0
E60: PV of shareholder distibutions | F60: =SUM(J59:CA59) -> 92218.688 | G60: =SMU -> € 000s
E62: =E$60 -> PV of shareholder distibutions | F62: =F$60 -> 92218.688 | G62: =G$60 -> € 000s
D63: less: | E63: =ConFin!E$117 -> PV of equity investment | F63: =ConFin!F$117 -> 69059.673 | G63: =ConFin!G$117 -> € 000s
E64: Shareholder NPV | F64: =F62 - F63 -> 23159.015 | G64: =G$60 -> € 000s

Sheet {Tmp}
A1: =RIGHT(CELL("filename", A1), LEN(CELL("filename", A1)) - SEARCH("]", CELL("filename", A1))) -> {Tmp}
E2: ='T&E'!E$24 -> Operating period flag | F2: ='T&E'!F$24 -> 0 | G2: ='T&E'!G$24 -> flag | H2: ='T&E'!H$24 -> 60 | I2: ='T&E'!I$24 -> 0 | J2: ='T&E'!J$24 -> 0 | K2: ='T&E'!K$24 -> 0 | L2: ='T&E'!L$24 -> 0 | ... CA2: ='T&E'!CA$24 -> 0
E3: ='T&E'!E$8 -> Model column counter | F3: ='T&E'!F$8 -> 0 | G3: ='T&E'!G$8 -> 0 | H3: ='T&E'!H$8 -> 0 | I3: ='T&E'!I$8 -> 0 | J3: ='T&E'!J$8 -> 1 | K3: ='T&E'!K$8 -> 2 | L3: ='T&E'!L$8 -> 3 | ... CA3: ='T&E'!CA$8 -> 70
E4: ='T&E'!E$12 -> Model period ending | F4: ='T&E'!F$12 -> constant | G4: ='T&E'!G$12 -> unit | H4: ='T&E'!H$12 -> total | I4: ='T&E'!I$12 -> 0 | J4: ='T&E'!J$12 -> 41639 | K4: ='T&E'!K$12 -> 41820 | L4: ='T&E'!L$12 -> 42004 | ... CA4: ='T&E'!CA$12 -> 54239
A6: BALANCE
E8: [xxx] - Initial balance | F8: 0 | G8: =SMU -> € 000s
E9: ='T&E'!E$19 -> Initial operations date flag | F9: ='T&E'!F$19 -> 0 | G9: ='T&E'!G$19 -> flag | H9: ='T&E'!H$19 -> 1 | I9: ='T&E'!I$19 -> 0 | J9: ='T&E'!J$19 -> 0 | K9: ='T&E'!K$19 -> 0 | L9: ='T&E'!L$19 -> 0 | ... CA9: ='T&E'!CA$19 -> 0
E11: [xxx] balance BEG | G11: =SMU -> € 000s | J11: =I14 -> 0 | K11: =J14 -> 0 | L11: =K14 -> 0 | M11: =L14 -> 0 | N11: =M14 -> 0 | O11: =N14 -> 0 | P11: =O14 -> 0 | Q11: =P14 -> 0 | ... CA11: =BZ14 -> 0
D12: plus: | E12: [increases in balance]
D13: less: | E13: [reductions in balance]
E14: [xxx] balance | G14: =SMU -> € 000s | J14: =IF( J9 = 1, $F8, J11 + J12 - J13) -> 0 | K14: =IF( K9 = 1, $F8, K11 + K12 - K13) -> 0 | L14: =IF( L9 = 1, $F8, L11 + L12 - L13) -> 0 | M14: =IF( M9 = 1, $F8, M11 + M12 - M13) -> 0 | N14: =IF( N9 = 1, $F8, N11 + N12 - N13) -> 0 | O14: =IF( O9 = 1, $F8, O11 + O12 - O13) -> 0 | P14: =IF( P9 = 1, $F8, P11 + P12 - P13) -> 0 | Q14: =IF( Q9 = 1, $F8, Q11 + Q12 - Q13) -> 0 | ... CA14: =IF( CA9 = 1, $F8, CA11 + CA12 - CA13) -> 0
A17: SIGN SWITCH
E19: Sign switch line item POS | G19: units | H19: =SUM(J19:CA19) -> 7000 | J19: 100 | K19: 100 | L19: 100 | M19: 100 | N19: 100 | O19: 100 | P19: 100 | Q19: 100 | R19: 100 | S19: 100 | T19: 100 | U19: 100 | V19: 100 | W19: 100 | X19: 100 | Y19: 100 | Z19: 100 | AA19: 100 | AB19: 100 | AC19: 100 | AD19: 100 | AE19: 100 | AF19: 100 | AG19: 100 | AH19: 100 | AI19: 100 | AJ19: 100 | AK19: 100 | AL19: 100 | AM19: 100 | AN19: 100 | AO19: 100 | AP19: 100 | AQ19: 100 | AR19: 100 | AS19: 100 | AT19: 100 | AU19: 100 | AV19: 100 | AW19: 100 | AX19: 100 | AY19: 100 | AZ19: 100 | BA19: 100 | BB19: 100 | BC19: 100 | BD19: 100 | BE19: 100 | BF19: 100 | BG19: 100 | BH19: 100 | BI19: 100 | BJ19: 100 | BK19: 100 | BL19: 100 | BM19: 100 | BN19: 100 | BO19: 100 | BP19: 100 | BQ19: 100 | BR19: 100 | BS19: 100 | BT19: 100 | BU19: 100 | BV19: 100 | BW19: 100 | BX19: 100 | BY19: 100 | BZ19: 100 | CA19: 100
E20: =LEFT(E19, LEN(E19) - 4) -> Sign switch line item | G20: =G19 -> units | H20: =SUM(J20:CA20) -> -7000 | J20: =-1 * J19 -> -100 | K20: =-1 * K19 -> -100 | L20: =-1 * L19 -> -100 | M20: =-1 * M19 -> -100 | N20: =-1 * N19 -> -100 | O20: =-1 * O19 -> -100 | P20: =-1 * P19 -> -100 | Q20: =-1 * Q19 -> -100 | ... CA20: =-1 * CA19 -> -100
